Workbook

Sheet 1

Sheet Annual Summary
D11: 2022 | E11: =+D11+1 | F11: Variance | G11: =+E11+1 | H11: Variance | I11: =+G11+1 | J11: Variance | K11: =+I11+1 | L11: =+K11+1 | M11: =+L11+1 | N11: =+M11+1 | O11: =+N11+1
C13: Service Income | D13: =SUMIF('Monthly Detail'!$1:$1,'Annual Summary'!D$11, 'Monthly Detail'!12:12) | E13: =SUMIF('Monthly Detail'!$1:$1,'Annual Summary'!E$11, 'Monthly Detail'!12:12) | F13: =+E13-D13 | G13: =SUMIF('Monthly Detail'!$1:$1,'Annual Summary'!G$11, 'Monthly Detail'!12:12) | H13: =+G13-E13 | I13: =SUMIF('Monthly Detail'!$1:$1,'Annual Summary'!I$11, 'Monthly Detail'!12:12) | J13: =+I13-G13 | K13: =SUMIF('Monthly Detail'!$1:$1,'Annual Summary'!K$11, 'Monthly Detail'!12:12) | L13: =SUMIF('Monthly Detail'!$1:$1,'Annual Summary'!L$11, 'Monthly Detail'!12:12) | M13: =SUMIF('Monthly Detail'!$1:$1,'Annual Summary'!M$11, 'Monthly Detail'!12:12) | N13: =SUMIF('Monthly Detail'!$1:$1,'Annual Summary'!N$11, 'Monthly Detail'!12:12) | O13: =SUMIF('Monthly Detail'!$1:$1,'Annual Summary'!O$11, 'Monthly Detail'!12:12)
C14: Tips | D14: =SUMIF('Monthly Detail'!$1:$1,'Annual Summary'!D$11, 'Monthly Detail'!13:13) | E14: =SUMIF('Monthly Detail'!$1:$1,'Annual Summary'!E$11, 'Monthly Detail'!13:13) | F14: =+E14-D14 | G14: =SUMIF('Monthly Detail'!$1:$1,'Annual Summary'!G$11, 'Monthly Detail'!13:13) | H14: =+G14-E14 | I14: =SUMIF('Monthly Detail'!$1:$1,'Annual Summary'!I$11, 'Monthly Detail'!13:13) | J14: =+I14-G14 | K14: =SUMIF('Monthly Detail'!$1:$1,'Annual Summary'!K$11, 'Monthly Detail'!13:13) | L14: =SUMIF('Monthly Detail'!$1:$1,'Annual Summary'!L$11, 'Monthly Detail'!13:13) | M14: =SUMIF('Monthly Detail'!$1:$1,'Annual Summary'!M$11, 'Monthly Detail'!13:13) | N14: =SUMIF('Monthly Detail'!$1:$1,'Annual Summary'!N$11, 'Monthly Detail'!13:13) | O14: =SUMIF('Monthly Detail'!$1:$1,'Annual Summary'!O$11, 'Monthly Detail'!13:13)
C15: Total Income | D15: =SUM(D13:D14) | E15: =SUM(E13:E14) | F15: =+E15-D15 | G15: =SUM(G13:G14) | H15: =+G15-E15 | I15: =SUM(I13:I14) | J15: =+I15-G15 | K15: =SUM(K13:K14) | L15: =SUM(L13:L14) | M15: =SUM(M13:M14) | N15: =SUM(N13:N14) | O15: =SUM(O13:O14)
C16: EOY # of Students | D16: =+SUMIFS('Monthly Detail'!17:17,'Monthly Detail'!4:4,DATE(D11,12,31)) | E16: =+SUMIFS('Monthly Detail'!17:17,'Monthly Detail'!4:4,DATE(E11,12,31)) | F16: =+E16-D16 | G16: =+SUMIFS('Monthly Detail'!17:17,'Monthly Detail'!4:4,DATE(G11,12,31)) | H16: =+G16-E16 | I16: =+SUMIFS('Monthly Detail'!17:17,'Monthly Detail'!4:4,DATE(I11,12,31)) | J16: =+I16-G16 | K16: =+SUMIFS('Monthly Detail'!17:17,'Monthly Detail'!4:4,DATE(K11,12,31)) | L16: =+SUMIFS('Monthly Detail'!17:17,'Monthly Detail'!4:4,DATE(L11,12,31)) | M16: =+SUMIFS('Monthly Detail'!17:17,'Monthly Detail'!4:4,DATE(M11,12,31)) | N16: =+SUMIFS('Monthly Detail'!17:17,'Monthly Detail'!4:4,DATE(N11,12,31)) | O16: =+SUMIFS('Monthly Detail'!17:17,'Monthly Detail'!4:4,DATE(O11,12,31))
C17: YOY Compounded Growth % | E17: =(E15/D15)-1 | F17: =+E17-D17 | G17: =(G15/E15)-1 | H17: =+G17-E17 | I17: =(I15/G15)-1 | J17: =+I17-G17 | K17: =(K15/I15)-1 | L17: =(L15/K15)-1 | M17: =(M15/L15)-1 | N17: =(N15/M15)-1 | O17: =(O15/N15)-1
C19: Subcontractor Expenses | D19: =SUMIF('Monthly Detail'!$1:$1,'Annual Summary'!D$11, 'Monthly Detail'!$65:$65) | E19: =SUMIF('Monthly Detail'!$1:$1,'Annual Summary'!E$11, 'Monthly Detail'!$65:$65) | F19: =+E19-D19 | G19: =SUMIF('Monthly Detail'!$1:$1,'Annual Summary'!G$11, 'Monthly Detail'!$65:$65) | H19: =+G19-E19 | I19: =SUMIF('Monthly Detail'!$1:$1,'Annual Summary'!I$11, 'Monthly Detail'!$65:$65) | J19: =+I19-G19 | K19: =SUMIF('Monthly Detail'!$1:$1,'Annual Summary'!K$11, 'Monthly Detail'!$65:$65) | L19: =SUMIF('Monthly Detail'!$1:$1,'Annual Summary'!L$11, 'Monthly Detail'!$65:$65) | M19: =SUMIF('Monthly Detail'!$1:$1,'Annual Summary'!M$11, 'Monthly Detail'!$65:$65) | N19: =SUMIF('Monthly Detail'!$1:$1,'Annual Summary'!N$11, 'Monthly Detail'!$65:$65) | O19: =SUMIF('Monthly Detail'!$1:$1,'Annual Summary'!O$11, 'Monthly Detail'!$65:$65)
C20: Gross Margin | D20: =D15-D19 | E20: =E15-E19 | F20: =+E20-D20 | G20: =G15-G19 | H20: =+G20-E20 | I20: =I15-I19 | J20: =+I20-G20 | K20: =K15-K19 | L20: =L15-L19 | M20: =M15-M19 | N20: =N15-N19 | O20: =O15-O19
C21: GM % | D21: =+D20/D15 | E21: =+E20/E15 | F21: =+E21-D21 | G21: =+G20/G15 | H21: =+G21-E21 | I21: =+I20/I15 | J21: =+I21-G21 | K21: =+K20/K15 | L21: =+L20/L15 | M21: =+M20/M15 | N21: =+N20/N15 | O21: =+O20/O15
C23: Sales & Marketing Expenses | D23: =SUMIF('Monthly Detail'!$1:$1,'Annual Summary'!D$11, 'Monthly Detail'!$72:$72) | E23: =SUMIF('Monthly Detail'!$1:$1,'Annual Summary'!E$11, 'Monthly Detail'!$72:$72) | F23: =+E23-D23 | G23: =SUMIF('Monthly Detail'!$1:$1,'Annual Summary'!G$11, 'Monthly Detail'!$72:$72) | H23: =+G23-E23 | I23: =SUMIF('Monthly Detail'!$1:$1,'Annual Summary'!I$11, 'Monthly Detail'!$72:$72) | J23: =+I23-G23 | K23: =SUMIF('Monthly Detail'!$1:$1,'Annual Summary'!K$11, 'Monthly Detail'!$72:$72) | L23: =SUMIF('Monthly Detail'!$1:$1,'Annual Summary'!L$11, 'Monthly Detail'!$72:$72) | M23: =SUMIF('Monthly Detail'!$1:$1,'Annual Summary'!M$11, 'Monthly Detail'!$72:$72) | N23: =SUMIF('Monthly Detail'!$1:$1,'Annual Summary'!N$11, 'Monthly Detail'!$72:$72) | O23: =SUMIF('Monthly Detail'!$1:$1,'Annual Summary'!O$11, 'Monthly Detail'!$72:$72)
C24: General & Admintrative Expenses | D24: =SUMIF('Monthly Detail'!$1:$1,'Annual Summary'!D$11, 'Monthly Detail'!$95:$95) | E24: =SUMIF('Monthly Detail'!$1:$1,'Annual Summary'!E$11, 'Monthly Detail'!$95:$95) | F24: =+E24-D24 | G24: =SUMIF('Monthly Detail'!$1:$1,'Annual Summary'!G$11, 'Monthly Detail'!$95:$95) | H24: =+G24-E24 | I24: =SUMIF('Monthly Detail'!$1:$1,'Annual Summary'!I$11, 'Monthly Detail'!$95:$95) | J24: =+I24-G24 | K24: =SUMIF('Monthly Detail'!$1:$1,'Annual Summary'!K$11, 'Monthly Detail'!$95:$95) | L24: =SUMIF('Monthly Detail'!$1:$1,'Annual Summary'!L$11, 'Monthly Detail'!$95:$95) | M24: =SUMIF('Monthly Detail'!$1:$1,'Annual Summary'!M$11, 'Monthly Detail'!$95:$95) | N24: =SUMIF('Monthly Detail'!$1:$1,'Annual Summary'!N$11, 'Monthly Detail'!$95:$95) | O24: =SUMIF('Monthly Detail'!$1:$1,'Annual Summary'!O$11, 'Monthly Detail'!$95:$95)
C25: Owner Guarenteed Payments | D25: =SUMIF('Monthly Detail'!$1:$1,'Annual Summary'!D$11, 'Monthly Detail'!96:96) | E25: =SUMIF('Monthly Detail'!$1:$1,'Annual Summary'!E$11, 'Monthly Detail'!96:96) | F25: =+E25-D25 | G25: =SUMIF('Monthly Detail'!$1:$1,'Annual Summary'!G$11, 'Monthly Detail'!96:96) | H25: =+G25-E25 | I25: =SUMIF('Monthly Detail'!$1:$1,'Annual Summary'!I$11, 'Monthly Detail'!96:96) | J25: =+I25-G25 | K25: =SUMIF('Monthly Detail'!$1:$1,'Annual Summary'!K$11, 'Monthly Detail'!96:96) | L25: =SUMIF('Monthly Detail'!$1:$1,'Annual Summary'!L$11, 'Monthly Detail'!96:96) | M25: =SUMIF('Monthly Detail'!$1:$1,'Annual Summary'!M$11, 'Monthly Detail'!96:96) | N25: =SUMIF('Monthly Detail'!$1:$1,'Annual Summary'!N$11, 'Monthly Detail'!96:96) | O25: =SUMIF('Monthly Detail'!$1:$1,'Annual Summary'!O$11, 'Monthly Detail'!96:96)
C26: Operating Expense | D26: =SUM(D23:D25) | E26: =SUM(E23:E25) | F26: =+E26-D26 | G26: =SUM(G23:G25) | H26: =+G26-E26 | I26: =SUM(I23:I25) | J26: =+I26-G26 | K26: =SUM(K23:K25) | L26: =SUM(L23:L25) | M26: =SUM(M23:M25) | N26: =SUM(N23:N25) | O26: =SUM(O23:O25)
C28: Net Operating Income (EBITDA) | D28: =D20-D26 | E28: =E20-E26 | F28: =+E28-D28 | G28: =G20-G26 | H28: =+G28-E28 | I28: =I20-I26 | J28: =+I28-G28 | K28: =K20-K26 | L28: =L20-L26 | M28: =M20-M26 | N28: =N20-N26 | O28: =O20-O26
C29: EBITDA % | D29: =D28/D15 | E29: =E28/E15 | F29: =+E29-D29 | G29: =G28/G15 | H29: =+G29-E29 | I29: =I28/I15 | J29: =+I29-G29 | K29: =K28/K15 | L29: =L28/L15 | M29: =M28/M15 | N29: =N28/N15 | O29: =O28/O15
C31: Other Income / (Expense) | D31: 0 | E31: 0 | F31: =+E31-D31 | G31: =SUMIF('Monthly Detail'!$1:$1,'Annual Summary'!G$11, 'Monthly Detail'!109:109) | H31: =+G31-E31 | I31: =SUMIF('Monthly Detail'!$1:$1,'Annual Summary'!I$11, 'Monthly Detail'!109:109) | J31: =+I31-G31 | K31: =SUMIF('Monthly Detail'!$1:$1,'Annual Summary'!K$11, 'Monthly Detail'!109:109) | L31: =SUMIF('Monthly Detail'!$1:$1,'Annual Summary'!L$11, 'Monthly Detail'!109:109) | M31: =SUMIF('Monthly Detail'!$1:$1,'Annual Summary'!M$11, 'Monthly Detail'!109:109) | N31: =SUMIF('Monthly Detail'!$1:$1,'Annual Summary'!N$11, 'Monthly Detail'!109:109) | O31: =SUMIF('Monthly Detail'!$1:$1,'Annual Summary'!O$11, 'Monthly Detail'!109:109)
C32: Net Income | D32: =D28+D31 | E32: =E28+E31 | F32: =+E32-D32 | G32: =G28+G31 | H32: =+G32-E32 | I32: =I28+I31 | J32: =+I32-G32 | K32: =K28+K31 | L32: =L28+L31 | M32: =M28+M31 | N32: =N28+N31 | O32: =O28+O31
C33: NI % | D33: =D32/D15 | E33: =E32/E15 | F33: =+E33-D33 | G33: =G32/G15 | H33: =+G33-E33 | I33: =I32/I15 | J33: =+I33-G33 | K33: =K32/K15 | L33: =L32/L15 | M33: =M32/M15 | N33: =N32/N15 | O33: =O32/O15
C34: Estimated Tax Burden | D34: =+IF(D32>0, D32*0.25, 0) | E34: =+IF(E32>0, E32*0.25, 0) | G34: =+IF(G32>0, G32*0.25, 0) | H34: =+G34-E34 | I34: =+IF(I32>0, I32*0.25, 0) | J34: =+I34-G34 | K34: =+IF(K32>0, K32*0.25, 0) | L34: =+IF(L32>0, L32*0.25, 0)
C35: S-Corp Tax Savings | I35: =+((I15-G15)+(I32-G32))*0.153 | K35: =+((K15-I15)+(K32-I32))*0.153 | L35: =+((L15-K15)+(L32-K32))*0.153
C36: Cash Balance | E36: =+SUMIF('Monthly Detail'!$4:$4, DATE(E11, 12, 31),'Monthly Detail'!$174:$174) | F36: =+SUMIF('Monthly Detail'!$4:$4, DATE(F11, 12, 31),'Monthly Detail'!$174:$174) | G36: =+SUMIF('Monthly Detail'!$4:$4, DATE(G11, 12, 31),'Monthly Detail'!$174:$174) | H36: =+G36-E36 | I36: =+SUMIF('Monthly Detail'!$4:$4, DATE(I11, 12, 31),'Monthly Detail'!$174:$174) | J36: =+I36-G36 | K36: =+SUMIF('Monthly Detail'!$4:$4, DATE(K11, 12, 31),'Monthly Detail'!$174:$174) | L36: =+SUMIF('Monthly Detail'!$4:$4, DATE(L11, 12, 31),'Monthly Detail'!$174:$174)

Sheet 2025 AOP
B8: 2025 Annual Operating Plan
C10: January | D10: February | E10: March | F10: April | G10: May | H10: June | I10: July | J10: August | K10: September | L10: October | M10: November | N10: December | P10: Total
C11: 45688 | D11: 45716 | E11: 45747 | F11: 45777 | G11: 45808 | H11: 45838 | I11: 45869 | J11: 45900 | K11: 45930 | L11: 45961 | M11: 45991 | N11: 46022 | O11: 46053
B12: Service Income | C12: 7677.1321 | D12: 12691.952 | E12: 7473.9 | F12: 9831.9706 | G12: 10732.473 | H12: 5809.4312 | I12: 10858.9 | J12: 15862.285 | K12: 12122.449 | L12: 15626.953 | M12: 8797.317 | N12: 6287.4785 | P12: 123772.24
B13: Tips | C13: 13.919186 | D13: 23.011412 | E13: 13.550712 | F13: 17.826062 | G13: 19.458736 | H13: 10.532912 | I13: 19.687958 | J13: 28.75945 | K13: 21.978862 | L13: 28.332777 | M13: 15.950161 | N13: 11.399646 | P13: 224.40787
B14: Total Income | C14: 7691.0513 | D14: 12714.964 | E14: 7487.4507 | F14: 9849.7967 | G14: 10751.932 | H14: 5819.9642 | I14: 10878.588 | J14: 15891.044 | K14: 12144.428 | L14: 15655.286 | M14: 8813.2671 | N14: 6298.8782 | P14: 123996.65
B15: # of Students | C15: 34.8 | D15: 35.8 | E15: 33.6 | F15: 32.4 | G15: 33.4 | H15: 29.2 | I15: 31.2 | J15: 37.2 | K15: 43.2 | L15: 45 | M15: 43.6 | N15: 42.2
B16: # of Sessions | C16: 34 | D16: 56 | E16: 36 | F16: 49 | G16: 76 | H16: 45 | I16: 118 | J16: 169 | K16: 125 | L16: 173 | M16: 90 | N16: 129.33333
B18: Subcontractor Expenses | C18: 0 | D18: 919.6069 | E18: 450 | F18: 1073.0882 | G18: 2850.0435 | H18: 1050 | I18: 1894.25 | J18: 4130.1794 | K18: 1256.4172 | L18: 1439.8958 | M18: 524 | N18: 0 | P18: 15587.481
B19: Gross Margin | C19: 7691.0513 | D19: 11795.357 | E19: 7037.4507 | F19: 8776.7084 | G19: 7901.8881 | H19: 4769.9642 | I19: 8984.338 | J19: 11760.865 | K19: 10888.011 | L19: 14215.39 | M19: 8289.2671 | N19: 6298.8782 | P19: 108409.17
B20: GM % | C20: 1 | D20: 0.92767522 | E20: 0.93989944 | F20: 0.89105478 | G20: 0.7349273 | H20: 0.81958652 | I20: 0.82587354 | J20: 0.74009389 | K20: 0.89654373 | L20: 0.90802494 | M20: 0.94054418 | N20: 1 | P20: 0.87429111
B22: Sales & Marketing Expenses | C22: 0 | D22: 0 | E22: 0 | F22: 0 | G22: 0 | H22: 0 | I22: 0 | J22: 0 | K22: 0 | L22: 0 | M22: 0 | N22: 0 | P22: 0
B23: General & Admintrative Expenses | C23: 1454.0336 | D23: 1416.0203 | E23: 1647.4689 | F23: 1523.6384 | G23: 1352.726 | H23: 1193.7039 | I23: 1556.8098 | J23: 2008.4271 | K23: 1397.6245 | L23: 1973.3255 | M23: 1340.2174 | N23: 1635.3956 | P23: 18499.391
B24: Operating Expenses | C24: 1454.0336 | D24: 1416.0203 | E24: 1647.4689 | F24: 1523.6384 | G24: 1352.726 | H24: 1193.7039 | I24: 1556.8098 | J24: 2008.4271 | K24: 1397.6245 | L24: 1973.3255 | M24: 1340.2174 | N24: 1635.3956 | P24: 18499.391
B26: Net Operating Income (EBITDA) | C26: 6237.0177 | D26: 10379.337 | E26: 5389.9818 | F26: 7253.0701 | G26: 6549.1621 | H26: 3576.2603 | I26: 7427.5281 | J26: 9752.4376 | K26: 9490.3861 | L26: 12242.065 | M26: 6949.0498 | N26: 4663.4826 | P26: 89909.777
B27: EBITDA % | C27: 0.81094475 | D27: 0.81630878 | E27: 0.71986875 | F27: 0.73636749 | G27: 0.60911493 | H27: 0.61448149 | I27: 0.68276583 | J27: 0.61370653 | K27: 0.78146013 | L27: 0.78197643 | M27: 0.78847601 | N27: 0.74036716 | P27: 0.72509844
B29: Other Income / (Expense) | C29: -800 | D29: -800 | E29: -800 | F29: -800 | G29: -800 | H29: -800 | I29: -800 | J29: -800 | K29: -800 | L29: -800 | M29: -800 | N29: -800 | P29: -9600
B30: Net Income | C30: 5437.0177 | D30: 9579.3366 | E30: 4589.9818 | F30: 6453.0701 | G30: 5749.1621 | H30: 2776.2603 | I30: 6627.5281 | J30: 8952.4376 | K30: 8690.3861 | L30: 11442.065 | M30: 6149.0498 | N30: 3863.4826 | P30: 80309.777
B31: NI % | C31: 0.70692776 | D31: 0.75339079 | E31: 0.61302331 | F31: 0.65514754 | G31: 0.5347097 | H31: 0.4770236 | I31: 0.60922687 | J31: 0.56336371 | K31: 0.7155863 | L31: 0.73087548 | M31: 0.69770377 | N31: 0.61336042 | P31: 0.64767699
B32: Cash Contributions | C32: 0 | D32: 0 | E32: 0 | F32: 2400 | G32: 0 | H32: 0 | I32: 0 | J32: 0 | K32: 0 | L32: 0 | M32: 0 | N32: 0 | P32: 2400
... B34: Accrued Tax Burden | C34: 1631.1053 | D34: 4744.9063 | E34: 6361.9008 | F34: 8537.8218 | G34: 10502.57 | H34: 11575.449 | I34: 13803.707 | J34: 16729.438 | K34: 19576.554 | L34: 23249.173 | M34: 25333.888 | N34: 26732.933 | P34: 26732.933
B36: Operating Cash | C36: 5910.492 | D36: 11084.272 | E36: 13626.641 | F36: 16286.345 | G36: 18578.006 | H36: 19238.674 | I36: 21452.662 | J36: 26002.178 | K36: 32304.328 | L36: 39688.856 | M36: 44161.647 | N36: 45353.467
B37: Cash Inflow (Outflow) | C37: 1691.5453 | D37: 5173.7804 | E37: 2542.3684 | F37: 2659.704 | G37: 2291.6609 | H37: 660.66802 | I37: 2213.988 | J37: 4549.5165 | K37: 6302.1499 | L37: 7384.5278 | M37: 4472.7907 | N37: 1191.8202

Sheet 2023 Overview
C10: =TEXT('Monthly Detail'!D4,"mmmm") | D10: =TEXT('Monthly Detail'!E4,"mmmm") | E10: =TEXT('Monthly Detail'!F4,"mmmm") | F10: =TEXT('Monthly Detail'!G4,"mmmm") | G10: =TEXT('Monthly Detail'!H4,"mmmm") | H10: =TEXT('Monthly Detail'!I4,"mmmm") | I10: =TEXT('Monthly Detail'!J4,"mmmm") | J10: =TEXT('Monthly Detail'!K4,"mmmm") | ... N10: =TEXT('Monthly Detail'!O4,"mmmm") | P10: Total
C11: 44957 | D11: 44985 | E11: 45016 | F11: 45046 | G11: 45077 | H11: 45107 | I11: 45138 | J11: 45169 | K11: 45199 | L11: 45230 | M11: 45260 | N11: 45291 | O11: 45322
B12: Service Income | C12: =SUMIF('Monthly Detail'!$4:$4, '2023 Overview'!C$11, 'Monthly Detail'!12:12) | D12: =SUMIF('Monthly Detail'!$4:$4, '2023 Overview'!D$11, 'Monthly Detail'!12:12) | E12: =SUMIF('Monthly Detail'!$4:$4, '2023 Overview'!E$11, 'Monthly Detail'!12:12) | F12: =SUMIF('Monthly Detail'!$4:$4, '2023 Overview'!F$11, 'Monthly Detail'!12:12) | G12: =SUMIF('Monthly Detail'!$4:$4, '2023 Overview'!G$11, 'Monthly Detail'!12:12) | H12: =SUMIF('Monthly Detail'!$4:$4, '2023 Overview'!H$11, 'Monthly Detail'!12:12) | I12: =SUMIF('Monthly Detail'!$4:$4, '2023 Overview'!I$11, 'Monthly Detail'!12:12) | J12: =SUMIF('Monthly Detail'!$4:$4, '2023 Overview'!J$11, 'Monthly Detail'!12:12) | ... N12: =SUMIF('Monthly Detail'!$4:$4, '2023 Overview'!N$11, 'Monthly Detail'!12:12) | P12: =SUM(C12:O12)
B13: Misc. | C13: =SUMIF('Monthly Detail'!$4:$4, '2023 Overview'!C$11, 'Monthly Detail'!13:13) | D13: =SUMIF('Monthly Detail'!$4:$4, '2023 Overview'!D$11, 'Monthly Detail'!13:13) | E13: =SUMIF('Monthly Detail'!$4:$4, '2023 Overview'!E$11, 'Monthly Detail'!13:13) | F13: =SUMIF('Monthly Detail'!$4:$4, '2023 Overview'!F$11, 'Monthly Detail'!13:13) | G13: =SUMIF('Monthly Detail'!$4:$4, '2023 Overview'!G$11, 'Monthly Detail'!13:13) | H13: =SUMIF('Monthly Detail'!$4:$4, '2023 Overview'!H$11, 'Monthly Detail'!13:13) | I13: =SUMIF('Monthly Detail'!$4:$4, '2023 Overview'!I$11, 'Monthly Detail'!13:13) | J13: =SUMIF('Monthly Detail'!$4:$4, '2023 Overview'!J$11, 'Monthly Detail'!13:13) | ... N13: =SUMIF('Monthly Detail'!$4:$4, '2023 Overview'!N$11, 'Monthly Detail'!13:13)
B14: Total Income | C14: =SUM(C12:C13) | D14: =SUM(D12:D13) | E14: =SUM(E12:E13) | F14: =SUM(F12:F13) | G14: =SUM(G12:G13) | H14: =SUM(H12:H13) | I14: =SUM(I12:I13) | J14: =SUM(J12:J13) | ... N14: =SUM(N12:N13) | P14: =SUM(P12:P12)
B16: Gross Margin | C16: =C14 | D16: =D14 | E16: =E14 | F16: =F14 | G16: =G14 | H16: =H14 | I16: =I14 | J16: =J14 | ... N16: =N14 | P16: =P14
B17: GM % | C17: =C16/C14 | D17: =D16/D14 | E17: =E16/E14 | F17: =F16/F14 | G17: =G16/G14 | H17: =H16/H14 | I17: =I16/I14 | J17: =J16/J14 | ... N17: =N16/N14 | P17: =P16/P14
B19: General & Admintrative Expenses | C19: =SUMIF('Monthly Detail'!$4:$4, '2023 Overview'!C$11, 'Monthly Detail'!$95:$95) | D19: =SUMIF('Monthly Detail'!$4:$4, '2023 Overview'!D$11, 'Monthly Detail'!$95:$95) | E19: =SUMIF('Monthly Detail'!$4:$4, '2023 Overview'!E$11, 'Monthly Detail'!$95:$95) | F19: =SUMIF('Monthly Detail'!$4:$4, '2023 Overview'!F$11, 'Monthly Detail'!$95:$95) | G19: =SUMIF('Monthly Detail'!$4:$4, '2023 Overview'!G$11, 'Monthly Detail'!$95:$95) | H19: =SUMIF('Monthly Detail'!$4:$4, '2023 Overview'!H$11, 'Monthly Detail'!$95:$95) | I19: =SUMIF('Monthly Detail'!$4:$4, '2023 Overview'!I$11, 'Monthly Detail'!$95:$95) | J19: =SUMIF('Monthly Detail'!$4:$4, '2023 Overview'!J$11, 'Monthly Detail'!$95:$95) | ... N19: =SUMIF('Monthly Detail'!$4:$4, '2023 Overview'!N$11, 'Monthly Detail'!$95:$95) | P19: =SUM(C19:O19)
B20: Operating Expenses | C20: =SUM(C19:C19) | D20: =SUM(D19:D19) | E20: =SUM(E19:E19) | F20: =SUM(F19:F19) | G20: =SUM(G19:G19) | H20: =SUM(H19:H19) | I20: =SUM(I19:I19) | J20: =SUM(J19:J19) | ... N20: =SUM(N19:N19) | P20: =SUM(P19:P19)
B22: Net Operating Income (EBITDA) | C22: =C16-C20 | D22: =D16-D20 | E22: =E16-E20 | F22: =F16-F20 | G22: =G16-G20 | H22: =H16-H20 | I22: =I16-I20 | J22: =J16-J20 | ... N22: =N16-N20 | P22: =P16-P20
B23: EBITDA % | C23: =C22/C14 | D23: =D22/D14 | E23: =E22/E14 | F23: =F22/F14 | G23: =G22/G14 | H23: =H22/H14 | I23: =I22/I14 | J23: =J22/J14 | ... N23: =N22/N14 | P23: =P22/P14
B25: Other Income / (Expense) | C25: =SUMIF('Monthly Detail'!$4:$4, '2023 Overview'!C$11, 'Monthly Detail'!104:104) | D25: =SUMIF('Monthly Detail'!$4:$4, '2023 Overview'!D$11, 'Monthly Detail'!104:104) | E25: =SUMIF('Monthly Detail'!$4:$4, '2023 Overview'!E$11, 'Monthly Detail'!104:104) | F25: =SUMIF('Monthly Detail'!$4:$4, '2023 Overview'!F$11, 'Monthly Detail'!104:104) | G25: =SUMIF('Monthly Detail'!$4:$4, '2023 Overview'!G$11, 'Monthly Detail'!104:104) | H25: =SUMIF('Monthly Detail'!$4:$4, '2023 Overview'!H$11, 'Monthly Detail'!104:104) | I25: =SUMIF('Monthly Detail'!$4:$4, '2023 Overview'!I$11, 'Monthly Detail'!104:104) | J25: =SUMIF('Monthly Detail'!$4:$4, '2023 Overview'!J$11, 'Monthly Detail'!104:104) | ... N25: =SUMIF('Monthly Detail'!$4:$4, '2023 Overview'!N$11, 'Monthly Detail'!104:104) | P25: =SUM(C25:O25)
B26: Net Income | C26: =C22+SUM(C25:C25) | D26: =D22+SUM(D25:D25) | E26: =E22+SUM(E25:E25) | F26: =F22+SUM(F25:F25) | G26: =G22+SUM(G25:G25) | H26: =H22+SUM(H25:H25) | I26: =I22+SUM(I25:I25) | J26: =J22+SUM(J25:J25) | ... N26: =N22+SUM(N25:N25) | P26: =P22+SUM(P25:P25)
B27: NI % | C27: =C26/C14 | D27: =D26/D14 | E27: =E26/E14 | F27: =F26/F14 | G27: =G26/G14 | H27: =H26/H14 | I27: =I26/I14 | J27: =J26/J14 | ... N27: =N26/N14 | P27: =P26/P14
B29: Operating Cash | C29: =SUMIF('Monthly Detail'!$4:$4, '2023 Overview'!C$11, 'Monthly Detail'!174:174) | D29: =SUMIF('Monthly Detail'!$4:$4, '2023 Overview'!D$11, 'Monthly Detail'!174:174) | E29: =SUMIF('Monthly Detail'!$4:$4, '2023 Overview'!E$11, 'Monthly Detail'!174:174) | F29: =SUMIF('Monthly Detail'!$4:$4, '2023 Overview'!F$11, 'Monthly Detail'!174:174) | G29: =SUMIF('Monthly Detail'!$4:$4, '2023 Overview'!G$11, 'Monthly Detail'!174:174) | H29: =SUMIF('Monthly Detail'!$4:$4, '2023 Overview'!H$11, 'Monthly Detail'!174:174) | I29: =SUMIF('Monthly Detail'!$4:$4, '2023 Overview'!I$11, 'Monthly Detail'!174:174) | J29: =SUMIF('Monthly Detail'!$4:$4, '2023 Overview'!J$11, 'Monthly Detail'!174:174) | ... N29: =SUMIF('Monthly Detail'!$4:$4, '2023 Overview'!N$11, 'Monthly Detail'!174:174)
B30: Cash Inflow (Outflow) | C30: =SUMIF('Monthly Detail'!$4:$4, '2023 Overview'!C$11, 'Monthly Detail'!171:171) | D30: =SUMIF('Monthly Detail'!$4:$4, '2023 Overview'!D$11, 'Monthly Detail'!171:171) | E30: =SUMIF('Monthly Detail'!$4:$4, '2023 Overview'!E$11, 'Monthly Detail'!171:171) | F30: =SUMIF('Monthly Detail'!$4:$4, '2023 Overview'!F$11, 'Monthly Detail'!171:171) | G30: =SUMIF('Monthly Detail'!$4:$4, '2023 Overview'!G$11, 'Monthly Detail'!171:171) | H30: =SUMIF('Monthly Detail'!$4:$4, '2023 Overview'!H$11, 'Monthly Detail'!171:171) | I30: =SUMIF('Monthly Detail'!$4:$4, '2023 Overview'!I$11, 'Monthly Detail'!171:171) | J30: =SUMIF('Monthly Detail'!$4:$4, '2023 Overview'!J$11, 'Monthly Detail'!171:171) | ... N30: =SUMIF('Monthly Detail'!$4:$4, '2023 Overview'!N$11, 'Monthly Detail'!171:171)

Sheet 2026 AOP
B8: 2026 Annual Operating Plan
C10: =TEXT('Monthly Detail'!D4,"mmmm") | D10: =TEXT('Monthly Detail'!E4,"mmmm") | E10: =TEXT('Monthly Detail'!F4,"mmmm") | F10: =TEXT('Monthly Detail'!G4,"mmmm") | G10: =TEXT('Monthly Detail'!H4,"mmmm") | H10: =TEXT('Monthly Detail'!I4,"mmmm") | I10: =TEXT('Monthly Detail'!J4,"mmmm") | J10: =TEXT('Monthly Detail'!K4,"mmmm") | ... N10: =TEXT('Monthly Detail'!O4,"mmmm") | P10: Total
C11: 46053 | D11: 46081 | E11: 46112 | F11: 46142 | G11: 46173 | H11: 46203 | I11: 46234 | J11: 46265 | K11: 46295 | L11: 46326 | M11: 46356 | N11: 46387 | O11: 45322
B12: Service Income | C12: =SUMIF('Monthly Detail'!$4:$4, '2026 AOP'!C$11, 'Monthly Detail'!12:12) | D12: =SUMIF('Monthly Detail'!$4:$4, '2026 AOP'!D$11, 'Monthly Detail'!12:12) | E12: =SUMIF('Monthly Detail'!$4:$4, '2026 AOP'!E$11, 'Monthly Detail'!12:12) | F12: =SUMIF('Monthly Detail'!$4:$4, '2026 AOP'!F$11, 'Monthly Detail'!12:12) | G12: =SUMIF('Monthly Detail'!$4:$4, '2026 AOP'!G$11, 'Monthly Detail'!12:12) | H12: =SUMIF('Monthly Detail'!$4:$4, '2026 AOP'!H$11, 'Monthly Detail'!12:12) | I12: =SUMIF('Monthly Detail'!$4:$4, '2026 AOP'!I$11, 'Monthly Detail'!12:12) | J12: =SUMIF('Monthly Detail'!$4:$4, '2026 AOP'!J$11, 'Monthly Detail'!12:12) | ... N12: =SUMIF('Monthly Detail'!$4:$4, '2026 AOP'!N$11, 'Monthly Detail'!12:12) | P12: =SUM(C12:O12)
B13: Tips | C13: =SUMIF('Monthly Detail'!$4:$4, '2026 AOP'!C$11, 'Monthly Detail'!13:13) | D13: =SUMIF('Monthly Detail'!$4:$4, '2026 AOP'!D$11, 'Monthly Detail'!13:13) | E13: =SUMIF('Monthly Detail'!$4:$4, '2026 AOP'!E$11, 'Monthly Detail'!13:13) | F13: =SUMIF('Monthly Detail'!$4:$4, '2026 AOP'!F$11, 'Monthly Detail'!13:13) | G13: =SUMIF('Monthly Detail'!$4:$4, '2026 AOP'!G$11, 'Monthly Detail'!13:13) | H13: =SUMIF('Monthly Detail'!$4:$4, '2026 AOP'!H$11, 'Monthly Detail'!13:13) | I13: =SUMIF('Monthly Detail'!$4:$4, '2026 AOP'!I$11, 'Monthly Detail'!13:13) | J13: =SUMIF('Monthly Detail'!$4:$4, '2026 AOP'!J$11, 'Monthly Detail'!13:13) | ... N13: =SUMIF('Monthly Detail'!$4:$4, '2026 AOP'!N$11, 'Monthly Detail'!13:13) | P13: =+SUM(C13:N13)
B14: Total Income | C14: =SUM(C12:C13) | D14: =SUM(D12:D13) | E14: =SUM(E12:E13) | F14: =SUM(F12:F13) | G14: =SUM(G12:G13) | H14: =SUM(H12:H13) | I14: =SUM(I12:I13) | J14: =SUM(J12:J13) | ... N14: =SUM(N12:N13) | P14: =SUM(P12:P13)
B15: # of Students | C15: =SUMIF('Monthly Detail'!$4:$4, '2026 AOP'!C$11, 'Monthly Detail'!17:17) | D15: =SUMIF('Monthly Detail'!$4:$4, '2026 AOP'!D$11, 'Monthly Detail'!17:17) | E15: =SUMIF('Monthly Detail'!$4:$4, '2026 AOP'!E$11, 'Monthly Detail'!17:17) | F15: =SUMIF('Monthly Detail'!$4:$4, '2026 AOP'!F$11, 'Monthly Detail'!17:17) | G15: =SUMIF('Monthly Detail'!$4:$4, '2026 AOP'!G$11, 'Monthly Detail'!17:17) | H15: =SUMIF('Monthly Detail'!$4:$4, '2026 AOP'!H$11, 'Monthly Detail'!17:17) | I15: =SUMIF('Monthly Detail'!$4:$4, '2026 AOP'!I$11, 'Monthly Detail'!17:17) | J15: =SUMIF('Monthly Detail'!$4:$4, '2026 AOP'!J$11, 'Monthly Detail'!17:17) | ... N15: =SUMIF('Monthly Detail'!$4:$4, '2026 AOP'!N$11, 'Monthly Detail'!17:17)
B16: # of Sessions | C16: =SUMIF('Monthly Detail'!$4:$4, '2026 AOP'!C$11, 'Monthly Detail'!22:22) | D16: =SUMIF('Monthly Detail'!$4:$4, '2026 AOP'!D$11, 'Monthly Detail'!22:22) | E16: =SUMIF('Monthly Detail'!$4:$4, '2026 AOP'!E$11, 'Monthly Detail'!22:22) | F16: =SUMIF('Monthly Detail'!$4:$4, '2026 AOP'!F$11, 'Monthly Detail'!22:22) | G16: =SUMIF('Monthly Detail'!$4:$4, '2026 AOP'!G$11, 'Monthly Detail'!22:22) | H16: =SUMIF('Monthly Detail'!$4:$4, '2026 AOP'!H$11, 'Monthly Detail'!22:22) | I16: =SUMIF('Monthly Detail'!$4:$4, '2026 AOP'!I$11, 'Monthly Detail'!22:22) | J16: =SUMIF('Monthly Detail'!$4:$4, '2026 AOP'!J$11, 'Monthly Detail'!22:22) | ... N16: =SUMIF('Monthly Detail'!$4:$4, '2026 AOP'!N$11, 'Monthly Detail'!22:22)
B18: Subcontractor Expenses | C18: =SUMIF('Monthly Detail'!$4:$4, '2026 AOP'!C$11, 'Monthly Detail'!65:65) | D18: =SUMIF('Monthly Detail'!$4:$4, '2026 AOP'!D$11, 'Monthly Detail'!65:65) | E18: =SUMIF('Monthly Detail'!$4:$4, '2026 AOP'!E$11, 'Monthly Detail'!65:65) | F18: =SUMIF('Monthly Detail'!$4:$4, '2026 AOP'!F$11, 'Monthly Detail'!65:65) | G18: =SUMIF('Monthly Detail'!$4:$4, '2026 AOP'!G$11, 'Monthly Detail'!65:65) | H18: =SUMIF('Monthly Detail'!$4:$4, '2026 AOP'!H$11, 'Monthly Detail'!65:65) | I18: =SUMIF('Monthly Detail'!$4:$4, '2026 AOP'!I$11, 'Monthly Detail'!65:65) | J18: =SUMIF('Monthly Detail'!$4:$4, '2026 AOP'!J$11, 'Monthly Detail'!65:65) | ... N18: =SUMIF('Monthly Detail'!$4:$4, '2026 AOP'!N$11, 'Monthly Detail'!65:65) | P18: =SUM(C18:O18)
B19: Gross Margin | C19: =C14-C18 | D19: =D14-D18 | E19: =E14-E18 | F19: =F14-F18 | G19: =G14-G18 | H19: =H14-H18 | I19: =I14-I18 | J19: =J14-J18 | ... N19: =N14-N18 | P19: =P14-P18
B20: GM % | C20: =C19/C14 | D20: =D19/D14 | E20: =E19/E14 | F20: =F19/F14 | G20: =G19/G14 | H20: =H19/H14 | I20: =I19/I14 | J20: =J19/J14 | ... N20: =N19/N14 | P20: =P19/P14
B22: Sales & Marketing Expenses | C22: =SUMIF('Monthly Detail'!$4:$4, '2026 AOP'!C$11, 'Monthly Detail'!$72:$72) | D22: =SUMIF('Monthly Detail'!$4:$4, '2026 AOP'!D$11, 'Monthly Detail'!$72:$72) | E22: =SUMIF('Monthly Detail'!$4:$4, '2026 AOP'!E$11, 'Monthly Detail'!$72:$72) | F22: =SUMIF('Monthly Detail'!$4:$4, '2026 AOP'!F$11, 'Monthly Detail'!$72:$72) | G22: =SUMIF('Monthly Detail'!$4:$4, '2026 AOP'!G$11, 'Monthly Detail'!$72:$72) | H22: =SUMIF('Monthly Detail'!$4:$4, '2026 AOP'!H$11, 'Monthly Detail'!$72:$72) | I22: =SUMIF('Monthly Detail'!$4:$4, '2026 AOP'!I$11, 'Monthly Detail'!$72:$72) | J22: =SUMIF('Monthly Detail'!$4:$4, '2026 AOP'!J$11, 'Monthly Detail'!$72:$72) | ... N22: =SUMIF('Monthly Detail'!$4:$4, '2026 AOP'!N$11, 'Monthly Detail'!$72:$72) | P22: =SUM(C22:O22)
B23: General & Admintrative Expenses | C23: =SUMIF('Monthly Detail'!$4:$4, '2026 AOP'!C$11, 'Monthly Detail'!$95:$95) | D23: =SUMIF('Monthly Detail'!$4:$4, '2026 AOP'!D$11, 'Monthly Detail'!$95:$95) | E23: =SUMIF('Monthly Detail'!$4:$4, '2026 AOP'!E$11, 'Monthly Detail'!$95:$95) | F23: =SUMIF('Monthly Detail'!$4:$4, '2026 AOP'!F$11, 'Monthly Detail'!$95:$95) | G23: =SUMIF('Monthly Detail'!$4:$4, '2026 AOP'!G$11, 'Monthly Detail'!$95:$95) | H23: =SUMIF('Monthly Detail'!$4:$4, '2026 AOP'!H$11, 'Monthly Detail'!$95:$95) | I23: =SUMIF('Monthly Detail'!$4:$4, '2026 AOP'!I$11, 'Monthly Detail'!$95:$95) | J23: =SUMIF('Monthly Detail'!$4:$4, '2026 AOP'!J$11, 'Monthly Detail'!$95:$95) | ... N23: =SUMIF('Monthly Detail'!$4:$4, '2026 AOP'!N$11, 'Monthly Detail'!$95:$95) | P23: =SUM(C23:O23)
B24: Operating Expenses | C24: =SUM(C23:C23) | D24: =SUM(D22:D23) | E24: =SUM(E22:E23) | F24: =SUM(F22:F23) | G24: =SUM(G22:G23) | H24: =SUM(H22:H23) | I24: =SUM(I22:I23) | J24: =SUM(J22:J23) | K24: =SUM(K22:K23) | ... N24: =SUM(N22:N23) | P24: =SUM(P22:P23)
B26: Net Operating Income (EBITDA) | C26: =C19-C24 | D26: =D19-D24 | E26: =E19-E24 | F26: =F19-F24 | G26: =G19-G24 | H26: =H19-H24 | I26: =I19-I24 | J26: =J19-J24 | ... N26: =N19-N24 | P26: =P19-P24
B27: EBITDA % | C27: =C26/C14 | D27: =D26/D14 | E27: =E26/E14 | F27: =F26/F14 | G27: =G26/G14 | H27: =H26/H14 | I27: =I26/I14 | J27: =J26/J14 | ... N27: =N26/N14 | P27: =P26/P14
B29: Other Income / (Expense) | C29: =SUMIF('Monthly Detail'!$4:$4, '2026 AOP'!C$11, 'Monthly Detail'!109:109) | D29: =SUMIF('Monthly Detail'!$4:$4, '2026 AOP'!D$11, 'Monthly Detail'!109:109) | E29: =SUMIF('Monthly Detail'!$4:$4, '2026 AOP'!E$11, 'Monthly Detail'!109:109) | F29: =SUMIF('Monthly Detail'!$4:$4, '2026 AOP'!F$11, 'Monthly Detail'!109:109) | G29: =SUMIF('Monthly Detail'!$4:$4, '2026 AOP'!G$11, 'Monthly Detail'!109:109) | H29: =SUMIF('Monthly Detail'!$4:$4, '2026 AOP'!H$11, 'Monthly Detail'!109:109) | I29: =SUMIF('Monthly Detail'!$4:$4, '2026 AOP'!I$11, 'Monthly Detail'!109:109) | J29: =SUMIF('Monthly Detail'!$4:$4, '2026 AOP'!J$11, 'Monthly Detail'!109:109) | ... N29: =SUMIF('Monthly Detail'!$4:$4, '2026 AOP'!N$11, 'Monthly Detail'!109:109) | P29: =SUM(C29:O29)
B30: Net Income | C30: =C26+SUM(C29:C29) | D30: =D26+SUM(D29:D29) | E30: =E26+SUM(E29:E29) | F30: =F26+SUM(F29:F29) | G30: =G26+SUM(G29:G29) | H30: =H26+SUM(H29:H29) | I30: =I26+SUM(I29:I29) | J30: =J26+SUM(J29:J29) | ... N30: =N26+SUM(N29:N29) | P30: =P26+SUM(P29:P29)
B31: NI % | C31: =C30/C14 | D31: =D30/D14 | E31: =E30/E14 | F31: =F30/F14 | G31: =G30/G14 | H31: =H30/H14 | I31: =I30/I14 | J31: =J30/J14 | ... N31: =N30/N14 | P31: =P30/P14
B32: Cash Contributions | C32: ='Monthly Detail'!AN149-'Monthly Detail'!AM149 | D32: ='Monthly Detail'!AO149-'Monthly Detail'!AN149 | E32: ='Monthly Detail'!AP149-'Monthly Detail'!AO149 | F32: ='Monthly Detail'!AQ149-'Monthly Detail'!AP149 | G32: ='Monthly Detail'!AR149-'Monthly Detail'!AQ149 | H32: ='Monthly Detail'!AS149-'Monthly Detail'!AR149 | I32: ='Monthly Detail'!AT149-'Monthly Detail'!AS149 | J32: ='Monthly Detail'!AU149-'Monthly Detail'!AT149 | ... N32: ='Monthly Detail'!AY149-'Monthly Detail'!AX149 | P32: =+SUM(C32:N32)
B33: Owner Cash Distributions/Taxes | C33: =+SUM('Monthly Detail'!AN150,'Monthly Detail'!AN152:AN153)-SUM('Monthly Detail'!AM150,'Monthly Detail'!AM152:AM153) | D33: =+SUM('Monthly Detail'!AO150,'Monthly Detail'!AO152:AO153)-SUM('Monthly Detail'!AN150,'Monthly Detail'!AN152:AN153) | E33: =+SUM('Monthly Detail'!AP150,'Monthly Detail'!AP152:AP153)-SUM('Monthly Detail'!AO150,'Monthly Detail'!AO152:AO153) | F33: =+SUM('Monthly Detail'!AQ150,'Monthly Detail'!AQ152:AQ153)-SUM('Monthly Detail'!AP150,'Monthly Detail'!AP152:AP153) | G33: =+SUM('Monthly Detail'!AR150,'Monthly Detail'!AR152:AR153)-SUM('Monthly Detail'!AQ150,'Monthly Detail'!AQ152:AQ153) | H33: =+SUM('Monthly Detail'!AS150,'Monthly Detail'!AS152:AS153)-SUM('Monthly Detail'!AR150,'Monthly Detail'!AR152:AR153) | I33: =+SUM('Monthly Detail'!AT150,'Monthly Detail'!AT152:AT153)-SUM('Monthly Detail'!AS150,'Monthly Detail'!AS152:AS153) | J33: =+SUM('Monthly Detail'!AU150,'Monthly Detail'!AU152:AU153)-SUM('Monthly Detail'!AT150,'Monthly Detail'!AT152:AT153) | ... N33: =+SUM('Monthly Detail'!AY150,'Monthly Detail'!AY152:AY153)-SUM('Monthly Detail'!AX150,'Monthly Detail'!AX152:AX153) | P33: =+SUM(C33:N33)
B34: Accrued Tax Burden | C34: =+C30*0.3 | D34: =+C34+(D26*0.3)-SUMIF('Monthly Detail'!$4:$4, '2026 AOP'!D$11, 'Monthly Detail'!77:77) | E34: =+D34+(E26*0.3)-SUMIF('Monthly Detail'!$4:$4, '2026 AOP'!E$11, 'Monthly Detail'!77:77) | F34: =+E34+(F26*0.3)-SUMIF('Monthly Detail'!$4:$4, '2026 AOP'!F$11, 'Monthly Detail'!77:77) | G34: =+F34+(G26*0.3)-SUMIF('Monthly Detail'!$4:$4, '2026 AOP'!G$11, 'Monthly Detail'!77:77) | H34: =+G34+(H26*0.3)-SUMIF('Monthly Detail'!$4:$4, '2026 AOP'!H$11, 'Monthly Detail'!77:77) | I34: =+H34+(I26*0.3)-SUMIF('Monthly Detail'!$4:$4, '2026 AOP'!I$11, 'Monthly Detail'!77:77) | J34: =+I34+(J26*0.3)-SUMIF('Monthly Detail'!$4:$4, '2026 AOP'!J$11, 'Monthly Detail'!77:77) | K34: =+J34+(K26*0.3)-SUMIF('Monthly Detail'!$4:$4, '2026 AOP'!K$11, 'Monthly Detail'!77:77) | ... N34: =+M34+(N26*0.3)-SUMIF('Monthly Detail'!$4:$4, '2026 AOP'!N$11, 'Monthly Detail'!77:77) | P34: =+N34
B36: Operating Cash | C36: =SUMIF('Monthly Detail'!$4:$4, '2026 AOP'!C$11, 'Monthly Detail'!174:174) | D36: =SUMIF('Monthly Detail'!$4:$4, '2026 AOP'!D$11, 'Monthly Detail'!174:174) | E36: =SUMIF('Monthly Detail'!$4:$4, '2026 AOP'!E$11, 'Monthly Detail'!174:174) | F36: =SUMIF('Monthly Detail'!$4:$4, '2026 AOP'!F$11, 'Monthly Detail'!174:174) | G36: =SUMIF('Monthly Detail'!$4:$4, '2026 AOP'!G$11, 'Monthly Detail'!174:174) | H36: =SUMIF('Monthly Detail'!$4:$4, '2026 AOP'!H$11, 'Monthly Detail'!174:174) | I36: =SUMIF('Monthly Detail'!$4:$4, '2026 AOP'!I$11, 'Monthly Detail'!174:174) | J36: =SUMIF('Monthly Detail'!$4:$4, '2026 AOP'!J$11, 'Monthly Detail'!174:174) | ... N36: =SUMIF('Monthly Detail'!$4:$4, '2026 AOP'!N$11, 'Monthly Detail'!174:174)
B37: Cash Inflow (Outflow) | C37: =SUMIF('Monthly Detail'!$4:$4, '2026 AOP'!C$11, 'Monthly Detail'!171:171) | D37: =SUMIF('Monthly Detail'!$4:$4, '2026 AOP'!D$11, 'Monthly Detail'!171:171) | E37: =SUMIF('Monthly Detail'!$4:$4, '2026 AOP'!E$11, 'Monthly Detail'!171:171) | F37: =SUMIF('Monthly Detail'!$4:$4, '2026 AOP'!F$11, 'Monthly Detail'!171:171) | G37: =SUMIF('Monthly Detail'!$4:$4, '2026 AOP'!G$11, 'Monthly Detail'!171:171) | H37: =SUMIF('Monthly Detail'!$4:$4, '2026 AOP'!H$11, 'Monthly Detail'!171:171) | I37: =SUMIF('Monthly Detail'!$4:$4, '2026 AOP'!I$11, 'Monthly Detail'!171:171) | J37: =SUMIF('Monthly Detail'!$4:$4, '2026 AOP'!J$11, 'Monthly Detail'!171:171) | ... N37: =SUMIF('Monthly Detail'!$4:$4, '2026 AOP'!N$11, 'Monthly Detail'!171:171)

Sheet 2025 Overview (Rolling)
B8: 2025 Overview (Rolling Forecast)
C10: =TEXT('Monthly Detail'!D4,"mmmm") | D10: =TEXT('Monthly Detail'!E4,"mmmm") | E10: =TEXT('Monthly Detail'!F4,"mmmm") | F10: =TEXT('Monthly Detail'!G4,"mmmm") | G10: =TEXT('Monthly Detail'!H4,"mmmm") | H10: =TEXT('Monthly Detail'!I4,"mmmm") | I10: =TEXT('Monthly Detail'!J4,"mmmm") | J10: =TEXT('Monthly Detail'!K4,"mmmm") | ... N10: =TEXT('Monthly Detail'!O4,"mmmm") | P10: Total
C11: 45688 | D11: 45716 | E11: 45747 | F11: 45777 | G11: 45808 | H11: 45838 | I11: 45869 | J11: 45900 | K11: 45930 | L11: 45961 | M11: 45991 | N11: 46022 | O11: 45322
B12: Service Income | C12: =SUMIF('Monthly Detail'!$4:$4, '2025 Overview (Rolling)'!C$11, 'Monthly Detail'!12:12) | D12: =SUMIF('Monthly Detail'!$4:$4, '2025 Overview (Rolling)'!D$11, 'Monthly Detail'!12:12) | E12: =SUMIF('Monthly Detail'!$4:$4, '2025 Overview (Rolling)'!E$11, 'Monthly Detail'!12:12) | F12: =SUMIF('Monthly Detail'!$4:$4, '2025 Overview (Rolling)'!F$11, 'Monthly Detail'!12:12) | G12: =SUMIF('Monthly Detail'!$4:$4, '2025 Overview (Rolling)'!G$11, 'Monthly Detail'!12:12) | H12: =SUMIF('Monthly Detail'!$4:$4, '2025 Overview (Rolling)'!H$11, 'Monthly Detail'!12:12) | I12: =SUMIF('Monthly Detail'!$4:$4, '2025 Overview (Rolling)'!I$11, 'Monthly Detail'!12:12) | J12: =SUMIF('Monthly Detail'!$4:$4, '2025 Overview (Rolling)'!J$11, 'Monthly Detail'!12:12) | ... N12: =SUMIF('Monthly Detail'!$4:$4, '2025 Overview (Rolling)'!N$11, 'Monthly Detail'!12:12) | P12: =SUM(C12:O12)
B13: Tips | C13: =SUMIF('Monthly Detail'!$4:$4, '2025 Overview (Rolling)'!C$11, 'Monthly Detail'!13:13) | D13: =SUMIF('Monthly Detail'!$4:$4, '2025 Overview (Rolling)'!D$11, 'Monthly Detail'!13:13) | E13: =SUMIF('Monthly Detail'!$4:$4, '2025 Overview (Rolling)'!E$11, 'Monthly Detail'!13:13) | F13: =SUMIF('Monthly Detail'!$4:$4, '2025 Overview (Rolling)'!F$11, 'Monthly Detail'!13:13) | G13: =SUMIF('Monthly Detail'!$4:$4, '2025 Overview (Rolling)'!G$11, 'Monthly Detail'!13:13) | H13: =SUMIF('Monthly Detail'!$4:$4, '2025 Overview (Rolling)'!H$11, 'Monthly Detail'!13:13) | I13: =SUMIF('Monthly Detail'!$4:$4, '2025 Overview (Rolling)'!I$11, 'Monthly Detail'!13:13) | J13: =SUMIF('Monthly Detail'!$4:$4, '2025 Overview (Rolling)'!J$11, 'Monthly Detail'!13:13) | ... N13: =SUMIF('Monthly Detail'!$4:$4, '2025 Overview (Rolling)'!N$11, 'Monthly Detail'!13:13) | P13: =+SUM(C13:N13)
B14: Total Income | C14: =SUM(C12:C13) | D14: =SUM(D12:D13) | E14: =SUM(E12:E13) | F14: =SUM(F12:F13) | G14: =SUM(G12:G13) | H14: =SUM(H12:H13) | I14: =SUM(I12:I13) | J14: =SUM(J12:J13) | ... N14: =SUM(N12:N13) | P14: =SUM(P12:P13)
B15: # of Students | C15: =SUMIF('Monthly Detail'!$4:$4, '2025 Overview (Rolling)'!C$11, 'Monthly Detail'!17:17) | D15: =SUMIF('Monthly Detail'!$4:$4, '2025 Overview (Rolling)'!D$11, 'Monthly Detail'!17:17) | E15: =SUMIF('Monthly Detail'!$4:$4, '2025 Overview (Rolling)'!E$11, 'Monthly Detail'!17:17) | F15: =SUMIF('Monthly Detail'!$4:$4, '2025 Overview (Rolling)'!F$11, 'Monthly Detail'!17:17) | G15: =SUMIF('Monthly Detail'!$4:$4, '2025 Overview (Rolling)'!G$11, 'Monthly Detail'!17:17) | H15: =SUMIF('Monthly Detail'!$4:$4, '2025 Overview (Rolling)'!H$11, 'Monthly Detail'!17:17) | I15: =SUMIF('Monthly Detail'!$4:$4, '2025 Overview (Rolling)'!I$11, 'Monthly Detail'!17:17) | J15: =SUMIF('Monthly Detail'!$4:$4, '2025 Overview (Rolling)'!J$11, 'Monthly Detail'!17:17) | ... N15: =SUMIF('Monthly Detail'!$4:$4, '2025 Overview (Rolling)'!N$11, 'Monthly Detail'!17:17)
B16: # of Sessions | C16: =SUMIF('Monthly Detail'!$4:$4, '2025 Overview (Rolling)'!C$11, 'Monthly Detail'!22:22) | D16: =SUMIF('Monthly Detail'!$4:$4, '2025 Overview (Rolling)'!D$11, 'Monthly Detail'!22:22) | E16: =SUMIF('Monthly Detail'!$4:$4, '2025 Overview (Rolling)'!E$11, 'Monthly Detail'!22:22) | F16: =SUMIF('Monthly Detail'!$4:$4, '2025 Overview (Rolling)'!F$11, 'Monthly Detail'!22:22) | G16: =SUMIF('Monthly Detail'!$4:$4, '2025 Overview (Rolling)'!G$11, 'Monthly Detail'!22:22) | H16: =SUMIF('Monthly Detail'!$4:$4, '2025 Overview (Rolling)'!H$11, 'Monthly Detail'!22:22) | I16: =SUMIF('Monthly Detail'!$4:$4, '2025 Overview (Rolling)'!I$11, 'Monthly Detail'!22:22) | J16: =SUMIF('Monthly Detail'!$4:$4, '2025 Overview (Rolling)'!J$11, 'Monthly Detail'!22:22) | ... N16: =SUMIF('Monthly Detail'!$4:$4, '2025 Overview (Rolling)'!N$11, 'Monthly Detail'!22:22)
B18: Subcontractor Expenses | C18: =SUMIF('Monthly Detail'!$4:$4, '2025 Overview (Rolling)'!C$11, 'Monthly Detail'!65:65) | D18: =SUMIF('Monthly Detail'!$4:$4, '2025 Overview (Rolling)'!D$11, 'Monthly Detail'!65:65) | E18: =SUMIF('Monthly Detail'!$4:$4, '2025 Overview (Rolling)'!E$11, 'Monthly Detail'!65:65) | F18: =SUMIF('Monthly Detail'!$4:$4, '2025 Overview (Rolling)'!F$11, 'Monthly Detail'!65:65) | G18: =SUMIF('Monthly Detail'!$4:$4, '2025 Overview (Rolling)'!G$11, 'Monthly Detail'!65:65) | H18: =SUMIF('Monthly Detail'!$4:$4, '2025 Overview (Rolling)'!H$11, 'Monthly Detail'!65:65) | I18: =SUMIF('Monthly Detail'!$4:$4, '2025 Overview (Rolling)'!I$11, 'Monthly Detail'!65:65) | J18: =SUMIF('Monthly Detail'!$4:$4, '2025 Overview (Rolling)'!J$11, 'Monthly Detail'!65:65) | ... N18: =SUMIF('Monthly Detail'!$4:$4, '2025 Overview (Rolling)'!N$11, 'Monthly Detail'!65:65) | P18: =SUM(C18:O18)
B19: Gross Margin | C19: =C14-C18 | D19: =D14-D18 | E19: =E14-E18 | F19: =F14-F18 | G19: =G14-G18 | H19: =H14-H18 | I19: =I14-I18 | J19: =J14-J18 | ... N19: =N14-N18 | P19: =P14-P18
B20: GM % | C20: =C19/C14 | D20: =D19/D14 | E20: =E19/E14 | F20: =F19/F14 | G20: =G19/G14 | H20: =H19/H14 | I20: =I19/I14 | J20: =J19/J14 | ... N20: =N19/N14 | P20: =P19/P14
B22: Sales & Marketing Expenses | C22: =SUMIF('Monthly Detail'!$4:$4, '2025 Overview (Rolling)'!C$11, 'Monthly Detail'!$72:$72) | D22: =SUMIF('Monthly Detail'!$4:$4, '2025 Overview (Rolling)'!D$11, 'Monthly Detail'!$72:$72) | E22: =SUMIF('Monthly Detail'!$4:$4, '2025 Overview (Rolling)'!E$11, 'Monthly Detail'!$72:$72) | F22: =SUMIF('Monthly Detail'!$4:$4, '2025 Overview (Rolling)'!F$11, 'Monthly Detail'!$72:$72) | G22: =SUMIF('Monthly Detail'!$4:$4, '2025 Overview (Rolling)'!G$11, 'Monthly Detail'!$72:$72) | H22: =SUMIF('Monthly Detail'!$4:$4, '2025 Overview (Rolling)'!H$11, 'Monthly Detail'!$72:$72) | I22: =SUMIF('Monthly Detail'!$4:$4, '2025 Overview (Rolling)'!I$11, 'Monthly Detail'!$72:$72) | J22: =SUMIF('Monthly Detail'!$4:$4, '2025 Overview (Rolling)'!J$11, 'Monthly Detail'!$72:$72) | ... N22: =SUMIF('Monthly Detail'!$4:$4, '2025 Overview (Rolling)'!N$11, 'Monthly Detail'!$72:$72) | P22: =SUM(C22:O22)
B23: General & Admintrative Expenses | C23: =SUMIF('Monthly Detail'!$4:$4, '2025 Overview (Rolling)'!C$11, 'Monthly Detail'!$95:$95) | D23: =SUMIF('Monthly Detail'!$4:$4, '2025 Overview (Rolling)'!D$11, 'Monthly Detail'!$95:$95) | E23: =SUMIF('Monthly Detail'!$4:$4, '2025 Overview (Rolling)'!E$11, 'Monthly Detail'!$95:$95) | F23: =SUMIF('Monthly Detail'!$4:$4, '2025 Overview (Rolling)'!F$11, 'Monthly Detail'!$95:$95) | G23: =SUMIF('Monthly Detail'!$4:$4, '2025 Overview (Rolling)'!G$11, 'Monthly Detail'!$95:$95) | H23: =SUMIF('Monthly Detail'!$4:$4, '2025 Overview (Rolling)'!H$11, 'Monthly Detail'!$95:$95) | I23: =SUMIF('Monthly Detail'!$4:$4, '2025 Overview (Rolling)'!I$11, 'Monthly Detail'!$95:$95) | J23: =SUMIF('Monthly Detail'!$4:$4, '2025 Overview (Rolling)'!J$11, 'Monthly Detail'!$95:$95) | ... N23: =SUMIF('Monthly Detail'!$4:$4, '2025 Overview (Rolling)'!N$11, 'Monthly Detail'!$95:$95) | P23: =SUM(C23:O23)
B24: Operating Expenses | C24: =SUM(C23:C23) | D24: =SUM(D22:D23) | E24: =SUM(E22:E23) | F24: =SUM(F22:F23) | G24: =SUM(G22:G23) | H24: =SUM(H22:H23) | I24: =SUM(I22:I23) | J24: =SUM(J22:J23) | K24: =SUM(K22:K23) | ... N24: =SUM(N22:N23) | P24: =SUM(P22:P23)
B26: Net Operating Income (EBITDA) | C26: =C19-C24 | D26: =D19-D24 | E26: =E19-E24 | F26: =F19-F24 | G26: =G19-G24 | H26: =H19-H24 | I26: =I19-I24 | J26: =J19-J24 | ... N26: =N19-N24 | P26: =P19-P24
B27: EBITDA % | C27: =C26/C14 | D27: =D26/D14 | E27: =E26/E14 | F27: =F26/F14 | G27: =G26/G14 | H27: =H26/H14 | I27: =I26/I14 | J27: =J26/J14 | ... N27: =N26/N14 | P27: =P26/P14
B29: Other Income / (Expense) | C29: =SUMIF('Monthly Detail'!$4:$4, '2025 Overview (Rolling)'!C$11, 'Monthly Detail'!109:109) | D29: =SUMIF('Monthly Detail'!$4:$4, '2025 Overview (Rolling)'!D$11, 'Monthly Detail'!109:109) | E29: =SUMIF('Monthly Detail'!$4:$4, '2025 Overview (Rolling)'!E$11, 'Monthly Detail'!109:109) | F29: =SUMIF('Monthly Detail'!$4:$4, '2025 Overview (Rolling)'!F$11, 'Monthly Detail'!109:109) | G29: =SUMIF('Monthly Detail'!$4:$4, '2025 Overview (Rolling)'!G$11, 'Monthly Detail'!109:109) | H29: =SUMIF('Monthly Detail'!$4:$4, '2025 Overview (Rolling)'!H$11, 'Monthly Detail'!109:109) | I29: =SUMIF('Monthly Detail'!$4:$4, '2025 Overview (Rolling)'!I$11, 'Monthly Detail'!109:109) | J29: =SUMIF('Monthly Detail'!$4:$4, '2025 Overview (Rolling)'!J$11, 'Monthly Detail'!109:109) | ... N29: =SUMIF('Monthly Detail'!$4:$4, '2025 Overview (Rolling)'!N$11, 'Monthly Detail'!109:109) | P29: =SUM(C29:O29)
B30: Net Income | C30: =C26+SUM(C29:C29) | D30: =D26+SUM(D29:D29) | E30: =E26+SUM(E29:E29) | F30: =F26+SUM(F29:F29) | G30: =G26+SUM(G29:G29) | H30: =H26+SUM(H29:H29) | I30: =I26+SUM(I29:I29) | J30: =J26+SUM(J29:J29) | ... N30: =N26+SUM(N29:N29) | P30: =P26+SUM(P29:P29)
B31: NI % | C31: =C30/C14 | D31: =D30/D14 | E31: =E30/E14 | F31: =F30/F14 | G31: =G30/G14 | H31: =H30/H14 | I31: =I30/I14 | J31: =J30/J14 | ... N31: =N30/N14 | P31: =P30/P14
B32: Cash Contributions | C32: ='Monthly Detail'!AN149-'Monthly Detail'!AM149 | D32: ='Monthly Detail'!AO149-'Monthly Detail'!AN149 | E32: ='Monthly Detail'!AP149-'Monthly Detail'!AO149 | F32: ='Monthly Detail'!AQ149-'Monthly Detail'!AP149 | G32: ='Monthly Detail'!AR149-'Monthly Detail'!AQ149 | H32: ='Monthly Detail'!AS149-'Monthly Detail'!AR149 | I32: ='Monthly Detail'!AT149-'Monthly Detail'!AS149 | J32: ='Monthly Detail'!AU149-'Monthly Detail'!AT149 | ... N32: ='Monthly Detail'!AY149-'Monthly Detail'!AX149 | P32: =+SUM(C32:N32)
B33: Owner Cash Distributions/Taxes | C33: =+SUM('Monthly Detail'!AN150,'Monthly Detail'!AN152:AN153)-SUM('Monthly Detail'!AM150,'Monthly Detail'!AM152:AM153) | D33: =+SUM('Monthly Detail'!AO150,'Monthly Detail'!AO152:AO153)-SUM('Monthly Detail'!AN150,'Monthly Detail'!AN152:AN153) | E33: =+SUM('Monthly Detail'!AP150,'Monthly Detail'!AP152:AP153)-SUM('Monthly Detail'!AO150,'Monthly Detail'!AO152:AO153) | F33: =+SUM('Monthly Detail'!AQ150,'Monthly Detail'!AQ152:AQ153)-SUM('Monthly Detail'!AP150,'Monthly Detail'!AP152:AP153) | G33: =+SUM('Monthly Detail'!AR150,'Monthly Detail'!AR152:AR153)-SUM('Monthly Detail'!AQ150,'Monthly Detail'!AQ152:AQ153) | H33: =+SUM('Monthly Detail'!AS150,'Monthly Detail'!AS152:AS153)-SUM('Monthly Detail'!AR150,'Monthly Detail'!AR152:AR153) | I33: =+SUM('Monthly Detail'!AT150,'Monthly Detail'!AT152:AT153)-SUM('Monthly Detail'!AS150,'Monthly Detail'!AS152:AS153) | J33: =+SUM('Monthly Detail'!AU150,'Monthly Detail'!AU152:AU153)-SUM('Monthly Detail'!AT150,'Monthly Detail'!AT152:AT153) | ... N33: =+SUM('Monthly Detail'!AY150,'Monthly Detail'!AY152:AY153)-SUM('Monthly Detail'!AX150,'Monthly Detail'!AX152:AX153) | P33: =+SUM(C33:N33)
B34: Accrued Tax Burden | C34: =+C30*0.3 | D34: =+C34+(D26*0.3)-SUMIF('Monthly Detail'!$4:$4, '2025 Overview (Rolling)'!D$11, 'Monthly Detail'!77:77) | E34: =+D34+(E26*0.3)-SUMIF('Monthly Detail'!$4:$4, '2025 Overview (Rolling)'!E$11, 'Monthly Detail'!77:77) | F34: =+E34+(F26*0.3)-SUMIF('Monthly Detail'!$4:$4, '2025 Overview (Rolling)'!F$11, 'Monthly Detail'!77:77) | G34: =+F34+(G26*0.3)-SUMIF('Monthly Detail'!$4:$4, '2025 Overview (Rolling)'!G$11, 'Monthly Detail'!77:77) | H34: =+G34+(H26*0.3)-SUMIF('Monthly Detail'!$4:$4, '2025 Overview (Rolling)'!H$11, 'Monthly Detail'!77:77) | I34: =+H34+(I26*0.3)-SUMIF('Monthly Detail'!$4:$4, '2025 Overview (Rolling)'!I$11, 'Monthly Detail'!77:77) | J34: =+I34+(J26*0.3)-SUMIF('Monthly Detail'!$4:$4, '2025 Overview (Rolling)'!J$11, 'Monthly Detail'!77:77) | K34: =+J34+(K26*0.3)-SUMIF('Monthly Detail'!$4:$4, '2025 Overview (Rolling)'!K$11, 'Monthly Detail'!77:77) | ... N34: =+M34+(N26*0.3)-SUMIF('Monthly Detail'!$4:$4, '2025 Overview (Rolling)'!N$11, 'Monthly Detail'!77:77) | P34: =+N34
B36: Operating Cash | C36: =SUMIF('Monthly Detail'!$4:$4, '2025 Overview (Rolling)'!C$11, 'Monthly Detail'!174:174) | D36: =SUMIF('Monthly Detail'!$4:$4, '2025 Overview (Rolling)'!D$11, 'Monthly Detail'!174:174) | E36: =SUMIF('Monthly Detail'!$4:$4, '2025 Overview (Rolling)'!E$11, 'Monthly Detail'!174:174) | F36: =SUMIF('Monthly Detail'!$4:$4, '2025 Overview (Rolling)'!F$11, 'Monthly Detail'!174:174) | G36: =SUMIF('Monthly Detail'!$4:$4, '2025 Overview (Rolling)'!G$11, 'Monthly Detail'!174:174) | H36: =SUMIF('Monthly Detail'!$4:$4, '2025 Overview (Rolling)'!H$11, 'Monthly Detail'!174:174) | I36: =SUMIF('Monthly Detail'!$4:$4, '2025 Overview (Rolling)'!I$11, 'Monthly Detail'!174:174) | J36: =SUMIF('Monthly Detail'!$4:$4, '2025 Overview (Rolling)'!J$11, 'Monthly Detail'!174:174) | ... N36: =SUMIF('Monthly Detail'!$4:$4, '2025 Overview (Rolling)'!N$11, 'Monthly Detail'!174:174)
B37: Cash Inflow (Outflow) | C37: =SUMIF('Monthly Detail'!$4:$4, '2025 Overview (Rolling)'!C$11, 'Monthly Detail'!171:171) | D37: =SUMIF('Monthly Detail'!$4:$4, '2025 Overview (Rolling)'!D$11, 'Monthly Detail'!171:171) | E37: =SUMIF('Monthly Detail'!$4:$4, '2025 Overview (Rolling)'!E$11, 'Monthly Detail'!171:171) | F37: =SUMIF('Monthly Detail'!$4:$4, '2025 Overview (Rolling)'!F$11, 'Monthly Detail'!171:171) | G37: =SUMIF('Monthly Detail'!$4:$4, '2025 Overview (Rolling)'!G$11, 'Monthly Detail'!171:171) | H37: =SUMIF('Monthly Detail'!$4:$4, '2025 Overview (Rolling)'!H$11, 'Monthly Detail'!171:171) | I37: =SUMIF('Monthly Detail'!$4:$4, '2025 Overview (Rolling)'!I$11, 'Monthly Detail'!171:171) | J37: =SUMIF('Monthly Detail'!$4:$4, '2025 Overview (Rolling)'!J$11, 'Monthly Detail'!171:171) | ... N37: =SUMIF('Monthly Detail'!$4:$4, '2025 Overview (Rolling)'!N$11, 'Monthly Detail'!171:171)

Sheet 2025 Overview (Budget)
B8: 2025 Overview (Annual Operating Plan)
C10: =TEXT('Monthly Detail'!D4,"mmmm") | D10: =TEXT('Monthly Detail'!E4,"mmmm") | E10: =TEXT('Monthly Detail'!F4,"mmmm") | F10: =TEXT('Monthly Detail'!G4,"mmmm") | G10: =TEXT('Monthly Detail'!H4,"mmmm") | H10: =TEXT('Monthly Detail'!I4,"mmmm") | I10: =TEXT('Monthly Detail'!J4,"mmmm") | J10: =TEXT('Monthly Detail'!K4,"mmmm") | ... N10: =TEXT('Monthly Detail'!O4,"mmmm") | P10: Total
C11: 45688 | D11: 45716 | E11: 45747 | F11: 45777 | G11: 45808 | H11: 45838 | I11: 45869 | J11: 45900 | K11: 45930 | L11: 45961 | M11: 45991 | N11: 46022 | O11: 45322
B12: Service Income | C12: =+'2025 Overview (Rolling)'!C12 | D12: =+'2025 Overview (Rolling)'!D12 | E12: =+'2025 Overview (Rolling)'!E12 | F12: =+'2025 Overview (Rolling)'!F12 | G12: =+'2025 Overview (Rolling)'!G12 | H12: =+'2025 Overview (Rolling)'!H12 | I12: =+'2025 Overview (Rolling)'!I12 | J12: =+'2025 Overview (Rolling)'!J12 | ... L12: =+'2025 Overview (Rolling)'!L12 | M12: =+'2025 AOP'!M12 | N12: =+'2025 AOP'!N12 | P12: =SUM(C12:O12)
B13: Tips | C13: =+'2025 Overview (Rolling)'!C13 | D13: =+'2025 Overview (Rolling)'!D13 | E13: =+'2025 Overview (Rolling)'!E13 | F13: =+'2025 Overview (Rolling)'!F13 | G13: =+'2025 Overview (Rolling)'!G13 | H13: =+'2025 Overview (Rolling)'!H13 | I13: =+'2025 Overview (Rolling)'!I13 | J13: =+'2025 Overview (Rolling)'!J13 | ... L13: =+'2025 Overview (Rolling)'!L13 | M13: =+'2025 AOP'!M13 | N13: =+'2025 AOP'!N13 | P13: =+SUM(C13:N13)
B14: Total Income | C14: =+'2025 Overview (Rolling)'!C14 | D14: =+'2025 Overview (Rolling)'!D14 | E14: =+'2025 Overview (Rolling)'!E14 | F14: =+'2025 Overview (Rolling)'!F14 | G14: =+'2025 Overview (Rolling)'!G14 | H14: =+'2025 Overview (Rolling)'!H14 | I14: =+'2025 Overview (Rolling)'!I14 | J14: =+'2025 Overview (Rolling)'!J14 | ... L14: =+'2025 Overview (Rolling)'!L14 | M14: =SUM(M12:M13) | N14: =SUM(N12:N13) | P14: =SUM(P12:P13)
B15: # of Students | C15: =+'2025 Overview (Rolling)'!C15 | D15: =+'2025 Overview (Rolling)'!D15 | E15: =+'2025 Overview (Rolling)'!E15 | F15: =+'2025 Overview (Rolling)'!F15 | G15: =+'2025 Overview (Rolling)'!G15 | H15: =+'2025 Overview (Rolling)'!H15 | I15: =+'2025 Overview (Rolling)'!I15 | J15: =+'2025 Overview (Rolling)'!J15 | ... L15: =+'2025 Overview (Rolling)'!L15 | M15: =+'2025 AOP'!M15 | N15: =+'2025 AOP'!N15
B17: Subcontractor Expenses | C17: =+'2025 Overview (Rolling)'!C18 | D17: =+'2025 Overview (Rolling)'!D18 | E17: =+'2025 Overview (Rolling)'!E18 | F17: =+'2025 Overview (Rolling)'!F18 | G17: =+'2025 Overview (Rolling)'!G18 | H17: =+'2025 Overview (Rolling)'!H18 | I17: =+'2025 Overview (Rolling)'!I18 | J17: =+'2025 Overview (Rolling)'!J18 | ... L17: =+'2025 Overview (Rolling)'!L18 | M17: =+'2025 AOP'!M18 | N17: =+'2025 AOP'!N18 | P17: =SUM(C17:O17)
B18: Gross Margin | C18: =+'2025 Overview (Rolling)'!C19 | D18: =+'2025 Overview (Rolling)'!D19 | E18: =+'2025 Overview (Rolling)'!E19 | F18: =+'2025 Overview (Rolling)'!F19 | G18: =+'2025 Overview (Rolling)'!G19 | H18: =+'2025 Overview (Rolling)'!H19 | I18: =+'2025 Overview (Rolling)'!I19 | J18: =+'2025 Overview (Rolling)'!J19 | ... L18: =+'2025 Overview (Rolling)'!L19 | M18: =M14-M17 | N18: =N14-N17 | P18: =P14-P17
B19: GM % | C19: =+'2025 Overview (Rolling)'!C20 | D19: =+'2025 Overview (Rolling)'!D20 | E19: =+'2025 Overview (Rolling)'!E20 | F19: =+'2025 Overview (Rolling)'!F20 | G19: =+'2025 Overview (Rolling)'!G20 | H19: =+'2025 Overview (Rolling)'!H20 | I19: =+'2025 Overview (Rolling)'!I20 | J19: =+'2025 Overview (Rolling)'!J20 | ... L19: =+'2025 Overview (Rolling)'!L20 | M19: =M18/M14 | N19: =N18/N14 | P19: =P18/P14
B21: Sales & Marketing Expenses | C21: =+'2025 Overview (Rolling)'!C22 | D21: =+'2025 Overview (Rolling)'!D22 | E21: =+'2025 Overview (Rolling)'!E22 | F21: =+'2025 Overview (Rolling)'!F22 | G21: =+'2025 Overview (Rolling)'!G22 | H21: =+'2025 Overview (Rolling)'!H22 | I21: =+'2025 Overview (Rolling)'!I22 | J21: =+'2025 Overview (Rolling)'!J22 | ... L21: =+'2025 Overview (Rolling)'!L22 | M21: =+'2025 AOP'!M22 | N21: =+'2025 AOP'!N22 | P21: =SUM(C21:O21)
B22: General & Admintrative Expenses | C22: =+'2025 Overview (Rolling)'!C23 | D22: =+'2025 Overview (Rolling)'!D23 | E22: =+'2025 Overview (Rolling)'!E23 | F22: =+'2025 Overview (Rolling)'!F23 | G22: =+'2025 Overview (Rolling)'!G23 | H22: =+'2025 Overview (Rolling)'!H23 | I22: =+'2025 Overview (Rolling)'!I23 | J22: =+'2025 Overview (Rolling)'!J23 | ... L22: =+'2025 Overview (Rolling)'!L23 | M22: =+'2025 AOP'!M23 | N22: =+'2025 AOP'!N23 | P22: =SUM(C22:O22)
B23: Operating Expenses | C23: =+'2025 Overview (Rolling)'!C24 | D23: =+'2025 Overview (Rolling)'!D24 | E23: =+'2025 Overview (Rolling)'!E24 | F23: =+'2025 Overview (Rolling)'!F24 | G23: =+'2025 Overview (Rolling)'!G24 | H23: =+'2025 Overview (Rolling)'!H24 | I23: =+'2025 Overview (Rolling)'!I24 | J23: =+'2025 Overview (Rolling)'!J24 | ... L23: =+'2025 Overview (Rolling)'!L24 | M23: =SUM(M21:M22) | N23: =SUM(N21:N22) | P23: =SUM(P21:P22)
B25: Net Operating Income (EBITDA) | C25: =+'2025 Overview (Rolling)'!C26 | D25: =+'2025 Overview (Rolling)'!D26 | E25: =+'2025 Overview (Rolling)'!E26 | F25: =+'2025 Overview (Rolling)'!F26 | G25: =+'2025 Overview (Rolling)'!G26 | H25: =+'2025 Overview (Rolling)'!H26 | I25: =+'2025 Overview (Rolling)'!I26 | J25: =+'2025 Overview (Rolling)'!J26 | ... L25: =+'2025 Overview (Rolling)'!L26 | M25: =M18-M23 | N25: =N18-N23 | P25: =P18-P23
B26: EBITDA % | C26: =+'2025 Overview (Rolling)'!C27 | D26: =+'2025 Overview (Rolling)'!D27 | E26: =+'2025 Overview (Rolling)'!E27 | F26: =+'2025 Overview (Rolling)'!F27 | G26: =+'2025 Overview (Rolling)'!G27 | H26: =+'2025 Overview (Rolling)'!H27 | I26: =+'2025 Overview (Rolling)'!I27 | J26: =+'2025 Overview (Rolling)'!J27 | ... L26: =+'2025 Overview (Rolling)'!L27 | M26: =M25/M14 | N26: =N25/N14 | P26: =P25/P14
B28: Other Income / (Expense) | C28: =+'2025 Overview (Rolling)'!C29 | D28: =+'2025 Overview (Rolling)'!D29 | E28: =+'2025 Overview (Rolling)'!E29 | F28: =+'2025 Overview (Rolling)'!F29 | G28: =+'2025 Overview (Rolling)'!G29 | H28: =+'2025 Overview (Rolling)'!H29 | I28: =+'2025 Overview (Rolling)'!I29 | J28: =+'2025 Overview (Rolling)'!J29 | ... L28: =+'2025 Overview (Rolling)'!L29 | M28: =+'2025 AOP'!M29 | N28: =+'2025 AOP'!N29 | P28: =SUM(C28:O28)
B29: Net Income | C29: =+'2025 Overview (Rolling)'!C30 | D29: =+'2025 Overview (Rolling)'!D30 | E29: =+'2025 Overview (Rolling)'!E30 | F29: =+'2025 Overview (Rolling)'!F30 | G29: =+'2025 Overview (Rolling)'!G30 | H29: =+'2025 Overview (Rolling)'!H30 | I29: =+'2025 Overview (Rolling)'!I30 | J29: =+'2025 Overview (Rolling)'!J30 | ... L29: =+'2025 Overview (Rolling)'!L30 | M29: =M25+SUM(M28:M28) | N29: =N25+SUM(N28:N28) | P29: =P25+SUM(P28:P28)
B30: NI % | C30: =+'2025 Overview (Rolling)'!C31 | D30: =+'2025 Overview (Rolling)'!D31 | E30: =+'2025 Overview (Rolling)'!E31 | F30: =+'2025 Overview (Rolling)'!F31 | G30: =+'2025 Overview (Rolling)'!G31 | H30: =+'2025 Overview (Rolling)'!H31 | I30: =+'2025 Overview (Rolling)'!I31 | J30: =+'2025 Overview (Rolling)'!J31 | ... L30: =+'2025 Overview (Rolling)'!L31 | M30: =M29/M14 | N30: =N29/N14 | P30: =P29/P14
B32: Operating Cash | C32: =+'2025 Overview (Rolling)'!C36 | D32: =+'2025 Overview (Rolling)'!D36 | E32: =+'2025 Overview (Rolling)'!E36 | F32: =+'2025 Overview (Rolling)'!F36 | G32: =+'2025 Overview (Rolling)'!G36 | H32: =+'2025 Overview (Rolling)'!H36 | I32: =+'2025 Overview (Rolling)'!I36 | J32: =+'2025 Overview (Rolling)'!J36 | ... L32: =+'2025 Overview (Rolling)'!L36 | M32: =+'2024 AOP'!M31 | N32: =+'2024 AOP'!N31
B33: Cash Inflow (Outflow) | C33: =+'2025 Overview (Rolling)'!C37 | D33: =+'2025 Overview (Rolling)'!D37 | E33: =+'2025 Overview (Rolling)'!E37 | F33: =+'2025 Overview (Rolling)'!F37 | G33: =+'2025 Overview (Rolling)'!G37 | H33: =+'2025 Overview (Rolling)'!H37 | I33: =+'2025 Overview (Rolling)'!I37 | J33: =+'2025 Overview (Rolling)'!J37 | ... L33: =+'2025 Overview (Rolling)'!L37 | M33: =+'2024 AOP'!M32 | N33: =+'2024 AOP'!N32

Sheet 2024 Overview (Rolling)
B8: 2024 Overview (Rolling Forecast)
C10: =TEXT('Monthly Detail'!D4,"mmmm") | D10: =TEXT('Monthly Detail'!E4,"mmmm") | E10: =TEXT('Monthly Detail'!F4,"mmmm") | F10: =TEXT('Monthly Detail'!G4,"mmmm") | G10: =TEXT('Monthly Detail'!H4,"mmmm") | H10: =TEXT('Monthly Detail'!I4,"mmmm") | I10: =TEXT('Monthly Detail'!J4,"mmmm") | J10: =TEXT('Monthly Detail'!K4,"mmmm") | ... N10: =TEXT('Monthly Detail'!O4,"mmmm") | P10: Total
C11: 45322 | D11: 45351 | E11: 45382 | F11: 45412 | G11: 45443 | H11: 45473 | I11: 45504 | J11: 45535 | K11: 45565 | L11: 45596 | M11: 45626 | N11: 45657 | O11: 45322
B12: Service Income | C12: =SUMIF('Monthly Detail'!$4:$4, '2024 Overview (Rolling)'!C$11, 'Monthly Detail'!12:12) | D12: =SUMIF('Monthly Detail'!$4:$4, '2024 Overview (Rolling)'!D$11, 'Monthly Detail'!12:12) | E12: =SUMIF('Monthly Detail'!$4:$4, '2024 Overview (Rolling)'!E$11, 'Monthly Detail'!12:12) | F12: =SUMIF('Monthly Detail'!$4:$4, '2024 Overview (Rolling)'!F$11, 'Monthly Detail'!12:12) | G12: =SUMIF('Monthly Detail'!$4:$4, '2024 Overview (Rolling)'!G$11, 'Monthly Detail'!12:12) | H12: =SUMIF('Monthly Detail'!$4:$4, '2024 Overview (Rolling)'!H$11, 'Monthly Detail'!12:12) | I12: =SUMIF('Monthly Detail'!$4:$4, '2024 Overview (Rolling)'!I$11, 'Monthly Detail'!12:12) | J12: =SUMIF('Monthly Detail'!$4:$4, '2024 Overview (Rolling)'!J$11, 'Monthly Detail'!12:12) | ... N12: =SUMIF('Monthly Detail'!$4:$4, '2024 Overview (Rolling)'!N$11, 'Monthly Detail'!12:12) | P12: =SUM(C12:O12)
B13: Tips | C13: =SUMIF('Monthly Detail'!$4:$4, '2024 Overview (Rolling)'!C$11, 'Monthly Detail'!13:13) | D13: =SUMIF('Monthly Detail'!$4:$4, '2024 Overview (Rolling)'!D$11, 'Monthly Detail'!13:13) | E13: =SUMIF('Monthly Detail'!$4:$4, '2024 Overview (Rolling)'!E$11, 'Monthly Detail'!13:13) | F13: =SUMIF('Monthly Detail'!$4:$4, '2024 Overview (Rolling)'!F$11, 'Monthly Detail'!13:13) | G13: =SUMIF('Monthly Detail'!$4:$4, '2024 Overview (Rolling)'!G$11, 'Monthly Detail'!13:13) | H13: =SUMIF('Monthly Detail'!$4:$4, '2024 Overview (Rolling)'!H$11, 'Monthly Detail'!13:13) | I13: =SUMIF('Monthly Detail'!$4:$4, '2024 Overview (Rolling)'!I$11, 'Monthly Detail'!13:13) | J13: =SUMIF('Monthly Detail'!$4:$4, '2024 Overview (Rolling)'!J$11, 'Monthly Detail'!13:13) | ... N13: =SUMIF('Monthly Detail'!$4:$4, '2024 Overview (Rolling)'!N$11, 'Monthly Detail'!13:13) | P13: =+SUM(C13:N13)
B14: Total Income | C14: =SUM(C12:C13) | D14: =SUM(D12:D13) | E14: =SUM(E12:E13) | F14: =SUM(F12:F13) | G14: =SUM(G12:G13) | H14: =SUM(H12:H13) | I14: =SUM(I12:I13) | J14: =SUM(J12:J13) | ... N14: =SUM(N12:N13) | P14: =SUM(P12:P13)
B15: # of Students | C15: =+'Monthly Detail'!AB17 | D15: =+'Monthly Detail'!AC17 | E15: =+'Monthly Detail'!AD17 | F15: =+'Monthly Detail'!AE17 | G15: =+'Monthly Detail'!AF17 | H15: =+'Monthly Detail'!AG17 | I15: =+'Monthly Detail'!AH17 | J15: =+'Monthly Detail'!AI17 | ... N15: =+'Monthly Detail'!AM17
B16: # of Sessions | C16: =+'Monthly Detail'!AB22 | D16: =+'Monthly Detail'!AC22 | E16: =+'Monthly Detail'!AD22 | F16: =+'Monthly Detail'!AE22 | G16: =+'Monthly Detail'!AF22 | H16: =+'Monthly Detail'!AG22 | I16: =+'Monthly Detail'!AH22 | J16: =+'Monthly Detail'!AI22 | ... N16: =+'Monthly Detail'!AM22
B18: Subcontractor Expenses | C18: =SUMIF('Monthly Detail'!$4:$4, '2025 Overview (Budget)'!C$11, 'Monthly Detail'!65:65) | D18: =SUMIF('Monthly Detail'!$4:$4, '2025 Overview (Budget)'!D$11, 'Monthly Detail'!65:65) | E18: =SUMIF('Monthly Detail'!$4:$4, '2025 Overview (Budget)'!E$11, 'Monthly Detail'!65:65) | F18: =SUMIF('Monthly Detail'!$4:$4, '2025 Overview (Budget)'!F$11, 'Monthly Detail'!65:65) | G18: =SUMIF('Monthly Detail'!$4:$4, '2025 Overview (Budget)'!G$11, 'Monthly Detail'!65:65) | H18: =SUMIF('Monthly Detail'!$4:$4, '2025 Overview (Budget)'!H$11, 'Monthly Detail'!65:65) | I18: =SUMIF('Monthly Detail'!$4:$4, '2025 Overview (Budget)'!I$11, 'Monthly Detail'!65:65) | J18: =SUMIF('Monthly Detail'!$4:$4, '2025 Overview (Budget)'!J$11, 'Monthly Detail'!65:65) | ... N18: =SUMIF('Monthly Detail'!$4:$4, '2025 Overview (Budget)'!N$11, 'Monthly Detail'!65:65) | P18: =SUM(C18:O18)
B19: Gross Margin | C19: =C14-C18 | D19: =D14-D18 | E19: =E14-E18 | F19: =F14-F18 | G19: =G14-G18 | H19: =H14-H18 | I19: =I14-I18 | J19: =J14-J18 | ... N19: =N14-N18 | P19: =P14-P18
B20: GM % | C20: =C19/C14 | D20: =D19/D14 | E20: =E19/E14 | F20: =F19/F14 | G20: =G19/G14 | H20: =H19/H14 | I20: =I19/I14 | J20: =J19/J14 | ... N20: =N19/N14 | P20: =P19/P14
B22: Sales & Marketing Expenses | C22: =SUMIF('Monthly Detail'!$4:$4, '2024 Overview (Rolling)'!C$11, 'Monthly Detail'!$72:$72) | D22: =SUMIF('Monthly Detail'!$4:$4, '2024 Overview (Rolling)'!D$11, 'Monthly Detail'!$72:$72) | E22: =SUMIF('Monthly Detail'!$4:$4, '2024 Overview (Rolling)'!E$11, 'Monthly Detail'!$72:$72) | F22: =SUMIF('Monthly Detail'!$4:$4, '2024 Overview (Rolling)'!F$11, 'Monthly Detail'!$72:$72) | G22: =SUMIF('Monthly Detail'!$4:$4, '2024 Overview (Rolling)'!G$11, 'Monthly Detail'!$72:$72) | H22: =SUMIF('Monthly Detail'!$4:$4, '2024 Overview (Rolling)'!H$11, 'Monthly Detail'!$72:$72) | I22: =SUMIF('Monthly Detail'!$4:$4, '2024 Overview (Rolling)'!I$11, 'Monthly Detail'!$72:$72) | J22: =SUMIF('Monthly Detail'!$4:$4, '2024 Overview (Rolling)'!J$11, 'Monthly Detail'!$72:$72) | ... N22: =SUMIF('Monthly Detail'!$4:$4, '2024 Overview (Rolling)'!N$11, 'Monthly Detail'!$72:$72) | P22: =SUM(C22:O22)
B23: General & Admintrative Expenses | C23: =SUMIF('Monthly Detail'!$4:$4, '2024 Overview (Rolling)'!C$11, 'Monthly Detail'!$95:$95) | D23: =SUMIF('Monthly Detail'!$4:$4, '2024 Overview (Rolling)'!D$11, 'Monthly Detail'!$95:$95) | E23: =SUMIF('Monthly Detail'!$4:$4, '2024 Overview (Rolling)'!E$11, 'Monthly Detail'!$95:$95) | F23: =SUMIF('Monthly Detail'!$4:$4, '2024 Overview (Rolling)'!F$11, 'Monthly Detail'!$95:$95) | G23: =SUMIF('Monthly Detail'!$4:$4, '2024 Overview (Rolling)'!G$11, 'Monthly Detail'!$95:$95) | H23: =SUMIF('Monthly Detail'!$4:$4, '2024 Overview (Rolling)'!H$11, 'Monthly Detail'!$95:$95) | I23: =SUMIF('Monthly Detail'!$4:$4, '2024 Overview (Rolling)'!I$11, 'Monthly Detail'!$95:$95) | J23: =SUMIF('Monthly Detail'!$4:$4, '2024 Overview (Rolling)'!J$11, 'Monthly Detail'!$95:$95) | ... N23: =SUMIF('Monthly Detail'!$4:$4, '2024 Overview (Rolling)'!N$11, 'Monthly Detail'!$95:$95) | P23: =SUM(C23:O23)
B24: Operating Expenses | C24: =SUM(C23:C23) | D24: =SUM(D22:D23) | E24: =SUM(E22:E23) | F24: =SUM(F22:F23) | G24: =SUM(G22:G23) | H24: =SUM(H22:H23) | I24: =SUM(I22:I23) | J24: =SUM(J22:J23) | K24: =SUM(K22:K23) | ... N24: =SUM(N22:N23) | P24: =SUM(P22:P23)
B26: Net Operating Income (EBITDA) | C26: =C19-C24 | D26: =D19-D24 | E26: =E19-E24 | F26: =F19-F24 | G26: =G19-G24 | H26: =H19-H24 | I26: =I19-I24 | J26: =J19-J24 | ... N26: =N19-N24 | P26: =P19-P24
B27: EBITDA % | C27: =C26/C14 | D27: =D26/D14 | E27: =E26/E14 | F27: =F26/F14 | G27: =G26/G14 | H27: =H26/H14 | I27: =I26/I14 | J27: =J26/J14 | ... N27: =N26/N14 | P27: =P26/P14
B29: Other Income / (Expense) | C29: =SUMIF('Monthly Detail'!$4:$4, '2024 Overview (Rolling)'!C$11, 'Monthly Detail'!109:109) | D29: =SUMIF('Monthly Detail'!$4:$4, '2024 Overview (Rolling)'!D$11, 'Monthly Detail'!109:109) | E29: =SUMIF('Monthly Detail'!$4:$4, '2024 Overview (Rolling)'!E$11, 'Monthly Detail'!109:109) | F29: =SUMIF('Monthly Detail'!$4:$4, '2024 Overview (Rolling)'!F$11, 'Monthly Detail'!109:109) | G29: =SUMIF('Monthly Detail'!$4:$4, '2024 Overview (Rolling)'!G$11, 'Monthly Detail'!109:109) | H29: =SUMIF('Monthly Detail'!$4:$4, '2024 Overview (Rolling)'!H$11, 'Monthly Detail'!109:109) | I29: =SUMIF('Monthly Detail'!$4:$4, '2024 Overview (Rolling)'!I$11, 'Monthly Detail'!109:109) | J29: =SUMIF('Monthly Detail'!$4:$4, '2024 Overview (Rolling)'!J$11, 'Monthly Detail'!109:109) | ... N29: =SUMIF('Monthly Detail'!$4:$4, '2024 Overview (Rolling)'!N$11, 'Monthly Detail'!109:109) | P29: =SUM(C29:O29)
B30: Net Income | C30: =C26+SUM(C29:C29) | D30: =D26+SUM(D29:D29) | E30: =E26+SUM(E29:E29) | F30: =F26+SUM(F29:F29) | G30: =G26+SUM(G29:G29) | H30: =H26+SUM(H29:H29) | I30: =I26+SUM(I29:I29) | J30: =J26+SUM(J29:J29) | ... N30: =N26+SUM(N29:N29) | P30: =P26+SUM(P29:P29)
B31: NI % | C31: =C30/C14 | D31: =D30/D14 | E31: =E30/E14 | F31: =F30/F14 | G31: =G30/G14 | H31: =H30/H14 | I31: =I30/I14 | J31: =J30/J14 | ... N31: =N30/N14 | P31: =P30/P14
B32: Cash Contributions | C32: =+'Monthly Detail'!AB149-'Monthly Detail'!AA149 | D32: =+'Monthly Detail'!AC149-'Monthly Detail'!AB149 | E32: =+'Monthly Detail'!AD149-'Monthly Detail'!AC149 | F32: =+'Monthly Detail'!AE149-'Monthly Detail'!AD149 | G32: =+'Monthly Detail'!AF149-'Monthly Detail'!AE149 | H32: =+'Monthly Detail'!AG149-'Monthly Detail'!AF149 | I32: =+'Monthly Detail'!AH149-'Monthly Detail'!AG149 | J32: =+'Monthly Detail'!AI149-'Monthly Detail'!AH149 | ... N32: =+'Monthly Detail'!AM149-'Monthly Detail'!AL149 | P32: =+SUM(C32:N32)
B33: Owner Cash Distributions | C33: =+'Monthly Detail'!AB150-'Monthly Detail'!AA150 | D33: =+'Monthly Detail'!AC150-'Monthly Detail'!AB150 | E33: =+'Monthly Detail'!AD150-'Monthly Detail'!AC150 | F33: =+'Monthly Detail'!AE150-'Monthly Detail'!AD150 | G33: =+'Monthly Detail'!AF150-'Monthly Detail'!AE150 | H33: =+'Monthly Detail'!AG150-'Monthly Detail'!AF150 | I33: =+'Monthly Detail'!AH150-'Monthly Detail'!AG150 | J33: =+'Monthly Detail'!AI150-'Monthly Detail'!AH150 | ... N33: =+'Monthly Detail'!AM150-'Monthly Detail'!AL150 | P33: =+SUM(C33:N33)
B34: Accrued Tax Burden | C34: =+(C30)*0.153 | D34: =+C34+((D26)*0.153) | E34: =+D34+((E26)*0.153) | F34: =+E34+((F26)*0.153) | G34: =+F34+((G26)*0.153) | H34: =+G34+((H26)*0.153) | I34: =+H34+((I26)*0.153) | J34: =+I34+((J26)*0.153) | K34: =+J34+((K26)*0.153) | ... N34: =+M34+((N26)*0.153) | P34: =+N34
B36: Operating Cash | C36: =SUMIF('Monthly Detail'!$4:$4, '2024 Overview (Rolling)'!C$11, 'Monthly Detail'!174:174) | D36: =SUMIF('Monthly Detail'!$4:$4, '2024 Overview (Rolling)'!D$11, 'Monthly Detail'!174:174) | E36: =SUMIF('Monthly Detail'!$4:$4, '2024 Overview (Rolling)'!E$11, 'Monthly Detail'!174:174) | F36: =SUMIF('Monthly Detail'!$4:$4, '2024 Overview (Rolling)'!F$11, 'Monthly Detail'!174:174) | G36: =SUMIF('Monthly Detail'!$4:$4, '2024 Overview (Rolling)'!G$11, 'Monthly Detail'!174:174) | H36: =SUMIF('Monthly Detail'!$4:$4, '2024 Overview (Rolling)'!H$11, 'Monthly Detail'!174:174) | I36: =SUMIF('Monthly Detail'!$4:$4, '2024 Overview (Rolling)'!I$11, 'Monthly Detail'!174:174) | J36: =SUMIF('Monthly Detail'!$4:$4, '2024 Overview (Rolling)'!J$11, 'Monthly Detail'!174:174) | ... N36: =SUMIF('Monthly Detail'!$4:$4, '2024 Overview (Rolling)'!N$11, 'Monthly Detail'!174:174)
B37: Cash Inflow (Outflow) | C37: =SUMIF('Monthly Detail'!$4:$4, '2024 Overview (Rolling)'!C$11, 'Monthly Detail'!171:171) | D37: =SUMIF('Monthly Detail'!$4:$4, '2024 Overview (Rolling)'!D$11, 'Monthly Detail'!171:171) | E37: =SUMIF('Monthly Detail'!$4:$4, '2024 Overview (Rolling)'!E$11, 'Monthly Detail'!171:171) | F37: =SUMIF('Monthly Detail'!$4:$4, '2024 Overview (Rolling)'!F$11, 'Monthly Detail'!171:171) | G37: =SUMIF('Monthly Detail'!$4:$4, '2024 Overview (Rolling)'!G$11, 'Monthly Detail'!171:171) | H37: =SUMIF('Monthly Detail'!$4:$4, '2024 Overview (Rolling)'!H$11, 'Monthly Detail'!171:171) | I37: =SUMIF('Monthly Detail'!$4:$4, '2024 Overview (Rolling)'!I$11, 'Monthly Detail'!171:171) | J37: =SUMIF('Monthly Detail'!$4:$4, '2024 Overview (Rolling)'!J$11, 'Monthly Detail'!171:171) | ... N37: =SUMIF('Monthly Detail'!$4:$4, '2024 Overview (Rolling)'!N$11, 'Monthly Detail'!171:171)

Sheet 2024 AOP
C10: January | D10: February | E10: March | F10: April | G10: May | H10: June | I10: July | J10: August | K10: September | L10: October | M10: November | N10: December | P10: Total
C11: 45322 | D11: 45351 | E11: 45382 | F11: 45412 | G11: 45443 | H11: 45473 | I11: 45504 | J11: 45535 | K11: 45565 | L11: 45596 | M11: 45626 | N11: 45657 | O11: 45322
B12: Service Income | C12: 3016.9792 | D12: 4844.1612 | E12: 3944.6332 | F12: 5914.9554 | G12: 10182.292 | H12: 6680.8712 | I12: 9818.9732 | J12: 9199.4885 | K12: 12430.846 | L12: 10145.197 | M12: 5993.1641 | N12: 4062.5 | P12: 86234.061
B13: Tips | C13: 49.5 | D13: 49.5 | E13: 49.5 | F13: 49.5 | G13: 49.5 | H13: 49.5 | I13: 49.5 | J13: 49.5 | K13: 49.5 | L13: 49.5 | M13: 49.5 | N13: 49.5 | P13: =+SUM(C13:N13)
B14: Total Income | C14: 3066.4792 | D14: 4893.6612 | E14: 3994.1332 | F14: 5964.4554 | G14: 10231.792 | H14: 6730.3712 | I14: 9868.4732 | J14: 9248.9885 | K14: 12480.346 | L14: 10194.697 | M14: 6042.6641 | N14: 4112 | P14: 86828.061
B15: # of Students | C15: 21 | D15: 33 | E15: 35 | F15: 33 | G15: 34 | H15: 34 | I15: 31 | J15: 32 | K15: 43 | L15: 38 | M15: 38 | N15: 38
B16: # of Sessions | C16: 28 | D16: 44.957723 | E16: 36.609377 | F16: 54.895556 | G16: 94.499879 | H16: 62.003873 | I16: 91.127991 | J16: 85.378673 | K16: 115.36828 | L16: 94.155612 | M16: 55.621396 | N16: 37.703277
B18: Gross Margin | C18: 3066.4792 | D18: 4893.6612 | E18: 3994.1332 | F18: 5964.4554 | G18: 10231.792 | H18: 6730.3712 | I18: 9868.4732 | J18: 9248.9885 | K18: 12480.346 | L18: 10194.697 | M18: 6042.6641 | N18: 4112 | P18: 86234.061
B19: GM % | C19: 1 | D19: 1 | E19: 1 | F19: 1 | G19: 1 | H19: 1 | I19: 1 | J19: 1 | K19: 1 | L19: 1 | M19: 1 | N19: 1 | P19: 1
B21: General & Admintrative Expenses | C21: 810.76067 | D21: 810.76067 | E21: 810.76067 | F21: 960.76067 | G21: 810.76067 | H21: 810.76067 | I21: 960.76067 | J21: 810.76067 | K21: 1846.502 | L21: 960.76067 | M21: 810.76067 | N21: 810.76067 | P21: 11214.869
B22: Operating Expenses | C22: 810.76067 | D22: 810.76067 | E22: 810.76067 | F22: 960.76067 | G22: 810.76067 | H22: 810.76067 | I22: 960.76067 | J22: 810.76067 | K22: 1846.502 | L22: 960.76067 | M22: 810.76067 | N22: 810.76067 | P22: 11214.869
B24: Net Operating Income (EBITDA) | C24: 2255.7185 | D24: 4082.9005 | E24: 3183.3725 | F24: 5003.6947 | G24: 9421.031 | H24: 5919.6105 | I24: 8907.7125 | J24: 8438.2278 | K24: 10633.844 | L24: 9233.9364 | M24: 5231.9034 | N24: 3301.2393 | P24: 75019.191
B25: EBITDA % | C25: 0.73560536 | D25: 0.83432432 | E25: 0.79701211 | F25: 0.83891896 | G25: 0.92076064 | H25: 0.87953701 | I25: 0.90264343 | J25: 0.91234061 | K25: 0.85204721 | L25: 0.90575878 | M25: 0.86582728 | N25: 0.80283058 | P25: 0.86994849
B27: Other Income / (Expense) | C27: 0 | D27: 0 | E27: 0 | F27: 0 | G27: 0 | H27: 0 | I27: 0 | J27: 0 | K27: 0 | L27: 0 | M27: 0 | N27: 0 | P27: 0
B28: Net Income | C28: 2255.7185 | D28: 4082.9005 | E28: 3183.3725 | F28: 5003.6947 | G28: 9421.031 | H28: 5919.6105 | I28: 8907.7125 | J28: 8438.2278 | K28: 10633.844 | L28: 9233.9364 | M28: 5231.9034 | N28: 3301.2393 | P28: 75019.191
B29: NI % | C29: 0.73560536 | D29: 0.83432432 | E29: 0.79701211 | F29: 0.83891896 | G29: 0.92076064 | H29: 0.87953701 | I29: 0.90264343 | J29: 0.91234061 | K29: 0.85204721 | L29: 0.90575878 | M29: 0.86582728 | N29: 0.80283058 | P29: 0.86994849
B31: Operating Cash | C31: 583.93524 | D31: 3316.6412 | E31: 5497.8005 | F31: 8902.7836 | G31: 15222.718 | H31: 20447.59 | I31: 26375.122 | J31: 28510.127 | K31: 33013.08 | L31: 34722.534 | M31: 36536.59 | N31: 38730.025
B32: Cash Inflow (Outflow) | C32: -413.08476 | D32: 2732.706 | E32: 2181.1593 | F32: 3404.9831 | G32: 6319.9345 | H32: 5224.8719 | I32: 5927.5321 | J32: 2135.0053 | K32: 4502.9521 | L32: 1709.4542 | M32: 1814.0563 | N32: 2193.4353

Sheet Quarterly Overview
C9: 45382 | D9: 45473 | F9: 45565 | H9: 45657
C10: Q1 2025 | D10: Q2 2025 | E10: Variance | F10: Q3 2025 | G10: Variance | H10: Q4 2025 | I10: Variance | K10: Total
C11: =+C10 | D11: =+D10 | F11: =+F10 | H11: =+H10 | J11: 45322
B12: Service Income | C12: =SUMIF('Monthly Detail'!$3:$3, 'Quarterly Overview'!C$11, 'Monthly Detail'!12:12) | D12: =SUMIF('Monthly Detail'!$3:$3, 'Quarterly Overview'!D$11, 'Monthly Detail'!12:12) | E12: =+D12-C12 | F12: =SUMIF('Monthly Detail'!$3:$3, 'Quarterly Overview'!F$11, 'Monthly Detail'!12:12) | G12: =+F12-D12 | H12: =SUMIF('Monthly Detail'!$3:$3, 'Quarterly Overview'!H$11, 'Monthly Detail'!12:12) | I12: =+H12-F12 | K12: =SUM(C12,D12,F12,H12)
B13: Tips | C13: =SUMIF('Monthly Detail'!$3:$3, 'Quarterly Overview'!C$11, 'Monthly Detail'!13:13) | D13: =SUMIF('Monthly Detail'!$3:$3, 'Quarterly Overview'!D$11, 'Monthly Detail'!13:13) | E13: =+D13-C13 | F13: =SUMIF('Monthly Detail'!$3:$3, 'Quarterly Overview'!F$11, 'Monthly Detail'!13:13) | G13: =+F13-D13 | H13: =SUMIF('Monthly Detail'!$3:$3, 'Quarterly Overview'!H$11, 'Monthly Detail'!13:13) | I13: =+H13-F13 | K13: =+SUM(H13,F13,D13,C13)
B14: Total Income | C14: =SUM(C12:C13) | D14: =SUM(D12:D13) | E14: =+D14-C14 | F14: =SUM(F12:F13) | G14: =+F14-D14 | H14: =SUM(H12:H13) | I14: =+H14-F14 | K14: =SUM(K12:K13)
B15: Avg. # of Students | C15: =+AVERAGEIFS('Monthly Detail'!17:17,'Monthly Detail'!3:3,'Quarterly Overview'!C10) | D15: =+AVERAGEIFS('Monthly Detail'!17:17,'Monthly Detail'!3:3,'Quarterly Overview'!D10) | E15: =+D15-C15 | F15: =+AVERAGEIFS('Monthly Detail'!17:17,'Monthly Detail'!3:3,'Quarterly Overview'!F10) | G15: =+F15-D15 | H15: =+AVERAGEIFS('Monthly Detail'!17:17,'Monthly Detail'!3:3,'Quarterly Overview'!H10) | I15: =+H15-F15
B17: Subcontractor Expenses | C17: =SUMIF('Monthly Detail'!$3:$3, 'Quarterly Overview'!C$11, 'Monthly Detail'!$65:$65) | D17: =SUMIF('Monthly Detail'!$3:$3, 'Quarterly Overview'!D$11, 'Monthly Detail'!$65:$65) | E17: =+D17-C17 | F17: =SUMIF('Monthly Detail'!$3:$3, 'Quarterly Overview'!F$11, 'Monthly Detail'!$65:$65) | G17: =+F17-E17 | H17: =SUMIF('Monthly Detail'!$3:$3, 'Quarterly Overview'!H$11, 'Monthly Detail'!$65:$65) | I17: =+H17-G17 | K17: =SUM(C17,D17,F17,H17)
B18: Gross Margin | C18: =C14-C17 | D18: =D14-D17 | E18: =+D18-C18 | F18: =F14-F17 | G18: =+F18-D18 | H18: =H14-H17 | I18: =+H18-F18 | K18: =K14-K17
B19: GM % | C19: =C18/C14 | D19: =D18/D14 | E19: =+D19-C19 | F19: =F18/F14 | G19: =+F19-D19 | H19: =H18/H14 | I19: =+H19-F19 | K19: =K18/K14
B21: Sales & Marketing Expenses | C21: =SUMIF('Monthly Detail'!$3:$3, 'Quarterly Overview'!C$11, 'Monthly Detail'!$72:$72) | D21: =SUMIF('Monthly Detail'!$3:$3, 'Quarterly Overview'!D$11, 'Monthly Detail'!$72:$72) | E21: =+D21-C21 | F21: =SUMIF('Monthly Detail'!$3:$3, 'Quarterly Overview'!F$11, 'Monthly Detail'!$72:$72) | G21: =SUMIF('Monthly Detail'!$3:$3, 'Quarterly Overview'!G$11, 'Monthly Detail'!$72:$72) | H21: =SUMIF('Monthly Detail'!$3:$3, 'Quarterly Overview'!H$11, 'Monthly Detail'!$72:$72) | I21: =SUMIF('Monthly Detail'!$3:$3, 'Quarterly Overview'!I$11, 'Monthly Detail'!$72:$72) | K21: =SUM(C21,D21,F21,H21)
B22: General & Admintrative Expenses | C22: =SUMIF('Monthly Detail'!$3:$3, 'Quarterly Overview'!C$11, 'Monthly Detail'!$95:$95) | D22: =SUMIF('Monthly Detail'!$3:$3, 'Quarterly Overview'!D$11, 'Monthly Detail'!$95:$95) | E22: =+D22-C22 | F22: =SUMIF('Monthly Detail'!$3:$3, 'Quarterly Overview'!F$11, 'Monthly Detail'!$95:$95) | G22: =+F22-D22 | H22: =SUMIF('Monthly Detail'!$3:$3, 'Quarterly Overview'!H$11, 'Monthly Detail'!$95:$95) | I22: =+H22-F22 | K22: =SUM(C22,D22,F22,H22)
B23: Operating Expenses | C23: =SUM(C21:C22) | D23: =SUM(D21:D22) | E23: =SUM(E21:E22) | F23: =SUM(F21:F22) | G23: =SUM(G21:G22) | H23: =SUM(H21:H22) | I23: =+H23-F23 | K23: =SUM(K21:K22)
B25: Net Operating Income (EBITDA) | C25: =C18-C23 | D25: =D18-D23 | E25: =+D25-C25 | F25: =F18-F23 | G25: =+F25-D25 | H25: =H18-H23 | I25: =+H25-F25 | K25: =K18-K23
B26: EBITDA % | C26: =C25/C14 | D26: =D25/D14 | E26: =+D26-C26 | F26: =F25/F14 | G26: =+F26-D26 | H26: =H25/H14 | I26: =+H26-F26 | K26: =K25/K14
B28: Other Income / (Expense) | C28: =SUMIF('Monthly Detail'!$3:$3, 'Quarterly Overview'!C$11, 'Monthly Detail'!109:109) | D28: =SUMIF('Monthly Detail'!$3:$3, 'Quarterly Overview'!D$11, 'Monthly Detail'!109:109) | E28: =+D28-C28 | F28: =SUMIF('Monthly Detail'!$3:$3, 'Quarterly Overview'!F$11, 'Monthly Detail'!109:109) | G28: =+F28-D28 | H28: =SUMIF('Monthly Detail'!$3:$3, 'Quarterly Overview'!H$11, 'Monthly Detail'!109:109) | I28: =+H28-F28 | K28: =SUM(C28,D28,F28,H28)
B29: Net Income | C29: =C25+SUM(C28:C28) | D29: =D25+SUM(D28:D28) | E29: =+D29-C29 | F29: =F25+SUM(F28:F28) | G29: =+F29-D29 | H29: =H25+SUM(H28:H28) | I29: =+H29-F29 | K29: =K25+SUM(K28:K28)
B30: NI % | C30: =C29/C14 | D30: =D29/D14 | E30: =+D30-C30 | F30: =F29/F14 | G30: =+F30-D30 | H30: =H29/H14 | I30: =+H30-F30 | K30: =K29/K14
B32: Operating Cash | C32: =SUMIF('Monthly Detail'!$4:$4, 'Quarterly Overview'!C$9, 'Monthly Detail'!174:174) | D32: =SUMIF('Monthly Detail'!$4:$4, 'Quarterly Overview'!D$9, 'Monthly Detail'!174:174) | F32: =SUMIF('Monthly Detail'!$4:$4, 'Quarterly Overview'!F$9, 'Monthly Detail'!174:174) | H32: =SUMIF('Monthly Detail'!$4:$4, 'Quarterly Overview'!H$9, 'Monthly Detail'!174:174)
B33: Cash Inflow (Outflow) | C33: =SUMIF('Monthly Detail'!$3:$3, 'Quarterly Overview'!C$10, 'Monthly Detail'!171:171) | D33: =SUMIF('Monthly Detail'!$3:$3, 'Quarterly Overview'!D$10, 'Monthly Detail'!171:171) | E33: =+D33-C33 | F33: =SUMIF('Monthly Detail'!$3:$3, 'Quarterly Overview'!F$10, 'Monthly Detail'!171:171) | G33: =+F33-D33 | H33: =SUMIF('Monthly Detail'!$3:$3, 'Quarterly Overview'!H$10, 'Monthly Detail'!171:171) | I33: =+H33-F33
C37: Q1 | D37: Q2 | F37: Q3 | H37: Q4
B38: 2024 AOP Income | C38: =+SUM('2025 AOP'!C14:E14) | D38: =+SUM('2025 AOP'!F14:H14) | F38: =+SUM('2025 AOP'!I14:K14) | H38: =+SUM('2025 AOP'!L14:N14)
B39: 2024 AOP Net Income | C39: =+AVERAGE('2025 AOP'!C28:E28) | D39: =+SUM('2025 AOP'!F28:H28) | F39: =+SUM('2025 AOP'!I28:K28) | H39: =+SUM('2025 AOP'!L28:N28)
B40: 2024 AOP Avg. Students | C40: =+AVERAGE('2025 AOP'!C15:E15) | D40: =+AVERAGE('2025 AOP'!F15:H15) | F40: =+AVERAGE('2025 AOP'!I15:K15) | H40: =+AVERAGE('2025 AOP'!L15:N15)

Sheet 2022 Overview
C10: =TEXT('Monthly Detail'!D4,"mmmm") | D10: =TEXT('Monthly Detail'!E4,"mmmm") | E10: =TEXT('Monthly Detail'!F4,"mmmm") | F10: =TEXT('Monthly Detail'!G4,"mmmm") | G10: =TEXT('Monthly Detail'!H4,"mmmm") | H10: =TEXT('Monthly Detail'!I4,"mmmm") | I10: =TEXT('Monthly Detail'!J4,"mmmm") | J10: =TEXT('Monthly Detail'!K4,"mmmm") | ... N10: =TEXT('Monthly Detail'!O4,"mmmm") | P10: Total
C11: 44592 | D11: 44620 | E11: 44651 | F11: 44681 | G11: 44712 | H11: 44742 | I11: 44773 | J11: 44804 | K11: 44834 | L11: 44865 | M11: 44895 | N11: 44926
B12: Service Income | C12: =SUMIF('Monthly Detail'!$4:$4, '2022 Overview'!C$11, 'Monthly Detail'!12:12) | D12: =SUMIF('Monthly Detail'!$4:$4, '2022 Overview'!D$11, 'Monthly Detail'!12:12) | E12: =SUMIF('Monthly Detail'!$4:$4, '2022 Overview'!E$11, 'Monthly Detail'!12:12) | F12: =SUMIF('Monthly Detail'!$4:$4, '2022 Overview'!F$11, 'Monthly Detail'!12:12) | G12: =SUMIF('Monthly Detail'!$4:$4, '2022 Overview'!G$11, 'Monthly Detail'!12:12) | H12: =SUMIF('Monthly Detail'!$4:$4, '2022 Overview'!H$11, 'Monthly Detail'!12:12) | I12: =SUMIF('Monthly Detail'!$4:$4, '2022 Overview'!I$11, 'Monthly Detail'!12:12) | J12: =SUMIF('Monthly Detail'!$4:$4, '2022 Overview'!J$11, 'Monthly Detail'!12:12) | ... N12: =SUMIF('Monthly Detail'!$4:$4, '2022 Overview'!N$11, 'Monthly Detail'!12:12) | P12: =SUM(C12:O12)
B13: Misc. | C13: =SUMIF('Monthly Detail'!$4:$4, '2022 Overview'!C$11, 'Monthly Detail'!13:13) | D13: =SUMIF('Monthly Detail'!$4:$4, '2022 Overview'!D$11, 'Monthly Detail'!13:13) | E13: =SUMIF('Monthly Detail'!$4:$4, '2022 Overview'!E$11, 'Monthly Detail'!13:13) | F13: =SUMIF('Monthly Detail'!$4:$4, '2022 Overview'!F$11, 'Monthly Detail'!13:13) | G13: =SUMIF('Monthly Detail'!$4:$4, '2022 Overview'!G$11, 'Monthly Detail'!13:13) | H13: =SUMIF('Monthly Detail'!$4:$4, '2022 Overview'!H$11, 'Monthly Detail'!13:13) | I13: =SUMIF('Monthly Detail'!$4:$4, '2022 Overview'!I$11, 'Monthly Detail'!13:13) | J13: =SUMIF('Monthly Detail'!$4:$4, '2022 Overview'!J$11, 'Monthly Detail'!13:13) | ... N13: =SUMIF('Monthly Detail'!$4:$4, '2022 Overview'!N$11, 'Monthly Detail'!13:13)
B14: Total Income | C14: 0.1 | D14: 0.1 | E14: 0.1 | F14: 0.1 | G14: 0.1 | H14: 0.1 | I14: 0.1 | J14: =SUM(J12:J13) | K14: =SUM(K12:K13) | L14: =SUM(L12:L13) | M14: =SUM(M12:M13) | N14: =SUM(N12:N13) | P14: =SUM(P12:P12)
B16: Gross Margin | C16: =C14 | D16: =D14 | E16: =E14 | F16: =F14 | G16: =G14 | H16: =H14 | I16: =I14 | J16: =J14 | ... N16: =N14 | P16: =P14
B17: GM % | C17: =C16/C14 | D17: =D16/D14 | E17: =E16/E14 | F17: =F16/F14 | G17: =G16/G14 | H17: =H16/H14 | I17: =I16/I14 | J17: =J16/J14 | ... N17: =N16/N14 | P17: =P16/P14
B19: General & Admintrative Expenses | C19: =SUMIF('Monthly Detail'!$4:$4, '2023 Overview'!C$11, 'Monthly Detail'!$95:$95) | D19: =SUMIF('Monthly Detail'!$4:$4, '2023 Overview'!D$11, 'Monthly Detail'!$95:$95) | E19: =SUMIF('Monthly Detail'!$4:$4, '2023 Overview'!E$11, 'Monthly Detail'!$95:$95) | F19: =SUMIF('Monthly Detail'!$4:$4, '2023 Overview'!F$11, 'Monthly Detail'!$95:$95) | G19: =SUMIF('Monthly Detail'!$4:$4, '2023 Overview'!G$11, 'Monthly Detail'!$95:$95) | H19: =SUMIF('Monthly Detail'!$4:$4, '2023 Overview'!H$11, 'Monthly Detail'!$95:$95) | I19: =SUMIF('Monthly Detail'!$4:$4, '2023 Overview'!I$11, 'Monthly Detail'!$95:$95) | J19: =SUMIF('Monthly Detail'!$4:$4, '2023 Overview'!J$11, 'Monthly Detail'!$95:$95) | ... N19: =SUMIF('Monthly Detail'!$4:$4, '2023 Overview'!N$11, 'Monthly Detail'!$95:$95) | P19: =SUM(C19:O19)
B20: Owner Guarenteed Payments | C20: =SUMIF('Monthly Detail'!$4:$4, '2022 Overview'!C$11, 'Monthly Detail'!52:52) | D20: =SUMIF('Monthly Detail'!$4:$4, '2022 Overview'!D$11, 'Monthly Detail'!52:52) | E20: =SUMIF('Monthly Detail'!$4:$4, '2022 Overview'!E$11, 'Monthly Detail'!52:52) | F20: =SUMIF('Monthly Detail'!$4:$4, '2022 Overview'!F$11, 'Monthly Detail'!52:52) | G20: =SUMIF('Monthly Detail'!$4:$4, '2022 Overview'!G$11, 'Monthly Detail'!52:52) | H20: =SUMIF('Monthly Detail'!$4:$4, '2022 Overview'!H$11, 'Monthly Detail'!52:52) | I20: =SUMIF('Monthly Detail'!$4:$4, '2022 Overview'!I$11, 'Monthly Detail'!52:52) | J20: =SUMIF('Monthly Detail'!$4:$4, '2022 Overview'!J$11, 'Monthly Detail'!52:52) | ... N20: =SUMIF('Monthly Detail'!$4:$4, '2022 Overview'!N$11, 'Monthly Detail'!52:52) | P20: =SUM(C20:O20)
B21: Operating Expenses | C21: =SUM(C19:C20) | D21: =SUM(D19:D20) | E21: =SUM(E19:E20) | F21: =SUM(F19:F20) | G21: =SUM(G19:G20) | H21: =SUM(H19:H20) | I21: =SUM(I19:I20) | J21: =SUM(J19:J20) | ... N21: =SUM(N19:N20) | P21: =SUM(P19:P20)
B23: Net Operating Income (EBITDA) | C23: =C16-C21 | D23: =D16-D21 | E23: =E16-E21 | F23: =F16-F21 | G23: =G16-G21 | H23: =H16-H21 | I23: =I16-I21 | J23: =J16-J21 | ... N23: =N16-N21 | P23: =P16-P21
B24: EBITDA % | C24: =C23/C14 | D24: =D23/D14 | E24: =E23/E14 | F24: =F23/F14 | G24: =G23/G14 | H24: =H23/H14 | I24: =I23/I14 | J24: =J23/J14 | ... N24: =N23/N14 | P24: =P23/P14
B26: Other Income / (Expense) | C26: =SUMIF('Monthly Detail'!$4:$4, '2022 Overview'!C$11, 'Monthly Detail'!88:88) | D26: =SUMIF('Monthly Detail'!$4:$4, '2022 Overview'!D$11, 'Monthly Detail'!88:88) | E26: =SUMIF('Monthly Detail'!$4:$4, '2022 Overview'!E$11, 'Monthly Detail'!88:88) | F26: =SUMIF('Monthly Detail'!$4:$4, '2022 Overview'!F$11, 'Monthly Detail'!88:88) | G26: =SUMIF('Monthly Detail'!$4:$4, '2022 Overview'!G$11, 'Monthly Detail'!88:88) | H26: =SUMIF('Monthly Detail'!$4:$4, '2022 Overview'!H$11, 'Monthly Detail'!88:88) | I26: =SUMIF('Monthly Detail'!$4:$4, '2022 Overview'!I$11, 'Monthly Detail'!88:88) | J26: =SUMIF('Monthly Detail'!$4:$4, '2022 Overview'!J$11, 'Monthly Detail'!88:88) | ... N26: =SUMIF('Monthly Detail'!$4:$4, '2022 Overview'!N$11, 'Monthly Detail'!88:88) | P26: =SUM(C26:O26)
B27: Net Income | C27: =C23+SUM(C26:C26) | D27: =D23+SUM(D26:D26) | E27: =E23+SUM(E26:E26) | F27: =F23+SUM(F26:F26) | G27: =G23+SUM(G26:G26) | H27: =H23+SUM(H26:H26) | I27: =I23+SUM(I26:I26) | J27: =J23+SUM(J26:J26) | ... N27: =N23+SUM(N26:N26) | P27: =P23+SUM(P26:P26)
B28: NI % | C28: =C27/C14 | D28: =D27/D14 | E28: =E27/E14 | F28: =F27/F14 | G28: =G27/G14 | H28: =H27/H14 | I28: =I27/I14 | J28: =J27/J14 | ... N28: =N27/N14 | P28: =P27/P14
B30: Operating Cash | C30: =SUMIF('Monthly Detail'!$4:$4, '2022 Overview'!C$11, 'Monthly Detail'!174:174) | D30: =SUMIF('Monthly Detail'!$4:$4, '2022 Overview'!D$11, 'Monthly Detail'!174:174) | E30: =SUMIF('Monthly Detail'!$4:$4, '2022 Overview'!E$11, 'Monthly Detail'!174:174) | F30: =SUMIF('Monthly Detail'!$4:$4, '2022 Overview'!F$11, 'Monthly Detail'!174:174) | G30: =SUMIF('Monthly Detail'!$4:$4, '2022 Overview'!G$11, 'Monthly Detail'!174:174) | H30: =SUMIF('Monthly Detail'!$4:$4, '2022 Overview'!H$11, 'Monthly Detail'!174:174) | I30: =SUMIF('Monthly Detail'!$4:$4, '2022 Overview'!I$11, 'Monthly Detail'!174:174) | J30: =SUMIF('Monthly Detail'!$4:$4, '2022 Overview'!J$11, 'Monthly Detail'!174:174) | ... N30: =SUMIF('Monthly Detail'!$4:$4, '2022 Overview'!N$11, 'Monthly Detail'!174:174)
B31: Cash Inflow (Outflow) | C31: =SUMIF('Monthly Detail'!$4:$4, '2022 Overview'!C$11, 'Monthly Detail'!160:160) | D31: =D30-C30 | E31: =E30-D30 | F31: =F30-E30 | G31: =G30-F30 | H31: =H30-G30 | I31: =I30-H30 | J31: =J30-I30 | K31: =K30-J30 | ... N31: =N30-M30

Sheet 2

Sheet Monthly Detail
D1: =YEAR(D4) | E1: =YEAR(E4) | F1: =YEAR(F4) | G1: =YEAR(G4) | H1: =YEAR(H4) | I1: =YEAR(I4) | J1: =YEAR(J4) | K1: =YEAR(K4) | ... DG1: =YEAR(DG4)
G2: Peak | H2: Peak | I2: Shoulder | J2: Shoulder | K2: Trough | L2: Shoulder | M2: Shoulder | N2: Trough | O2: Shoulder | P2: Shoulder | Q2: Peak | R2: Shoulder | S2: Shoulder | T2: Peak | U2: Shoulder | V2: Peak | W2: Peak | X2: Peak | Y2: Shoulder | Z2: Trough | AA2: Trough | AB2: =+P2 | AC2: =+Q2 | AD2: =+R2 | AE2: =+S2 | AF2: =+T2 | AG2: =+U2 | AH2: =+V2 | AI2: =+W2 | ... DG2: =+CU2
D3: =+"Q1 "&D1 | E3: =+"Q1 "&E1 | F3: =+"Q1 "&F1 | G3: =+"Q2 "&G1 | H3: =+"Q2 "&H1 | I3: =+"Q2 "&I1 | J3: =+"Q3 "&J1 | K3: =+"Q3 "&K1 | L3: =+"Q3 "&L1 | M3: =+"Q4 "&M1 | N3: =+"Q4 "&N1 | O3: =+"Q4 "&O1 | P3: =+"Q1 "&P1 | Q3: =+"Q1 "&Q1 | R3: =+"Q1 "&R1 | S3: =+"Q2 "&S1 | T3: =+"Q2 "&T1 | U3: =+"Q2 "&U1 | V3: =+"Q3 "&V1 | W3: =+"Q3 "&W1 | X3: =+"Q3 "&X1 | Y3: =+"Q4 "&Y1 | Z3: =+"Q4 "&Z1 | AA3: =+"Q4 "&AA1 | AB3: =+"Q1 "&AB1 | AC3: =+"Q1 "&AC1 | AD3: =+"Q1 "&AD1 | AE3: =+"Q2 "&AE1 | AF3: =+"Q2 "&AF1 | AG3: =+"Q2 "&AG1 | AH3: =+"Q3 "&AH1 | AI3: =+"Q3 "&AI1 | AJ3: =+"Q3 "&AJ1 | AK3: =+"Q4 "&AK1 | AL3: =+"Q4 "&AL1 | AM3: =+"Q4 "&AM1 | AN3: =+"Q1 "&AN1 | AO3: =+"Q1 "&AO1 | AP3: =+"Q1 "&AP1 | AQ3: =+"Q2 "&AQ1 | AR3: =+"Q2 "&AR1 | AS3: =+"Q2 "&AS1 | AT3: =+"Q3 "&AT1 | AU3: =+"Q3 "&AU1 | AV3: =+"Q3 "&AV1 | AW3: =+"Q4 "&AW1 | AX3: =+"Q4 "&AX1 | AY3: =+"Q4 "&AY1 | AZ3: =+"Q1 "&AZ1 | BA3: =+"Q1 "&BA1 | BB3: =+"Q1 "&BB1 | BC3: =+"Q2 "&BC1 | BD3: =+"Q2 "&BD1 | BE3: =+"Q2 "&BE1 | BF3: =+"Q3 "&BF1 | BG3: =+"Q3 "&BG1 | BH3: =+"Q3 "&BH1 | BI3: =+"Q4 "&BI1 | BJ3: =+"Q4 "&BJ1 | BK3: =+"Q4 "&BK1 | BL3: =+"Q1 "&BL1 | BM3: =+"Q1 "&BM1 | BN3: =+"Q1 "&BN1 | BO3: =+"Q2 "&BO1 | BP3: =+"Q2 "&BP1 | BQ3: =+"Q2 "&BQ1 | BR3: =+"Q3 "&BR1 | BS3: =+"Q3 "&BS1 | BT3: =+"Q3 "&BT1 | BU3: =+"Q4 "&BU1 | BV3: =+"Q4 "&BV1 | BW3: =+"Q4 "&BW1 | BX3: =+"Q1 "&BX1 | BY3: =+"Q1 "&BY1 | BZ3: =+"Q1 "&BZ1 | CA3: =+"Q2 "&CA1 | CB3: =+"Q2 "&CB1 | CC3: =+"Q2 "&CC1 | CD3: =+"Q3 "&CD1 | CE3: =+"Q3 "&CE1 | CF3: =+"Q3 "&CF1 | CG3: =+"Q4 "&CG1 | CH3: =+"Q4 "&CH1 | CI3: =+"Q4 "&CI1 | CJ3: =+"Q1 "&CJ1 | CK3: =+"Q1 "&CK1 | CL3: =+"Q1 "&CL1 | CM3: =+"Q2 "&CM1 | CN3: =+"Q2 "&CN1 | CO3: =+"Q2 "&CO1 | CP3: =+"Q3 "&CP1 | CQ3: =+"Q3 "&CQ1 | CR3: =+"Q3 "&CR1 | CS3: =+"Q4 "&CS1 | CT3: =+"Q4 "&CT1 | CU3: =+"Q4 "&CU1 | CV3: =+"Q1 "&CV1 | CW3: =+"Q1 "&CW1 | CX3: =+"Q1 "&CX1 | CY3: =+"Q2 "&CY1 | CZ3: =+"Q2 "&CZ1 | DA3: =+"Q2 "&DA1 | DB3: =+"Q3 "&DB1 | DC3: =+"Q3 "&DC1 | DD3: =+"Q3 "&DD1 | DE3: =+"Q4 "&DE1 | DF3: =+"Q4 "&DF1 | DG3: =+"Q4 "&DG1
D4: 44592 | E4: 44620 | F4: 44651 | G4: 44681 | H4: 44712 | I4: 44742 | J4: 44773 | K4: 44804 | L4: 44834 | M4: 44865 | N4: 44895 | O4: 44926 | P4: 44957 | Q4: 44985 | R4: 45016 | S4: 45046 | T4: 45077 | U4: 45107 | V4: 45138 | W4: 45169 | X4: 45199 | Y4: 45230 | Z4: 45260 | AA4: 45291 | AB4: 45322 | AC4: 45351 | AD4: 45382 | AE4: 45412 | AF4: 45443 | AG4: 45473 | AH4: 45504 | AI4: 45535 | AJ4: 45565 | AK4: 45596 | AL4: 45626 | AM4: 45657 | AN4: 45688 | AO4: 45716 | AP4: 45747 | AQ4: 45777 | AR4: 45808 | AS4: 45838 | AT4: 45869 | AU4: 45900 | AV4: 45930 | AW4: 45961 | AX4: 45991 | AY4: 46022 | AZ4: 46053 | BA4: 46081 | BB4: 46112 | BC4: 46142 | BD4: 46173 | BE4: 46203 | BF4: 46234 | BG4: 46265 | BH4: 46295 | BI4: 46326 | BJ4: 46356 | BK4: 46387 | BL4: 46418 | BM4: 46446 | BN4: 46477 | BO4: 46507 | BP4: 46538 | BQ4: 46568 | BR4: 46599 | BS4: 46630 | BT4: 46660 | BU4: 46691 | BV4: 46721 | BW4: 46752 | BX4: 46783 | BY4: 46812 | BZ4: 46843 | CA4: 46873 | CB4: 46904 | CC4: 46934 | CD4: 46965 | CE4: 46996 | CF4: 47026 | CG4: 47057 | CH4: 47087 | CI4: 47118 | CJ4: 47149 | CK4: 47177 | CL4: 47208 | CM4: 47238 | CN4: 47269 | CO4: 47299 | CP4: 47330 | CQ4: 47361 | CR4: 47391 | CS4: 47422 | CT4: 47452 | CU4: 47483 | CV4: 47514 | CW4: 47542 | CX4: 47573 | CY4: 47603 | CZ4: 47634 | DA4: 47664 | DB4: 47695 | DC4: 47726 | DD4: 47756 | DE4: 47787 | DF4: 47817 | DG4: 47848
B5: Income
B6: 50000 Service Income | D6: =0 | E6: =0 | F6: =0 | G6: =0 | H6: =0 | I6: =0 | J6: =0 | K6: 0 | L6: 0 | M6: 0
B7: 50100 Tutoring Sessions | D7: =0 | E7: =0 | F7: =0 | G7: =0 | H7: =0 | I7: =0 | J7: 0 | K7: 50 | L7: 350 | M7: 2640 | N7: 1865 | O7: 1932.5 | P7: 1360 | Q7: 1225 | R7: 1177.5 | S7: 1875 | T7: 2446.25 | U7: 1963.75 | V7: 2220 | W7: 5316.66 | X7: 4203.34 | Y7: 3105 | Z7: 2692.5 | AA7: 1350 | AB7: 1342.5 | AC7: 2167.5 | AD7: 1847.5 | AE7: 2035 | AF7: 1725 | AG7: 1285 | AH7: 1122.52 | AI7: 506.26 | AJ7: 326.25 | AK7: 135 | AL7: 727.5 | AM7: 585 | AN7: 371.25 | AO7: 1108.75 | AP7: 1537.5 | AQ7: 435 | AR7: 281.25 | AT7: 168.75 | AU7: 843.75 | AV7: =1443.75 | AW7: =1871.26 | AX7: =+(AX36*AX28)+(AX32*AX40) | AY7: =+(AY36*AY28)+(AY32*AY40) | AZ7: =+(AZ36*AZ28)+(AZ32*AZ40) | BA7: =+(BA36*BA28)+(BA32*BA40) | BB7: =+(BB36*BB28)+(BB32*BB40) | BC7: =+(BC36*BC28)+(BC32*BC40) | BD7: =+(BD36*BD28)+(BD32*BD40) | BE7: =+(BE36*BE28)+(BE32*BE40) | ... DG7: =+(DG36*DG28)+(DG32*DG40)
B8: 50200 SAT/ACT Prep | D8: =0 | E8: =0 | F8: =0 | G8: =0 | H8: =0 | I8: =0 | J8: 0 | K8: 175 | L8: 50 | M8: 325 | N8: 225 | O8: 0 | V8: 150 | W8: 140 | X8: 1827.5 | Y8: 1620 | Z8: 1070 | AA8: 700 | AB8: 1110 | AC8: 2115 | AD8: 1470 | AE8: 1935 | AF8: 3645 | AG8: 1305.01 | AH8: 4406.25 | AI8: 8085 | AJ8: 1530 | AK8: 2085 | AL8: 956.25 | AM8: 1706.25 | AN8: 3195 | AO8: 4511.25 | AP8: 5467.5 | AQ8: 2733.75 | AR8: 4901.25 | AS8: 2047.5 | AT8: 5011.25 | AU8: 5946.25 | AV8: =8113.75 | AW8: =4536.25 | AX8: =+AX37*AX29 | AY8: =+AY37*AY29 | AZ8: =+AZ37*AZ29 | BA8: =+BA37*BA29 | BB8: =+BB37*BB29 | BC8: =+BC37*BC29 | BD8: =+BD37*BD29 | BE8: =+BE37*BE29 | ... DG8: =+DG37*DG29
B9: 50300 Resume Review | AI9: 851.25 | AJ9: 997.5 | AK9: 1592.5 | AL9: 150 | AO9: 562.5 | AR9: 450 | AS9: 637.5 | AT9: 1212.5 | AU9: 1750 | AV9: =2272.5 | AW9: =2393.75 | AX9: =+AX38*AX30 | AY9: =+AY38*AY30 | AZ9: =+AZ38*AZ30 | BA9: =+BA38*BA30 | BB9: =+BB38*BB30 | BC9: =+BC38*BC30 | BD9: =+BD38*BD30 | BE9: =+BE38*BE30 | ... DG9: =+DG38*DG30
B10: 50400 College Essay Review | D10: =0 | E10: =0 | F10: =0 | G10: =0 | H10: =0 | I10: =0 | J10: 0 | K10: 150 | L10: 675 | M10: 675 | N10: 0 | O10: 100 | P10: 150 | S10: 44.91 | U10: 75 | V10: 415 | W10: 1595 | X10: 2690 | Y10: 3315 | Z10: 1065 | AA10: 45 | AB10: 195 | AC10: 75 | AD10: 150 | AE10: 30 | AG10: 1706.25 | AH10: 3502.5 | AI10: 4631.25 | AJ10: 7043.75 | AK10: 13573.75 | AL10: 7730 | AM10: 2868.75 | AN10: 2911.25 | AO10: 1870 | AP10: 625 | AQ10: 587.5 | AR10: 400 | AS10: 4137.5 | AT10: 8462.5 | AU10: 11872.5 | AV10: =16427.5 | AW10: =30345 | AX10: =+AX39*AX31 | AY10: =+AY39*AY31 | AZ10: =+AZ39*AZ31 | BA10: =+BA39*BA31 | BB10: =+BB39*BB31 | BC10: =+BC39*BC31 | BD10: =+BD39*BD31 | BE10: =+BE39*BE31 | ... DG10: =+DG39*DG31
B11: 50500 Interview Prep | AB11: 237.5 | AR11: 0 | AS11: 0 | AT11: 0 | AU11: 0 | AV11: 0 | AW11: =187.5
B12: Total 50000 Service Income | D12: =(((D6)+(D7))+(D8))+(D10) | E12: =(((E6)+(E7))+(E8))+(E10) | F12: =(((F6)+(F7))+(F8))+(F10) | G12: =(((G6)+(G7))+(G8))+(G10) | H12: =(((H6)+(H7))+(H8))+(H10) | I12: =(((I6)+(I7))+(I8))+(I10) | J12: =(((J6)+(J7))+(J8))+(J10) | K12: =SUM(K7:K10) | L12: =SUM(L7:L10) | M12: =SUM(M7:M10) | N12: =SUM(N7:N10) | O12: =SUM(O7:O10) | P12: =SUM(P7:P10) | Q12: =SUM(Q7:Q10) | R12: =SUM(R7:R10) | ... Z12: =SUM(Z7:Z10) | AA12: =SUM(AA7:AA11) | AB12: =SUM(AB7:AB11) | AC12: =SUM(AC7:AC11) | AD12: =SUM(AD7:AD11) | AE12: =SUM(AE7:AE11) | AF12: =SUM(AF7:AF11) | AG12: =SUM(AG7:AG11) | AH12: =SUM(AH7:AH11) | ... DG12: =SUM(DG7:DG11)
B13: 70000 Tips/Miscellaneous | D13: =0 | E13: =0 | F13: =0 | G13: =0 | H13: =0 | I13: =0 | J13: =0 | K13: 0 | L13: 0 | M13: 125 | N13: 0 | O13: 0 | P13: 35.99 | Q13: 30.75 | R13: 29.25 | S13: 37.5 | T13: 40.68 | U13: 4.68 | V13: 50.5 | W13: 27 | X13: 35.25 | Y13: 156.37 | Z13: 110.62 | AA13: 49.5 | AB13: 117 | AD13: 12 | AE13: 18 | AF13: 50.08 | AG13: 12 | AH13: 29.62 | AI13: 37.5 | AK13: 19.5 | AL13: 9.75 | AM13: 34 | AN13: 108 | AO13: 59.62 | AP13: 52.37 | AR13: 12 | AS13: 93.5 | AT13: 75 | AU13: 44.5 | AV13: 50 | AW13: 29.37 | AX13: =+AX15*AX12 | AY13: =+AY15*AY12 | AZ13: =+AZ15*AZ12 | BA13: =+BA15*BA12 | BB13: =+BB15*BB12 | BC13: =+BC15*BC12 | BD13: =+BD15*BD12 | BE13: =+BE15*BE12 | ... DG13: =+DG15*DG12
B14: Total Income | C14: Total Revenue | D14: =(D12)+(D13) | E14: =(E12)+(E13) | F14: =(F12)+(F13) | G14: =(G12)+(G13) | H14: =(H12)+(H13) | I14: =(I12)+(I13) | J14: =(J12)+(J13) | K14: =K13+K12 | L14: =L13+L12 | M14: =M13+M12 | N14: =N13+N12 | O14: =O13+O12 | P14: =P13+P12 | Q14: =Q13+Q12 | R14: =R13+R12 | ... DG14: =DG13+DG12
C15: Tips as a % of Revenue | K15: =+K13/K12 | L15: =+L13/L12 | M15: =+M13/M12 | N15: =+N13/N12 | O15: =+O13/O12 | P15: =+P13/P12 | Q15: =+Q13/Q12 | R15: =+R13/R12 | ... AW15: =+AW13/AW12 | AX15: =+AVERAGE(AR15:AW15) | AY15: =+AX15 | AZ15: =+AY15 | BA15: =+AZ15 | BB15: =+BA15 | BC15: =+BB15 | BD15: =+BC15 | BE15: =+BD15 | BF15: =+BE15 | ... DG15: =+DF15
C17: # of Students | E17: 12 | F17: 8 | G17: 7 | H17: 10 | I17: 13 | J17: 11 | K17: 5 | L17: 9 | M17: 17 | N17: 11 | O17: 7 | P17: 12 | Q17: 10 | R17: 10 | S17: 7 | T17: 9 | U17: 13 | V17: 8 | W17: 19 | X17: 29 | Y17: 32 | Z17: 32 | AA17: 19 | AB17: 16 | AC17: 15 | AD17: 20 | AE17: 17 | AF17: 20 | AG17: 24 | AH17: 30 | AI17: 38 | AJ17: 42 | AK17: 48 | AL17: 44 | AM17: 23 | AN17: 24 | AO17: 28 | AP17: 24 | AQ17: 23 | AR17: 20 | AS17: 25 | AT17: 35 | AU17: 48 | AV17: 57 | AW17: 67 | AX17: =+AW17+AX19 | AY17: =+AX17+AY19 | AZ17: =+AY17+AZ19 | BA17: =+AZ17+BA19 | BB17: =+BA17+BB19 | BC17: =+BB17+BC19 | BD17: =+BC17+BD19 | BE17: =+BD17+BE19 | ... DG17: =+DF17+DG19
C18: # of Recurring Students | AO18: 18 | AP18: 21 | AQ18: 19 | AR18: 19 | AS18: 19 | AT18: 19 | AU18: 19 | AV18: 19 | AW18: 51
C19: Net New Students | E19: =E17-D17 | F19: =F17-E17 | G19: =G17-F17 | H19: =H17-G17 | I19: =I17-H17 | J19: =J17-I17 | K19: =K17-J17 | L19: =L17-K17 | ... AW19: =AW17-AV17 | AX19: =+AX20+AX21 | AY19: =+AY20+AY21 | AZ19: =+AZ20+AZ21 | BA19: =+BA20+BA21 | BB19: =+BB20+BB21 | BC19: =+BC20+BC21 | BD19: =+BD20+BD21 | BE19: =+BE20+BE21 | ... DG19: =+DG20+DG21
C20: Additions | F20: =+IF(F17>E17,F17-E17, 0) | G20: =+IF(G17>F17,G17-F17, 0) | H20: =+IF(H17>G17,H17-G17, 0) | I20: =+IF(I17>H17,I17-H17, 0) | J20: =+IF(J17>I17,J17-I17, 0) | K20: =+IF(K17>J17,K17-J17, 0) | L20: =+IF(L17>K17,L17-K17, 0) | M20: =+IF(M17>L17,M17-L17, 0) | ... P20: =+IF(P17>O17,P17-O17, 0) | Q20: 2 | R20: 2 | S20: 3 | T20: 6 | U20: 11 | V20: 4 | W20: 12 | X20: 13 | Y20: 8 | Z20: 14 | AA20: 5 | AB20: 4 | AC20: 5 | AD20: 7 | AE20: 5 | AF20: 6 | AG20: 15 | AH20: 7 | AI20: 10 | AJ20: 10 | AK20: 9 | AL20: 6 | AM20: 5 | AN20: 5 | AO20: 11 | AP20: 4 | AQ20: 5 | AR20: 3 | AS20: 3 | AT20: 12 | AU20: 15 | AV20: 15 | AW20: 16 | AX20: =IF(AX2="Trough",INDEX($H$55:$H$57,MATCH(AX2,$E$55:$E$57,0)),IF(AX2="Shoulder",INDEX($H$55:$H$57,MATCH(AX2,$E$55:$E$57,0)),INDEX($H$55:$H$57,MATCH(AX2,$E$55:$E$57,0)))) | AY20: =IF(AY2="Trough",INDEX($I$55:$I$57,MATCH(AY2,$E$55:$E$57,0)),IF(AY2="Shoulder",INDEX($I$55:$I$57,MATCH(AY2,$E$55:$E$57,0)),INDEX($I$55:$I$57,MATCH(AY2,$E$55:$E$57,0))))-20 | AZ20: =IF(AZ2="Trough",INDEX($J$55:$J$57,MATCH(AZ2,$E$55:$E$57,0)),IF(AZ2="Shoulder",INDEX($J$55:$J$57,MATCH(AZ2,$E$55:$E$57,0)),INDEX($J$55:$J$57,MATCH(AZ2,$E$55:$E$57,0)))) | BA20: =IF(BA2="Trough",INDEX($J$55:$J$57,MATCH(BA2,$E$55:$E$57,0)),IF(BA2="Shoulder",INDEX($J$55:$J$57,MATCH(BA2,$E$55:$E$57,0)),INDEX($J$55:$J$57,MATCH(BA2,$E$55:$E$57,0)))) | BB20: =IF(BB2="Trough",INDEX($J$55:$J$57,MATCH(BB2,$E$55:$E$57,0)),IF(BB2="Shoulder",INDEX($J$55:$J$57,MATCH(BB2,$E$55:$E$57,0)),INDEX($J$55:$J$57,MATCH(BB2,$E$55:$E$57,0)))) | BC20: =IF(BC2="Trough",INDEX($J$55:$J$57,MATCH(BC2,$E$55:$E$57,0)),IF(BC2="Shoulder",INDEX($J$55:$J$57,MATCH(BC2,$E$55:$E$57,0)),INDEX($J$55:$J$57,MATCH(BC2,$E$55:$E$57,0)))) | BD20: =IF(BD2="Trough",INDEX($J$55:$J$57,MATCH(BD2,$E$55:$E$57,0)),IF(BD2="Shoulder",INDEX($J$55:$J$57,MATCH(BD2,$E$55:$E$57,0)),INDEX($J$55:$J$57,MATCH(BD2,$E$55:$E$57,0)))) | BE20: =IF(BE2="Trough",INDEX($J$55:$J$57,MATCH(BE2,$E$55:$E$57,0)),IF(BE2="Shoulder",INDEX($J$55:$J$57,MATCH(BE2,$E$55:$E$57,0)),INDEX($J$55:$J$57,MATCH(BE2,$E$55:$E$57,0)))) | BF20: =IF(BF2="Trough",INDEX($J$55:$J$57,MATCH(BF2,$E$55:$E$57,0)),IF(BF2="Shoulder",INDEX($J$55:$J$57,MATCH(BF2,$E$55:$E$57,0)),INDEX($J$55:$J$57,MATCH(BF2,$E$55:$E$57,0)))) | BG20: =IF(BG2="Trough",INDEX($J$55:$J$57,MATCH(BG2,$E$55:$E$57,0)),IF(BG2="Shoulder",INDEX($J$55:$J$57,MATCH(BG2,$E$55:$E$57,0)),INDEX($J$55:$J$57,MATCH(BG2,$E$55:$E$57,0)))) | ... BK20: =IF(BK2="Trough",INDEX($J$55:$J$57,MATCH(BK2,$E$55:$E$57,0)),IF(BK2="Shoulder",INDEX($J$55:$J$57,MATCH(BK2,$E$55:$E$57,0)),INDEX($J$55:$J$57,MATCH(BK2,$E$55:$E$57,0)))) | BL20: =IF(BL2="Trough",INDEX($K$55:$K$57,MATCH(BL2,$E$55:$E$57,0)),IF(BL2="Shoulder",INDEX($K$55:$K$57,MATCH(BL2,$E$55:$E$57,0)),INDEX($K$55:$K$57,MATCH(BL2,$E$55:$E$57,0)))) | BM20: =IF(BM2="Trough",INDEX($K$55:$K$57,MATCH(BM2,$E$55:$E$57,0)),IF(BM2="Shoulder",INDEX($K$55:$K$57,MATCH(BM2,$E$55:$E$57,0)),INDEX($K$55:$K$57,MATCH(BM2,$E$55:$E$57,0)))) | BN20: =IF(BN2="Trough",INDEX($K$55:$K$57,MATCH(BN2,$E$55:$E$57,0)),IF(BN2="Shoulder",INDEX($K$55:$K$57,MATCH(BN2,$E$55:$E$57,0)),INDEX($K$55:$K$57,MATCH(BN2,$E$55:$E$57,0)))) | BO20: =IF(BO2="Trough",INDEX($K$55:$K$57,MATCH(BO2,$E$55:$E$57,0)),IF(BO2="Shoulder",INDEX($K$55:$K$57,MATCH(BO2,$E$55:$E$57,0)),INDEX($K$55:$K$57,MATCH(BO2,$E$55:$E$57,0)))) | BP20: =IF(BP2="Trough",INDEX($K$55:$K$57,MATCH(BP2,$E$55:$E$57,0)),IF(BP2="Shoulder",INDEX($K$55:$K$57,MATCH(BP2,$E$55:$E$57,0)),INDEX($K$55:$K$57,MATCH(BP2,$E$55:$E$57,0)))) | BQ20: =IF(BQ2="Trough",INDEX($K$55:$K$57,MATCH(BQ2,$E$55:$E$57,0)),IF(BQ2="Shoulder",INDEX($K$55:$K$57,MATCH(BQ2,$E$55:$E$57,0)),INDEX($K$55:$K$57,MATCH(BQ2,$E$55:$E$57,0)))) | BR20: =IF(BR2="Trough",INDEX($K$55:$K$57,MATCH(BR2,$E$55:$E$57,0)),IF(BR2="Shoulder",INDEX($K$55:$K$57,MATCH(BR2,$E$55:$E$57,0)),INDEX($K$55:$K$57,MATCH(BR2,$E$55:$E$57,0)))) | BS20: =IF(BS2="Trough",INDEX($K$55:$K$57,MATCH(BS2,$E$55:$E$57,0)),IF(BS2="Shoulder",INDEX($K$55:$K$57,MATCH(BS2,$E$55:$E$57,0)),INDEX($K$55:$K$57,MATCH(BS2,$E$55:$E$57,0)))) | ... BW20: =IF(BW2="Trough",INDEX($K$55:$K$57,MATCH(BW2,$E$55:$E$57,0)),IF(BW2="Shoulder",INDEX($K$55:$K$57,MATCH(BW2,$E$55:$E$57,0)),INDEX($K$55:$K$57,MATCH(BW2,$E$55:$E$57,0)))) | BX20: =IF(BX2="Trough",INDEX($L$55:$L$57,MATCH(BX2,$E$55:$E$57,0)),IF(BX2="Shoulder",INDEX($L$55:$L$57,MATCH(BX2,$E$55:$E$57,0)),INDEX($L$55:$L$57,MATCH(BX2,$E$55:$E$57,0)))) | BY20: =IF(BY2="Trough",INDEX($L$55:$L$57,MATCH(BY2,$E$55:$E$57,0)),IF(BY2="Shoulder",INDEX($L$55:$L$57,MATCH(BY2,$E$55:$E$57,0)),INDEX($L$55:$L$57,MATCH(BY2,$E$55:$E$57,0)))) | BZ20: =IF(BZ2="Trough",INDEX($L$55:$L$57,MATCH(BZ2,$E$55:$E$57,0)),IF(BZ2="Shoulder",INDEX($L$55:$L$57,MATCH(BZ2,$E$55:$E$57,0)),INDEX($L$55:$L$57,MATCH(BZ2,$E$55:$E$57,0)))) | CA20: =IF(CA2="Trough",INDEX($L$55:$L$57,MATCH(CA2,$E$55:$E$57,0)),IF(CA2="Shoulder",INDEX($L$55:$L$57,MATCH(CA2,$E$55:$E$57,0)),INDEX($L$55:$L$57,MATCH(CA2,$E$55:$E$57,0)))) | CB20: =IF(CB2="Trough",INDEX($L$55:$L$57,MATCH(CB2,$E$55:$E$57,0)),IF(CB2="Shoulder",INDEX($L$55:$L$57,MATCH(CB2,$E$55:$E$57,0)),INDEX($L$55:$L$57,MATCH(CB2,$E$55:$E$57,0)))) | CC20: =IF(CC2="Trough",INDEX($L$55:$L$57,MATCH(CC2,$E$55:$E$57,0)),IF(CC2="Shoulder",INDEX($L$55:$L$57,MATCH(CC2,$E$55:$E$57,0)),INDEX($L$55:$L$57,MATCH(CC2,$E$55:$E$57,0)))) | CD20: =IF(CD2="Trough",INDEX($L$55:$L$57,MATCH(CD2,$E$55:$E$57,0)),IF(CD2="Shoulder",INDEX($L$55:$L$57,MATCH(CD2,$E$55:$E$57,0)),INDEX($L$55:$L$57,MATCH(CD2,$E$55:$E$57,0)))) | CE20: =IF(CE2="Trough",INDEX($L$55:$L$57,MATCH(CE2,$E$55:$E$57,0)),IF(CE2="Shoulder",INDEX($L$55:$L$57,MATCH(CE2,$E$55:$E$57,0)),INDEX($L$55:$L$57,MATCH(CE2,$E$55:$E$57,0)))) | ... CI20: =IF(CI2="Trough",INDEX($L$55:$L$57,MATCH(CI2,$E$55:$E$57,0)),IF(CI2="Shoulder",INDEX($L$55:$L$57,MATCH(CI2,$E$55:$E$57,0)),INDEX($L$55:$L$57,MATCH(CI2,$E$55:$E$57,0)))) | CJ20: =IF(CJ2="Trough",INDEX($M$55:$M$57,MATCH(CJ2,$E$55:$E$57,0)),IF(CJ2="Shoulder",INDEX($M$55:$M$57,MATCH(CJ2,$E$55:$E$57,0)),INDEX($M$55:$M$57,MATCH(CJ2,$E$55:$E$57,0)))) | CK20: =IF(CK2="Trough",INDEX($M$55:$M$57,MATCH(CK2,$E$55:$E$57,0)),IF(CK2="Shoulder",INDEX($M$55:$M$57,MATCH(CK2,$E$55:$E$57,0)),INDEX($M$55:$M$57,MATCH(CK2,$E$55:$E$57,0)))) | CL20: =IF(CL2="Trough",INDEX($M$55:$M$57,MATCH(CL2,$E$55:$E$57,0)),IF(CL2="Shoulder",INDEX($M$55:$M$57,MATCH(CL2,$E$55:$E$57,0)),INDEX($M$55:$M$57,MATCH(CL2,$E$55:$E$57,0)))) | CM20: =IF(CM2="Trough",INDEX($M$55:$M$57,MATCH(CM2,$E$55:$E$57,0)),IF(CM2="Shoulder",INDEX($M$55:$M$57,MATCH(CM2,$E$55:$E$57,0)),INDEX($M$55:$M$57,MATCH(CM2,$E$55:$E$57,0)))) | CN20: =IF(CN2="Trough",INDEX($M$55:$M$57,MATCH(CN2,$E$55:$E$57,0)),IF(CN2="Shoulder",INDEX($M$55:$M$57,MATCH(CN2,$E$55:$E$57,0)),INDEX($M$55:$M$57,MATCH(CN2,$E$55:$E$57,0)))) | CO20: =IF(CO2="Trough",INDEX($M$55:$M$57,MATCH(CO2,$E$55:$E$57,0)),IF(CO2="Shoulder",INDEX($M$55:$M$57,MATCH(CO2,$E$55:$E$57,0)),INDEX($M$55:$M$57,MATCH(CO2,$E$55:$E$57,0)))) | CP20: =IF(CP2="Trough",INDEX($M$55:$M$57,MATCH(CP2,$E$55:$E$57,0)),IF(CP2="Shoulder",INDEX($M$55:$M$57,MATCH(CP2,$E$55:$E$57,0)),INDEX($M$55:$M$57,MATCH(CP2,$E$55:$E$57,0)))) | CQ20: =IF(CQ2="Trough",INDEX($M$55:$M$57,MATCH(CQ2,$E$55:$E$57,0)),IF(CQ2="Shoulder",INDEX($M$55:$M$57,MATCH(CQ2,$E$55:$E$57,0)),INDEX($M$55:$M$57,MATCH(CQ2,$E$55:$E$57,0)))) | ... CU20: =IF(CU2="Trough",INDEX($M$55:$M$57,MATCH(CU2,$E$55:$E$57,0)),IF(CU2="Shoulder",INDEX($M$55:$M$57,MATCH(CU2,$E$55:$E$57,0)),INDEX($M$55:$M$57,MATCH(CU2,$E$55:$E$57,0)))) | CV20: =IF(CV2="Trough",INDEX($N$55:$N$57,MATCH(CV2,$E$55:$E$57,0)),IF(CV2="Shoulder",INDEX($N$55:$N$57,MATCH(CV2,$E$55:$E$57,0)),INDEX($N$55:$N$57,MATCH(CV2,$E$55:$E$57,0)))) | CW20: =IF(CW2="Trough",INDEX($N$55:$N$57,MATCH(CW2,$E$55:$E$57,0)),IF(CW2="Shoulder",INDEX($N$55:$N$57,MATCH(CW2,$E$55:$E$57,0)),INDEX($N$55:$N$57,MATCH(CW2,$E$55:$E$57,0)))) | CX20: =IF(CX2="Trough",INDEX($N$55:$N$57,MATCH(CX2,$E$55:$E$57,0)),IF(CX2="Shoulder",INDEX($N$55:$N$57,MATCH(CX2,$E$55:$E$57,0)),INDEX($N$55:$N$57,MATCH(CX2,$E$55:$E$57,0)))) | CY20: =IF(CY2="Trough",INDEX($N$55:$N$57,MATCH(CY2,$E$55:$E$57,0)),IF(CY2="Shoulder",INDEX($N$55:$N$57,MATCH(CY2,$E$55:$E$57,0)),INDEX($N$55:$N$57,MATCH(CY2,$E$55:$E$57,0)))) | CZ20: =IF(CZ2="Trough",INDEX($N$55:$N$57,MATCH(CZ2,$E$55:$E$57,0)),IF(CZ2="Shoulder",INDEX($N$55:$N$57,MATCH(CZ2,$E$55:$E$57,0)),INDEX($N$55:$N$57,MATCH(CZ2,$E$55:$E$57,0)))) | DA20: =IF(DA2="Trough",INDEX($N$55:$N$57,MATCH(DA2,$E$55:$E$57,0)),IF(DA2="Shoulder",INDEX($N$55:$N$57,MATCH(DA2,$E$55:$E$57,0)),INDEX($N$55:$N$57,MATCH(DA2,$E$55:$E$57,0)))) | DB20: =IF(DB2="Trough",INDEX($N$55:$N$57,MATCH(DB2,$E$55:$E$57,0)),IF(DB2="Shoulder",INDEX($N$55:$N$57,MATCH(DB2,$E$55:$E$57,0)),INDEX($N$55:$N$57,MATCH(DB2,$E$55:$E$57,0)))) | DC20: =IF(DC2="Trough",INDEX($N$55:$N$57,MATCH(DC2,$E$55:$E$57,0)),IF(DC2="Shoulder",INDEX($N$55:$N$57,MATCH(DC2,$E$55:$E$57,0)),INDEX($N$55:$N$57,MATCH(DC2,$E$55:$E$57,0)))) | ... DG20: =IF(DG2="Trough",INDEX($N$55:$N$57,MATCH(DG2,$E$55:$E$57,0)),IF(DG2="Shoulder",INDEX($N$55:$N$57,MATCH(DG2,$E$55:$E$57,0)),INDEX($N$55:$N$57,MATCH(DG2,$E$55:$E$57,0))))
C21: Subtrctions | F21: =+IF(F17<E17,F17-E17, 0) | G21: =+IF(G17<F17,G17-F17, 0) | H21: =+IF(H17<G17,H17-G17, 0) | I21: =+IF(I17<H17,I17-H17, 0) | J21: =+IF(J17<I17,J17-I17, 0) | K21: =+IF(K17<J17,K17-J17, 0) | L21: =+IF(L17<K17,L17-K17, 0) | M21: =+IF(M17<L17,M17-L17, 0) | ... P21: =+IF(P17<O17,P17-O17, 0) | Q21: -4 | R21: -2 | S21: -6 | T21: -4 | U21: -7 | V21: -9 | W21: -1 | X21: -3 | Y21: -5 | Z21: -14 | AA21: -18 | AB21: -7 | AC21: -4 | AD21: -2 | AE21: -8 | AF21: -3 | AG21: -11 | AH21: -1 | AI21: -2 | AJ21: -6 | AK21: -3 | AL21: -10 | AM21: -26 | AN21: -11 | AO21: -7 | AP21: -8 | AQ21: -6 | AR21: -6 | AS21: -6 | AT21: -2 | AU21: -2 | AV21: -6 | AW21: -6 | AX21: =+ROUNDUP(AW17*AW42, 0) | AY21: =+ROUNDUP(AX17*AX42, 0) | AZ21: =+ROUNDUP(AY17*AY42, 0) | BA21: =+ROUNDUP(AZ17*AZ42, 0) | BB21: =+ROUNDUP(BA17*BA42, 0) | BC21: =+ROUNDUP(BB17*BB42, 0) | BD21: =+ROUNDUP(BC17*BC42, 0) | BE21: =+ROUNDUP(BD17*BD42, 0) | ... DG21: =+ROUNDUP(DF17*DF42, 0)
C22: # of Sessions | P22: 21 | Q22: 22 | R22: 20 | S22: 16 | T22: 25 | U22: 22 | V22: 23 | W22: 70 | X22: 110 | Y22: 114 | Z22: 73 | AA22: 31 | AB22: 34 | AC22: 56 | AD22: 36 | AE22: 49 | AF22: 76 | AG22: 45 | AH22: 118 | AI22: 169 | AJ22: 125 | AK22: 173 | AL22: 90 | AM22: 50 | AN22: 56 | AO22: 66 | AP22: 73 | AQ22: 37 | AR22: 62 | AS22: 51 | AT22: 120 | AU22: 163 | AV22: 240 | AW22: 275 | AX22: =+AVERAGE(AU22:AW22) | AY22: =+(AX22/AX26)*AY26 | AZ22: =+(AY22/AY26)*AZ26 | BA22: =+(AZ22/AZ26)*BA26 | BB22: =+(BA22/BA26)*BB26 | BC22: =+(BB22/BB26)*BC26 | BD22: =+(BC22/BC26)*BD26 | BE22: =+(BD22/BD26)*BE26 | BF22: =+(BE22/BE26)*BF26 | ... DG22: =+(DF22/DF26)*DG26
B23: Coverage
B24: 125 | C24: Billing Days | E24: =NETWORKDAYS(D4+1,E4,Holidays!$B$3:$B$62) | F24: =NETWORKDAYS(E4+1,F4,Holidays!$B$3:$B$62) | G24: =NETWORKDAYS(F4+1,G4,Holidays!$B$3:$B$62) | H24: =NETWORKDAYS(G4+1,H4,Holidays!$B$3:$B$62) | I24: =NETWORKDAYS(H4+1,I4,Holidays!$B$3:$B$62) | J24: =NETWORKDAYS(I4+1,J4,Holidays!$B$3:$B$62) | K24: =NETWORKDAYS(J4+1,K4,Holidays!$B$3:$B$62) | L24: =NETWORKDAYS(K4+1,L4,Holidays!$B$3:$B$62) | ... DG24: =NETWORKDAYS(DF4+1,DG4,Holidays!$B$3:$B$62)
C25: Hours / Day / Student | E25: =+E26/E24/E17 | F25: =+F26/F24/F17 | G25: =+G26/G24/G17 | H25: =+H26/H24/H17 | I25: =+I26/I24/I17 | J25: =+J26/J24/J17 | K25: =+K26/K24/K17 | L25: =+L26/L24/L17 | ... AW25: =+AW26/AW24/AW17 | AX25: =+AL25 | AY25: =+AM25 | AZ25: =+AN25 | BA25: =+AO25 | BB25: =+AP25 | BC25: =+AQ25 | BD25: =+AR25 | BE25: =+AS25 | ... DG25: =+CU25
C26: Total Bill Hours | E26: 1 | F26: 1 | G26: 1 | H26: 1 | I26: 1 | J26: 1 | K26: 7.5 | L26: =20.5 | M26: 57.25 | N26: 31 | O26: 15 | P26: =+SUM(P28:P32) | Q26: =+SUM(Q28:Q32) | R26: =+SUM(R28:R32) | S26: =+SUM(S28:S32) | T26: =+SUM(T28:T32) | U26: =+SUM(U28:U32) | V26: =+SUM(V28:V32) | W26: =+SUM(W28:W32) | ... AW26: =+SUM(AW28:AW32) | AX26: =+(AX17*AX24*AX25) | AY26: =+(AY17*AY24*AY25) | AZ26: =+(AZ17*AZ24*AZ25) | BA26: =+(BA17*BA24*BA25) | BB26: =+(BB17*BB24*BB25) | BC26: =+(BC17*BC24*BC25) | BD26: =+(BD17*BD24*BD25) | BE26: =+(BE17*BE24*BE25) | ... DG26: =+(DG17*DG24*DG25)
C27: River Hours | L27: 3.75 | M27: 14.75 | N27: 13.5 | O27: 14 | P27: 14 | Q27: 14 | R27: 5.5 | S27: 4.5 | T27: 5 | U27: 25.75 | V27: 11.75 | W27: 0 | X27: 0 | Y27: 0 | Z27: 0 | AA27: 0 | AB27: 0 | AC27: 0 | AD27: 0 | AE27: 0 | AF27: 0 | AG27: 0 | AH27: 0 | AI27: 0 | AJ27: 0 | AK27: 0 | AL27: 0 | AM27: 0 | AN27: 0 | AO27: 0 | AP27: 0 | AQ27: 0 | AR27: 0 | AS27: 0 | AT27: 0 | AU27: 0 | AV27: 0 | AW27: 0 | AX27: 0 | AY27: =AX27 | AZ27: =AY27 | BA27: =AZ27 | BB27: =BA27 | BC27: =BB27 | BD27: =BC27 | BE27: =BD27 | BF27: =BE27 | ... DG27: =DF27
C28: Total Tutoring Hours | P28: 21.5 | Q28: =8.25+5 | R28: 18.25 | S28: 16.25 | T28: 37 | U28: 40.75 | V28: 22 | W28: 56.25 | X28: 60 | Y28: 58.5 | Z28: 47.75 | AA28: 21.75 | AB28: 22.25 | AC28: 36 | AD28: 25.75 | AE28: 32 | AF28: 27.5 | AG28: 14 | AH28: 15.5 | AI28: 14 | AJ28: 4.75 | AK28: 2.25 | AL28: 10 | AM28: 8 | AN28: 4.25 | AO28: 13 | AP28: 20.5 | AQ28: 5 | AR28: 3.75 | AS28: 0 | AT28: 2.25 | AU28: 11.25 | AV28: 19.25 | AW28: 24.5 | AX28: =+IFERROR(AX$26*(AL28/AL$26), 0) | AY28: =+IFERROR(AY$26*(AM28/AM$26), 0) | AZ28: =+IFERROR(AZ$26*(AN28/AN$26), 0) | BA28: =+IFERROR(BA$26*(AO28/AO$26), 0) | BB28: =+IFERROR(BB$26*(AP28/AP$26), 0) | BC28: =+IFERROR(BC$26*(AQ28/AQ$26), 0) | BD28: =+IFERROR(BD$26*(AR28/AR$26), 0) | BE28: =+IFERROR(BE$26*(AS28/AS$26), 0) | ... DG28: =+IFERROR(DG$26*(CU28/CU$26), 0)
C29: Total SAT/ACT Prep Hours | P29: 0 | Q29: 0 | R29: 0 | S29: 0 | T29: 0 | U29: 0 | V29: 2.5 | W29: 1 | X29: 25.25 | Y29: 22.5 | Z29: 16.5 | AA29: 10 | AB29: 18.5 | AC29: 35.25 | AD29: 24.5 | AE29: 32.25 | AF29: 60.75 | AG29: 24.5 | AH29: 68.25 | AI29: 126.75 | AJ29: 22 | AK29: 30.5 | AL29: 14 | AM29: 25 | AN29: 46.75 | AO29: 63 | AP29: 74.25 | AQ29: 37 | AR29: 66.75 | AS29: 27.5 | AT29: 67.75 | AU29: 78.25 | AV29: 106 | AW29: 57.75 | AX29: =+IFERROR(AX$26*(AL29/AL$26), 0) | AY29: =+IFERROR(AY$26*(AM29/AM$26), 0) | AZ29: =+IFERROR(AZ$26*(AN29/AN$26), 0) | BA29: =+IFERROR(BA$26*(AO29/AO$26), 0) | BB29: =+IFERROR(BB$26*(AP29/AP$26), 0) | BC29: =+IFERROR(BC$26*(AQ29/AQ$26), 0) | BD29: =+IFERROR(BD$26*(AR29/AR$26), 0) | BE29: =+IFERROR(BE$26*(AS29/AS$26), 0) | ... DG29: =+IFERROR(DG$26*(CU29/CU$26), 0)
C30: Total Resume Review | AI30: 12.25 | AJ30: 15.25 | AK30: 21.5 | AL30: 1.75 | AM30: 0 | AN30: 0 | AO30: 3.75 | AR30: 2.25 | AS30: 5.5 | AT30: 8.75 | AU30: 12.25 | AV30: 16.75 | AW30: =17+1.25 | AX30: =+IFERROR(AX$26*(AL30/AL$26), 0) | AY30: =+IFERROR(AY$26*(AM30/AM$26), 0) | AZ30: =+IFERROR(AZ$26*(AN30/AN$26), 0) | BA30: =+IFERROR(BA$26*(AO30/AO$26), 0) | BB30: =+IFERROR(BB$26*(AP30/AP$26), 0) | BC30: =+IFERROR(BC$26*(AQ30/AQ$26), 0) | BD30: =+IFERROR(BD$26*(AR30/AR$26), 0) | BE30: =+IFERROR(BE$26*(AS30/AS$26), 0) | ... DG30: =+IFERROR(DG$26*(CU30/CU$26), 0)
C31: Total College Service Hours | P31: 3 | Q31: 0 | R31: 0 | S31: 1 | T31: 0 | U31: 1.25 | V31: 7.25 | W31: 27 | X31: 45.25 | Y31: 55.25 | Z31: 17.75 | AA31: 0.75 | AB31: 3.25 | AC31: 2.25 | AD31: 4 | AE31: 0.5 | AF31: 1.25 | AG31: 20 | AH31: 52 | AI31: 68.75 | AJ31: 101.25 | AK31: 157.5 | AL31: 93 | AM31: 29.75 | AN31: =15+9.25+15.25 | AO31: 19.25 | AP31: 5.75 | AQ31: 4.75 | AR31: 3 | AS31: 30 | AT31: 61 | AU31: 82.75 | AV31: 117.25 | AW31: 207.5 | AX31: =+IFERROR(AX$26*(AL31/AL$26), 0)-50 | AY31: =+IFERROR(AY$26*(AM31/AM$26), 0) | AZ31: =+IFERROR(AZ$26*(AN31/AN$26), 0) | BA31: =+IFERROR(BA$26*(AO31/AO$26), 0) | BB31: =+IFERROR(BB$26*(AP31/AP$26), 0) | BC31: =+IFERROR(BC$26*(AQ31/AQ$26), 0) | BD31: =+IFERROR(BD$26*(AR31/AR$26), 0) | BE31: =+IFERROR(BE$26*(AS31/AS$26), 0) | BF31: =+IFERROR(BF$26*(AT31/AT$26), 0) | ... DG31: =+IFERROR(DG$26*(CU31/CU$26), 0)
C32: Total Dance Hours | P32: 1.83 | Q32: 8 | R32: 2.75 | S32: 1 | T32: 5.25 | U32: 0 | V32: 0 | W32: 0 | X32: 0 | Y32: 0 | Z32: 2 | AA32: 2 | AB32: 1 | AC32: 1 | AD32: 6 | AE32: 5 | AF32: 0 | AG32: 1 | AH32: 0 | AI32: 0 | AJ32: 0 | AK32: 0 | AL32: 0 | AM32: 0 | AN32: 3 | AO32: 2 | AQ32: 1 | AX32: =+IFERROR(AX$26*(AL32/AL$26), 0) | AY32: =+IFERROR(AY$26*(AM32/AM$26), 0) | AZ32: =+IFERROR(AZ$26*(AN32/AN$26), 0) | BA32: =+IFERROR(BA$26*(AO32/AO$26), 0) | BB32: =+IFERROR(BB$26*(AP32/AP$26), 0) | BC32: =+IFERROR(BC$26*(AQ32/AQ$26), 0) | BD32: =+IFERROR(BD$26*(AR32/AR$26), 0) | BE32: =+IFERROR(BE$26*(AS32/AS$26), 0) | ... DG32: =+IFERROR(DG$26*(CU32/CU$26), 0)
C33: Subcontracted Hours | AW33: 105 | AX33: =+AX30+(SUM(AX28:AX29,AX31)/3) | AY33: =+AY30+(SUM(AY28:AY29,AY31)/3) | AZ33: =+AZ30+(SUM(AZ28:AZ29,AZ31)/3) | BA33: =+BA30+(SUM(BA28:BA29,BA31)/3) | BB33: =+BB30+(SUM(BB28:BB29,BB31)/3) | BC33: =+BC30+(SUM(BC28:BC29,BC31)/3) | BD33: =+BD30+(SUM(BD28:BD29,BD31)/3) | BE33: =+BE30+(SUM(BE28:BE29,BE31)/3) | ... DG33: =+DG30+(SUM(DG28:DG29,DG31)/3)
C34: Owner Hours | AW34: =+AW26-AW33 | AX34: =+AX26-AX33 | AY34: =+AY26-AY33 | AZ34: =+AZ26-AZ33 | BA34: =+BA26-BA33 | BB34: =+BB26-BB33 | BC34: =+BC26-BC33 | BD34: =+BD26-BD33 | ... DG34: =+DG26-DG33
C35: Realized / Effective Bill Rate | E35: =+E14/(E26+E27) | F35: =+F14/(F26+F27) | G35: =+G14/(G26+G27) | H35: =+H14/(H26+H27) | I35: =+I14/(I26+I27) | J35: =+J14/(J26+J27) | K35: =+K14/(K26+K27) | L35: =+L14/(L26+L27) | ... O35: =+O14/(O26+O27) | P35: =+P14/(P26) | Q35: =+Q14/(Q26) | R35: =+R14/(R26) | S35: =+S14/(S26+SUM(Q27:S27)) | T35: =+T14/(T26) | U35: =+U14/(U26) | V35: =+V14/(V26+(SUM($T$27:$V$27)/2)) | W35: =+W14/(W26+(SUM($T$27:$V$27)/2)) | X35: =+X14/(X26) | Y35: =+Y14/(Y26) | Z35: =+Z14/(Z26) | AA35: =+AA14/(AA26) | AB35: =+AB14/(AB26) | AC35: =+AC14/(AC26) | AD35: =+AD14/(AD26) | AE35: =+AE14/(AE26) | ... DG35: =+DG14/(DG26)
C36: Tutoring Bill Rate | P36: =+(P7-(P32*60))/P28 | Q36: =+(Q7-(Q32*60))/Q28 | R36: =+(R7-(R32*60))/R28 | S36: =+(S7-(S32*60))/S28 | T36: =+(T7-(T32*60))/T28 | U36: =+(U7-(U32*60))/U28 | V36: =+(V7-(V32*60))/V28 | W36: =+(W7-(W32*60))/W28 | ... AM36: =+(AM7-(AM32*60))/AM28 | AN36: =+IFERROR((AN7-(AN32*60))/AN28, 0) | AO36: =+IFERROR((AO7-(AO32*60))/AO28, 0) | AP36: =+IFERROR((AP7-(AP32*60))/AP28, 0) | AQ36: =+IFERROR((AQ7-(AQ32*60))/AQ28, 0) | AR36: =+IFERROR((AR7-(AR32*60))/AR28, 0) | AS36: =+IFERROR((AS7-(AS32*60))/AS28, 0) | AT36: =+IFERROR((AT7-(AT32*60))/AT28, 0) | AU36: =+IFERROR((AU7-(AU32*60))/AU28, 0) | ... AW36: =+IFERROR((AW7-(AW32*60))/AW28, 0) | AX36: 75 | AY36: =+AX36 | AZ36: =+AY36 | BA36: =+AZ36 | BB36: =+BA36 | BC36: =+BB36 | BD36: =+BC36 | BE36: =+BD36 | BF36: =+BE36 | ... DG36: =+DF36
C37: SAT/ACT Bill Rate | P37: =+IFERROR(P8/P29, 0) | Q37: =+IFERROR(Q8/Q29, 0) | R37: =+IFERROR(R8/R29, 0) | S37: =+IFERROR(S8/S29, 0) | T37: =+IFERROR(T8/T29, 0) | U37: =+IFERROR(U8/U29, 0) | V37: =+IFERROR(V8/V29, 0) | W37: =+IFERROR(W8/W29, 0) | ... AW37: =+IFERROR(AW8/AW29, 0) | AX37: 75 | AY37: =+AX37 | AZ37: =+AY37 | BA37: =+AZ37 | BB37: =+BA37 | BC37: =+BB37 | BD37: =+BC37 | BE37: =+BD37 | BF37: =+BE37 | ... DG37: =+DF37
C38: Resume Review Bill Rate | P38: =+IFERROR(P9/P30, 0) | Q38: =+IFERROR(Q9/Q30, 0) | R38: =+IFERROR(R9/R30, 0) | S38: =+IFERROR(S9/S30, 0) | T38: =+IFERROR(T9/T30, 0) | U38: =+IFERROR(U9/U30, 0) | V38: =+IFERROR(V9/V30, 0) | W38: =+IFERROR(W9/W30, 0) | ... AW38: =+IFERROR(AW9/AW30, 0) | AX38: 135 | AY38: =+AX38 | AZ38: =+AY38 | BA38: =+AZ38 | BB38: =+BA38 | BC38: =+BB38 | BD38: =+BC38 | BE38: =+BD38 | BF38: =+BE38 | ... DG38: =+DF38
C39: College Services Bill Rate | P39: =IFERROR(P10/P31, 0) | Q39: =IFERROR(Q10/Q31, 0) | R39: =IFERROR(R10/R31, 0) | S39: =IFERROR(S10/S31, 0) | T39: =IFERROR(T10/T31, 0) | U39: =IFERROR(U10/U31, 0) | V39: =IFERROR(V10/V31, 0) | W39: =IFERROR(W10/W31, 0) | ... AW39: =IFERROR(AW10/AW31, 0) | AX39: 135 | AY39: =+AX39 | AZ39: =+AY39 | BA39: =+AZ39 | BB39: =+BA39 | BC39: =+BB39 | BD39: =+BC39 | BE39: =+BD39 | BF39: =+BE39 | ... DG39: =+DF39
C40: Dance Bill Rate | P40: =+IFERROR((P32*60)/P32, 0) | Q40: =+IFERROR((Q32*60)/Q32, 0) | R40: =+IFERROR((R32*60)/R32, 0) | S40: =+IFERROR((S32*60)/S32, 0) | T40: =+IFERROR((T32*60)/T32, 0) | U40: =+IFERROR((U32*60)/U32, 0) | V40: =+IFERROR((V32*60)/V32, 0) | W40: =+IFERROR((W32*60)/W32, 0) | ... AW40: =+IFERROR((AW32*60)/AW32, 0) | AX40: 60 | AY40: =+AX40 | AZ40: =+AY40 | BA40: =+AZ40 | BB40: =+BA40 | BC40: =+BB40 | BD40: =+BC40 | BE40: =+BD40 | BF40: =+BE40 | ... DG40: =+DF40
C42: T6M Avg Monthly Attrition | L42: =+AVERAGE(F21:L21)/AVERAGE(F17:L17) | M42: =+AVERAGE(G21:M21)/AVERAGE(G17:M17) | N42: =+AVERAGE(H21:N21)/AVERAGE(H17:N17) | O42: =+AVERAGE(I21:O21)/AVERAGE(I17:O17) | P42: =+AVERAGE(J21:P21)/AVERAGE(J17:P17) | Q42: =+AVERAGE(K21:Q21)/AVERAGE(K17:Q17) | R42: =+AVERAGE(L21:R21)/AVERAGE(L17:R17) | S42: =+AVERAGE(M21:S21)/AVERAGE(M17:S17) | ... AW42: =+AVERAGE(AQ21:AW21)/AVERAGE(AQ17:AW17) | AX42: =+AL42 | AY42: =+AM42 | AZ42: =+AN42+0.05 | BA42: =+AO42+0.05 | BB42: =+AP42+0.05 | BC42: =+AQ42+0.05 | BD42: =+AR42+0.05 | BE42: =+AS42+0.05 | BF42: =+AT42+0.05 | BG42: =+AU42+0.05 | ... BK42: =+AY42+0.05 | BL42: =+AZ42 | BM42: =+BA42 | BN42: =+BB42 | BO42: =+BC42 | BP42: =+BD42 | BQ42: =+BE42 | BR42: =+BF42 | BS42: =+BG42 | ... DG42: =+CU42
C43: Implied Tenure | L43: =1/-L42 | M43: =1/-M42 | N43: =1/-N42 | O43: =1/-O42 | P43: =1/-P42 | Q43: =1/-Q42 | R43: =1/-R42 | S43: =1/-S42 | ... DG43: =1/-DG42
C44: Average Revenue | L44: =+L14/AVERAGE(G17:L17) | M44: =+M14/AVERAGE(H17:M17) | N44: =+N14/AVERAGE(I17:N17) | O44: =+O14/AVERAGE(J17:O17) | P44: =+P14/AVERAGE(K17:P17) | Q44: =+Q14/AVERAGE(L17:Q17) | R44: =+R14/AVERAGE(M17:R17) | S44: =+S14/AVERAGE(N17:S17) | ... DG44: =+DG14/AVERAGE(DB17:DG17)
C45: Lifetime Revenue | L45: =+L44*L43 | M45: =+M44*M43 | N45: =+N44*N43 | O45: =+O44*O43 | P45: =+P44*P43 | Q45: =+Q44*Q43 | R45: =+R44*R43 | S45: =+S44*S43 | ... DG45: =+DG44*DG43
C46: GM% | L46: =+L99/L14 | M46: =+M99/M14 | N46: =+N99/N14 | O46: =+O99/O14 | P46: =+P99/P14 | Q46: =+Q99/Q14 | R46: =+R99/R14 | S46: =+S99/S14 | ... AM46: =+AM99/AM14 | AN46: =+AN66/AN14 | AO46: =+AO66/AO14 | AP46: =+AP66/AP14 | AQ46: =+AQ66/AQ14 | AR46: =+AR66/AR14 | AS46: =+AS66/AS14 | AT46: =+AT66/AT14 | AU46: =+AU66/AU14 | ... DG46: =+DG66/DG14
C47: T3M LTV | L47: =+AVERAGE(L46*L45,K46*K45, J46*J45) | M47: =+AVERAGE(M46*M45,L46*L45, K46*K45) | N47: =+AVERAGE(N46*N45,M46*M45, L46*L45) | O47: =+AVERAGE(O46*O45,N46*N45, M46*M45) | P47: =+AVERAGE(P46*P45,O46*O45, N46*N45) | Q47: =+AVERAGE(Q46*Q45,P46*P45, O46*O45) | R47: =+AVERAGE(R46*R45,Q46*Q45, P46*P45) | S47: =+AVERAGE(S46*S45,R46*R45, Q46*Q45) | ... DG47: =+AVERAGE(DG46*DG45,DF46*DF45, DE46*DE45)
C48: T3M CAC | L48: =+AVERAGE(J102:L102) | M48: =+AVERAGE(K102:M102) | N48: =+AVERAGE(L102:N102) | O48: =+AVERAGE(M102:O102) | P48: =+AVERAGE(N102:P102) | Q48: =+AVERAGE(O102:Q102) | R48: =+AVERAGE(P102:R102) | S48: =+AVERAGE(Q102:S102) | ... DG48: =+AVERAGE(DE102:DG102)
C49: LTV/CAC | L49: =+L47/L48 | M49: =+M47/M48 | N49: =+N47/N48 | O49: =+O47/O48 | P49: =+P47/P48 | Q49: =+Q47/Q48 | R49: =+R47/R48 | S49: =+S47/S48 | ... DG49: =+DG47/DG48
C50: Payback | L50: =+L48/(L44*L46) | M50: =+M48/(M44*M46) | N50: =+N48/(N44*N46) | O50: =+O48/(O44*O46) | P50: =+P48/(P44*P46) | Q50: =+Q48/(Q44*Q46) | R50: =+R48/(R44*R46) | S50: =+S48/(S44*S46) | ... DG50: =+DG48/(DG44*DG46)
C51: Utilization % | E51: =+E25/8 | F51: =+F25/8 | G51: =+G25/8 | H51: =+H25/8 | I51: =+I25/8 | J51: =+J25/8 | K51: =+K25/8 | L51: =+L25/8 | ... DG51: =+DG25/8
F53: 2022 | G53: 2023 | H53: 2024 | I53: 2025 | J53: 2026 | K53: 2027 | L53: 2028 | M53: 2029 | N53: 2030 | Q53: 2022 | R53: 2023 | S53: 2024 | T53: 2025 | U53: 2026 | V53: 2027 | W53: 2028 | X53: 2028 | Y53: 2028 | Z53: 2029 | AA53: 2029
E54: Average | F54: =ROUNDUP(AVERAGE(F55:F57), 0) | G54: =ROUNDUP(AVERAGE(G55:G57), 0) | H54: =ROUNDUP(AVERAGE(H55:H57), 0) | I54: =ROUNDUP(AVERAGE(I55:I57), 0) | J54: =ROUNDUP(AVERAGE(J55:J57), 0) | K54: =ROUNDUP(AVERAGE(K55:K57), 0) | L54: =ROUNDUP(AVERAGE(L55:L57), 0) | M54: =ROUNDUP(AVERAGE(M55:M57), 0) | N54: =ROUNDUP(AVERAGE(N55:N57), 0) | P54: Average | Q54: =ROUNDUP(AVERAGE(Q55:Q57), 0) | R54: =ROUNDUP(AVERAGE(R55:R57), 0) | S54: =ROUNDUP(AVERAGE(S55:S57), 0) | T54: =ROUNDUP(AVERAGE(T55:T57), 0) | U54: =ROUNDUP(AVERAGE(U55:U57), 0) | V54: =ROUNDUP(AVERAGE(V55:V57), 0) | W54: =ROUNDUP(AVERAGE(W55:W57), 0) | X54: =ROUNDUP(AVERAGE(X55:X57), 0) | ... AA54: =ROUNDUP(AVERAGE(AA55:AA57), 0)
E55: Peak | F55: 3 | G55: 3 | H55: 10 | I55: =+H55*1.4 | J55: =+I55*1.2 | K55: =+J55*1.4 | L55: =+K55*1.4 | M55: =+L55*1.4 | N55: =+M55*1.4 | P55: Peak | Q55: =AVERAGEIFS($E$25:$DG$25, $H$2:$DJ$2,$E$55, $H$1:$DJ$1, Q53) | R55: =AVERAGEIFS($E$25:$DG$25, $H$2:$DJ$2,$E$55, $H$1:$DJ$1, R53) | S55: =AVERAGEIFS($E$25:$DG$25, $H$2:$DJ$2,$E$55, $H$1:$DJ$1, S53) | T55: =AVERAGEIFS($E$25:$DG$25, $H$2:$DJ$2,$E$55, $H$1:$DJ$1, T53) | U55: =AVERAGEIFS($E$25:$DG$25, $H$2:$DJ$2,$E$55, $H$1:$DJ$1, U53) | V55: =AVERAGEIFS($E$25:$DG$25, $H$2:$DJ$2,$E$55, $H$1:$DJ$1, V53) | W55: =AVERAGEIFS($E$25:$DG$25, $H$2:$DJ$2,$E$55, $H$1:$DJ$1, W53) | X55: =AVERAGEIFS($E$25:$DG$25, $H$2:$DJ$2,$E$55, $H$1:$DJ$1, X53) | ... AA55: =AVERAGEIFS($E$25:$DG$25, $H$2:$DJ$2,$E$55, $H$1:$DJ$1, AA53)
E56: Shoulder | F56: 5 | G56: =+F56+1 | H56: 7 | I56: =+H56*1.4 | J56: =+I56*1.2 | K56: =+J56*1.4 | L56: =+K56*1.4 | M56: =+L56*1.4 | N56: =+M56*1.4 | P56: Shoulder | Q56: =+AVERAGEIFS($E$25:$DG$25, $H$2:$DJ$2,$E$56, $H$1:$DJ$1, Q53) | R56: =+AVERAGEIFS($E$25:$DG$25, $H$2:$DJ$2,$E$56, $H$1:$DJ$1, R53) | S56: =+AVERAGEIFS($E$25:$DG$25, $H$2:$DJ$2,$E$56, $H$1:$DJ$1, S53) | T56: =+AVERAGEIFS($E$25:$DG$25, $H$2:$DJ$2,$E$56, $H$1:$DJ$1, T53) | U56: =+AVERAGEIFS($E$25:$DG$25, $H$2:$DJ$2,$E$56, $H$1:$DJ$1, U53) | V56: =+AVERAGEIFS($E$25:$DG$25, $H$2:$DJ$2,$E$56, $H$1:$DJ$1, V53) | W56: =+AVERAGEIFS($E$25:$DG$25, $H$2:$DJ$2,$E$56, $H$1:$DJ$1, W53) | X56: =+AVERAGEIFS($E$25:$DG$25, $H$2:$DJ$2,$E$56, $H$1:$DJ$1, X53) | ... AA56: =+AVERAGEIFS($E$25:$DG$25, $H$2:$DJ$2,$E$56, $H$1:$DJ$1, AA53)
E57: Trough | F57: 1 | G57: 1 | H57: 4 | I57: =+H57*1.4 | J57: =+I57*1.2 | K57: =+J57*1.4 | L57: =+K57*1.4 | M57: =+L57*1.4 | N57: =+M57*1.4 | P57: Trough | Q57: =AVERAGEIFS($E$25:$DG$25, $H$2:$DJ$2,$E$57, $H$1:$DJ$1, Q53) | R57: =AVERAGEIFS($E$25:$DG$25, $H$2:$DJ$2,$E$57, $H$1:$DJ$1, R53) | S57: =AVERAGEIFS($E$25:$DG$25, $H$2:$DJ$2,$E$57, $H$1:$DJ$1, S53) | T57: =AVERAGEIFS($E$25:$DG$25, $H$2:$DJ$2,$E$57, $H$1:$DJ$1, T53) | U57: =AVERAGEIFS($E$25:$DG$25, $H$2:$DJ$2,$E$57, $H$1:$DJ$1, U53) | V57: =AVERAGEIFS($E$25:$DG$25, $H$2:$DJ$2,$E$57, $H$1:$DJ$1, V53) | W57: =AVERAGEIFS($E$25:$DG$25, $H$2:$DJ$2,$E$57, $H$1:$DJ$1, W53) | X57: =AVERAGEIFS($E$25:$DG$25, $H$2:$DJ$2,$E$57, $H$1:$DJ$1, X53) | ... AA57: =AVERAGEIFS($E$25:$DG$25, $H$2:$DJ$2,$E$57, $H$1:$DJ$1, AA53)
E58: Trough | F58: =F57/F54-1 | G58: =G57/G54-1 | H58: =H57/H54-1 | I58: =I57/I54-1 | J58: =J57/J54-1 | K58: =K57/K54-1 | L58: =L57/L54-1 | M58: =M57/M54-1 | N58: =N57/N54-1 | P58: Trough | Q58: =Q57/Q54-1 | R58: =R57/R54-1 | S58: =S57/S54-1 | T58: =T57/T54-1 | U58: =U57/U54-1 | V58: =V57/V54-1 | W58: =W57/W54-1 | X58: =X57/X54-1 | ... AA58: =AA57/AA54-1
E59: Shoulder | F59: =F56/F54-1 | G59: =G56/G54-1 | H59: =H56/H54-1 | I59: =I56/I54-1 | J59: =J56/J54-1 | K59: =K56/K54-1 | L59: =L56/L54-1 | M59: =M56/M54-1 | N59: =N56/N54-1 | P59: Shoulder | Q59: =Q56/Q54-1 | R59: =R56/R54-1 | S59: =S56/S54-1 | T59: =T56/T54-1 | U59: =U56/U54-1 | V59: =V56/V54-1 | W59: =W56/W54-1 | X59: =X56/X54-1 | ... AA59: =AA56/AA54-1
B62: 50000 Subcontractors
B63: 51000 Subcontractors - Tutors | AH63: 150 | AI63: 740 | AJ63: 817.5 | AK63: 937.5 | AL63: 170 | AN63: 0 | AO63: 450 | AP63: 0 | AQ63: 0 | AR63: 270 | AS63: 0 | AT63: 1042.5 | AU63: 450 | AV63: =3989.94 | AW63: =6135 | AX63: =+'People Plan'!Y20 | AY63: =+'People Plan'!Z20 | AZ63: =+'People Plan'!AA20 | BA63: =+'People Plan'!AB20 | BB63: =+'People Plan'!AC20 | BC63: =+'People Plan'!AD20 | BD63: =+'People Plan'!AE20 | BE63: =+'People Plan'!AF20 | ... DG63: =+'People Plan'!CH20
B64: 51000 Subcontractors - Interns | AH64: 450 | AI64: 150 | AM64: 599 | AN64: 0 | AO64: 0 | AP64: 0 | AQ64: 0 | AR64: 0 | AS64: 0 | AT64: 540 | AU64: 234 | AV64: =86.8 | AW64: =120 | AX64: =+'People Plan'!Y7 | AY64: =+'People Plan'!Z7 | AZ64: =+'People Plan'!AA7 | BA64: =+'People Plan'!AB7 | BB64: =+'People Plan'!AC7 | BC64: =+'People Plan'!AD7 | BD64: =+'People Plan'!AE7 | BE64: =+'People Plan'!AF7 | ... DG64: =+'People Plan'!CH7
B65: Total 50000 Subcontractors | AB65: =SUM(AB63:AB64) | AC65: =SUM(AC63:AC64) | AD65: =SUM(AD63:AD64) | AE65: =SUM(AE63:AE64) | AF65: =SUM(AF63:AF64) | AG65: =SUM(AG63:AG64) | AH65: =SUM(AH63:AH64) | AI65: =SUM(AI63:AI64) | ... AS65: =SUM(AS63:AS64) | AT65: =SUM(AT62:AT64) | AU65: =SUM(AU62:AU64) | AV65: =SUM(AV62:AV64) | AW65: =SUM(AW62:AW64) | AX65: =SUM(AX63:AX64) | AY65: =SUM(AY63:AY64) | AZ65: =SUM(AZ63:AZ64) | BA65: =SUM(BA63:BA64) | BB65: =SUM(BB63:BB64) | BC65: =SUM(BC63:BC64) | BD65: =SUM(BD63:BD64) | BE65: =SUM(BE63:BE64) | ... DG65: =SUM(DG63:DG64)
B66: Gross Profit | D66: =(D14)-(0) | E66: =(E14)-(0) | F66: =(F14)-(0) | G66: =(G14)-(0) | H66: =(H14)-(0) | I66: =(I14)-(0) | J66: =(J14)-(0) | K66: =K14 | L66: =L14 | M66: =M14 | N66: =N14 | O66: =O14 | P66: =P14 | Q66: =Q14 | R66: =R14 | ... AA66: =AA14 | AB66: =AB14-AB65 | AC66: =AC14-AC65 | AD66: =AD14-AD65 | AE66: =AE14-AE65 | AF66: =AF14-AF65 | AG66: =AG14-AG65 | AH66: =AH14-AH65 | AI66: =AI14-AI65 | ... DG66: =DG14-DG65
C67: GP % | E67: =+E53/8 | F67: =+F53/8 | G67: =+G53/8 | H67: =+H53/8 | I67: =+I53/8 | J67: =+J53/8 | K67: =+K53/8 | L67: =+L53/8 | ... O67: =+O53/8 | P67: =+P66/#REF! | Q67: =+Q66/#REF! | R67: =+R66/#REF! | S67: =+S66/#REF! | T67: =+T66/#REF! | U67: =+U66/#REF! | V67: =+V66/#REF! | W67: =+W66/#REF! | ... AA67: =+AA66/#REF! | AB67: =+AB66/AB14 | AC67: =+AC66/AC14 | AD67: =+AD66/AD14 | AE67: =+AE66/AE14 | AF67: =+AF66/AF14 | AG67: =+AG66/AG14 | AH67: =+AH66/AH14 | AI67: =+AI66/AI14 | ... DG67: =+DG66/DG14
B69: Expenses
B70: 30000 Sales & Marketing Expenses
B71: 30200 Events/Sponsorships | AC71: 1179.44 | AE71: 2400 | AG71: 665.56 | AH71: 0 | AI71: 0 | AJ71: 0 | AK71: 0 | AL71: 0 | AM71: 0 | AN71: 0 | AO71: 0 | AP71: 0 | AQ71: 0 | AR71: 0 | AS71: 0 | AT71: 0 | AU71: 0 | AV71: 0 | AW71: 0 | AX71: =+IF(AX3<>AW3, SUM(AU71:AW71), 0)*1.1 | AY71: =+IF(AY3<>AX3, SUM(AV71:AX71), 0)*1.1 | AZ71: =+IF(AZ3<>AY3, SUM(AW71:AY71), 0)*1.1 | BA71: =+IF(BA3<>AZ3, SUM(AX71:AZ71), 0)*1.1 | BB71: =+IF(BB3<>BA3, SUM(AY71:BA71), 0)*1.1 | BC71: =+IF(BC3<>BB3, SUM(AZ71:BB71), 0)*1.1 | BD71: =+IF(BD3<>BC3, SUM(BA71:BC71), 0)*1.1 | BE71: =+IF(BE3<>BD3, SUM(BB71:BD71), 0)*1.1 | ... DG71: =+IF(DG3<>DF3, SUM(DD71:DF71), 0)*1.1
B72: Total Sales & Marketing Expenses | P72: =SUM(P71) | Q72: =SUM(Q71) | R72: =SUM(R71) | S72: =SUM(S71) | T72: =SUM(T71) | U72: =SUM(U71) | V72: =SUM(V71) | W72: =SUM(W71) | ... DG72: =SUM(DG71)
B74: 60000 G&A Expenses
B75: 60000 General & Administrative Expenses
B76: Owner Salary | AN76: 1275 | AO76: 4005 | AP76: 4410 | AQ76: 2450 | AR76: 1960 | AS76: 2450 | AT76: 7280 | AU76: 14252.7 | AV76: =9800 | AW76: =14350 | AX76: =+'People Plan'!Z19 | AY76: =+'People Plan'!AA19 | AZ76: =+'People Plan'!AB19 | BA76: =+'People Plan'!AC19 | BB76: =+'People Plan'!AD19 | BC76: =+'People Plan'!AE19 | BD76: =+'People Plan'!AF19 | BE76: =+'People Plan'!AG19 | ... DG76: =+'People Plan'!CI19
B77: Owner Payroll Taxes | AN77: 137.07 | AO77: 435.82 | AP77: 416.3 | AQ77: 187.43 | AR77: 149.94 | AS77: 187.42 | AT77: 150.77 | AU77: 833.44 | AV77: =749.7 | AW77: =1097.77 | AX77: =+AX76*AX81 | AY77: =+AY76*AY81 | AZ77: =+AZ76*AZ81 | BA77: =+BA76*BA81 | BB77: =+BB76*BB81 | BC77: =+BC76*BC81 | BD77: =+BD76*BD81 | BE77: =+BE76*BE81 | ... DG77: =+DG76*DG81
B78: Owner Benefits | AN78: 0 | AO78: 0 | AP78: 0 | AQ78: 0 | AR78: 0 | AS78: 0 | AT78: 0 | AU78: 0 | AV78: 0 | AW78: 0 | AX78: =+AX76*AX82 | AY78: =+AY76*AY82 | AZ78: =+AZ76*AZ82 | BA78: =+BA76*BA82 | BB78: =+BB76*BB82 | BC78: =+BC76*BC82 | BD78: =+BD76*BD82 | BE78: =+BE76*BE82 | ... DG78: =+DG76*DG82
B79: Owner Reimbursements | AN79: 995.35 | AO79: 615 | AP79: 0 | AQ79: 0 | AR79: 0 | AS79: 0 | AT79: 0 | AU79: 0 | AV79: 0 | AW79: 0 | AX79: 0 | AY79: =+AX79 | AZ79: =+AY79 | BA79: =+AZ79 | BB79: =+BA79 | BC79: =+BB79 | BD79: =+BC79 | BE79: =+BD79 | BF79: =+BE79 | ... DG79: =+DF79
B80: Total Owner Payroll Burden | AH80: =SUM(AH76:AH78) | AI80: =SUM(AI76:AI78) | AJ80: =SUM(AJ76:AJ78) | AK80: =SUM(AK76:AK78) | AL80: =SUM(AL76:AL78) | AM80: =SUM(AM76:AM78) | AN80: =SUM(AN76:AN79) | AO80: =SUM(AO76:AO79) | AP80: =SUM(AP76:AP79) | AQ80: =SUM(AQ76:AQ79) | AR80: =SUM(AR76:AR79) | AS80: =SUM(AS76:AS79) | AT80: =SUM(AT76:AT79) | AU80: =SUM(AU76:AU79) | ... DG80: =SUM(DG76:DG79)
C81: Payroll Tax as a % of Salary | AN81: =+AN77/AN76 | AO81: =+AO77/AO76 | AP81: =+AP77/AP76 | AQ81: =+AQ77/AQ76 | AR81: =+AR77/AR76 | AS81: =+AS77/AS76 | AT81: =+AT77/AT76 | AU81: =+AU77/AU76 | ... AW81: =+AW77/AW76 | AX81: 0.0765 | AY81: =+AX81 | AZ81: =+AY81 | BA81: =+AZ81 | BB81: =+BA81 | BC81: =+BB81 | BD81: =+BC81 | BE81: =+BD81 | BF81: =+BE81 | ... DG81: =+DF81
C82: Benefits as a % of Salary | AX82: 0 | AY82: =+AX82 | AZ82: =+AY82 | BA82: =+AZ82 | BB82: =+BA82 | BC82: =+BB82 | BD82: =+BC82 | BE82: =+BD82 | BF82: =+BE82 | ... BW82: =+BV82 | BX82: 0.15 | BY82: =+BX82 | BZ82: =+BY82 | CA82: =+BZ82 | CB82: =+CA82 | CC82: =+CB82 | CD82: =+CC82 | CE82: =+CD82 | CF82: =+CE82 | ... CI82: =+CH82 | CJ82: 0.2 | CK82: =+CJ82 | CL82: =+CK82 | CM82: =+CL82 | CN82: =+CM82 | CO82: =+CN82 | CP82: =+CO82 | CQ82: =+CP82 | CR82: =+CQ82 | ... DG82: =+DF82
B83: 60210 Website Services | Y83: 300 | AA83: 300 | AI83: 0 | AJ83: 0 | AK83: 0 | AL83: 0 | AM83: 0 | AN83: 0 | AO83: 0 | AP83: 0 | AQ83: 0 | AR83: 0 | AS83: 0 | AT83: 0 | AU83: 0 | AV83: 0 | AW83: 0 | AX83: 0 | AY83: =AX83 | AZ83: =AVERAGE(AT83:AY83)*1.2 | BA83: =AZ83 | BB83: =BA83 | BC83: =BB83 | BD83: =BC83 | BE83: =BD83 | BF83: =BE83 | BG83: =BF83 | BH83: =BG83 | ... BK83: =BJ83 | BL83: =AVERAGE(BF83:BK83)*1.2 | BM83: =BL83 | BN83: =BM83 | BO83: =BN83 | BP83: =BO83 | BQ83: =BP83 | BR83: =BQ83 | BS83: =BR83 | BT83: =BS83 | ... BW83: =BV83 | BX83: =AVERAGE(BR83:BW83)*1.2 | BY83: =BX83 | BZ83: =BY83 | CA83: =BZ83 | CB83: =CA83 | CC83: =CB83 | CD83: =CC83 | CE83: =CD83 | CF83: =CE83 | ... CI83: =CH83 | CJ83: =AVERAGE(CD83:CI83)*1.2 | CK83: =CJ83 | CL83: =CK83 | CM83: =CL83 | CN83: =CM83 | CO83: =CN83 | CP83: =CO83 | CQ83: =CP83 | CR83: =CQ83 | ... CU83: =CT83 | CV83: =AVERAGE(CP83:CU83)*1.2 | CW83: =CV83 | CX83: =CW83 | CY83: =CX83 | CZ83: =CY83 | DA83: =CZ83 | DB83: =DA83 | DC83: =DB83 | DD83: =DC83 | ... DG83: =DF83
B84: 60100 Travel | AH84: 13.59 | AI84: 15.71 | AR84: 44.17 | AS84: 49.63 | AT84: 126.3 | AU84: 417.97 | AV84: 0 | AW84: =222.44 | AX84: 75 | AY84: =AX84 | AZ84: =AY84 | BA84: =AZ84 | BB84: =BA84 | BC84: =BB84 | BD84: =BC84 | BE84: =BD84 | BF84: =BE84 | ... DG84: =DF84
B85: 60200 Computer & Software Expenses | D85: =0 | E85: =0 | F85: =0 | G85: =0 | H85: =0 | I85: =0 | J85: 0 | K85: 0 | L85: 12 | M85: 271.2 | N85: 12 | O85: 12 | P85: 12 | Q85: 12 | R85: 12 | S85: 12 | T85: 53 | U85: 156 | V85: 12 | W85: 12 | X85: 240.91 | Y85: 352.91 | Z85: 28.91 | AA85: 28.91 | AB85: 78.91 | AC85: 28.91 | AD85: 86.19 | AE85: 12 | AF85: 154.47 | AG85: 310.12 | AH85: 1251.13 | AI85: 14.81 | AJ85: 76.75 | AK85: 90.81 | AL85: 100.41 | AM85: 107.82 | AN85: 218.17 | AO85: 118.63 | AP85: 118.81 | AQ85: 202.32 | AR85: 241.38 | AS85: 433.68 | AT85: 209.45 | AU85: 336.39 | AV85: =843.04 | AW85: =709.4 | AX85: 150 | AY85: =AX85 | AZ85: =AVERAGE(AT85:AY85)*1.2 | BA85: =AZ85 | BB85: =BA85 | BC85: =BB85 | BD85: =BC85 | BE85: =BD85 | BF85: =BE85 | BG85: =BF85 | BH85: =BG85 | ... BK85: =BJ85 | BL85: =AVERAGE(BF85:BK85)*1.2 | BM85: =BL85 | BN85: =BM85 | BO85: =BN85 | BP85: =BO85 | BQ85: =BP85 | BR85: =BQ85 | BS85: =BR85 | BT85: =BS85 | ... BW85: =BV85 | BX85: =AVERAGE(BR85:BW85)*1.2 | BY85: =BX85 | BZ85: =BY85 | CA85: =BZ85 | CB85: =CA85 | CC85: =CB85 | CD85: =CC85 | CE85: =CD85 | CF85: =CE85 | ... CI85: =CH85 | CJ85: =AVERAGE(CD85:CI85)*1.2 | CK85: =CJ85 | CL85: =CK85 | CM85: =CL85 | CN85: =CM85 | CO85: =CN85 | CP85: =CO85 | CQ85: =CP85 | CR85: =CQ85 | ... CU85: =CT85 | CV85: =AVERAGE(CP85:CU85)*1.2 | CW85: =CV85 | CX85: =CW85 | CY85: =CX85 | CZ85: =CY85 | DA85: =CZ85 | DB85: =DA85 | DC85: =DB85 | DD85: =DC85 | ... DG85: =DF85
B86: 60300 Donations/Gifts | D86: =0 | E86: =0 | F86: =0 | G86: =0 | H86: =0 | I86: =0 | J86: 0 | K86: 0 | L86: 0 | M86: 50 | N86: 250 | O86: 0 | X86: 150 | Z86: 430 | AD86: 50 | AF86: 141.19 | AJ86: 80 | AK86: 65 | AL86: 387.9 | AM86: 45 | AN86: 485 | AO86: 424 | AP86: 152.63 | AR86: 346.05 | AS86: 100 | AT86: 79.04 | AV86: =574.22 | AW86: =150.39 | AX86: 100 | AY86: =AX86 | AZ86: =AY86 | BA86: =AZ86 | BB86: =BA86 | BC86: =BB86 | BD86: =BC86 | BE86: =BD86 | BF86: =BE86 | ... DG86: =DF86
B87: 60400 Fees/Subscriptions | D87: =0 | E87: =0 | F87: =0 | G87: =0 | H87: =0 | I87: =0 | J87: 0 | K87: 0 | L87: 15 | M87: 19 | N87: 0 | O87: 0 | Y87: 13.86 | AI87: 42.58 | AQ87: 0 | AR87: 0 | AS87: 0 | AT87: 0 | AU87: 0 | AV87: 0 | AW87: 0 | AX87: =AVERAGE(AO87:AW87) | AY87: =AX87 | AZ87: =AY87 | BA87: =AZ87 | BB87: =BA87 | BC87: =BB87 | BD87: =BC87 | BE87: =BD87 | BF87: =BE87 | ... DG87: =DF87
B88: 60500 Finance & Accounting | D88: =0 | E88: =0 | F88: =0 | G88: =0 | H88: =0 | I88: =0 | J88: 0 | K88: 0 | L88: 0 | M88: 279.6 | N88: 75 | O88: 75 | P88: 75 | Q88: 75 | S88: 75 | T88: 165 | U88: 225 | V88: 75 | W88: 75 | X88: 225 | Y88: 75 | Z88: 75 | AA88: 225 | AB88: 75 | AC88: 112.5 | AD88: 225 | AE88: 75 | AF88: 75 | AG88: 225 | AH88: 185 | AI88: 207.5 | AJ88: 208.75 | AK88: 350 | AL88: 241.25 | AM88: 140 | AN88: 711.25 | AO88: 412.5 | AP88: 1155.73 | AQ88: 415 | AR88: 356.25 | AS88: 281.25 | AT88: 450 | AU88: 453.75 | AV88: 337.5 | AW88: =581.25 | AX88: =IF(AX3<>AW3, 450, 275)+150 | AY88: =IF(AY3<>AX3, 450, 275) | AZ88: =IF(AZ3<>AY3, 450, 275) | BA88: =IF(BA3<>AZ3, 450, 275) | BB88: =IF(BB3<>BA3, 450, 275) | BC88: =IF(BC3<>BB3, 450, 275) | BD88: =IF(BD3<>BC3, 450, 275) | BE88: =IF(BE3<>BD3, 450, 275) | BF88: =IF(BF3<>BE3, 450, 275) | ... DG88: =IF(DG3<>DF3, 450, 275)
B89: 60600 Bank Fees | D89: =0 | E89: =0 | F89: =0 | G89: =0 | H89: =0 | I89: =0 | J89: 0 | K89: 0 | L89: 0 | M89: 26.86 | N89: 105.23 | O89: 22.43 | P89: 118.13 | Q89: 36.76 | R89: 63.36 | S89: 153.85 | T89: 72.88 | U89: 27.48 | V89: 17.2 | W89: 33.76 | X89: 48.31 | Y89: 29 | Z89: 29 | AD89: 1.75 | AE89: 4.55 | AF89: 3.5 | AH89: 31.6 | AK89: 29 | AP89: =52 | AQ89: 0 | AR89: 0 | AS89: 0 | AT89: 0 | AU89: 0 | AV89: 2 | AW89: =80.44 | AX89: =AVERAGE(AR89:AW89) | AY89: =AX89 | AZ89: =AY89 | BA89: =AZ89 | BB89: =BA89 | BC89: =BB89 | BD89: =BC89 | BE89: =BD89 | BF89: =BE89 | ... DG89: =DF89
B90: 60700 Meals and Entertainment | T90: 22 | AH90: 218.02 | AI90: 57.06 | AJ90: 44.41 | AL90: 837.07 | AN90: 50 | AO90: 251.46 | AR90: 285.65 | AS90: 315.29 | AT90: 326.19 | AU90: 484.06 | AV90: 383.29 | AW90: =677.01 | AX90: =AVERAGE(AR90:AW90) | AY90: =AX90 | AZ90: =AY90 | BA90: =AZ90 | BB90: =BA90 | BC90: =BB90 | BD90: =BC90 | BE90: =BD90 | BF90: =BE90 | ... DG90: =DF90
B91: 60800 QB Fees | D91: 0 | E91: 0 | F91: 0 | G91: 0 | H91: 0 | I91: 0 | J91: 0 | K91: 0 | L91: 0 | M91: 0 | N91: 30 | O91: 52.67 | P91: 30 | Q91: 30 | R91: 30 | S91: 31.99 | T91: 45.38 | U91: 51.04 | V91: 92.49 | W91: 194.71 | X91: 210.47 | Y91: 313.34 | Z91: 205.12 | AA91: 105.16 | AB91: 124.93 | AC91: 156.19 | AD91: 141.67 | AE91: 145.28 | AF91: 173.37 | AG91: 236.32 | AH91: 228.28 | AI91: 404.2 | AJ91: 334.27 | AK91: 523.21 | AL91: 315.97 | AM91: 199.98 | AN91: 229.96 | AO91: 281.21 | AP91: 303.5 | AQ91: 167.72 | AR91: 171.91 | AS91: 212.1 | AT91: 440.63 | AU91: 658.74 | AV91: 666.46 | AW91: =921.67 | AX91: =+AX101*AX12 | AY91: =+AY101*AY12 | AZ91: =+AZ101*AZ12 | BA91: =+BA101*BA12 | BB91: =+BB101*BB12 | BC91: =+BC101*BC12 | BD91: =+BD101*BD12 | BE91: =+BE101*BE12 | ... DG91: =+DG101*DG12
B92: 60900 Professional/Legal Fees | D92: =0 | E92: =0 | F92: =0 | G92: =0 | H92: =0 | I92: =0 | J92: 0 | K92: 0 | L92: 0 | M92: 1150 | N92: 0 | O92: 0 | U92: 50 | V92: 55 | W92: 200 | X92: 633.5 | AI92: 490 | AK92: 262.5 | AP92: =707 | AQ92: 235.5 | AT92: 275 | AU92: 88 | AX92: =AVERAGE(AR92:AW92) | AY92: =+AM92 | AZ92: =+AN92 | BA92: =+AO92 | BB92: =+AP92 | BC92: =+AQ92 | BD92: =+AR92 | BE92: =+AS92 | BF92: =+AT92 | ... DG92: =+CU92
B93: 61100 Utilities | T93: 192.74 | U93: 137.74 | V93: 181.07 | W93: 286.48 | X93: 138.17 | Y93: 263.36 | Z93: 138.4 | AA93: 138.4 | AB93: 138.4 | AC93: 138.42 | AD93: 138.42 | AE93: 145.97 | AF93: 142.42 | AG93: 142.42 | AH93: 219.14 | AI93: 164.46 | AJ93: 134.46 | AK93: 260.35 | AL93: 157.41 | AM93: 127.41 | AN93: 128.5 | AO93: 155.68 | AP93: 123.02 | AQ93: 123.02 | AR93: 123.01 | AS93: 123.01 | AT93: 123.01 | AU93: 122.99 | AV93: 161.99 | AW93: =155.86 | AX93: =+AW93 | AY93: =+AX93 | AZ93: =+AY93 | BA93: =+AZ93 | BB93: =+BA93 | BC93: =+BB93 | BD93: =+BC93 | BE93: =+BD93 | ... DG93: =+DF93
B94: 61200 Taxes/Licenses | W94: 50 | AD94: 300 | AI94: 50 | AR94: 0 | AS94: 0 | AT94: 50 | AX94: =AVERAGE(AO94:AW94) | AY94: =+AX94 | AZ94: =+AY94 | BA94: =+AZ94 | BB94: =+BA94 | BC94: =+BB94 | BD94: =+BC94 | BE94: =+BD94 | BF94: =+BE94 | ... DG94: =+DF94
B95: Total G&A Expenses | D95: =SUM(D85:D92) | E95: =SUM(E85:E92) | F95: =SUM(F85:F92) | G95: =SUM(G85:G92) | H95: =SUM(H85:H92) | I95: =SUM(I85:I92) | J95: =SUM(J85:J92) | K95: =SUM(K85:K92) | ... O95: =SUM(O85:O92) | P95: =SUM(P85:P94) | Q95: =SUM(Q85:Q94) | R95: =SUM(R85:R94) | S95: =SUM(S85:S94) | T95: =SUM(T85:T94) | U95: =SUM(U85:U94) | V95: =SUM(V85:V94) | W95: =SUM(W85:W94) | X95: =SUM(X85:X94) | Y95: =SUM(Y74:Y94) | Z95: =SUM(Z74:Z94) | AA95: =SUM(AA74:AA94) | AB95: =SUM(AB74:AB94) | AC95: =SUM(AC74:AC94) | AD95: =SUM(AD74:AD94) | AE95: =SUM(AE74:AE94) | AF95: =SUM(AF74:AF94) | ... AM95: =SUM(AM74:AM94) | AN95: =SUM(AN83:AN94)+AN80 | AO95: =SUM(AO83:AO94)+AO80 | AP95: =SUM(AP83:AP94)+AP80 | AQ95: =SUM(AQ83:AQ94)+AQ80 | AR95: =SUM(AR83:AR94)+AR80 | AS95: =SUM(AS83:AS94)+AS80 | AT95: =SUM(AT83:AT94)+AT80 | AU95: =SUM(AU83:AU94)+AU80 | ... DG95: =SUM(DG83:DG94)+DG80
B96: 61000 Owner Guarenteed Payments | D96: 0 | E96: 0 | F96: 0 | G96: 0 | H96: 0 | I96: 0 | AB96: =AA96 | AC96: =AB96 | AD96: =AC96 | AE96: =AD96 | AF96: =AE96 | AG96: =AF96 | AH96: =AG96 | AI96: =AH96 | ... DG96: =DF96
B97: Total Expenses | D97: =SUM(D95:D96) | E97: =SUM(E95:E96) | F97: =SUM(F95:F96) | G97: =SUM(G95:G96) | H97: =SUM(H95:H96) | I97: =SUM(I95:I96) | J97: =SUM(J95:J96) | K97: =SUM(K95:K96) | ... DG97: =SUM(DG95:DG96)
B98: Total Operating Expenses | P98: =+P95+P72 | Q98: =+Q95+Q72 | R98: =+R95+R72 | S98: =+S95+S72 | T98: =+T95+T72 | U98: =+U95+U72 | V98: =+V95+V72 | W98: =+W95+W72 | ... DG98: =+DG95+DG72
B99: Net Operating Income | D99: =D66-D97 | E99: =E66-E97 | F99: =F66-F97 | G99: =G66-G97 | H99: =H66-H97 | I99: =I66-I97 | J99: =J66-J97 | K99: =K66-K97 | ... O99: =O66-O97 | P99: =P66-P98 | Q99: =Q66-Q98 | R99: =R66-R98 | S99: =S66-S98 | T99: =T66-T98 | U99: =U66-U98 | V99: =V66-V98 | W99: =W66-W98 | ... DG99: =DG66-DG98
C100: NOI % | E100: =+E86/8 | F100: =+F86/8 | G100: =+G86/8 | H100: =+H86/8 | I100: =+I86/8 | J100: =+J86/8 | K100: =+K86/8 | L100: =+L86/8 | ... O100: =+O86/8 | P100: =+P99/P14 | Q100: =+Q99/Q14 | R100: =+R99/R14 | S100: =+S99/S14 | T100: =+T99/T14 | U100: =+U99/U14 | V100: =+V99/V14 | W100: =+W99/W14 | ... DG100: =+DG99/DG14
C101: QBO Fees as a % of Revenue | AB101: =+AB91/AB12 | AC101: =+AC91/AC12 | AD101: =+AD91/AD12 | AE101: =+AE91/AE12 | AF101: =+AF91/AF12 | AG101: =+AG91/AG12 | AH101: =+AH91/AH12 | AI101: =+AI91/AI12 | ... AW101: =+AW91/AW12 | AX101: =+AVERAGE(AU101:AW101) | AY101: =+AX101 | AZ101: =+AY101 | BA101: =+AZ101 | BB101: =+BA101 | BC101: =+BB101 | BD101: =+BC101 | BE101: =+BD101 | BF101: =+BE101 | ... DG101: =+DF101
C102: CAC | L102: =L85+L89+L63+L71 | M102: =M85+M89+M63+M71 | N102: =N85+N89+N63+N71 | O102: =O85+O89+O63+O71 | P102: =P85+P89+P63+P71 | Q102: =Q85+Q89+Q63+Q71 | R102: =R85+R89+R63+R71 | S102: =S85+S89+S63+S71 | ... AA102: =AA85+AA89+AA63+AA71 | AB102: =AB85+AB89+AB65+AB71 | AC102: =AC85+AC89+AC65+AC71 | AD102: =AD85+AD89+AD65+AD71 | AE102: =AE85+AE89+AE65+AE71 | AF102: =AF85+AF89+AF65+AF71 | AG102: =AG85+AG89+AG65+AG71 | AH102: =AH85+AH89+AH65+AH71 | AI102: =AI85+AI89+AI65+AI71 | ... AP102: =AP85+AP89+AP65+AP71 | AQ102: =AQ85+AQ65+AQ71+SUM(AQ89:AQ91) | AR102: =AR85+AR65+AR71+SUM(AR89:AR91) | AS102: =AS85+AS65+AS71+SUM(AS89:AS91) | AT102: =AT85+AT65+AT71+SUM(AT89:AT91) | AU102: =AU85+AU65+AU71+SUM(AU89:AU91) | AV102: =AV85+AV65+AV71+SUM(AV89:AV91) | AW102: =AW85+AW65+AW71+SUM(AW89:AW91) | AX102: =AX85+AX65+AX71+SUM(AX89:AX91) | ... DG102: =DG85+DG65+DG71+SUM(DG89:DG91)
B103: Other Income | AG103: 25
B104: Interest Income | D104: =0 | E104: =0 | F104: =0 | G104: =0 | H104: =0 | I104: =0 | J104: =0 | K104: 0 | L104: 0 | M104: 0.02 | N104: 0.03 | O104: 0.01 | P104: 0 | Q104: 0 | R104: 0 | S104: 0.01 | T104: 0.01 | U104: 0.01 | V104: 0.03 | W104: 0.01 | X104: 0 | Y104: 0 | Z104: 0 | AA104: 0 | AG104: 0 | AI104: 0.43 | AJ104: 0.69 | AK104: 1.74 | AL104: 2.41 | AM104: 0.08 | AN104: 0.01 | AO104: 0.01 | AP104: 0.01 | AQ104: 0.01 | AR104: 0.06 | AS104: 0.01 | AT104: 0.03 | AU104: 0.03 | AV104: 0.99 | AW104: 4.56 | AX104: 0 | AY104: =AX104 | AZ104: =AY104 | BA104: =AZ104 | BB104: =BA104 | BC104: =BB104 | BD104: =BC104 | BE104: =BD104 | BF104: =BE104 | ... DG104: =DF104
B105: Total Other Income | D105: =D104 | E105: =E104 | F105: =F104 | G105: =G104 | H105: =H104 | I105: =I104 | J105: =J104 | K105: 0 | L105: 0 | M105: 0.02 | N105: =N104 | O105: =O104 | P105: =P104 | Q105: =Q104 | R105: =R104 | S105: =S104 | T105: =T104 | U105: =U104 | ... AF105: =AF104 | AG105: =SUM(AG103:AG104) | AH105: =AH104 | AI105: =AI104 | AJ105: =AJ104 | AK105: =AK104 | AL105: =AL104 | AM105: =AM104 | AN105: =AN104 | AO105: =AO104 | AP105: =AP104 | AQ105: =SUM(AQ103:AQ104) | AR105: =AR104 | AS105: =AS104 | AT105: =AT104 | AU105: =AU104 | AV105: =AV104 | AW105: =AW104 | AX105: =AX104 | AY105: =AY104 | ... DG105: =DG104
B106: Other Expenses
B107: 73000 Home Office Deduction | D107: =0 | E107: =0 | F107: =0 | G107: =0 | H107: =0 | I107: =0 | J107: =0 | K107: 0 | L107: 0 | M107: 0 | N107: 0 | O107: 0 | P107: 0 | Q107: 0 | R107: 0 | S107: 0 | T107: 0 | U107: 0 | V107: 0 | W107: 0 | X107: 0 | Y107: 0 | Z107: 0 | AA107: 0 | AG107: 715.26 | AH107: 715.26 | AI107: 639.62 | AJ107: 719.87 | AK107: 733.37 | AL107: 735.08 | AM107: 790.12 | AN107: 821.85 | AO107: 775.58 | AP107: 757.93 | AQ107: 757.93 | AR107: 692.93 | AS107: 769.03 | AT107: 775.28 | AU107: 727.35 | AV107: 727.35 | AW107: 846.79 | AX107: 800 | AY107: =AX107 | AZ107: =AY107 | BA107: =AZ107 | BB107: =BA107 | BC107: =BB107 | BD107: =BC107 | BE107: =BD107 | BF107: =BE107 | ... DG107: =DF107
...

Sheet 3

Sheet October
A1: Student | B1: Date | C1: Hours | D1: Rate ($/hr) | E1: Coin | F1: Billed? | G1: Received payment? | H1: Topic | I1: Tip? | J1: Paid via invoice? | K1: Totals
A2: Abby Owen | B2: 44836 | C2: 1 | D2: 50 | E2: 50 | F2: Yes | G2: Yes | H2: Math (general homework) | I2: No | J2: No | K2: 50 | N2: BALANCED
A3: Abby Owen | B3: 44846 | C3: 2 | D3: 50 | E3: 100 | F3: Yes | G3: Yes | H3: Algebra 2 | I3: No | J3: YES | K3: 100
A4: Abby Owen | B4: 44858 | C4: 1 | D4: 50 | E4: 50 | F4: Yes | G4: Yes | H4: Emergency Math Lab | I4: No | J4: YES | K4: 50
A5: Abby Owen | B5: 44859 | C5: 0.75 | D5: 50 | E5: 37.5 | F5: Yes | G5: Yes | H5: Logarithmic Functions Review | I5: No | J5: YES | K5: 37.5
A6: Abby Owen | B6: 44861 | C6: 1 | D6: 50 | E6: 50 | F6: Yes | G6: Yes | H6: Precalc - Exponentials and Logs | I6: No | J6: YES | K6: 50
A7: Addison O'Connor | B7: 44849 | C7: 1 | D7: 60 | E7: 60 | F7: Yes | G7: Yes | H7: Choreography Review | I7: No | J7: YES | K7: 60
A8: Caroline Frey | B8: 44852 | C8: 3.5 | D8: 50 | E8: 175 | F8: Yes | G8: Yes | H8: TN and CoC Essay Supplement Finalization | I8: Yes | J8: No - Venmo b/c tip; sent to personal account but transferred accordingly (sent to Eric and Eric venmo'd business acc) | K8: 200
A9: Caroline Frey | B9: 44857 | C9: 1 | D9: 50 | E9: 50 | F9: Yes | G9: Yes | H9: Bama Honors Appliation | I9: No | J9: No - venmo b/c tip | K9: 50
A10: Claire Cecotti | B10: 44837 | C10: 1 | D10: 50 | E10: 50 | F10: Yes | G10: Yes | H10: SAT Math, Piecewise Functions Test | I10: No | J10: YES | K10: 50
A11: Elle Mishler | B11: 44842 | C11: 1 | D11: 60 | E11: 60 | F11: Yes | G11: Yes | H11: Algebra 1 | I11: No | J11: YES | K11: 60
A12: Elle Mishler | B12: 44846 | C12: 1 | D12: 60 | E12: 60 | F12: Yes | G12: Yes | H12: Algebra 1 | I12: No | J12: YES | K12: 60
A13: Elle Mishler | B13: 44853 | C13: 1.25 | D13: 60 | E13: 75 | F13: Yes | G13: Yes | H13: Algebra 1 Review | I13: No | J13: YES | K13: 75
A14: Gabby Bagot | B14: 44856 | C14: 1 | D14: 60 | E14: 60 | F14: Yes | G14: Yes | H14: Algebra 1 | I14: No | J14: YES | K14: 60 | N14: *Sujay 21 Oct, 23 Oct, 29 Oct, and 30 Oct were all billed together.
A15: Julia Cecotti | B15: 44845 | C15: 1 | D15: 50 | E15: 50 | F15: Yes | G15: Yes | H15: Precalc - piecewise functions | I15: No | J15: YES | K15: 50
A16: Julia Cecotti | B16: 44851 | C16: 1.5 | D16: 50 | E16: 75 | F16: Yes | G16: Yes | H16: Limits and Discontinuity | I16: No | J16: YES | K16: 75
A17: Kathryn Oakford | B17: 44851 | C17: 1.5 | D17: 50 | E17: 75 | F17: Yes | G17: Yes | H17: Business Calculus | I17: No | J17: YES | K17: 75
A18: Kathryn Oakford | B18: 44857 | C18: 1.5 | D18: 50 | E18: 75 | F18: Yes | G18: Yes | H18: Business Calculus | I18: No | J18: YES | K18: 75 | O18: Row Labels | P18: Sum of Hours | Q18: Sum of Coin
A19: Kaylie Thompson | B19: 44836 | C19: 1.5 | D19: 50 | E19: 75 | F19: Yes | G19: Yes | H19: Common App Finalizaiton | I19: No | J19: No | K19: 75 | O19: Abby Owen | P19: 5.75 | Q19: 287.5
A20: Maddie Wilson | B20: 44836 | C20: 2 | D20: 50 | E20: 100 | F20: Yes | G20: Yes | H20: ACT Math | I20: No | J20: No | K20: 100 | O20: Addison O'Connor | P20: 1 | Q20: 60
A21: Maddie Wilson | B21: 44854 | C21: 1.5 | D21: 50 | E21: 75 | F21: Yes | G21: Yes | H21: ACT Math | I21: No | J21: No - received via PayPal and Transferred | K21: 75 | O21: Caroline Frey | P21: 4.5 | Q21: 225
A22: Maddox Rogers | B22: 44847 | C22: 2 | D22: 50 | E22: 100 | F22: Yes | G22: Yes | H22: College Essay | I22: No | J22: YES | K22: 100 | O22: Claire Cecotti | P22: 1 | Q22: 50
A23: Naura Peters | B23: 44856 | C23: 0.5 | D23: 60 | E23: 30 | F23: Yes | G23: Yes | H23: Private lesson | I23: No | J23: YES | K23: 30 | O23: Elle Mishler | P23: 3.25 | Q23: 195
A24: Nicolette Batori | B24: 44857 | C24: 2 | D24: 50 | E24: 100 | F24: Yes | G24: Yes | H24: AP Test Advice, Volunteering advice, SAT Math | I24: No | J24: YES | K24: 100 | O24: Gabby Bagot | P24: 1 | Q24: 60
A25: Nicolette Batori | B25: 44863 | C25: 1 | D25: 50 | E25: 50 | F25: Yes | G25: Yes | H25: SAT Math | I25: No | J25: YES | K25: 50 | O25: Julia Cecotti | P25: 2.5 | Q25: 125
A26: Nicolette Batori | B26: 44865 | C26: 1 | D26: 50 | E26: 50 | F26: Yes | G26: Yes | H26: SAT Math | I26: No | J26: YES | K26: 50 | O26: Kathryn Oakford | P26: 3 | Q26: 150
A27: Rohan Skanda | B27: 44838 | C27: 1 | D27: 50 | E27: 50 | F27: Yes | G27: Yes | H27: AOS Integrated Math + Science | I27: No | J27: YES | K27: 50 | O27: Kaylie Thompson | P27: 1.5 | Q27: 75
A28: Rohan Skanda | B28: 44840 | C28: 2 | D28: 50 | E28: 100 | F28: Yes | G28: Yes | H28: AOS Integrated Math + Science | I28: No | J28: YES | K28: 100 | O28: Maddie Wilson | P28: 3.5 | Q28: 175
A29: Rohan Skanda | B29: 44851 | C29: 1.5 | D29: 50 | E29: 75 | F29: Yes | G29: Yes | H29: Math and Physics Review | I29: No | J29: YES | K29: 75 | O29: Maddox Rogers | P29: 2 | Q29: 100
A30: Rohan Skanda | B30: 44857 | C30: 1 | D30: 50 | E30: 75 | F30: Yes | G30: Yes | H30: AOS Integrated Math + Science | I30: No | J30: YES | K30: 75 | O30: Naura Peters | P30: 0.5 | Q30: 30
... A36: Sophia Gonzales | B36: 44861 | C36: 1 | D36: 60 | E36: 60 | F36: Yes | G36: Yes | H36: Physics | I36: No | J36: YES | K36: 60 | O36: Grand Total | P36: 57.25 | Q36: 2840
A37: Sujay Penugonda | B37: 44840 | C37: 1.5 | D37: 50 | E37: 75 | F37: Yes | G37: Yes | H37: Supplemental Essays | I37: No | J37: YES | K37: 75
A38: Sujay Penugonda | B38: 44855 | C38: 2 | D38: 50 | E38: 100 | F38: Yes | G38: Yes | H38: College Essay | I38: No | J38: YES | K38: 100
A39: Sujay Penugonda | B39: 44857 | C39: 0.5 | D39: 50 | E39: 25 | F39: No | G39: Yes | H39: College Essay | I39: No | J39: YES | K39: 25
A40: Sujay Penugonda | B40: 44863 | C40: 5 | D40: 50 | E40: 125 | F40: Yes | G40: Yes | H40: College Essay | I40: No | J40: YES | K40: 250
A41: Sujay Penugonda | B41: 44864 | C41: 2.5 | D41: 50 | E41: 125 | F41: Yes | G41: Yes | H41: College Essay | I41: No | J41: No - asked to send via Zelle. Transferred from personal to biz immediately. | K41: 125
K43: =SUM(K2:K41)

Sheet September
A1: Student | B1: Date | C1: Hours | D1: Rate ($/hr) | E1: Coin | F1: Billed? | G1: Received payment? | H1: Topic | I1: Tip? | J1: Totals
A2: Rohan Skanda | B2: 44822 | C2: 1 | D2: 50 | E2: 50 | F2: Yes | G2: Yes | H2: AOS Math/Science | I2: No | J2: 50 | M2: BALANCED
A3: Maddie Wilson | B3: 44822 | C3: 2 | D3: 50 | E3: 100 | F3: Yes | G3: Yes | H3: College Essay | I3: No | J3: 100
A4: Caroline Frey | B4: 44822 | C4: 1.5 | D4: 50 | E4: 75 | F4: Yes | G4: Yes | H4: College Supplemental Essays | I4: 25 | J4: 100
A5: Kathryn Oakford | B5: 44822 | C5: 1.5 | D5: 50 | E5: 75 | F5: Yes | G5: Yes | H5: Business Calc | I5: No | J5: 75
A6: Kaylie Thompson | B6: 44822 | C6: 1.5 | D6: 50 | E6: 75 | F6: Yes | G6: Yes | H6: College Essay | I6: No | J6: 75
A7: Abby Owen | B7: 44823 | C7: 2 | D7: 50 | E7: 100 | F7: Yes | G7: Yes | H7: Math Practice for Quiz | I7: No | J7: 100
A8: Kathryn Oakford | B8: 44823 | C8: 1 | D8: 50 | E8: 50 | F8: Yes | G8: Yes | H8: Business Calc | I8: No | J8: 50
A9: Maddie Wilson | B9: 44826 | C9: 1 | D9: 50 | E9: 50 | F9: Yes | G9: Yes | H9: ACT Math, NHS Essay | I9: No | J9: 50
A10: Mckenzie Frey | B10: 44827 | C10: 0.5 | D10: 50 | E10: 25 | F10: No | G10: Yes (accounted for in October w Caroline) | H10: PR/Project Planning | O10: Row Labels | P10: Sum of Hours | Q10: Sum of Coin
A11: Maddie Wilson | B11: 44827 | C11: 1 | D11: 50 | E11: 50 | F11: Yes | G11: Yes | H11: NHS Essay | I11: No | J11: 50 | O11: Abby Owen | P11: 2 | Q11: 100
A12: Claire Cecotti | B12: 44829 | C12: 1 | D12: 50 | E12: 50 | F12: Yes | G12: Yes | H12: Algebra Review/SAT Math | I12: No | J12: 50 | O12: Caroline Frey | P12: 1.5 | Q12: 75
A13: Maddie Wilson | B13: 44829 | C13: 2 | D13: 100 | E13: 100 | F13: Yes | G13: Yes | H13: Supplemental Essays | I13: No | J13: 100 | O13: Claire Cecotti | P13: 2 | Q13: 100
A14: Sam Cormier | B14: 44829 | C14: 2 | D14: 100 | E14: 100 | F14: Yes | G14: Yes | H14: Supplemental Essays | I14: No | J14: 100 | O14: Kathryn Oakford | P14: 2.5 | Q14: 125
A15: Claire Cecotti | B15: 44830 | C15: 1 | D15: 50 | E15: 50 | F15: Yes | G15: Yes | H15: Algebra Review/SAT Math | I15: No | J15: 50 | O15: Kaylie Thompson | P15: 1.5 | Q15: 75
A16: Maddie Wilson | B16: 44832 | C16: 1.5 | D16: 50 | E16: 75 | F16: Yes | G16: Yes | H16: Supplemental Essays | I16: No | J16: 75 | O16: Maddie Wilson | P16: 7.5 | Q16: 375
O17: Mckenzie Frey | P17: 0.5 | Q17: 25
J18: =SUM(J2:J16) | O18: Rohan Skanda | P18: 1 | Q18: 50
O19: Sam Cormier | P19: 2 | Q19: 100
O20: Grand Total | P20: 20.5 | Q20: 1025

Sheet August
A1: Student | B1: Date | C1: Hours | D1: Rate ($/hr) | E1: Coin | F1: Billed? | G1: Received payment? | H1: Topic | I1: Tip? | J1: Totals
A2: Caroline Frey | B2: 44793 | C2: 0.5 | D2: 50 | E2: =C2*D2 | F2: Yes | G2: Yes | H2: Adderal form | I2: 10 | J2: =E2+I2
A3: Nicolette Batori | B3: 44794 | C3: 1.5 | D3: 50 | E3: =C3*D3 | F3: No | G3: Yes | H3: SAT/ACT overview, college talk/prep | I3: 0 | J3: =E3+I3
A4: Maddie Wilson | B4: 44794 | C4: 1 | D4: 50 | E4: =C4*D4 | F4: No | G4: No | H4: ACT Science | J4: =E4+I4
A5: Sujay Penugonda | B5: 44796 | C5: 2 | D5: 50 | E5: =C5*D5 | F5: Yes | G5: Yes | H5: Essay | J5: =E5+I5 | O5: Row Labels | P5: Sum of Hours | Q5: Sum of Coin
A6: Maddie Wilson | B6: 44796 | C6: 2 | D6: 50 | E6: =C6*D6 | F6: No | G6: No | H6: ACT Math, college essay | J6: =E6+I6 | O6: Caroline Frey | P6: 0.5 | Q6: 25
A7: Matthew Aasen | B7: 44796 | C7: 0.5 | D7: 50 | E7: =C7*D7 | F7: Yes | G7: Yes | H7: 2nd read common app | J7: =E7+I7 | O7: Maddie Wilson | P7: 3 | Q7: 150
O8: Matthew Aasen | P8: 0.5 | Q8: 25
O9: Nicolette Batori | P9: 1.5 | Q9: 75
J10: =SUM(J2:J7) | O10: Sujay Penugonda | P10: 2 | Q10: 100
O11: Grand Total | P11: 7.5 | Q11: 375
J12: BALANCED

Sheet People Plan
H2: 45473 | I2: =EOMONTH(H2,1) | J2: =EOMONTH(I2,1) | K2: =EOMONTH(J2,1) | L2: =EOMONTH(K2,1) | M2: =EOMONTH(L2,1) | N2: =EOMONTH(M2,1) | O2: =EOMONTH(N2,1) | P2: =EOMONTH(O2,1) | ... FB2: =EOMONTH(FA2,1)
B3: Name | C3: Position | D3: Hourly Rate | E3: Avg. Hours
B4: Nvaid | C4: Intern | D4: 12 | E4: =4.33*10 | I4: 0 | J4: 0 | K4: 0 | L4: 0 | M4: 0 | N4: 0 | O4: 0 | P4: 0 | Q4: 0 | R4: 0 | S4: 0 | U4: 240
B5: Charles | C5: Intern | D5: 15 | E5: =4.33*10 | I5: 450 | J5: 150 | K5: 0 | L5: 0 | M5: 0 | O5: 0 | P5: 0 | Q5: 0 | R5: 0 | S5: 0
B6: Luke | C6: Intern | D6: 15 | E6: =4.33*10 | R6: 0 | S6: 0
B7: Rising Freshmen | C7: Intern | O7: 0 | P7: 0 | Q7: 0 | R7: 0 | S7: 0 | U7: 300 | V7: 234 | W7: =86.8 | X7: 120
F8: Total Interns Expense | H8: =SUM(H4:H7) | I8: =SUM(I4:I7) | J8: =SUM(J4:J7) | K8: =SUM(K4:K7) | L8: =SUM(L4:L7) | M8: =SUM(M4:M7) | N8: =SUM(N4:N7) | O8: =SUM(O4:O7) | ... FB8: =SUM(FB4:FB7)
E10: Hours Threshold
B11: Cheri? | C11: Subsititute Tutor | D11: 50 | H11: =+IF(('Monthly Detail'!AG26-'Monthly Detail'!$B$24)>0,('Monthly Detail'!AG26-'Monthly Detail'!$B$24)*'People Plan'!$D$11, 0) | I11: 0 | J11: 0 | K11: 0 | L11: 0 | M11: =+IF(('Monthly Detail'!AL26-'Monthly Detail'!$B$24)>0,('Monthly Detail'!AL26-'Monthly Detail'!$B$24)*'People Plan'!$D$11, 0) | N11: =+IF(('Monthly Detail'!AM28-'Monthly Detail'!$B$24)>0,('Monthly Detail'!AM28-'Monthly Detail'!$B$24)*'People Plan'!$D$11, 0) | O11: 0 | P11: 0 | Q11: 0 | R11: 0 | S11: 0 | T11: =+IF(('Monthly Detail'!AS28-'Monthly Detail'!$B$24)>0,('Monthly Detail'!AS28-'Monthly Detail'!$B$24)*'People Plan'!$D$11, 0) | U11: =+IF(('Monthly Detail'!AT28-'Monthly Detail'!$B$24)>0,('Monthly Detail'!AT28-'Monthly Detail'!$B$24)*'People Plan'!$D$11, 0) | V11: =+IF(('Monthly Detail'!AU28-'Monthly Detail'!$B$24)>0,('Monthly Detail'!AU28-'Monthly Detail'!$B$24)*'People Plan'!$D$11, 0) | W11: =+IF(('Monthly Detail'!AV28-'Monthly Detail'!$B$24)>0,('Monthly Detail'!AV28-'Monthly Detail'!$B$24)*'People Plan'!$D$11, 0) | X11: =+IF(('Monthly Detail'!AW28-'Monthly Detail'!$B$24)>0,('Monthly Detail'!AW28-'Monthly Detail'!$B$24)*'People Plan'!$D$11, 0) | Y11: =+IF(('Monthly Detail'!AX28-'Monthly Detail'!$B$24)>0,('Monthly Detail'!AX28-'Monthly Detail'!$B$24)*'People Plan'!$D$11, 0) | Z11: =+IF(('Monthly Detail'!AY28-'Monthly Detail'!$B$24)>0,('Monthly Detail'!AY28-'Monthly Detail'!$B$24)*'People Plan'!$D$11, 0) | AA11: =+IF(('Monthly Detail'!AZ28-'Monthly Detail'!$B$24)>0,('Monthly Detail'!AZ28-'Monthly Detail'!$B$24)*'People Plan'!$D$11, 0) | ... FB11: =+IF(('Monthly Detail'!GA28-'Monthly Detail'!$B$24)>0,('Monthly Detail'!GA28-'Monthly Detail'!$B$24)*'People Plan'!$D$11, 0)
B12: Madeline | C12: Subsititute Tutor - RESUME REVIEW | D12: 50 | E12: 3 | H12: =+IF(('Monthly Detail'!AG24-'Monthly Detail'!$B$24)>0,('Monthly Detail'!AG24-'Monthly Detail'!$B$24)*'People Plan'!$D$11, 0) | I12: 150 | J12: 740 | K12: 817.5 | L12: 937.5 | M12: 170 | N12: =+IF(('Monthly Detail'!AM30-$E$12)>0,('Monthly Detail'!AM30-$E$12)*'People Plan'!$D$12, 0) | O12: 0 | P12: 802.5 | Q12: 375 | R12: 0 | S12: 270 | T12: 0 | U12: 720 | V12: 240 | W12: 1419.96 | X12: 1020 | Y12: =+IF(('Monthly Detail'!AX30-$E$12)>0,('Monthly Detail'!AX30-$E$12)*'People Plan'!$D$12, 0) | Z12: =+IF(('Monthly Detail'!AY30-$E$12)>0,('Monthly Detail'!AY30-$E$12)*'People Plan'!$D$12, 0) | AA12: =+IF(('Monthly Detail'!AZ30-$E$12)>0,('Monthly Detail'!AZ30-$E$12)*'People Plan'!$D$12, 0) | AB12: =+IF(('Monthly Detail'!BA30-$E$12)>0,('Monthly Detail'!BA30-$E$12)*'People Plan'!$D$12, 0) | AC12: =+IF(('Monthly Detail'!BB30-$E$12)>0,('Monthly Detail'!BB30-$E$12)*'People Plan'!$D$12, 0) | AD12: =+IF(('Monthly Detail'!BC30-$E$12)>0,('Monthly Detail'!BC30-$E$12)*'People Plan'!$D$12, 0) | AE12: =+IF(('Monthly Detail'!BD30-$E$12)>0,('Monthly Detail'!BD30-$E$12)*'People Plan'!$D$12, 0) | AF12: =+IF(('Monthly Detail'!BE30-$E$12)>0,('Monthly Detail'!BE30-$E$12)*'People Plan'!$D$12, 0) | ... FB12: =+IF(('Monthly Detail'!GA30-$E$12)>0,('Monthly Detail'!GA30-$E$12)*'People Plan'!$D$12, 0)
B13: Tyler | C13: Subsititute Tutor - SAT/ACT PREP | D13: 50 | E13: 50 | O13: 0 | P13: 0 | Q13: 0 | R13: 0 | S13: 0 | T13: 0 | U13: 120 | V13: 210 | W13: 270 | X13: 390 | Y13: =+IF(('Monthly Detail'!AX29-$E$13)>0,('Monthly Detail'!AX29-$E$13)*'People Plan'!$D$13, 0) | Z13: =+IF(('Monthly Detail'!AY29-$E$13)>0,('Monthly Detail'!AY29-$E$13)*'People Plan'!$D$13, 0) | AA13: =+IF(('Monthly Detail'!AZ29-$E$13)>0,('Monthly Detail'!AZ29-$E$13)*'People Plan'!$D$13, 0) | AB13: =+IF(('Monthly Detail'!BA29-$E$13)>0,('Monthly Detail'!BA29-$E$13)*'People Plan'!$D$13, 0) | AC13: =+IF(('Monthly Detail'!BB29-$E$13)>0,('Monthly Detail'!BB29-$E$13)*'People Plan'!$D$13, 0) | AD13: =+IF(('Monthly Detail'!BC29-$E$13)>0,('Monthly Detail'!BC29-$E$13)*'People Plan'!$D$13, 0) | AE13: =+IF(('Monthly Detail'!BD29-$E$13)>0,('Monthly Detail'!BD29-$E$13)*'People Plan'!$D$13, 0) | AF13: =+IF(('Monthly Detail'!BE29-$E$13)>0,('Monthly Detail'!BE29-$E$13)*'People Plan'!$D$13, 0) | ... FB13: =+IF(('Monthly Detail'!GA29-$E$13)>0,('Monthly Detail'!GA29-$E$13)*'People Plan'!$D$13, 0)
C14: Marketing Coordinator | D14: 75 | E14: 6 | Z14: =+IF(('Monthly Detail'!AY30-$E$14)>0,('Monthly Detail'!AY30-$E$14)*$D$14, 0) | AA14: =+IF(('Monthly Detail'!AZ30-$E$14)>0,('Monthly Detail'!AZ30-$E$14)*$D$14, 0) | AB14: =+IF(('Monthly Detail'!BA30-$E$14)>0,('Monthly Detail'!BA30-$E$14)*$D$14, 0) | AC14: =+IF(('Monthly Detail'!BB30-$E$14)>0,('Monthly Detail'!BB30-$E$14)*$D$14, 0) | AD14: =+IF(('Monthly Detail'!BC30-$E$14)>0,('Monthly Detail'!BC30-$E$14)*$D$14, 0) | AE14: =+IF(('Monthly Detail'!BD30-$E$14)>0,('Monthly Detail'!BD30-$E$14)*$D$14, 0) | AF14: =+IF(('Monthly Detail'!BE30-$E$14)>0,('Monthly Detail'!BE30-$E$14)*$D$14, 0) | AG14: =+IF(('Monthly Detail'!BF30-$E$14)>0,('Monthly Detail'!BF30-$E$14)*$D$14, 0) | ... FB14: =+IF(('Monthly Detail'!GA30-$E$14)>0,('Monthly Detail'!GA30-$E$14)*$D$14, 0)
B15: ChanChal | C15: Subsititute Tutor - SAT/ACT PREP | U15: 202.5 | V15: 0 | W15: 2299.98 | X15: 4725 | Y15: =+IF(('Monthly Detail'!AX31-$E$13)>0,('Monthly Detail'!AX31-$E$13)*'People Plan'!$D$13, 0) | Z15: =+IF(('Monthly Detail'!AY31-$E$13)>0,('Monthly Detail'!AY31-$E$13)*'People Plan'!$D$13, 0) | AA15: =+IF(('Monthly Detail'!AZ31-$E$13)>0,('Monthly Detail'!AZ31-$E$13)*'People Plan'!$D$13, 0) | AB15: =+IF(('Monthly Detail'!BA31-$E$13)>0,('Monthly Detail'!BA31-$E$13)*'People Plan'!$D$13, 0) | AC15: =+IF(('Monthly Detail'!BB31-$E$13)>0,('Monthly Detail'!BB31-$E$13)*'People Plan'!$D$13, 0) | AD15: =+IF(('Monthly Detail'!BC31-$E$13)>0,('Monthly Detail'!BC31-$E$13)*'People Plan'!$D$13, 0) | AE15: =+IF(('Monthly Detail'!BD31-$E$13)>0,('Monthly Detail'!BD31-$E$13)*'People Plan'!$D$13, 0) | AF15: =+IF(('Monthly Detail'!BE31-$E$13)>0,('Monthly Detail'!BE31-$E$13)*'People Plan'!$D$13, 0) | ... FB15: =+IF(('Monthly Detail'!GA31-$E$13)>0,('Monthly Detail'!GA31-$E$13)*'People Plan'!$D$13, 0)
B18: Lauren Est | C18: Owner | D18: 70 | E18: 170 | O18: 1275 | P18: 4005 | Q18: 4410 | R18: 2450 | S18: 1960 | T18: 2450 | U18: 7280 | V18: 14252.7 | W18: 9800 | X18: 14350 | Y18: =+$D$18*'Monthly Detail'!AX34 | Z18: =+$D$18*'Monthly Detail'!AY34 | AA18: =+$D$18*'Monthly Detail'!AZ34 | AB18: =+$D$18*'Monthly Detail'!BA34 | AC18: =+$D$18*'Monthly Detail'!BB34 | AD18: =+$D$18*'Monthly Detail'!BC34 | AE18: =+$D$18*'Monthly Detail'!BD34 | AF18: =+$D$18*'Monthly Detail'!BE34 | ... FB18: =+$D$18*'Monthly Detail'!GA34
F19: Total Owner Wages | O19: =SUM(O18) | P19: =SUM(P18) | Q19: =SUM(Q18) | R19: =SUM(R18) | S19: =SUM(S18) | T19: =SUM(T18) | U19: =SUM(U18) | V19: =SUM(V18) | ... FB19: =SUM(FB18)
F20: Total Tutors Expense | H20: =SUM(H11:H16) | I20: =SUM(I11:I16) | J20: =SUM(J11:J16) | K20: =SUM(K11:K16) | L20: =SUM(L11:L16) | M20: =SUM(M11:M16) | N20: =SUM(N11:N16) | O20: =SUM(O11:O16) | ... FB20: =SUM(FB11:FB16)
F21: Total Contractors Expense | H21: =+H8+H20 | I21: =+I8+I20 | J21: =+J8+J20 | K21: =+K8+K20 | L21: =+L8+L20 | M21: =+M8+M20 | N21: =+N8+N20 | O21: =+O8+O20 | ... FB21: =+FB8+FB20

Sheet Actual vs. Forecast
B14: 45991
D15: 45169 | E15: 45199 | F15: 45230 | G15: 45260 | H15: 45291 | I15: 45322 | J15: 45351 | K15: 45382 | L15: 45412 | M15: 45443 | N15: 45473 | O15: 45504 | P15: 45535 | Q15: 45596 | R15: 45626 | S15: 45657 | T15: 45688 | U15: 45716 | V15: 45747 | W15: 45777 | X15: 45808 | Y15: 45838 | Z15: 45869 | AA15: 45900 | AB15: 45930 | AC15: 10/31/2025 | AD15: Forecast | AE15: 45169 | AF15: 45199 | AG15: 45230 | AH15: 45260 | AI15: 45291 | AJ15: 45322 | AK15: 45351 | AL15: 45382 | AM15: 45412 | AN15: 45443 | AO15: 45473 | AP15: 45504 | AQ15: 45535 | AR15: 45565 | AS15: 45596 | AT15: 45626 | AU15: 45657 | AV15: 45688 | AW15: 45716 | AX15: 45747 | AY15: 45777 | AZ15: 45808 | BA15: 45838 | BB15: 45869 | BC15: 45900 | BD15: 45930 | BE15: 10/31/2025 | BF15: Actual | BG15: 45322 | BH15: 45351 | BI15: 45382 | BJ15: 45412 | BK15: 45443 | BL15: 45473 | BM15: 45504 | BN15: 45535 | BO15: 45565 | BP15: 45596 | BQ15: 45626 | BR15: 45657 | BS15: 45688 | BT15: 45716 | BU15: 45747 | BV15: 45777 | BW15: 45808 | BX15: 45838 | BY15: 45869 | BZ15: 45900 | CA15: 45930 | CB15: 10/31/2025 | CC15: Budget | CD15: 46022 | CE15: Variance (Forecast) | CF15: Variance (Budget)
B16: Total Income | D16: 4938 | E16: 4489.5 | F16: 5810.25 | G16: 4881.37 | H16: 8589.37 | I16: 3066.4792 | J16: 3175.0214 | K16: 2422.2799 | L16: 4440.4242 | M16: 6044.6787 | N16: 4035.0139 | O16: 6070.8648 | P16: 9070.6433 | Q16: 11517.552 | R16: 8370.8924 | S16: 5536.9286 | T16: 5536.9286 | U16: 5536.9286 | V16: 5536.9286 | W16: 6629.6135 | X16: 6629.6135 | Y16: 6629.6135 | Z16: 10577.152 | AA16: 17228.129 | AB16: 17092.79 | AC16: 23851.27 | AD16: =+SUMIF('Monthly Detail'!$4:$4, $B$14,'Monthly Detail'!$14:$14) | AE16: =+SUMIF('[1]Monthly Detail'!$4:$4, AD15,'[1]Monthly Detail'!$14:$14) | AF16: =+SUMIF('[1]Monthly Detail'!$4:$4, AE15,'[1]Monthly Detail'!$14:$14) | AG16: =+SUMIF('[1]Monthly Detail'!$4:$4, AF15,'[1]Monthly Detail'!$14:$14) | AH16: =+SUMIF('[1]Monthly Detail'!$4:$4, AG15,'[1]Monthly Detail'!$14:$14) | AI16: =+SUMIF('[1]Monthly Detail'!$4:$4, AH15,'[1]Monthly Detail'!$14:$14) | AJ16: =+SUMIF('[1]Monthly Detail'!$4:$4, AI15,'[1]Monthly Detail'!$14:$14) | AK16: =+SUMIF('[1]Monthly Detail'!$4:$4, AJ15,'[1]Monthly Detail'!$14:$14) | AL16: =+SUMIF('[1]Monthly Detail'!$4:$4, AK15,'[1]Monthly Detail'!$14:$14) | AM16: =+SUMIF('[1]Monthly Detail'!$4:$4, AL15,'[1]Monthly Detail'!$14:$14) | AN16: 5705.08 | AO16: 4308.26 | AP16: 9060.89 | AQ16: 14111.26 | AT16: 9573.5 | AU16: 5194 | AV16: 6585.5 | AW16: 8112.12 | AX16: 7682.37 | AY16: 3756.25 | AZ16: 6044.5 | BA16: 6916 | BB16: 6916 | BC16: 6916 | BD16: 6916 | BE16: 6916 | BF16: =+SUMIF('Monthly Detail'!$4:$4, $B$14,'Monthly Detail'!$14:$14) | BG16: =+'2024 AOP'!C14 | BH16: =+'2024 AOP'!D14 | BI16: =+'2024 AOP'!E14 | BJ16: =+'2024 AOP'!F14 | BK16: =+'2024 AOP'!G14 | BL16: =+'2024 AOP'!H14 | BM16: =+'2024 AOP'!I14 | BN16: =+'2024 AOP'!J14 | BO16: =+'2024 AOP'!L14 | BP16: 6042.6641 | BQ16: =+'2024 AOP'!M14 | BR16: =+'2024 AOP'!N14 | BS16: 9543.3537 | BT16: 12714.964 | BU16: 7487.4507 | BV16: 9849.7967 | BW16: 10751.932 | BX16: 5819.9642 | BY16: 10878.588 | BZ16: 15891.044 | CA16: 12144.428 | CB16: 15655.286 | CC16: 8813.2671 | CD16: 6298.8782 | CE16: =BF16-AD16 | CF16: =BF16-CC16
B17: KPIs | C17: # of Students | D17: 17 | E17: 17 | F17: 20 | G17: 18 | H17: 34 | I17: 21 | J17: 21 | K17: 21 | L17: 27 | M17: 22 | N17: 22 | O17: 19 | P17: 32 | Q17: 41 | R17: 44 | S17: 41 | T17: 41 | U17: 41 | V17: 41 | W17: 25 | X17: 25 | Y17: 25 | Z17: 24 | AA17: 36 | AB17: 50 | AC17: 55 | AD17: =+SUMIF('Monthly Detail'!$4:$4, $B$14,'Monthly Detail'!17:17) | AE17: =+SUMIF('[1]Monthly Detail'!$4:$4, AD15,'[1]Monthly Detail'!17:17) | AF17: =+SUMIF('[1]Monthly Detail'!$4:$4, AE15,'[1]Monthly Detail'!17:17) | AG17: =+SUMIF('[1]Monthly Detail'!$4:$4, AF15,'[1]Monthly Detail'!17:17) | AH17: =+SUMIF('[1]Monthly Detail'!$4:$4, AG15,'[1]Monthly Detail'!17:17) | AI17: =+SUMIF('[1]Monthly Detail'!$4:$4, AH15,'[1]Monthly Detail'!17:17) | AJ17: =+SUMIF('[1]Monthly Detail'!$4:$4, AI15,'[1]Monthly Detail'!17:17) | AK17: =+SUMIF('[1]Monthly Detail'!$4:$4, AJ15,'[1]Monthly Detail'!17:17) | AL17: =+SUMIF('[1]Monthly Detail'!$4:$4, AK15,'[1]Monthly Detail'!17:17) | AM17: =+SUMIF('[1]Monthly Detail'!$4:$4, AL15,'[1]Monthly Detail'!17:17) | AN17: 22 | AO17: 16 | AP17: 30 | AQ17: 38 | AT17: 44 | AU17: 23 | AV17: 24 | AW17: 28 | AX17: 24 | AY17: 23 | AZ17: 20 | BA17: 25 | BB17: 25 | BC17: 25 | BD17: 25 | BE17: 25 | BF17: =+SUMIF('Monthly Detail'!$4:$4, $B$14,'Monthly Detail'!17:17) | BG17: 21 | BH17: 33 | BI17: 35 | BJ17: 33 | BK17: 34 | BL17: 34 | BM17: 31 | BN17: 32 | BO17: 43 | BP17: 38 | BQ17: 38 | BR17: 38 | BS17: 24 | BT17: 35.8 | BU17: 33.6 | BV17: 32.4 | BW17: 33.4 | BX17: 29.2 | BY17: 31.2 | BZ17: 37.2 | CA17: 43.2 | CB17: 45 | CC17: 43.6 | CD17: 42.2 | CE17: =BF17-AD17 | CF17: =BF17-CC17
C18: Net New Students | D18: 2 | E18: 0 | F18: 2 | G18: 2 | H18: 2 | I18: 2 | J18: 2 | K18: 2 | L18: 2 | M18: 2 | N18: 0 | O18: 3 | P18: 2 | Q18: -1 | R18: -4 | S18: -3 | T18: -3 | U18: -3 | V18: -3 | W18: 3 | X18: 3 | Y18: 3 | Z18: -1 | AA18: 1 | AB18: 1 | AC18: -2 | AD18: =+SUMIF('Monthly Detail'!$4:$4, $B$14,'Monthly Detail'!19:19) | AE18: =+SUMIF('[1]Monthly Detail'!$4:$4, AD15,'[1]Monthly Detail'!19:19) | AF18: =+SUMIF('[1]Monthly Detail'!$4:$4, AE15,'[1]Monthly Detail'!19:19) | AG18: =+SUMIF('[1]Monthly Detail'!$4:$4, AF15,'[1]Monthly Detail'!19:19) | AH18: =+SUMIF('[1]Monthly Detail'!$4:$4, AG15,'[1]Monthly Detail'!19:19) | AI18: =+SUMIF('[1]Monthly Detail'!$4:$4, AH15,'[1]Monthly Detail'!19:19) | AJ18: =+SUMIF('[1]Monthly Detail'!$4:$4, AI15,'[1]Monthly Detail'!19:19) | AK18: =+SUMIF('[1]Monthly Detail'!$4:$4, AJ15,'[1]Monthly Detail'!19:19) | AL18: =+SUMIF('[1]Monthly Detail'!$4:$4, AK15,'[1]Monthly Detail'!19:19) | AM18: =+SUMIF('[1]Monthly Detail'!$4:$4, AL15,'[1]Monthly Detail'!19:19) | AN18: 2 | AO18: -6 | AP18: 6 | AQ18: 8 | AT18: -4 | AU18: -21 | AV18: 1 | AW18: 4 | AX18: -4 | AY18: -1 | AZ18: -3 | BA18: 5 | BB18: 5 | BC18: 5 | BD18: 5 | BE18: 5 | BF18: =+SUMIF('Monthly Detail'!$4:$4, $B$14,'Monthly Detail'!19:19) | BG18: 2 | BH18: 12 | BI18: 2 | BJ18: -2 | BK18: 1 | BL18: 0 | BM18: -3 | BN18: 1 | BO18: 11 | BP18: 0 | BQ18: 0 | BR18: 0 | BS18: 7 | BT18: 1 | BU18: -2.2 | BV18: -1.2 | BW18: 1 | BX18: -4.2 | BY18: 2 | BZ18: 6 | CA18: 6 | CB18: 1.8 | CC18: -1.4 | CD18: -1.4 | CE18: =BF18-AD18 | CF18: =BF18-CC18
C19: # of Sessions | D19: 70 | E19: 50 | F19: 28 | G19: 28 | H19: 28 | I19: 72.666667 | J19: 28 | K19: 28 | L19: 28 | M19: 59 | N19: 65.333333 | O19: 60 | P19: 79.666667 | Q19: 137.33333 | R19: 155.66667 | S19: 129.33333 | T19: 129.33333 | U19: 129.33333 | V19: 129.33333 | W19: 57.333333 | X19: 57.333333 | Y19: 57.333333 | Z19: 50 | AA19: 77.666667 | AB19: 111.66667 | AC19: 174.33333 | AD19: =+SUMIF('Monthly Detail'!$4:$4, $B$14,'Monthly Detail'!22:22) | AE19: =+SUMIF('[1]Monthly Detail'!$4:$4, AD15,'[1]Monthly Detail'!22:22) | AF19: =+SUMIF('[1]Monthly Detail'!$4:$4, AE15,'[1]Monthly Detail'!22:22) | AG19: =+SUMIF('[1]Monthly Detail'!$4:$4, AF15,'[1]Monthly Detail'!22:22) | AH19: =+SUMIF('[1]Monthly Detail'!$4:$4, AG15,'[1]Monthly Detail'!22:22) | AI19: =+SUMIF('[1]Monthly Detail'!$4:$4, AH15,'[1]Monthly Detail'!22:22) | AJ19: =+SUMIF('[1]Monthly Detail'!$4:$4, AI15,'[1]Monthly Detail'!22:22) | AK19: =+SUMIF('[1]Monthly Detail'!$4:$4, AJ15,'[1]Monthly Detail'!22:22) | AL19: =+SUMIF('[1]Monthly Detail'!$4:$4, AK15,'[1]Monthly Detail'!22:22) | AM19: =+SUMIF('[1]Monthly Detail'!$4:$4, AL15,'[1]Monthly Detail'!22:22) | AN19: 85 | AO19: 30 | AP19: 118 | AQ19: 169 | AT19: 90 | AU19: 50 | AV19: 56 | AW19: 66 | AX19: 73 | AY19: 37 | AZ19: 62 | BA19: 51 | BB19: 51 | BC19: 51 | BD19: 51 | BE19: 51 | BF19: =+SUMIF('Monthly Detail'!$4:$4, $B$14,'Monthly Detail'!22:22) | BG19: 28 | BH19: 44.957723 | BI19: 36.609377 | BJ19: 54.895556 | BK19: 94.499879 | BL19: 62.003873 | BM19: 91.127991 | BN19: 85.378673 | BO19: 115.36828 | BP19: 55.621396 | BQ19: 55.621396 | BR19: 37.703277 | BS19: 65.333333 | BT19: 294.18455 | BU19: 175.84396 | BV19: 230.9412 | BW19: 248.3679 | BX19: 132.05018 | BY19: 245.26428 | BZ19: 359.98193 | CA19: 268.15975 | CB19: 344.87032 | CC19: 193.66336 | CD19: 147.13119 | CE19: =BF19-AD19 | CF19: =BF19-CC19
C20: Hours / Day | D20: 0.2 | E20: 0.21 | F20: 0.21 | G20: 0.21 | H20: 0.21 | I20: 0.10448413 | J20: 0.11184211 | K20: 0.085869565 | L20: 0.13035714 | M20: 0.21338384 | N20: 0.15909091 | O20: 0.1984375 | P20: 0.19279176 | Q20: 0.19353693 | R20: 0.13125 | S20: 0.095567867 | T20: 0.095567867 | U20: 0.095567867 | V20: 0.095567867 | W20: 0.14345238 | X20: 0.14345238 | Y20: 0.14345238 | Z20: 0.20568182 | AA20: 0.2652512 | AB20: 0.16241497 | AC20: 0.19180254 | AD20: =+SUMIF('Monthly Detail'!$4:$4, $B$14,'Monthly Detail'!25:25) | AE20: =+SUMIF('[1]Monthly Detail'!$4:$4, AD15,'[1]Monthly Detail'!25:25) | AF20: =+SUMIF('[1]Monthly Detail'!$4:$4, AE15,'[1]Monthly Detail'!25:25) | AG20: =+SUMIF('[1]Monthly Detail'!$4:$4, AF15,'[1]Monthly Detail'!25:25) | AH20: =+SUMIF('[1]Monthly Detail'!$4:$4, AG15,'[1]Monthly Detail'!25:25) | AI20: =+SUMIF('[1]Monthly Detail'!$4:$4, AH15,'[1]Monthly Detail'!25:25) | AJ20: =+SUMIF('[1]Monthly Detail'!$4:$4, AI15,'[1]Monthly Detail'!25:25) | AK20: =+SUMIF('[1]Monthly Detail'!$4:$4, AJ15,'[1]Monthly Detail'!25:25) | AL20: =+SUMIF('[1]Monthly Detail'!$4:$4, AK15,'[1]Monthly Detail'!25:25) | AM20: =+SUMIF('[1]Monthly Detail'!$4:$4, AL15,'[1]Monthly Detail'!25:25) | AN20: 0.18626482 | AO20: 0.159375 | AP20: 0.20568182 | AQ20: 0.2652512 | AT20: 0.14204545 | AU20: 0.14359268 | AV20: 0.16938406 | AW20: 0.18035714 | AX20: 0.19940476 | AY20: 0.094367589 | AZ20: 0.17215909 | BA20: 0.12 | BB20: 0.12 | BC20: 0.12 | BD20: 0.12 | BE20: 0.12 | BF20: =+SUMIF('Monthly Detail'!$4:$4, $B$14,'Monthly Detail'!25:25) | BG20: 0.10448413 | BH20: 0.11184211 | BI20: 0.085869565 | BJ20: 0.13035714 | BK20: 0.20833333 | BL20: 0.15719697 | BM20: 0.23035714 | BN20: 0.20907928 | BO20: 0.22025862 | BP20: 0.1328125 | BQ20: 0.1328125 | BR20: 0.090027701 | BS20: 0.23650794 | BT20: 0.23650794 | BU20: 0.14345238 | BV20: 0.18649733 | BW20: 0.19456522 | BX20: 0.12395833 | BY20: 0.20568182 | BZ20: 0.2652512 | CA20: 0.16241497 | CB20: 0.19180254 | CC20: 0.14204545 | CD20: 0.095567867 | CE20: =BF20-AD20 | CF20: =BF20-CC20
C21: Total Bill Hours | D21: 78.2 | E21: 71 | F21: 92.4 | G21: 75.6 | H21: 135.66 | I21: 48.271667 | J21: 49.322368 | K21: 37.868478 | L21: 77.432143 | M21: 107.97222 | N21: 70 | O21: 82.946875 | P21: 135.7254 | Q21: 182.50533 | R21: 131.44833 | S21: 74.447368 | T21: 74.447368 | U21: 74.447368 | V21: 74.447368 | W21: 87.3125 | X21: 87.3125 | Y21: 87.3125 | Z21: 120.6 | AA21: 212.5299 | AB21: 190.65646 | AC21: 242.63021 | AD21: =+SUMIF('Monthly Detail'!$4:$4, $B$14,'Monthly Detail'!26:26) | AE21: =+SUMIF('[1]Monthly Detail'!$4:$4, AD15,'[1]Monthly Detail'!26:26) | AF21: =+SUMIF('[1]Monthly Detail'!$4:$4, AE15,'[1]Monthly Detail'!26:26) | AG21: =+SUMIF('[1]Monthly Detail'!$4:$4, AF15,'[1]Monthly Detail'!26:26) | AH21: =+SUMIF('[1]Monthly Detail'!$4:$4, AG15,'[1]Monthly Detail'!26:26) | AI21: =+SUMIF('[1]Monthly Detail'!$4:$4, AH15,'[1]Monthly Detail'!26:26) | AJ21: =+SUMIF('[1]Monthly Detail'!$4:$4, AI15,'[1]Monthly Detail'!26:26) | AK21: =+SUMIF('[1]Monthly Detail'!$4:$4, AJ15,'[1]Monthly Detail'!26:26) | AL21: =+SUMIF('[1]Monthly Detail'!$4:$4, AK15,'[1]Monthly Detail'!26:26) | AM21: =+SUMIF('[1]Monthly Detail'!$4:$4, AL15,'[1]Monthly Detail'!26:26) | AN21: 94.25 | AO21: 51 | AP21: 135.75 | AQ21: 221.75 | AT21: 118.75 | AU21: 62.75 | AV21: 93.5 | AW21: 101 | AX21: 100.5 | AY21: 47.75 | AZ21: 75.75 | BA21: 63 | BB21: 63 | BC21: 63 | BD21: 63 | BE21: 63 | BF21: =+SUMIF('Monthly Detail'!$4:$4, $B$14,'Monthly Detail'!26:26) | BG21: 48.271667 | BH21: 77.506579 | BI21: 63.11413 | BJ21: 94.639286 | BK21: 162.91667 | BL21: 106.89394 | BM21: 157.10357 | BN21: 147.19182 | BO21: 198.89353 | BP21: 95.890625 | BQ21: 95.890625 | BR21: 65 | BS21: 125.52381 | BT21: 169.33968 | BU21: 101.22 | BV21: 132.93529 | BW21: 142.96652 | BX21: 76.01125 | BY21: 141.18 | BZ21: 207.21423 | CA21: 154.35918 | CB21: 198.51562 | CC21: 111.47727 | CD21: 84.692244 | CE21: =BF21-AD21 | CF21: =BF21-CC21
C22: River Hours | D22: 0 | F22: 0 | G22: 0 | I22: 0 | J22: 0 | K22: 0 | L22: 0 | M22: 0 | N22: 0 | O22: 0 | P22: 0 | Q22: 0 | R22: 0 | S22: 0 | T22: 0 | U22: 0 | V22: 0 | W22: 0 | X22: 0 | Y22: 0 | Z22: 0 | AA22: 0 | AB22: 0 | AC22: 0 | AD22: =+SUMIF('Monthly Detail'!$4:$4, N14,'Monthly Detail'!27:27) | AE22: =+SUMIF('[1]Monthly Detail'!$4:$4, AD15,'[1]Monthly Detail'!27:27) | AF22: =+SUMIF('[1]Monthly Detail'!$4:$4, AE15,'[1]Monthly Detail'!27:27) | AG22: =+SUMIF('[1]Monthly Detail'!$4:$4, AF15,'[1]Monthly Detail'!27:27) | AH22: =+SUMIF('[1]Monthly Detail'!$4:$4, AG15,'[1]Monthly Detail'!27:27) | AI22: =+SUMIF('[1]Monthly Detail'!$4:$4, AH15,'[1]Monthly Detail'!27:27) | AJ22: =+SUMIF('[1]Monthly Detail'!$4:$4, AI15,'[1]Monthly Detail'!27:27) | AK22: =+SUMIF('[1]Monthly Detail'!$4:$4, AJ15,'[1]Monthly Detail'!27:27) | AL22: =+SUMIF('[1]Monthly Detail'!$4:$4, AK15,'[1]Monthly Detail'!27:27) | AM22: =+SUMIF('[1]Monthly Detail'!$4:$4, AL15,'[1]Monthly Detail'!27:27) | AN22: 0 | AO22: 0 | AP22: 0 | AQ22: 0 | AT22: 0 | AU22: 0 | AV22: 0 | AW22: 0 | AX22: 0 | AY22: 0 | AZ22: 0 | BA22: 0 | BB22: 0 | BC22: 0 | BD22: 0 | BE22: 0 | BF22: =+SUMIF('Monthly Detail'!$4:$4, N14,'Monthly Detail'!27:27) | BG22: 0 | BH22: 0 | BI22: 0 | BJ22: 0 | BK22: 0 | BL22: 0 | BM22: 0 | BN22: 0 | BO22: 0 | BP22: 0 | BQ22: 0 | BR22: 0 | BS22: 0 | BT22: 0 | BU22: 0 | BV22: 0 | BW22: 0 | BX22: 0 | BY22: 0 | BZ22: 0 | CA22: 0 | CB22: 0 | CC22: 0 | CD22: 0 | CE22: =BF22-AD22 | CF22: =BF22-CC22
C23: Realized / Effective Bill Rate | D23: 62.5 | E23: 62.5 | F23: 62.5 | G23: 62.5 | H23: 62.5 | I23: 62.5 | J23: 62.5 | K23: 62.5 | L23: 62.5 | M23: 62.5 | N23: 62.5 | O23: 73.189795 | P23: 66.830846 | Q23: 63.108031 | R23: 63.681998 | S23: 74.373731 | T23: 74.373731 | U23: 74.373731 | V23: 74.373731 | W23: 75.929718 | X23: 75.929718 | Y23: 75.929718 | Z23: 87.704412 | AA23: 81.06214 | AB23: 89.652296 | AC23: 98.302969 | AD23: =+SUMIF('Monthly Detail'!$4:$4, $B$14,'Monthly Detail'!35:35) | AE23: =+SUMIF('[1]Monthly Detail'!$4:$4, AD15,'[1]Monthly Detail'!33:33) | AF23: =+SUMIF('[1]Monthly Detail'!$4:$4, AE15,'[1]Monthly Detail'!33:33) | AG23: =+SUMIF('[1]Monthly Detail'!$4:$4, AF15,'[1]Monthly Detail'!33:33) | AH23: =+SUMIF('[1]Monthly Detail'!$4:$4, AG15,'[1]Monthly Detail'!33:33) | AI23: =+SUMIF('[1]Monthly Detail'!$4:$4, AH15,'[1]Monthly Detail'!33:33) | AJ23: =+SUMIF('[1]Monthly Detail'!$4:$4, AI15,'[1]Monthly Detail'!33:33) | AK23: =+SUMIF('[1]Monthly Detail'!$4:$4, AJ15,'[1]Monthly Detail'!33:33) | AL23: =+SUMIF('[1]Monthly Detail'!$4:$4, AK15,'[1]Monthly Detail'!33:33) | AM23: =+SUMIF('[1]Monthly Detail'!$4:$4, AL15,'[1]Monthly Detail'!33:33) | AN23: 60.531353 | AO23: 84.475686 | AP23: 66.746888 | AQ23: 63.635896 | AT23: 80.618947 | AU23: 82.772908 | AV23: 70.433155 | AW23: 80.31802 | AX23: 76.441493 | AY23: 78.664921 | AZ23: 79.79538 | BA23: 109.77778 | BB23: 109.77778 | BC23: 109.77778 | BD23: 109.77778 | BE23: 109.77778 | BF23: =+SUMIF('Monthly Detail'!$4:$4, $B$14,'Monthly Detail'!35:35) | BG23: 62.5 | BH23: 62.5 | BI23: 62.5 | BJ23: 62.5 | BK23: 62.5 | BL23: 62.5 | BM23: 62.5 | BN23: 62.5 | BO23: 62.5 | BP23: 62.5 | BQ23: 62.5 | BR23: 62.5 | BS23: 76.028235 | BT23: 75.085554 | BU23: 73.972048 | BV23: 74.094669 | BW23: 75.205939 | BX23: 76.567142 | BY23: 77.054738 | BZ23: 76.68896 | CA23: 78.676419 | CB23: 78.861731 | CC23: 79.058869 | CD23: 74.373731 | CE23: =BF23-AD23 | CF23: =BF23-CC23
CE24: =BF24-AD24 | CF24: =BF24-CC24
C25: Utilization % | D25: 0.025 | E25: 0.02625 | F25: 0.02625 | G25: 0.02625 | H25: 0.02625 | I25: 0.013060516 | J25: 0.013980263 | K25: 0.010733696 | L25: 0.016294643 | M25: 0.02667298 | N25: 0.019886364 | O25: 0.024804687 | P25: 0.02409897 | Q25: 0.024192116 | R25: 0.01640625 | S25: 0.011945983 | T25: 0.011945983 | U25: 0.011945983 | V25: 0.011945983 | W25: 0.017931548 | X25: 0.017931548 | Y25: 0.017931548 | Z25: 0.025710227 | AA25: 0.0331564 | AB25: 0.020301871 | AC25: 0.023975317 | AD25: =+SUMIF('Monthly Detail'!$4:$4, $B$14,'Monthly Detail'!51:51) | AE25: =+SUMIF('[1]Monthly Detail'!$4:$4, AD15,'[1]Monthly Detail'!49:49) | AF25: =+SUMIF('[1]Monthly Detail'!$4:$4, AE15,'[1]Monthly Detail'!49:49) | AG25: =+SUMIF('[1]Monthly Detail'!$4:$4, AF15,'[1]Monthly Detail'!49:49) | AH25: =+SUMIF('[1]Monthly Detail'!$4:$4, AG15,'[1]Monthly Detail'!49:49) | AI25: =+SUMIF('[1]Monthly Detail'!$4:$4, AH15,'[1]Monthly Detail'!49:49) | AJ25: =+SUMIF('[1]Monthly Detail'!$4:$4, AI15,'[1]Monthly Detail'!49:49) | AK25: =+SUMIF('[1]Monthly Detail'!$4:$4, AJ15,'[1]Monthly Detail'!49:49) | AL25: =+SUMIF('[1]Monthly Detail'!$4:$4, AK15,'[1]Monthly Detail'!49:49) | AM25: =+SUMIF('[1]Monthly Detail'!$4:$4, AL15,'[1]Monthly Detail'!49:49) | AN25: 0.023283103 | AO25: 0.019921875 | AP25: 0.025710227 | AQ25: 0.0331564 | AT25: 0.017755682 | AU25: 0.017949085 | AV25: 0.021173007 | AW25: 0.022544643 | AX25: 0.024925595 | AY25: 0.011795949 | AZ25: 0.021519886 | BA25: 0.015 | BB25: 0.015 | BC25: 0.015 | BD25: 0.015 | BE25: 0.015 | BF25: =+SUMIF('Monthly Detail'!$4:$4, $B$14,'Monthly Detail'!51:51) | BG25: 0.013060516 | BH25: 0.013980263 | BI25: 0.010733696 | BJ25: 0.016294643 | BK25: 0.026041667 | BL25: 0.019649621 | BM25: 0.028794643 | BN25: 0.02613491 | BO25: 0.027532328 | BP25: 0.016601562 | BQ25: 0.016601562 | BR25: 0.011253463 | BS25: 0.029563492 | BT25: 0.029563492 | BU25: 0.017931548 | BV25: 0.023312166 | BW25: 0.024320652 | BX25: 0.015494792 | BY25: 0.025710227 | BZ25: 0.0331564 | CA25: 0.020301871 | CB25: 0.023975317 | CC25: 0.017755682 | CD25: 0.011945983 | CE25: =BF25-AD25 | CF25: =BF25-CC25
B26: Expenses | CE26: =BF26-AD26 | CF26: =BF26-CC26
B27: Subcontractors | M27: 0 | N27: 0 | O27: 650 | P27: 1612.624 | Q27: 3394.8663 | R27: 1928.1833 | S27: 0 | T27: 0 | U27: 0 | V27: 0 | W27: 450 | X27: 450 | Y27: 450 | Z27: 981.65746 | AA27: 4023.9944 | AB27: 450 | AC27: 1081.7708 | AD27: =+SUMIF('Monthly Detail'!$4:$4, $B$14,'Monthly Detail'!65:65) | AN27: 0 | AO27: 0 | AP27: 610 | AQ27: 900 | AT27: 170 | AU27: 599 | AV27: 0 | AW27: 450 | AX27: 0 | AY27: 0 | AZ27: 270 | BA27: 0 | BB27: 0 | BC27: 0 | BD27: 0 | BE27: 0 | BF27: =+SUMIF('Monthly Detail'!$4:$4, $B$14,'Monthly Detail'!65:65) | BK27: 0 | BL27: 0 | BM27: 0 | BN27: 0 | BO27: 1035.7414 | BP27: 0 | BR27: 0 | BS27: 919.6069 | BT27: 2106.1905 | BU27: 600 | BV27: 1173.2353 | BW27: 2952.0761 | BX27: 600 | BY27: 1649 | BZ27: 3994.4258 | CA27: 821.63265 | CB27: 1007.8125 | CC27: 82.141148 | CD27: 0 | CE27: =BF27-AD27 | CF27: =BF27-CC27
B28: Gross Proft | D28: =+D2-D27 | E28: =+E2-E27 | F28: 5166.6267 | G28: 3957.7217 | H28: 7569.7233 | I28: 2255.7185 | J28: 1022.188 | K28: 1435.4299 | L28: 3942.5625 | M28: 4387.4071 | N28: 3311.2272 | O28: =+O16-O27 | P28: 7458.0193 | Q28: 8122.6854 | R28: 6442.7091 | S28: 4937.9286 | T28: 4937.9286 | U28: 4937.9286 | V28: 4937.9286 | W28: 6179.6135 | X28: 6179.6135 | Y28: 6179.6135 | Z28: 9595.4946 | AA28: 13204.134 | AB28: 16642.79 | AC28: 22769.499 | AD28: =+BD16-BD27 | AE28: =+AD2-AD27 | AF28: =+AE2-AE27 | AG28: =+AF2-AF27 | AH28: =+AG2-AG27 | AI28: =+AH2-AH27 | AJ28: =+AI2-AI27 | AK28: =+AJ2-AJ27 | AL28: =+AK2-AK27 | AM28: =+AL2-AL27 | AN28: 5015.13 | AO28: 4308.26 | AP28: 8450.89 | AQ28: 13211.26 | AT28: 9403.5 | AU28: 4595 | AV28: 6585.5 | AW28: 7662.12 | AX28: 7682.37 | AY28: 3756.25 | AZ28: 5774.5 | BA28: 6916 | BB28: 6916 | BC28: 6916 | BD28: 6916 | BE28: 6916 | BF28: =+BD16-BD27 | BG28: =+BE2-BE27 | BH28: =+BF2-BF27 | BI28: =+BG2-BG27 | BJ28: =+BH2-BH27 | BK28: =+BI2-BI27 | BL28: =+BJ16-BJ27 | BM28: =+BK16-BK27 | BN28: =+BL16-BL27 | BO28: =+BM2-BM27 | BP28: 0 | BQ28: =+BO2-BO27 | BR28: =+BP16-BP27 | BS28: 8623.7468 | BT28: 10608.773 | BU28: 6887.4507 | BV28: 8676.5614 | BW28: 7799.8555 | BX28: 5219.9642 | BY28: 9229.588 | BZ28: 11896.618 | CA28: 11322.795 | CB28: 14647.473 | CC28: 8731.126 | CD28: 6298.8782 | CE28: =BF28-AD28 | CF28: =BF28-CC28
B29: GM% | J29: =+J28/J2 | K29: 0.59259456 | L29: 0.8878797 | M29: 0.72582965 | N29: 0.8206235 | O29: =+O28/O16 | P29: 0.82221503 | Q29: 0.7052441 | R29: 0.76965618 | S29: 0.89181728 | T29: 0.89181728 | U29: 0.89181728 | V29: 0.89181728 | W29: 0.93212274 | X29: 0.93212274 | Y29: 0.93212274 | Z29: 0.90719076 | AA29: 0.76642882 | AB29: 0.97367311 | AC29: 0.95464515 | AD29: =+BD28/BD16 | AK29: 0.87906392 | AL29: 0.87906392 | AM29: 0.87906392 | AN29: 0.87906392 | AO29: 1 | AP29: 0.9326777 | AQ29: 0.93622115 | AT29: 0.98224265 | AU29: 0.88467462 | AV29: 1 | AW29: 0.94452745 | AX29: 1 | AY29: 1 | AZ29: 0.95533129 | BA29: 1 | BB29: 1 | BC29: 1 | BD29: 1 | BE29: 1 | BF29: =+BD28/BD16 | BG29: =+BE28/BE16 | BH29: =+BF28/BF16 | BI29: =+BG28/BG16 | BJ29: =+BH28/BH16 | BK29: =+BI28/BI16 | BL29: =+BJ28/BJ16 | BM29: =+BK28/BK16 | ... BO29: =+BM28/BM16 | BP29: 0 | BQ29: =+BO28/BO16 | BR29: =+BP28/BP16 | BS29: 0.90363902 | BT29: 0.8343534 | BU29: 0.91986592 | BV29: 0.88088736 | BW29: 0.7254376 | BX29: 0.89690658 | BY29: 0.84841783 | BZ29: 0.74863667 | CA29: 0.93234489 | CB29: 0.93562478 | CC29: 0.99067983 | CD29: 1 | CE29: =BF29-AD29 | CF29: =BF29-CC29
B30: Events | J30: 1179.44 | K30: 0 | L30: 2358.88 | M30: 1179.44 | N30: 0 | O30: 0 | P30: 0 | Q30: 1400 | R30: 0 | S30: 0 | W30: 0 | X30: 0 | Y30: 0 | Z30: 0 | AA30: 0 | AB30: 0 | AC30: 0 | AD30: =+SUMIF('Monthly Detail'!$4:$4, $B$14,'Monthly Detail'!71:71) | AK30: =+SUMIF('[1]Monthly Detail'!$4:$4, AJ15,'[1]Monthly Detail'!69:69) | AL30: =+SUMIF('[1]Monthly Detail'!$4:$4, AK15,'[1]Monthly Detail'!69:69) | AM30: =+SUMIF('[1]Monthly Detail'!$4:$4, AL15,'[1]Monthly Detail'!69:69) | AN30: 0 | AO30: 665.56 | AP30: 0 | AQ30: 0 | AT30: 0 | AU30: 0 | AV30: 0 | AW30: 0 | AX30: 0 | AY30: 0 | AZ30: 0 | BA30: 0 | BB30: 0 | BC30: 0 | BD30: 0 | BE30: 0 | BF30: =+SUMIF('Monthly Detail'!$4:$4, $B$14,'Monthly Detail'!71:71) | BH30: 0 | BL30: 0 | BM30: 0 | BN30: 0 | BP30: 0 | BR30: 0 | BS30: 0 | BT30: 0 | BU30: 0 | BV30: 0 | BW30: 0 | BX30: 0 | BY30: 0 | BZ30: 0 | CA30: 0 | CB30: 0 | CC30: 0 | CD30: 0 | CE30: =BF30-AD30 | CF30: =BF30-CC30
B31: Owner Payroll Burden | W31: 2172.5375 | X31: 2172.5375 | Y31: 2172.5375 | Z31: 3660.1 | AA31: 3660.1 | AB31: 5274.85 | AC31: 12810.35 | AD31: =+SUMIF('Monthly Detail'!$4:$4, $B$14,'Monthly Detail'!80:80) | AV31: 2407.42 | AW31: 5055.82 | AX31: 4826.3 | AY31: 2637.43 | AZ31: 2109.94 | BA31: 2637.42 | BB31: 2637.42 | BC31: 2637.42 | BD31: 2637.42 | BE31: 2637.42 | BF31: =+SUMIF('Monthly Detail'!$4:$4, $B$14,'Monthly Detail'!80:80) | BS31: 2367.8875 | BT31: 2172.5375 | BU31: 2172.5375 | BV31: 2172.5375 | BW31: 2172.5375 | BX31: 2172.5375 | BY31: 2172.5375 | BZ31: 2172.5375 | CA31: 2172.5375 | CB31: 2172.5375 | CC31: 2172.5375 | CD31: 2172.5375 | CE31: =BF31-AD31 | CF31: =BF31-CC31
B32: Travel | O32: 0 | P32: 75 | Q32: 75 | R32: 75 | S32: 75 | T32: 75 | U32: 75 | V32: 75 | W32: 75 | X32: 75 | Y32: 75 | Z32: 75 | AA32: 75 | AB32: 75 | AC32: 75 | AD32: =+SUMIF('Monthly Detail'!$4:$4, $B$14,'Monthly Detail'!84:84) | AP32: 17.54 | AQ32: 15.71 | AT32: 0 | AU32: 0 | AV32: 0 | AW32: 0 | AX32: 0 | AY32: 0 | AZ32: 44.17 | BA32: 49.63 | BB32: 49.63 | BC32: 49.63 | BD32: 49.63 | BE32: 49.63 | BF32: =+SUMIF('Monthly Detail'!$4:$4, $B$14,'Monthly Detail'!84:84) | BM32: 0 | BN32: 0 | BP32: 0 | BR32: 0 | BS32: 75 | BT32: 75 | BU32: 75 | BV32: 75 | BW32: 75 | BX32: 75 | BY32: 75 | BZ32: 75 | CA32: 75 | CB32: 75 | CC32: 75 | CD32: 75 | CE32: =BF32-AD32 | CF32: =BF32-CC32
B33: Computer & Software | D33: 12 | E33: 12 | F33: 12 | G33: 12 | H33: 12 | I33: 12 | J33: 12 | K33: 12 | L33: 12 | M33: 12 | N33: 114.89833 | O33: 1300.7667 | P33: 111.76667 | Q33: 304.78667 | R33: 303.21333 | S33: 316.34833 | T33: 316.34833 | U33: 316.34833 | V33: 316.34833 | W33: 150 | X33: 150 | Y33: 150 | Z33: 150 | AA33: 150 | AB33: 150 | AC33: 150 | AD33: =+SUMIF('Monthly Detail'!$4:$4, $B$14,'Monthly Detail'!85:85) | AE33: =+SUMIF('[1]Monthly Detail'!$4:$4, AD15,'[1]Monthly Detail'!83:83) | AF33: =+SUMIF('[1]Monthly Detail'!$4:$4, AE15,'[1]Monthly Detail'!83:83) | AG33: =+SUMIF('[1]Monthly Detail'!$4:$4, AF15,'[1]Monthly Detail'!83:83) | AH33: =+SUMIF('[1]Monthly Detail'!$4:$4, AG15,'[1]Monthly Detail'!83:83) | AI33: =+SUMIF('[1]Monthly Detail'!$4:$4, AH15,'[1]Monthly Detail'!83:83) | AJ33: =+SUMIF('[1]Monthly Detail'!$4:$4, AI15,'[1]Monthly Detail'!83:83) | AK33: =+SUMIF('[1]Monthly Detail'!$4:$4, AJ15,'[1]Monthly Detail'!83:83) | AL33: =+SUMIF('[1]Monthly Detail'!$4:$4, AK15,'[1]Monthly Detail'!83:83) | AM33: =+SUMIF('[1]Monthly Detail'!$4:$4, AL15,'[1]Monthly Detail'!83:83) | AN33: 154.47 | AO33: 310.12 | AP33: 1251.13 | AQ33: 14.81 | AT33: 100.41 | AU33: 107.82 | AV33: 218.17 | AW33: 118.63 | AX33: 118.81 | AY33: 202.32 | AZ33: 241.38 | BA33: 433.68 | BB33: 433.68 | BC33: 433.68 | BD33: 433.68 | BE33: 433.68 | BF33: =+SUMIF('Monthly Detail'!$4:$4, $B$14,'Monthly Detail'!85:85) | BG33: 12 | BH33: 12 | BI33: 12 | BJ33: 12 | BK33: 12 | BL33: 12 | BM33: 12 | BN33: 12 | BO33: 12 | BP33: 12 | BQ33: 12 | BR33: 12 | BS33: 150 | BT33: 150 | BU33: 150 | BV33: 150 | BW33: 150 | BX33: 150 | BY33: 150 | BZ33: 150 | CA33: 150 | CB33: 150 | CC33: 150 | CD33: 150 | CE33: =BF33-AD33 | CF33: =BF33-CC33
B34: Donations/Gifts | D34: 100 | E34: 100 | F34: 100 | G34: 100 | H34: 100 | I34: 100 | J34: 100 | K34: 100 | L34: 100 | M34: 100 | N34: 100 | O34: 100 | P34: 100 | Q34: 100 | R34: 100 | S34: 100 | T34: 100 | U34: 100 | V34: 100 | W34: 100 | X34: 100 | Y34: 100 | Z34: 100 | AA34: 100 | AB34: 100 | AC34: 100 | AD34: =+SUMIF('Monthly Detail'!$4:$4, $B$14,'Monthly Detail'!86:86) | AE34: =+SUMIF('[1]Monthly Detail'!$4:$4, AD15,'[1]Monthly Detail'!84:84) | AF34: =+SUMIF('[1]Monthly Detail'!$4:$4, AE15,'[1]Monthly Detail'!84:84) | AG34: =+SUMIF('[1]Monthly Detail'!$4:$4, AF15,'[1]Monthly Detail'!84:84) | AH34: =+SUMIF('[1]Monthly Detail'!$4:$4, AG15,'[1]Monthly Detail'!84:84) | AI34: =+SUMIF('[1]Monthly Detail'!$4:$4, AH15,'[1]Monthly Detail'!84:84) | AJ34: =+SUMIF('[1]Monthly Detail'!$4:$4, AI15,'[1]Monthly Detail'!84:84) | AK34: =+SUMIF('[1]Monthly Detail'!$4:$4, AJ15,'[1]Monthly Detail'!84:84) | AL34: =+SUMIF('[1]Monthly Detail'!$4:$4, AK15,'[1]Monthly Detail'!84:84) | AM34: =+SUMIF('[1]Monthly Detail'!$4:$4, AL15,'[1]Monthly Detail'!84:84) | AN34: 141.19 | AO34: 0 | AP34: 0 | AQ34: 0 | AT34: 472.9 | AU34: 45 | AV34: 485 | AW34: 424 | AX34: 152.63 | AY34: 0 | AZ34: 246.05 | BA34: 100 | BB34: 100 | BC34: 100 | BD34: 100 | BE34: 100 | BF34: =+SUMIF('Monthly Detail'!$4:$4, $B$14,'Monthly Detail'!86:86) | BG34: 100 | BH34: 100 | BI34: 100 | BJ34: 100 | BK34: 100 | BL34: 100 | BM34: 100 | BN34: 100 | BO34: 100 | BP34: 100 | BQ34: 100 | BR34: 100 | BS34: 100 | BT34: 0 | BU34: 0 | BV34: 50 | BW34: 0 | BX34: 0 | BY34: 50 | BZ34: 0 | CA34: 0 | CB34: 50 | CC34: 50 | CD34: 50 | CE34: =BF34-AD34 | CF34: =BF34-CC34
B35: Fees/Subscriptions | D35: 0 | E35: 0 | F35: 0 | G35: 13.86 | H35: 0 | I35: 0 | J35: 0 | K35: 0 | L35: 0 | M35: 0 | N35: 0 | O35: 0 | P35: 0 | Q35: 42.58 | R35: 42.58 | S35: 42.58 | T35: 42.58 | U35: 42.58 | V35: 42.58 | W35: 42.58 | X35: 42.58 | Y35: 42.58 | Z35: 0 | AA35: 0 | AB35: 0 | AC35: 0 | AD35: =+SUMIF('Monthly Detail'!$4:$4, $B$14,'Monthly Detail'!87:87) | AE35: =+SUMIF('[1]Monthly Detail'!$4:$4, AD15,'[1]Monthly Detail'!85:85) | AF35: =+SUMIF('[1]Monthly Detail'!$4:$4, AE15,'[1]Monthly Detail'!85:85) | AG35: =+SUMIF('[1]Monthly Detail'!$4:$4, AF15,'[1]Monthly Detail'!85:85) | AH35: =+SUMIF('[1]Monthly Detail'!$4:$4, AG15,'[1]Monthly Detail'!85:85) | AI35: =+SUMIF('[1]Monthly Detail'!$4:$4, AH15,'[1]Monthly Detail'!85:85) | AJ35: =+SUMIF('[1]Monthly Detail'!$4:$4, AI15,'[1]Monthly Detail'!85:85) | AK35: =+SUMIF('[1]Monthly Detail'!$4:$4, AJ15,'[1]Monthly Detail'!85:85) | AL35: =+SUMIF('[1]Monthly Detail'!$4:$4, AK15,'[1]Monthly Detail'!85:85) | AM35: =+SUMIF('[1]Monthly Detail'!$4:$4, AL15,'[1]Monthly Detail'!85:85) | AN35: 0 | AO35: 0 | AP35: 0 | AQ35: 42.58 | AT35: 0 | AU35: 0 | AV35: 0 | AW35: 0 | AX35: 0 | AY35: 0 | AZ35: 0 | BA35: 0 | BB35: 0 | BC35: 0 | BD35: 0 | BE35: 0 | BF35: =+SUMIF('Monthly Detail'!$4:$4, $B$14,'Monthly Detail'!87:87) | BG35: 0 | BH35: 0 | BI35: 0 | BJ35: 0 | BK35: 0 | BL35: 0 | BM35: 0 | BN35: 0 | BO35: 0 | BP35: 0 | BQ35: 0 | BR35: 0 | BS35: 42.58 | BT35: 42.58 | BU35: 42.58 | BV35: 42.58 | BW35: 42.58 | BX35: 42.58 | BY35: 42.58 | BZ35: 42.58 | CA35: 42.58 | CB35: 42.58 | CC35: 42.58 | CD35: 42.58 | CE35: =BF35-AD35 | CF35: =BF35-CC35
B36: Finance & Accounting | D36: 75 | E36: 225 | F36: 75 | G36: 75 | H36: 225 | I36: 75 | J36: 112.5 | K36: 225 | L36: 75 | M36: 75 | N36: 225 | O36: 150 | P36: 200 | Q36: 200 | R36: 200 | S36: 200 | T36: 200 | U36: 200 | V36: 200 | W36: 200 | X36: 200 | Y36: 200 | Z36: 375 | AA36: 500 | AB36: 275 | AC36: 600 | AD36: =+SUMIF('Monthly Detail'!$4:$4, $B$14,'Monthly Detail'!88:88) | AE36: =+SUMIF('[1]Monthly Detail'!$4:$4, AD15,'[1]Monthly Detail'!86:86) | AF36: =+SUMIF('[1]Monthly Detail'!$4:$4, AE15,'[1]Monthly Detail'!86:86) | AG36: =+SUMIF('[1]Monthly Detail'!$4:$4, AF15,'[1]Monthly Detail'!86:86) | AH36: =+SUMIF('[1]Monthly Detail'!$4:$4, AG15,'[1]Monthly Detail'!86:86) | AI36: =+SUMIF('[1]Monthly Detail'!$4:$4, AH15,'[1]Monthly Detail'!86:86) | AJ36: =+SUMIF('[1]Monthly Detail'!$4:$4, AI15,'[1]Monthly Detail'!86:86) | AK36: =+SUMIF('[1]Monthly Detail'!$4:$4, AJ15,'[1]Monthly Detail'!86:86) | AL36: =+SUMIF('[1]Monthly Detail'!$4:$4, AK15,'[1]Monthly Detail'!86:86) | AM36: =+SUMIF('[1]Monthly Detail'!$4:$4, AL15,'[1]Monthly Detail'!86:86) | AN36: 75 | AO36: 225 | AP36: 185 | AQ36: 207.5 | AT36: 241.25 | AU36: 140 | AV36: 711.25 | AW36: 412.5 | AX36: 1155.73 | AY36: 415 | AZ36: 356.25 | BA36: 281.25 | BB36: 281.25 | BC36: 281.25 | BD36: 281.25 | BE36: 281.25 | BF36: =+SUMIF('Monthly Detail'!$4:$4, $B$14,'Monthly Detail'!88:88) | BG36: 75 | BH36: 75 | BI36: 225 | BJ36: 75 | BK36: 75 | BL36: 225 | BM36: 75 | BN36: 75 | BO36: 225 | BP36: 75 | BQ36: 75 | BR36: 225 | BS36: 200 | BT36: 200 | BU36: 600 | BV36: 350 | BW36: 200 | BX36: 200 | BY36: 350 | BZ36: 200 | CA36: 200 | CB36: 350 | CC36: 200 | CD36: 200 | CE36: =BF36-AD36 | CF36: =BF36-CC36
B37: Bank Fees | D37: 28.905 | E37: 20.336667 | F37: 58.913333 | G37: 38.105 | H37: 30.791667 | I37: 31.454 | J37: 23.345 | K37: 17.718333 | L37: 9.9583333 | M37: 5.8833333 | N37: 2.45 | O37: 2.45 | P37: 8.28 | Q37: 13.216667 | R37: 21.366667 | S37: 30.3 | T37: 30.3 | U37: 30.3 | V37: 30.3 | W37: 29 | X37: 29 | Y37: 29 | Z37: 13 | AA37: 10.4 | AB37: 8.6666667 | AC37: 0.33333333 | AD37: =+SUMIF('Monthly Detail'!$4:$4, $B$14,'Monthly Detail'!89:89) | AE37: =+SUMIF('[1]Monthly Detail'!$4:$4, AD15,'[1]Monthly Detail'!87:87) | AF37: =+SUMIF('[1]Monthly Detail'!$4:$4, AE15,'[1]Monthly Detail'!87:87) | AG37: =+SUMIF('[1]Monthly Detail'!$4:$4, AF15,'[1]Monthly Detail'!87:87) | AH37: =+SUMIF('[1]Monthly Detail'!$4:$4, AG15,'[1]Monthly Detail'!87:87) | AI37: =+SUMIF('[1]Monthly Detail'!$4:$4, AH15,'[1]Monthly Detail'!87:87) | AJ37: =+SUMIF('[1]Monthly Detail'!$4:$4, AI15,'[1]Monthly Detail'!87:87) | AK37: =+SUMIF('[1]Monthly Detail'!$4:$4, AJ15,'[1]Monthly Detail'!87:87) | AL37: =+SUMIF('[1]Monthly Detail'!$4:$4, AK15,'[1]Monthly Detail'!87:87) | AM37: =+SUMIF('[1]Monthly Detail'!$4:$4, AL15,'[1]Monthly Detail'!87:87) | AN37: 3.5 | AO37: 0 | AP37: 31.6 | AQ37: 0 | AT37: 0 | AU37: 0 | AV37: 0 | AW37: 0 | AX37: 52 | AY37: 0 | AZ37: 0 | BA37: 0 | BB37: 0 | BC37: 0 | BD37: 0 | BE37: 0 | BF37: =+SUMIF('Monthly Detail'!$4:$4, $B$14,'Monthly Detail'!89:89) | BG37: 31.454 | BH37: 31.454 | BI37: 31.454 | BJ37: 31.454 | BK37: 31.454 | BL37: 31.454 | BM37: 31.454 | BN37: 31.454 | BO37: 31.454 | BP37: 31.454 | BQ37: 31.454 | BR37: 31.454 | BS37: 29 | BT37: 30.3 | BU37: 30.3 | BV37: 30.3 | BW37: 30.3 | BX37: 30.3 | BY37: 30.3 | BZ37: 30.3 | CA37: 30.3 | CB37: 30.3 | CC37: 30.3 | CD37: 30.3 | CE37: =BF37-AD37 | CF37: =BF37-CC37
B38: Meals and Entertainment | D38: 0 | F38: 0 | G38: 0 | H38: 0 | J38: 0 | K38: 0 | L38: 0 | M38: 0 | N38: 0 | O38: 0 | P38: 218.02 | Q38: 106.49667 | R38: 121.3 | S38: 289.14 | T38: 289.14 | U38: 289.14 | V38: 289.14 | W38: 295.735 | X38: 295.735 | Y38: 295.735 | Z38: 225.6 | AA38: 294.6475 | AB38: 352.7975 | AC38: 358.896 | AD38: =+SUMIF('Monthly Detail'!$4:$4, $B$14,'Monthly Detail'!90:90) | AE38: =+SUMIF('[1]Monthly Detail'!$4:$4, AD15,'[1]Monthly Detail'!88:88) | AF38: =+SUMIF('[1]Monthly Detail'!$4:$4, AE15,'[1]Monthly Detail'!88:88) | AG38: =+SUMIF('[1]Monthly Detail'!$4:$4, AF15,'[1]Monthly Detail'!88:88) | AH38: =+SUMIF('[1]Monthly Detail'!$4:$4, AG15,'[1]Monthly Detail'!88:88) | AI38: =+SUMIF('[1]Monthly Detail'!$4:$4, AH15,'[1]Monthly Detail'!88:88) | AJ38: =+SUMIF('[1]Monthly Detail'!$4:$4, AI15,'[1]Monthly Detail'!88:88) | AK38: =+SUMIF('[1]Monthly Detail'!$4:$4, AJ15,'[1]Monthly Detail'!88:88) | AL38: =+SUMIF('[1]Monthly Detail'!$4:$4, AK15,'[1]Monthly Detail'!88:88) | AM38: =+SUMIF('[1]Monthly Detail'!$4:$4, AL15,'[1]Monthly Detail'!88:88) | AN38: 0 | AO38: 0 | AP38: 218.02 | AQ38: 57.06 | AT38: 837.07 | AU38: 0 | AV38: 50 | AW38: 251.46 | AX38: 0 | AY38: 0 | AZ38: 285.65 | BA38: 315.29 | BB38: 315.29 | BC38: 315.29 | BD38: 315.29 | BE38: 315.29 | BF38: =+SUMIF('Monthly Detail'!$4:$4, $B$14,'Monthly Detail'!90:90) | BL38: 0 | BM38: 0 | BN38: 0 | BS38: 247.135 | BT38: 289.14 | BU38: 289.14 | BV38: 289.14 | BW38: 289.14 | BX38: 289.14 | BY38: 289.14 | BZ38: 289.14 | CA38: 289.14 | CB38: 289.14 | CC38: 289.14 | CD38: 289.14 | CE38: =BF38-AD38 | CF38: =BF38-CC38
B39: QBO Fees | D39: 93.21 | E39: 194.71 | F39: 210.47 | G39: 313.34 | H39: 226.36 | I39: 105.16 | J39: 124.93 | K39: 156.19 | L39: 141.67 | M39: 145.28 | N39: 141.1 | O39: 247.63911 | P39: 339.03334 | Q39: 335.89848 | R39: 257.52077 | S39: 178.52795 | T39: 178.52795 | U39: 178.52795 | V39: 178.52795 | W39: 238.92855 | X39: 238.92855 | Y39: 238.92855 | Z39: 364.67415 | AA39: 509.55028 | AB39: 527.38243 | AC39: 677.12335 | AD39: =+SUMIF('Monthly Detail'!$4:$4, $B$14,'Monthly Detail'!91:91) | AE39: =+SUMIF('[1]Monthly Detail'!$4:$4, AD15,'[1]Monthly Detail'!89:89) | AF39: =+SUMIF('[1]Monthly Detail'!$4:$4, AE15,'[1]Monthly Detail'!89:89) | AG39: =+SUMIF('[1]Monthly Detail'!$4:$4, AF15,'[1]Monthly Detail'!89:89) | AH39: =+SUMIF('[1]Monthly Detail'!$4:$4, AG15,'[1]Monthly Detail'!89:89) | AI39: =+SUMIF('[1]Monthly Detail'!$4:$4, AH15,'[1]Monthly Detail'!89:89) | AJ39: =+SUMIF('[1]Monthly Detail'!$4:$4, AI15,'[1]Monthly Detail'!89:89) | AK39: =+SUMIF('[1]Monthly Detail'!$4:$4, AJ15,'[1]Monthly Detail'!89:89) | AL39: =+SUMIF('[1]Monthly Detail'!$4:$4, AK15,'[1]Monthly Detail'!89:89) | AM39: =+SUMIF('[1]Monthly Detail'!$4:$4, AL15,'[1]Monthly Detail'!89:89) | AN39: 173.37 | AO39: 236.32 | AP39: 228.28 | AQ39: 404.2 | AT39: 315.97 | AU39: 199.98 | AV39: 229.96 | AW39: 281.21 | AX39: 303.5 | AY39: 167.72 | AZ39: 171.91 | BA39: 212.1 | BB39: 212.1 | BC39: 212.1 | BD39: 212.1 | BE39: 212.1 | BF39: =+SUMIF('Monthly Detail'!$4:$4, $B$14,'Monthly Detail'!91:91) | BG39: 105.16 | BH39: 105.16 | BI39: 105.16 | BJ39: 105.16 | BK39: 105.16 | BL39: 105.16 | BM39: 105.16 | BN39: 105.16 | BO39: 105.16 | BP39: 105.16 | BQ39: 105.16 | BR39: 105.16 | BS39: 340.05685 | BT39: 409.97033 | BU39: 241.41891 | BV39: 317.58835 | BW39: 346.67601 | BX39: 187.65391 | BY39: 350.75981 | BZ39: 512.37713 | CA39: 391.57446 | CB39: 504.77555 | CC39: 284.16739 | CD39: 203.0956 | CE39: =BF39-AD39 | CF39: =BF39-CC39
B40: Professional/Legal Fees | D40: 0 | E40: 0 | F40: 0 | G40: 171.41667 | H40: 234.625 | I40: 296.16667 | J40: 416.75 | K40: 316.75 | L40: 0 | M40: 0 | N40: 0 | O40: 0 | P40: 0 | Q40: 490 | R40: 376.25 | S40: 376.25 | T40: 376.25 | U40: 376.25 | V40: 376.25 | W40: 262.5 | X40: 262.5 | Y40: 262.5 | Z40: 471.25 | AA40: 405.83333 | AB40: 326.375 | AC40: 199.5 | AD40: =+SUMIF('Monthly Detail'!$4:$4, $B$14,'Monthly Detail'!92:92) | AE40: =+SUMIF('[1]Monthly Detail'!$4:$4, AD15,'[1]Monthly Detail'!90:90) | AF40: =+SUMIF('[1]Monthly Detail'!$4:$4, AE15,'[1]Monthly Detail'!90:90) | AG40: =+SUMIF('[1]Monthly Detail'!$4:$4, AF15,'[1]Monthly Detail'!90:90) | AH40: =+SUMIF('[1]Monthly Detail'!$4:$4, AG15,'[1]Monthly Detail'!90:90) | AI40: =+SUMIF('[1]Monthly Detail'!$4:$4, AH15,'[1]Monthly Detail'!90:90) | AJ40: =+SUMIF('[1]Monthly Detail'!$4:$4, AI15,'[1]Monthly Detail'!90:90) | AK40: =+SUMIF('[1]Monthly Detail'!$4:$4, AJ15,'[1]Monthly Detail'!90:90) | AL40: =+SUMIF('[1]Monthly Detail'!$4:$4, AK15,'[1]Monthly Detail'!90:90) | AM40: =+SUMIF('[1]Monthly Detail'!$4:$4, AL15,'[1]Monthly Detail'!90:90) | AN40: 0 | AO40: 0 | AP40: 0 | AQ40: 490 | AT40: 0 | AU40: 0 | AV40: 0 | AW40: 0 | AX40: 707 | AY40: 235.5 | AZ40: 0 | BA40: 0 | BB40: 0 | BC40: 0 | BD40: 0 | BE40: 0 | BF40: =+SUMIF('Monthly Detail'!$4:$4, $B$14,'Monthly Detail'!92:92) | BG40: 296.16667 | BH40: 296.16667 | BI40: 296.16667 | BJ40: 296.16667 | BK40: 296.16667 | BL40: 296.16667 | BM40: 296.16667 | BN40: 296.16667 | BO40: 296.16667 | BP40: 296.16667 | BQ40: 296.16667 | BR40: 296.16667 | BS40: 376.25 | BT40: 0 | BU40: 0 | BV40: 0 | BW40: 0 | BX40: 0 | BY40: 0 | BZ40: 490 | CA40: 0 | CB40: 262.5 | CC40: 0 | CD40: 376.25 | CE40: =BF40-AD40 | CF40: =BF40-CC40
B41: Utilities | D41: 170.51667 | E41: 199.5075 | F41: 187.24 | G41: 199.92667 | H41: 190.87 | I41: 190.98 | J41: 183.86833 | K41: 159.19167 | L41: 159.23333 | M41: 139.66833 | N41: 140.33833 | O41: 141.00833 | P41: 202.29 | Q41: 378.53 | R41: 260.35 | S41: 169.03 | T41: 169.03 | U41: 169.03 | V41: 169.03 | W41: 155.68 | X41: 155.68 | Y41: 155.68 | Z41: 123.01 | AA41: 123.01 | AB41: 122.99 | AC41: 161.99 | AD41: =+SUMIF('Monthly Detail'!$4:$4, $B$14,'Monthly Detail'!93:93) | AE41: =+SUMIF('[1]Monthly Detail'!$4:$4, AD15,'[1]Monthly Detail'!91:91) | AF41: =+SUMIF('[1]Monthly Detail'!$4:$4, AE15,'[1]Monthly Detail'!91:91) | AG41: =+SUMIF('[1]Monthly Detail'!$4:$4, AF15,'[1]Monthly Detail'!91:91) | AH41: =+SUMIF('[1]Monthly Detail'!$4:$4, AG15,'[1]Monthly Detail'!91:91) | AI41: =+SUMIF('[1]Monthly Detail'!$4:$4, AH15,'[1]Monthly Detail'!91:91) | AJ41: =+SUMIF('[1]Monthly Detail'!$4:$4, AI15,'[1]Monthly Detail'!91:91) | AK41: =+SUMIF('[1]Monthly Detail'!$4:$4, AJ15,'[1]Monthly Detail'!91:91) | AL41: =+SUMIF('[1]Monthly Detail'!$4:$4, AK15,'[1]Monthly Detail'!91:91) | AM41: =+SUMIF('[1]Monthly Detail'!$4:$4, AL15,'[1]Monthly Detail'!91:91) | AN41: 142.42 | AO41: 142.42 | AP41: 202.29 | AQ41: 164.46 | AT41: 169.03 | AU41: 127.41 | AV41: 128.5 | AW41: 155.68 | AX41: 123.02 | AY41: 123.02 | AZ41: 123.01 | BA41: 123.01 | BB41: 123.01 | BC41: 123.01 | BD41: 123.01 | BE41: 123.01 | BF41: =+SUMIF('Monthly Detail'!$4:$4, $B$14,'Monthly Detail'!93:93) | BG41: 190.98 | BH41: 190.98 | BI41: 190.98 | BJ41: 190.98 | BK41: 190.98 | BL41: 190.98 | BM41: 190.98 | BN41: 190.98 | BO41: 190.98 | BP41: 190.98 | BQ41: 190.98 | BR41: 190.98 | BS41: 128.5 | BT41: 169.03 | BU41: 169.03 | BV41: 169.03 | BW41: 169.03 | BX41: 169.03 | BY41: 169.03 | BZ41: 169.03 | CA41: 169.03 | CB41: 169.03 | CC41: 169.03 | CD41: 169.03 | CE41: =BF41-AD41 | CF41: =BF41-CC41
B42: Taxes/Licenses | M42: 0 | N42: 0 | O42: 0 | P42: 0 | Q42: 50 | R42: 50 | S42: 50 | T42: 50 | U42: 50 | V42: 50 | W42: 50 | X42: 50 | Y42: 50 | Z42: 0 | AA42: 16.666667 | AB42: 16.666667 | AC42: 16.666667 | AD42: =+SUMIF('Monthly Detail'!$4:$4, $B$14,'Monthly Detail'!94:94) | AN42: 0 | AO42: 0 | AP42: 0 | AQ42: 50 | AT42: 0 | AU42: 0 | AV42: 0 | AW42: 0 | AX42: 0 | AY42: 0 | AZ42: 0 | BA42: 0 | BB42: 0 | BC42: 0 | BD42: 0 | BE42: 0 | BF42: =+SUMIF('Monthly Detail'!$4:$4, $B$14,'Monthly Detail'!94:94) | BK42: 0 | BL42: 0 | BM42: 0 | BN42: 0 | BR42: 0 | BS42: 50 | BT42: 50 | BU42: 50 | BV42: 50 | BW42: 50 | BX42: 50 | BY42: 50 | BZ42: 50 | CA42: 50 | CB42: 50 | CC42: 50 | CD42: 50 | CE42: =BF42-AD42 | CF42: =BF42-CC42
