Workbook

Sheet 1

Sheet Annual Summary
D11: 2022 | E11: =+D11+1 -> 2023 | F11: Variance | G11: =+E11+1 -> 2024 | H11: Variance | I11: =+G11+1 -> 2025 | J11: =+I11+1 -> 2026 | K11: =+J11+1 -> 2027 | L11: =+K11+1 -> 2028 | M11: =+L11+1 -> 2029 | N11: =+M11+1 -> 2030
C13: Service Income | D13: =SUMIF('Monthly Detail'!$1:$1,'Annual Summary'!D$11, 'Monthly Detail'!12:12) -> 9212.5 | E13: =SUMIF('Monthly Detail'!$1:$1,'Annual Summary'!E$11, 'Monthly Detail'!12:12) -> 43837.41 | F13: =+E13-D13 -> 34624.91 | G13: =SUMIF('Monthly Detail'!$1:$1,'Annual Summary'!G$11, 'Monthly Detail'!12:12) -> 89488.79 | H13: =+G13-E13 -> 45651.38 | I13: =SUMIF('Monthly Detail'!$1:$1,'Annual Summary'!I$11, 'Monthly Detail'!12:12) -> 172325.82 | J13: =SUMIF('Monthly Detail'!$1:$1,'Annual Summary'!J$11, 'Monthly Detail'!12:12) -> 245759.64 | K13: =SUMIF('Monthly Detail'!$1:$1,'Annual Summary'!K$11, 'Monthly Detail'!12:12) -> 329658.57 | L13: =SUMIF('Monthly Detail'!$1:$1,'Annual Summary'!L$11, 'Monthly Detail'!12:12) -> 460399.19 | M13: =SUMIF('Monthly Detail'!$1:$1,'Annual Summary'!M$11, 'Monthly Detail'!12:12) -> 652731 | N13: =SUMIF('Monthly Detail'!$1:$1,'Annual Summary'!N$11, 'Monthly Detail'!12:12) -> 921050.81
C14: Tips | D14: =SUMIF('Monthly Detail'!$1:$1,'Annual Summary'!D$11, 'Monthly Detail'!13:13) -> 125 | E14: =SUMIF('Monthly Detail'!$1:$1,'Annual Summary'!E$11, 'Monthly Detail'!13:13) -> 608.09 | F14: =+E14-D14 -> 483.09 | G14: =SUMIF('Monthly Detail'!$1:$1,'Annual Summary'!G$11, 'Monthly Detail'!13:13) -> 339.45 | H14: =+G14-E14 -> -268.64 | I14: =SUMIF('Monthly Detail'!$1:$1,'Annual Summary'!I$11, 'Monthly Detail'!13:13) -> 654.50436 | J14: =SUMIF('Monthly Detail'!$1:$1,'Annual Summary'!J$11, 'Monthly Detail'!13:13) -> 1041.9737 | K14: =SUMIF('Monthly Detail'!$1:$1,'Annual Summary'!K$11, 'Monthly Detail'!13:13) -> 1397.6891 | L14: =SUMIF('Monthly Detail'!$1:$1,'Annual Summary'!L$11, 'Monthly Detail'!13:13) -> 1952.0042 | M14: =SUMIF('Monthly Detail'!$1:$1,'Annual Summary'!M$11, 'Monthly Detail'!13:13) -> 2767.4543 | N14: =SUMIF('Monthly Detail'!$1:$1,'Annual Summary'!N$11, 'Monthly Detail'!13:13) -> 3905.0788
C15: Total Income | D15: =SUM(D13:D14) -> 9337.5 | E15: =SUM(E13:E14) -> 44445.5 | F15: =+E15-D15 -> 35108 | G15: =SUM(G13:G14) -> 89828.24 | H15: =+G15-E15 -> 45382.74 | I15: =SUM(I13:I14) -> 172980.33 | J15: =SUM(J13:J14) -> 246801.61 | K15: =SUM(K13:K14) -> 331056.26 | L15: =SUM(L13:L14) -> 462351.19 | M15: =SUM(M13:M14) -> 655498.46 | N15: =SUM(N13:N14) -> 924955.89
C16: EOY # of Students | D16: =+SUMIFS('Monthly Detail'!17:17,'Monthly Detail'!4:4,DATE(D11,12,31)) -> 7 | E16: =+SUMIFS('Monthly Detail'!17:17,'Monthly Detail'!4:4,DATE(E11,12,31)) -> 19 | F16: =+E16-D16 -> 12 | G16: =+SUMIFS('Monthly Detail'!17:17,'Monthly Detail'!4:4,DATE(G11,12,31)) -> 23 | H16: =+G16-E16 -> 4 | I16: =+SUMIFS('Monthly Detail'!17:17,'Monthly Detail'!4:4,DATE(I11,12,31)) -> 57.6 | J16: =+SUMIFS('Monthly Detail'!17:17,'Monthly Detail'!4:4,DATE(J11,12,31)) -> 63.88 | K16: =+SUMIFS('Monthly Detail'!17:17,'Monthly Detail'!4:4,DATE(K11,12,31)) -> 89.072 | L16: =+SUMIFS('Monthly Detail'!17:17,'Monthly Detail'!4:4,DATE(L11,12,31)) -> 124.3408 | M16: =+SUMIFS('Monthly Detail'!17:17,'Monthly Detail'!4:4,DATE(M11,12,31)) -> 177.51712 | N16: =+SUMIFS('Monthly Detail'!17:17,'Monthly Detail'!4:4,DATE(N11,12,31)) -> 248.76397
C17: YOY Compounded Growth % | E17: =(E15/D15)-1 -> 3.7598929 | F17: =+E17-D17 -> 3.7598929 | G17: =(G15/E15)-1 -> 1.0210874 | H17: =+G17-E17 -> -2.7388055 | I17: =(I15/G15)-1 -> 0.9256787 | J17: =(J15/I15)-1 -> 0.42676114 | K17: =(K15/J15)-1 -> 0.34138614 | L17: =(L15/K15)-1 -> 0.39659401 | M17: =(M15/L15)-1 -> 0.41775012 | N17: =(N15/M15)-1 -> 0.41107256
C19: Subcontractor Expenses | D19: =SUMIF('Monthly Detail'!$1:$1,'Annual Summary'!D$11, 'Monthly Detail'!$63:$63) -> 0 | E19: =SUMIF('Monthly Detail'!$1:$1,'Annual Summary'!E$11, 'Monthly Detail'!$63:$63) -> 0 | F19: =+E19-D19 -> 0 | G19: =SUMIF('Monthly Detail'!$1:$1,'Annual Summary'!G$11, 'Monthly Detail'!$63:$63) -> 4014 | H19: =+G19-E19 -> 4014 | I19: =SUMIF('Monthly Detail'!$1:$1,'Annual Summary'!I$11, 'Monthly Detail'!$63:$63) -> 14278.194 | J19: =SUMIF('Monthly Detail'!$1:$1,'Annual Summary'!J$11, 'Monthly Detail'!$63:$63) -> 35654.857 | K19: =SUMIF('Monthly Detail'!$1:$1,'Annual Summary'!K$11, 'Monthly Detail'!$63:$63) -> 57005.125 | L19: =SUMIF('Monthly Detail'!$1:$1,'Annual Summary'!L$11, 'Monthly Detail'!$63:$63) -> 91695.815 | M19: =SUMIF('Monthly Detail'!$1:$1,'Annual Summary'!M$11, 'Monthly Detail'!$63:$63) -> 141680.31 | N19: =SUMIF('Monthly Detail'!$1:$1,'Annual Summary'!N$11, 'Monthly Detail'!$63:$63) -> 214895.34
C20: Gross Margin | D20: =D15-D19 -> 9337.5 | E20: =E15-E19 -> 44445.5 | F20: =+E20-D20 -> 35108 | G20: =G15-G19 -> 85814.24 | H20: =+G20-E20 -> 41368.74 | I20: =I15-I19 -> 158702.13 | J20: =J15-J19 -> 211146.75 | K20: =K15-K19 -> 274051.14 | L20: =L15-L19 -> 370655.38 | M20: =M15-M19 -> 513818.15 | N20: =N15-N19 -> 710060.55
C21: GM % | D21: =+D20/D15 -> 1 | E21: =+E20/E15 -> 1 | F21: =+E21-D21 -> 0 | G21: =+G20/G15 -> 0.95531472 | H21: =+G21-E21 -> -0.044685279 | I21: =+I20/I15 -> 0.9174577 | J21: =+J20/J15 -> 0.85553232 | K21: =+K20/K15 -> 0.82780835 | L21: =+L20/L15 -> 0.80167497 | M21: =+M20/M15 -> 0.78385867 | N21: =+N20/N15 -> 0.76766964
C23: Sales & Marketing Expenses | D23: =SUMIF('Monthly Detail'!$1:$1,'Annual Summary'!D$11, 'Monthly Detail'!$70:$70) -> 0 | E23: =SUMIF('Monthly Detail'!$1:$1,'Annual Summary'!E$11, 'Monthly Detail'!$70:$70) -> 0 | F23: =+E23-D23 -> 0 | G23: =SUMIF('Monthly Detail'!$1:$1,'Annual Summary'!G$11, 'Monthly Detail'!$70:$70) -> 4245 | H23: =+G23-E23 -> 4245 | I23: =SUMIF('Monthly Detail'!$1:$1,'Annual Summary'!I$11, 'Monthly Detail'!$70:$70) -> 0 | J23: =SUMIF('Monthly Detail'!$1:$1,'Annual Summary'!J$11, 'Monthly Detail'!$70:$70) -> 0 | K23: =SUMIF('Monthly Detail'!$1:$1,'Annual Summary'!K$11, 'Monthly Detail'!$70:$70) -> 0 | L23: =SUMIF('Monthly Detail'!$1:$1,'Annual Summary'!L$11, 'Monthly Detail'!$70:$70) -> 0 | M23: =SUMIF('Monthly Detail'!$1:$1,'Annual Summary'!M$11, 'Monthly Detail'!$70:$70) -> 0 | N23: =SUMIF('Monthly Detail'!$1:$1,'Annual Summary'!N$11, 'Monthly Detail'!$70:$70) -> 0
C24: General & Admintrative Expenses | D24: =SUMIF('Monthly Detail'!$1:$1,'Annual Summary'!D$11, 'Monthly Detail'!$93:$93) -> 2457.99 | E24: =SUMIF('Monthly Detail'!$1:$1,'Annual Summary'!E$11, 'Monthly Detail'!$93:$93) -> 7947.79 | F24: =+E24-D24 -> 5489.8 | G24: =SUMIF('Monthly Detail'!$1:$1,'Annual Summary'!G$11, 'Monthly Detail'!$93:$93) -> 12495.71 | H24: =+G24-E24 -> 4547.92 | I24: =SUMIF('Monthly Detail'!$1:$1,'Annual Summary'!I$11, 'Monthly Detail'!$93:$93) -> 118763.02 | J24: =SUMIF('Monthly Detail'!$1:$1,'Annual Summary'!J$11, 'Monthly Detail'!$93:$93) -> 180740.57 | K24: =SUMIF('Monthly Detail'!$1:$1,'Annual Summary'!K$11, 'Monthly Detail'!$93:$93) -> 184109.16 | L24: =SUMIF('Monthly Detail'!$1:$1,'Annual Summary'!L$11, 'Monthly Detail'!$93:$93) -> 210365.98 | M24: =SUMIF('Monthly Detail'!$1:$1,'Annual Summary'!M$11, 'Monthly Detail'!$93:$93) -> 224246.92 | N24: =SUMIF('Monthly Detail'!$1:$1,'Annual Summary'!N$11, 'Monthly Detail'!$93:$93) -> 233327.72
C25: Owner Guarenteed Payments | D25: =SUMIF('Monthly Detail'!$1:$1,'Annual Summary'!D$11, 'Monthly Detail'!94:94) -> 0 | E25: =SUMIF('Monthly Detail'!$1:$1,'Annual Summary'!E$11, 'Monthly Detail'!94:94) -> 0 | F25: =+E25-D25 -> 0 | G25: =SUMIF('Monthly Detail'!$1:$1,'Annual Summary'!G$11, 'Monthly Detail'!94:94) -> 0 | H25: =+G25-E25 -> 0 | I25: =SUMIF('Monthly Detail'!$1:$1,'Annual Summary'!I$11, 'Monthly Detail'!94:94) -> 0 | J25: =SUMIF('Monthly Detail'!$1:$1,'Annual Summary'!J$11, 'Monthly Detail'!94:94) -> 0 | K25: =SUMIF('Monthly Detail'!$1:$1,'Annual Summary'!K$11, 'Monthly Detail'!94:94) -> 0 | L25: =SUMIF('Monthly Detail'!$1:$1,'Annual Summary'!L$11, 'Monthly Detail'!94:94) -> 0 | M25: =SUMIF('Monthly Detail'!$1:$1,'Annual Summary'!M$11, 'Monthly Detail'!94:94) -> 0 | N25: =SUMIF('Monthly Detail'!$1:$1,'Annual Summary'!N$11, 'Monthly Detail'!94:94) -> 0
C26: Operating Expense | D26: =SUM(D23:D25) -> 2457.99 | E26: =SUM(E23:E25) -> 7947.79 | F26: =+E26-D26 -> 5489.8 | G26: =SUM(G23:G25) -> 16740.71 | H26: =+G26-E26 -> 8792.92 | I26: =SUM(I23:I25) -> 118763.02 | J26: =SUM(J23:J25) -> 180740.57 | K26: =SUM(K23:K25) -> 184109.16 | L26: =SUM(L23:L25) -> 210365.98 | M26: =SUM(M23:M25) -> 224246.92 | N26: =SUM(N23:N25) -> 233327.72
C28: Net Operating Income (EBITDA) | D28: =D20-D26 -> 6879.51 | E28: =E20-E26 -> 36497.71 | F28: =+E28-D28 -> 29618.2 | G28: =G20-G26 -> 69073.53 | H28: =+G28-E28 -> 32575.82 | I28: =I20-I26 -> 39939.114 | J28: =J20-J26 -> 30406.183 | K28: =K20-K26 -> 89941.979 | L28: =L20-L26 -> 160289.39 | M28: =M20-M26 -> 289571.23 | N28: =N20-N26 -> 476732.83
C29: EBITDA % | D29: =D28/D15 -> 0.73676145 | E29: =E28/E15 -> 0.82117897 | F29: =+E29-D29 -> 0.084417526 | G29: =G28/G15 -> 0.76895117 | H29: =+G29-E29 -> -0.052227805 | I29: =I28/I15 -> 0.23088818 | J29: =J28/J15 -> 0.12320091 | K29: =K28/K15 -> 0.27168185 | L29: =L28/L15 -> 0.34668321 | M29: =M28/M15 -> 0.4417573 | N29: =N28/N15 -> 0.51541142
C31: Other Income / (Expense) | D31: 0 | E31: 0 | F31: =+E31-D31 -> 0 | G31: =SUMIF('Monthly Detail'!$1:$1,'Annual Summary'!G$11, 'Monthly Detail'!107:107) -> -5018.23 | H31: =+G31-E31 -> -5018.23 | I31: =SUMIF('Monthly Detail'!$1:$1,'Annual Summary'!I$11, 'Monthly Detail'!107:107) -> -9246.3 | J31: =SUMIF('Monthly Detail'!$1:$1,'Annual Summary'!J$11, 'Monthly Detail'!107:107) -> -9600 | K31: =SUMIF('Monthly Detail'!$1:$1,'Annual Summary'!K$11, 'Monthly Detail'!107:107) -> -9600 | L31: =SUMIF('Monthly Detail'!$1:$1,'Annual Summary'!L$11, 'Monthly Detail'!107:107) -> -9600 | M31: =SUMIF('Monthly Detail'!$1:$1,'Annual Summary'!M$11, 'Monthly Detail'!107:107) -> -9600 | N31: =SUMIF('Monthly Detail'!$1:$1,'Annual Summary'!N$11, 'Monthly Detail'!107:107) -> -9600
C32: Net Income | D32: =D28+D31 -> 6879.51 | E32: =E28+E31 -> 36497.71 | F32: =+E32-D32 -> 29618.2 | G32: =G28+G31 -> 64055.3 | H32: =+G32-E32 -> 27557.59 | I32: =I28+I31 -> 30692.814 | J32: =J28+J31 -> 20806.183 | K32: =K28+K31 -> 80341.979 | L32: =L28+L31 -> 150689.39 | M32: =M28+M31 -> 279971.23 | N32: =N28+N31 -> 467132.83
C33: NI % | D33: =D32/D15 -> 0.73676145 | E33: =E32/E15 -> 0.82117897 | F33: =+E33-D33 -> 0.084417526 | G33: =G32/G15 -> 0.71308644 | H33: =+G33-E33 -> -0.10809253 | I33: =I32/I15 -> 0.17743528 | J33: =J32/J15 -> 0.084303271 | K33: =K32/K15 -> 0.24268376 | L33: =L32/L15 -> 0.32591977 | M33: =M32/M15 -> 0.42711196 | N33: =N32/N15 -> 0.50503255

Sheet 2025 AOP
B8: 2025 Annual Operating Plan
C10: January | D10: February | E10: March | F10: April | G10: May | H10: June | I10: July | J10: August | K10: September | L10: October | M10: November | N10: December | P10: Total
C11: 45688 | D11: 45716 | E11: 45747 | F11: 45777 | G11: 45808 | H11: 45838 | I11: 45869 | J11: 45900 | K11: 45930 | L11: 45961 | M11: 45991 | N11: 46022 | O11: 46053
B12: Service Income | C12: 7677.1321 | D12: 12691.952 | E12: 7473.9 | F12: 9831.9706 | G12: 10732.473 | H12: 5809.4312 | I12: 10858.9 | J12: 15862.285 | K12: 12122.449 | L12: 15626.953 | M12: 8797.317 | N12: 6287.4785 | P12: 123772.24
B13: Tips | C13: 13.919186 | D13: 23.011412 | E13: 13.550712 | F13: 17.826062 | G13: 19.458736 | H13: 10.532912 | I13: 19.687958 | J13: 28.75945 | K13: 21.978862 | L13: 28.332777 | M13: 15.950161 | N13: 11.399646 | P13: 224.40787
B14: Total Income | C14: 7691.0513 | D14: 12714.964 | E14: 7487.4507 | F14: 9849.7967 | G14: 10751.932 | H14: 5819.9642 | I14: 10878.588 | J14: 15891.044 | K14: 12144.428 | L14: 15655.286 | M14: 8813.2671 | N14: 6298.8782 | P14: 123996.65
B15: # of Students | C15: 34.8 | D15: 35.8 | E15: 33.6 | F15: 32.4 | G15: 33.4 | H15: 29.2 | I15: 31.2 | J15: 37.2 | K15: 43.2 | L15: 45 | M15: 43.6 | N15: 42.2
B16: # of Sessions | C16: 34 | D16: 56 | E16: 36 | F16: 49 | G16: 76 | H16: 45 | I16: 118 | J16: 169 | K16: 125 | L16: 173 | M16: 90 | N16: 129.33333
B18: Subcontractor Expenses | C18: 0 | D18: 919.6069 | E18: 450 | F18: 1073.0882 | G18: 2850.0435 | H18: 1050 | I18: 1894.25 | J18: 4130.1794 | K18: 1256.4172 | L18: 1439.8958 | M18: 524 | N18: 0 | P18: 15587.481
B19: Gross Margin | C19: 7691.0513 | D19: 11795.357 | E19: 7037.4507 | F19: 8776.7084 | G19: 7901.8881 | H19: 4769.9642 | I19: 8984.338 | J19: 11760.865 | K19: 10888.011 | L19: 14215.39 | M19: 8289.2671 | N19: 6298.8782 | P19: 108409.17
B20: GM % | C20: 1 | D20: 0.92767522 | E20: 0.93989944 | F20: 0.89105478 | G20: 0.7349273 | H20: 0.81958652 | I20: 0.82587354 | J20: 0.74009389 | K20: 0.89654373 | L20: 0.90802494 | M20: 0.94054418 | N20: 1 | P20: 0.87429111
B22: Sales & Marketing Expenses | C22: 0 | D22: 0 | E22: 0 | F22: 0 | G22: 0 | H22: 0 | I22: 0 | J22: 0 | K22: 0 | L22: 0 | M22: 0 | N22: 0 | P22: 0
B23: General & Admintrative Expenses | C23: 1454.0336 | D23: 1416.0203 | E23: 1647.4689 | F23: 1523.6384 | G23: 1352.726 | H23: 1193.7039 | I23: 1556.8098 | J23: 2008.4271 | K23: 1397.6245 | L23: 1973.3255 | M23: 1340.2174 | N23: 1635.3956 | P23: 18499.391
B24: Operating Expenses | C24: 1454.0336 | D24: 1416.0203 | E24: 1647.4689 | F24: 1523.6384 | G24: 1352.726 | H24: 1193.7039 | I24: 1556.8098 | J24: 2008.4271 | K24: 1397.6245 | L24: 1973.3255 | M24: 1340.2174 | N24: 1635.3956 | P24: 18499.391
B26: Net Operating Income (EBITDA) | C26: 6237.0177 | D26: 10379.337 | E26: 5389.9818 | F26: 7253.0701 | G26: 6549.1621 | H26: 3576.2603 | I26: 7427.5281 | J26: 9752.4376 | K26: 9490.3861 | L26: 12242.065 | M26: 6949.0498 | N26: 4663.4826 | P26: 89909.777
B27: EBITDA % | C27: 0.81094475 | D27: 0.81630878 | E27: 0.71986875 | F27: 0.73636749 | G27: 0.60911493 | H27: 0.61448149 | I27: 0.68276583 | J27: 0.61370653 | K27: 0.78146013 | L27: 0.78197643 | M27: 0.78847601 | N27: 0.74036716 | P27: 0.72509844
B29: Other Income / (Expense) | C29: -800 | D29: -800 | E29: -800 | F29: -800 | G29: -800 | H29: -800 | I29: -800 | J29: -800 | K29: -800 | L29: -800 | M29: -800 | N29: -800 | P29: -9600
B30: Net Income | C30: 5437.0177 | D30: 9579.3366 | E30: 4589.9818 | F30: 6453.0701 | G30: 5749.1621 | H30: 2776.2603 | I30: 6627.5281 | J30: 8952.4376 | K30: 8690.3861 | L30: 11442.065 | M30: 6149.0498 | N30: 3863.4826 | P30: 80309.777
B31: NI % | C31: 0.70692776 | D31: 0.75339079 | E31: 0.61302331 | F31: 0.65514754 | G31: 0.5347097 | H31: 0.4770236 | I31: 0.60922687 | J31: 0.56336371 | K31: 0.7155863 | L31: 0.73087548 | M31: 0.69770377 | N31: 0.61336042 | P31: 0.64767699
B32: Cash Contributions | C32: 0 | D32: 0 | E32: 0 | F32: 2400 | G32: 0 | H32: 0 | I32: 0 | J32: 0 | K32: 0 | L32: 0 | M32: 0 | N32: 0 | P32: 2400
... B34: Accrued Tax Burden | C34: 1631.1053 | D34: 4744.9063 | E34: 6361.9008 | F34: 8537.8218 | G34: 10502.57 | H34: 11575.449 | I34: 13803.707 | J34: 16729.438 | K34: 19576.554 | L34: 23249.173 | M34: 25333.888 | N34: 26732.933 | P34: 26732.933
B36: Operating Cash | C36: 5910.492 | D36: 11084.272 | E36: 13626.641 | F36: 16286.345 | G36: 18578.006 | H36: 19238.674 | I36: 21452.662 | J36: 26002.178 | K36: 32304.328 | L36: 39688.856 | M36: 44161.647 | N36: 45353.467
B37: Cash Inflow (Outflow) | C37: 1691.5453 | D37: 5173.7804 | E37: 2542.3684 | F37: 2659.704 | G37: 2291.6609 | H37: 660.66802 | I37: 2213.988 | J37: 4549.5165 | K37: 6302.1499 | L37: 7384.5278 | M37: 4472.7907 | N37: 1191.8202

Sheet 2023 Overview
C10: =TEXT('Monthly Detail'!D4,"mmmm") -> January | D10: =TEXT('Monthly Detail'!E4,"mmmm") -> February | E10: =TEXT('Monthly Detail'!F4,"mmmm") -> March | F10: =TEXT('Monthly Detail'!G4,"mmmm") -> April | G10: =TEXT('Monthly Detail'!H4,"mmmm") -> May | H10: =TEXT('Monthly Detail'!I4,"mmmm") -> June | I10: =TEXT('Monthly Detail'!J4,"mmmm") -> July | J10: =TEXT('Monthly Detail'!K4,"mmmm") -> August | ... N10: =TEXT('Monthly Detail'!O4,"mmmm") -> December | P10: Total
C11: 44957 | D11: 44985 | E11: 45016 | F11: 45046 | G11: 45077 | H11: 45107 | I11: 45138 | J11: 45169 | K11: 45199 | L11: 45230 | M11: 45260 | N11: 45291 | O11: 45322
B12: Service Income | C12: =SUMIF('Monthly Detail'!$4:$4, '2023 Overview'!C$11, 'Monthly Detail'!12:12) -> 1510 | D12: =SUMIF('Monthly Detail'!$4:$4, '2023 Overview'!D$11, 'Monthly Detail'!12:12) -> 1225 | E12: =SUMIF('Monthly Detail'!$4:$4, '2023 Overview'!E$11, 'Monthly Detail'!12:12) -> 1177.5 | F12: =SUMIF('Monthly Detail'!$4:$4, '2023 Overview'!F$11, 'Monthly Detail'!12:12) -> 1919.91 | G12: =SUMIF('Monthly Detail'!$4:$4, '2023 Overview'!G$11, 'Monthly Detail'!12:12) -> 2446.25 | H12: =SUMIF('Monthly Detail'!$4:$4, '2023 Overview'!H$11, 'Monthly Detail'!12:12) -> 2038.75 | I12: =SUMIF('Monthly Detail'!$4:$4, '2023 Overview'!I$11, 'Monthly Detail'!12:12) -> 2785 | J12: =SUMIF('Monthly Detail'!$4:$4, '2023 Overview'!J$11, 'Monthly Detail'!12:12) -> 7051.66 | ... N12: =SUMIF('Monthly Detail'!$4:$4, '2023 Overview'!N$11, 'Monthly Detail'!12:12) -> 2095 | P12: =SUM(C12:O12) -> 43837.41
B13: Misc. | C13: =SUMIF('Monthly Detail'!$4:$4, '2023 Overview'!C$11, 'Monthly Detail'!13:13) -> 35.99 | D13: =SUMIF('Monthly Detail'!$4:$4, '2023 Overview'!D$11, 'Monthly Detail'!13:13) -> 30.75 | E13: =SUMIF('Monthly Detail'!$4:$4, '2023 Overview'!E$11, 'Monthly Detail'!13:13) -> 29.25 | F13: =SUMIF('Monthly Detail'!$4:$4, '2023 Overview'!F$11, 'Monthly Detail'!13:13) -> 37.5 | G13: =SUMIF('Monthly Detail'!$4:$4, '2023 Overview'!G$11, 'Monthly Detail'!13:13) -> 40.68 | H13: =SUMIF('Monthly Detail'!$4:$4, '2023 Overview'!H$11, 'Monthly Detail'!13:13) -> 4.68 | I13: =SUMIF('Monthly Detail'!$4:$4, '2023 Overview'!I$11, 'Monthly Detail'!13:13) -> 50.5 | J13: =SUMIF('Monthly Detail'!$4:$4, '2023 Overview'!J$11, 'Monthly Detail'!13:13) -> 27 | ... N13: =SUMIF('Monthly Detail'!$4:$4, '2023 Overview'!N$11, 'Monthly Detail'!13:13) -> 49.5
B14: Total Income | C14: =SUM(C12:C13) -> 1545.99 | D14: =SUM(D12:D13) -> 1255.75 | E14: =SUM(E12:E13) -> 1206.75 | F14: =SUM(F12:F13) -> 1957.41 | G14: =SUM(G12:G13) -> 2486.93 | H14: =SUM(H12:H13) -> 2043.43 | I14: =SUM(I12:I13) -> 2835.5 | J14: =SUM(J12:J13) -> 7078.66 | ... N14: =SUM(N12:N13) -> 2144.5 | P14: =SUM(P12:P12) -> 43837.41
B16: Gross Margin | C16: =C14 -> 1545.99 | D16: =D14 -> 1255.75 | E16: =E14 -> 1206.75 | F16: =F14 -> 1957.41 | G16: =G14 -> 2486.93 | H16: =H14 -> 2043.43 | I16: =I14 -> 2835.5 | J16: =J14 -> 7078.66 | ... N16: =N14 -> 2144.5 | P16: =P14 -> 43837.41
B17: GM % | C17: =C16/C14 -> 1 | D17: =D16/D14 -> 1 | E17: =E16/E14 -> 1 | F17: =F16/F14 -> 1 | G17: =G16/G14 -> 1 | H17: =H16/H14 -> 1 | I17: =I16/I14 -> 1 | J17: =J16/J14 -> 1 | ... N17: =N16/N14 -> 1 | P17: =P16/P14 -> 1
B19: General & Admintrative Expenses | C19: =SUMIF('Monthly Detail'!$4:$4, '2023 Overview'!C$11, 'Monthly Detail'!$93:$93) -> 235.13 | D19: =SUMIF('Monthly Detail'!$4:$4, '2023 Overview'!D$11, 'Monthly Detail'!$93:$93) -> 153.76 | E19: =SUMIF('Monthly Detail'!$4:$4, '2023 Overview'!E$11, 'Monthly Detail'!$93:$93) -> 105.36 | F19: =SUMIF('Monthly Detail'!$4:$4, '2023 Overview'!F$11, 'Monthly Detail'!$93:$93) -> 272.84 | G19: =SUMIF('Monthly Detail'!$4:$4, '2023 Overview'!G$11, 'Monthly Detail'!$93:$93) -> 551 | H19: =SUMIF('Monthly Detail'!$4:$4, '2023 Overview'!H$11, 'Monthly Detail'!$93:$93) -> 647.26 | I19: =SUMIF('Monthly Detail'!$4:$4, '2023 Overview'!I$11, 'Monthly Detail'!$93:$93) -> 432.76 | J19: =SUMIF('Monthly Detail'!$4:$4, '2023 Overview'!J$11, 'Monthly Detail'!$93:$93) -> 851.95 | ... N19: =SUMIF('Monthly Detail'!$4:$4, '2023 Overview'!N$11, 'Monthly Detail'!$93:$93) -> 797.47 | P19: =SUM(C19:O19) -> 7947.79
B20: Operating Expenses | C20: =SUM(C19:C19) -> 235.13 | D20: =SUM(D19:D19) -> 153.76 | E20: =SUM(E19:E19) -> 105.36 | F20: =SUM(F19:F19) -> 272.84 | G20: =SUM(G19:G19) -> 551 | H20: =SUM(H19:H19) -> 647.26 | I20: =SUM(I19:I19) -> 432.76 | J20: =SUM(J19:J19) -> 851.95 | ... N20: =SUM(N19:N19) -> 797.47 | P20: =SUM(P19:P19) -> 7947.79
B22: Net Operating Income (EBITDA) | C22: =C16-C20 -> 1310.86 | D22: =D16-D20 -> 1101.99 | E22: =E16-E20 -> 1101.39 | F22: =F16-F20 -> 1684.57 | G22: =G16-G20 -> 1935.93 | H22: =H16-H20 -> 1396.17 | I22: =I16-I20 -> 2402.74 | J22: =J16-J20 -> 6226.71 | ... N22: =N16-N20 -> 1347.03 | P22: =P16-P20 -> 35889.62
B23: EBITDA % | C23: =C22/C14 -> 0.84790975 | D23: =D22/D14 -> 0.87755525 | E23: =E22/E14 -> 0.91269111 | F23: =F22/F14 -> 0.86061173 | G23: =G22/G14 -> 0.77844169 | H23: =H22/H14 -> 0.68324826 | I23: =I22/I14 -> 0.84737789 | J23: =J22/J14 -> 0.8796453 | ... N23: =N22/N14 -> 0.62813243 | P23: =P22/P14 -> 0.81869846
B25: Other Income / (Expense) | C25: =SUMIF('Monthly Detail'!$4:$4, '2023 Overview'!C$11, 'Monthly Detail'!102:102) -> 0 | D25: =SUMIF('Monthly Detail'!$4:$4, '2023 Overview'!D$11, 'Monthly Detail'!102:102) -> 0 | E25: =SUMIF('Monthly Detail'!$4:$4, '2023 Overview'!E$11, 'Monthly Detail'!102:102) -> 0 | F25: =SUMIF('Monthly Detail'!$4:$4, '2023 Overview'!F$11, 'Monthly Detail'!102:102) -> 0.01 | G25: =SUMIF('Monthly Detail'!$4:$4, '2023 Overview'!G$11, 'Monthly Detail'!102:102) -> 0.01 | H25: =SUMIF('Monthly Detail'!$4:$4, '2023 Overview'!H$11, 'Monthly Detail'!102:102) -> 0.01 | I25: =SUMIF('Monthly Detail'!$4:$4, '2023 Overview'!I$11, 'Monthly Detail'!102:102) -> 0.03 | J25: =SUMIF('Monthly Detail'!$4:$4, '2023 Overview'!J$11, 'Monthly Detail'!102:102) -> 0.01 | ... N25: =SUMIF('Monthly Detail'!$4:$4, '2023 Overview'!N$11, 'Monthly Detail'!102:102) -> 0 | P25: =SUM(C25:O25) -> 0.07
B26: Net Income | C26: =C22+SUM(C25:C25) -> 1310.86 | D26: =D22+SUM(D25:D25) -> 1101.99 | E26: =E22+SUM(E25:E25) -> 1101.39 | F26: =F22+SUM(F25:F25) -> 1684.58 | G26: =G22+SUM(G25:G25) -> 1935.94 | H26: =H22+SUM(H25:H25) -> 1396.18 | I26: =I22+SUM(I25:I25) -> 2402.77 | J26: =J22+SUM(J25:J25) -> 6226.72 | ... N26: =N22+SUM(N25:N25) -> 1347.03 | P26: =P22+SUM(P25:P25) -> 35889.69
B27: NI % | C27: =C26/C14 -> 0.84790975 | D27: =D26/D14 -> 0.87755525 | E27: =E26/E14 -> 0.91269111 | F27: =F26/F14 -> 0.86061684 | G27: =G26/G14 -> 0.77844571 | H27: =H26/H14 -> 0.68325316 | I27: =I26/I14 -> 0.84738847 | J27: =J26/J14 -> 0.87964671 | ... N27: =N26/N14 -> 0.62813243 | P27: =P26/P14 -> 0.81870006
B29: Operating Cash | C29: =SUMIF('Monthly Detail'!$4:$4, '2023 Overview'!C$11, 'Monthly Detail'!172:172) -> 169.96 | D29: =SUMIF('Monthly Detail'!$4:$4, '2023 Overview'!D$11, 'Monthly Detail'!172:172) -> 212.95 | E29: =SUMIF('Monthly Detail'!$4:$4, '2023 Overview'!E$11, 'Monthly Detail'!172:172) -> 127.39 | F29: =SUMIF('Monthly Detail'!$4:$4, '2023 Overview'!F$11, 'Monthly Detail'!172:172) -> 395.42 | G29: =SUMIF('Monthly Detail'!$4:$4, '2023 Overview'!G$11, 'Monthly Detail'!172:172) -> 300.21 | H29: =SUMIF('Monthly Detail'!$4:$4, '2023 Overview'!H$11, 'Monthly Detail'!172:172) -> 433.57 | I29: =SUMIF('Monthly Detail'!$4:$4, '2023 Overview'!I$11, 'Monthly Detail'!172:172) -> 566.73 | J29: =SUMIF('Monthly Detail'!$4:$4, '2023 Overview'!J$11, 'Monthly Detail'!172:172) -> 503.45 | ... N29: =SUMIF('Monthly Detail'!$4:$4, '2023 Overview'!N$11, 'Monthly Detail'!172:172) -> 997.02
B30: Cash Inflow (Outflow) | C30: =SUMIF('Monthly Detail'!$4:$4, '2023 Overview'!C$11, 'Monthly Detail'!169:169) -> 225.86 | D30: =SUMIF('Monthly Detail'!$4:$4, '2023 Overview'!D$11, 'Monthly Detail'!169:169) -> 42.99 | E30: =SUMIF('Monthly Detail'!$4:$4, '2023 Overview'!E$11, 'Monthly Detail'!169:169) -> -85.56 | F30: =SUMIF('Monthly Detail'!$4:$4, '2023 Overview'!F$11, 'Monthly Detail'!169:169) -> 268.03 | G30: =SUMIF('Monthly Detail'!$4:$4, '2023 Overview'!G$11, 'Monthly Detail'!169:169) -> -95.21 | H30: =SUMIF('Monthly Detail'!$4:$4, '2023 Overview'!H$11, 'Monthly Detail'!169:169) -> 133.36 | I30: =SUMIF('Monthly Detail'!$4:$4, '2023 Overview'!I$11, 'Monthly Detail'!169:169) -> 133.16 | J30: =SUMIF('Monthly Detail'!$4:$4, '2023 Overview'!J$11, 'Monthly Detail'!169:169) -> -63.28 | ... N30: =SUMIF('Monthly Detail'!$4:$4, '2023 Overview'!N$11, 'Monthly Detail'!169:169) -> 269.53

Sheet 2025 Overview (Rolling)
B8: 2025 Overview (Rolling Forecast)
C10: =TEXT('Monthly Detail'!D4,"mmmm") -> January | D10: =TEXT('Monthly Detail'!E4,"mmmm") -> February | E10: =TEXT('Monthly Detail'!F4,"mmmm") -> March | F10: =TEXT('Monthly Detail'!G4,"mmmm") -> April | G10: =TEXT('Monthly Detail'!H4,"mmmm") -> May | H10: =TEXT('Monthly Detail'!I4,"mmmm") -> June | I10: =TEXT('Monthly Detail'!J4,"mmmm") -> July | J10: =TEXT('Monthly Detail'!K4,"mmmm") -> August | ... N10: =TEXT('Monthly Detail'!O4,"mmmm") -> December | P10: Total
C11: 45688 | D11: 45716 | E11: 45747 | F11: 45777 | G11: 45808 | H11: 45838 | I11: 45869 | J11: 45900 | K11: 45930 | L11: 45961 | M11: 45991 | N11: 46022 | O11: 45322
B12: Service Income | C12: =SUMIF('Monthly Detail'!$4:$4, '2025 Overview (Rolling)'!C$11, 'Monthly Detail'!12:12) -> 6477.5 | D12: =SUMIF('Monthly Detail'!$4:$4, '2025 Overview (Rolling)'!D$11, 'Monthly Detail'!12:12) -> 8052.5 | E12: =SUMIF('Monthly Detail'!$4:$4, '2025 Overview (Rolling)'!E$11, 'Monthly Detail'!12:12) -> 7630 | F12: =SUMIF('Monthly Detail'!$4:$4, '2025 Overview (Rolling)'!F$11, 'Monthly Detail'!12:12) -> 3756.25 | G12: =SUMIF('Monthly Detail'!$4:$4, '2025 Overview (Rolling)'!G$11, 'Monthly Detail'!12:12) -> 6032.5 | H12: =SUMIF('Monthly Detail'!$4:$4, '2025 Overview (Rolling)'!H$11, 'Monthly Detail'!12:12) -> 6822.5 | I12: =SUMIF('Monthly Detail'!$4:$4, '2025 Overview (Rolling)'!I$11, 'Monthly Detail'!12:12) -> 14855 | J12: =SUMIF('Monthly Detail'!$4:$4, '2025 Overview (Rolling)'!J$11, 'Monthly Detail'!12:12) -> 20412.5 | ... N12: =SUMIF('Monthly Detail'!$4:$4, '2025 Overview (Rolling)'!N$11, 'Monthly Detail'!12:12) -> 17967.542 | P12: =SUM(C12:O12) -> 172325.82
B13: Tips | C13: =SUMIF('Monthly Detail'!$4:$4, '2025 Overview (Rolling)'!C$11, 'Monthly Detail'!13:13) -> 108 | D13: =SUMIF('Monthly Detail'!$4:$4, '2025 Overview (Rolling)'!D$11, 'Monthly Detail'!13:13) -> 59.62 | E13: =SUMIF('Monthly Detail'!$4:$4, '2025 Overview (Rolling)'!E$11, 'Monthly Detail'!13:13) -> 52.37 | F13: =SUMIF('Monthly Detail'!$4:$4, '2025 Overview (Rolling)'!F$11, 'Monthly Detail'!13:13) -> 0 | G13: =SUMIF('Monthly Detail'!$4:$4, '2025 Overview (Rolling)'!G$11, 'Monthly Detail'!13:13) -> 12 | H13: =SUMIF('Monthly Detail'!$4:$4, '2025 Overview (Rolling)'!H$11, 'Monthly Detail'!13:13) -> 93.5 | I13: =SUMIF('Monthly Detail'!$4:$4, '2025 Overview (Rolling)'!I$11, 'Monthly Detail'!13:13) -> 75 | J13: =SUMIF('Monthly Detail'!$4:$4, '2025 Overview (Rolling)'!J$11, 'Monthly Detail'!13:13) -> 44.5 | ... N13: =SUMIF('Monthly Detail'!$4:$4, '2025 Overview (Rolling)'!N$11, 'Monthly Detail'!13:13) -> 76.178933 | P13: =+SUM(C13:N13) -> 654.50436
B14: Total Income | C14: =SUM(C12:C13) -> 6585.5 | D14: =SUM(D12:D13) -> 8112.12 | E14: =SUM(E12:E13) -> 7682.37 | F14: =SUM(F12:F13) -> 3756.25 | G14: =SUM(G12:G13) -> 6044.5 | H14: =SUM(H12:H13) -> 6916 | I14: =SUM(I12:I13) -> 14930 | J14: =SUM(J12:J13) -> 20457 | ... N14: =SUM(N12:N13) -> 18043.721 | P14: =SUM(P12:P13) -> 172980.33
B15: # of Students | C15: =SUMIF('Monthly Detail'!$4:$4, '2025 Overview (Rolling)'!C$11, 'Monthly Detail'!17:17) -> 24 | D15: =SUMIF('Monthly Detail'!$4:$4, '2025 Overview (Rolling)'!D$11, 'Monthly Detail'!17:17) -> 28 | E15: =SUMIF('Monthly Detail'!$4:$4, '2025 Overview (Rolling)'!E$11, 'Monthly Detail'!17:17) -> 24 | F15: =SUMIF('Monthly Detail'!$4:$4, '2025 Overview (Rolling)'!F$11, 'Monthly Detail'!17:17) -> 23 | G15: =SUMIF('Monthly Detail'!$4:$4, '2025 Overview (Rolling)'!G$11, 'Monthly Detail'!17:17) -> 20 | H15: =SUMIF('Monthly Detail'!$4:$4, '2025 Overview (Rolling)'!H$11, 'Monthly Detail'!17:17) -> 25 | I15: =SUMIF('Monthly Detail'!$4:$4, '2025 Overview (Rolling)'!I$11, 'Monthly Detail'!17:17) -> 35 | J15: =SUMIF('Monthly Detail'!$4:$4, '2025 Overview (Rolling)'!J$11, 'Monthly Detail'!17:17) -> 48 | ... N15: =SUMIF('Monthly Detail'!$4:$4, '2025 Overview (Rolling)'!N$11, 'Monthly Detail'!17:17) -> 57.6
B16: # of Sessions | C16: =SUMIF('Monthly Detail'!$4:$4, '2025 Overview (Rolling)'!C$11, 'Monthly Detail'!22:22) -> 56 | D16: =SUMIF('Monthly Detail'!$4:$4, '2025 Overview (Rolling)'!D$11, 'Monthly Detail'!22:22) -> 66 | E16: =SUMIF('Monthly Detail'!$4:$4, '2025 Overview (Rolling)'!E$11, 'Monthly Detail'!22:22) -> 73 | F16: =SUMIF('Monthly Detail'!$4:$4, '2025 Overview (Rolling)'!F$11, 'Monthly Detail'!22:22) -> 37 | G16: =SUMIF('Monthly Detail'!$4:$4, '2025 Overview (Rolling)'!G$11, 'Monthly Detail'!22:22) -> 62 | H16: =SUMIF('Monthly Detail'!$4:$4, '2025 Overview (Rolling)'!H$11, 'Monthly Detail'!22:22) -> 51 | I16: =SUMIF('Monthly Detail'!$4:$4, '2025 Overview (Rolling)'!I$11, 'Monthly Detail'!22:22) -> 120 | J16: =SUMIF('Monthly Detail'!$4:$4, '2025 Overview (Rolling)'!J$11, 'Monthly Detail'!22:22) -> 163 | ... N16: =SUMIF('Monthly Detail'!$4:$4, '2025 Overview (Rolling)'!N$11, 'Monthly Detail'!22:22) -> 247.623
B18: Subcontractor Expenses | C18: =SUMIF('Monthly Detail'!$4:$4, '2025 Overview (Rolling)'!C$11, 'Monthly Detail'!63:63) -> 0 | D18: =SUMIF('Monthly Detail'!$4:$4, '2025 Overview (Rolling)'!D$11, 'Monthly Detail'!63:63) -> 450 | E18: =SUMIF('Monthly Detail'!$4:$4, '2025 Overview (Rolling)'!E$11, 'Monthly Detail'!63:63) -> 0 | F18: =SUMIF('Monthly Detail'!$4:$4, '2025 Overview (Rolling)'!F$11, 'Monthly Detail'!63:63) -> 0 | G18: =SUMIF('Monthly Detail'!$4:$4, '2025 Overview (Rolling)'!G$11, 'Monthly Detail'!63:63) -> 270 | H18: =SUMIF('Monthly Detail'!$4:$4, '2025 Overview (Rolling)'!H$11, 'Monthly Detail'!63:63) -> 0 | I18: =SUMIF('Monthly Detail'!$4:$4, '2025 Overview (Rolling)'!I$11, 'Monthly Detail'!63:63) -> 1582.5 | J18: =SUMIF('Monthly Detail'!$4:$4, '2025 Overview (Rolling)'!J$11, 'Monthly Detail'!63:63) -> 684 | ... N18: =SUMIF('Monthly Detail'!$4:$4, '2025 Overview (Rolling)'!N$11, 'Monthly Detail'!63:63) -> 959.95423 | P18: =SUM(C18:O18) -> 14278.194
B19: Gross Margin | C19: =C14-C18 -> 6585.5 | D19: =D14-D18 -> 7662.12 | E19: =E14-E18 -> 7682.37 | F19: =F14-F18 -> 3756.25 | G19: =G14-G18 -> 5774.5 | H19: =H14-H18 -> 6916 | I19: =I14-I18 -> 13347.5 | J19: =J14-J18 -> 19773 | ... N19: =N14-N18 -> 17083.767 | P19: =P14-P18 -> 158702.13
B20: GM % | C20: =C19/C14 -> 1 | D20: =D19/D14 -> 0.94452745 | E20: =E19/E14 -> 1 | F20: =F19/F14 -> 1 | G20: =G19/G14 -> 0.95533129 | H20: =H19/H14 -> 1 | I20: =I19/I14 -> 0.89400536 | J20: =J19/J14 -> 0.96656401 | ... N20: =N19/N14 -> 0.94679843 | P20: =P19/P14 -> 0.9174577
B22: Sales & Marketing Expenses | C22: =SUMIF('Monthly Detail'!$4:$4, '2025 Overview (Rolling)'!C$11, 'Monthly Detail'!$70:$70) -> 0 | D22: =SUMIF('Monthly Detail'!$4:$4, '2025 Overview (Rolling)'!D$11, 'Monthly Detail'!$70:$70) -> 0 | E22: =SUMIF('Monthly Detail'!$4:$4, '2025 Overview (Rolling)'!E$11, 'Monthly Detail'!$70:$70) -> 0 | F22: =SUMIF('Monthly Detail'!$4:$4, '2025 Overview (Rolling)'!F$11, 'Monthly Detail'!$70:$70) -> 0 | G22: =SUMIF('Monthly Detail'!$4:$4, '2025 Overview (Rolling)'!G$11, 'Monthly Detail'!$70:$70) -> 0 | H22: =SUMIF('Monthly Detail'!$4:$4, '2025 Overview (Rolling)'!H$11, 'Monthly Detail'!$70:$70) -> 0 | I22: =SUMIF('Monthly Detail'!$4:$4, '2025 Overview (Rolling)'!I$11, 'Monthly Detail'!$70:$70) -> 0 | J22: =SUMIF('Monthly Detail'!$4:$4, '2025 Overview (Rolling)'!J$11, 'Monthly Detail'!$70:$70) -> 0 | ... N22: =SUMIF('Monthly Detail'!$4:$4, '2025 Overview (Rolling)'!N$11, 'Monthly Detail'!$70:$70) -> 0 | P22: =SUM(C22:O22) -> 0
B23: General & Admintrative Expenses | C23: =SUMIF('Monthly Detail'!$4:$4, '2025 Overview (Rolling)'!C$11, 'Monthly Detail'!$93:$93) -> 4230.3 | D23: =SUMIF('Monthly Detail'!$4:$4, '2025 Overview (Rolling)'!D$11, 'Monthly Detail'!$93:$93) -> 6699.3 | E23: =SUMIF('Monthly Detail'!$4:$4, '2025 Overview (Rolling)'!E$11, 'Monthly Detail'!$93:$93) -> 7438.99 | F23: =SUMIF('Monthly Detail'!$4:$4, '2025 Overview (Rolling)'!F$11, 'Monthly Detail'!$93:$93) -> 3780.99 | G23: =SUMIF('Monthly Detail'!$4:$4, '2025 Overview (Rolling)'!G$11, 'Monthly Detail'!$93:$93) -> 3678.36 | H23: =SUMIF('Monthly Detail'!$4:$4, '2025 Overview (Rolling)'!H$11, 'Monthly Detail'!$93:$93) -> 4152.38 | I23: =SUMIF('Monthly Detail'!$4:$4, '2025 Overview (Rolling)'!I$11, 'Monthly Detail'!$93:$93) -> 9510.39 | J23: =SUMIF('Monthly Detail'!$4:$4, '2025 Overview (Rolling)'!J$11, 'Monthly Detail'!$93:$93) -> 17648.04 | ... N23: =SUMIF('Monthly Detail'!$4:$4, '2025 Overview (Rolling)'!N$11, 'Monthly Detail'!$93:$93) -> 14483.406 | P23: =SUM(C23:O23) -> 118763.02
B24: Operating Expenses | C24: =SUM(C23:C23) -> 4230.3 | D24: =SUM(D22:D23) -> 6699.3 | E24: =SUM(E22:E23) -> 7438.99 | F24: =SUM(F22:F23) -> 3780.99 | G24: =SUM(G22:G23) -> 3678.36 | H24: =SUM(H22:H23) -> 4152.38 | I24: =SUM(I22:I23) -> 9510.39 | J24: =SUM(J22:J23) -> 17648.04 | K24: =SUM(K22:K23) -> 13518.2 | ... N24: =SUM(N22:N23) -> 14483.406 | P24: =SUM(P22:P23) -> 118763.02
B26: Net Operating Income (EBITDA) | C26: =C19-C24 -> 2355.2 | D26: =D19-D24 -> 962.82 | E26: =E19-E24 -> 243.38 | F26: =F19-F24 -> -24.74 | G26: =G19-G24 -> 2096.14 | H26: =H19-H24 -> 2763.62 | I26: =I19-I24 -> 3837.11 | J26: =J19-J24 -> 2124.96 | ... N26: =N19-N24 -> 2600.3611 | P26: =P19-P24 -> 39939.114
B27: EBITDA % | C27: =C26/C14 -> 0.3576342 | D27: =D26/D14 -> 0.11868907 | E27: =E26/E14 -> 0.031680328 | F27: =F26/F14 -> -0.0065863561 | G27: =G26/G14 -> 0.34678468 | H27: =H26/H14 -> 0.39959803 | I27: =I26/I14 -> 0.2570067 | J27: =J26/J14 -> 0.10387447 | ... N27: =N26/N14 -> 0.14411446 | P27: =P26/P14 -> 0.23088818
B29: Other Income / (Expense) | C29: =SUMIF('Monthly Detail'!$4:$4, '2025 Overview (Rolling)'!C$11, 'Monthly Detail'!107:107) -> -821.84 | D29: =SUMIF('Monthly Detail'!$4:$4, '2025 Overview (Rolling)'!D$11, 'Monthly Detail'!107:107) -> -775.57 | E29: =SUMIF('Monthly Detail'!$4:$4, '2025 Overview (Rolling)'!E$11, 'Monthly Detail'!107:107) -> -757.92 | F29: =SUMIF('Monthly Detail'!$4:$4, '2025 Overview (Rolling)'!F$11, 'Monthly Detail'!107:107) -> -757.92 | G29: =SUMIF('Monthly Detail'!$4:$4, '2025 Overview (Rolling)'!G$11, 'Monthly Detail'!107:107) -> -692.87 | H29: =SUMIF('Monthly Detail'!$4:$4, '2025 Overview (Rolling)'!H$11, 'Monthly Detail'!107:107) -> -769.02 | I29: =SUMIF('Monthly Detail'!$4:$4, '2025 Overview (Rolling)'!I$11, 'Monthly Detail'!107:107) -> -775.25 | J29: =SUMIF('Monthly Detail'!$4:$4, '2025 Overview (Rolling)'!J$11, 'Monthly Detail'!107:107) -> -727.32 | ... N29: =SUMIF('Monthly Detail'!$4:$4, '2025 Overview (Rolling)'!N$11, 'Monthly Detail'!107:107) -> -800 | P29: =SUM(C29:O29) -> -9246.3
B30: Net Income | C30: =C26+SUM(C29:C29) -> 1533.36 | D30: =D26+SUM(D29:D29) -> 187.25 | E30: =E26+SUM(E29:E29) -> -514.54 | F30: =F26+SUM(F29:F29) -> -782.66 | G30: =G26+SUM(G29:G29) -> 1403.27 | H30: =H26+SUM(H29:H29) -> 1994.6 | I30: =I26+SUM(I29:I29) -> 3061.86 | J30: =J26+SUM(J29:J29) -> 1397.64 | ... N30: =N26+SUM(N29:N29) -> 1800.3611 | P30: =P26+SUM(P29:P29) -> 30692.814
B31: NI % | C31: =C30/C14 -> 0.23283881 | D31: =D30/D14 -> 0.023082745 | E31: =E30/E14 -> -0.066976727 | F31: =F30/F14 -> -0.20836206 | G31: =G30/G14 -> 0.23215651 | H31: =H30/H14 -> 0.2884037 | I31: =I30/I14 -> 0.20508104 | J31: =J30/J14 -> 0.068320868 | ... N31: =N30/N14 -> 0.099777707 | P31: =P30/P14 -> 0.17743528
B32: Cash Contributions | C32: ='Monthly Detail'!AN147-'Monthly Detail'!AM147 -> 0 | D32: ='Monthly Detail'!AO147-'Monthly Detail'!AN147 -> 0 | E32: ='Monthly Detail'!AP147-'Monthly Detail'!AO147 -> 0 | F32: ='Monthly Detail'!AQ147-'Monthly Detail'!AP147 -> 20675 | G32: ='Monthly Detail'!AR147-'Monthly Detail'!AQ147 -> 7721 | H32: ='Monthly Detail'!AS147-'Monthly Detail'!AR147 -> 0 | I32: ='Monthly Detail'!AT147-'Monthly Detail'!AS147 -> 250 | J32: ='Monthly Detail'!AU147-'Monthly Detail'!AT147 -> 0 | ... N32: ='Monthly Detail'!AY147-'Monthly Detail'!AX147 -> 0 | P32: =+SUM(C32:N32) -> 30646
B33: Owner Cash Distributions/Taxes | C33: =+SUM('Monthly Detail'!AN148,'Monthly Detail'!AN150:AN151)-SUM('Monthly Detail'!AM148,'Monthly Detail'!AM150:AM151) -> -2150 | D33: =+SUM('Monthly Detail'!AO148,'Monthly Detail'!AO150:AO151)-SUM('Monthly Detail'!AN148,'Monthly Detail'!AN150:AN151) -> 0 | E33: =+SUM('Monthly Detail'!AP148,'Monthly Detail'!AP150:AP151)-SUM('Monthly Detail'!AO148,'Monthly Detail'!AO150:AO151) -> 0 | F33: =+SUM('Monthly Detail'!AQ148,'Monthly Detail'!AQ150:AQ151)-SUM('Monthly Detail'!AP148,'Monthly Detail'!AP150:AP151) -> -20674 | G33: =+SUM('Monthly Detail'!AR148,'Monthly Detail'!AR150:AR151)-SUM('Monthly Detail'!AQ148,'Monthly Detail'!AQ150:AQ151) -> -8467.49 | H33: =+SUM('Monthly Detail'!AS148,'Monthly Detail'!AS150:AS151)-SUM('Monthly Detail'!AR148,'Monthly Detail'!AR150:AR151) -> 655.25 | I33: =+SUM('Monthly Detail'!AT148,'Monthly Detail'!AT150:AT151)-SUM('Monthly Detail'!AS148,'Monthly Detail'!AS150:AS151) -> -1057.78 | J33: =+SUM('Monthly Detail'!AU148,'Monthly Detail'!AU150:AU151)-SUM('Monthly Detail'!AT148,'Monthly Detail'!AT150:AT151) -> 0 | ... N33: =+SUM('Monthly Detail'!AY148,'Monthly Detail'!AY150:AY151)-SUM('Monthly Detail'!AX148,'Monthly Detail'!AX150:AX151) -> 0 | P33: =+SUM(C33:N33) -> -34268.24
B34: Accrued Tax Burden | C34: =+C30*0.3 -> 460.008 | D34: =+C34+(D26*0.3)-SUMIF('Monthly Detail'!$4:$4, '2025 Overview (Rolling)'!D$11, 'Monthly Detail'!75:75) -> 313.034 | E34: =+D34+(E26*0.3)-SUMIF('Monthly Detail'!$4:$4, '2025 Overview (Rolling)'!E$11, 'Monthly Detail'!75:75) -> -30.252 | F34: =+E34+(F26*0.3)-SUMIF('Monthly Detail'!$4:$4, '2025 Overview (Rolling)'!F$11, 'Monthly Detail'!75:75) -> -225.104 | G34: =+F34+(G26*0.3)-SUMIF('Monthly Detail'!$4:$4, '2025 Overview (Rolling)'!G$11, 'Monthly Detail'!75:75) -> 253.798 | H34: =+G34+(H26*0.3)-SUMIF('Monthly Detail'!$4:$4, '2025 Overview (Rolling)'!H$11, 'Monthly Detail'!75:75) -> 895.464 | I34: =+H34+(I26*0.3)-SUMIF('Monthly Detail'!$4:$4, '2025 Overview (Rolling)'!I$11, 'Monthly Detail'!75:75) -> 1895.827 | J34: =+I34+(J26*0.3)-SUMIF('Monthly Detail'!$4:$4, '2025 Overview (Rolling)'!J$11, 'Monthly Detail'!75:75) -> 1699.875 | K34: =+J34+(K26*0.3)-SUMIF('Monthly Detail'!$4:$4, '2025 Overview (Rolling)'!K$11, 'Monthly Detail'!75:75) -> 4163.943 | ... N34: =+M34+(N26*0.3)-SUMIF('Monthly Detail'!$4:$4, '2025 Overview (Rolling)'!N$11, 'Monthly Detail'!75:75) -> 5705.8921 | P34: =+N34 -> 5705.8921
B36: Operating Cash | C36: =SUMIF('Monthly Detail'!$4:$4, '2025 Overview (Rolling)'!C$11, 'Monthly Detail'!172:172) -> 3823.59 | D36: =SUMIF('Monthly Detail'!$4:$4, '2025 Overview (Rolling)'!D$11, 'Monthly Detail'!172:172) -> 494.25 | E36: =SUMIF('Monthly Detail'!$4:$4, '2025 Overview (Rolling)'!E$11, 'Monthly Detail'!172:172) -> 985.19 | F36: =SUMIF('Monthly Detail'!$4:$4, '2025 Overview (Rolling)'!F$11, 'Monthly Detail'!172:172) -> 1331.53 | G36: =SUMIF('Monthly Detail'!$4:$4, '2025 Overview (Rolling)'!G$11, 'Monthly Detail'!172:172) -> 557.08 | H36: =SUMIF('Monthly Detail'!$4:$4, '2025 Overview (Rolling)'!H$11, 'Monthly Detail'!172:172) -> 1059.5 | I36: =SUMIF('Monthly Detail'!$4:$4, '2025 Overview (Rolling)'!I$11, 'Monthly Detail'!172:172) -> 3158.83 | J36: =SUMIF('Monthly Detail'!$4:$4, '2025 Overview (Rolling)'!J$11, 'Monthly Detail'!172:172) -> 3999.47 | ... N36: =SUMIF('Monthly Detail'!$4:$4, '2025 Overview (Rolling)'!N$11, 'Monthly Detail'!172:172) -> 26701.564
B37: Cash Inflow (Outflow) | C37: =SUMIF('Monthly Detail'!$4:$4, '2025 Overview (Rolling)'!C$11, 'Monthly Detail'!169:169) -> 3530.76 | D37: =SUMIF('Monthly Detail'!$4:$4, '2025 Overview (Rolling)'!D$11, 'Monthly Detail'!169:169) -> -3329.34 | E37: =SUMIF('Monthly Detail'!$4:$4, '2025 Overview (Rolling)'!E$11, 'Monthly Detail'!169:169) -> 490.94 | F37: =SUMIF('Monthly Detail'!$4:$4, '2025 Overview (Rolling)'!F$11, 'Monthly Detail'!169:169) -> 346.34 | G37: =SUMIF('Monthly Detail'!$4:$4, '2025 Overview (Rolling)'!G$11, 'Monthly Detail'!169:169) -> -774.45 | H37: =SUMIF('Monthly Detail'!$4:$4, '2025 Overview (Rolling)'!H$11, 'Monthly Detail'!169:169) -> 502.42 | I37: =SUMIF('Monthly Detail'!$4:$4, '2025 Overview (Rolling)'!I$11, 'Monthly Detail'!169:169) -> 2099.33 | J37: =SUMIF('Monthly Detail'!$4:$4, '2025 Overview (Rolling)'!J$11, 'Monthly Detail'!169:169) -> 840.64 | ... N37: =SUMIF('Monthly Detail'!$4:$4, '2025 Overview (Rolling)'!N$11, 'Monthly Detail'!169:169) -> 935.93232

Sheet 2025 Overview (Budget)
B8: 2025 Overview (Annual Operating Plan)
C10: =TEXT('Monthly Detail'!D4,"mmmm") -> January | D10: =TEXT('Monthly Detail'!E4,"mmmm") -> February | E10: =TEXT('Monthly Detail'!F4,"mmmm") -> March | F10: =TEXT('Monthly Detail'!G4,"mmmm") -> April | G10: =TEXT('Monthly Detail'!H4,"mmmm") -> May | H10: =TEXT('Monthly Detail'!I4,"mmmm") -> June | I10: =TEXT('Monthly Detail'!J4,"mmmm") -> July | J10: =TEXT('Monthly Detail'!K4,"mmmm") -> August | ... N10: =TEXT('Monthly Detail'!O4,"mmmm") -> December | P10: Total
C11: 45688 | D11: 45716 | E11: 45747 | F11: 45777 | G11: 45808 | H11: 45838 | I11: 45869 | J11: 45900 | K11: 45930 | L11: 45961 | M11: 45991 | N11: 46022 | O11: 45322
B12: Service Income | C12: =+'2025 Overview (Rolling)'!C12 -> 6477.5 | D12: =+'2025 Overview (Rolling)'!D12 -> 8052.5 | E12: =+'2025 Overview (Rolling)'!E12 -> 7630 | F12: =+'2025 Overview (Rolling)'!F12 -> 3756.25 | G12: =+'2025 Overview (Rolling)'!G12 -> 6032.5 | H12: =+'2025 Overview (Rolling)'!H12 -> 6822.5 | I12: =+'2025 Overview (Rolling)'!I12 -> 14855 | J12: =+'2025 Overview (Rolling)'!J12 -> 20412.5 | ... L12: =+'2025 Overview (Rolling)'!L12 -> 39333.76 | M12: =+'2025 AOP'!M12 -> 8797.317 | N12: =+'2025 AOP'!N12 -> 6287.4785 | P12: =SUM(C12:O12) -> 156714.81
B13: Tips | C13: =+'2025 Overview (Rolling)'!C13 -> 108 | D13: =+'2025 Overview (Rolling)'!D13 -> 59.62 | E13: =+'2025 Overview (Rolling)'!E13 -> 52.37 | F13: =+'2025 Overview (Rolling)'!F13 -> 0 | G13: =+'2025 Overview (Rolling)'!G13 -> 12 | H13: =+'2025 Overview (Rolling)'!H13 -> 93.5 | I13: =+'2025 Overview (Rolling)'!I13 -> 75 | J13: =+'2025 Overview (Rolling)'!J13 -> 44.5 | ... L13: =+'2025 Overview (Rolling)'!L13 -> 29.37 | M13: =+'2025 AOP'!M13 -> 15.950161 | N13: =+'2025 AOP'!N13 -> 11.399646 | P13: =+SUM(C13:N13) -> 551.70981
B14: Total Income | C14: =+'2025 Overview (Rolling)'!C14 -> 6585.5 | D14: =+'2025 Overview (Rolling)'!D14 -> 8112.12 | E14: =+'2025 Overview (Rolling)'!E14 -> 7682.37 | F14: =+'2025 Overview (Rolling)'!F14 -> 3756.25 | G14: =+'2025 Overview (Rolling)'!G14 -> 6044.5 | H14: =+'2025 Overview (Rolling)'!H14 -> 6916 | I14: =+'2025 Overview (Rolling)'!I14 -> 14930 | J14: =+'2025 Overview (Rolling)'!J14 -> 20457 | ... L14: =+'2025 Overview (Rolling)'!L14 -> 39363.13 | M14: =SUM(M12:M13) -> 8813.2671 | N14: =SUM(N12:N13) -> 6298.8782 | P14: =SUM(P12:P13) -> 157266.52
B15: # of Students | C15: =+'2025 Overview (Rolling)'!C15 -> 24 | D15: =+'2025 Overview (Rolling)'!D15 -> 28 | E15: =+'2025 Overview (Rolling)'!E15 -> 24 | F15: =+'2025 Overview (Rolling)'!F15 -> 23 | G15: =+'2025 Overview (Rolling)'!G15 -> 20 | H15: =+'2025 Overview (Rolling)'!H15 -> 25 | I15: =+'2025 Overview (Rolling)'!I15 -> 35 | J15: =+'2025 Overview (Rolling)'!J15 -> 48 | ... L15: =+'2025 Overview (Rolling)'!L15 -> 67 | M15: =+'2025 AOP'!M15 -> 43.6 | N15: =+'2025 AOP'!N15 -> 42.2
B17: Subcontractor Expenses | C17: =+'2025 Overview (Rolling)'!C18 -> 0 | D17: =+'2025 Overview (Rolling)'!D18 -> 450 | E17: =+'2025 Overview (Rolling)'!E18 -> 0 | F17: =+'2025 Overview (Rolling)'!F18 -> 0 | G17: =+'2025 Overview (Rolling)'!G18 -> 270 | H17: =+'2025 Overview (Rolling)'!H18 -> 0 | I17: =+'2025 Overview (Rolling)'!I18 -> 1582.5 | J17: =+'2025 Overview (Rolling)'!J18 -> 684 | ... L17: =+'2025 Overview (Rolling)'!L18 -> 6255 | M17: =+'2025 AOP'!M18 -> 524 | N17: =+'2025 AOP'!N18 -> 0 | P17: =SUM(C17:O17) -> 13842.24
B18: Gross Margin | C18: =+'2025 Overview (Rolling)'!C19 -> 6585.5 | D18: =+'2025 Overview (Rolling)'!D19 -> 7662.12 | E18: =+'2025 Overview (Rolling)'!E19 -> 7682.37 | F18: =+'2025 Overview (Rolling)'!F19 -> 3756.25 | G18: =+'2025 Overview (Rolling)'!G19 -> 5774.5 | H18: =+'2025 Overview (Rolling)'!H19 -> 6916 | I18: =+'2025 Overview (Rolling)'!I19 -> 13347.5 | J18: =+'2025 Overview (Rolling)'!J19 -> 19773 | ... L18: =+'2025 Overview (Rolling)'!L19 -> 33108.13 | M18: =M14-M17 -> 8289.2671 | N18: =N14-N17 -> 6298.8782 | P18: =P14-P17 -> 143424.28
B19: GM % | C19: =+'2025 Overview (Rolling)'!C20 -> 1 | D19: =+'2025 Overview (Rolling)'!D20 -> 0.94452745 | E19: =+'2025 Overview (Rolling)'!E20 -> 1 | F19: =+'2025 Overview (Rolling)'!F20 -> 1 | G19: =+'2025 Overview (Rolling)'!G20 -> 0.95533129 | H19: =+'2025 Overview (Rolling)'!H20 -> 1 | I19: =+'2025 Overview (Rolling)'!I20 -> 0.89400536 | J19: =+'2025 Overview (Rolling)'!J20 -> 0.96656401 | ... L19: =+'2025 Overview (Rolling)'!L20 -> 0.84109495 | M19: =M18/M14 -> 0.94054418 | N19: =N18/N14 -> 1 | P19: =P18/P14 -> 0.91198228
B21: Sales & Marketing Expenses | C21: =+'2025 Overview (Rolling)'!C22 -> 0 | D21: =+'2025 Overview (Rolling)'!D22 -> 0 | E21: =+'2025 Overview (Rolling)'!E22 -> 0 | F21: =+'2025 Overview (Rolling)'!F22 -> 0 | G21: =+'2025 Overview (Rolling)'!G22 -> 0 | H21: =+'2025 Overview (Rolling)'!H22 -> 0 | I21: =+'2025 Overview (Rolling)'!I22 -> 0 | J21: =+'2025 Overview (Rolling)'!J22 -> 0 | ... L21: =+'2025 Overview (Rolling)'!L22 -> 0 | M21: =+'2025 AOP'!M22 -> 0 | N21: =+'2025 AOP'!N22 -> 0 | P21: =SUM(C21:O21) -> 0
B22: General & Admintrative Expenses | C22: =+'2025 Overview (Rolling)'!C23 -> 4230.3 | D22: =+'2025 Overview (Rolling)'!D23 -> 6699.3 | E22: =+'2025 Overview (Rolling)'!E23 -> 7438.99 | F22: =+'2025 Overview (Rolling)'!F23 -> 3780.99 | G22: =+'2025 Overview (Rolling)'!G23 -> 3678.36 | H22: =+'2025 Overview (Rolling)'!H23 -> 4152.38 | I22: =+'2025 Overview (Rolling)'!I23 -> 9510.39 | J22: =+'2025 Overview (Rolling)'!J23 -> 17648.04 | ... L22: =+'2025 Overview (Rolling)'!L23 -> 18946.23 | M22: =+'2025 AOP'!M23 -> 1340.2174 | N22: =+'2025 AOP'!N23 -> 1635.3956 | P22: =SUM(C22:O22) -> 92578.793
B23: Operating Expenses | C23: =+'2025 Overview (Rolling)'!C24 -> 4230.3 | D23: =+'2025 Overview (Rolling)'!D24 -> 6699.3 | E23: =+'2025 Overview (Rolling)'!E24 -> 7438.99 | F23: =+'2025 Overview (Rolling)'!F24 -> 3780.99 | G23: =+'2025 Overview (Rolling)'!G24 -> 3678.36 | H23: =+'2025 Overview (Rolling)'!H24 -> 4152.38 | I23: =+'2025 Overview (Rolling)'!I24 -> 9510.39 | J23: =+'2025 Overview (Rolling)'!J24 -> 17648.04 | ... L23: =+'2025 Overview (Rolling)'!L24 -> 18946.23 | M23: =SUM(M21:M22) -> 1340.2174 | N23: =SUM(N21:N22) -> 1635.3956 | P23: =SUM(P21:P22) -> 92578.793
B25: Net Operating Income (EBITDA) | C25: =+'2025 Overview (Rolling)'!C26 -> 2355.2 | D25: =+'2025 Overview (Rolling)'!D26 -> 962.82 | E25: =+'2025 Overview (Rolling)'!E26 -> 243.38 | F25: =+'2025 Overview (Rolling)'!F26 -> -24.74 | G25: =+'2025 Overview (Rolling)'!G26 -> 2096.14 | H25: =+'2025 Overview (Rolling)'!H26 -> 2763.62 | I25: =+'2025 Overview (Rolling)'!I26 -> 3837.11 | J25: =+'2025 Overview (Rolling)'!J26 -> 2124.96 | ... L25: =+'2025 Overview (Rolling)'!L26 -> 14161.9 | M25: =M18-M23 -> 6949.0498 | N25: =N18-N23 -> 4663.4826 | P25: =P18-P23 -> 50845.482
B26: EBITDA % | C26: =+'2025 Overview (Rolling)'!C27 -> 0.3576342 | D26: =+'2025 Overview (Rolling)'!D27 -> 0.11868907 | E26: =+'2025 Overview (Rolling)'!E27 -> 0.031680328 | F26: =+'2025 Overview (Rolling)'!F27 -> -0.0065863561 | G26: =+'2025 Overview (Rolling)'!G27 -> 0.34678468 | H26: =+'2025 Overview (Rolling)'!H27 -> 0.39959803 | I26: =+'2025 Overview (Rolling)'!I27 -> 0.2570067 | J26: =+'2025 Overview (Rolling)'!J27 -> 0.10387447 | ... L26: =+'2025 Overview (Rolling)'!L27 -> 0.35977576 | M26: =M25/M14 -> 0.78847601 | N26: =N25/N14 -> 0.74036716 | P26: =P25/P14 -> 0.32330774
B28: Other Income / (Expense) | C28: =+'2025 Overview (Rolling)'!C29 -> -821.84 | D28: =+'2025 Overview (Rolling)'!D29 -> -775.57 | E28: =+'2025 Overview (Rolling)'!E29 -> -757.92 | F28: =+'2025 Overview (Rolling)'!F29 -> -757.92 | G28: =+'2025 Overview (Rolling)'!G29 -> -692.87 | H28: =+'2025 Overview (Rolling)'!H29 -> -769.02 | I28: =+'2025 Overview (Rolling)'!I29 -> -775.25 | J28: =+'2025 Overview (Rolling)'!J29 -> -727.32 | ... L28: =+'2025 Overview (Rolling)'!L29 -> -842.23 | M28: =+'2025 AOP'!M29 -> -800 | N28: =+'2025 AOP'!N29 -> -800 | P28: =SUM(C28:O28) -> -9246.3
B29: Net Income | C29: =+'2025 Overview (Rolling)'!C30 -> 1533.36 | D29: =+'2025 Overview (Rolling)'!D30 -> 187.25 | E29: =+'2025 Overview (Rolling)'!E30 -> -514.54 | F29: =+'2025 Overview (Rolling)'!F30 -> -782.66 | G29: =+'2025 Overview (Rolling)'!G30 -> 1403.27 | H29: =+'2025 Overview (Rolling)'!H30 -> 1994.6 | I29: =+'2025 Overview (Rolling)'!I30 -> 3061.86 | J29: =+'2025 Overview (Rolling)'!J30 -> 1397.64 | ... L29: =+'2025 Overview (Rolling)'!L30 -> 13319.67 | M29: =M25+SUM(M28:M28) -> 6149.0498 | N29: =N25+SUM(N28:N28) -> 3863.4826 | P29: =P25+SUM(P28:P28) -> 41599.182
B30: NI % | C30: =+'2025 Overview (Rolling)'!C31 -> 0.23283881 | D30: =+'2025 Overview (Rolling)'!D31 -> 0.023082745 | E30: =+'2025 Overview (Rolling)'!E31 -> -0.066976727 | F30: =+'2025 Overview (Rolling)'!F31 -> -0.20836206 | G30: =+'2025 Overview (Rolling)'!G31 -> 0.23215651 | H30: =+'2025 Overview (Rolling)'!H31 -> 0.2884037 | I30: =+'2025 Overview (Rolling)'!I31 -> 0.20508104 | J30: =+'2025 Overview (Rolling)'!J31 -> 0.068320868 | ... L30: =+'2025 Overview (Rolling)'!L31 -> 0.33837934 | M30: =M29/M14 -> 0.69770377 | N30: =N29/N14 -> 0.61336042 | P30: =P29/P14 -> 0.26451392
B32: Operating Cash | C32: =+'2025 Overview (Rolling)'!C36 -> 3823.59 | D32: =+'2025 Overview (Rolling)'!D36 -> 494.25 | E32: =+'2025 Overview (Rolling)'!E36 -> 985.19 | F32: =+'2025 Overview (Rolling)'!F36 -> 1331.53 | G32: =+'2025 Overview (Rolling)'!G36 -> 557.08 | H32: =+'2025 Overview (Rolling)'!H36 -> 1059.5 | I32: =+'2025 Overview (Rolling)'!I36 -> 3158.83 | J32: =+'2025 Overview (Rolling)'!J36 -> 3999.47 | ... L32: =+'2025 Overview (Rolling)'!L36 -> 10262.87 | M32: =+'2024 AOP'!M31 -> 36536.59 | N32: =+'2024 AOP'!N31 -> 38730.025
B33: Cash Inflow (Outflow) | C33: =+'2025 Overview (Rolling)'!C37 -> 3530.76 | D33: =+'2025 Overview (Rolling)'!D37 -> -3329.34 | E33: =+'2025 Overview (Rolling)'!E37 -> 490.94 | F33: =+'2025 Overview (Rolling)'!F37 -> 346.34 | G33: =+'2025 Overview (Rolling)'!G37 -> -774.45 | H33: =+'2025 Overview (Rolling)'!H37 -> 502.42 | I33: =+'2025 Overview (Rolling)'!I37 -> 2099.33 | J33: =+'2025 Overview (Rolling)'!J37 -> 840.64 | ... L33: =+'2025 Overview (Rolling)'!L37 -> 4129.67 | M33: =+'2024 AOP'!M32 -> 1814.0563 | N33: =+'2024 AOP'!N32 -> 2193.4353

Sheet 2024 Overview (Rolling)
B8: 2024 Overview (Rolling Forecast)
C10: =TEXT('Monthly Detail'!D4,"mmmm") -> January | D10: =TEXT('Monthly Detail'!E4,"mmmm") -> February | E10: =TEXT('Monthly Detail'!F4,"mmmm") -> March | F10: =TEXT('Monthly Detail'!G4,"mmmm") -> April | G10: =TEXT('Monthly Detail'!H4,"mmmm") -> May | H10: =TEXT('Monthly Detail'!I4,"mmmm") -> June | I10: =TEXT('Monthly Detail'!J4,"mmmm") -> July | J10: =TEXT('Monthly Detail'!K4,"mmmm") -> August | ... N10: =TEXT('Monthly Detail'!O4,"mmmm") -> December | P10: Total
C11: 45322 | D11: 45351 | E11: 45382 | F11: 45412 | G11: 45443 | H11: 45473 | I11: 45504 | J11: 45535 | K11: 45565 | L11: 45596 | M11: 45626 | N11: 45657 | O11: 45322
B12: Service Income | C12: =SUMIF('Monthly Detail'!$4:$4, '2024 Overview (Rolling)'!C$11, 'Monthly Detail'!12:12) -> 2885 | D12: =SUMIF('Monthly Detail'!$4:$4, '2024 Overview (Rolling)'!D$11, 'Monthly Detail'!12:12) -> 4357.5 | E12: =SUMIF('Monthly Detail'!$4:$4, '2024 Overview (Rolling)'!E$11, 'Monthly Detail'!12:12) -> 3467.5 | F12: =SUMIF('Monthly Detail'!$4:$4, '2024 Overview (Rolling)'!F$11, 'Monthly Detail'!12:12) -> 4000 | G12: =SUMIF('Monthly Detail'!$4:$4, '2024 Overview (Rolling)'!G$11, 'Monthly Detail'!12:12) -> 5370 | H12: =SUMIF('Monthly Detail'!$4:$4, '2024 Overview (Rolling)'!H$11, 'Monthly Detail'!12:12) -> 4296.26 | I12: =SUMIF('Monthly Detail'!$4:$4, '2024 Overview (Rolling)'!I$11, 'Monthly Detail'!12:12) -> 9031.27 | J12: =SUMIF('Monthly Detail'!$4:$4, '2024 Overview (Rolling)'!J$11, 'Monthly Detail'!12:12) -> 14073.76 | ... N12: =SUMIF('Monthly Detail'!$4:$4, '2024 Overview (Rolling)'!N$11, 'Monthly Detail'!12:12) -> 5160 | P12: =SUM(C12:O12) -> 89488.79
B13: Tips | C13: =SUMIF('Monthly Detail'!$4:$4, '2024 Overview (Rolling)'!C$11, 'Monthly Detail'!13:13) -> 117 | D13: =SUMIF('Monthly Detail'!$4:$4, '2024 Overview (Rolling)'!D$11, 'Monthly Detail'!13:13) -> 0 | E13: =SUMIF('Monthly Detail'!$4:$4, '2024 Overview (Rolling)'!E$11, 'Monthly Detail'!13:13) -> 12 | F13: =SUMIF('Monthly Detail'!$4:$4, '2024 Overview (Rolling)'!F$11, 'Monthly Detail'!13:13) -> 18 | G13: =SUMIF('Monthly Detail'!$4:$4, '2024 Overview (Rolling)'!G$11, 'Monthly Detail'!13:13) -> 50.08 | H13: =SUMIF('Monthly Detail'!$4:$4, '2024 Overview (Rolling)'!H$11, 'Monthly Detail'!13:13) -> 12 | I13: =SUMIF('Monthly Detail'!$4:$4, '2024 Overview (Rolling)'!I$11, 'Monthly Detail'!13:13) -> 29.62 | J13: =SUMIF('Monthly Detail'!$4:$4, '2024 Overview (Rolling)'!J$11, 'Monthly Detail'!13:13) -> 37.5 | ... N13: =SUMIF('Monthly Detail'!$4:$4, '2024 Overview (Rolling)'!N$11, 'Monthly Detail'!13:13) -> 34 | P13: =+SUM(C13:N13) -> 339.45
B14: Total Income | C14: =SUM(C12:C13) -> 3002 | D14: =SUM(D12:D13) -> 4357.5 | E14: =SUM(E12:E13) -> 3479.5 | F14: =SUM(F12:F13) -> 4018 | G14: =SUM(G12:G13) -> 5420.08 | H14: =SUM(H12:H13) -> 4308.26 | I14: =SUM(I12:I13) -> 9060.89 | J14: =SUM(J12:J13) -> 14111.26 | ... N14: =SUM(N12:N13) -> 5194 | P14: =SUM(P12:P13) -> 89828.24
B15: # of Students | C15: =+'Monthly Detail'!AB17 -> 16 | D15: =+'Monthly Detail'!AC17 -> 15 | E15: =+'Monthly Detail'!AD17 -> 20 | F15: =+'Monthly Detail'!AE17 -> 17 | G15: =+'Monthly Detail'!AF17 -> 20 | H15: =+'Monthly Detail'!AG17 -> 24 | I15: =+'Monthly Detail'!AH17 -> 30 | J15: =+'Monthly Detail'!AI17 -> 38 | ... N15: =+'Monthly Detail'!AM17 -> 23
B16: # of Sessions | C16: =+'Monthly Detail'!AB22 -> 34 | D16: =+'Monthly Detail'!AC22 -> 56 | E16: =+'Monthly Detail'!AD22 -> 36 | F16: =+'Monthly Detail'!AE22 -> 49 | G16: =+'Monthly Detail'!AF22 -> 76 | H16: =+'Monthly Detail'!AG22 -> 45 | I16: =+'Monthly Detail'!AH22 -> 118 | J16: =+'Monthly Detail'!AI22 -> 169 | ... N16: =+'Monthly Detail'!AM22 -> 50
B18: Subcontractor Expenses | C18: =SUMIF('Monthly Detail'!$4:$4, '2025 Overview (Budget)'!C$11, 'Monthly Detail'!63:63) -> 0 | D18: =SUMIF('Monthly Detail'!$4:$4, '2025 Overview (Budget)'!D$11, 'Monthly Detail'!63:63) -> 450 | E18: =SUMIF('Monthly Detail'!$4:$4, '2025 Overview (Budget)'!E$11, 'Monthly Detail'!63:63) -> 0 | F18: =SUMIF('Monthly Detail'!$4:$4, '2025 Overview (Budget)'!F$11, 'Monthly Detail'!63:63) -> 0 | G18: =SUMIF('Monthly Detail'!$4:$4, '2025 Overview (Budget)'!G$11, 'Monthly Detail'!63:63) -> 270 | H18: =SUMIF('Monthly Detail'!$4:$4, '2025 Overview (Budget)'!H$11, 'Monthly Detail'!63:63) -> 0 | I18: =SUMIF('Monthly Detail'!$4:$4, '2025 Overview (Budget)'!I$11, 'Monthly Detail'!63:63) -> 1582.5 | J18: =SUMIF('Monthly Detail'!$4:$4, '2025 Overview (Budget)'!J$11, 'Monthly Detail'!63:63) -> 684 | ... N18: =SUMIF('Monthly Detail'!$4:$4, '2025 Overview (Budget)'!N$11, 'Monthly Detail'!63:63) -> 959.95423 | P18: =SUM(C18:O18) -> 14278.194
B19: Gross Margin | C19: =C14-C18 -> 3002 | D19: =D14-D18 -> 3907.5 | E19: =E14-E18 -> 3479.5 | F19: =F14-F18 -> 4018 | G19: =G14-G18 -> 5150.08 | H19: =H14-H18 -> 4308.26 | I19: =I14-I18 -> 7478.39 | J19: =J14-J18 -> 13427.26 | ... N19: =N14-N18 -> 4234.0458 | P19: =P14-P18 -> 75550.046
B20: GM % | C20: =C19/C14 -> 1 | D20: =D19/D14 -> 0.89672978 | E20: =E19/E14 -> 1 | F20: =F19/F14 -> 1 | G20: =G19/G14 -> 0.95018524 | H20: =H19/H14 -> 1 | I20: =I19/I14 -> 0.82534828 | J20: =J19/J14 -> 0.95152807 | ... N20: =N19/N14 -> 0.81518016 | P20: =P19/P14 -> 0.84105005
B22: Sales & Marketing Expenses | C22: =SUMIF('Monthly Detail'!$4:$4, '2024 Overview (Rolling)'!C$11, 'Monthly Detail'!$70:$70) -> 0 | D22: =SUMIF('Monthly Detail'!$4:$4, '2024 Overview (Rolling)'!D$11, 'Monthly Detail'!$70:$70) -> 1179.44 | E22: =SUMIF('Monthly Detail'!$4:$4, '2024 Overview (Rolling)'!E$11, 'Monthly Detail'!$70:$70) -> 0 | F22: =SUMIF('Monthly Detail'!$4:$4, '2024 Overview (Rolling)'!F$11, 'Monthly Detail'!$70:$70) -> 2400 | G22: =SUMIF('Monthly Detail'!$4:$4, '2024 Overview (Rolling)'!G$11, 'Monthly Detail'!$70:$70) -> 0 | H22: =SUMIF('Monthly Detail'!$4:$4, '2024 Overview (Rolling)'!H$11, 'Monthly Detail'!$70:$70) -> 665.56 | I22: =SUMIF('Monthly Detail'!$4:$4, '2024 Overview (Rolling)'!I$11, 'Monthly Detail'!$70:$70) -> 0 | J22: =SUMIF('Monthly Detail'!$4:$4, '2024 Overview (Rolling)'!J$11, 'Monthly Detail'!$70:$70) -> 0 | ... N22: =SUMIF('Monthly Detail'!$4:$4, '2024 Overview (Rolling)'!N$11, 'Monthly Detail'!$70:$70) -> 0 | P22: =SUM(C22:O22) -> 4245
B23: General & Admintrative Expenses | C23: =SUMIF('Monthly Detail'!$4:$4, '2024 Overview (Rolling)'!C$11, 'Monthly Detail'!$93:$93) -> 417.24 | D23: =SUMIF('Monthly Detail'!$4:$4, '2024 Overview (Rolling)'!D$11, 'Monthly Detail'!$93:$93) -> 436.02 | E23: =SUMIF('Monthly Detail'!$4:$4, '2024 Overview (Rolling)'!E$11, 'Monthly Detail'!$93:$93) -> 943.03 | F23: =SUMIF('Monthly Detail'!$4:$4, '2024 Overview (Rolling)'!F$11, 'Monthly Detail'!$93:$93) -> 382.8 | G23: =SUMIF('Monthly Detail'!$4:$4, '2024 Overview (Rolling)'!G$11, 'Monthly Detail'!$93:$93) -> 689.95 | H23: =SUMIF('Monthly Detail'!$4:$4, '2024 Overview (Rolling)'!H$11, 'Monthly Detail'!$93:$93) -> 913.86 | I23: =SUMIF('Monthly Detail'!$4:$4, '2024 Overview (Rolling)'!I$11, 'Monthly Detail'!$93:$93) -> 2146.76 | J23: =SUMIF('Monthly Detail'!$4:$4, '2024 Overview (Rolling)'!J$11, 'Monthly Detail'!$93:$93) -> 1446.32 | ... N23: =SUMIF('Monthly Detail'!$4:$4, '2024 Overview (Rolling)'!N$11, 'Monthly Detail'!$93:$93) -> 620.21 | P23: =SUM(C23:O23) -> 12495.71
B24: Operating Expenses | C24: =SUM(C23:C23) -> 417.24 | D24: =SUM(D22:D23) -> 1615.46 | E24: =SUM(E22:E23) -> 943.03 | F24: =SUM(F22:F23) -> 2782.8 | G24: =SUM(G22:G23) -> 689.95 | H24: =SUM(H22:H23) -> 1579.42 | I24: =SUM(I22:I23) -> 2146.76 | J24: =SUM(J22:J23) -> 1446.32 | K24: =SUM(K22:K23) -> 878.64 | ... N24: =SUM(N22:N23) -> 620.21 | P24: =SUM(P22:P23) -> 16740.71
B26: Net Operating Income (EBITDA) | C26: =C19-C24 -> 2584.76 | D26: =D19-D24 -> 2292.04 | E26: =E19-E24 -> 2536.47 | F26: =F19-F24 -> 1235.2 | G26: =G19-G24 -> 4460.13 | H26: =H19-H24 -> 2728.84 | I26: =I19-I24 -> 5331.63 | J26: =J19-J24 -> 11980.94 | ... N26: =N19-N24 -> 3613.8358 | P26: =P19-P24 -> 58809.336
B27: EBITDA % | C27: =C26/C14 -> 0.86101266 | D27: =D26/D14 -> 0.52599885 | E27: =E26/E14 -> 0.72897543 | F27: =F26/F14 -> 0.30741663 | G27: =G26/G14 -> 0.82289007 | H27: =H26/H14 -> 0.63339724 | I27: =I26/I14 -> 0.58842233 | J27: =J26/J14 -> 0.84903403 | ... N27: =N26/N14 -> 0.69577123 | P27: =P26/P14 -> 0.6546865
B29: Other Income / (Expense) | C29: =SUMIF('Monthly Detail'!$4:$4, '2024 Overview (Rolling)'!C$11, 'Monthly Detail'!107:107) -> 0 | D29: =SUMIF('Monthly Detail'!$4:$4, '2024 Overview (Rolling)'!D$11, 'Monthly Detail'!107:107) -> 0 | E29: =SUMIF('Monthly Detail'!$4:$4, '2024 Overview (Rolling)'!E$11, 'Monthly Detail'!107:107) -> 0 | F29: =SUMIF('Monthly Detail'!$4:$4, '2024 Overview (Rolling)'!F$11, 'Monthly Detail'!107:107) -> 0 | G29: =SUMIF('Monthly Detail'!$4:$4, '2024 Overview (Rolling)'!G$11, 'Monthly Detail'!107:107) -> 0 | H29: =SUMIF('Monthly Detail'!$4:$4, '2024 Overview (Rolling)'!H$11, 'Monthly Detail'!107:107) -> -690.26 | I29: =SUMIF('Monthly Detail'!$4:$4, '2024 Overview (Rolling)'!I$11, 'Monthly Detail'!107:107) -> -715.26 | J29: =SUMIF('Monthly Detail'!$4:$4, '2024 Overview (Rolling)'!J$11, 'Monthly Detail'!107:107) -> -639.19 | ... N29: =SUMIF('Monthly Detail'!$4:$4, '2024 Overview (Rolling)'!N$11, 'Monthly Detail'!107:107) -> -790.04 | P29: =SUM(C29:O29) -> -5018.23
B30: Net Income | C30: =C26+SUM(C29:C29) -> 2584.76 | D30: =D26+SUM(D29:D29) -> 2292.04 | E30: =E26+SUM(E29:E29) -> 2536.47 | F30: =F26+SUM(F29:F29) -> 1235.2 | G30: =G26+SUM(G29:G29) -> 4460.13 | H30: =H26+SUM(H29:H29) -> 2038.58 | I30: =I26+SUM(I29:I29) -> 4616.37 | J30: =J26+SUM(J29:J29) -> 11341.75 | ... N30: =N26+SUM(N29:N29) -> 2823.7958 | P30: =P26+SUM(P29:P29) -> 53791.106
B31: NI % | C31: =C30/C14 -> 0.86101266 | D31: =D30/D14 -> 0.52599885 | E31: =E30/E14 -> 0.72897543 | F31: =F30/F14 -> 0.30741663 | G31: =G30/G14 -> 0.82289007 | H31: =H30/H14 -> 0.47317943 | I31: =I30/I14 -> 0.50948306 | J31: =J30/J14 -> 0.80373758 | ... N31: =N30/N14 -> 0.54366495 | P31: =P30/P14 -> 0.59882177
B32: Cash Contributions | C32: =+'Monthly Detail'!AB147-'Monthly Detail'!AA147 -> 0 | D32: =+'Monthly Detail'!AC147-'Monthly Detail'!AB147 -> 0 | E32: =+'Monthly Detail'!AD147-'Monthly Detail'!AC147 -> 0 | F32: =+'Monthly Detail'!AE147-'Monthly Detail'!AD147 -> 2400 | G32: =+'Monthly Detail'!AF147-'Monthly Detail'!AE147 -> 0 | H32: =+'Monthly Detail'!AG147-'Monthly Detail'!AF147 -> 0 | I32: =+'Monthly Detail'!AH147-'Monthly Detail'!AG147 -> 0 | J32: =+'Monthly Detail'!AI147-'Monthly Detail'!AH147 -> 0 | ... N32: =+'Monthly Detail'!AM147-'Monthly Detail'!AL147 -> 0 | P32: =+SUM(C32:N32) -> 2400
B33: Owner Cash Distributions | C33: =+'Monthly Detail'!AB148-'Monthly Detail'!AA148 -> -1900 | D33: =+'Monthly Detail'!AC148-'Monthly Detail'!AB148 -> -3325 | E33: =+'Monthly Detail'!AD148-'Monthly Detail'!AC148 -> -3220 | F33: =+'Monthly Detail'!AE148-'Monthly Detail'!AD148 -> -2325 | G33: =+'Monthly Detail'!AF148-'Monthly Detail'!AE148 -> -4100 | H33: =+'Monthly Detail'!AG148-'Monthly Detail'!AF148 -> -2750 | I33: =+'Monthly Detail'!AH148-'Monthly Detail'!AG148 -> -2903.95 | J33: =+'Monthly Detail'!AI148-'Monthly Detail'!AH148 -> -9775 | ... N33: =+'Monthly Detail'!AM148-'Monthly Detail'!AL148 -> -7452.41 | P33: =+SUM(C33:N33) -> -64798.86
B34: Accrued Tax Burden | C34: =+(C30)*0.153 -> 395.46828 | D34: =+C34+((D26)*0.153) -> 746.1504 | E34: =+D34+((E26)*0.153) -> 1134.2303 | F34: =+E34+((F26)*0.153) -> 1323.2159 | G34: =+F34+((G26)*0.153) -> 2005.6158 | H34: =+G34+((H26)*0.153) -> 2423.1283 | I34: =+H34+((I26)*0.153) -> 3238.8677 | J34: =+I34+((J26)*0.153) -> 5071.9515 | K34: =+J34+((K26)*0.153) -> 5828.0959 | ... N34: =+M34+((N26)*0.153) -> 8997.8284 | P34: =+N34 -> 8997.8284
B36: Operating Cash | C36: =SUMIF('Monthly Detail'!$4:$4, '2024 Overview (Rolling)'!C$11, 'Monthly Detail'!172:172) -> 1291.78 | D36: =SUMIF('Monthly Detail'!$4:$4, '2024 Overview (Rolling)'!D$11, 'Monthly Detail'!172:172) -> 551.32 | E36: =SUMIF('Monthly Detail'!$4:$4, '2024 Overview (Rolling)'!E$11, 'Monthly Detail'!172:172) -> 177.79 | F36: =SUMIF('Monthly Detail'!$4:$4, '2024 Overview (Rolling)'!F$11, 'Monthly Detail'!172:172) -> 1342.99 | G36: =SUMIF('Monthly Detail'!$4:$4, '2024 Overview (Rolling)'!G$11, 'Monthly Detail'!172:172) -> 1278.09 | H36: =SUMIF('Monthly Detail'!$4:$4, '2024 Overview (Rolling)'!H$11, 'Monthly Detail'!172:172) -> 1615.7 | I36: =SUMIF('Monthly Detail'!$4:$4, '2024 Overview (Rolling)'!I$11, 'Monthly Detail'!172:172) -> 3158.98 | J36: =SUMIF('Monthly Detail'!$4:$4, '2024 Overview (Rolling)'!J$11, 'Monthly Detail'!172:172) -> 3192.6 | ... N36: =SUMIF('Monthly Detail'!$4:$4, '2024 Overview (Rolling)'!N$11, 'Monthly Detail'!172:172) -> 292.83
B37: Cash Inflow (Outflow) | C37: =SUMIF('Monthly Detail'!$4:$4, '2024 Overview (Rolling)'!C$11, 'Monthly Detail'!169:169) -> 294.76 | D37: =SUMIF('Monthly Detail'!$4:$4, '2024 Overview (Rolling)'!D$11, 'Monthly Detail'!169:169) -> -740.46 | E37: =SUMIF('Monthly Detail'!$4:$4, '2024 Overview (Rolling)'!E$11, 'Monthly Detail'!169:169) -> -373.53 | F37: =SUMIF('Monthly Detail'!$4:$4, '2024 Overview (Rolling)'!F$11, 'Monthly Detail'!169:169) -> 1165.2 | G37: =SUMIF('Monthly Detail'!$4:$4, '2024 Overview (Rolling)'!G$11, 'Monthly Detail'!169:169) -> -64.9 | H37: =SUMIF('Monthly Detail'!$4:$4, '2024 Overview (Rolling)'!H$11, 'Monthly Detail'!169:169) -> 337.61 | I37: =SUMIF('Monthly Detail'!$4:$4, '2024 Overview (Rolling)'!I$11, 'Monthly Detail'!169:169) -> 1543.28 | J37: =SUMIF('Monthly Detail'!$4:$4, '2024 Overview (Rolling)'!J$11, 'Monthly Detail'!169:169) -> 33.62 | ... N37: =SUMIF('Monthly Detail'!$4:$4, '2024 Overview (Rolling)'!N$11, 'Monthly Detail'!169:169) -> -3421.57

Sheet 2024 AOP
C10: January | D10: February | E10: March | F10: April | G10: May | H10: June | I10: July | J10: August | K10: September | L10: October | M10: November | N10: December | P10: Total
C11: 45322 | D11: 45351 | E11: 45382 | F11: 45412 | G11: 45443 | H11: 45473 | I11: 45504 | J11: 45535 | K11: 45565 | L11: 45596 | M11: 45626 | N11: 45657 | O11: 45322
B12: Service Income | C12: 3016.9792 | D12: 4844.1612 | E12: 3944.6332 | F12: 5914.9554 | G12: 10182.292 | H12: 6680.8712 | I12: 9818.9732 | J12: 9199.4885 | K12: 12430.846 | L12: 10145.197 | M12: 5993.1641 | N12: 4062.5 | P12: 86234.061
B13: Tips | C13: 49.5 | D13: 49.5 | E13: 49.5 | F13: 49.5 | G13: 49.5 | H13: 49.5 | I13: 49.5 | J13: 49.5 | K13: 49.5 | L13: 49.5 | M13: 49.5 | N13: 49.5 | P13: =+SUM(C13:N13) -> 594
B14: Total Income | C14: 3066.4792 | D14: 4893.6612 | E14: 3994.1332 | F14: 5964.4554 | G14: 10231.792 | H14: 6730.3712 | I14: 9868.4732 | J14: 9248.9885 | K14: 12480.346 | L14: 10194.697 | M14: 6042.6641 | N14: 4112 | P14: 86828.061
B15: # of Students | C15: 21 | D15: 33 | E15: 35 | F15: 33 | G15: 34 | H15: 34 | I15: 31 | J15: 32 | K15: 43 | L15: 38 | M15: 38 | N15: 38
B16: # of Sessions | C16: 28 | D16: 44.957723 | E16: 36.609377 | F16: 54.895556 | G16: 94.499879 | H16: 62.003873 | I16: 91.127991 | J16: 85.378673 | K16: 115.36828 | L16: 94.155612 | M16: 55.621396 | N16: 37.703277
B18: Gross Margin | C18: 3066.4792 | D18: 4893.6612 | E18: 3994.1332 | F18: 5964.4554 | G18: 10231.792 | H18: 6730.3712 | I18: 9868.4732 | J18: 9248.9885 | K18: 12480.346 | L18: 10194.697 | M18: 6042.6641 | N18: 4112 | P18: 86234.061
B19: GM % | C19: 1 | D19: 1 | E19: 1 | F19: 1 | G19: 1 | H19: 1 | I19: 1 | J19: 1 | K19: 1 | L19: 1 | M19: 1 | N19: 1 | P19: 1
B21: General & Admintrative Expenses | C21: 810.76067 | D21: 810.76067 | E21: 810.76067 | F21: 960.76067 | G21: 810.76067 | H21: 810.76067 | I21: 960.76067 | J21: 810.76067 | K21: 1846.502 | L21: 960.76067 | M21: 810.76067 | N21: 810.76067 | P21: 11214.869
B22: Operating Expenses | C22: 810.76067 | D22: 810.76067 | E22: 810.76067 | F22: 960.76067 | G22: 810.76067 | H22: 810.76067 | I22: 960.76067 | J22: 810.76067 | K22: 1846.502 | L22: 960.76067 | M22: 810.76067 | N22: 810.76067 | P22: 11214.869
B24: Net Operating Income (EBITDA) | C24: 2255.7185 | D24: 4082.9005 | E24: 3183.3725 | F24: 5003.6947 | G24: 9421.031 | H24: 5919.6105 | I24: 8907.7125 | J24: 8438.2278 | K24: 10633.844 | L24: 9233.9364 | M24: 5231.9034 | N24: 3301.2393 | P24: 75019.191
B25: EBITDA % | C25: 0.73560536 | D25: 0.83432432 | E25: 0.79701211 | F25: 0.83891896 | G25: 0.92076064 | H25: 0.87953701 | I25: 0.90264343 | J25: 0.91234061 | K25: 0.85204721 | L25: 0.90575878 | M25: 0.86582728 | N25: 0.80283058 | P25: 0.86994849
B27: Other Income / (Expense) | C27: 0 | D27: 0 | E27: 0 | F27: 0 | G27: 0 | H27: 0 | I27: 0 | J27: 0 | K27: 0 | L27: 0 | M27: 0 | N27: 0 | P27: 0
B28: Net Income | C28: 2255.7185 | D28: 4082.9005 | E28: 3183.3725 | F28: 5003.6947 | G28: 9421.031 | H28: 5919.6105 | I28: 8907.7125 | J28: 8438.2278 | K28: 10633.844 | L28: 9233.9364 | M28: 5231.9034 | N28: 3301.2393 | P28: 75019.191
B29: NI % | C29: 0.73560536 | D29: 0.83432432 | E29: 0.79701211 | F29: 0.83891896 | G29: 0.92076064 | H29: 0.87953701 | I29: 0.90264343 | J29: 0.91234061 | K29: 0.85204721 | L29: 0.90575878 | M29: 0.86582728 | N29: 0.80283058 | P29: 0.86994849
B31: Operating Cash | C31: 583.93524 | D31: 3316.6412 | E31: 5497.8005 | F31: 8902.7836 | G31: 15222.718 | H31: 20447.59 | I31: 26375.122 | J31: 28510.127 | K31: 33013.08 | L31: 34722.534 | M31: 36536.59 | N31: 38730.025
B32: Cash Inflow (Outflow) | C32: -413.08476 | D32: 2732.706 | E32: 2181.1593 | F32: 3404.9831 | G32: 6319.9345 | H32: 5224.8719 | I32: 5927.5321 | J32: 2135.0053 | K32: 4502.9521 | L32: 1709.4542 | M32: 1814.0563 | N32: 2193.4353

Sheet Quarterly Overview
C9: 45382 | D9: 45473 | F9: 45565 | H9: 45657
C10: Q1 2025 | D10: Q2 2025 | E10: Variance | F10: Q3 2025 | G10: Variance | H10: Q4 2025 | I10: Variance | K10: Total
C11: =+C10 -> Q1 2025 | D11: =+D10 -> Q2 2025 | F11: =+F10 -> Q3 2025 | H11: =+H10 -> Q4 2025 | J11: 45322
B12: Service Income | C12: =SUMIF('Monthly Detail'!$3:$3, 'Quarterly Overview'!C$11, 'Monthly Detail'!12:12) -> 22160 | D12: =SUMIF('Monthly Detail'!$3:$3, 'Quarterly Overview'!D$11, 'Monthly Detail'!12:12) -> 16611.25 | E12: =+D12-C12 -> -5548.75 | F12: =SUMIF('Monthly Detail'!$3:$3, 'Quarterly Overview'!F$11, 'Monthly Detail'!12:12) -> 63525 | G12: =+F12-D12 -> 46913.75 | H12: =SUMIF('Monthly Detail'!$3:$3, 'Quarterly Overview'!H$11, 'Monthly Detail'!12:12) -> 70029.574 | I12: =+H12-F12 -> 6504.5739 | K12: =SUM(C12,D12,F12,H12) -> 172325.82
B13: Tips | C13: =SUMIF('Monthly Detail'!$3:$3, 'Quarterly Overview'!C$11, 'Monthly Detail'!13:13) -> 219.99 | D13: =SUMIF('Monthly Detail'!$3:$3, 'Quarterly Overview'!D$11, 'Monthly Detail'!13:13) -> 105.5 | E13: =+D13-C13 -> -114.49 | F13: =SUMIF('Monthly Detail'!$3:$3, 'Quarterly Overview'!F$11, 'Monthly Detail'!13:13) -> 169.5 | G13: =+F13-D13 -> 64 | H13: =SUMIF('Monthly Detail'!$3:$3, 'Quarterly Overview'!H$11, 'Monthly Detail'!13:13) -> 159.51436 | I13: =+H13-F13 -> -9.9856368 | K13: =+SUM(H13,F13,D13,C13) -> 654.50436
B14: Total Income | C14: =SUM(C12:C13) -> 22379.99 | D14: =SUM(D12:D13) -> 16716.75 | E14: =+D14-C14 -> -5663.24 | F14: =SUM(F12:F13) -> 63694.5 | G14: =+F14-D14 -> 46977.75 | H14: =SUM(H12:H13) -> 70189.088 | I14: =+H14-F14 -> 6494.5882 | K14: =SUM(K12:K13) -> 172980.33
B15: Avg. # of Students | C15: =+AVERAGEIFS('Monthly Detail'!17:17,'Monthly Detail'!3:3,'Quarterly Overview'!C10) -> 25.333333 | D15: =+AVERAGEIFS('Monthly Detail'!17:17,'Monthly Detail'!3:3,'Quarterly Overview'!D10) -> 22.666667 | E15: =+D15-C15 -> -2.6666667 | F15: =+AVERAGEIFS('Monthly Detail'!17:17,'Monthly Detail'!3:3,'Quarterly Overview'!F10) -> 46.666667 | G15: =+F15-D15 -> 24 | H15: =+AVERAGEIFS('Monthly Detail'!17:17,'Monthly Detail'!3:3,'Quarterly Overview'!H10) -> 62.2 | I15: =+H15-F15 -> 15.533333
B17: Subcontractor Expenses | C17: =SUMIF('Monthly Detail'!$3:$3, 'Quarterly Overview'!C$11, 'Monthly Detail'!$63:$63) -> 450 | D17: =SUMIF('Monthly Detail'!$3:$3, 'Quarterly Overview'!D$11, 'Monthly Detail'!$63:$63) -> 270 | E17: =+D17-C17 -> -180 | F17: =SUMIF('Monthly Detail'!$3:$3, 'Quarterly Overview'!F$11, 'Monthly Detail'!$63:$63) -> 6343.24 | G17: =+F17-E17 -> 6523.24 | H17: =SUMIF('Monthly Detail'!$3:$3, 'Quarterly Overview'!H$11, 'Monthly Detail'!$63:$63) -> 7214.9542 | I17: =+H17-G17 -> 691.71423 | K17: =SUM(C17,D17,F17,H17) -> 14278.194
B18: Gross Margin | C18: =C14-C17 -> 21929.99 | D18: =D14-D17 -> 16446.75 | E18: =+D18-C18 -> -5483.24 | F18: =F14-F17 -> 57351.26 | G18: =+F18-D18 -> 40904.51 | H18: =H14-H17 -> 62974.134 | I18: =+H18-F18 -> 5622.874 | K18: =K14-K17 -> 158702.13
B19: GM % | C19: =C18/C14 -> 0.97989275 | D19: =D18/D14 -> 0.98384854 | E19: =+D19-C19 -> 0.0039557827 | F19: =F18/F14 -> 0.9004115 | G19: =+F19-D19 -> -0.08343704 | H19: =H18/H14 -> 0.8972069 | I19: =+H19-F19 -> -0.0032045993 | K19: =K18/K14 -> 0.9174577
B21: Sales & Marketing Expenses | C21: =SUMIF('Monthly Detail'!$3:$3, 'Quarterly Overview'!C$11, 'Monthly Detail'!$70:$70) -> 0 | D21: =SUMIF('Monthly Detail'!$3:$3, 'Quarterly Overview'!D$11, 'Monthly Detail'!$70:$70) -> 0 | E21: =+D21-C21 -> 0 | F21: =SUMIF('Monthly Detail'!$3:$3, 'Quarterly Overview'!F$11, 'Monthly Detail'!$70:$70) -> 0 | G21: =SUMIF('Monthly Detail'!$3:$3, 'Quarterly Overview'!G$11, 'Monthly Detail'!$70:$70) -> 0 | H21: =SUMIF('Monthly Detail'!$3:$3, 'Quarterly Overview'!H$11, 'Monthly Detail'!$70:$70) -> 0 | I21: =SUMIF('Monthly Detail'!$3:$3, 'Quarterly Overview'!I$11, 'Monthly Detail'!$70:$70) -> 0 | K21: =SUM(C21,D21,F21,H21) -> 0
B22: General & Admintrative Expenses | C22: =SUMIF('Monthly Detail'!$3:$3, 'Quarterly Overview'!C$11, 'Monthly Detail'!$93:$93) -> 18368.59 | D22: =SUMIF('Monthly Detail'!$3:$3, 'Quarterly Overview'!D$11, 'Monthly Detail'!$93:$93) -> 11611.73 | E22: =+D22-C22 -> -6756.86 | F22: =SUMIF('Monthly Detail'!$3:$3, 'Quarterly Overview'!F$11, 'Monthly Detail'!$93:$93) -> 40676.63 | G22: =+F22-D22 -> 29064.9 | H22: =SUMIF('Monthly Detail'!$3:$3, 'Quarterly Overview'!H$11, 'Monthly Detail'!$93:$93) -> 48106.07 | I22: =+H22-F22 -> 7429.4402 | K22: =SUM(C22,D22,F22,H22) -> 118763.02
B23: Operating Expenses | C23: =SUM(C21:C22) -> 18368.59 | D23: =SUM(D21:D22) -> 11611.73 | E23: =SUM(E21:E22) -> -6756.86 | F23: =SUM(F21:F22) -> 40676.63 | G23: =SUM(G21:G22) -> 29064.9 | H23: =SUM(H21:H22) -> 48106.07 | I23: =+H23-F23 -> 7429.4402 | K23: =SUM(K21:K22) -> 118763.02
B25: Net Operating Income (EBITDA) | C25: =C18-C23 -> 3561.4 | D25: =D18-D23 -> 4835.02 | E25: =+D25-C25 -> 1273.62 | F25: =F18-F23 -> 16674.63 | G25: =+F25-D25 -> 11839.61 | H25: =H18-H23 -> 14868.064 | I25: =+H25-F25 -> -1806.5662 | K25: =K18-K23 -> 39939.114
B26: EBITDA % | C26: =C25/C14 -> 0.15913323 | D26: =D25/D14 -> 0.28923206 | E26: =+D26-C26 -> 0.13009883 | F26: =F25/F14 -> 0.26179074 | G26: =+F26-D26 -> -0.027441322 | H26: =H25/H14 -> 0.21182871 | I26: =+H26-F26 -> -0.049962028 | K26: =K25/K14 -> 0.23088818
B28: Other Income / (Expense) | C28: =SUMIF('Monthly Detail'!$3:$3, 'Quarterly Overview'!C$11, 'Monthly Detail'!107:107) -> -2355.33 | D28: =SUMIF('Monthly Detail'!$3:$3, 'Quarterly Overview'!D$11, 'Monthly Detail'!107:107) -> -2219.81 | E28: =+D28-C28 -> 135.52 | F28: =SUMIF('Monthly Detail'!$3:$3, 'Quarterly Overview'!F$11, 'Monthly Detail'!107:107) -> -2228.93 | G28: =+F28-D28 -> -9.12 | H28: =SUMIF('Monthly Detail'!$3:$3, 'Quarterly Overview'!H$11, 'Monthly Detail'!107:107) -> -2442.23 | I28: =+H28-F28 -> -213.3 | K28: =SUM(C28,D28,F28,H28) -> -9246.3
B29: Net Income | C29: =C25+SUM(C28:C28) -> 1206.07 | D29: =D25+SUM(D28:D28) -> 2615.21 | E29: =+D29-C29 -> 1409.14 | F29: =F25+SUM(F28:F28) -> 14445.7 | G29: =+F29-D29 -> 11830.49 | H29: =H25+SUM(H28:H28) -> 12425.834 | I29: =+H29-F29 -> -2019.8662 | K29: =K25+SUM(K28:K28) -> 30692.814
B30: NI % | C30: =C29/C14 -> 0.053890551 | D30: =D29/D14 -> 0.15644249 | E30: =+D30-C30 -> 0.10255194 | F30: =F29/F14 -> 0.22679666 | G30: =+F30-D30 -> 0.070354172 | H30: =H29/H14 -> 0.1770337 | I30: =+H30-F30 -> -0.049762965 | K30: =K29/K14 -> 0.17743528
B32: Operating Cash | C32: =SUMIF('Monthly Detail'!$4:$4, 'Quarterly Overview'!C$9, 'Monthly Detail'!172:172) -> 177.79 | D32: =SUMIF('Monthly Detail'!$4:$4, 'Quarterly Overview'!D$9, 'Monthly Detail'!172:172) -> 1615.7 | F32: =SUMIF('Monthly Detail'!$4:$4, 'Quarterly Overview'!F$9, 'Monthly Detail'!172:172) -> 4237.52 | H32: =SUMIF('Monthly Detail'!$4:$4, 'Quarterly Overview'!H$9, 'Monthly Detail'!172:172) -> 292.83
B33: Cash Inflow (Outflow) | C33: =SUMIF('Monthly Detail'!$3:$3, 'Quarterly Overview'!C$10, 'Monthly Detail'!169:169) -> 692.36 | D33: =SUMIF('Monthly Detail'!$3:$3, 'Quarterly Overview'!D$10, 'Monthly Detail'!169:169) -> 74.31 | E33: =+D33-C33 -> -618.05 | F33: =SUMIF('Monthly Detail'!$3:$3, 'Quarterly Overview'!F$10, 'Monthly Detail'!169:169) -> 5073.7 | G33: =+F33-D33 -> 4999.39 | H33: =SUMIF('Monthly Detail'!$3:$3, 'Quarterly Overview'!H$10, 'Monthly Detail'!169:169) -> 20568.364 | I33: =+H33-F33 -> 15494.664
C37: Q1 | D37: Q2 | F37: Q3 | H37: Q4
B38: 2024 AOP Income | C38: =+SUM('2025 AOP'!C14:E14) -> 27893.466 | D38: =+SUM('2025 AOP'!F14:H14) -> 26421.692 | F38: =+SUM('2025 AOP'!I14:K14) -> 38914.06 | H38: =+SUM('2025 AOP'!L14:N14) -> 30767.431
B39: 2024 AOP Net Income | C39: =+AVERAGE('2025 AOP'!C28:E28) -> #DIV/0! | D39: =+SUM('2025 AOP'!F28:H28) -> 0 | F39: =+SUM('2025 AOP'!I28:K28) -> 0 | H39: =+SUM('2025 AOP'!L28:N28) -> 0
B40: 2024 AOP Avg. Students | C40: =+AVERAGE('2025 AOP'!C15:E15) -> 34.733333 | D40: =+AVERAGE('2025 AOP'!F15:H15) -> 31.666667 | F40: =+AVERAGE('2025 AOP'!I15:K15) -> 37.2 | H40: =+AVERAGE('2025 AOP'!L15:N15) -> 43.6

Sheet 2022 Overview
C10: =TEXT('Monthly Detail'!D4,"mmmm") -> January | D10: =TEXT('Monthly Detail'!E4,"mmmm") -> February | E10: =TEXT('Monthly Detail'!F4,"mmmm") -> March | F10: =TEXT('Monthly Detail'!G4,"mmmm") -> April | G10: =TEXT('Monthly Detail'!H4,"mmmm") -> May | H10: =TEXT('Monthly Detail'!I4,"mmmm") -> June | I10: =TEXT('Monthly Detail'!J4,"mmmm") -> July | J10: =TEXT('Monthly Detail'!K4,"mmmm") -> August | ... N10: =TEXT('Monthly Detail'!O4,"mmmm") -> December | P10: Total
C11: 44592 | D11: 44620 | E11: 44651 | F11: 44681 | G11: 44712 | H11: 44742 | I11: 44773 | J11: 44804 | K11: 44834 | L11: 44865 | M11: 44895 | N11: 44926
B12: Service Income | C12: =SUMIF('Monthly Detail'!$4:$4, '2022 Overview'!C$11, 'Monthly Detail'!12:12) -> 0 | D12: =SUMIF('Monthly Detail'!$4:$4, '2022 Overview'!D$11, 'Monthly Detail'!12:12) -> 0 | E12: =SUMIF('Monthly Detail'!$4:$4, '2022 Overview'!E$11, 'Monthly Detail'!12:12) -> 0 | F12: =SUMIF('Monthly Detail'!$4:$4, '2022 Overview'!F$11, 'Monthly Detail'!12:12) -> 0 | G12: =SUMIF('Monthly Detail'!$4:$4, '2022 Overview'!G$11, 'Monthly Detail'!12:12) -> 0 | H12: =SUMIF('Monthly Detail'!$4:$4, '2022 Overview'!H$11, 'Monthly Detail'!12:12) -> 0 | I12: =SUMIF('Monthly Detail'!$4:$4, '2022 Overview'!I$11, 'Monthly Detail'!12:12) -> 0 | J12: =SUMIF('Monthly Detail'!$4:$4, '2022 Overview'!J$11, 'Monthly Detail'!12:12) -> 375 | ... N12: =SUMIF('Monthly Detail'!$4:$4, '2022 Overview'!N$11, 'Monthly Detail'!12:12) -> 2032.5 | P12: =SUM(C12:O12) -> 9212.5
B13: Misc. | C13: =SUMIF('Monthly Detail'!$4:$4, '2022 Overview'!C$11, 'Monthly Detail'!13:13) -> 0 | D13: =SUMIF('Monthly Detail'!$4:$4, '2022 Overview'!D$11, 'Monthly Detail'!13:13) -> 0 | E13: =SUMIF('Monthly Detail'!$4:$4, '2022 Overview'!E$11, 'Monthly Detail'!13:13) -> 0 | F13: =SUMIF('Monthly Detail'!$4:$4, '2022 Overview'!F$11, 'Monthly Detail'!13:13) -> 0 | G13: =SUMIF('Monthly Detail'!$4:$4, '2022 Overview'!G$11, 'Monthly Detail'!13:13) -> 0 | H13: =SUMIF('Monthly Detail'!$4:$4, '2022 Overview'!H$11, 'Monthly Detail'!13:13) -> 0 | I13: =SUMIF('Monthly Detail'!$4:$4, '2022 Overview'!I$11, 'Monthly Detail'!13:13) -> 0 | J13: =SUMIF('Monthly Detail'!$4:$4, '2022 Overview'!J$11, 'Monthly Detail'!13:13) -> 0 | ... N13: =SUMIF('Monthly Detail'!$4:$4, '2022 Overview'!N$11, 'Monthly Detail'!13:13) -> 0
B14: Total Income | C14: 0.1 | D14: 0.1 | E14: 0.1 | F14: 0.1 | G14: 0.1 | H14: 0.1 | I14: 0.1 | J14: =SUM(J12:J13) -> 375 | K14: =SUM(K12:K13) -> 1075 | L14: =SUM(L12:L13) -> 3765 | M14: =SUM(M12:M13) -> 2090 | N14: =SUM(N12:N13) -> 2032.5 | P14: =SUM(P12:P12) -> 9212.5
B16: Gross Margin | C16: =C14 -> 0.1 | D16: =D14 -> 0.1 | E16: =E14 -> 0.1 | F16: =F14 -> 0.1 | G16: =G14 -> 0.1 | H16: =H14 -> 0.1 | I16: =I14 -> 0.1 | J16: =J14 -> 375 | ... N16: =N14 -> 2032.5 | P16: =P14 -> 9212.5
B17: GM % | C17: =C16/C14 -> 1 | D17: =D16/D14 -> 1 | E17: =E16/E14 -> 1 | F17: =F16/F14 -> 1 | G17: =G16/G14 -> 1 | H17: =H16/H14 -> 1 | I17: =I16/I14 -> 1 | J17: =J16/J14 -> 1 | ... N17: =N16/N14 -> 1 | P17: =P16/P14 -> 1
B19: General & Admintrative Expenses | C19: =SUMIF('Monthly Detail'!$4:$4, '2023 Overview'!C$11, 'Monthly Detail'!$93:$93) -> 235.13 | D19: =SUMIF('Monthly Detail'!$4:$4, '2023 Overview'!D$11, 'Monthly Detail'!$93:$93) -> 153.76 | E19: =SUMIF('Monthly Detail'!$4:$4, '2023 Overview'!E$11, 'Monthly Detail'!$93:$93) -> 105.36 | F19: =SUMIF('Monthly Detail'!$4:$4, '2023 Overview'!F$11, 'Monthly Detail'!$93:$93) -> 272.84 | G19: =SUMIF('Monthly Detail'!$4:$4, '2023 Overview'!G$11, 'Monthly Detail'!$93:$93) -> 551 | H19: =SUMIF('Monthly Detail'!$4:$4, '2023 Overview'!H$11, 'Monthly Detail'!$93:$93) -> 647.26 | I19: =SUMIF('Monthly Detail'!$4:$4, '2023 Overview'!I$11, 'Monthly Detail'!$93:$93) -> 432.76 | J19: =SUMIF('Monthly Detail'!$4:$4, '2023 Overview'!J$11, 'Monthly Detail'!$93:$93) -> 851.95 | ... N19: =SUMIF('Monthly Detail'!$4:$4, '2023 Overview'!N$11, 'Monthly Detail'!$93:$93) -> 797.47 | P19: =SUM(C19:O19) -> 7947.79
B20: Owner Guarenteed Payments | C20: =SUMIF('Monthly Detail'!$4:$4, '2022 Overview'!C$11, 'Monthly Detail'!50:50) -> 0 | D20: =SUMIF('Monthly Detail'!$4:$4, '2022 Overview'!D$11, 'Monthly Detail'!50:50) -> 0 | E20: =SUMIF('Monthly Detail'!$4:$4, '2022 Overview'!E$11, 'Monthly Detail'!50:50) -> 0 | F20: =SUMIF('Monthly Detail'!$4:$4, '2022 Overview'!F$11, 'Monthly Detail'!50:50) -> 0 | G20: =SUMIF('Monthly Detail'!$4:$4, '2022 Overview'!G$11, 'Monthly Detail'!50:50) -> 0 | H20: =SUMIF('Monthly Detail'!$4:$4, '2022 Overview'!H$11, 'Monthly Detail'!50:50) -> 0 | I20: =SUMIF('Monthly Detail'!$4:$4, '2022 Overview'!I$11, 'Monthly Detail'!50:50) -> 0 | J20: =SUMIF('Monthly Detail'!$4:$4, '2022 Overview'!J$11, 'Monthly Detail'!50:50) -> 0 | ... N20: =SUMIF('Monthly Detail'!$4:$4, '2022 Overview'!N$11, 'Monthly Detail'!50:50) -> 0 | P20: =SUM(C20:O20) -> 0
B21: Operating Expenses | C21: =SUM(C19:C20) -> 235.13 | D21: =SUM(D19:D20) -> 153.76 | E21: =SUM(E19:E20) -> 105.36 | F21: =SUM(F19:F20) -> 272.84 | G21: =SUM(G19:G20) -> 551 | H21: =SUM(H19:H20) -> 647.26 | I21: =SUM(I19:I20) -> 432.76 | J21: =SUM(J19:J20) -> 851.95 | ... N21: =SUM(N19:N20) -> 797.47 | P21: =SUM(P19:P20) -> 7947.79
B23: Net Operating Income (EBITDA) | C23: =C16-C21 -> -235.03 | D23: =D16-D21 -> -153.66 | E23: =E16-E21 -> -105.26 | F23: =F16-F21 -> -272.74 | G23: =G16-G21 -> -550.9 | H23: =H16-H21 -> -647.16 | I23: =I16-I21 -> -432.66 | J23: =J16-J21 -> -476.95 | ... N23: =N16-N21 -> 1235.03 | P23: =P16-P21 -> 1264.71
B24: EBITDA % | C24: =C23/C14 -> -2350.3 | D24: =D23/D14 -> -1536.6 | E24: =E23/E14 -> -1052.6 | F24: =F23/F14 -> -2727.4 | G24: =G23/G14 -> -5509 | H24: =H23/H14 -> -6471.6 | I24: =I23/I14 -> -4326.6 | J24: =J23/J14 -> -1.2718667 | ... N24: =N23/N14 -> 0.60764084 | P24: =P23/P14 -> 0.13728195
B26: Other Income / (Expense) | C26: =SUMIF('Monthly Detail'!$4:$4, '2022 Overview'!C$11, 'Monthly Detail'!86:86) -> 0 | D26: =SUMIF('Monthly Detail'!$4:$4, '2022 Overview'!D$11, 'Monthly Detail'!86:86) -> 0 | E26: =SUMIF('Monthly Detail'!$4:$4, '2022 Overview'!E$11, 'Monthly Detail'!86:86) -> 0 | F26: =SUMIF('Monthly Detail'!$4:$4, '2022 Overview'!F$11, 'Monthly Detail'!86:86) -> 0 | G26: =SUMIF('Monthly Detail'!$4:$4, '2022 Overview'!G$11, 'Monthly Detail'!86:86) -> 0 | H26: =SUMIF('Monthly Detail'!$4:$4, '2022 Overview'!H$11, 'Monthly Detail'!86:86) -> 0 | I26: =SUMIF('Monthly Detail'!$4:$4, '2022 Overview'!I$11, 'Monthly Detail'!86:86) -> 0 | J26: =SUMIF('Monthly Detail'!$4:$4, '2022 Overview'!J$11, 'Monthly Detail'!86:86) -> 0 | ... N26: =SUMIF('Monthly Detail'!$4:$4, '2022 Overview'!N$11, 'Monthly Detail'!86:86) -> 75 | P26: =SUM(C26:O26) -> 429.6
B27: Net Income | C27: =C23+SUM(C26:C26) -> -235.03 | D27: =D23+SUM(D26:D26) -> -153.66 | E27: =E23+SUM(E26:E26) -> -105.26 | F27: =F23+SUM(F26:F26) -> -272.74 | G27: =G23+SUM(G26:G26) -> -550.9 | H27: =H23+SUM(H26:H26) -> -647.16 | I27: =I23+SUM(I26:I26) -> -432.66 | J27: =J23+SUM(J26:J26) -> -476.95 | ... N27: =N23+SUM(N26:N26) -> 1310.03 | P27: =P23+SUM(P26:P26) -> 1694.31
B28: NI % | C28: =C27/C14 -> -2350.3 | D28: =D27/D14 -> -1536.6 | E28: =E27/E14 -> -1052.6 | F28: =F27/F14 -> -2727.4 | G28: =G27/G14 -> -5509 | H28: =H27/H14 -> -6471.6 | I28: =I27/I14 -> -4326.6 | J28: =J27/J14 -> -1.2718667 | ... N28: =N27/N14 -> 0.64454121 | P28: =P27/P14 -> 0.18391425
B30: Operating Cash | C30: =SUMIF('Monthly Detail'!$4:$4, '2022 Overview'!C$11, 'Monthly Detail'!172:172) -> 0 | D30: =SUMIF('Monthly Detail'!$4:$4, '2022 Overview'!D$11, 'Monthly Detail'!172:172) -> 0 | E30: =SUMIF('Monthly Detail'!$4:$4, '2022 Overview'!E$11, 'Monthly Detail'!172:172) -> 0 | F30: =SUMIF('Monthly Detail'!$4:$4, '2022 Overview'!F$11, 'Monthly Detail'!172:172) -> 0 | G30: =SUMIF('Monthly Detail'!$4:$4, '2022 Overview'!G$11, 'Monthly Detail'!172:172) -> 0 | H30: =SUMIF('Monthly Detail'!$4:$4, '2022 Overview'!H$11, 'Monthly Detail'!172:172) -> 0 | I30: =SUMIF('Monthly Detail'!$4:$4, '2022 Overview'!I$11, 'Monthly Detail'!172:172) -> 0 | J30: =SUMIF('Monthly Detail'!$4:$4, '2022 Overview'!J$11, 'Monthly Detail'!172:172) -> 255 | ... N30: =SUMIF('Monthly Detail'!$4:$4, '2022 Overview'!N$11, 'Monthly Detail'!172:172) -> -55.9
B31: Cash Inflow (Outflow) | C31: =SUMIF('Monthly Detail'!$4:$4, '2022 Overview'!C$11, 'Monthly Detail'!158:158) -> 0 | D31: =D30-C30 -> 0 | E31: =E30-D30 -> 0 | F31: =F30-E30 -> 0 | G31: =G30-F30 -> 0 | H31: =H30-G30 -> 0 | I31: =I30-H30 -> 0 | J31: =J30-I30 -> 255 | K31: =K30-J30 -> 223 | ... N31: =N30-M30 -> -918.3

Sheet 2

Sheet Monthly Detail
D1: =YEAR(D4) -> 2022 | E1: =YEAR(E4) -> 2022 | F1: =YEAR(F4) -> 2022 | G1: =YEAR(G4) -> 2022 | H1: =YEAR(H4) -> 2022 | I1: =YEAR(I4) -> 2022 | J1: =YEAR(J4) -> 2022 | K1: =YEAR(K4) -> 2022 | ... DG1: =YEAR(DG4) -> 2030
G2: Peak | H2: Peak | I2: Shoulder | J2: Shoulder | K2: Trough | L2: Shoulder | M2: Shoulder | N2: Trough | O2: Shoulder | P2: Shoulder | Q2: Peak | R2: Shoulder | S2: Shoulder | T2: Peak | U2: Shoulder | V2: Peak | W2: Peak | X2: Peak | Y2: Shoulder | Z2: Trough | AA2: Trough | AB2: =+P2 -> Shoulder | AC2: =+Q2 -> Peak | AD2: =+R2 -> Shoulder | AE2: =+S2 -> Shoulder | AF2: =+T2 -> Peak | AG2: =+U2 -> Shoulder | AH2: =+V2 -> Peak | AI2: =+W2 -> Peak | ... DG2: =+CU2 -> Trough
D3: =+"Q1 "&D1 -> Q1 2022 | E3: =+"Q1 "&E1 -> Q1 2022 | F3: =+"Q1 "&F1 -> Q1 2022 | G3: =+"Q2 "&G1 -> Q2 2022 | H3: =+"Q2 "&H1 -> Q2 2022 | I3: =+"Q2 "&I1 -> Q2 2022 | J3: =+"Q3 "&J1 -> Q3 2022 | K3: =+"Q3 "&K1 -> Q3 2022 | L3: =+"Q3 "&L1 -> Q3 2022 | M3: =+"Q4 "&M1 -> Q4 2022 | N3: =+"Q4 "&N1 -> Q4 2022 | O3: =+"Q4 "&O1 -> Q4 2022 | P3: =+"Q1 "&P1 -> Q1 2023 | Q3: =+"Q1 "&Q1 -> Q1 2023 | R3: =+"Q1 "&R1 -> Q1 2023 | S3: =+"Q2 "&S1 -> Q2 2023 | T3: =+"Q2 "&T1 -> Q2 2023 | U3: =+"Q2 "&U1 -> Q2 2023 | V3: =+"Q3 "&V1 -> Q3 2023 | W3: =+"Q3 "&W1 -> Q3 2023 | X3: =+"Q3 "&X1 -> Q3 2023 | Y3: =+"Q4 "&Y1 -> Q4 2023 | Z3: =+"Q4 "&Z1 -> Q4 2023 | AA3: =+"Q4 "&AA1 -> Q4 2023 | AB3: =+"Q1 "&AB1 -> Q1 2024 | AC3: =+"Q1 "&AC1 -> Q1 2024 | AD3: =+"Q1 "&AD1 -> Q1 2024 | AE3: =+"Q2 "&AE1 -> Q2 2024 | AF3: =+"Q2 "&AF1 -> Q2 2024 | AG3: =+"Q2 "&AG1 -> Q2 2024 | AH3: =+"Q3 "&AH1 -> Q3 2024 | AI3: =+"Q3 "&AI1 -> Q3 2024 | AJ3: =+"Q3 "&AJ1 -> Q3 2024 | AK3: =+"Q4 "&AK1 -> Q4 2024 | AL3: =+"Q4 "&AL1 -> Q4 2024 | AM3: =+"Q4 "&AM1 -> Q4 2024 | AN3: =+"Q1 "&AN1 -> Q1 2025 | AO3: =+"Q1 "&AO1 -> Q1 2025 | AP3: =+"Q1 "&AP1 -> Q1 2025 | AQ3: =+"Q2 "&AQ1 -> Q2 2025 | AR3: =+"Q2 "&AR1 -> Q2 2025 | AS3: =+"Q2 "&AS1 -> Q2 2025 | AT3: =+"Q3 "&AT1 -> Q3 2025 | AU3: =+"Q3 "&AU1 -> Q3 2025 | AV3: =+"Q3 "&AV1 -> Q3 2025 | AW3: =+"Q4 "&AW1 -> Q4 2025 | AX3: =+"Q4 "&AX1 -> Q4 2025 | AY3: =+"Q4 "&AY1 -> Q4 2025 | AZ3: =+"Q1 "&AZ1 -> Q1 2026 | BA3: =+"Q1 "&BA1 -> Q1 2026 | BB3: =+"Q1 "&BB1 -> Q1 2026 | BC3: =+"Q2 "&BC1 -> Q2 2026 | BD3: =+"Q2 "&BD1 -> Q2 2026 | BE3: =+"Q2 "&BE1 -> Q2 2026 | BF3: =+"Q3 "&BF1 -> Q3 2026 | BG3: =+"Q3 "&BG1 -> Q3 2026 | BH3: =+"Q3 "&BH1 -> Q3 2026 | BI3: =+"Q4 "&BI1 -> Q4 2026 | BJ3: =+"Q4 "&BJ1 -> Q4 2026 | BK3: =+"Q4 "&BK1 -> Q4 2026 | BL3: =+"Q1 "&BL1 -> Q1 2027 | BM3: =+"Q1 "&BM1 -> Q1 2027 | BN3: =+"Q1 "&BN1 -> Q1 2027 | BO3: =+"Q2 "&BO1 -> Q2 2027 | BP3: =+"Q2 "&BP1 -> Q2 2027 | BQ3: =+"Q2 "&BQ1 -> Q2 2027 | BR3: =+"Q3 "&BR1 -> Q3 2027 | BS3: =+"Q3 "&BS1 -> Q3 2027 | BT3: =+"Q3 "&BT1 -> Q3 2027 | BU3: =+"Q4 "&BU1 -> Q4 2027 | BV3: =+"Q4 "&BV1 -> Q4 2027 | BW3: =+"Q4 "&BW1 -> Q4 2027 | BX3: =+"Q1 "&BX1 -> Q1 2028 | BY3: =+"Q1 "&BY1 -> Q1 2028 | BZ3: =+"Q1 "&BZ1 -> Q1 2028 | CA3: =+"Q2 "&CA1 -> Q2 2028 | CB3: =+"Q2 "&CB1 -> Q2 2028 | CC3: =+"Q2 "&CC1 -> Q2 2028 | CD3: =+"Q3 "&CD1 -> Q3 2028 | CE3: =+"Q3 "&CE1 -> Q3 2028 | CF3: =+"Q3 "&CF1 -> Q3 2028 | CG3: =+"Q4 "&CG1 -> Q4 2028 | CH3: =+"Q4 "&CH1 -> Q4 2028 | CI3: =+"Q4 "&CI1 -> Q4 2028 | CJ3: =+"Q1 "&CJ1 -> Q1 2029 | CK3: =+"Q1 "&CK1 -> Q1 2029 | CL3: =+"Q1 "&CL1 -> Q1 2029 | CM3: =+"Q2 "&CM1 -> Q2 2029 | CN3: =+"Q2 "&CN1 -> Q2 2029 | CO3: =+"Q2 "&CO1 -> Q2 2029 | CP3: =+"Q3 "&CP1 -> Q3 2029 | CQ3: =+"Q3 "&CQ1 -> Q3 2029 | CR3: =+"Q3 "&CR1 -> Q3 2029 | CS3: =+"Q4 "&CS1 -> Q4 2029 | CT3: =+"Q4 "&CT1 -> Q4 2029 | CU3: =+"Q4 "&CU1 -> Q4 2029 | CV3: =+"Q1 "&CV1 -> Q1 2030 | CW3: =+"Q1 "&CW1 -> Q1 2030 | CX3: =+"Q1 "&CX1 -> Q1 2030 | CY3: =+"Q2 "&CY1 -> Q2 2030 | CZ3: =+"Q2 "&CZ1 -> Q2 2030 | DA3: =+"Q2 "&DA1 -> Q2 2030 | DB3: =+"Q3 "&DB1 -> Q3 2030 | DC3: =+"Q3 "&DC1 -> Q3 2030 | DD3: =+"Q3 "&DD1 -> Q3 2030 | DE3: =+"Q4 "&DE1 -> Q4 2030 | DF3: =+"Q4 "&DF1 -> Q4 2030 | DG3: =+"Q4 "&DG1 -> Q4 2030
D4: 44592 | E4: 44620 | F4: 44651 | G4: 44681 | H4: 44712 | I4: 44742 | J4: 44773 | K4: 44804 | L4: 44834 | M4: 44865 | N4: 44895 | O4: 44926 | P4: 44957 | Q4: 44985 | R4: 45016 | S4: 45046 | T4: 45077 | U4: 45107 | V4: 45138 | W4: 45169 | X4: 45199 | Y4: 45230 | Z4: 45260 | AA4: 45291 | AB4: 45322 | AC4: 45351 | AD4: 45382 | AE4: 45412 | AF4: 45443 | AG4: 45473 | AH4: 45504 | AI4: 45535 | AJ4: 45565 | AK4: 45596 | AL4: 45626 | AM4: 45657 | AN4: 45688 | AO4: =EOMONTH(AN4,1) -> 45716 | AP4: =EOMONTH(AO4,1) -> 45747 | AQ4: =EOMONTH(AP4,1) -> 45777 | AR4: =EOMONTH(AQ4,1) -> 45808 | AS4: =EOMONTH(AR4,1) -> 45838 | AT4: =EOMONTH(AS4,1) -> 45869 | AU4: =EOMONTH(AT4,1) -> 45900 | AV4: =EOMONTH(AU4,1) -> 45930 | ... DG4: =EOMONTH(DF4,1) -> 47848
B5: Income
B6: 50000 Service Income | D6: =0 -> 0 | E6: =0 -> 0 | F6: =0 -> 0 | G6: =0 -> 0 | H6: =0 -> 0 | I6: =0 -> 0 | J6: =0 -> 0 | K6: 0 | L6: 0 | M6: 0
B7: 50100 Tutoring Sessions | D7: =0 -> 0 | E7: =0 -> 0 | F7: =0 -> 0 | G7: =0 -> 0 | H7: =0 -> 0 | I7: =0 -> 0 | J7: 0 | K7: 50 | L7: 350 | M7: 2640 | N7: 1865 | O7: 1932.5 | P7: 1360 | Q7: 1225 | R7: 1177.5 | S7: 1875 | T7: 2446.25 | U7: 1963.75 | V7: 2220 | W7: 5316.66 | X7: 4203.34 | Y7: 3105 | Z7: 2692.5 | AA7: 1350 | AB7: 1342.5 | AC7: 2167.5 | AD7: 1847.5 | AE7: 2035 | AF7: 1725 | AG7: 1285 | AH7: 1122.52 | AI7: 506.26 | AJ7: 326.25 | AK7: 135 | AL7: 727.5 | AM7: 585 | AN7: 371.25 | AO7: 1108.75 | AP7: 1537.5 | AQ7: 435 | AR7: 281.25 | AT7: 168.75 | AU7: 843.75 | AV7: =1443.75 -> 1443.75 | AW7: =1871.26 -> 1871.26 | AX7: =+(AX34*AX28)+(AX32*AX38) -> 1001.1962 | AY7: =+(AY34*AY28)+(AY32*AY38) -> 1660.778 | AZ7: =+(AZ34*AZ28)+(AZ32*AZ38) -> 1139.3908 | BA7: =+(BA34*BA28)+(BA32*BA38) -> 2460.6214 | BB7: =+(BB34*BB28)+(BB32*BB38) -> 4002.625 | BC7: =+(BC34*BC28)+(BC32*BC38) -> 1028.113 | BD7: =+(BD34*BD28)+(BD32*BD38) -> 737.74432 | BE7: =+(BE34*BE28)+(BE32*BE38) -> 0 | ... DG7: =+(DG34*DG28)+(DG32*DG38) -> 7514.1519
B8: 50200 SAT/ACT Prep | D8: =0 -> 0 | E8: =0 -> 0 | F8: =0 -> 0 | G8: =0 -> 0 | H8: =0 -> 0 | I8: =0 -> 0 | J8: 0 | K8: 175 | L8: 50 | M8: 325 | N8: 225 | O8: 0 | V8: 150 | W8: 140 | X8: 1827.5 | Y8: 1620 | Z8: 1070 | AA8: 700 | AB8: 1110 | AC8: 2115 | AD8: 1470 | AE8: 1935 | AF8: 3645 | AG8: 1305.01 | AH8: 4406.25 | AI8: 8085 | AJ8: 1530 | AK8: 2085 | AL8: 956.25 | AM8: 1706.25 | AN8: 3195 | AO8: 4511.25 | AP8: 5467.5 | AQ8: 2733.75 | AR8: 4901.25 | AS8: 2047.5 | AT8: 5011.25 | AU8: 5946.25 | AV8: =8113.75 -> 8113.75 | AW8: =4536.25 -> 4536.25 | AX8: =+AX35*AX29 -> 1401.6746 | AY8: =+AY35*AY29 -> 5189.9314 | AZ8: =+AZ35*AZ29 -> 8010.0027 | BA8: =+BA35*BA29 -> 10617.75 | BB8: =+BB35*BB29 -> 14497.312 | BC8: =+BC35*BC29 -> 6558.6522 | BD8: =+BD35*BD29 -> 13131.849 | BE8: =+BE35*BE29 -> 4034.4857 | ... DG8: =+DG35*DG29 -> 23481.725
B9: 50300 Resume Review | AI9: 851.25 | AJ9: 997.5 | AK9: 1592.5 | AL9: 150 | AO9: 562.5 | AR9: 450 | AS9: 637.5 | AT9: 1212.5 | AU9: 1750 | AV9: =2272.5 -> 2272.5 | AW9: =2393.75 -> 2393.75 | AX9: =+AX36*AX30 -> 315.37679 | AY9: =+AY36*AY30 -> 0 | AZ9: =+AZ36*AZ30 -> 0 | BA9: =+BA36*BA30 -> 1137.6161 | BB9: =+BB36*BB30 -> 0 | BC9: =+BC36*BC30 -> 0 | BD9: =+BD36*BD30 -> 796.76386 | BE9: =+BE36*BE30 -> 1452.4149 | ... DG9: =+DG36*DG30 -> 0
B10: 50400 College Essay Review | D10: =0 -> 0 | E10: =0 -> 0 | F10: =0 -> 0 | G10: =0 -> 0 | H10: =0 -> 0 | I10: =0 -> 0 | J10: 0 | K10: 150 | L10: 675 | M10: 675 | N10: 0 | O10: 100 | P10: 150 | S10: 44.91 | U10: 75 | V10: 415 | W10: 1595 | X10: 2690 | Y10: 3315 | Z10: 1065 | AA10: 45 | AB10: 195 | AC10: 75 | AD10: 150 | AE10: 30 | AG10: 1706.25 | AH10: 3502.5 | AI10: 4631.25 | AJ10: 7043.75 | AK10: 13573.75 | AL10: 7730 | AM10: 2868.75 | AN10: 2911.25 | AO10: 1870 | AP10: 625 | AQ10: 587.5 | AR10: 400 | AS10: 4137.5 | AT10: 8462.5 | AU10: 11872.5 | AV10: =16427.5 -> 16427.5 | AW10: =30345 -> 30345 | AX10: =+AX37*AX31 -> 10010.024 | AY10: =+AY37*AY31 -> 11116.833 | AZ10: =+AZ37*AZ31 -> 12182.058 | BA10: =+BA37*BA31 -> 5839.7625 | BB10: =+BB37*BB31 -> 2020.8375 | BC10: =+BC37*BC31 -> 1515.5804 | BD10: =+BD37*BD31 -> 1062.3518 | BE10: =+BE37*BE31 -> 7922.2629 | ... DG10: =+DG37*DG31 -> 50297.854
B11: 50500 Interview Prep | AB11: 237.5 | AR11: 0 | AS11: 0 | AT11: 0 | AU11: 0 | AV11: 0 | AW11: =187.5 -> 187.5
B12: Total 50000 Service Income | D12: =(((D6)+(D7))+(D8))+(D10) -> 0 | E12: =(((E6)+(E7))+(E8))+(E10) -> 0 | F12: =(((F6)+(F7))+(F8))+(F10) -> 0 | G12: =(((G6)+(G7))+(G8))+(G10) -> 0 | H12: =(((H6)+(H7))+(H8))+(H10) -> 0 | I12: =(((I6)+(I7))+(I8))+(I10) -> 0 | J12: =(((J6)+(J7))+(J8))+(J10) -> 0 | K12: =SUM(K7:K10) -> 375 | L12: =SUM(L7:L10) -> 1075 | M12: =SUM(M7:M10) -> 3640 | N12: =SUM(N7:N10) -> 2090 | O12: =SUM(O7:O10) -> 2032.5 | P12: =SUM(P7:P10) -> 1510 | Q12: =SUM(Q7:Q10) -> 1225 | R12: =SUM(R7:R10) -> 1177.5 | ... Z12: =SUM(Z7:Z10) -> 4827.5 | AA12: =SUM(AA7:AA11) -> 2095 | AB12: =SUM(AB7:AB11) -> 2885 | AC12: =SUM(AC7:AC11) -> 4357.5 | AD12: =SUM(AD7:AD11) -> 3467.5 | AE12: =SUM(AE7:AE11) -> 4000 | AF12: =SUM(AF7:AF11) -> 5370 | AG12: =SUM(AG7:AG11) -> 4296.26 | AH12: =SUM(AH7:AH11) -> 9031.27 | ... DG12: =SUM(DG7:DG11) -> 81293.731
B13: 70000 Tips/Miscellaneous | D13: =0 -> 0 | E13: =0 -> 0 | F13: =0 -> 0 | G13: =0 -> 0 | H13: =0 -> 0 | I13: =0 -> 0 | J13: =0 -> 0 | K13: 0 | L13: 0 | M13: 125 | N13: 0 | O13: 0 | P13: 35.99 | Q13: 30.75 | R13: 29.25 | S13: 37.5 | T13: 40.68 | U13: 4.68 | V13: 50.5 | W13: 27 | X13: 35.25 | Y13: 156.37 | Z13: 110.62 | AA13: 49.5 | AB13: 117 | AD13: 12 | AE13: 18 | AF13: 50.08 | AG13: 12 | AH13: 29.62 | AI13: 37.5 | AK13: 19.5 | AL13: 9.75 | AM13: 34 | AN13: 108 | AO13: 59.62 | AP13: 52.37 | AR13: 12 | AS13: 93.5 | AT13: 75 | AU13: 44.5 | AV13: 50 | AW13: 29.37 | AX13: =+AX15*AX12 -> 53.96543 | AY13: =+AY15*AY12 -> 76.178933 | AZ13: =+AZ15*AZ12 -> 90.441261 | BA13: =+BA15*BA12 -> 85.032533 | BB13: =+BB15*BB12 -> 87.00415 | BC13: =+BC15*BC12 -> 38.5922 | BD13: =+BD15*BD12 -> 66.686709 | BE13: =+BE15*BE12 -> 56.852281 | ... DG13: =+DG15*DG12 -> 344.66983
B14: Total Income | C14: Total Revenue | D14: =(D12)+(D13) -> 0 | E14: =(E12)+(E13) -> 0 | F14: =(F12)+(F13) -> 0 | G14: =(G12)+(G13) -> 0 | H14: =(H12)+(H13) -> 0 | I14: =(I12)+(I13) -> 0 | J14: =(J12)+(J13) -> 0 | K14: =K13+K12 -> 375 | L14: =L13+L12 -> 1075 | M14: =M13+M12 -> 3765 | N14: =N13+N12 -> 2090 | O14: =O13+O12 -> 2032.5 | P14: =P13+P12 -> 1545.99 | Q14: =Q13+Q12 -> 1255.75 | R14: =R13+R12 -> 1206.75 | ... DG14: =DG13+DG12 -> 81638.401
C15: Tips as a % of Revenue | K15: =+K13/K12 -> 0 | L15: =+L13/L12 -> 0 | M15: =+M13/M12 -> 0.034340659 | N15: =+N13/N12 -> 0 | O15: =+O13/O12 -> 0 | P15: =+P13/P12 -> 0.023834437 | Q15: =+Q13/Q12 -> 0.025102041 | R15: =+R13/R12 -> 0.024840764 | ... AW15: =+AW13/AW12 -> 0.00074668682 | AX15: =+AVERAGE(AR15:AW15) -> 0.0042398082 | AY15: =+AX15 -> 0.0042398082 | AZ15: =+AY15 -> 0.0042398082 | BA15: =+AZ15 -> 0.0042398082 | BB15: =+BA15 -> 0.0042398082 | BC15: =+BB15 -> 0.0042398082 | BD15: =+BC15 -> 0.0042398082 | BE15: =+BD15 -> 0.0042398082 | BF15: =+BE15 -> 0.0042398082 | ... DG15: =+DF15 -> 0.0042398082
C17: # of Students | E17: 12 | F17: 8 | G17: 7 | H17: 10 | I17: 13 | J17: 11 | K17: 5 | L17: 9 | M17: 17 | N17: 11 | O17: 7 | P17: 12 | Q17: 10 | R17: 10 | S17: 7 | T17: 9 | U17: 13 | V17: 8 | W17: 19 | X17: 29 | Y17: 32 | Z17: 32 | AA17: 19 | AB17: 16 | AC17: 15 | AD17: 20 | AE17: 17 | AF17: 20 | AG17: 24 | AH17: 30 | AI17: 38 | AJ17: 42 | AK17: 48 | AL17: 44 | AM17: 23 | AN17: 24 | AO17: 28 | AP17: 24 | AQ17: 23 | AR17: 20 | AS17: 25 | AT17: 35 | AU17: 48 | AV17: 57 | AW17: 67 | AX17: =+AW17+AX19 -> 62 | AY17: =+AX17+AY19 -> 57.6 | AZ17: =+AY17+AZ19 -> 57.32 | BA17: =+AZ17+BA19 -> 62.92 | BB17: =+BA17+BB19 -> 59.64 | BC17: =+BB17+BC19 -> 54.36 | BD17: =+BC17+BD19 -> 54.96 | BE17: =+BD17+BE19 -> 46.68 | ... DG17: =+DF17+DG19 -> 248.76397
C18: # of Recurring Students | AO18: 18 | AP18: 21 | AQ18: 19 | AR18: 19 | AS18: 19 | AT18: 19 | AU18: 19 | AV18: 19 | AW18: 51
C19: Net New Students | E19: =E17-D17 -> 12 | F19: =F17-E17 -> -4 | G19: =G17-F17 -> -1 | H19: =H17-G17 -> 3 | I19: =I17-H17 -> 3 | J19: =J17-I17 -> -2 | K19: =K17-J17 -> -6 | L19: =L17-K17 -> 4 | ... AW19: =AW17-AV17 -> 10 | AX19: =+AX20+AX21 -> -5 | AY19: =+AY20+AY21 -> -4.4 | AZ19: =+AZ20+AZ21 -> -0.28 | BA19: =+BA20+BA21 -> 5.6 | BB19: =+BB20+BB21 -> -3.28 | BC19: =+BC20+BC21 -> -5.28 | BD19: =+BD20+BD21 -> 0.6 | BE19: =+BE20+BE21 -> -8.28 | ... DG19: =+DG20+DG21 -> -7.881856
C20: Additions | F20: =+IF(F17>E17,F17-E17, 0) -> 0 | G20: =+IF(G17>F17,G17-F17, 0) -> 0 | H20: =+IF(H17>G17,H17-G17, 0) -> 3 | I20: =+IF(I17>H17,I17-H17, 0) -> 3 | J20: =+IF(J17>I17,J17-I17, 0) -> 0 | K20: =+IF(K17>J17,K17-J17, 0) -> 0 | L20: =+IF(L17>K17,L17-K17, 0) -> 4 | M20: =+IF(M17>L17,M17-L17, 0) -> 8 | ... P20: =+IF(P17>O17,P17-O17, 0) -> 5 | Q20: 2 | R20: 2 | S20: 3 | T20: 6 | U20: 11 | V20: 4 | W20: 12 | X20: 13 | Y20: 8 | Z20: 14 | AA20: 5 | AB20: 4 | AC20: 5 | AD20: 7 | AE20: 5 | AF20: 6 | AG20: 15 | AH20: 7 | AI20: 10 | AJ20: 10 | AK20: 9 | AL20: 6 | AM20: 5 | AN20: 5 | AO20: 11 | AP20: 4 | AQ20: 5 | AR20: 3 | AS20: 3 | AT20: 12 | AU20: 15 | AV20: 15 | AW20: 16 | AX20: =IF(AX2="Trough",INDEX($H$53:$H$55,MATCH(AX2,$E$53:$E$55,0)),IF(AX2="Shoulder",INDEX($H$53:$H$55,MATCH(AX2,$E$53:$E$55,0)),INDEX($H$53:$H$55,MATCH(AX2,$E$53:$E$55,0)))) -> 4 | AY20: =IF(AY2="Trough",INDEX($I$53:$I$55,MATCH(AY2,$E$53:$E$55,0)),IF(AY2="Shoulder",INDEX($I$53:$I$55,MATCH(AY2,$E$53:$E$55,0)),INDEX($I$53:$I$55,MATCH(AY2,$E$53:$E$55,0)))) -> 5.6 | AZ20: =IF(AZ2="Trough",INDEX($J$53:$J$55,MATCH(AZ2,$E$53:$E$55,0)),IF(AZ2="Shoulder",INDEX($J$53:$J$55,MATCH(AZ2,$E$53:$E$55,0)),INDEX($J$53:$J$55,MATCH(AZ2,$E$53:$E$55,0)))) -> 13.72 | BA20: =IF(BA2="Trough",INDEX($J$53:$J$55,MATCH(BA2,$E$53:$E$55,0)),IF(BA2="Shoulder",INDEX($J$53:$J$55,MATCH(BA2,$E$53:$E$55,0)),INDEX($J$53:$J$55,MATCH(BA2,$E$53:$E$55,0)))) -> 19.6 | BB20: =IF(BB2="Trough",INDEX($J$53:$J$55,MATCH(BB2,$E$53:$E$55,0)),IF(BB2="Shoulder",INDEX($J$53:$J$55,MATCH(BB2,$E$53:$E$55,0)),INDEX($J$53:$J$55,MATCH(BB2,$E$53:$E$55,0)))) -> 13.72 | BC20: =IF(BC2="Trough",INDEX($J$53:$J$55,MATCH(BC2,$E$53:$E$55,0)),IF(BC2="Shoulder",INDEX($J$53:$J$55,MATCH(BC2,$E$53:$E$55,0)),INDEX($J$53:$J$55,MATCH(BC2,$E$53:$E$55,0)))) -> 13.72 | BD20: =IF(BD2="Trough",INDEX($J$53:$J$55,MATCH(BD2,$E$53:$E$55,0)),IF(BD2="Shoulder",INDEX($J$53:$J$55,MATCH(BD2,$E$53:$E$55,0)),INDEX($J$53:$J$55,MATCH(BD2,$E$53:$E$55,0)))) -> 19.6 | BE20: =IF(BE2="Trough",INDEX($J$53:$J$55,MATCH(BE2,$E$53:$E$55,0)),IF(BE2="Shoulder",INDEX($J$53:$J$55,MATCH(BE2,$E$53:$E$55,0)),INDEX($J$53:$J$55,MATCH(BE2,$E$53:$E$55,0)))) -> 13.72 | BF20: =IF(BF2="Trough",INDEX($J$53:$J$55,MATCH(BF2,$E$53:$E$55,0)),IF(BF2="Shoulder",INDEX($J$53:$J$55,MATCH(BF2,$E$53:$E$55,0)),INDEX($J$53:$J$55,MATCH(BF2,$E$53:$E$55,0)))) -> 19.6 | BG20: =IF(BG2="Trough",INDEX($J$53:$J$55,MATCH(BG2,$E$53:$E$55,0)),IF(BG2="Shoulder",INDEX($J$53:$J$55,MATCH(BG2,$E$53:$E$55,0)),INDEX($J$53:$J$55,MATCH(BG2,$E$53:$E$55,0)))) -> 19.6 | ... BK20: =IF(BK2="Trough",INDEX($J$53:$J$55,MATCH(BK2,$E$53:$E$55,0)),IF(BK2="Shoulder",INDEX($J$53:$J$55,MATCH(BK2,$E$53:$E$55,0)),INDEX($J$53:$J$55,MATCH(BK2,$E$53:$E$55,0)))) -> 7.84 | BL20: =IF(BL2="Trough",INDEX($K$53:$K$55,MATCH(BL2,$E$53:$E$55,0)),IF(BL2="Shoulder",INDEX($K$53:$K$55,MATCH(BL2,$E$53:$E$55,0)),INDEX($K$53:$K$55,MATCH(BL2,$E$53:$E$55,0)))) -> 19.208 | BM20: =IF(BM2="Trough",INDEX($K$53:$K$55,MATCH(BM2,$E$53:$E$55,0)),IF(BM2="Shoulder",INDEX($K$53:$K$55,MATCH(BM2,$E$53:$E$55,0)),INDEX($K$53:$K$55,MATCH(BM2,$E$53:$E$55,0)))) -> 27.44 | BN20: =IF(BN2="Trough",INDEX($K$53:$K$55,MATCH(BN2,$E$53:$E$55,0)),IF(BN2="Shoulder",INDEX($K$53:$K$55,MATCH(BN2,$E$53:$E$55,0)),INDEX($K$53:$K$55,MATCH(BN2,$E$53:$E$55,0)))) -> 19.208 | BO20: =IF(BO2="Trough",INDEX($K$53:$K$55,MATCH(BO2,$E$53:$E$55,0)),IF(BO2="Shoulder",INDEX($K$53:$K$55,MATCH(BO2,$E$53:$E$55,0)),INDEX($K$53:$K$55,MATCH(BO2,$E$53:$E$55,0)))) -> 19.208 | BP20: =IF(BP2="Trough",INDEX($K$53:$K$55,MATCH(BP2,$E$53:$E$55,0)),IF(BP2="Shoulder",INDEX($K$53:$K$55,MATCH(BP2,$E$53:$E$55,0)),INDEX($K$53:$K$55,MATCH(BP2,$E$53:$E$55,0)))) -> 27.44 | BQ20: =IF(BQ2="Trough",INDEX($K$53:$K$55,MATCH(BQ2,$E$53:$E$55,0)),IF(BQ2="Shoulder",INDEX($K$53:$K$55,MATCH(BQ2,$E$53:$E$55,0)),INDEX($K$53:$K$55,MATCH(BQ2,$E$53:$E$55,0)))) -> 19.208 | BR20: =IF(BR2="Trough",INDEX($K$53:$K$55,MATCH(BR2,$E$53:$E$55,0)),IF(BR2="Shoulder",INDEX($K$53:$K$55,MATCH(BR2,$E$53:$E$55,0)),INDEX($K$53:$K$55,MATCH(BR2,$E$53:$E$55,0)))) -> 27.44 | BS20: =IF(BS2="Trough",INDEX($K$53:$K$55,MATCH(BS2,$E$53:$E$55,0)),IF(BS2="Shoulder",INDEX($K$53:$K$55,MATCH(BS2,$E$53:$E$55,0)),INDEX($K$53:$K$55,MATCH(BS2,$E$53:$E$55,0)))) -> 27.44 | ... BW20: =IF(BW2="Trough",INDEX($K$53:$K$55,MATCH(BW2,$E$53:$E$55,0)),IF(BW2="Shoulder",INDEX($K$53:$K$55,MATCH(BW2,$E$53:$E$55,0)),INDEX($K$53:$K$55,MATCH(BW2,$E$53:$E$55,0)))) -> 10.976 | BX20: =IF(BX2="Trough",INDEX($L$53:$L$55,MATCH(BX2,$E$53:$E$55,0)),IF(BX2="Shoulder",INDEX($L$53:$L$55,MATCH(BX2,$E$53:$E$55,0)),INDEX($L$53:$L$55,MATCH(BX2,$E$53:$E$55,0)))) -> 26.8912 | BY20: =IF(BY2="Trough",INDEX($L$53:$L$55,MATCH(BY2,$E$53:$E$55,0)),IF(BY2="Shoulder",INDEX($L$53:$L$55,MATCH(BY2,$E$53:$E$55,0)),INDEX($L$53:$L$55,MATCH(BY2,$E$53:$E$55,0)))) -> 38.416 | BZ20: =IF(BZ2="Trough",INDEX($L$53:$L$55,MATCH(BZ2,$E$53:$E$55,0)),IF(BZ2="Shoulder",INDEX($L$53:$L$55,MATCH(BZ2,$E$53:$E$55,0)),INDEX($L$53:$L$55,MATCH(BZ2,$E$53:$E$55,0)))) -> 26.8912 | CA20: =IF(CA2="Trough",INDEX($L$53:$L$55,MATCH(CA2,$E$53:$E$55,0)),IF(CA2="Shoulder",INDEX($L$53:$L$55,MATCH(CA2,$E$53:$E$55,0)),INDEX($L$53:$L$55,MATCH(CA2,$E$53:$E$55,0)))) -> 26.8912 | CB20: =IF(CB2="Trough",INDEX($L$53:$L$55,MATCH(CB2,$E$53:$E$55,0)),IF(CB2="Shoulder",INDEX($L$53:$L$55,MATCH(CB2,$E$53:$E$55,0)),INDEX($L$53:$L$55,MATCH(CB2,$E$53:$E$55,0)))) -> 38.416 | CC20: =IF(CC2="Trough",INDEX($L$53:$L$55,MATCH(CC2,$E$53:$E$55,0)),IF(CC2="Shoulder",INDEX($L$53:$L$55,MATCH(CC2,$E$53:$E$55,0)),INDEX($L$53:$L$55,MATCH(CC2,$E$53:$E$55,0)))) -> 26.8912 | CD20: =IF(CD2="Trough",INDEX($L$53:$L$55,MATCH(CD2,$E$53:$E$55,0)),IF(CD2="Shoulder",INDEX($L$53:$L$55,MATCH(CD2,$E$53:$E$55,0)),INDEX($L$53:$L$55,MATCH(CD2,$E$53:$E$55,0)))) -> 38.416 | CE20: =IF(CE2="Trough",INDEX($L$53:$L$55,MATCH(CE2,$E$53:$E$55,0)),IF(CE2="Shoulder",INDEX($L$53:$L$55,MATCH(CE2,$E$53:$E$55,0)),INDEX($L$53:$L$55,MATCH(CE2,$E$53:$E$55,0)))) -> 38.416 | ... CI20: =IF(CI2="Trough",INDEX($L$53:$L$55,MATCH(CI2,$E$53:$E$55,0)),IF(CI2="Shoulder",INDEX($L$53:$L$55,MATCH(CI2,$E$53:$E$55,0)),INDEX($L$53:$L$55,MATCH(CI2,$E$53:$E$55,0)))) -> 15.3664 | CJ20: =IF(CJ2="Trough",INDEX($M$53:$M$55,MATCH(CJ2,$E$53:$E$55,0)),IF(CJ2="Shoulder",INDEX($M$53:$M$55,MATCH(CJ2,$E$53:$E$55,0)),INDEX($M$53:$M$55,MATCH(CJ2,$E$53:$E$55,0)))) -> 37.64768 | CK20: =IF(CK2="Trough",INDEX($M$53:$M$55,MATCH(CK2,$E$53:$E$55,0)),IF(CK2="Shoulder",INDEX($M$53:$M$55,MATCH(CK2,$E$53:$E$55,0)),INDEX($M$53:$M$55,MATCH(CK2,$E$53:$E$55,0)))) -> 53.7824 | CL20: =IF(CL2="Trough",INDEX($M$53:$M$55,MATCH(CL2,$E$53:$E$55,0)),IF(CL2="Shoulder",INDEX($M$53:$M$55,MATCH(CL2,$E$53:$E$55,0)),INDEX($M$53:$M$55,MATCH(CL2,$E$53:$E$55,0)))) -> 37.64768 | CM20: =IF(CM2="Trough",INDEX($M$53:$M$55,MATCH(CM2,$E$53:$E$55,0)),IF(CM2="Shoulder",INDEX($M$53:$M$55,MATCH(CM2,$E$53:$E$55,0)),INDEX($M$53:$M$55,MATCH(CM2,$E$53:$E$55,0)))) -> 37.64768 | CN20: =IF(CN2="Trough",INDEX($M$53:$M$55,MATCH(CN2,$E$53:$E$55,0)),IF(CN2="Shoulder",INDEX($M$53:$M$55,MATCH(CN2,$E$53:$E$55,0)),INDEX($M$53:$M$55,MATCH(CN2,$E$53:$E$55,0)))) -> 53.7824 | CO20: =IF(CO2="Trough",INDEX($M$53:$M$55,MATCH(CO2,$E$53:$E$55,0)),IF(CO2="Shoulder",INDEX($M$53:$M$55,MATCH(CO2,$E$53:$E$55,0)),INDEX($M$53:$M$55,MATCH(CO2,$E$53:$E$55,0)))) -> 37.64768 | CP20: =IF(CP2="Trough",INDEX($M$53:$M$55,MATCH(CP2,$E$53:$E$55,0)),IF(CP2="Shoulder",INDEX($M$53:$M$55,MATCH(CP2,$E$53:$E$55,0)),INDEX($M$53:$M$55,MATCH(CP2,$E$53:$E$55,0)))) -> 53.7824 | CQ20: =IF(CQ2="Trough",INDEX($M$53:$M$55,MATCH(CQ2,$E$53:$E$55,0)),IF(CQ2="Shoulder",INDEX($M$53:$M$55,MATCH(CQ2,$E$53:$E$55,0)),INDEX($M$53:$M$55,MATCH(CQ2,$E$53:$E$55,0)))) -> 53.7824 | ... CU20: =IF(CU2="Trough",INDEX($M$53:$M$55,MATCH(CU2,$E$53:$E$55,0)),IF(CU2="Shoulder",INDEX($M$53:$M$55,MATCH(CU2,$E$53:$E$55,0)),INDEX($M$53:$M$55,MATCH(CU2,$E$53:$E$55,0)))) -> 21.51296 | CV20: =IF(CV2="Trough",INDEX($N$53:$N$55,MATCH(CV2,$E$53:$E$55,0)),IF(CV2="Shoulder",INDEX($N$53:$N$55,MATCH(CV2,$E$53:$E$55,0)),INDEX($N$53:$N$55,MATCH(CV2,$E$53:$E$55,0)))) -> 52.706752 | CW20: =IF(CW2="Trough",INDEX($N$53:$N$55,MATCH(CW2,$E$53:$E$55,0)),IF(CW2="Shoulder",INDEX($N$53:$N$55,MATCH(CW2,$E$53:$E$55,0)),INDEX($N$53:$N$55,MATCH(CW2,$E$53:$E$55,0)))) -> 75.29536 | CX20: =IF(CX2="Trough",INDEX($N$53:$N$55,MATCH(CX2,$E$53:$E$55,0)),IF(CX2="Shoulder",INDEX($N$53:$N$55,MATCH(CX2,$E$53:$E$55,0)),INDEX($N$53:$N$55,MATCH(CX2,$E$53:$E$55,0)))) -> 52.706752 | CY20: =IF(CY2="Trough",INDEX($N$53:$N$55,MATCH(CY2,$E$53:$E$55,0)),IF(CY2="Shoulder",INDEX($N$53:$N$55,MATCH(CY2,$E$53:$E$55,0)),INDEX($N$53:$N$55,MATCH(CY2,$E$53:$E$55,0)))) -> 52.706752 | CZ20: =IF(CZ2="Trough",INDEX($N$53:$N$55,MATCH(CZ2,$E$53:$E$55,0)),IF(CZ2="Shoulder",INDEX($N$53:$N$55,MATCH(CZ2,$E$53:$E$55,0)),INDEX($N$53:$N$55,MATCH(CZ2,$E$53:$E$55,0)))) -> 75.29536 | DA20: =IF(DA2="Trough",INDEX($N$53:$N$55,MATCH(DA2,$E$53:$E$55,0)),IF(DA2="Shoulder",INDEX($N$53:$N$55,MATCH(DA2,$E$53:$E$55,0)),INDEX($N$53:$N$55,MATCH(DA2,$E$53:$E$55,0)))) -> 52.706752 | DB20: =IF(DB2="Trough",INDEX($N$53:$N$55,MATCH(DB2,$E$53:$E$55,0)),IF(DB2="Shoulder",INDEX($N$53:$N$55,MATCH(DB2,$E$53:$E$55,0)),INDEX($N$53:$N$55,MATCH(DB2,$E$53:$E$55,0)))) -> 75.29536 | DC20: =IF(DC2="Trough",INDEX($N$53:$N$55,MATCH(DC2,$E$53:$E$55,0)),IF(DC2="Shoulder",INDEX($N$53:$N$55,MATCH(DC2,$E$53:$E$55,0)),INDEX($N$53:$N$55,MATCH(DC2,$E$53:$E$55,0)))) -> 75.29536 | ... DG20: =IF(DG2="Trough",INDEX($N$53:$N$55,MATCH(DG2,$E$53:$E$55,0)),IF(DG2="Shoulder",INDEX($N$53:$N$55,MATCH(DG2,$E$53:$E$55,0)),INDEX($N$53:$N$55,MATCH(DG2,$E$53:$E$55,0)))) -> 30.118144
C21: Subtrctions | F21: =+IF(F17<E17,F17-E17, 0) -> -4 | G21: =+IF(G17<F17,G17-F17, 0) -> -1 | H21: =+IF(H17<G17,H17-G17, 0) -> 0 | I21: =+IF(I17<H17,I17-H17, 0) -> 0 | J21: =+IF(J17<I17,J17-I17, 0) -> -2 | K21: =+IF(K17<J17,K17-J17, 0) -> -6 | L21: =+IF(L17<K17,L17-K17, 0) -> 0 | M21: =+IF(M17<L17,M17-L17, 0) -> 0 | ... P21: =+IF(P17<O17,P17-O17, 0) -> 0 | Q21: -4 | R21: -2 | S21: -6 | T21: -4 | U21: -7 | V21: -9 | W21: -1 | X21: -3 | Y21: -5 | Z21: -14 | AA21: -18 | AB21: -7 | AC21: -4 | AD21: -2 | AE21: -8 | AF21: -3 | AG21: -11 | AH21: -1 | AI21: -2 | AJ21: -6 | AK21: -3 | AL21: -10 | AM21: -26 | AN21: -11 | AO21: -7 | AP21: -8 | AQ21: -6 | AR21: -6 | AS21: -6 | AT21: -2 | AU21: -2 | AV21: -6 | AW21: -6 | AX21: =+ROUNDUP(AW17*AW40, 0) -> -9 | AY21: =+ROUNDUP(AX17*AX40, 0) -> -10 | AZ21: =+ROUNDUP(AY17*AY40, 0) -> -14 | BA21: =+ROUNDUP(AZ17*AZ40, 0) -> -14 | BB21: =+ROUNDUP(BA17*BA40, 0) -> -17 | BC21: =+ROUNDUP(BB17*BB40, 0) -> -19 | BD21: =+ROUNDUP(BC17*BC40, 0) -> -19 | BE21: =+ROUNDUP(BD17*BD40, 0) -> -22 | ... DG21: =+ROUNDUP(DF17*DF40, 0) -> -38
C22: # of Sessions | P22: 21 | Q22: 22 | R22: 20 | S22: 16 | T22: 25 | U22: 22 | V22: 23 | W22: 70 | X22: 110 | Y22: 114 | Z22: 73 | AA22: 31 | AB22: 34 | AC22: 56 | AD22: 36 | AE22: 49 | AF22: 76 | AG22: 45 | AH22: 118 | AI22: 169 | AJ22: 125 | AK22: 173 | AL22: 90 | AM22: 50 | AN22: 56 | AO22: 66 | AP22: 73 | AQ22: 37 | AR22: 62 | AS22: 51 | AT22: 120 | AU22: 163 | AV22: 240 | AW22: 275 | AX22: =+AVERAGE(AU22:AW22) -> 226 | AY22: =+(AX22/AX26)*AY26 -> 247.623 | AZ22: =+(AY22/AY26)*AZ26 -> 304.52174 | BA22: =+(AZ22/AZ26)*BA26 -> 323.57053 | BB22: =+(BA22/BA26)*BB26 -> 373.00336 | BC22: =+(BB22/BB26)*BC26 -> 160.89476 | BD22: =+(BC22/BC26)*BD26 -> 283.27802 | BE22: =+(BD22/BD26)*BE26 -> 175.69188 | BF22: =+(BE22/BE26)*BF26 -> 275.42235 | ... DG22: =+(DF22/DF26)*DG26 -> 1120.3645
B23: Coverage
B24: 125 | C24: Billing Days | E24: =NETWORKDAYS(D4+1,E4,Holidays!$B$3:$B$62) -> 19 | F24: =NETWORKDAYS(E4+1,F4,Holidays!$B$3:$B$62) -> 23 | G24: =NETWORKDAYS(F4+1,G4,Holidays!$B$3:$B$62) -> 21 | H24: =NETWORKDAYS(G4+1,H4,Holidays!$B$3:$B$62) -> 21 | I24: =NETWORKDAYS(H4+1,I4,Holidays!$B$3:$B$62) -> 22 | J24: =NETWORKDAYS(I4+1,J4,Holidays!$B$3:$B$62) -> 20 | K24: =NETWORKDAYS(J4+1,K4,Holidays!$B$3:$B$62) -> 23 | L24: =NETWORKDAYS(K4+1,L4,Holidays!$B$3:$B$62) -> 21 | ... DG24: =NETWORKDAYS(DF4+1,DG4,Holidays!$B$3:$B$62) -> 22
C25: Hours / Day / Student | E25: =+E26/E24/E17 -> 0.0043859649 | F25: =+F26/F24/F17 -> 0.0054347826 | G25: =+G26/G24/G17 -> 0.0068027211 | H25: =+H26/H24/H17 -> 0.0047619048 | I25: =+I26/I24/I17 -> 0.0034965035 | J25: =+J26/J24/J17 -> 0.0045454545 | K25: =+K26/K24/K17 -> 0.065217391 | L25: =+L26/L24/L17 -> 0.10846561 | ... AW25: =+AW26/AW24/AW17 -> 0.19987021 | AX25: =+AL25 -> 0.14204545 | AY25: =+AM25 -> 0.14359268 | AZ25: =+AN25 -> 0.16938406 | BA25: =+AO25 -> 0.18035714 | BB25: =+AP25 -> 0.19940476 | BC25: =+AQ25 -> 0.094367589 | BD25: =+AR25 -> 0.17215909 | BE25: =+AS25 -> 0.12 | ... DG25: =+CU25 -> 0.14359268
C26: Total Bill Hours | E26: 1 | F26: 1 | G26: 1 | H26: 1 | I26: 1 | J26: 1 | K26: 7.5 | L26: =20.5 -> 20.5 | M26: 57.25 | N26: 31 | O26: 15 | P26: =+SUM(P28:P32) -> 26.33 | Q26: =+SUM(Q28:Q32) -> 21.25 | R26: =+SUM(R28:R32) -> 21 | S26: =+SUM(S28:S32) -> 18.25 | T26: =+SUM(T28:T32) -> 42.25 | U26: =+SUM(U28:U32) -> 42 | V26: =+SUM(V28:V32) -> 31.75 | W26: =+SUM(W28:W32) -> 84.25 | ... AW26: =+SUM(AW28:AW32) -> 308 | AX26: =+(AX17*AX24*AX25) -> 158.52273 | AY26: =+(AY17*AY24*AY25) -> 173.6897 | AZ26: =+(AZ17*AZ24*AZ25) -> 213.60007 | BA26: =+(BA17*BA24*BA25) -> 226.96143 | BB26: =+(BB17*BB24*BB25) -> 261.635 | BC26: =+(BC17*BC24*BC25) -> 112.85609 | BD26: =+(BD17*BD24*BD25) -> 198.69914 | BE26: =+(BE17*BE24*BE25) -> 123.2352 | ... DG26: =+(DG17*DG24*DG25) -> 785.85505
C27: River Hours | L27: 3.75 | M27: 14.75 | N27: 13.5 | O27: 14 | P27: 14 | Q27: 14 | R27: 5.5 | S27: 4.5 | T27: 5 | U27: 25.75 | V27: 11.75 | W27: 0 | X27: 0 | Y27: 0 | Z27: 0 | AA27: 0 | AB27: 0 | AC27: 0 | AD27: 0 | AE27: 0 | AF27: 0 | AG27: 0 | AH27: 0 | AI27: 0 | AJ27: 0 | AK27: 0 | AL27: 0 | AM27: 0 | AN27: 0 | AO27: 0 | AP27: 0 | AQ27: 0 | AR27: 0 | AS27: 0 | AT27: 0 | AU27: 0 | AV27: 0 | AW27: 0 | AX27: 0 | AY27: =AX27 -> 0 | AZ27: =AY27 -> 0 | BA27: =AZ27 -> 0 | BB27: =BA27 -> 0 | BC27: =BB27 -> 0 | BD27: =BC27 -> 0 | BE27: =BD27 -> 0 | BF27: =BE27 -> 0 | ... DG27: =DF27 -> 0
C28: Total Tutoring Hours | P28: 21.5 | Q28: =8.25+5 -> 13.25 | R28: 18.25 | S28: 16.25 | T28: 37 | U28: 40.75 | V28: 22 | W28: 56.25 | X28: 60 | Y28: 58.5 | Z28: 47.75 | AA28: 21.75 | AB28: 22.25 | AC28: 36 | AD28: 25.75 | AE28: 32 | AF28: 27.5 | AG28: 14 | AH28: 15.5 | AI28: 14 | AJ28: 4.75 | AK28: 2.25 | AL28: 10 | AM28: 8 | AN28: 4.25 | AO28: 13 | AP28: 20.5 | AQ28: 5 | AR28: 3.75 | AS28: 0 | AT28: 2.25 | AU28: 11.25 | AV28: 19.25 | AW28: 24.5 | AX28: =+IFERROR(AX$26*(AL28/AL$26), 0) -> 13.349282 | AY28: =+IFERROR(AY$26*(AM28/AM$26), 0) -> 22.143707 | AZ28: =+IFERROR(AZ$26*(AN28/AN$26), 0) -> 9.7090942 | BA28: =+IFERROR(BA$26*(AO28/AO$26), 0) -> 29.212857 | BB28: =+IFERROR(BB$26*(AP28/AP$26), 0) -> 53.368333 | BC28: =+IFERROR(BC$26*(AQ28/AQ$26), 0) -> 11.817391 | BD28: =+IFERROR(BD$26*(AR28/AR$26), 0) -> 9.8365909 | BE28: =+IFERROR(BE$26*(AS28/AS$26), 0) -> 0 | ... DG28: =+IFERROR(DG$26*(CU28/CU$26), 0) -> 100.18869
C29: Total SAT/ACT Prep Hours | P29: 0 | Q29: 0 | R29: 0 | S29: 0 | T29: 0 | U29: 0 | V29: 2.5 | W29: 1 | X29: 25.25 | Y29: 22.5 | Z29: 16.5 | AA29: 10 | AB29: 18.5 | AC29: 35.25 | AD29: 24.5 | AE29: 32.25 | AF29: 60.75 | AG29: 24.5 | AH29: 68.25 | AI29: 126.75 | AJ29: 22 | AK29: 30.5 | AL29: 14 | AM29: 25 | AN29: 46.75 | AO29: 63 | AP29: 74.25 | AQ29: 37 | AR29: 66.75 | AS29: 27.5 | AT29: 67.75 | AU29: 78.25 | AV29: 106 | AW29: 57.75 | AX29: =+IFERROR(AX$26*(AL29/AL$26), 0) -> 18.688995 | AY29: =+IFERROR(AY$26*(AM29/AM$26), 0) -> 69.199085 | AZ29: =+IFERROR(AZ$26*(AN29/AN$26), 0) -> 106.80004 | BA29: =+IFERROR(BA$26*(AO29/AO$26), 0) -> 141.57 | BB29: =+IFERROR(BB$26*(AP29/AP$26), 0) -> 193.2975 | BC29: =+IFERROR(BC$26*(AQ29/AQ$26), 0) -> 87.448696 | BD29: =+IFERROR(BD$26*(AR29/AR$26), 0) -> 175.09132 | BE29: =+IFERROR(BE$26*(AS29/AS$26), 0) -> 53.793143 | ... DG29: =+IFERROR(DG$26*(CU29/CU$26), 0) -> 313.08966
C30: Total Resume Review | AI30: 12.25 | AJ30: 15.25 | AK30: 21.5 | AL30: 1.75 | AM30: 0 | AN30: 0 | AO30: 3.75 | AR30: 2.25 | AS30: 5.5 | AT30: 8.75 | AU30: 12.25 | AV30: 16.75 | AW30: =17+1.25 -> 18.25 | AX30: =+IFERROR(AX$26*(AL30/AL$26), 0) -> 2.3361244 | AY30: =+IFERROR(AY$26*(AM30/AM$26), 0) -> 0 | AZ30: =+IFERROR(AZ$26*(AN30/AN$26), 0) -> 0 | BA30: =+IFERROR(BA$26*(AO30/AO$26), 0) -> 8.4267857 | BB30: =+IFERROR(BB$26*(AP30/AP$26), 0) -> 0 | BC30: =+IFERROR(BC$26*(AQ30/AQ$26), 0) -> 0 | BD30: =+IFERROR(BD$26*(AR30/AR$26), 0) -> 5.9019545 | BE30: =+IFERROR(BE$26*(AS30/AS$26), 0) -> 10.758629 | ... DG30: =+IFERROR(DG$26*(CU30/CU$26), 0) -> 0
C31: Total College Service Hours | P31: 3 | Q31: 0 | R31: 0 | S31: 1 | T31: 0 | U31: 1.25 | V31: 7.25 | W31: 27 | X31: 45.25 | Y31: 55.25 | Z31: 17.75 | AA31: 0.75 | AB31: 3.25 | AC31: 2.25 | AD31: 4 | AE31: 0.5 | AF31: 1.25 | AG31: 20 | AH31: 52 | AI31: 68.75 | AJ31: 101.25 | AK31: 157.5 | AL31: 93 | AM31: 29.75 | AN31: =15+9.25+15.25 -> 39.5 | AO31: 19.25 | AP31: 5.75 | AQ31: 4.75 | AR31: 3 | AS31: 30 | AT31: 61 | AU31: 82.75 | AV31: 117.25 | AW31: 207.5 | AX31: =+IFERROR(AX$26*(AL31/AL$26), 0)-50 -> 74.148325 | AY31: =+IFERROR(AY$26*(AM31/AM$26), 0) -> 82.346911 | AZ31: =+IFERROR(AZ$26*(AN31/AN$26), 0) -> 90.237464 | BA31: =+IFERROR(BA$26*(AO31/AO$26), 0) -> 43.2575 | BB31: =+IFERROR(BB$26*(AP31/AP$26), 0) -> 14.969167 | BC31: =+IFERROR(BC$26*(AQ31/AQ$26), 0) -> 11.226522 | BD31: =+IFERROR(BD$26*(AR31/AR$26), 0) -> 7.8692727 | BE31: =+IFERROR(BE$26*(AS31/AS$26), 0) -> 58.683429 | BF31: =+IFERROR(BF$26*(AT31/AT$26), 0) -> 84.325766 | ... DG31: =+IFERROR(DG$26*(CU31/CU$26), 0) -> 372.5767
C32: Total Dance Hours | P32: 1.83 | Q32: 8 | R32: 2.75 | S32: 1 | T32: 5.25 | U32: 0 | V32: 0 | W32: 0 | X32: 0 | Y32: 0 | Z32: 2 | AA32: 2 | AB32: 1 | AC32: 1 | AD32: 6 | AE32: 5 | AF32: 0 | AG32: 1 | AH32: 0 | AI32: 0 | AJ32: 0 | AK32: 0 | AL32: 0 | AM32: 0 | AN32: 3 | AO32: 2 | AQ32: 1 | AX32: =+IFERROR(AX$26*(AL32/AL$26), 0) -> 0 | AY32: =+IFERROR(AY$26*(AM32/AM$26), 0) -> 0 | AZ32: =+IFERROR(AZ$26*(AN32/AN$26), 0) -> 6.8534783 | BA32: =+IFERROR(BA$26*(AO32/AO$26), 0) -> 4.4942857 | BB32: =+IFERROR(BB$26*(AP32/AP$26), 0) -> 0 | BC32: =+IFERROR(BC$26*(AQ32/AQ$26), 0) -> 2.3634783 | BD32: =+IFERROR(BD$26*(AR32/AR$26), 0) -> 0 | BE32: =+IFERROR(BE$26*(AS32/AS$26), 0) -> 0 | ... DG32: =+IFERROR(DG$26*(CU32/CU$26), 0) -> 0
C33: Realized / Effective Bill Rate | E33: =+E14/(E26+E27) -> 0 | F33: =+F14/(F26+F27) -> 0 | G33: =+G14/(G26+G27) -> 0 | H33: =+H14/(H26+H27) -> 0 | I33: =+I14/(I26+I27) -> 0 | J33: =+J14/(J26+J27) -> 0 | K33: =+K14/(K26+K27) -> 50 | L33: =+L14/(L26+L27) -> 44.329897 | ... O33: =+O14/(O26+O27) -> 70.086207 | P33: =+P14/(P26) -> 58.715913 | Q33: =+Q14/(Q26) -> 59.094118 | R33: =+R14/(R26) -> 57.464286 | S33: =+S14/(S26+SUM(Q27:S27)) -> 46.329231 | T33: =+T14/(T26) -> 58.862249 | U33: =+U14/(U26) -> 48.653095 | V33: =+V14/(V26+(SUM($T$27:$V$27)/2)) -> 53.5 | W33: =+W14/(W26+(SUM($T$27:$V$27)/2)) -> 67.096303 | X33: =+X14/(X26) -> 67.096475 | Y33: =+Y14/(Y26) -> 60.156844 | Z33: =+Z14/(Z26) -> 58.787143 | AA33: =+AA14/(AA26) -> 62.15942 | AB33: =+AB14/(AB26) -> 66.711111 | AC33: =+AC14/(AC26) -> 58.489933 | AD33: =+AD14/(AD26) -> 57.751037 | AE33: =+AE14/(AE26) -> 57.605735 | ... DG33: =+DG14/(DG26) -> 103.88481
C34: Tutoring Bill Rate | P34: =+(P7-(P32*60))/P28 -> 58.148837 | Q34: =+(Q7-(Q32*60))/Q28 -> 56.226415 | R34: =+(R7-(R32*60))/R28 -> 55.479452 | S34: =+(S7-(S32*60))/S28 -> 111.69231 | T34: =+(T7-(T32*60))/T28 -> 57.601351 | U34: =+(U7-(U32*60))/U28 -> 48.190184 | V34: =+(V7-(V32*60))/V28 -> 100.90909 | W34: =+(W7-(W32*60))/W28 -> 94.5184 | ... AM34: =+(AM7-(AM32*60))/AM28 -> 73.125 | AN34: =+IFERROR((AN7-(AN32*60))/AN28, 0) -> 45 | AO34: =+IFERROR((AO7-(AO32*60))/AO28, 0) -> 76.057692 | AP34: =+IFERROR((AP7-(AP32*60))/AP28, 0) -> 75 | AQ34: =+IFERROR((AQ7-(AQ32*60))/AQ28, 0) -> 75 | AR34: =+IFERROR((AR7-(AR32*60))/AR28, 0) -> 75 | AS34: =+IFERROR((AS7-(AS32*60))/AS28, 0) -> 0 | AT34: =+IFERROR((AT7-(AT32*60))/AT28, 0) -> 75 | AU34: =+IFERROR((AU7-(AU32*60))/AU28, 0) -> 75 | ... AW34: =+IFERROR((AW7-(AW32*60))/AW28, 0) -> 76.377959 | AX34: 75 | AY34: =+AX34 -> 75 | AZ34: =+AY34 -> 75 | BA34: =+AZ34 -> 75 | BB34: =+BA34 -> 75 | BC34: =+BB34 -> 75 | BD34: =+BC34 -> 75 | BE34: =+BD34 -> 75 | BF34: =+BE34 -> 75 | ... DG34: =+DF34 -> 75
C35: SAT/ACT Bill Rate | P35: =+IFERROR(P8/P29, 0) -> 0 | Q35: =+IFERROR(Q8/Q29, 0) -> 0 | R35: =+IFERROR(R8/R29, 0) -> 0 | S35: =+IFERROR(S8/S29, 0) -> 0 | T35: =+IFERROR(T8/T29, 0) -> 0 | U35: =+IFERROR(U8/U29, 0) -> 0 | V35: =+IFERROR(V8/V29, 0) -> 60 | W35: =+IFERROR(W8/W29, 0) -> 140 | ... AW35: =+IFERROR(AW8/AW29, 0) -> 78.549784 | AX35: 75 | AY35: =+AX35 -> 75 | AZ35: =+AY35 -> 75 | BA35: =+AZ35 -> 75 | BB35: =+BA35 -> 75 | BC35: =+BB35 -> 75 | BD35: =+BC35 -> 75 | BE35: =+BD35 -> 75 | BF35: =+BE35 -> 75 | ... DG35: =+DF35 -> 75
C36: Resume Review Bill Rate | P36: =+IFERROR(P9/P30, 0) -> 0 | Q36: =+IFERROR(Q9/Q30, 0) -> 0 | R36: =+IFERROR(R9/R30, 0) -> 0 | S36: =+IFERROR(S9/S30, 0) -> 0 | T36: =+IFERROR(T9/T30, 0) -> 0 | U36: =+IFERROR(U9/U30, 0) -> 0 | V36: =+IFERROR(V9/V30, 0) -> 0 | W36: =+IFERROR(W9/W30, 0) -> 0 | ... AW36: =+IFERROR(AW9/AW30, 0) -> 131.16438 | AX36: 135 | AY36: =+AX36 -> 135 | AZ36: =+AY36 -> 135 | BA36: =+AZ36 -> 135 | BB36: =+BA36 -> 135 | BC36: =+BB36 -> 135 | BD36: =+BC36 -> 135 | BE36: =+BD36 -> 135 | BF36: =+BE36 -> 135 | ... DG36: =+DF36 -> 135
C37: College Services Bill Rate | P37: =IFERROR(P10/P31, 0) -> 50 | Q37: =IFERROR(Q10/Q31, 0) -> 0 | R37: =IFERROR(R10/R31, 0) -> 0 | S37: =IFERROR(S10/S31, 0) -> 44.91 | T37: =IFERROR(T10/T31, 0) -> 0 | U37: =IFERROR(U10/U31, 0) -> 60 | V37: =IFERROR(V10/V31, 0) -> 57.241379 | W37: =IFERROR(W10/W31, 0) -> 59.074074 | ... AW37: =IFERROR(AW10/AW31, 0) -> 146.24096 | AX37: 135 | AY37: =+AX37 -> 135 | AZ37: =+AY37 -> 135 | BA37: =+AZ37 -> 135 | BB37: =+BA37 -> 135 | BC37: =+BB37 -> 135 | BD37: =+BC37 -> 135 | BE37: =+BD37 -> 135 | BF37: =+BE37 -> 135 | ... DG37: =+DF37 -> 135
C38: Dance Bill Rate | P38: =+IFERROR((P32*60)/P32, 0) -> 60 | Q38: =+IFERROR((Q32*60)/Q32, 0) -> 60 | R38: =+IFERROR((R32*60)/R32, 0) -> 60 | S38: =+IFERROR((S32*60)/S32, 0) -> 60 | T38: =+IFERROR((T32*60)/T32, 0) -> 60 | U38: =+IFERROR((U32*60)/U32, 0) -> 0 | V38: =+IFERROR((V32*60)/V32, 0) -> 0 | W38: =+IFERROR((W32*60)/W32, 0) -> 0 | ... AW38: =+IFERROR((AW32*60)/AW32, 0) -> 0 | AX38: 60 | AY38: =+AX38 -> 60 | AZ38: =+AY38 -> 60 | BA38: =+AZ38 -> 60 | BB38: =+BA38 -> 60 | BC38: =+BB38 -> 60 | BD38: =+BC38 -> 60 | BE38: =+BD38 -> 60 | BF38: =+BE38 -> 60 | ... DG38: =+DF38 -> 60
C40: T6M Avg Monthly Attrition | L40: =+AVERAGE(F21:L21)/AVERAGE(F17:L17) -> -0.20634921 | M40: =+AVERAGE(G21:M21)/AVERAGE(G17:M17) -> -0.125 | N40: =+AVERAGE(H21:N21)/AVERAGE(H17:N17) -> -0.18421053 | O40: =+AVERAGE(I21:O21)/AVERAGE(I17:O17) -> -0.24657534 | P40: =+AVERAGE(J21:P21)/AVERAGE(J17:P17) -> -0.25 | Q40: =+AVERAGE(K21:Q21)/AVERAGE(K17:Q17) -> -0.28169014 | R40: =+AVERAGE(L21:R21)/AVERAGE(L17:R17) -> -0.21052632 | S40: =+AVERAGE(M21:S21)/AVERAGE(M17:S17) -> -0.2972973 | ... AW40: =+AVERAGE(AQ21:AW21)/AVERAGE(AQ17:AW17) -> -0.12363636 | AX40: =+AL40 -> -0.14634146 | AY40: =+AM40 -> -0.23694779 | AZ40: =+AN40 -> -0.23694779 | BA40: =+AO40 -> -0.26315789 | BB40: =+AP40 -> -0.30472103 | BC40: =+AQ40 -> -0.3317757 | BD40: =+AR40 -> -0.39784946 | BE40: =+AS40 -> -0.41916168 | ... DG40: =+CU40 -> -0.23694779
C41: Implied Tenure | L41: =1/-L40 -> 4.8461538 | M41: =1/-M40 -> 8 | N41: =1/-N40 -> 5.4285714 | O41: =1/-O40 -> 4.0555556 | P41: =1/-P40 -> 4 | Q41: =1/-Q40 -> 3.55 | R41: =1/-R40 -> 4.75 | S41: =1/-S40 -> 3.3636364 | ... DG41: =1/-DG40 -> 4.220339
C42: Average Revenue | L42: =+L14/AVERAGE(G17:L17) -> 117.27273 | M42: =+M14/AVERAGE(H17:M17) -> 347.53846 | N42: =+N14/AVERAGE(I17:N17) -> 190 | O42: =+O14/AVERAGE(J17:O17) -> 203.25 | P42: =+P14/AVERAGE(K17:P17) -> 152.06459 | Q42: =+Q14/AVERAGE(L17:Q17) -> 114.15909 | R42: =+R14/AVERAGE(M17:R17) -> 108.06716 | S42: =+S14/AVERAGE(N17:S17) -> 206.04316 | ... DG42: =+DG14/AVERAGE(DB17:DG17) -> 351.00353
C43: Lifetime Revenue | L43: =+L42*L41 -> 568.32168 | M43: =+M42*M41 -> 2780.3077 | N43: =+N42*N41 -> 1031.4286 | O43: =+O42*O41 -> 824.29167 | P43: =+P42*P41 -> 608.25836 | Q43: =+Q42*Q41 -> 405.26477 | R43: =+R42*R41 -> 513.31903 | S43: =+S42*S41 -> 693.05426 | ... DG43: =+DG42*DG41 -> 1481.3539
C44: GM% | L44: =+L97/L14 -> 0.97488372 | M44: =+M97/M14 -> 0.52279947 | N44: =+N97/N14 -> 0.77405263 | O44: =+O97/O14 -> 0.920246 | P44: =+P97/P14 -> 0.84790975 | Q44: =+Q97/Q14 -> 0.87755525 | R44: =+R97/R14 -> 0.91269111 | S44: =+S97/S14 -> 0.86061173 | ... AM44: =+AM97/AM14 -> 0.76526569 | AN44: =+AN64/AN14 -> 1 | AO44: =+AO64/AO14 -> 0.94452745 | AP44: =+AP64/AP14 -> 1 | AQ44: =+AQ64/AQ14 -> 1 | AR44: =+AR64/AR14 -> 0.95533129 | AS44: =+AS64/AS14 -> 1 | AT44: =+AT64/AT14 -> 0.89400536 | AU44: =+AU64/AU14 -> 0.96656401 | ... DG44: =+DG64/DG14 -> 0.83886893
C45: T3M LTV | L45: =+AVERAGE(L44*L43,K44*K43, J44*J43) -> 184.68252 | M45: =+AVERAGE(M44*M43,L44*L43, K44*K43) -> 669.19698 | N45: =+AVERAGE(N44*N43,M44*M43, L44*L43) -> 935.32365 | O45: =+AVERAGE(O44*O43,N44*N43, M44*M43) -> 1003.4915 | P45: =+AVERAGE(P44*P43,O44*O43, N44*N43) -> 690.8931 | Q45: =+AVERAGE(Q44*Q43,P44*P43, O44*O43) -> 543.31385 | R45: =+AVERAGE(R44*R43,Q44*Q43, P44*P43) -> 446.63071 | S45: =+AVERAGE(S44*S43,R44*R43, Q44*Q43) -> 473.53152 | ... DG45: =+AVERAGE(DG44*DG43,DF44*DF43, DE44*DE43) -> 2679.8383
C46: T3M CAC | L46: =+AVERAGE(J100:L100) -> 12 | M46: =+AVERAGE(K100:M100) -> 155.03 | N46: =+AVERAGE(L100:N100) -> 142.43 | O46: =+AVERAGE(M100:O100) -> 149.90667 | P46: =+AVERAGE(N100:P100) -> 93.93 | Q46: =+AVERAGE(O100:Q100) -> 71.106667 | R46: =+AVERAGE(P100:R100) -> 84.75 | S46: =+AVERAGE(Q100:S100) -> 96.656667 | ... DG46: =+AVERAGE(DE100:DG100) -> 13145.468
C47: LTV/CAC | L47: =+L45/L46 -> 15.39021 | M47: =+M45/M46 -> 4.3165644 | N47: =+N45/N46 -> 6.5669006 | O47: =+O45/O46 -> 6.6941085 | P47: =+P45/P46 -> 7.3554041 | Q47: =+Q45/Q46 -> 7.6408285 | R47: =+R45/R46 -> 5.2699789 | S47: =+S45/S46 -> 4.8991088 | ... DG47: =+DG45/DG46 -> 0.20386025
C48: Payback | L48: =+L46/(L42*L44) -> 0.10496183 | M48: =+M46/(M42*M44) -> 0.85325283 | N48: =+N46/(N42*N44) -> 0.9684504 | O48: =+O46/(O42*O44) -> 0.80146849 | P48: =+P46/(P42*P44) -> 0.72849503 | Q48: =+Q46/(Q42*Q44) -> 0.70978261 | R48: =+R46/(R42*R44) -> 0.85925512 | S48: =+S46/(S42*S44) -> 0.54508767 | ... DG48: =+DG46/(DG42*DG44) -> 44.644755
C49: Utilization % | E49: =+E25/8 -> 0.00054824561 | F49: =+F25/8 -> 0.00067934783 | G49: =+G25/8 -> 0.00085034014 | H49: =+H25/8 -> 0.0005952381 | I49: =+I25/8 -> 0.00043706294 | J49: =+J25/8 -> 0.00056818182 | K49: =+K25/8 -> 0.0081521739 | L49: =+L25/8 -> 0.013558201 | ... DG49: =+DG25/8 -> 0.017949085
F51: 2022 | G51: 2023 | H51: 2024 | I51: 2025 | J51: 2026 | K51: 2027 | L51: 2028 | M51: 2029 | N51: 2030 | Q51: 2022 | R51: 2023 | S51: 2024 | T51: 2025 | U51: 2026 | V51: 2027 | W51: 2028 | X51: 2028 | Y51: 2028 | Z51: 2029 | AA51: 2029
E52: Average | F52: =ROUNDUP(AVERAGE(F53:F55), 0) -> 3 | G52: =ROUNDUP(AVERAGE(G53:G55), 0) -> 4 | H52: =ROUNDUP(AVERAGE(H53:H55), 0) -> 7 | I52: =ROUNDUP(AVERAGE(I53:I55), 0) -> 10 | J52: =ROUNDUP(AVERAGE(J53:J55), 0) -> 14 | K52: =ROUNDUP(AVERAGE(K53:K55), 0) -> 20 | L52: =ROUNDUP(AVERAGE(L53:L55), 0) -> 27 | M52: =ROUNDUP(AVERAGE(M53:M55), 0) -> 38 | N52: =ROUNDUP(AVERAGE(N53:N55), 0) -> 53 | P52: Average | Q52: =ROUNDUP(AVERAGE(Q53:Q55), 0) -> 1 | R52: =ROUNDUP(AVERAGE(R53:R55), 0) -> 1 | S52: =ROUNDUP(AVERAGE(S53:S55), 0) -> 1 | T52: =ROUNDUP(AVERAGE(T53:T55), 0) -> 1 | U52: =ROUNDUP(AVERAGE(U53:U55), 0) -> 1 | V52: =ROUNDUP(AVERAGE(V53:V55), 0) -> 1 | W52: =ROUNDUP(AVERAGE(W53:W55), 0) -> 1 | X52: =ROUNDUP(AVERAGE(X53:X55), 0) -> 1 | ... AA52: =ROUNDUP(AVERAGE(AA53:AA55), 0) -> 1
E53: Peak | F53: 3 | G53: 3 | H53: 10 | I53: =+H53*1.4 -> 14 | J53: =+I53*1.4 -> 19.6 | K53: =+J53*1.4 -> 27.44 | L53: =+K53*1.4 -> 38.416 | M53: =+L53*1.4 -> 53.7824 | N53: =+M53*1.4 -> 75.29536 | P53: Peak | Q53: =AVERAGEIFS($E$25:$DG$25, $H$2:$DJ$2,$E$53, $H$1:$DJ$1, Q51) -> 0.0043859649 | R53: =AVERAGEIFS($E$25:$DG$25, $H$2:$DJ$2,$E$53, $H$1:$DJ$1, R51) -> 0.14732707 | S53: =AVERAGEIFS($E$25:$DG$25, $H$2:$DJ$2,$E$53, $H$1:$DJ$1, S51) -> 0.17455576 | T53: =AVERAGEIFS($E$25:$DG$25, $H$2:$DJ$2,$E$53, $H$1:$DJ$1, T51) -> 0.14178586 | U53: =AVERAGEIFS($E$25:$DG$25, $H$2:$DJ$2,$E$53, $H$1:$DJ$1, U51) -> 0.14178586 | V53: =AVERAGEIFS($E$25:$DG$25, $H$2:$DJ$2,$E$53, $H$1:$DJ$1, V51) -> 0.14178586 | W53: =AVERAGEIFS($E$25:$DG$25, $H$2:$DJ$2,$E$53, $H$1:$DJ$1, W51) -> 0.14178586 | X53: =AVERAGEIFS($E$25:$DG$25, $H$2:$DJ$2,$E$53, $H$1:$DJ$1, X51) -> 0.14178586 | ... AA53: =AVERAGEIFS($E$25:$DG$25, $H$2:$DJ$2,$E$53, $H$1:$DJ$1, AA51) -> 0.14178586
E54: Shoulder | F54: 5 | G54: =+F54+1 -> 6 | H54: 7 | I54: =+H54*1.4 -> 9.8 | J54: =+I54*1.4 -> 13.72 | K54: =+J54*1.4 -> 19.208 | L54: =+K54*1.4 -> 26.8912 | M54: =+L54*1.4 -> 37.64768 | N54: =+M54*1.4 -> 52.706752 | P54: Shoulder | Q54: =+AVERAGEIFS($E$25:$DG$25, $H$2:$DJ$2,$E$54, $H$1:$DJ$1, Q51) -> 0.025749014 | R54: =+AVERAGEIFS($E$25:$DG$25, $H$2:$DJ$2,$E$54, $H$1:$DJ$1, R51) -> 0.13132619 | S54: =+AVERAGEIFS($E$25:$DG$25, $H$2:$DJ$2,$E$54, $H$1:$DJ$1, S51) -> 0.15321598 | T54: =+AVERAGEIFS($E$25:$DG$25, $H$2:$DJ$2,$E$54, $H$1:$DJ$1, T51) -> 0.17713551 | U54: =+AVERAGEIFS($E$25:$DG$25, $H$2:$DJ$2,$E$54, $H$1:$DJ$1, U51) -> 0.17874904 | V54: =+AVERAGEIFS($E$25:$DG$25, $H$2:$DJ$2,$E$54, $H$1:$DJ$1, V51) -> 0.17874904 | W54: =+AVERAGEIFS($E$25:$DG$25, $H$2:$DJ$2,$E$54, $H$1:$DJ$1, W51) -> 0.17874904 | X54: =+AVERAGEIFS($E$25:$DG$25, $H$2:$DJ$2,$E$54, $H$1:$DJ$1, X51) -> 0.17874904 | ... AA54: =+AVERAGEIFS($E$25:$DG$25, $H$2:$DJ$2,$E$54, $H$1:$DJ$1, AA51) -> 0.17874904
E55: Trough | F55: 1 | G55: 1 | H55: 4 | I55: =+H55*1.4 -> 5.6 | J55: =+I55*1.4 -> 7.84 | K55: =+J55*1.4 -> 10.976 | L55: =+K55*1.4 -> 15.3664 | M55: =+L55*1.4 -> 21.51296 | N55: =+M55*1.4 -> 30.118144 | P55: Trough | Q55: =AVERAGEIFS($E$25:$DG$25, $H$2:$DJ$2,$E$55, $H$1:$DJ$1, Q51) -> 0.034989648 | R55: =AVERAGEIFS($E$25:$DG$25, $H$2:$DJ$2,$E$55, $H$1:$DJ$1, R51) -> 0.20889588 | S55: =AVERAGEIFS($E$25:$DG$25, $H$2:$DJ$2,$E$55, $H$1:$DJ$1, S51) -> 0.21383308 | T55: =AVERAGEIFS($E$25:$DG$25, $H$2:$DJ$2,$E$55, $H$1:$DJ$1, T51) -> 0.19488708 | U55: =AVERAGEIFS($E$25:$DG$25, $H$2:$DJ$2,$E$55, $H$1:$DJ$1, U51) -> 0.19488708 | V55: =AVERAGEIFS($E$25:$DG$25, $H$2:$DJ$2,$E$55, $H$1:$DJ$1, V51) -> 0.19488708 | W55: =AVERAGEIFS($E$25:$DG$25, $H$2:$DJ$2,$E$55, $H$1:$DJ$1, W51) -> 0.19488708 | X55: =AVERAGEIFS($E$25:$DG$25, $H$2:$DJ$2,$E$55, $H$1:$DJ$1, X51) -> 0.19488708 | ... AA55: =AVERAGEIFS($E$25:$DG$25, $H$2:$DJ$2,$E$55, $H$1:$DJ$1, AA51) -> 0.19488708
E56: Trough | F56: =F55/F52-1 -> -0.66666667 | G56: =G55/G52-1 -> -0.75 | H56: =H55/H52-1 -> -0.42857143 | I56: =I55/I52-1 -> -0.44 | J56: =J55/J52-1 -> -0.44 | K56: =K55/K52-1 -> -0.4512 | L56: =L55/L52-1 -> -0.43087407 | M56: =M55/M52-1 -> -0.43386947 | N56: =N55/N52-1 -> -0.43173313 | P56: Trough | Q56: =Q55/Q52-1 -> -0.96501035 | R56: =R55/R52-1 -> -0.79110412 | S56: =S55/S52-1 -> -0.78616692 | T56: =T55/T52-1 -> -0.80511292 | U56: =U55/U52-1 -> -0.80511292 | V56: =V55/V52-1 -> -0.80511292 | W56: =W55/W52-1 -> -0.80511292 | X56: =X55/X52-1 -> -0.80511292 | ... AA56: =AA55/AA52-1 -> -0.80511292
E57: Shoulder | F57: =F54/F52-1 -> 0.66666667 | G57: =G54/G52-1 -> 0.5 | H57: =H54/H52-1 -> 0 | I57: =I54/I52-1 -> -0.02 | J57: =J54/J52-1 -> -0.02 | K57: =K54/K52-1 -> -0.0396 | L57: =L54/L52-1 -> -0.0040296296 | M57: =M54/M52-1 -> -0.0092715789 | N57: =N54/N52-1 -> -0.0055329811 | P57: Shoulder | Q57: =Q54/Q52-1 -> -0.97425099 | R57: =R54/R52-1 -> -0.86867381 | S57: =S54/S52-1 -> -0.84678402 | T57: =T54/T52-1 -> -0.82286449 | U57: =U54/U52-1 -> -0.82125096 | V57: =V54/V52-1 -> -0.82125096 | W57: =W54/W52-1 -> -0.82125096 | X57: =X54/X52-1 -> -0.82125096 | ... AA57: =AA54/AA52-1 -> -0.82125096
B60: 50000 Subcontractors
B61: 51000 Subcontractors - Tutors | AH61: 150 | AI61: 740 | AJ61: 817.5 | AK61: 937.5 | AL61: 170 | AN61: 0 | AO61: 450 | AP61: 0 | AQ61: 0 | AR61: 270 | AS61: 0 | AT61: 1042.5 | AU61: 450 | AV61: =3989.94 -> 3989.94 | AW61: =6135 -> 6135 | AX61: =+'People Plan'!Y19 -> 0 | AY61: =+'People Plan'!Z19 -> 959.95423 | AZ61: =+'People Plan'!AA19 -> 2840.0018 | BA61: =+'People Plan'!AB19 -> 4849.8393 | BB61: =+'People Plan'!AC19 -> 7164.875 | BC61: =+'People Plan'!AD19 -> 1872.4348 | BD61: =+'People Plan'!AE19 -> 6399.6636 | BE61: =+'People Plan'!AF19 -> 577.58857 | ... DG61: =+'People Plan'!CH19 -> 13154.483
B62: 51000 Subcontractors - Interns | AH62: 450 | AI62: 150 | AM62: 599 | AN62: 0 | AO62: 0 | AP62: 0 | AQ62: 0 | AR62: 0 | AS62: 0 | AT62: 540 | AU62: 234 | AV62: =86.8 -> 86.8 | AW62: =120 -> 120 | AX62: =+'People Plan'!Y7 -> 0 | AY62: =+'People Plan'!Z7 -> 0 | AZ62: =+'People Plan'!AA7 -> 0 | BA62: =+'People Plan'!AB7 -> 0 | BB62: =+'People Plan'!AC7 -> 0 | BC62: =+'People Plan'!AD7 -> 0 | BD62: =+'People Plan'!AE7 -> 0 | BE62: =+'People Plan'!AF7 -> 0 | ... DG62: =+'People Plan'!CH7 -> 0
B63: Total 50000 Subcontractors | AB63: =SUM(AB61:AB62) -> 0 | AC63: =SUM(AC61:AC62) -> 0 | AD63: =SUM(AD61:AD62) -> 0 | AE63: =SUM(AE61:AE62) -> 0 | AF63: =SUM(AF61:AF62) -> 0 | AG63: =SUM(AG61:AG62) -> 0 | AH63: =SUM(AH61:AH62) -> 600 | AI63: =SUM(AI61:AI62) -> 890 | ... AS63: =SUM(AS61:AS62) -> 0 | AT63: =SUM(AT60:AT62) -> 1582.5 | AU63: =SUM(AU60:AU62) -> 684 | AV63: =SUM(AV60:AV62) -> 4076.74 | AW63: =SUM(AW60:AW62) -> 6255 | AX63: =SUM(AX61:AX62) -> 0 | AY63: =SUM(AY61:AY62) -> 959.95423 | AZ63: =SUM(AZ61:AZ62) -> 2840.0018 | BA63: =SUM(BA61:BA62) -> 4849.8393 | BB63: =SUM(BB61:BB62) -> 7164.875 | BC63: =SUM(BC61:BC62) -> 1872.4348 | BD63: =SUM(BD61:BD62) -> 6399.6636 | BE63: =SUM(BE61:BE62) -> 577.58857 | ... DG63: =SUM(DG61:DG62) -> 13154.483
B64: Gross Profit | D64: =(D14)-(0) -> 0 | E64: =(E14)-(0) -> 0 | F64: =(F14)-(0) -> 0 | G64: =(G14)-(0) -> 0 | H64: =(H14)-(0) -> 0 | I64: =(I14)-(0) -> 0 | J64: =(J14)-(0) -> 0 | K64: =K14 -> 375 | L64: =L14 -> 1075 | M64: =M14 -> 3765 | N64: =N14 -> 2090 | O64: =O14 -> 2032.5 | P64: =P14 -> 1545.99 | Q64: =Q14 -> 1255.75 | R64: =R14 -> 1206.75 | ... AA64: =AA14 -> 2144.5 | AB64: =AB14-AB63 -> 3002 | AC64: =AC14-AC63 -> 4357.5 | AD64: =AD14-AD63 -> 3479.5 | AE64: =AE14-AE63 -> 4018 | AF64: =AF14-AF63 -> 5420.08 | AG64: =AG14-AG63 -> 4308.26 | AH64: =AH14-AH63 -> 8460.89 | AI64: =AI14-AI63 -> 13221.26 | ... DG64: =DG14-DG63 -> 68483.918
C65: GP % | E65: =+E51/8 -> 0 | F65: =+F51/8 -> 252.75 | G65: =+G51/8 -> 252.875 | H65: =+H51/8 -> 253 | I65: =+I51/8 -> 253.125 | J65: =+J51/8 -> 253.25 | K65: =+K51/8 -> 253.375 | L65: =+L51/8 -> 253.5 | ... O65: =+O51/8 -> 0 | P65: =+P64/#REF! -> #REF! | Q65: =+Q64/#REF! -> #REF! | R65: =+R64/#REF! -> #REF! | S65: =+S64/#REF! -> #REF! | T65: =+T64/#REF! -> #REF! | U65: =+U64/#REF! -> #REF! | V65: =+V64/#REF! -> #REF! | W65: =+W64/#REF! -> #REF! | ... AA65: =+AA64/#REF! -> #REF! | AB65: =+AB64/AB14 -> 1 | AC65: =+AC64/AC14 -> 1 | AD65: =+AD64/AD14 -> 1 | AE65: =+AE64/AE14 -> 1 | AF65: =+AF64/AF14 -> 1 | AG65: =+AG64/AG14 -> 1 | AH65: =+AH64/AH14 -> 0.93378134 | AI65: =+AI64/AI14 -> 0.9369298 | ... DG65: =+DG64/DG14 -> 0.83886893
B67: Expenses
B68: 30000 Sales & Marketing Expenses
B69: 30200 Events/Sponsorships | AC69: 1179.44 | AE69: 2400 | AG69: 665.56 | AH69: 0 | AI69: 0 | AJ69: 0 | AK69: 0 | AL69: 0 | AM69: 0 | AN69: 0 | AO69: 0 | AP69: 0 | AQ69: 0 | AR69: 0 | AS69: 0 | AT69: 0 | AU69: 0 | AV69: 0 | AW69: 0 | AX69: =+IF(AX3<>AW3, SUM(AU69:AW69), 0)*1.1 -> 0 | AY69: =+IF(AY3<>AX3, SUM(AV69:AX69), 0)*1.1 -> 0 | AZ69: =+IF(AZ3<>AY3, SUM(AW69:AY69), 0)*1.1 -> 0 | BA69: =+IF(BA3<>AZ3, SUM(AX69:AZ69), 0)*1.1 -> 0 | BB69: =+IF(BB3<>BA3, SUM(AY69:BA69), 0)*1.1 -> 0 | BC69: =+IF(BC3<>BB3, SUM(AZ69:BB69), 0)*1.1 -> 0 | BD69: =+IF(BD3<>BC3, SUM(BA69:BC69), 0)*1.1 -> 0 | BE69: =+IF(BE3<>BD3, SUM(BB69:BD69), 0)*1.1 -> 0 | ... DG69: =+IF(DG3<>DF3, SUM(DD69:DF69), 0)*1.1 -> 0
B70: Total Sales & Marketing Expenses | P70: =SUM(P69) -> 0 | Q70: =SUM(Q69) -> 0 | R70: =SUM(R69) -> 0 | S70: =SUM(S69) -> 0 | T70: =SUM(T69) -> 0 | U70: =SUM(U69) -> 0 | V70: =SUM(V69) -> 0 | W70: =SUM(W69) -> 0 | ... DG70: =SUM(DG69) -> 0
B72: 60000 G&A Expenses
B73: 60000 General & Administrative Expenses
B74: Owner Salary | AN74: 1275 | AO74: 4005 | AP74: 4410 | AQ74: 2450 | AR74: 1960 | AS74: 2450 | AT74: 7280 | AU74: 14252.7 | AV74: =9800 -> 9800 | AW74: =14350 -> 14350 | AX74: =+'People Plan'!Z18 -> 11900 | AY74: =+'People Plan'!AA18 -> 11900 | AZ74: =+'People Plan'!AB18 -> 11900 | BA74: =+'People Plan'!AC18 -> 11900 | BB74: =+'People Plan'!AD18 -> 11900 | BC74: =+'People Plan'!AE18 -> 11900 | BD74: =+'People Plan'!AF18 -> 11900 | BE74: =+'People Plan'!AG18 -> 11900 | ... DG74: =+'People Plan'!CI18 -> 11900
B75: Owner Payroll Taxes | AN75: 137.07 | AO75: 435.82 | AP75: 416.3 | AQ75: 187.43 | AR75: 149.94 | AS75: 187.42 | AT75: 150.77 | AU75: 833.44 | AV75: =749.7 -> 749.7 | AW75: =1097.77 -> 1097.77 | AX75: =+AX74*AX79 -> 910.35 | AY75: =+AY74*AY79 -> 910.35 | AZ75: =+AZ74*AZ79 -> 910.35 | BA75: =+BA74*BA79 -> 910.35 | BB75: =+BB74*BB79 -> 910.35 | BC75: =+BC74*BC79 -> 910.35 | BD75: =+BD74*BD79 -> 910.35 | BE75: =+BE74*BE79 -> 910.35 | ... DG75: =+DG74*DG79 -> 910.35
B76: Owner Benefits | AN76: 0 | AO76: 0 | AP76: 0 | AQ76: 0 | AR76: 0 | AS76: 0 | AT76: 0 | AU76: 0 | AV76: 0 | AW76: 0 | AX76: =+AX74*AX80 -> 0 | AY76: =+AY74*AY80 -> 0 | AZ76: =+AZ74*AZ80 -> 0 | BA76: =+BA74*BA80 -> 0 | BB76: =+BB74*BB80 -> 0 | BC76: =+BC74*BC80 -> 0 | BD76: =+BD74*BD80 -> 0 | BE76: =+BE74*BE80 -> 0 | ... DG76: =+DG74*DG80 -> 2380
B77: Owner Reimbursements | AN77: 995.35 | AO77: 615 | AP77: 0 | AQ77: 0 | AR77: 0 | AS77: 0 | AT77: 0 | AU77: 0 | AV77: 0 | AW77: 0 | AX77: 0 | AY77: =+AX77 -> 0 | AZ77: =+AY77 -> 0 | BA77: =+AZ77 -> 0 | BB77: =+BA77 -> 0 | BC77: =+BB77 -> 0 | BD77: =+BC77 -> 0 | BE77: =+BD77 -> 0 | BF77: =+BE77 -> 0 | ... DG77: =+DF77 -> 0
B78: Total Owner Payroll Burden | AH78: =SUM(AH74:AH76) -> 0 | AI78: =SUM(AI74:AI76) -> 0 | AJ78: =SUM(AJ74:AJ76) -> 0 | AK78: =SUM(AK74:AK76) -> 0 | AL78: =SUM(AL74:AL76) -> 0 | AM78: =SUM(AM74:AM76) -> 0 | AN78: =SUM(AN74:AN77) -> 2407.42 | AO78: =SUM(AO74:AO77) -> 5055.82 | AP78: =SUM(AP74:AP77) -> 4826.3 | AQ78: =SUM(AQ74:AQ77) -> 2637.43 | AR78: =SUM(AR74:AR77) -> 2109.94 | AS78: =SUM(AS74:AS77) -> 2637.42 | AT78: =SUM(AT74:AT77) -> 7430.77 | AU78: =SUM(AU74:AU77) -> 15086.14 | ... DG78: =SUM(DG74:DG77) -> 15190.35
C79: Payroll Tax as a % of Salary | AN79: =+AN75/AN74 -> 0.10750588 | AO79: =+AO75/AO74 -> 0.10881898 | AP79: =+AP75/AP74 -> 0.094399093 | AQ79: =+AQ75/AQ74 -> 0.076502041 | AR79: =+AR75/AR74 -> 0.0765 | AS79: =+AS75/AS74 -> 0.076497959 | AT79: =+AT75/AT74 -> 0.020710165 | AU79: =+AU75/AU74 -> 0.058475938 | ... AW79: =+AW75/AW74 -> 0.076499652 | AX79: 0.0765 | AY79: =+AX79 -> 0.0765 | AZ79: =+AY79 -> 0.0765 | BA79: =+AZ79 -> 0.0765 | BB79: =+BA79 -> 0.0765 | BC79: =+BB79 -> 0.0765 | BD79: =+BC79 -> 0.0765 | BE79: =+BD79 -> 0.0765 | BF79: =+BE79 -> 0.0765 | ... DG79: =+DF79 -> 0.0765
C80: Benefits as a % of Salary | AX80: 0 | AY80: =+AX80 -> 0 | AZ80: =+AY80 -> 0 | BA80: =+AZ80 -> 0 | BB80: =+BA80 -> 0 | BC80: =+BB80 -> 0 | BD80: =+BC80 -> 0 | BE80: =+BD80 -> 0 | BF80: =+BE80 -> 0 | ... BW80: =+BV80 -> 0 | BX80: 0.15 | BY80: =+BX80 -> 0.15 | BZ80: =+BY80 -> 0.15 | CA80: =+BZ80 -> 0.15 | CB80: =+CA80 -> 0.15 | CC80: =+CB80 -> 0.15 | CD80: =+CC80 -> 0.15 | CE80: =+CD80 -> 0.15 | CF80: =+CE80 -> 0.15 | ... CI80: =+CH80 -> 0.15 | CJ80: 0.2 | CK80: =+CJ80 -> 0.2 | CL80: =+CK80 -> 0.2 | CM80: =+CL80 -> 0.2 | CN80: =+CM80 -> 0.2 | CO80: =+CN80 -> 0.2 | CP80: =+CO80 -> 0.2 | CQ80: =+CP80 -> 0.2 | CR80: =+CQ80 -> 0.2 | ... DG80: =+DF80 -> 0.2
B81: 60210 Website Services | Y81: 300 | AA81: 300 | AI81: 0 | AJ81: 0 | AK81: 0 | AL81: 0 | AM81: 0 | AN81: 0 | AO81: 0 | AP81: 0 | AQ81: 0 | AR81: 0 | AS81: 0 | AT81: 0 | AU81: 0 | AV81: 0 | AW81: 0 | AX81: 0 | AY81: =AX81 -> 0 | AZ81: =AVERAGE(AT81:AY81)*1.2 -> 0 | BA81: =AZ81 -> 0 | BB81: =BA81 -> 0 | BC81: =BB81 -> 0 | BD81: =BC81 -> 0 | BE81: =BD81 -> 0 | BF81: =BE81 -> 0 | BG81: =BF81 -> 0 | BH81: =BG81 -> 0 | ... BK81: =BJ81 -> 0 | BL81: =AVERAGE(BF81:BK81)*1.2 -> 0 | BM81: =BL81 -> 0 | BN81: =BM81 -> 0 | BO81: =BN81 -> 0 | BP81: =BO81 -> 0 | BQ81: =BP81 -> 0 | BR81: =BQ81 -> 0 | BS81: =BR81 -> 0 | BT81: =BS81 -> 0 | ... BW81: =BV81 -> 0 | BX81: =AVERAGE(BR81:BW81)*1.2 -> 0 | BY81: =BX81 -> 0 | BZ81: =BY81 -> 0 | CA81: =BZ81 -> 0 | CB81: =CA81 -> 0 | CC81: =CB81 -> 0 | CD81: =CC81 -> 0 | CE81: =CD81 -> 0 | CF81: =CE81 -> 0 | ... CI81: =CH81 -> 0 | CJ81: =AVERAGE(CD81:CI81)*1.2 -> 0 | CK81: =CJ81 -> 0 | CL81: =CK81 -> 0 | CM81: =CL81 -> 0 | CN81: =CM81 -> 0 | CO81: =CN81 -> 0 | CP81: =CO81 -> 0 | CQ81: =CP81 -> 0 | CR81: =CQ81 -> 0 | ... CU81: =CT81 -> 0 | CV81: =AVERAGE(CP81:CU81)*1.2 -> 0 | CW81: =CV81 -> 0 | CX81: =CW81 -> 0 | CY81: =CX81 -> 0 | CZ81: =CY81 -> 0 | DA81: =CZ81 -> 0 | DB81: =DA81 -> 0 | DC81: =DB81 -> 0 | DD81: =DC81 -> 0 | ... DG81: =DF81 -> 0
B82: 60100 Travel | AH82: 13.59 | AI82: 15.71 | AR82: 44.17 | AS82: 49.63 | AT82: 126.3 | AU82: 417.97 | AV82: 0 | AW82: =222.44 -> 222.44 | AX82: 75 | AY82: =AX82 -> 75 | AZ82: =AY82 -> 75 | BA82: =AZ82 -> 75 | BB82: =BA82 -> 75 | BC82: =BB82 -> 75 | BD82: =BC82 -> 75 | BE82: =BD82 -> 75 | BF82: =BE82 -> 75 | ... DG82: =DF82 -> 75
B83: 60200 Computer & Software Expenses | D83: =0 -> 0 | E83: =0 -> 0 | F83: =0 -> 0 | G83: =0 -> 0 | H83: =0 -> 0 | I83: =0 -> 0 | J83: 0 | K83: 0 | L83: 12 | M83: 271.2 | N83: 12 | O83: 12 | P83: 12 | Q83: 12 | R83: 12 | S83: 12 | T83: 53 | U83: 156 | V83: 12 | W83: 12 | X83: 240.91 | Y83: 352.91 | Z83: 28.91 | AA83: 28.91 | AB83: 78.91 | AC83: 28.91 | AD83: 86.19 | AE83: 12 | AF83: 154.47 | AG83: 310.12 | AH83: 1251.13 | AI83: 14.81 | AJ83: 76.75 | AK83: 90.81 | AL83: 100.41 | AM83: 107.82 | AN83: 218.17 | AO83: 118.63 | AP83: 118.81 | AQ83: 202.32 | AR83: 241.38 | AS83: 433.68 | AT83: 209.45 | AU83: 336.39 | AV83: =843.04 -> 843.04 | AW83: =709.4 -> 709.4 | AX83: 150 | AY83: =AX83 -> 150 | AZ83: =AVERAGE(AT83:AY83)*1.2 -> 479.656 | BA83: =AZ83 -> 479.656 | BB83: =BA83 -> 479.656 | BC83: =BB83 -> 479.656 | BD83: =BC83 -> 479.656 | BE83: =BD83 -> 479.656 | BF83: =BE83 -> 479.656 | BG83: =BF83 -> 479.656 | BH83: =BG83 -> 479.656 | ... BK83: =BJ83 -> 479.656 | BL83: =AVERAGE(BF83:BK83)*1.2 -> 575.5872 | BM83: =BL83 -> 575.5872 | BN83: =BM83 -> 575.5872 | BO83: =BN83 -> 575.5872 | BP83: =BO83 -> 575.5872 | BQ83: =BP83 -> 575.5872 | BR83: =BQ83 -> 575.5872 | BS83: =BR83 -> 575.5872 | BT83: =BS83 -> 575.5872 | ... BW83: =BV83 -> 575.5872 | BX83: =AVERAGE(BR83:BW83)*1.2 -> 690.70464 | BY83: =BX83 -> 690.70464 | BZ83: =BY83 -> 690.70464 | CA83: =BZ83 -> 690.70464 | CB83: =CA83 -> 690.70464 | CC83: =CB83 -> 690.70464 | CD83: =CC83 -> 690.70464 | CE83: =CD83 -> 690.70464 | CF83: =CE83 -> 690.70464 | ... CI83: =CH83 -> 690.70464 | CJ83: =AVERAGE(CD83:CI83)*1.2 -> 828.84557 | CK83: =CJ83 -> 828.84557 | CL83: =CK83 -> 828.84557 | CM83: =CL83 -> 828.84557 | CN83: =CM83 -> 828.84557 | CO83: =CN83 -> 828.84557 | CP83: =CO83 -> 828.84557 | CQ83: =CP83 -> 828.84557 | CR83: =CQ83 -> 828.84557 | ... CU83: =CT83 -> 828.84557 | CV83: =AVERAGE(CP83:CU83)*1.2 -> 994.61468 | CW83: =CV83 -> 994.61468 | CX83: =CW83 -> 994.61468 | CY83: =CX83 -> 994.61468 | CZ83: =CY83 -> 994.61468 | DA83: =CZ83 -> 994.61468 | DB83: =DA83 -> 994.61468 | DC83: =DB83 -> 994.61468 | DD83: =DC83 -> 994.61468 | ... DG83: =DF83 -> 994.61468
B84: 60300 Donations/Gifts | D84: =0 -> 0 | E84: =0 -> 0 | F84: =0 -> 0 | G84: =0 -> 0 | H84: =0 -> 0 | I84: =0 -> 0 | J84: 0 | K84: 0 | L84: 0 | M84: 50 | N84: 250 | O84: 0 | X84: 150 | Z84: 430 | AD84: 50 | AF84: 141.19 | AJ84: 80 | AK84: 65 | AL84: 387.9 | AM84: 45 | AN84: 485 | AO84: 424 | AP84: 152.63 | AR84: 346.05 | AS84: 100 | AT84: 79.04 | AV84: =574.22 -> 574.22 | AW84: =150.39 -> 150.39 | AX84: 100 | AY84: =AX84 -> 100 | AZ84: =AY84 -> 100 | BA84: =AZ84 -> 100 | BB84: =BA84 -> 100 | BC84: =BB84 -> 100 | BD84: =BC84 -> 100 | BE84: =BD84 -> 100 | BF84: =BE84 -> 100 | ... DG84: =DF84 -> 100
B85: 60400 Fees/Subscriptions | D85: =0 -> 0 | E85: =0 -> 0 | F85: =0 -> 0 | G85: =0 -> 0 | H85: =0 -> 0 | I85: =0 -> 0 | J85: 0 | K85: 0 | L85: 15 | M85: 19 | N85: 0 | O85: 0 | Y85: 13.86 | AI85: 42.58 | AQ85: 0 | AR85: 0 | AS85: 0 | AT85: 0 | AU85: 0 | AV85: 0 | AW85: 0 | AX85: =AVERAGE(AO85:AW85) -> 0 | AY85: =AX85 -> 0 | AZ85: =AY85 -> 0 | BA85: =AZ85 -> 0 | BB85: =BA85 -> 0 | BC85: =BB85 -> 0 | BD85: =BC85 -> 0 | BE85: =BD85 -> 0 | BF85: =BE85 -> 0 | ... DG85: =DF85 -> 0
B86: 60500 Finance & Accounting | D86: =0 -> 0 | E86: =0 -> 0 | F86: =0 -> 0 | G86: =0 -> 0 | H86: =0 -> 0 | I86: =0 -> 0 | J86: 0 | K86: 0 | L86: 0 | M86: 279.6 | N86: 75 | O86: 75 | P86: 75 | Q86: 75 | S86: 75 | T86: 165 | U86: 225 | V86: 75 | W86: 75 | X86: 225 | Y86: 75 | Z86: 75 | AA86: 225 | AB86: 75 | AC86: 112.5 | AD86: 225 | AE86: 75 | AF86: 75 | AG86: 225 | AH86: 185 | AI86: 207.5 | AJ86: 208.75 | AK86: 350 | AL86: 241.25 | AM86: 140 | AN86: 711.25 | AO86: 412.5 | AP86: 1155.73 | AQ86: 415 | AR86: 356.25 | AS86: 281.25 | AT86: 450 | AU86: 453.75 | AV86: 337.5 | AW86: =581.25 -> 581.25 | AX86: =IF(AX3<>AW3, 450, 275)+150 -> 425 | AY86: =IF(AY3<>AX3, 450, 275) -> 275 | AZ86: =IF(AZ3<>AY3, 450, 275) -> 450 | BA86: =IF(BA3<>AZ3, 450, 275) -> 275 | BB86: =IF(BB3<>BA3, 450, 275) -> 275 | BC86: =IF(BC3<>BB3, 450, 275) -> 450 | BD86: =IF(BD3<>BC3, 450, 275) -> 275 | BE86: =IF(BE3<>BD3, 450, 275) -> 275 | BF86: =IF(BF3<>BE3, 450, 275) -> 450 | ... DG86: =IF(DG3<>DF3, 450, 275) -> 275
B87: 60600 Bank Fees | D87: =0 -> 0 | E87: =0 -> 0 | F87: =0 -> 0 | G87: =0 -> 0 | H87: =0 -> 0 | I87: =0 -> 0 | J87: 0 | K87: 0 | L87: 0 | M87: 26.86 | N87: 105.23 | O87: 22.43 | P87: 118.13 | Q87: 36.76 | R87: 63.36 | S87: 153.85 | T87: 72.88 | U87: 27.48 | V87: 17.2 | W87: 33.76 | X87: 48.31 | Y87: 29 | Z87: 29 | AD87: 1.75 | AE87: 4.55 | AF87: 3.5 | AH87: 31.6 | AK87: 29 | AP87: =52 -> 52 | AQ87: 0 | AR87: 0 | AS87: 0 | AT87: 0 | AU87: 0 | AV87: 2 | AW87: =80.44 -> 80.44 | AX87: =AVERAGE(AR87:AW87) -> 13.74 | AY87: =AX87 -> 13.74 | AZ87: =AY87 -> 13.74 | BA87: =AZ87 -> 13.74 | BB87: =BA87 -> 13.74 | BC87: =BB87 -> 13.74 | BD87: =BC87 -> 13.74 | BE87: =BD87 -> 13.74 | BF87: =BE87 -> 13.74 | ... DG87: =DF87 -> 13.74
B88: 60700 Meals and Entertainment | T88: 22 | AH88: 218.02 | AI88: 57.06 | AJ88: 44.41 | AL88: 837.07 | AN88: 50 | AO88: 251.46 | AR88: 285.65 | AS88: 315.29 | AT88: 326.19 | AU88: 484.06 | AV88: 383.29 | AW88: =677.01 -> 677.01 | AX88: =AVERAGE(AR88:AW88) -> 411.915 | AY88: =AX88 -> 411.915 | AZ88: =AY88 -> 411.915 | BA88: =AZ88 -> 411.915 | BB88: =BA88 -> 411.915 | BC88: =BB88 -> 411.915 | BD88: =BC88 -> 411.915 | BE88: =BD88 -> 411.915 | BF88: =BE88 -> 411.915 | ... DG88: =DF88 -> 411.915
B89: 60800 QB Fees | D89: 0 | E89: 0 | F89: 0 | G89: 0 | H89: 0 | I89: 0 | J89: 0 | K89: 0 | L89: 0 | M89: 0 | N89: 30 | O89: 52.67 | P89: 30 | Q89: 30 | R89: 30 | S89: 31.99 | T89: 45.38 | U89: 51.04 | V89: 92.49 | W89: 194.71 | X89: 210.47 | Y89: 313.34 | Z89: 205.12 | AA89: 105.16 | AB89: 124.93 | AC89: 156.19 | AD89: 141.67 | AE89: 145.28 | AF89: 173.37 | AG89: 236.32 | AH89: 228.28 | AI89: 404.2 | AJ89: 334.27 | AK89: 523.21 | AL89: 315.97 | AM89: 199.98 | AN89: 229.96 | AO89: 281.21 | AP89: 303.5 | AQ89: 167.72 | AR89: 171.91 | AS89: 212.1 | AT89: 440.63 | AU89: 658.74 | AV89: 666.46 | AW89: =921.67 -> 921.67 | AX89: =+AX99*AX12 -> 336.40261 | AY89: =+AY99*AY12 -> 474.87423 | AZ89: =+AZ99*AZ12 -> 563.78086 | BA89: =+BA99*BA12 -> 530.06464 | BB89: =+BB99*BB12 -> 542.35505 | BC89: =+BC99*BC12 -> 240.57099 | BD89: =+BD99*BD12 -> 415.70285 | BE89: =+BE99*BE12 -> 354.39829 | ... DG89: =+DG99*DG12 -> 2148.5575
B90: 60900 Professional/Legal Fees | D90: =0 -> 0 | E90: =0 -> 0 | F90: =0 -> 0 | G90: =0 -> 0 | H90: =0 -> 0 | I90: =0 -> 0 | J90: 0 | K90: 0 | L90: 0 | M90: 1150 | N90: 0 | O90: 0 | U90: 50 | V90: 55 | W90: 200 | X90: 633.5 | AI90: 490 | AK90: 262.5 | AP90: =707 -> 707 | AQ90: 235.5 | AT90: 275 | AU90: 88 | AX90: =AVERAGE(AR90:AW90) -> 181.5 | AY90: =+AM90 -> 0 | AZ90: =+AN90 -> 0 | BA90: =+AO90 -> 0 | BB90: =+AP90 -> 707 | BC90: =+AQ90 -> 235.5 | BD90: =+AR90 -> 0 | BE90: =+AS90 -> 0 | BF90: =+AT90 -> 275 | ... DG90: =+CU90 -> 0
B91: 61100 Utilities | T91: 192.74 | U91: 137.74 | V91: 181.07 | W91: 286.48 | X91: 138.17 | Y91: 263.36 | Z91: 138.4 | AA91: 138.4 | AB91: 138.4 | AC91: 138.42 | AD91: 138.42 | AE91: 145.97 | AF91: 142.42 | AG91: 142.42 | AH91: 219.14 | AI91: 164.46 | AJ91: 134.46 | AK91: 260.35 | AL91: 157.41 | AM91: 127.41 | AN91: 128.5 | AO91: 155.68 | AP91: 123.02 | AQ91: 123.02 | AR91: 123.01 | AS91: 123.01 | AT91: 123.01 | AU91: 122.99 | AV91: 161.99 | AW91: =155.86 -> 155.86 | AX91: =+AW91 -> 155.86 | AY91: =+AX91 -> 155.86 | AZ91: =+AY91 -> 155.86 | BA91: =+AZ91 -> 155.86 | BB91: =+BA91 -> 155.86 | BC91: =+BB91 -> 155.86 | BD91: =+BC91 -> 155.86 | BE91: =+BD91 -> 155.86 | ... DG91: =+DF91 -> 155.86
B92: 61200 Taxes/Licenses | W92: 50 | AD92: 300 | AI92: 50 | AR92: 0 | AS92: 0 | AT92: 50 | AX92: =AVERAGE(AO92:AW92) -> 16.666667 | AY92: =+AX92 -> 16.666667 | AZ92: =+AY92 -> 16.666667 | BA92: =+AZ92 -> 16.666667 | BB92: =+BA92 -> 16.666667 | BC92: =+BB92 -> 16.666667 | BD92: =+BC92 -> 16.666667 | BE92: =+BD92 -> 16.666667 | BF92: =+BE92 -> 16.666667 | ... DG92: =+DF92 -> 16.666667
B93: Total G&A Expenses | D93: =SUM(D83:D90) -> 0 | E93: =SUM(E83:E90) -> 0 | F93: =SUM(F83:F90) -> 0 | G93: =SUM(G83:G90) -> 0 | H93: =SUM(H83:H90) -> 0 | I93: =SUM(I83:I90) -> 0 | J93: =SUM(J83:J90) -> 0 | K93: =SUM(K83:K90) -> 0 | ... O93: =SUM(O83:O90) -> 162.1 | P93: =SUM(P83:P92) -> 235.13 | Q93: =SUM(Q83:Q92) -> 153.76 | R93: =SUM(R83:R92) -> 105.36 | S93: =SUM(S83:S92) -> 272.84 | T93: =SUM(T83:T92) -> 551 | U93: =SUM(U83:U92) -> 647.26 | V93: =SUM(V83:V92) -> 432.76 | W93: =SUM(W83:W92) -> 851.95 | X93: =SUM(X83:X92) -> 1646.36 | Y93: =SUM(Y72:Y92) -> 1347.47 | Z93: =SUM(Z72:Z92) -> 906.43 | AA93: =SUM(AA72:AA92) -> 797.47 | AB93: =SUM(AB72:AB92) -> 417.24 | AC93: =SUM(AC72:AC92) -> 436.02 | AD93: =SUM(AD72:AD92) -> 943.03 | AE93: =SUM(AE72:AE92) -> 382.8 | AF93: =SUM(AF72:AF92) -> 689.95 | ... AM93: =SUM(AM72:AM92) -> 620.21 | AN93: =SUM(AN81:AN92)+AN78 -> 4230.3 | AO93: =SUM(AO81:AO92)+AO78 -> 6699.3 | AP93: =SUM(AP81:AP92)+AP78 -> 7438.99 | AQ93: =SUM(AQ81:AQ92)+AQ78 -> 3780.99 | AR93: =SUM(AR81:AR92)+AR78 -> 3678.36 | AS93: =SUM(AS81:AS92)+AS78 -> 4152.38 | AT93: =SUM(AT81:AT92)+AT78 -> 9510.39 | AU93: =SUM(AU81:AU92)+AU78 -> 17648.04 | ... DG93: =SUM(DG81:DG92)+DG78 -> 19381.704
B94: 61000 Owner Guarenteed Payments | D94: 0 | E94: 0 | F94: 0 | G94: 0 | H94: 0 | I94: 0 | AB94: =AA94 -> 0 | AC94: =AB94 -> 0 | AD94: =AC94 -> 0 | AE94: =AD94 -> 0 | AF94: =AE94 -> 0 | AG94: =AF94 -> 0 | AH94: =AG94 -> 0 | AI94: =AH94 -> 0 | ... DG94: =DF94 -> 0
B95: Total Expenses | D95: =SUM(D93:D94) -> 0 | E95: =SUM(E93:E94) -> 0 | F95: =SUM(F93:F94) -> 0 | G95: =SUM(G93:G94) -> 0 | H95: =SUM(H93:H94) -> 0 | I95: =SUM(I93:I94) -> 0 | J95: =SUM(J93:J94) -> 0 | K95: =SUM(K93:K94) -> 0 | ... DG95: =SUM(DG93:DG94) -> 19381.704
B96: Total Operating Expenses | P96: =+P93+P70 -> 235.13 | Q96: =+Q93+Q70 -> 153.76 | R96: =+R93+R70 -> 105.36 | S96: =+S93+S70 -> 272.84 | T96: =+T93+T70 -> 551 | U96: =+U93+U70 -> 647.26 | V96: =+V93+V70 -> 432.76 | W96: =+W93+W70 -> 851.95 | ... DG96: =+DG93+DG70 -> 19381.704
B97: Net Operating Income | D97: =D64-D95 -> 0 | E97: =E64-E95 -> 0 | F97: =F64-F95 -> 0 | G97: =G64-G95 -> 0 | H97: =H64-H95 -> 0 | I97: =I64-I95 -> 0 | J97: =J64-J95 -> 0 | K97: =K64-K95 -> 375 | ... O97: =O64-O95 -> 1870.4 | P97: =P64-P96 -> 1310.86 | Q97: =Q64-Q96 -> 1101.99 | R97: =R64-R96 -> 1101.39 | S97: =S64-S96 -> 1684.57 | T97: =T64-T96 -> 1935.93 | U97: =U64-U96 -> 1396.17 | V97: =V64-V96 -> 2402.74 | W97: =W64-W96 -> 6226.71 | ... DG97: =DG64-DG96 -> 49102.214
C98: NOI % | E98: =+E84/8 -> 0 | F98: =+F84/8 -> 0 | G98: =+G84/8 -> 0 | H98: =+H84/8 -> 0 | I98: =+I84/8 -> 0 | J98: =+J84/8 -> 0 | K98: =+K84/8 -> 0 | L98: =+L84/8 -> 0 | ... O98: =+O84/8 -> 0 | P98: =+P97/P14 -> 0.84790975 | Q98: =+Q97/Q14 -> 0.87755525 | R98: =+R97/R14 -> 0.91269111 | S98: =+S97/S14 -> 0.86061173 | T98: =+T97/T14 -> 0.77844169 | U98: =+U97/U14 -> 0.68324826 | V98: =+V97/V14 -> 0.84737789 | W98: =+W97/W14 -> 0.8796453 | ... DG98: =+DG97/DG14 -> 0.60145977
C99: QBO Fees as a % of Revenue | AB99: =+AB89/AB12 -> 0.043303293 | AC99: =+AC89/AC12 -> 0.035843947 | AD99: =+AD89/AD12 -> 0.040856525 | AE99: =+AE89/AE12 -> 0.03632 | AF99: =+AF89/AF12 -> 0.032284916 | AG99: =+AG89/AG12 -> 0.055005982 | AH99: =+AH89/AH12 -> 0.025276622 | AI99: =+AI89/AI12 -> 0.028720115 | ... AW99: =+AW89/AW12 -> 0.023432034 | AX99: =+AVERAGE(AU99:AW99) -> 0.02642956 | AY99: =+AX99 -> 0.02642956 | AZ99: =+AY99 -> 0.02642956 | BA99: =+AZ99 -> 0.02642956 | BB99: =+BA99 -> 0.02642956 | BC99: =+BB99 -> 0.02642956 | BD99: =+BC99 -> 0.02642956 | BE99: =+BD99 -> 0.02642956 | BF99: =+BE99 -> 0.02642956 | ... DG99: =+DF99 -> 0.02642956
C100: CAC | L100: =L83+L87+L61+L69 -> 12 | M100: =M83+M87+M61+M69 -> 298.06 | N100: =N83+N87+N61+N69 -> 117.23 | O100: =O83+O87+O61+O69 -> 34.43 | P100: =P83+P87+P61+P69 -> 130.13 | Q100: =Q83+Q87+Q61+Q69 -> 48.76 | R100: =R83+R87+R61+R69 -> 75.36 | S100: =S83+S87+S61+S69 -> 165.85 | ... AA100: =AA83+AA87+AA61+AA69 -> 28.91 | AB100: =AB83+AB87+AB63+AB69 -> 78.91 | AC100: =AC83+AC87+AC63+AC69 -> 1208.35 | AD100: =AD83+AD87+AD63+AD69 -> 87.94 | AE100: =AE83+AE87+AE63+AE69 -> 2416.55 | AF100: =AF83+AF87+AF63+AF69 -> 157.97 | AG100: =AG83+AG87+AG63+AG69 -> 975.68 | AH100: =AH83+AH87+AH63+AH69 -> 1882.73 | AI100: =AI83+AI87+AI63+AI69 -> 904.81 | ... AP100: =AP83+AP87+AP63+AP69 -> 170.81 | AQ100: =AQ83+AQ63+AQ69+SUM(AQ87:AQ89) -> 370.04 | AR100: =AR83+AR63+AR69+SUM(AR87:AR89) -> 968.94 | AS100: =AS83+AS63+AS69+SUM(AS87:AS89) -> 961.07 | AT100: =AT83+AT63+AT69+SUM(AT87:AT89) -> 2558.77 | AU100: =AU83+AU63+AU69+SUM(AU87:AU89) -> 2163.19 | AV100: =AV83+AV63+AV69+SUM(AV87:AV89) -> 5971.53 | AW100: =AW83+AW63+AW69+SUM(AW87:AW89) -> 8643.52 | AX100: =AX83+AX63+AX69+SUM(AX87:AX89) -> 912.05761 | ... DG100: =DG83+DG63+DG69+SUM(DG87:DG89) -> 16723.31
B101: Other Income | AG101: 25
B102: Interest Income | D102: =0 -> 0 | E102: =0 -> 0 | F102: =0 -> 0 | G102: =0 -> 0 | H102: =0 -> 0 | I102: =0 -> 0 | J102: =0 -> 0 | K102: 0 | L102: 0 | M102: 0.02 | N102: 0.03 | O102: 0.01 | P102: 0 | Q102: 0 | R102: 0 | S102: 0.01 | T102: 0.01 | U102: 0.01 | V102: 0.03 | W102: 0.01 | X102: 0 | Y102: 0 | Z102: 0 | AA102: 0 | AG102: 0 | AI102: 0.43 | AJ102: 0.69 | AK102: 1.74 | AL102: 2.41 | AM102: 0.08 | AN102: 0.01 | AO102: 0.01 | AP102: 0.01 | AQ102: 0.01 | AR102: 0.06 | AS102: 0.01 | AT102: 0.03 | AU102: 0.03 | AV102: 0.99 | AW102: 4.56 | AX102: 0 | AY102: =AX102 -> 0 | AZ102: =AY102 -> 0 | BA102: =AZ102 -> 0 | BB102: =BA102 -> 0 | BC102: =BB102 -> 0 | BD102: =BC102 -> 0 | BE102: =BD102 -> 0 | BF102: =BE102 -> 0 | ... DG102: =DF102 -> 0
B103: Total Other Income | D103: =D102 -> 0 | E103: =E102 -> 0 | F103: =F102 -> 0 | G103: =G102 -> 0 | H103: =H102 -> 0 | I103: =I102 -> 0 | J103: =J102 -> 0 | K103: 0 | L103: 0 | M103: 0.02 | N103: =N102 -> 0.03 | O103: =O102 -> 0.01 | P103: =P102 -> 0 | Q103: =Q102 -> 0 | R103: =R102 -> 0 | S103: =S102 -> 0.01 | T103: =T102 -> 0.01 | U103: =U102 -> 0.01 | ... AF103: =AF102 -> 0 | AG103: =SUM(AG101:AG102) -> 25 | AH103: =AH102 -> 0 | AI103: =AI102 -> 0.43 | AJ103: =AJ102 -> 0.69 | AK103: =AK102 -> 1.74 | AL103: =AL102 -> 2.41 | AM103: =AM102 -> 0.08 | AN103: =AN102 -> 0.01 | AO103: =AO102 -> 0.01 | AP103: =AP102 -> 0.01 | AQ103: =SUM(AQ101:AQ102) -> 0.01 | AR103: =AR102 -> 0.06 | AS103: =AS102 -> 0.01 | AT103: =AT102 -> 0.03 | AU103: =AU102 -> 0.03 | AV103: =AV102 -> 0.99 | AW103: =AW102 -> 4.56 | AX103: =AX102 -> 0 | AY103: =AY102 -> 0 | ... DG103: =DG102 -> 0
B104: Other Expenses
B105: 73000 Home Office Deduction | D105: =0 -> 0 | E105: =0 -> 0 | F105: =0 -> 0 | G105: =0 -> 0 | H105: =0 -> 0 | I105: =0 -> 0 | J105: =0 -> 0 | K105: 0 | L105: 0 | M105: 0 | N105: 0 | O105: 0 | P105: 0 | Q105: 0 | R105: 0 | S105: 0 | T105: 0 | U105: 0 | V105: 0 | W105: 0 | X105: 0 | Y105: 0 | Z105: 0 | AA105: 0 | AG105: 715.26 | AH105: 715.26 | AI105: 639.62 | AJ105: 719.87 | AK105: 733.37 | AL105: 735.08 | AM105: 790.12 | AN105: 821.85 | AO105: 775.58 | AP105: 757.93 | AQ105: 757.93 | AR105: 692.93 | AS105: 769.03 | AT105: 775.28 | AU105: 727.35 | AV105: 727.35 | AW105: 846.79 | AX105: 800 | AY105: =AX105 -> 800 | AZ105: =AY105 -> 800 | BA105: =AZ105 -> 800 | BB105: =BA105 -> 800 | BC105: =BB105 -> 800 | BD105: =BC105 -> 800 | BE105: =BD105 -> 800 | BF105: =BE105 -> 800 | ... DG105: =DF105 -> 800
B106: Total Other Expenses | D106: =D105 -> 0 | E106: =E105 -> 0 | F106: =F105 -> 0 | G106: =G105 -> 0 | H106: =H105 -> 0 | I106: =I105 -> 0 | J106: =J105 -> 0 | K106: 0 | L106: 0 | M106: 0 | N106: =N105 -> 0 | O106: =O105 -> 0 | P106: =P105 -> 0 | Q106: =Q105 -> 0 | R106: =R105 -> 0 | S106: =S105 -> 0 | T106: =T105 -> 0 | U106: =U105 -> 0 | ... DG106: =DG105 -> 800
B107: Net Other Income | D107: =D103 -> 0 | E107: =E103 -> 0 | F107: =F103 -> 0 | G107: =G103 -> 0 | H107: =H103 -> 0 | I107: =I103 -> 0 | J107: =J103 -> 0 | K107: =K103 -> 0 | L107: =L103 -> 0 | M107: =M103-M106 -> 0.02 | N107: =N103-N106 -> 0.03 | O107: =O103-O106 -> 0.01 | P107: =P103-P106 -> 0 | Q107: =Q103-Q106 -> 0 | R107: =R103-R106 -> 0 | S107: =S103-S106 -> 0.01 | T107: =T103-T106 -> 0.01 | ... DG107: =DG103-DG106 -> -800
...

Sheet 3

Sheet October
A1: Student | B1: Date | C1: Hours | D1: Rate ($/hr) | E1: Coin | F1: Billed? | G1: Received payment? | H1: Topic | I1: Tip? | J1: Paid via invoice? | K1: Totals
A2: Abby Owen | B2: 44836 | C2: 1 | D2: 50 | E2: 50 | F2: Yes | G2: Yes | H2: Math (general homework) | I2: No | J2: No | K2: 50 | N2: BALANCED
A3: Abby Owen | B3: 44846 | C3: 2 | D3: 50 | E3: 100 | F3: Yes | G3: Yes | H3: Algebra 2 | I3: No | J3: YES | K3: 100
A4: Abby Owen | B4: 44858 | C4: 1 | D4: 50 | E4: 50 | F4: Yes | G4: Yes | H4: Emergency Math Lab | I4: No | J4: YES | K4: 50
A5: Abby Owen | B5: 44859 | C5: 0.75 | D5: 50 | E5: 37.5 | F5: Yes | G5: Yes | H5: Logarithmic Functions Review | I5: No | J5: YES | K5: 37.5
A6: Abby Owen | B6: 44861 | C6: 1 | D6: 50 | E6: 50 | F6: Yes | G6: Yes | H6: Precalc - Exponentials and Logs | I6: No | J6: YES | K6: 50
A7: Addison O'Connor | B7: 44849 | C7: 1 | D7: 60 | E7: 60 | F7: Yes | G7: Yes | H7: Choreography Review | I7: No | J7: YES | K7: 60
A8: Caroline Frey | B8: 44852 | C8: 3.5 | D8: 50 | E8: 175 | F8: Yes | G8: Yes | H8: TN and CoC Essay Supplement Finalization | I8: Yes | J8: No - Venmo b/c tip; sent to personal account but transferred accordingly (sent to Eric and Eric venmo'd business acc) | K8: 200
A9: Caroline Frey | B9: 44857 | C9: 1 | D9: 50 | E9: 50 | F9: Yes | G9: Yes | H9: Bama Honors Appliation | I9: No | J9: No - venmo b/c tip | K9: 50
A10: Claire Cecotti | B10: 44837 | C10: 1 | D10: 50 | E10: 50 | F10: Yes | G10: Yes | H10: SAT Math, Piecewise Functions Test | I10: No | J10: YES | K10: 50
A11: Elle Mishler | B11: 44842 | C11: 1 | D11: 60 | E11: 60 | F11: Yes | G11: Yes | H11: Algebra 1 | I11: No | J11: YES | K11: 60
A12: Elle Mishler | B12: 44846 | C12: 1 | D12: 60 | E12: 60 | F12: Yes | G12: Yes | H12: Algebra 1 | I12: No | J12: YES | K12: 60
A13: Elle Mishler | B13: 44853 | C13: 1.25 | D13: 60 | E13: 75 | F13: Yes | G13: Yes | H13: Algebra 1 Review | I13: No | J13: YES | K13: 75
A14: Gabby Bagot | B14: 44856 | C14: 1 | D14: 60 | E14: 60 | F14: Yes | G14: Yes | H14: Algebra 1 | I14: No | J14: YES | K14: 60 | N14: *Sujay 21 Oct, 23 Oct, 29 Oct, and 30 Oct were all billed together.
A15: Julia Cecotti | B15: 44845 | C15: 1 | D15: 50 | E15: 50 | F15: Yes | G15: Yes | H15: Precalc - piecewise functions | I15: No | J15: YES | K15: 50
A16: Julia Cecotti | B16: 44851 | C16: 1.5 | D16: 50 | E16: 75 | F16: Yes | G16: Yes | H16: Limits and Discontinuity | I16: No | J16: YES | K16: 75
A17: Kathryn Oakford | B17: 44851 | C17: 1.5 | D17: 50 | E17: 75 | F17: Yes | G17: Yes | H17: Business Calculus | I17: No | J17: YES | K17: 75
A18: Kathryn Oakford | B18: 44857 | C18: 1.5 | D18: 50 | E18: 75 | F18: Yes | G18: Yes | H18: Business Calculus | I18: No | J18: YES | K18: 75 | O18: Row Labels | P18: Sum of Hours | Q18: Sum of Coin
A19: Kaylie Thompson | B19: 44836 | C19: 1.5 | D19: 50 | E19: 75 | F19: Yes | G19: Yes | H19: Common App Finalizaiton | I19: No | J19: No | K19: 75 | O19: Abby Owen | P19: 5.75 | Q19: 287.5
A20: Maddie Wilson | B20: 44836 | C20: 2 | D20: 50 | E20: 100 | F20: Yes | G20: Yes | H20: ACT Math | I20: No | J20: No | K20: 100 | O20: Addison O'Connor | P20: 1 | Q20: 60
A21: Maddie Wilson | B21: 44854 | C21: 1.5 | D21: 50 | E21: 75 | F21: Yes | G21: Yes | H21: ACT Math | I21: No | J21: No - received via PayPal and Transferred | K21: 75 | O21: Caroline Frey | P21: 4.5 | Q21: 225
A22: Maddox Rogers | B22: 44847 | C22: 2 | D22: 50 | E22: 100 | F22: Yes | G22: Yes | H22: College Essay | I22: No | J22: YES | K22: 100 | O22: Claire Cecotti | P22: 1 | Q22: 50
A23: Naura Peters | B23: 44856 | C23: 0.5 | D23: 60 | E23: 30 | F23: Yes | G23: Yes | H23: Private lesson | I23: No | J23: YES | K23: 30 | O23: Elle Mishler | P23: 3.25 | Q23: 195
A24: Nicolette Batori | B24: 44857 | C24: 2 | D24: 50 | E24: 100 | F24: Yes | G24: Yes | H24: AP Test Advice, Volunteering advice, SAT Math | I24: No | J24: YES | K24: 100 | O24: Gabby Bagot | P24: 1 | Q24: 60
A25: Nicolette Batori | B25: 44863 | C25: 1 | D25: 50 | E25: 50 | F25: Yes | G25: Yes | H25: SAT Math | I25: No | J25: YES | K25: 50 | O25: Julia Cecotti | P25: 2.5 | Q25: 125
A26: Nicolette Batori | B26: 44865 | C26: 1 | D26: 50 | E26: 50 | F26: Yes | G26: Yes | H26: SAT Math | I26: No | J26: YES | K26: 50 | O26: Kathryn Oakford | P26: 3 | Q26: 150
A27: Rohan Skanda | B27: 44838 | C27: 1 | D27: 50 | E27: 50 | F27: Yes | G27: Yes | H27: AOS Integrated Math + Science | I27: No | J27: YES | K27: 50 | O27: Kaylie Thompson | P27: 1.5 | Q27: 75
A28: Rohan Skanda | B28: 44840 | C28: 2 | D28: 50 | E28: 100 | F28: Yes | G28: Yes | H28: AOS Integrated Math + Science | I28: No | J28: YES | K28: 100 | O28: Maddie Wilson | P28: 3.5 | Q28: 175
A29: Rohan Skanda | B29: 44851 | C29: 1.5 | D29: 50 | E29: 75 | F29: Yes | G29: Yes | H29: Math and Physics Review | I29: No | J29: YES | K29: 75 | O29: Maddox Rogers | P29: 2 | Q29: 100
A30: Rohan Skanda | B30: 44857 | C30: 1 | D30: 50 | E30: 75 | F30: Yes | G30: Yes | H30: AOS Integrated Math + Science | I30: No | J30: YES | K30: 75 | O30: Naura Peters | P30: 0.5 | Q30: 30
... A36: Sophia Gonzales | B36: 44861 | C36: 1 | D36: 60 | E36: 60 | F36: Yes | G36: Yes | H36: Physics | I36: No | J36: YES | K36: 60 | O36: Grand Total | P36: 57.25 | Q36: 2840
A37: Sujay Penugonda | B37: 44840 | C37: 1.5 | D37: 50 | E37: 75 | F37: Yes | G37: Yes | H37: Supplemental Essays | I37: No | J37: YES | K37: 75
A38: Sujay Penugonda | B38: 44855 | C38: 2 | D38: 50 | E38: 100 | F38: Yes | G38: Yes | H38: College Essay | I38: No | J38: YES | K38: 100
A39: Sujay Penugonda | B39: 44857 | C39: 0.5 | D39: 50 | E39: 25 | F39: No | G39: Yes | H39: College Essay | I39: No | J39: YES | K39: 25
A40: Sujay Penugonda | B40: 44863 | C40: 5 | D40: 50 | E40: 125 | F40: Yes | G40: Yes | H40: College Essay | I40: No | J40: YES | K40: 250
A41: Sujay Penugonda | B41: 44864 | C41: 2.5 | D41: 50 | E41: 125 | F41: Yes | G41: Yes | H41: College Essay | I41: No | J41: No - asked to send via Zelle. Transferred from personal to biz immediately. | K41: 125
K43: =SUM(K2:K41) -> 2990

Sheet September
A1: Student | B1: Date | C1: Hours | D1: Rate ($/hr) | E1: Coin | F1: Billed? | G1: Received payment? | H1: Topic | I1: Tip? | J1: Totals
A2: Rohan Skanda | B2: 44822 | C2: 1 | D2: 50 | E2: 50 | F2: Yes | G2: Yes | H2: AOS Math/Science | I2: No | J2: 50 | M2: BALANCED
A3: Maddie Wilson | B3: 44822 | C3: 2 | D3: 50 | E3: 100 | F3: Yes | G3: Yes | H3: College Essay | I3: No | J3: 100
A4: Caroline Frey | B4: 44822 | C4: 1.5 | D4: 50 | E4: 75 | F4: Yes | G4: Yes | H4: College Supplemental Essays | I4: 25 | J4: 100
A5: Kathryn Oakford | B5: 44822 | C5: 1.5 | D5: 50 | E5: 75 | F5: Yes | G5: Yes | H5: Business Calc | I5: No | J5: 75
A6: Kaylie Thompson | B6: 44822 | C6: 1.5 | D6: 50 | E6: 75 | F6: Yes | G6: Yes | H6: College Essay | I6: No | J6: 75
A7: Abby Owen | B7: 44823 | C7: 2 | D7: 50 | E7: 100 | F7: Yes | G7: Yes | H7: Math Practice for Quiz | I7: No | J7: 100
A8: Kathryn Oakford | B8: 44823 | C8: 1 | D8: 50 | E8: 50 | F8: Yes | G8: Yes | H8: Business Calc | I8: No | J8: 50
A9: Maddie Wilson | B9: 44826 | C9: 1 | D9: 50 | E9: 50 | F9: Yes | G9: Yes | H9: ACT Math, NHS Essay | I9: No | J9: 50
A10: Mckenzie Frey | B10: 44827 | C10: 0.5 | D10: 50 | E10: 25 | F10: No | G10: Yes (accounted for in October w Caroline) | H10: PR/Project Planning | O10: Row Labels | P10: Sum of Hours | Q10: Sum of Coin
A11: Maddie Wilson | B11: 44827 | C11: 1 | D11: 50 | E11: 50 | F11: Yes | G11: Yes | H11: NHS Essay | I11: No | J11: 50 | O11: Abby Owen | P11: 2 | Q11: 100
A12: Claire Cecotti | B12: 44829 | C12: 1 | D12: 50 | E12: 50 | F12: Yes | G12: Yes | H12: Algebra Review/SAT Math | I12: No | J12: 50 | O12: Caroline Frey | P12: 1.5 | Q12: 75
A13: Maddie Wilson | B13: 44829 | C13: 2 | D13: 100 | E13: 100 | F13: Yes | G13: Yes | H13: Supplemental Essays | I13: No | J13: 100 | O13: Claire Cecotti | P13: 2 | Q13: 100
A14: Sam Cormier | B14: 44829 | C14: 2 | D14: 100 | E14: 100 | F14: Yes | G14: Yes | H14: Supplemental Essays | I14: No | J14: 100 | O14: Kathryn Oakford | P14: 2.5 | Q14: 125
A15: Claire Cecotti | B15: 44830 | C15: 1 | D15: 50 | E15: 50 | F15: Yes | G15: Yes | H15: Algebra Review/SAT Math | I15: No | J15: 50 | O15: Kaylie Thompson | P15: 1.5 | Q15: 75
A16: Maddie Wilson | B16: 44832 | C16: 1.5 | D16: 50 | E16: 75 | F16: Yes | G16: Yes | H16: Supplemental Essays | I16: No | J16: 75 | O16: Maddie Wilson | P16: 7.5 | Q16: 375
O17: Mckenzie Frey | P17: 0.5 | Q17: 25
J18: =SUM(J2:J16) -> 1025 | O18: Rohan Skanda | P18: 1 | Q18: 50
O19: Sam Cormier | P19: 2 | Q19: 100
O20: Grand Total | P20: 20.5 | Q20: 1025

Sheet August
A1: Student | B1: Date | C1: Hours | D1: Rate ($/hr) | E1: Coin | F1: Billed? | G1: Received payment? | H1: Topic | I1: Tip? | J1: Totals
A2: Caroline Frey | B2: 44793 | C2: 0.5 | D2: 50 | E2: =C2*D2 -> 25 | F2: Yes | G2: Yes | H2: Adderal form | I2: 10 | J2: =E2+I2 -> 35
A3: Nicolette Batori | B3: 44794 | C3: 1.5 | D3: 50 | E3: =C3*D3 -> 75 | F3: No | G3: Yes | H3: SAT/ACT overview, college talk/prep | I3: 0 | J3: =E3+I3 -> 75
A4: Maddie Wilson | B4: 44794 | C4: 1 | D4: 50 | E4: =C4*D4 -> 50 | F4: No | G4: No | H4: ACT Science | J4: =E4+I4 -> 50
A5: Sujay Penugonda | B5: 44796 | C5: 2 | D5: 50 | E5: =C5*D5 -> 100 | F5: Yes | G5: Yes | H5: Essay | J5: =E5+I5 -> 100 | O5: Row Labels | P5: Sum of Hours | Q5: Sum of Coin
A6: Maddie Wilson | B6: 44796 | C6: 2 | D6: 50 | E6: =C6*D6 -> 100 | F6: No | G6: No | H6: ACT Math, college essay | J6: =E6+I6 -> 100 | O6: Caroline Frey | P6: 0.5 | Q6: 25
A7: Matthew Aasen | B7: 44796 | C7: 0.5 | D7: 50 | E7: =C7*D7 -> 25 | F7: Yes | G7: Yes | H7: 2nd read common app | J7: =E7+I7 -> 25 | O7: Maddie Wilson | P7: 3 | Q7: 150
O8: Matthew Aasen | P8: 0.5 | Q8: 25
O9: Nicolette Batori | P9: 1.5 | Q9: 75
J10: =SUM(J2:J7) -> 385 | O10: Sujay Penugonda | P10: 2 | Q10: 100
O11: Grand Total | P11: 7.5 | Q11: 375
J12: BALANCED

Sheet People Plan
H2: 45473 | I2: =EOMONTH(H2,1) -> 45504 | J2: =EOMONTH(I2,1) -> 45535 | K2: =EOMONTH(J2,1) -> 45565 | L2: =EOMONTH(K2,1) -> 45596 | M2: =EOMONTH(L2,1) -> 45626 | N2: =EOMONTH(M2,1) -> 45657 | O2: =EOMONTH(N2,1) -> 45688 | P2: =EOMONTH(O2,1) -> 45716 | ... FB2: =EOMONTH(FA2,1) -> 50040
B3: Name | C3: Position | D3: Hourly Rate | E3: Avg. Hours
B4: Nvaid | C4: Intern | D4: 12 | E4: =4.33*10 -> 43.3 | I4: 0 | J4: 0 | K4: 0 | L4: 0 | M4: 0 | N4: 0 | O4: 0 | P4: 0 | Q4: 0 | R4: 0 | S4: 0 | U4: 240
B5: Charles | C5: Intern | D5: 15 | E5: =4.33*10 -> 43.3 | I5: 450 | J5: 150 | K5: 0 | L5: 0 | M5: 0 | O5: 0 | P5: 0 | Q5: 0 | R5: 0 | S5: 0
B6: Luke | C6: Intern | D6: 15 | E6: =4.33*10 -> 43.3 | R6: 0 | S6: 0
B7: Rising Freshmen | C7: Intern | O7: 0 | P7: 0 | Q7: 0 | R7: 0 | S7: 0 | U7: 300 | V7: 234 | W7: =86.8 -> 86.8 | X7: 120
F8: Total Interns Expense | H8: =SUM(H4:H7) -> 0 | I8: =SUM(I4:I7) -> 450 | J8: =SUM(J4:J7) -> 150 | K8: =SUM(K4:K7) -> 0 | L8: =SUM(L4:L7) -> 0 | M8: =SUM(M4:M7) -> 0 | N8: =SUM(N4:N7) -> 0 | O8: =SUM(O4:O7) -> 0 | ... FB8: =SUM(FB4:FB7) -> 0
E10: Hours Threshold
B11: Cheri? | C11: Subsititute Tutor | D11: 50 | H11: =+IF(('Monthly Detail'!AG26-'Monthly Detail'!$B$24)>0,('Monthly Detail'!AG26-'Monthly Detail'!$B$24)*'People Plan'!$D$11, 0) -> 0 | I11: 0 | J11: 0 | K11: 0 | L11: 0 | M11: =+IF(('Monthly Detail'!AL26-'Monthly Detail'!$B$24)>0,('Monthly Detail'!AL26-'Monthly Detail'!$B$24)*'People Plan'!$D$11, 0) -> 0 | N11: =+IF(('Monthly Detail'!AM28-'Monthly Detail'!$B$24)>0,('Monthly Detail'!AM28-'Monthly Detail'!$B$24)*'People Plan'!$D$11, 0) -> 0 | O11: 0 | P11: 0 | Q11: 0 | R11: 0 | S11: 0 | T11: =+IF(('Monthly Detail'!AS28-'Monthly Detail'!$B$24)>0,('Monthly Detail'!AS28-'Monthly Detail'!$B$24)*'People Plan'!$D$11, 0) -> 0 | U11: =+IF(('Monthly Detail'!AT28-'Monthly Detail'!$B$24)>0,('Monthly Detail'!AT28-'Monthly Detail'!$B$24)*'People Plan'!$D$11, 0) -> 0 | V11: =+IF(('Monthly Detail'!AU28-'Monthly Detail'!$B$24)>0,('Monthly Detail'!AU28-'Monthly Detail'!$B$24)*'People Plan'!$D$11, 0) -> 0 | W11: =+IF(('Monthly Detail'!AV28-'Monthly Detail'!$B$24)>0,('Monthly Detail'!AV28-'Monthly Detail'!$B$24)*'People Plan'!$D$11, 0) -> 0 | X11: =+IF(('Monthly Detail'!AW28-'Monthly Detail'!$B$24)>0,('Monthly Detail'!AW28-'Monthly Detail'!$B$24)*'People Plan'!$D$11, 0) -> 0 | Y11: =+IF(('Monthly Detail'!AX28-'Monthly Detail'!$B$24)>0,('Monthly Detail'!AX28-'Monthly Detail'!$B$24)*'People Plan'!$D$11, 0) -> 0 | Z11: =+IF(('Monthly Detail'!AY28-'Monthly Detail'!$B$24)>0,('Monthly Detail'!AY28-'Monthly Detail'!$B$24)*'People Plan'!$D$11, 0) -> 0 | AA11: =+IF(('Monthly Detail'!AZ28-'Monthly Detail'!$B$24)>0,('Monthly Detail'!AZ28-'Monthly Detail'!$B$24)*'People Plan'!$D$11, 0) -> 0 | ... FB11: =+IF(('Monthly Detail'!GA28-'Monthly Detail'!$B$24)>0,('Monthly Detail'!GA28-'Monthly Detail'!$B$24)*'People Plan'!$D$11, 0) -> 0
B12: Madeline | C12: Subsititute Tutor - RESUME REVIEW | D12: 50 | E12: 3 | H12: =+IF(('Monthly Detail'!AG24-'Monthly Detail'!$B$24)>0,('Monthly Detail'!AG24-'Monthly Detail'!$B$24)*'People Plan'!$D$11, 0) -> 0 | I12: 150 | J12: 740 | K12: 817.5 | L12: 937.5 | M12: 170 | N12: =+IF(('Monthly Detail'!AM30-$E$12)>0,('Monthly Detail'!AM30-$E$12)*'People Plan'!$D$12, 0) -> 0 | O12: 0 | P12: 802.5 | Q12: 375 | R12: 0 | S12: 270 | T12: 0 | U12: 720 | V12: 240 | W12: 1419.96 | X12: 1020 | Y12: =+IF(('Monthly Detail'!AX30-$E$12)>0,('Monthly Detail'!AX30-$E$12)*'People Plan'!$D$12, 0) -> 0 | Z12: =+IF(('Monthly Detail'!AY30-$E$12)>0,('Monthly Detail'!AY30-$E$12)*'People Plan'!$D$12, 0) -> 0 | AA12: =+IF(('Monthly Detail'!AZ30-$E$12)>0,('Monthly Detail'!AZ30-$E$12)*'People Plan'!$D$12, 0) -> 0 | AB12: =+IF(('Monthly Detail'!BA30-$E$12)>0,('Monthly Detail'!BA30-$E$12)*'People Plan'!$D$12, 0) -> 271.33929 | AC12: =+IF(('Monthly Detail'!BB30-$E$12)>0,('Monthly Detail'!BB30-$E$12)*'People Plan'!$D$12, 0) -> 0 | AD12: =+IF(('Monthly Detail'!BC30-$E$12)>0,('Monthly Detail'!BC30-$E$12)*'People Plan'!$D$12, 0) -> 0 | AE12: =+IF(('Monthly Detail'!BD30-$E$12)>0,('Monthly Detail'!BD30-$E$12)*'People Plan'!$D$12, 0) -> 145.09773 | AF12: =+IF(('Monthly Detail'!BE30-$E$12)>0,('Monthly Detail'!BE30-$E$12)*'People Plan'!$D$12, 0) -> 387.93143 | ... FB12: =+IF(('Monthly Detail'!GA30-$E$12)>0,('Monthly Detail'!GA30-$E$12)*'People Plan'!$D$12, 0) -> 0
B13: Tyler | C13: Subsititute Tutor - SAT/ACT PREP | D13: 50 | E13: 50 | O13: 0 | P13: 0 | Q13: 0 | R13: 0 | S13: 0 | T13: 0 | U13: 120 | V13: 210 | W13: 270 | X13: 390 | Y13: =+IF(('Monthly Detail'!AX29-$E$13)>0,('Monthly Detail'!AX29-$E$13)*'People Plan'!$D$13, 0) -> 0 | Z13: =+IF(('Monthly Detail'!AY29-$E$13)>0,('Monthly Detail'!AY29-$E$13)*'People Plan'!$D$13, 0) -> 959.95423 | AA13: =+IF(('Monthly Detail'!AZ29-$E$13)>0,('Monthly Detail'!AZ29-$E$13)*'People Plan'!$D$13, 0) -> 2840.0018 | AB13: =+IF(('Monthly Detail'!BA29-$E$13)>0,('Monthly Detail'!BA29-$E$13)*'People Plan'!$D$13, 0) -> 4578.5 | AC13: =+IF(('Monthly Detail'!BB29-$E$13)>0,('Monthly Detail'!BB29-$E$13)*'People Plan'!$D$13, 0) -> 7164.875 | AD13: =+IF(('Monthly Detail'!BC29-$E$13)>0,('Monthly Detail'!BC29-$E$13)*'People Plan'!$D$13, 0) -> 1872.4348 | AE13: =+IF(('Monthly Detail'!BD29-$E$13)>0,('Monthly Detail'!BD29-$E$13)*'People Plan'!$D$13, 0) -> 6254.5659 | AF13: =+IF(('Monthly Detail'!BE29-$E$13)>0,('Monthly Detail'!BE29-$E$13)*'People Plan'!$D$13, 0) -> 189.65714 | ... FB13: =+IF(('Monthly Detail'!GA29-$E$13)>0,('Monthly Detail'!GA29-$E$13)*'People Plan'!$D$13, 0) -> 0
B14: ChanChal | C14: Subsititute Tutor - SAT/ACT PREP | U14: 202.5 | V14: 0 | W14: 2299.98 | X14: 4725
B17: Lauren Est | C17: Owner | D17: 70 | E17: 170 | O17: 1275 | P17: 4005 | Q17: 4410 | R17: 2450 | S17: 1960 | T17: 2450 | U17: 7280 | V17: 14252.7 | W17: 9800 | X17: 14350 | Y17: =+$D$17*$E$17 -> 11900 | Z17: =+$D$17*$E$17 -> 11900 | AA17: =+$D$17*$E$17 -> 11900 | AB17: =+$D$17*$E$17 -> 11900 | AC17: =+$D$17*$E$17 -> 11900 | AD17: =+$D$17*$E$17 -> 11900 | AE17: =+$D$17*$E$17 -> 11900 | AF17: =+$D$17*$E$17 -> 11900 | ... FB17: =+$D$17*$E$17 -> 11900
F18: Total Owner Wages | O18: =SUM(O17) -> 1275 | P18: =SUM(P17) -> 4005 | Q18: =SUM(Q17) -> 4410 | R18: =SUM(R17) -> 2450 | S18: =SUM(S17) -> 1960 | T18: =SUM(T17) -> 2450 | U18: =SUM(U17) -> 7280 | V18: =SUM(V17) -> 14252.7 | ... FB18: =SUM(FB17) -> 11900
F19: Total Tutors Expense | H19: =SUM(H11:H15) -> 0 | I19: =SUM(I11:I15) -> 150 | J19: =SUM(J11:J15) -> 740 | K19: =SUM(K11:K15) -> 817.5 | L19: =SUM(L11:L15) -> 937.5 | M19: =SUM(M11:M15) -> 170 | N19: =SUM(N11:N15) -> 0 | O19: =SUM(O11:O15) -> 0 | ... FB19: =SUM(FB11:FB15) -> 0
F20: Total Contractors Expense | H20: =+H8+H19 -> 0 | I20: =+I8+I19 -> 600 | J20: =+J8+J19 -> 890 | K20: =+K8+K19 -> 817.5 | L20: =+L8+L19 -> 937.5 | M20: =+M8+M19 -> 170 | N20: =+N8+N19 -> 0 | O20: =+O8+O19 -> 0 | ... FB20: =+FB8+FB19 -> 0

Sheet Actual vs. Forecast
B14: 45961
E15: 45169 | F15: 45199 | G15: 45230 | H15: 45260 | I15: 45291 | J15: 45322 | K15: 45351 | L15: 45382 | M15: 45412 | N15: 45443 | O15: 45473 | P15: 45504 | Q15: 45535 | R15: 45596 | S15: 45626 | T15: 45657 | U15: 45688 | V15: 45716 | W15: 45747 | X15: 45777 | Y15: 45808 | Z15: 45838 | AA15: 45869 | AB15: 45900 | AC15: 45930 | AD15: =EOMONTH(AB15,2) -> 45961 | AE15: =EOMONTH(AD15,1) -> 45991 | AF15: =EOMONTH(AE15,1) -> 46022 | AG15: =EOMONTH(AF15,1) -> 46053 | AH15: =EOMONTH(AG15,1) -> 46081 | AI15: =EOMONTH(AH15,1) -> 46112 | AJ15: =EOMONTH(AI15,1) -> 46142 | AK15: =EOMONTH(AJ15,1) -> 46173 | AL15: =EOMONTH(AK15,1) -> 46203 | ... AO15: =EOMONTH(AN15,1) -> 46295 | AP15: Forecast | AQ15: Actual | AR15: 45322 | AS15: 45351 | AT15: 45382 | AU15: 45412 | AV15: 45443 | AW15: 45473 | AX15: 45504 | AY15: 45535 | AZ15: 45565 | BA15: 45596 | BB15: 45626 | BC15: 45657 | BD15: 45688 | BE15: 45716 | BF15: 45747 | BG15: 45777 | BH15: 45808 | BI15: 45838 | BJ15: 45869 | BK15: 45900 | BL15: 45930 | BM15: Budget | BN15: 45991 | BO15: 46022 | BP15: Variance (Forecast) | BQ15: Variance (Budget)
B16: Total Income | E16: 4938 | F16: 4489.5 | G16: 5810.25 | H16: 4881.37 | I16: 8589.37 | J16: 3066.4792 | K16: 3175.0214 | L16: 2422.2799 | M16: 4440.4242 | N16: 6044.6787 | O16: 4035.0139 | P16: 6070.8648 | Q16: 9070.6433 | R16: 11517.552 | S16: 8370.8924 | T16: 5536.9286 | U16: 5536.9286 | V16: 5536.9286 | W16: 5536.9286 | X16: 6629.6135 | Y16: 6629.6135 | Z16: 6629.6135 | AA16: 10577.152 | AB16: 17228.129 | AC16: 17092.79 | AD16: =+SUMIF('Monthly Detail'!$4:$4, AD15,'Monthly Detail'!$14:$14) -> 39363.13 | AE16: =+SUMIF('Monthly Detail'!$4:$4, AE15,'Monthly Detail'!$14:$14) -> 12782.237 | AF16: =+SUMIF('Monthly Detail'!$4:$4, AF15,'Monthly Detail'!$14:$14) -> 18043.721 | AG16: =+SUMIF('Monthly Detail'!$4:$4, AG15,'Monthly Detail'!$14:$14) -> 21421.892 | AH16: =+SUMIF('Monthly Detail'!$4:$4, AH15,'Monthly Detail'!$14:$14) -> 20140.783 | AI16: =+SUMIF('Monthly Detail'!$4:$4, AI15,'Monthly Detail'!$14:$14) -> 20607.779 | AJ16: =+SUMIF('Monthly Detail'!$4:$4, AJ15,'Monthly Detail'!$14:$14) -> 9140.9379 | AK16: =+SUMIF('Monthly Detail'!$4:$4, AK15,'Monthly Detail'!$14:$14) -> 15795.396 | AL16: 5705.08 | AM16: 4308.26 | AN16: 9060.89 | AO16: 14111.26 | AP16: 23851.27 | AQ16: =+SUMIF('Monthly Detail'!$4:$4, $B$14,'Monthly Detail'!$14:$14) -> 39363.13 | AR16: =+'2024 AOP'!C14 -> 3066.4792 | AS16: =+'2024 AOP'!D14 -> 4893.6612 | AT16: =+'2024 AOP'!E14 -> 3994.1332 | AU16: =+'2024 AOP'!F14 -> 5964.4554 | AV16: =+'2024 AOP'!G14 -> 10231.792 | AW16: =+'2024 AOP'!H14 -> 6730.3712 | AX16: =+'2024 AOP'!I14 -> 9868.4732 | AY16: =+'2024 AOP'!J14 -> 9248.9885 | AZ16: =+'2024 AOP'!L14 -> 10194.697 | BA16: 6042.6641 | BB16: =+'2024 AOP'!M14 -> 6042.6641 | BC16: =+'2024 AOP'!N14 -> 4112 | BD16: 9543.3537 | BE16: 12714.964 | BF16: 7487.4507 | BG16: 9849.7967 | BH16: 10751.932 | BI16: 5819.9642 | BJ16: 10878.588 | BK16: 15891.044 | BL16: 12144.428 | BM16: 15655.286 | BN16: 8813.2671 | BO16: 6298.8782 | BP16: =+AQ16-AP16 -> 15511.86 | BQ16: =+AQ16-BM16 -> 23707.844
B17: KPIs | C17: # of Students | E17: 17 | F17: 17 | G17: 20 | H17: 18 | I17: 34 | J17: 21 | K17: 21 | L17: 21 | M17: 27 | N17: 22 | O17: 22 | P17: 19 | Q17: 32 | R17: 41 | S17: 44 | T17: 41 | U17: 41 | V17: 41 | W17: 41 | X17: 25 | Y17: 25 | Z17: 25 | AA17: 24 | AB17: 36 | AC17: 50 | AD17: =+SUMIF('Monthly Detail'!$4:$4, AD15,'Monthly Detail'!17:17) -> 67 | AE17: =+SUMIF('Monthly Detail'!$4:$4, AE15,'Monthly Detail'!17:17) -> 62 | AF17: =+SUMIF('Monthly Detail'!$4:$4, AF15,'Monthly Detail'!17:17) -> 57.6 | AG17: =+SUMIF('Monthly Detail'!$4:$4, AG15,'Monthly Detail'!17:17) -> 57.32 | AH17: =+SUMIF('Monthly Detail'!$4:$4, AH15,'Monthly Detail'!17:17) -> 62.92 | AI17: =+SUMIF('Monthly Detail'!$4:$4, AI15,'Monthly Detail'!17:17) -> 59.64 | AJ17: =+SUMIF('Monthly Detail'!$4:$4, AJ15,'Monthly Detail'!17:17) -> 54.36 | AK17: =+SUMIF('Monthly Detail'!$4:$4, AK15,'Monthly Detail'!17:17) -> 54.96 | AL17: 22 | AM17: 16 | AN17: 30 | AO17: 38 | AP17: 55 | AQ17: =+SUMIF('Monthly Detail'!$4:$4, $B$14,'Monthly Detail'!17:17) -> 67 | AR17: 21 | AS17: 33 | AT17: 35 | AU17: 33 | AV17: 34 | AW17: 34 | AX17: 31 | AY17: 32 | AZ17: 43 | BA17: 38 | BB17: 38 | BC17: 38 | BD17: 24 | BE17: 35.8 | BF17: 33.6 | BG17: 32.4 | BH17: 33.4 | BI17: 29.2 | BJ17: 31.2 | BK17: 37.2 | BL17: 43.2 | BM17: 45 | BN17: 43.6 | BO17: 42.2 | BP17: =+AQ17-AP17 -> 12 | BQ17: =+AQ17-BM17 -> 22
C18: Net New Students | E18: 2 | F18: 0 | G18: 2 | H18: 2 | I18: 2 | J18: 2 | K18: 2 | L18: 2 | M18: 2 | N18: 2 | O18: 0 | P18: 3 | Q18: 2 | R18: -1 | S18: -4 | T18: -3 | U18: -3 | V18: -3 | W18: -3 | X18: 3 | Y18: 3 | Z18: 3 | AA18: -1 | AB18: 1 | AC18: 1 | AD18: =+SUMIF('Monthly Detail'!$4:$4, AD15,'Monthly Detail'!19:19) -> 10 | AE18: =+SUMIF('Monthly Detail'!$4:$4, AE15,'Monthly Detail'!19:19) -> -5 | AF18: =+SUMIF('Monthly Detail'!$4:$4, AF15,'Monthly Detail'!19:19) -> -4.4 | AG18: =+SUMIF('Monthly Detail'!$4:$4, AG15,'Monthly Detail'!19:19) -> -0.28 | AH18: =+SUMIF('Monthly Detail'!$4:$4, AH15,'Monthly Detail'!19:19) -> 5.6 | AI18: =+SUMIF('Monthly Detail'!$4:$4, AI15,'Monthly Detail'!19:19) -> -3.28 | AJ18: =+SUMIF('Monthly Detail'!$4:$4, AJ15,'Monthly Detail'!19:19) -> -5.28 | AK18: =+SUMIF('Monthly Detail'!$4:$4, AK15,'Monthly Detail'!19:19) -> 0.6 | AL18: 2 | AM18: -6 | AN18: 6 | AO18: 8 | AP18: -2 | AQ18: =+SUMIF('Monthly Detail'!$4:$4, $B$14,'Monthly Detail'!19:19) -> 10 | AR18: 2 | AS18: 12 | AT18: 2 | AU18: -2 | AV18: 1 | AW18: 0 | AX18: -3 | AY18: 1 | AZ18: 11 | BA18: 0 | BB18: 0 | BC18: 0 | BD18: 7 | BE18: 1 | BF18: -2.2 | BG18: -1.2 | BH18: 1 | BI18: -4.2 | BJ18: 2 | BK18: 6 | BL18: 6 | BM18: 1.8 | BN18: -1.4 | BO18: -1.4 | BP18: =+AQ18-AP18 -> 12 | BQ18: =+AQ18-BM18 -> 8.2
C19: # of Sessions | E19: 70 | F19: 50 | G19: 28 | H19: 28 | I19: 28 | J19: 72.666667 | K19: 28 | L19: 28 | M19: 28 | N19: 59 | O19: 65.333333 | P19: 60 | Q19: 79.666667 | R19: 137.33333 | S19: 155.66667 | T19: 129.33333 | U19: 129.33333 | V19: 129.33333 | W19: 129.33333 | X19: 57.333333 | Y19: 57.333333 | Z19: 57.333333 | AA19: 50 | AB19: 77.666667 | AC19: 111.66667 | AD19: =+SUMIF('Monthly Detail'!$4:$4, AD15,'Monthly Detail'!22:22) -> 275 | AE19: =+SUMIF('Monthly Detail'!$4:$4, AE15,'Monthly Detail'!22:22) -> 226 | AF19: =+SUMIF('Monthly Detail'!$4:$4, AF15,'Monthly Detail'!22:22) -> 247.623 | AG19: =+SUMIF('Monthly Detail'!$4:$4, AG15,'Monthly Detail'!22:22) -> 304.52174 | AH19: =+SUMIF('Monthly Detail'!$4:$4, AH15,'Monthly Detail'!22:22) -> 323.57053 | AI19: =+SUMIF('Monthly Detail'!$4:$4, AI15,'Monthly Detail'!22:22) -> 373.00336 | AJ19: =+SUMIF('Monthly Detail'!$4:$4, AJ15,'Monthly Detail'!22:22) -> 160.89476 | AK19: =+SUMIF('Monthly Detail'!$4:$4, AK15,'Monthly Detail'!22:22) -> 283.27802 | AL19: 85 | AM19: 30 | AN19: 118 | AO19: 169 | AP19: 174.33333 | AQ19: =+SUMIF('Monthly Detail'!$4:$4, $B$14,'Monthly Detail'!22:22) -> 275 | AR19: 28 | AS19: 44.957723 | AT19: 36.609377 | AU19: 54.895556 | AV19: 94.499879 | AW19: 62.003873 | AX19: 91.127991 | AY19: 85.378673 | AZ19: 115.36828 | BA19: 55.621396 | BB19: 55.621396 | BC19: 37.703277 | BD19: 65.333333 | BE19: 294.18455 | BF19: 175.84396 | BG19: 230.9412 | BH19: 248.3679 | BI19: 132.05018 | BJ19: 245.26428 | BK19: 359.98193 | BL19: 268.15975 | BM19: 344.87032 | BN19: 193.66336 | BO19: 147.13119 | BP19: =+AQ19-AP19 -> 100.66667 | BQ19: =+AQ19-BM19 -> -69.870316
C20: Hours / Day | E20: 0.2 | F20: 0.21 | G20: 0.21 | H20: 0.21 | I20: 0.21 | J20: 0.10448413 | K20: 0.11184211 | L20: 0.085869565 | M20: 0.13035714 | N20: 0.21338384 | O20: 0.15909091 | P20: 0.1984375 | Q20: 0.19279176 | R20: 0.19353693 | S20: 0.13125 | T20: 0.095567867 | U20: 0.095567867 | V20: 0.095567867 | W20: 0.095567867 | X20: 0.14345238 | Y20: 0.14345238 | Z20: 0.14345238 | AA20: 0.20568182 | AB20: 0.2652512 | AC20: 0.16241497 | AD20: =+SUMIF('Monthly Detail'!$4:$4, AD15,'Monthly Detail'!25:25) -> 0.19987021 | AE20: =+SUMIF('Monthly Detail'!$4:$4, AE15,'Monthly Detail'!25:25) -> 0.14204545 | AF20: =+SUMIF('Monthly Detail'!$4:$4, AF15,'Monthly Detail'!25:25) -> 0.14359268 | AG20: =+SUMIF('Monthly Detail'!$4:$4, AG15,'Monthly Detail'!25:25) -> 0.16938406 | AH20: =+SUMIF('Monthly Detail'!$4:$4, AH15,'Monthly Detail'!25:25) -> 0.18035714 | AI20: =+SUMIF('Monthly Detail'!$4:$4, AI15,'Monthly Detail'!25:25) -> 0.19940476 | AJ20: =+SUMIF('Monthly Detail'!$4:$4, AJ15,'Monthly Detail'!25:25) -> 0.094367589 | AK20: =+SUMIF('Monthly Detail'!$4:$4, AK15,'Monthly Detail'!25:25) -> 0.17215909 | AL20: 0.18626482 | AM20: 0.159375 | AN20: 0.20568182 | AO20: 0.2652512 | AP20: 0.19180254 | AQ20: =+SUMIF('Monthly Detail'!$4:$4, $B$14,'Monthly Detail'!25:25) -> 0.19987021 | AR20: 0.10448413 | AS20: 0.11184211 | AT20: 0.085869565 | AU20: 0.13035714 | AV20: 0.20833333 | AW20: 0.15719697 | AX20: 0.23035714 | AY20: 0.20907928 | AZ20: 0.22025862 | BA20: 0.1328125 | BB20: 0.1328125 | BC20: 0.090027701 | BD20: 0.23650794 | BE20: 0.23650794 | BF20: 0.14345238 | BG20: 0.18649733 | BH20: 0.19456522 | BI20: 0.12395833 | BJ20: 0.20568182 | BK20: 0.2652512 | BL20: 0.16241497 | BM20: 0.19180254 | BN20: 0.14204545 | BO20: 0.095567867 | BP20: =+AQ20-AP20 -> 0.0080676779 | BQ20: =+AQ20-BM20 -> 0.0080676779
C21: Total Bill Hours | E21: 78.2 | F21: 71 | G21: 92.4 | H21: 75.6 | I21: 135.66 | J21: 48.271667 | K21: 49.322368 | L21: 37.868478 | M21: 77.432143 | N21: 107.97222 | O21: 70 | P21: 82.946875 | Q21: 135.7254 | R21: 182.50533 | S21: 131.44833 | T21: 74.447368 | U21: 74.447368 | V21: 74.447368 | W21: 74.447368 | X21: 87.3125 | Y21: 87.3125 | Z21: 87.3125 | AA21: 120.6 | AB21: 212.5299 | AC21: 190.65646 | AD21: =+SUMIF('Monthly Detail'!$4:$4, AD15,'Monthly Detail'!26:26) -> 308 | AE21: =+SUMIF('Monthly Detail'!$4:$4, AE15,'Monthly Detail'!26:26) -> 158.52273 | AF21: =+SUMIF('Monthly Detail'!$4:$4, AF15,'Monthly Detail'!26:26) -> 173.6897 | AG21: =+SUMIF('Monthly Detail'!$4:$4, AG15,'Monthly Detail'!26:26) -> 213.60007 | AH21: =+SUMIF('Monthly Detail'!$4:$4, AH15,'Monthly Detail'!26:26) -> 226.96143 | AI21: =+SUMIF('Monthly Detail'!$4:$4, AI15,'Monthly Detail'!26:26) -> 261.635 | AJ21: =+SUMIF('Monthly Detail'!$4:$4, AJ15,'Monthly Detail'!26:26) -> 112.85609 | AK21: =+SUMIF('Monthly Detail'!$4:$4, AK15,'Monthly Detail'!26:26) -> 198.69914 | AL21: 94.25 | AM21: 51 | AN21: 135.75 | AO21: 221.75 | AP21: 242.63021 | AQ21: =+SUMIF('Monthly Detail'!$4:$4, $B$14,'Monthly Detail'!26:26) -> 308 | AR21: 48.271667 | AS21: 77.506579 | AT21: 63.11413 | AU21: 94.639286 | AV21: 162.91667 | AW21: 106.89394 | AX21: 157.10357 | AY21: 147.19182 | AZ21: 198.89353 | BA21: 95.890625 | BB21: 95.890625 | BC21: 65 | BD21: 125.52381 | BE21: 169.33968 | BF21: 101.22 | BG21: 132.93529 | BH21: 142.96652 | BI21: 76.01125 | BJ21: 141.18 | BK21: 207.21423 | BL21: 154.35918 | BM21: 198.51562 | BN21: 111.47727 | BO21: 84.692244 | BP21: =+AQ21-AP21 -> 65.369792 | BQ21: =+AQ21-BM21 -> 109.48438
C22: River Hours | E22: 0 | G22: 0 | H22: 0 | J22: 0 | K22: 0 | L22: 0 | M22: 0 | N22: 0 | O22: 0 | P22: 0 | Q22: 0 | R22: 0 | S22: 0 | T22: 0 | U22: 0 | V22: 0 | W22: 0 | X22: 0 | Y22: 0 | Z22: 0 | AA22: 0 | AB22: 0 | AC22: 0 | AD22: =+SUMIF('Monthly Detail'!$4:$4, AD15,'Monthly Detail'!27:27) -> 0 | AE22: =+SUMIF('Monthly Detail'!$4:$4, AE15,'Monthly Detail'!27:27) -> 0 | AF22: =+SUMIF('Monthly Detail'!$4:$4, AF15,'Monthly Detail'!27:27) -> 0 | AG22: =+SUMIF('Monthly Detail'!$4:$4, AG15,'Monthly Detail'!27:27) -> 0 | AH22: =+SUMIF('Monthly Detail'!$4:$4, AH15,'Monthly Detail'!27:27) -> 0 | AI22: =+SUMIF('Monthly Detail'!$4:$4, AI15,'Monthly Detail'!27:27) -> 0 | AJ22: =+SUMIF('Monthly Detail'!$4:$4, AJ15,'Monthly Detail'!27:27) -> 0 | AK22: =+SUMIF('Monthly Detail'!$4:$4, AK15,'Monthly Detail'!27:27) -> 0 | AL22: 0 | AM22: 0 | AN22: 0 | AO22: 0 | AP22: 0 | AQ22: =+SUMIF('Monthly Detail'!$4:$4, O14,'Monthly Detail'!27:27) -> 0 | AR22: 0 | AS22: 0 | AT22: 0 | AU22: 0 | AV22: 0 | AW22: 0 | AX22: 0 | AY22: 0 | AZ22: 0 | BA22: 0 | BB22: 0 | BC22: 0 | BD22: 0 | BE22: 0 | BF22: 0 | BG22: 0 | BH22: 0 | BI22: 0 | BJ22: 0 | BK22: 0 | BL22: 0 | BM22: 0 | BN22: 0 | BO22: 0 | BP22: =+AQ22-AP22 -> 0 | BQ22: =+AQ22-BM22 -> 0
C23: Realized / Effective Bill Rate | E23: 62.5 | F23: 62.5 | G23: 62.5 | H23: 62.5 | I23: 62.5 | J23: 62.5 | K23: 62.5 | L23: 62.5 | M23: 62.5 | N23: 62.5 | O23: 62.5 | P23: 73.189795 | Q23: 66.830846 | R23: 63.108031 | S23: 63.681998 | T23: 74.373731 | U23: 74.373731 | V23: 74.373731 | W23: 74.373731 | X23: 75.929718 | Y23: 75.929718 | Z23: 75.929718 | AA23: 87.704412 | AB23: 81.06214 | AC23: 89.652296 | AD23: =+SUMIF('Monthly Detail'!$4:$4, AD15,'Monthly Detail'!33:33) -> 127.80237 | AE23: =+SUMIF('Monthly Detail'!$4:$4, AE15,'Monthly Detail'!33:33) -> 80.633466 | AF23: =+SUMIF('Monthly Detail'!$4:$4, AF15,'Monthly Detail'!33:33) -> 103.88481 | AG23: =+SUMIF('Monthly Detail'!$4:$4, AG15,'Monthly Detail'!33:33) -> 100.28972 | AH23: =+SUMIF('Monthly Detail'!$4:$4, AH15,'Monthly Detail'!33:33) -> 88.740993 | AI23: =+SUMIF('Monthly Detail'!$4:$4, AI15,'Monthly Detail'!33:33) -> 78.765376 | AJ23: =+SUMIF('Monthly Detail'!$4:$4, AJ15,'Monthly Detail'!33:33) -> 80.99641 | AK23: =+SUMIF('Monthly Detail'!$4:$4, AK15,'Monthly Detail'!33:33) -> 79.494032 | AL23: 60.531353 | AM23: 84.475686 | AN23: 66.746888 | AO23: 63.635896 | AP23: 98.302969 | AQ23: =+SUMIF('Monthly Detail'!$4:$4, $B$14,'Monthly Detail'!33:33) -> 127.80237 | AR23: 62.5 | AS23: 62.5 | AT23: 62.5 | AU23: 62.5 | AV23: 62.5 | AW23: 62.5 | AX23: 62.5 | AY23: 62.5 | AZ23: 62.5 | BA23: 62.5 | BB23: 62.5 | BC23: 62.5 | BD23: 76.028235 | BE23: 75.085554 | BF23: 73.972048 | BG23: 74.094669 | BH23: 75.205939 | BI23: 76.567142 | BJ23: 77.054738 | BK23: 76.68896 | BL23: 78.676419 | BM23: 78.861731 | BN23: 79.058869 | BO23: 74.373731 | BP23: =+AQ23-AP23 -> 29.499401 | BQ23: =+AQ23-BM23 -> 48.940639
BP24: =+AQ24-AP24 -> 0 | BQ24: =+AQ24-BM24 -> 0
C25: Utilization % | E25: 0.025 | F25: 0.02625 | G25: 0.02625 | H25: 0.02625 | I25: 0.02625 | J25: 0.013060516 | K25: 0.013980263 | L25: 0.010733696 | M25: 0.016294643 | N25: 0.02667298 | O25: 0.019886364 | P25: 0.024804687 | Q25: 0.02409897 | R25: 0.024192116 | S25: 0.01640625 | T25: 0.011945983 | U25: 0.011945983 | V25: 0.011945983 | W25: 0.011945983 | X25: 0.017931548 | Y25: 0.017931548 | Z25: 0.017931548 | AA25: 0.025710227 | AB25: 0.0331564 | AC25: 0.020301871 | AD25: =+SUMIF('Monthly Detail'!$4:$4, AD15,'Monthly Detail'!49:49) -> 0.024983777 | AE25: =+SUMIF('Monthly Detail'!$4:$4, AE15,'Monthly Detail'!49:49) -> 0.017755682 | AF25: =+SUMIF('Monthly Detail'!$4:$4, AF15,'Monthly Detail'!49:49) -> 0.017949085 | AG25: =+SUMIF('Monthly Detail'!$4:$4, AG15,'Monthly Detail'!49:49) -> 0.021173007 | AH25: =+SUMIF('Monthly Detail'!$4:$4, AH15,'Monthly Detail'!49:49) -> 0.022544643 | AI25: =+SUMIF('Monthly Detail'!$4:$4, AI15,'Monthly Detail'!49:49) -> 0.024925595 | AJ25: =+SUMIF('Monthly Detail'!$4:$4, AJ15,'Monthly Detail'!49:49) -> 0.011795949 | AK25: =+SUMIF('Monthly Detail'!$4:$4, AK15,'Monthly Detail'!49:49) -> 0.021519886 | AL25: 0.023283103 | AM25: 0.019921875 | AN25: 0.025710227 | AO25: 0.0331564 | AP25: 0.023975317 | AQ25: =+SUMIF('Monthly Detail'!$4:$4, $B$14,'Monthly Detail'!49:49) -> 0.024983777 | AR25: 0.013060516 | AS25: 0.013980263 | AT25: 0.010733696 | AU25: 0.016294643 | AV25: 0.026041667 | AW25: 0.019649621 | AX25: 0.028794643 | AY25: 0.02613491 | AZ25: 0.027532328 | BA25: 0.016601562 | BB25: 0.016601562 | BC25: 0.011253463 | BD25: 0.029563492 | BE25: 0.029563492 | BF25: 0.017931548 | BG25: 0.023312166 | BH25: 0.024320652 | BI25: 0.015494792 | BJ25: 0.025710227 | BK25: 0.0331564 | BL25: 0.020301871 | BM25: 0.023975317 | BN25: 0.017755682 | BO25: 0.011945983 | BP25: =+AQ25-AP25 -> 0.0010084597 | BQ25: =+AQ25-BM25 -> 0.0010084597
B26: Expenses | BP26: =+AQ26-AP26 -> 0 | BQ26: =+AQ26-BM26 -> 0
B27: Subcontractors | N27: 0 | O27: 0 | P27: 650 | Q27: 1612.624 | R27: 3394.8663 | S27: 1928.1833 | T27: 0 | U27: 0 | V27: 0 | W27: 0 | X27: 450 | Y27: 450 | Z27: 450 | AA27: 981.65746 | AB27: 4023.9944 | AC27: 450 | AL27: 0 | AM27: 0 | AN27: 610 | AO27: 900 | AP27: 1081.7708 | AQ27: =+SUMIF('Monthly Detail'!$4:$4, $B$14,'Monthly Detail'!63:63) -> 6255 | AV27: 0 | AW27: 0 | AX27: 0 | AY27: 0 | AZ27: 1035.7414 | BA27: 0 | BC27: 0 | BD27: 919.6069 | BE27: 2106.1905 | BF27: 600 | BG27: 1173.2353 | BH27: 2952.0761 | BI27: 600 | BJ27: 1649 | BK27: 3994.4258 | BL27: 821.63265 | BM27: 1007.8125 | BN27: 82.141148 | BO27: 0 | BP27: =+AQ27-AP27 -> 5173.2292 | BQ27: =+AQ27-BM27 -> 5247.1875
B28: Gross Proft | E28: =+E2-E27 -> 0 | F28: =+F2-F27 -> 0 | G28: 5166.6267 | H28: 3957.7217 | I28: 7569.7233 | J28: 2255.7185 | K28: 1022.188 | L28: 1435.4299 | M28: 3942.5625 | N28: 4387.4071 | O28: 3311.2272 | P28: =+P16-P27 -> 5420.8648 | Q28: 7458.0193 | R28: 8122.6854 | S28: 6442.7091 | T28: 4937.9286 | U28: 4937.9286 | V28: 4937.9286 | W28: 4937.9286 | X28: 6179.6135 | Y28: 6179.6135 | Z28: 6179.6135 | AA28: 9595.4946 | AB28: 13204.134 | AC28: 16642.79 | AD28: =+AD2-AD27 -> 0 | AE28: =+AE2-AE27 -> 0 | AF28: =+AF2-AF27 -> 0 | AG28: =+AG2-AG27 -> 0 | AH28: =+AH2-AH27 -> 0 | AI28: =+AI2-AI27 -> 0 | AJ28: =+AJ2-AJ27 -> 0 | AK28: =+AK2-AK27 -> 0 | AL28: 5015.13 | AM28: 4308.26 | AN28: 8450.89 | AO28: 13211.26 | AP28: 22769.499 | AQ28: =+AQ16-AQ27 -> 33108.13 | AR28: =+AR2-AR27 -> 0 | AS28: =+AS2-AS27 -> 0 | AT28: =+AT2-AT27 -> 0 | AU28: =+AU2-AU27 -> 0 | AV28: =+AV2-AV27 -> 0 | AW28: =+AW16-AW27 -> 6730.3712 | AX28: =+AX16-AX27 -> 9868.4732 | AY28: =+AY16-AY27 -> 9248.9885 | AZ28: =+AZ2-AZ27 -> -1035.7414 | BA28: 0 | BB28: =+BB2-BB27 -> 0 | BC28: =+BC16-BC27 -> 4112 | BD28: 8623.7468 | BE28: 10608.773 | BF28: 6887.4507 | BG28: 8676.5614 | BH28: 7799.8555 | BI28: 5219.9642 | BJ28: 9229.588 | BK28: 11896.618 | BL28: 11322.795 | BM28: 14647.473 | BN28: 8731.126 | BO28: 6298.8782 | BP28: =+AQ28-AP28 -> 10338.631 | BQ28: =+AQ28-BM28 -> 18460.657
B29: GM% | K29: =+K28/K2 -> #DIV/0! | L29: 0.59259456 | M29: 0.8878797 | N29: 0.72582965 | O29: 0.8206235 | P29: =+P28/P16 -> 0.89293123 | Q29: 0.82221503 | R29: 0.7052441 | S29: 0.76965618 | T29: 0.89181728 | U29: 0.89181728 | V29: 0.89181728 | W29: 0.89181728 | X29: 0.93212274 | Y29: 0.93212274 | Z29: 0.93212274 | AA29: 0.90719076 | AB29: 0.76642882 | AC29: 0.97367311 | AI29: 0.87906392 | AJ29: 0.87906392 | AK29: 0.87906392 | AL29: 0.87906392 | AM29: 1 | AN29: 0.9326777 | AO29: 0.93622115 | AP29: 0.95464515 | AQ29: =+AQ28/AQ16 -> 0.84109495 | AR29: =+AR28/AR16 -> 0 | AS29: =+AS28/AS16 -> 0 | AT29: =+AT28/AT16 -> 0 | AU29: =+AU28/AU16 -> 0 | AV29: =+AV28/AV16 -> 0 | AW29: =+AW28/AW16 -> 1 | AX29: =+AX28/AX16 -> 1 | ... AZ29: =+AZ28/AZ16 -> -0.10159609 | BA29: 0 | BB29: =+BB28/BB16 -> 0 | BC29: =+BC28/BC16 -> 1 | BD29: 0.90363902 | BE29: 0.8343534 | BF29: 0.91986592 | BG29: 0.88088736 | BH29: 0.7254376 | BI29: 0.89690658 | BJ29: 0.84841783 | BK29: 0.74863667 | BL29: 0.93234489 | BM29: 0.93562478 | BN29: 0.99067983 | BO29: 1 | BP29: =+AQ29-AP29 -> -0.11355019 | BQ29: =+AQ29-BM29 -> -0.094529825
B30: Events | K30: 1179.44 | L30: 0 | M30: 2358.88 | N30: 1179.44 | O30: 0 | P30: 0 | Q30: 0 | R30: 1400 | S30: 0 | T30: 0 | X30: 0 | Y30: 0 | Z30: 0 | AA30: 0 | AB30: 0 | AC30: 0 | AI30: =+SUMIF('Monthly Detail'!$4:$4, AI15,'Monthly Detail'!69:69) -> 0 | AJ30: =+SUMIF('Monthly Detail'!$4:$4, AJ15,'Monthly Detail'!69:69) -> 0 | AK30: =+SUMIF('Monthly Detail'!$4:$4, AK15,'Monthly Detail'!69:69) -> 0 | AL30: 0 | AM30: 665.56 | AN30: 0 | AO30: 0 | AP30: 0 | AQ30: =+SUMIF('Monthly Detail'!$4:$4, $B$14,'Monthly Detail'!69:69) -> 0 | AS30: 0 | AW30: 0 | AX30: 0 | AY30: 0 | BA30: 0 | BC30: 0 | BD30: 0 | BE30: 0 | BF30: 0 | BG30: 0 | BH30: 0 | BI30: 0 | BJ30: 0 | BK30: 0 | BL30: 0 | BM30: 0 | BN30: 0 | BO30: 0 | BP30: =+AQ30-AP30 -> 0 | BQ30: =+AQ30-BM30 -> 0
B31: Owner Payroll Burden | X31: 2172.5375 | Y31: 2172.5375 | Z31: 2172.5375 | AA31: 3660.1 | AB31: 3660.1 | AC31: 5274.85 | AP31: 12810.35 | AQ31: =+SUMIF('Monthly Detail'!$4:$4, $B$14,'Monthly Detail'!78:78) -> 15447.77 | BD31: 2367.8875 | BE31: 2172.5375 | BF31: 2172.5375 | BG31: 2172.5375 | BH31: 2172.5375 | BI31: 2172.5375 | BJ31: 2172.5375 | BK31: 2172.5375 | BL31: 2172.5375 | BM31: 2172.5375 | BN31: 2172.5375 | BO31: 2172.5375 | BP31: =+AQ31-AP31 -> 2637.42 | BQ31: =+AQ31-BM31 -> 13275.233
B32: Travel | P32: 0 | Q32: 75 | R32: 75 | S32: 75 | T32: 75 | U32: 75 | V32: 75 | W32: 75 | X32: 75 | Y32: 75 | Z32: 75 | AA32: 75 | AB32: 75 | AC32: 75 | AN32: 17.54 | AO32: 15.71 | AP32: 75 | AQ32: =+SUMIF('Monthly Detail'!$4:$4, $B$14,'Monthly Detail'!82:82) -> 222.44 | AX32: 0 | AY32: 0 | BA32: 0 | BC32: 0 | BD32: 75 | BE32: 75 | BF32: 75 | BG32: 75 | BH32: 75 | BI32: 75 | BJ32: 75 | BK32: 75 | BL32: 75 | BM32: 75 | BN32: 75 | BO32: 75 | BP32: =+AQ32-AP32 -> 147.44 | BQ32: =+AQ32-BM32 -> 147.44
B33: Computer & Software | E33: 12 | F33: 12 | G33: 12 | H33: 12 | I33: 12 | J33: 12 | K33: 12 | L33: 12 | M33: 12 | N33: 12 | O33: 114.89833 | P33: 1300.7667 | Q33: 111.76667 | R33: 304.78667 | S33: 303.21333 | T33: 316.34833 | U33: 316.34833 | V33: 316.34833 | W33: 316.34833 | X33: 150 | Y33: 150 | Z33: 150 | AA33: 150 | AB33: 150 | AC33: 150 | AD33: =+SUMIF('Monthly Detail'!$4:$4, AD15,'Monthly Detail'!83:83) -> 709.4 | AE33: =+SUMIF('Monthly Detail'!$4:$4, AE15,'Monthly Detail'!83:83) -> 150 | AF33: =+SUMIF('Monthly Detail'!$4:$4, AF15,'Monthly Detail'!83:83) -> 150 | AG33: =+SUMIF('Monthly Detail'!$4:$4, AG15,'Monthly Detail'!83:83) -> 479.656 | AH33: =+SUMIF('Monthly Detail'!$4:$4, AH15,'Monthly Detail'!83:83) -> 479.656 | AI33: =+SUMIF('Monthly Detail'!$4:$4, AI15,'Monthly Detail'!83:83) -> 479.656 | AJ33: =+SUMIF('Monthly Detail'!$4:$4, AJ15,'Monthly Detail'!83:83) -> 479.656 | AK33: =+SUMIF('Monthly Detail'!$4:$4, AK15,'Monthly Detail'!83:83) -> 479.656 | AL33: 154.47 | AM33: 310.12 | AN33: 1251.13 | AO33: 14.81 | AP33: 150 | AQ33: =+SUMIF('Monthly Detail'!$4:$4, $B$14,'Monthly Detail'!83:83) -> 709.4 | AR33: 12 | AS33: 12 | AT33: 12 | AU33: 12 | AV33: 12 | AW33: 12 | AX33: 12 | AY33: 12 | AZ33: 12 | BA33: 12 | BB33: 12 | BC33: 12 | BD33: 150 | BE33: 150 | BF33: 150 | BG33: 150 | BH33: 150 | BI33: 150 | BJ33: 150 | BK33: 150 | BL33: 150 | BM33: 150 | BN33: 150 | BO33: 150 | BP33: =+AQ33-AP33 -> 559.4 | BQ33: =+AQ33-BM33 -> 559.4
B34: Donations/Gifts | E34: 100 | F34: 100 | G34: 100 | H34: 100 | I34: 100 | J34: 100 | K34: 100 | L34: 100 | M34: 100 | N34: 100 | O34: 100 | P34: 100 | Q34: 100 | R34: 100 | S34: 100 | T34: 100 | U34: 100 | V34: 100 | W34: 100 | X34: 100 | Y34: 100 | Z34: 100 | AA34: 100 | AB34: 100 | AC34: 100 | AD34: =+SUMIF('Monthly Detail'!$4:$4, AD15,'Monthly Detail'!84:84) -> 150.39 | AE34: =+SUMIF('Monthly Detail'!$4:$4, AE15,'Monthly Detail'!84:84) -> 100 | AF34: =+SUMIF('Monthly Detail'!$4:$4, AF15,'Monthly Detail'!84:84) -> 100 | AG34: =+SUMIF('Monthly Detail'!$4:$4, AG15,'Monthly Detail'!84:84) -> 100 | AH34: =+SUMIF('Monthly Detail'!$4:$4, AH15,'Monthly Detail'!84:84) -> 100 | AI34: =+SUMIF('Monthly Detail'!$4:$4, AI15,'Monthly Detail'!84:84) -> 100 | AJ34: =+SUMIF('Monthly Detail'!$4:$4, AJ15,'Monthly Detail'!84:84) -> 100 | AK34: =+SUMIF('Monthly Detail'!$4:$4, AK15,'Monthly Detail'!84:84) -> 100 | AL34: 141.19 | AM34: 0 | AN34: 0 | AO34: 0 | AP34: 100 | AQ34: =+SUMIF('Monthly Detail'!$4:$4, $B$14,'Monthly Detail'!84:84) -> 150.39 | AR34: 100 | AS34: 100 | AT34: 100 | AU34: 100 | AV34: 100 | AW34: 100 | AX34: 100 | AY34: 100 | AZ34: 100 | BA34: 100 | BB34: 100 | BC34: 100 | BD34: 100 | BE34: 0 | BF34: 0 | BG34: 50 | BH34: 0 | BI34: 0 | BJ34: 50 | BK34: 0 | BL34: 0 | BM34: 50 | BN34: 50 | BO34: 50 | BP34: =+AQ34-AP34 -> 50.39 | BQ34: =+AQ34-BM34 -> 100.39
B35: Fees/Subscriptions | E35: 0 | F35: 0 | G35: 0 | H35: 13.86 | I35: 0 | J35: 0 | K35: 0 | L35: 0 | M35: 0 | N35: 0 | O35: 0 | P35: 0 | Q35: 0 | R35: 42.58 | S35: 42.58 | T35: 42.58 | U35: 42.58 | V35: 42.58 | W35: 42.58 | X35: 42.58 | Y35: 42.58 | Z35: 42.58 | AA35: 0 | AB35: 0 | AC35: 0 | AD35: =+SUMIF('Monthly Detail'!$4:$4, AD15,'Monthly Detail'!85:85) -> 0 | AE35: =+SUMIF('Monthly Detail'!$4:$4, AE15,'Monthly Detail'!85:85) -> 0 | AF35: =+SUMIF('Monthly Detail'!$4:$4, AF15,'Monthly Detail'!85:85) -> 0 | AG35: =+SUMIF('Monthly Detail'!$4:$4, AG15,'Monthly Detail'!85:85) -> 0 | AH35: =+SUMIF('Monthly Detail'!$4:$4, AH15,'Monthly Detail'!85:85) -> 0 | AI35: =+SUMIF('Monthly Detail'!$4:$4, AI15,'Monthly Detail'!85:85) -> 0 | AJ35: =+SUMIF('Monthly Detail'!$4:$4, AJ15,'Monthly Detail'!85:85) -> 0 | AK35: =+SUMIF('Monthly Detail'!$4:$4, AK15,'Monthly Detail'!85:85) -> 0 | AL35: 0 | AM35: 0 | AN35: 0 | AO35: 42.58 | AP35: 0 | AQ35: =+SUMIF('Monthly Detail'!$4:$4, $B$14,'Monthly Detail'!85:85) -> 0 | AR35: 0 | AS35: 0 | AT35: 0 | AU35: 0 | AV35: 0 | AW35: 0 | AX35: 0 | AY35: 0 | AZ35: 0 | BA35: 0 | BB35: 0 | BC35: 0 | BD35: 42.58 | BE35: 42.58 | BF35: 42.58 | BG35: 42.58 | BH35: 42.58 | BI35: 42.58 | BJ35: 42.58 | BK35: 42.58 | BL35: 42.58 | BM35: 42.58 | BN35: 42.58 | BO35: 42.58 | BP35: =+AQ35-AP35 -> 0 | BQ35: =+AQ35-BM35 -> -42.58
B36: Finance & Accounting | E36: 75 | F36: 225 | G36: 75 | H36: 75 | I36: 225 | J36: 75 | K36: 112.5 | L36: 225 | M36: 75 | N36: 75 | O36: 225 | P36: 150 | Q36: 200 | R36: 200 | S36: 200 | T36: 200 | U36: 200 | V36: 200 | W36: 200 | X36: 200 | Y36: 200 | Z36: 200 | AA36: 375 | AB36: 500 | AC36: 275 | AD36: =+SUMIF('Monthly Detail'!$4:$4, AD15,'Monthly Detail'!86:86) -> 581.25 | AE36: =+SUMIF('Monthly Detail'!$4:$4, AE15,'Monthly Detail'!86:86) -> 425 | AF36: =+SUMIF('Monthly Detail'!$4:$4, AF15,'Monthly Detail'!86:86) -> 275 | AG36: =+SUMIF('Monthly Detail'!$4:$4, AG15,'Monthly Detail'!86:86) -> 450 | AH36: =+SUMIF('Monthly Detail'!$4:$4, AH15,'Monthly Detail'!86:86) -> 275 | AI36: =+SUMIF('Monthly Detail'!$4:$4, AI15,'Monthly Detail'!86:86) -> 275 | AJ36: =+SUMIF('Monthly Detail'!$4:$4, AJ15,'Monthly Detail'!86:86) -> 450 | AK36: =+SUMIF('Monthly Detail'!$4:$4, AK15,'Monthly Detail'!86:86) -> 275 | AL36: 75 | AM36: 225 | AN36: 185 | AO36: 207.5 | AP36: 600 | AQ36: =+SUMIF('Monthly Detail'!$4:$4, $B$14,'Monthly Detail'!86:86) -> 581.25 | AR36: 75 | AS36: 75 | AT36: 225 | AU36: 75 | AV36: 75 | AW36: 225 | AX36: 75 | AY36: 75 | AZ36: 225 | BA36: 75 | BB36: 75 | BC36: 225 | BD36: 200 | BE36: 200 | BF36: 600 | BG36: 350 | BH36: 200 | BI36: 200 | BJ36: 350 | BK36: 200 | BL36: 200 | BM36: 350 | BN36: 200 | BO36: 200 | BP36: =+AQ36-AP36 -> -18.75 | BQ36: =+AQ36-BM36 -> 231.25
B37: Bank Fees | E37: 28.905 | F37: 20.336667 | G37: 58.913333 | H37: 38.105 | I37: 30.791667 | J37: 31.454 | K37: 23.345 | L37: 17.718333 | M37: 9.9583333 | N37: 5.8833333 | O37: 2.45 | P37: 2.45 | Q37: 8.28 | R37: 13.216667 | S37: 21.366667 | T37: 30.3 | U37: 30.3 | V37: 30.3 | W37: 30.3 | X37: 29 | Y37: 29 | Z37: 29 | AA37: 13 | AB37: 10.4 | AC37: 8.6666667 | AD37: =+SUMIF('Monthly Detail'!$4:$4, AD15,'Monthly Detail'!87:87) -> 80.44 | AE37: =+SUMIF('Monthly Detail'!$4:$4, AE15,'Monthly Detail'!87:87) -> 13.74 | AF37: =+SUMIF('Monthly Detail'!$4:$4, AF15,'Monthly Detail'!87:87) -> 13.74 | AG37: =+SUMIF('Monthly Detail'!$4:$4, AG15,'Monthly Detail'!87:87) -> 13.74 | AH37: =+SUMIF('Monthly Detail'!$4:$4, AH15,'Monthly Detail'!87:87) -> 13.74 | AI37: =+SUMIF('Monthly Detail'!$4:$4, AI15,'Monthly Detail'!87:87) -> 13.74 | AJ37: =+SUMIF('Monthly Detail'!$4:$4, AJ15,'Monthly Detail'!87:87) -> 13.74 | AK37: =+SUMIF('Monthly Detail'!$4:$4, AK15,'Monthly Detail'!87:87) -> 13.74 | AL37: 3.5 | AM37: 0 | AN37: 31.6 | AO37: 0 | AP37: 0.33333333 | AQ37: =+SUMIF('Monthly Detail'!$4:$4, $B$14,'Monthly Detail'!87:87) -> 80.44 | AR37: 31.454 | AS37: 31.454 | AT37: 31.454 | AU37: 31.454 | AV37: 31.454 | AW37: 31.454 | AX37: 31.454 | AY37: 31.454 | AZ37: 31.454 | BA37: 31.454 | BB37: 31.454 | BC37: 31.454 | BD37: 29 | BE37: 30.3 | BF37: 30.3 | BG37: 30.3 | BH37: 30.3 | BI37: 30.3 | BJ37: 30.3 | BK37: 30.3 | BL37: 30.3 | BM37: 30.3 | BN37: 30.3 | BO37: 30.3 | BP37: =+AQ37-AP37 -> 80.106667 | BQ37: =+AQ37-BM37 -> 50.14
B38: Meals and Entertainment | E38: 0 | G38: 0 | H38: 0 | I38: 0 | K38: 0 | L38: 0 | M38: 0 | N38: 0 | O38: 0 | P38: 0 | Q38: 218.02 | R38: 106.49667 | S38: 121.3 | T38: 289.14 | U38: 289.14 | V38: 289.14 | W38: 289.14 | X38: 295.735 | Y38: 295.735 | Z38: 295.735 | AA38: 225.6 | AB38: 294.6475 | AC38: 352.7975 | AD38: =+SUMIF('Monthly Detail'!$4:$4, AD15,'Monthly Detail'!88:88) -> 677.01 | AE38: =+SUMIF('Monthly Detail'!$4:$4, AE15,'Monthly Detail'!88:88) -> 411.915 | AF38: =+SUMIF('Monthly Detail'!$4:$4, AF15,'Monthly Detail'!88:88) -> 411.915 | AG38: =+SUMIF('Monthly Detail'!$4:$4, AG15,'Monthly Detail'!88:88) -> 411.915 | AH38: =+SUMIF('Monthly Detail'!$4:$4, AH15,'Monthly Detail'!88:88) -> 411.915 | AI38: =+SUMIF('Monthly Detail'!$4:$4, AI15,'Monthly Detail'!88:88) -> 411.915 | AJ38: =+SUMIF('Monthly Detail'!$4:$4, AJ15,'Monthly Detail'!88:88) -> 411.915 | AK38: =+SUMIF('Monthly Detail'!$4:$4, AK15,'Monthly Detail'!88:88) -> 411.915 | AL38: 0 | AM38: 0 | AN38: 218.02 | AO38: 57.06 | AP38: 358.896 | AQ38: =+SUMIF('Monthly Detail'!$4:$4, $B$14,'Monthly Detail'!88:88) -> 677.01 | AW38: 0 | AX38: 0 | AY38: 0 | BD38: 247.135 | BE38: 289.14 | BF38: 289.14 | BG38: 289.14 | BH38: 289.14 | BI38: 289.14 | BJ38: 289.14 | BK38: 289.14 | BL38: 289.14 | BM38: 289.14 | BN38: 289.14 | BO38: 289.14 | BP38: =+AQ38-AP38 -> 318.114 | BQ38: =+AQ38-BM38 -> 387.87
