Workbook

Sheet 1

Sheet Annual Summary
D17: 2023 | E17: =+D17+1 | F17: =+E17+1 | G17: =+F17+1 | H17: =+G17+1 | I17: =+H17+1 | J17: =+I17+1 | K17: =+J17+1
C19: Service Income | D19: =SUMIF('Monthly Detail'!$1:$1,'Annual Summary'!D$17, 'Monthly Detail'!9:9) | E19: =SUMIF('Monthly Detail'!$1:$1,'Annual Summary'!E$17, 'Monthly Detail'!9:9) | F19: =SUMIF('Monthly Detail'!$1:$1,'Annual Summary'!F$17, 'Monthly Detail'!9:9) | G19: =SUMIF('Monthly Detail'!$1:$1,'Annual Summary'!G$17, 'Monthly Detail'!9:9) | H19: =SUMIF('Monthly Detail'!$1:$1,'Annual Summary'!H$17, 'Monthly Detail'!9:9) | I19: =SUMIF('Monthly Detail'!$1:$1,'Annual Summary'!I$17, 'Monthly Detail'!9:9) | J19: =SUMIF('Monthly Detail'!$1:$1,'Annual Summary'!J$17, 'Monthly Detail'!9:9) | K19: =SUMIF('Monthly Detail'!$1:$1,'Annual Summary'!K$17, 'Monthly Detail'!9:9)
C20: Misc | D20: =SUMIF('Monthly Detail'!$1:$1,'Annual Summary'!D$17, 'Monthly Detail'!12:12) | E20: =SUMIF('Monthly Detail'!$1:$1,'Annual Summary'!E$17, 'Monthly Detail'!12:12) | F20: =SUMIF('Monthly Detail'!$1:$1,'Annual Summary'!F$17, 'Monthly Detail'!12:12) | G20: =SUMIF('Monthly Detail'!$1:$1,'Annual Summary'!G$17, 'Monthly Detail'!12:12) | H20: =SUMIF('Monthly Detail'!$1:$1,'Annual Summary'!H$17, 'Monthly Detail'!12:12) | I20: =SUMIF('Monthly Detail'!$1:$1,'Annual Summary'!I$17, 'Monthly Detail'!12:12) | J20: =SUMIF('Monthly Detail'!$1:$1,'Annual Summary'!J$17, 'Monthly Detail'!12:12) | K20: =SUMIF('Monthly Detail'!$1:$1,'Annual Summary'!K$17, 'Monthly Detail'!12:12)
C21: Total Income | D21: =SUM(D19:D20) | E21: =SUM(E19:E20) | F21: =SUM(F19:F20) | G21: =SUM(G19:G20) | H21: =SUM(H19:H20) | I21: =SUM(I19:I20) | J21: =SUM(J19:J20) | K21: =SUM(K19:K20)
C22: # of Appointments | D22: =SUMIF('Monthly Detail'!$1:$1,'Annual Summary'!D$17, 'Monthly Detail'!15:15) | E22: =SUMIF('Monthly Detail'!$1:$1,'Annual Summary'!E$17, 'Monthly Detail'!15:15) | F22: =SUMIF('Monthly Detail'!$1:$1,'Annual Summary'!F$17, 'Monthly Detail'!15:15) | G22: =SUMIF('Monthly Detail'!$1:$1,'Annual Summary'!G$17, 'Monthly Detail'!15:15) | H22: =SUMIF('Monthly Detail'!$1:$1,'Annual Summary'!H$17, 'Monthly Detail'!15:15) | I22: =SUMIF('Monthly Detail'!$1:$1,'Annual Summary'!I$17, 'Monthly Detail'!15:15) | J22: =SUMIF('Monthly Detail'!$1:$1,'Annual Summary'!J$17, 'Monthly Detail'!15:15) | K22: =SUMIF('Monthly Detail'!$1:$1,'Annual Summary'!K$17, 'Monthly Detail'!15:15)
C23: MRR | D23: =AVERAGEIF('Monthly Detail'!$1:$1,'Annual Summary'!D$17, 'Monthly Detail'!41:41) | E23: =AVERAGEIF('Monthly Detail'!$1:$1,'Annual Summary'!E$17, 'Monthly Detail'!41:41) | F23: =AVERAGEIF('Monthly Detail'!$1:$1,'Annual Summary'!F$17, 'Monthly Detail'!41:41) | G23: =AVERAGEIF('Monthly Detail'!$1:$1,'Annual Summary'!G$17, 'Monthly Detail'!41:41) | H23: =AVERAGEIF('Monthly Detail'!$1:$1,'Annual Summary'!H$17, 'Monthly Detail'!41:41) | I23: =AVERAGEIF('Monthly Detail'!$1:$1,'Annual Summary'!I$17, 'Monthly Detail'!41:41) | J23: =AVERAGEIF('Monthly Detail'!$1:$1,'Annual Summary'!J$17, 'Monthly Detail'!41:41) | K23: =AVERAGEIF('Monthly Detail'!$1:$1,'Annual Summary'!K$17, 'Monthly Detail'!41:41)
C24: Recurring Client Base | D24: =AVERAGEIF('Monthly Detail'!$1:$1,'Annual Summary'!D$17, 'Monthly Detail'!17:17) | E24: =AVERAGEIF('Monthly Detail'!$1:$1,'Annual Summary'!E$17, 'Monthly Detail'!17:17) | F24: =AVERAGEIF('Monthly Detail'!$1:$1,'Annual Summary'!F$17, 'Monthly Detail'!17:17) | G24: =AVERAGEIF('Monthly Detail'!$1:$1,'Annual Summary'!G$17, 'Monthly Detail'!17:17) | H24: =AVERAGEIF('Monthly Detail'!$1:$1,'Annual Summary'!H$17, 'Monthly Detail'!17:17) | I24: =AVERAGEIF('Monthly Detail'!$1:$1,'Annual Summary'!I$17, 'Monthly Detail'!17:17) | J24: =AVERAGEIF('Monthly Detail'!$1:$1,'Annual Summary'!J$17, 'Monthly Detail'!17:17) | K24: =AVERAGEIF('Monthly Detail'!$1:$1,'Annual Summary'!K$17, 'Monthly Detail'!17:17)
C25: YOY Compounded Growth % | E25: - | F25: =(F21/E21)-1 | G25: =(G21/F21)-1 | H25: =(H21/G21)-1 | I25: =(I21/H21)-1 | J25: =(J21/I21)-1 | K25: =(K21/J21)-1
C27: Materials - COGS | D27: =SUMIF('Monthly Detail'!$1:$1,'Annual Summary'!D$17, 'Monthly Detail'!58:58) | E27: =SUMIF('Monthly Detail'!$1:$1,'Annual Summary'!E$17, 'Monthly Detail'!58:58) | F27: =SUMIF('Monthly Detail'!$1:$1,'Annual Summary'!F$17, 'Monthly Detail'!58:58) | G27: =SUMIF('Monthly Detail'!$1:$1,'Annual Summary'!G$17, 'Monthly Detail'!58:58) | H27: =SUMIF('Monthly Detail'!$1:$1,'Annual Summary'!H$17, 'Monthly Detail'!58:58) | I27: =SUMIF('Monthly Detail'!$1:$1,'Annual Summary'!I$17, 'Monthly Detail'!58:58) | J27: =SUMIF('Monthly Detail'!$1:$1,'Annual Summary'!J$17, 'Monthly Detail'!58:58) | K27: =SUMIF('Monthly Detail'!$1:$1,'Annual Summary'!K$17, 'Monthly Detail'!58:58)
C28: Software - COS | D28: =SUMIF('Monthly Detail'!$1:$1,'Annual Summary'!D$17, 'Monthly Detail'!59:59) | E28: =SUMIF('Monthly Detail'!$1:$1,'Annual Summary'!E$17, 'Monthly Detail'!59:59) | F28: =SUMIF('Monthly Detail'!$1:$1,'Annual Summary'!F$17, 'Monthly Detail'!59:59) | G28: =SUMIF('Monthly Detail'!$1:$1,'Annual Summary'!G$17, 'Monthly Detail'!59:59) | H28: =SUMIF('Monthly Detail'!$1:$1,'Annual Summary'!H$17, 'Monthly Detail'!59:59) | I28: =SUMIF('Monthly Detail'!$1:$1,'Annual Summary'!I$17, 'Monthly Detail'!59:59) | J28: =SUMIF('Monthly Detail'!$1:$1,'Annual Summary'!J$17, 'Monthly Detail'!59:59) | K28: =SUMIF('Monthly Detail'!$1:$1,'Annual Summary'!K$17, 'Monthly Detail'!59:59)
C29: Contractors - COS | D29: =SUMIF('Monthly Detail'!$1:$1,'Annual Summary'!D$17, 'Monthly Detail'!60:60) | E29: =SUMIF('Monthly Detail'!$1:$1,'Annual Summary'!E$17, 'Monthly Detail'!60:60) | F29: =SUMIF('Monthly Detail'!$1:$1,'Annual Summary'!F$17, 'Monthly Detail'!60:60) | G29: =SUMIF('Monthly Detail'!$1:$1,'Annual Summary'!G$17, 'Monthly Detail'!60:60) | H29: =SUMIF('Monthly Detail'!$1:$1,'Annual Summary'!H$17, 'Monthly Detail'!60:60) | I29: =SUMIF('Monthly Detail'!$1:$1,'Annual Summary'!I$17, 'Monthly Detail'!60:60) | J29: =SUMIF('Monthly Detail'!$1:$1,'Annual Summary'!J$17, 'Monthly Detail'!60:60) | K29: =SUMIF('Monthly Detail'!$1:$1,'Annual Summary'!K$17, 'Monthly Detail'!60:60)
C30: Total Cost of Goods Sold (COGS) | D30: =SUM(D27:D29) | E30: =SUM(E27:E29) | F30: =SUM(F27:F29) | G30: =SUM(G27:G29) | H30: =SUM(H27:H29) | I30: =SUM(I27:I29) | J30: =SUM(J27:J29) | K30: =SUM(K27:K29)
C32: Gross Margin | D32: =D21-D30 | E32: =E21-E30 | F32: =F21-F30 | G32: =G21-G30 | H32: =H21-H30 | I32: =I21-I30 | J32: =J21-J30 | K32: =K21-K30
C33: GM % | D33: =+D32/D21 | E33: =+E32/E21 | F33: =+F32/F21 | G33: =+G32/G21 | H33: =+H32/H21 | I33: =+I32/I21 | J33: =+J32/J21 | K33: =+K32/K21
C35: General & Admintrative Expenses | D35: =SUMIF('Monthly Detail'!$1:$1,'Annual Summary'!D$17, 'Monthly Detail'!$89:$89) | E35: =SUMIF('Monthly Detail'!$1:$1,'Annual Summary'!E$17, 'Monthly Detail'!$89:$89)+SUMIF('Monthly Detail'!$1:$1,'Annual Summary'!E$17, 'Monthly Detail'!$90:$90) | F35: =SUMIF('Monthly Detail'!$1:$1,'Annual Summary'!F$17, 'Monthly Detail'!$89:$89)+SUMIF('Monthly Detail'!$1:$1,'Annual Summary'!F$17, 'Monthly Detail'!$90:$90) | G35: =SUMIF('Monthly Detail'!$1:$1,'Annual Summary'!G$17, 'Monthly Detail'!$89:$89)+SUMIF('Monthly Detail'!$1:$1,'Annual Summary'!G$17, 'Monthly Detail'!$90:$90) | H35: =SUMIF('Monthly Detail'!$1:$1,'Annual Summary'!H$17, 'Monthly Detail'!$89:$89)+SUMIF('Monthly Detail'!$1:$1,'Annual Summary'!H$17, 'Monthly Detail'!$90:$90) | I35: =SUMIF('Monthly Detail'!$1:$1,'Annual Summary'!I$17, 'Monthly Detail'!$89:$89)+SUMIF('Monthly Detail'!$1:$1,'Annual Summary'!I$17, 'Monthly Detail'!$90:$90) | J35: =SUMIF('Monthly Detail'!$1:$1,'Annual Summary'!J$17, 'Monthly Detail'!$89:$89) | K35: =SUMIF('Monthly Detail'!$1:$1,'Annual Summary'!K$17, 'Monthly Detail'!$89:$89)
C36: Operating Expense | D36: =SUM(D35:D35) | E36: =SUM(E35:E35) | F36: =SUM(F35:F35) | G36: =SUM(G35:G35) | H36: =SUM(H35:H35) | I36: =SUM(I35:I35) | J36: =SUM(J35:J35) | K36: =SUM(K35:K35)
C38: Net Operating Income (EBITDA) | D38: =D32-D36 | E38: =E32-E36 | F38: =F32-F36 | G38: =G32-G36 | H38: =H32-H36 | I38: =I32-I36 | J38: =J32-J36 | K38: =K32-K36
C39: EBITDA % | D39: =D38/D21 | E39: =E38/E21 | F39: =F38/F21 | G39: =G38/G21 | H39: =H38/H21 | I39: =I38/I21 | J39: =J38/J21 | K39: =K38/K21
C41: Other Income / (Expense) | D41: =SUMIF('Monthly Detail'!$1:$1,'Annual Summary'!D$17, 'Monthly Detail'!95:95) | E41: =SUMIF('Monthly Detail'!$1:$1,'Annual Summary'!E$17, 'Monthly Detail'!95:95) | F41: =SUMIF('Monthly Detail'!$1:$1,'Annual Summary'!F$17, 'Monthly Detail'!95:95) | G41: =SUMIF('Monthly Detail'!$1:$1,'Annual Summary'!G$17, 'Monthly Detail'!95:95) | H41: =SUMIF('Monthly Detail'!$1:$1,'Annual Summary'!H$17, 'Monthly Detail'!95:95) | I41: =SUMIF('Monthly Detail'!$1:$1,'Annual Summary'!I$17, 'Monthly Detail'!95:95) | J41: =SUMIF('Monthly Detail'!$1:$1,'Annual Summary'!J$17, 'Monthly Detail'!95:95) | K41: =SUMIF('Monthly Detail'!$1:$1,'Annual Summary'!K$17, 'Monthly Detail'!95:95)
C42: Net Income | D42: =D38+D41 | E42: =E38+E41 | F42: =F38+F41 | G42: =G38+G41 | H42: =H38+H41 | I42: =I38+I41 | J42: =J38+J41 | K42: =K38+K41
C43: NI % | D43: =D42/D21 | E43: =E42/E21 | F43: =F42/F21 | G43: =G42/G21 | H43: =H42/H21 | I43: =I42/I21 | J43: =J42/J21 | K43: =K42/K21
C44: Estimated Tax Burden | D44: =+IF(D42>0, D42*0.25, 0) | E44: =+IF(E42>0, E42*0.25, 0) | F44: =+IF(F42>0, F42*0.25, 0) | G44: =+IF(G42>0, G42*0.25, 0) | H44: =+IF(H42>0, H42*0.25, 0) | I44: =+IF(I42>0, I42*0.25, 0) | J44: =+IF(J42>0, J42*0.25, 0) | K44: =+IF(K42>0, K42*0.25, 0)
C45: Cash Balance | D45: #VALUE! | E45: =+SUMIF('Monthly Detail'!$4:$4, DATE(E17, 12, 31),'Monthly Detail'!$173:$173) | F45: =+SUMIF('Monthly Detail'!$4:$4, DATE(F17, 12, 31),'Monthly Detail'!$173:$173) | G45: =+SUMIF('Monthly Detail'!$4:$4, DATE(G17, 12, 31),'Monthly Detail'!$173:$173) | H45: =+SUMIF('Monthly Detail'!$4:$4, DATE(H17, 12, 31),'Monthly Detail'!$173:$173) | I45: =+SUMIF('Monthly Detail'!$4:$4, DATE(I17, 12, 31),'Monthly Detail'!$173:$173) | J45: =+SUMIF('Monthly Detail'!$4:$4, DATE(J17, 12, 31),'Monthly Detail'!$173:$173) | K45: =+SUMIF('Monthly Detail'!$4:$4, DATE(K17, 12, 31),'Monthly Detail'!$173:$173)

Sheet 2023 Overview
C10: =TEXT('Monthly Detail'!D4,"mmmm") | D10: =TEXT('Monthly Detail'!E4,"mmmm") | E10: =TEXT('Monthly Detail'!F4,"mmmm") | F10: =TEXT('Monthly Detail'!G4,"mmmm") | G10: =TEXT('Monthly Detail'!H4,"mmmm") | H10: =TEXT('Monthly Detail'!I4,"mmmm") | I10: =TEXT('Monthly Detail'!J4,"mmmm") | J10: =TEXT('Monthly Detail'!K4,"mmmm") | ... N10: =TEXT('Monthly Detail'!O4,"mmmm") | P10: Total
C11: 44957 | D11: 44985 | E11: 45016 | F11: 45046 | G11: 45077 | H11: 45107 | I11: 45138 | J11: 45169 | K11: 45199 | L11: 45230 | M11: 45260 | N11: 45291 | O11: 45322
B12: Service Income | C12: =SUMIF('Monthly Detail'!$4:$4, '2023 Overview'!C$11, 'Monthly Detail'!9:9) | D12: =SUMIF('Monthly Detail'!$4:$4, '2023 Overview'!D$11, 'Monthly Detail'!9:9) | E12: =SUMIF('Monthly Detail'!$4:$4, '2023 Overview'!E$11, 'Monthly Detail'!9:9) | F12: =SUMIF('Monthly Detail'!$4:$4, '2023 Overview'!F$11, 'Monthly Detail'!9:9) | G12: =SUMIF('Monthly Detail'!$4:$4, '2023 Overview'!G$11, 'Monthly Detail'!9:9) | H12: =SUMIF('Monthly Detail'!$4:$4, '2023 Overview'!H$11, 'Monthly Detail'!9:9) | I12: =SUMIF('Monthly Detail'!$4:$4, '2023 Overview'!I$11, 'Monthly Detail'!9:9) | J12: =SUMIF('Monthly Detail'!$4:$4, '2023 Overview'!J$11, 'Monthly Detail'!9:9) | ... N12: =SUMIF('Monthly Detail'!$4:$4, '2023 Overview'!N$11, 'Monthly Detail'!9:9) | P12: =SUM(C12:O12)
B13: Misc. | C13: =SUMIF('Monthly Detail'!$4:$4, '2023 Overview'!C$11, 'Monthly Detail'!12:12) | D13: =SUMIF('Monthly Detail'!$4:$4, '2023 Overview'!D$11, 'Monthly Detail'!12:12) | E13: =SUMIF('Monthly Detail'!$4:$4, '2023 Overview'!E$11, 'Monthly Detail'!12:12) | F13: =SUMIF('Monthly Detail'!$4:$4, '2023 Overview'!F$11, 'Monthly Detail'!12:12) | G13: =SUMIF('Monthly Detail'!$4:$4, '2023 Overview'!G$11, 'Monthly Detail'!12:12) | H13: =SUMIF('Monthly Detail'!$4:$4, '2023 Overview'!H$11, 'Monthly Detail'!12:12) | I13: =SUMIF('Monthly Detail'!$4:$4, '2023 Overview'!I$11, 'Monthly Detail'!12:12) | J13: =SUMIF('Monthly Detail'!$4:$4, '2023 Overview'!J$11, 'Monthly Detail'!12:12) | ... N13: =SUMIF('Monthly Detail'!$4:$4, '2023 Overview'!N$11, 'Monthly Detail'!12:12)
B14: Total Income | C14: =SUM(C12:C13) | D14: =SUM(D12:D13) | E14: =SUM(E12:E13) | F14: =SUM(F12:F13) | G14: =SUM(G12:G13) | H14: =SUM(H12:H13) | I14: =SUM(I12:I13) | J14: =SUM(J12:J13) | ... N14: =SUM(N12:N13) | P14: =SUM(P12:P12)
B16: Gross Margin | C16: =C14 | D16: =D14 | E16: =E14 | F16: =F14 | G16: =G14 | H16: =H14 | I16: =I14 | J16: =J14 | ... N16: =N14 | P16: =P14
B17: GM % | C17: =C16/C14 | D17: =D16/D14 | E17: =E16/E14 | F17: =F16/F14 | G17: =G16/G14 | H17: =H16/H14 | I17: =I16/I14 | J17: =J16/J14 | ... N17: =N16/N14 | P17: =P16/P14
B19: General & Admintrative Expenses | C19: =SUMIF('Monthly Detail'!$4:$4, '2023 Overview'!C$11, 'Monthly Detail'!$89:$89) | D19: =SUMIF('Monthly Detail'!$4:$4, '2023 Overview'!D$11, 'Monthly Detail'!$89:$89) | E19: =SUMIF('Monthly Detail'!$4:$4, '2023 Overview'!E$11, 'Monthly Detail'!$89:$89) | F19: =SUMIF('Monthly Detail'!$4:$4, '2023 Overview'!F$11, 'Monthly Detail'!$89:$89) | G19: =SUMIF('Monthly Detail'!$4:$4, '2023 Overview'!G$11, 'Monthly Detail'!$89:$89) | H19: =SUMIF('Monthly Detail'!$4:$4, '2023 Overview'!H$11, 'Monthly Detail'!$89:$89) | I19: =SUMIF('Monthly Detail'!$4:$4, '2023 Overview'!I$11, 'Monthly Detail'!$89:$89) | J19: =SUMIF('Monthly Detail'!$4:$4, '2023 Overview'!J$11, 'Monthly Detail'!$89:$89) | ... N19: =SUMIF('Monthly Detail'!$4:$4, '2023 Overview'!N$11, 'Monthly Detail'!$89:$89) | P19: =SUM(C19:O19)
B20: Operating Expenses | C20: =SUM(C19:C19) | D20: =SUM(D19:D19) | E20: =SUM(E19:E19) | F20: =SUM(F19:F19) | G20: =SUM(G19:G19) | H20: =SUM(H19:H19) | I20: =SUM(I19:I19) | J20: =SUM(J19:J19) | ... N20: =SUM(N19:N19) | P20: =SUM(P19:P19)
B22: Net Operating Income (EBITDA) | C22: =C16-C20 | D22: =D16-D20 | E22: =E16-E20 | F22: =F16-F20 | G22: =G16-G20 | H22: =H16-H20 | I22: =I16-I20 | J22: =J16-J20 | ... N22: =N16-N20 | P22: =P16-P20
B23: EBITDA % | C23: =C22/C14 | D23: =D22/D14 | E23: =E22/E14 | F23: =F22/F14 | G23: =G22/G14 | H23: =H22/H14 | I23: =I22/I14 | J23: =J22/J14 | ... N23: =N22/N14 | P23: =P22/P14
B25: Other Income / (Expense) | C25: =SUMIF('Monthly Detail'!$4:$4, '2023 Overview'!C$11, 'Monthly Detail'!95:95) | D25: =SUMIF('Monthly Detail'!$4:$4, '2023 Overview'!D$11, 'Monthly Detail'!95:95) | E25: =SUMIF('Monthly Detail'!$4:$4, '2023 Overview'!E$11, 'Monthly Detail'!95:95) | F25: =SUMIF('Monthly Detail'!$4:$4, '2023 Overview'!F$11, 'Monthly Detail'!95:95) | G25: =SUMIF('Monthly Detail'!$4:$4, '2023 Overview'!G$11, 'Monthly Detail'!95:95) | H25: =SUMIF('Monthly Detail'!$4:$4, '2023 Overview'!H$11, 'Monthly Detail'!95:95) | I25: =SUMIF('Monthly Detail'!$4:$4, '2023 Overview'!I$11, 'Monthly Detail'!95:95) | J25: =SUMIF('Monthly Detail'!$4:$4, '2023 Overview'!J$11, 'Monthly Detail'!95:95) | ... N25: =SUMIF('Monthly Detail'!$4:$4, '2023 Overview'!N$11, 'Monthly Detail'!95:95) | P25: =SUM(C25:O25)
B26: Net Income | C26: =C22+SUM(C25:C25) | D26: =D22+SUM(D25:D25) | E26: =E22+SUM(E25:E25) | F26: =F22+SUM(F25:F25) | G26: =G22+SUM(G25:G25) | H26: =H22+SUM(H25:H25) | I26: =I22+SUM(I25:I25) | J26: =J22+SUM(J25:J25) | ... N26: =N22+SUM(N25:N25) | P26: =P22+SUM(P25:P25)
B27: NI % | C27: =C26/C14 | D27: =D26/D14 | E27: =E26/E14 | F27: =F26/F14 | G27: =G26/G14 | H27: =H26/H14 | I27: =I26/I14 | J27: =J26/J14 | ... N27: =N26/N14 | P27: =P26/P14
B29: Operating Cash | C29: =SUMIF('Monthly Detail'!$4:$4, '2023 Overview'!C$11, 'Monthly Detail'!173:173) | D29: =SUMIF('Monthly Detail'!$4:$4, '2023 Overview'!D$11, 'Monthly Detail'!173:173) | E29: =SUMIF('Monthly Detail'!$4:$4, '2023 Overview'!E$11, 'Monthly Detail'!173:173) | F29: =SUMIF('Monthly Detail'!$4:$4, '2023 Overview'!F$11, 'Monthly Detail'!173:173) | G29: =SUMIF('Monthly Detail'!$4:$4, '2023 Overview'!G$11, 'Monthly Detail'!173:173) | H29: =SUMIF('Monthly Detail'!$4:$4, '2023 Overview'!H$11, 'Monthly Detail'!173:173) | I29: =SUMIF('Monthly Detail'!$4:$4, '2023 Overview'!I$11, 'Monthly Detail'!173:173) | J29: =SUMIF('Monthly Detail'!$4:$4, '2023 Overview'!J$11, 'Monthly Detail'!173:173) | ... N29: =SUMIF('Monthly Detail'!$4:$4, '2023 Overview'!N$11, 'Monthly Detail'!173:173)
B30: Cash Inflow (Outflow) | C30: =SUMIF('Monthly Detail'!$4:$4, '2023 Overview'!C$11, 'Monthly Detail'!170:170) | D30: =SUMIF('Monthly Detail'!$4:$4, '2023 Overview'!D$11, 'Monthly Detail'!170:170) | E30: =SUMIF('Monthly Detail'!$4:$4, '2023 Overview'!E$11, 'Monthly Detail'!170:170) | F30: =SUMIF('Monthly Detail'!$4:$4, '2023 Overview'!F$11, 'Monthly Detail'!170:170) | G30: =SUMIF('Monthly Detail'!$4:$4, '2023 Overview'!G$11, 'Monthly Detail'!170:170) | H30: =SUMIF('Monthly Detail'!$4:$4, '2023 Overview'!H$11, 'Monthly Detail'!170:170) | I30: =SUMIF('Monthly Detail'!$4:$4, '2023 Overview'!I$11, 'Monthly Detail'!170:170) | J30: =SUMIF('Monthly Detail'!$4:$4, '2023 Overview'!J$11, 'Monthly Detail'!170:170) | ... N30: =SUMIF('Monthly Detail'!$4:$4, '2023 Overview'!N$11, 'Monthly Detail'!170:170)

Sheet 2025 Overview (Budget)
B15: 2025 Overview (Annual Operating Plan)
C18: January | D18: February | E18: March | F18: April | G18: May | H18: June | I18: July | J18: August | K18: September | L18: October | M18: November | N18: December | P18: Total
C19: 45688 | D19: 45716 | E19: 45747 | F19: 45777 | G19: 45808 | H19: 45838 | I19: 45869 | J19: 45900 | K19: 45930 | L19: 45961 | M19: 45991 | N19: 46022 | O19: 45322
B20: Service Income | C20: =SUMIF('Monthly Detail'!$4:$4, '2025 Overview (Budget)'!C$19, 'Monthly Detail'!13:13) | D20: =SUMIF('Monthly Detail'!$4:$4, '2025 Overview (Budget)'!D$19, 'Monthly Detail'!13:13) | E20: =SUMIF('Monthly Detail'!$4:$4, '2025 Overview (Budget)'!E$19, 'Monthly Detail'!13:13) | F20: =SUMIF('Monthly Detail'!$4:$4, '2025 Overview (Budget)'!F$19, 'Monthly Detail'!13:13) | G20: =SUMIF('Monthly Detail'!$4:$4, '2025 Overview (Budget)'!G$19, 'Monthly Detail'!13:13) | H20: =SUMIF('Monthly Detail'!$4:$4, '2025 Overview (Budget)'!H$19, 'Monthly Detail'!13:13) | I20: =SUMIF('Monthly Detail'!$4:$4, '2025 Overview (Budget)'!I$19, 'Monthly Detail'!13:13) | J20: =SUMIF('Monthly Detail'!$4:$4, '2025 Overview (Budget)'!J$19, 'Monthly Detail'!13:13) | ... L20: =SUMIF('Monthly Detail'!$4:$4, '2025 Overview (Budget)'!L$19, 'Monthly Detail'!13:13) | M20: =+'2025 AOP'!M20 | N20: =+'2025 AOP'!N20 | P20: =SUM(C20:O20)
B21: Misc. | C21: =SUMIF('Monthly Detail'!$4:$4, '2025 Overview (Budget)'!C$19, 'Monthly Detail'!12:12) | D21: =SUMIF('Monthly Detail'!$4:$4, '2025 Overview (Budget)'!D$19, 'Monthly Detail'!12:12) | E21: =SUMIF('Monthly Detail'!$4:$4, '2025 Overview (Budget)'!E$19, 'Monthly Detail'!12:12) | F21: =SUMIF('Monthly Detail'!$4:$4, '2025 Overview (Budget)'!F$19, 'Monthly Detail'!12:12) | G21: =SUMIF('Monthly Detail'!$4:$4, '2025 Overview (Budget)'!G$19, 'Monthly Detail'!12:12) | H21: =SUMIF('Monthly Detail'!$4:$4, '2025 Overview (Budget)'!H$19, 'Monthly Detail'!12:12) | I21: =SUMIF('Monthly Detail'!$4:$4, '2025 Overview (Budget)'!I$19, 'Monthly Detail'!12:12) | J21: =SUMIF('Monthly Detail'!$4:$4, '2025 Overview (Budget)'!J$19, 'Monthly Detail'!12:12) | ... L21: =SUMIF('Monthly Detail'!$4:$4, '2025 Overview (Budget)'!L$19, 'Monthly Detail'!12:12) | M21: =+'2025 AOP'!M21 | N21: =+'2025 AOP'!N21 | P21: =SUM(C21:O21)
B22: Total Income | C22: =SUM(C20:C21) | D22: =SUM(D20:D21) | E22: =SUM(E20:E21) | F22: =SUM(F20:F21) | G22: =SUM(G20:G21) | H22: =SUM(H20:H21) | I22: =SUM(I20:I21) | J22: =SUM(J20:J21) | ... L22: =SUM(L20:L21) | M22: =+'2025 AOP'!M22 | N22: =+'2025 AOP'!N22 | P22: =SUM(P20:P20)
B23: # of Appointments | C23: =SUMIF('Monthly Detail'!$4:$4, '2025 Overview (Budget)'!C$19, 'Monthly Detail'!15:15) | D23: =SUMIF('Monthly Detail'!$4:$4, '2025 Overview (Budget)'!D$19, 'Monthly Detail'!15:15) | E23: =SUMIF('Monthly Detail'!$4:$4, '2025 Overview (Budget)'!E$19, 'Monthly Detail'!15:15) | F23: =SUMIF('Monthly Detail'!$4:$4, '2025 Overview (Budget)'!F$19, 'Monthly Detail'!15:15) | G23: =SUMIF('Monthly Detail'!$4:$4, '2025 Overview (Budget)'!G$19, 'Monthly Detail'!15:15) | H23: =SUMIF('Monthly Detail'!$4:$4, '2025 Overview (Budget)'!H$19, 'Monthly Detail'!15:15) | I23: =SUMIF('Monthly Detail'!$4:$4, '2025 Overview (Budget)'!I$19, 'Monthly Detail'!15:15) | J23: =SUMIF('Monthly Detail'!$4:$4, '2025 Overview (Budget)'!J$19, 'Monthly Detail'!15:15) | ... L23: =SUMIF('Monthly Detail'!$4:$4, '2025 Overview (Budget)'!L$19, 'Monthly Detail'!15:15) | M23: =+'2025 AOP'!M23 | N23: =+'2025 AOP'!N23 | P23: =+SUM(C23:N23)
B24: MRR | C24: =SUMIF('Monthly Detail'!$4:$4, '2025 Overview (Budget)'!C$19, 'Monthly Detail'!41:41) | D24: =SUMIF('Monthly Detail'!$4:$4, '2025 Overview (Budget)'!D$19, 'Monthly Detail'!41:41) | E24: =SUMIF('Monthly Detail'!$4:$4, '2025 Overview (Budget)'!E$19, 'Monthly Detail'!41:41) | F24: =SUMIF('Monthly Detail'!$4:$4, '2025 Overview (Budget)'!F$19, 'Monthly Detail'!41:41) | G24: =SUMIF('Monthly Detail'!$4:$4, '2025 Overview (Budget)'!G$19, 'Monthly Detail'!41:41) | H24: =SUMIF('Monthly Detail'!$4:$4, '2025 Overview (Budget)'!H$19, 'Monthly Detail'!41:41) | I24: =SUMIF('Monthly Detail'!$4:$4, '2025 Overview (Budget)'!I$19, 'Monthly Detail'!41:41) | J24: =SUMIF('Monthly Detail'!$4:$4, '2025 Overview (Budget)'!J$19, 'Monthly Detail'!41:41) | ... L24: =SUMIF('Monthly Detail'!$4:$4, '2025 Overview (Budget)'!L$19, 'Monthly Detail'!41:41) | M24: =+'2025 AOP'!M24 | N24: =+'2025 AOP'!N24 | P24: =+AVERAGE(C24:N24)
B25: Recurring Client Base | C25: =SUMIF('Monthly Detail'!$4:$4, '2025 Overview (Budget)'!C$19, 'Monthly Detail'!17:17) | D25: =SUMIF('Monthly Detail'!$4:$4, '2025 Overview (Budget)'!D$19, 'Monthly Detail'!17:17) | E25: =SUMIF('Monthly Detail'!$4:$4, '2025 Overview (Budget)'!E$19, 'Monthly Detail'!17:17) | F25: =SUMIF('Monthly Detail'!$4:$4, '2025 Overview (Budget)'!F$19, 'Monthly Detail'!17:17) | G25: =SUMIF('Monthly Detail'!$4:$4, '2025 Overview (Budget)'!G$19, 'Monthly Detail'!17:17) | H25: =SUMIF('Monthly Detail'!$4:$4, '2025 Overview (Budget)'!H$19, 'Monthly Detail'!17:17) | I25: =SUMIF('Monthly Detail'!$4:$4, '2025 Overview (Budget)'!I$19, 'Monthly Detail'!17:17) | J25: =SUMIF('Monthly Detail'!$4:$4, '2025 Overview (Budget)'!J$19, 'Monthly Detail'!17:17) | ... L25: =SUMIF('Monthly Detail'!$4:$4, '2025 Overview (Budget)'!L$19, 'Monthly Detail'!17:17) | M25: =+'2025 AOP'!M25 | N25: =+'2025 AOP'!N25
B28: Software - COS | C28: =SUMIF('Monthly Detail'!$4:$4, '2025 Overview (Budget)'!C$19, 'Monthly Detail'!58:58) | D28: =SUMIF('Monthly Detail'!$4:$4, '2025 Overview (Budget)'!D$19, 'Monthly Detail'!58:58) | E28: =SUMIF('Monthly Detail'!$4:$4, '2025 Overview (Budget)'!E$19, 'Monthly Detail'!58:58) | F28: =SUMIF('Monthly Detail'!$4:$4, '2025 Overview (Budget)'!F$19, 'Monthly Detail'!58:58) | G28: =SUMIF('Monthly Detail'!$4:$4, '2025 Overview (Budget)'!G$19, 'Monthly Detail'!58:58) | H28: =SUMIF('Monthly Detail'!$4:$4, '2025 Overview (Budget)'!H$19, 'Monthly Detail'!58:58) | I28: =SUMIF('Monthly Detail'!$4:$4, '2025 Overview (Budget)'!I$19, 'Monthly Detail'!58:58) | J28: =SUMIF('Monthly Detail'!$4:$4, '2025 Overview (Budget)'!J$19, 'Monthly Detail'!58:58) | ... L28: =SUMIF('Monthly Detail'!$4:$4, '2025 Overview (Budget)'!L$19, 'Monthly Detail'!58:58) | M28: =+'2025 AOP'!M28 | N28: =+'2025 AOP'!N28 | P28: =+SUM(C28:N28)
B29: Materials - COGS | C29: =SUMIF('Monthly Detail'!$4:$4, '2025 Overview (Budget)'!C$19, 'Monthly Detail'!59:59) | D29: =SUMIF('Monthly Detail'!$4:$4, '2025 Overview (Budget)'!D$19, 'Monthly Detail'!59:59) | E29: =SUMIF('Monthly Detail'!$4:$4, '2025 Overview (Budget)'!E$19, 'Monthly Detail'!59:59) | F29: =SUMIF('Monthly Detail'!$4:$4, '2025 Overview (Budget)'!F$19, 'Monthly Detail'!59:59) | G29: =SUMIF('Monthly Detail'!$4:$4, '2025 Overview (Budget)'!G$19, 'Monthly Detail'!59:59) | H29: =SUMIF('Monthly Detail'!$4:$4, '2025 Overview (Budget)'!H$19, 'Monthly Detail'!59:59) | I29: =SUMIF('Monthly Detail'!$4:$4, '2025 Overview (Budget)'!I$19, 'Monthly Detail'!59:59) | J29: =SUMIF('Monthly Detail'!$4:$4, '2025 Overview (Budget)'!J$19, 'Monthly Detail'!59:59) | ... L29: =SUMIF('Monthly Detail'!$4:$4, '2025 Overview (Budget)'!L$19, 'Monthly Detail'!59:59) | M29: =+'2025 AOP'!M29 | N29: =+'2025 AOP'!N29 | P29: =+SUM(C29:N29)
B30: Contractors - COS | C30: =SUMIF('Monthly Detail'!$4:$4, '2025 Overview (Budget)'!C$19, 'Monthly Detail'!60:60) | D30: =SUMIF('Monthly Detail'!$4:$4, '2025 Overview (Budget)'!D$19, 'Monthly Detail'!60:60) | E30: =SUMIF('Monthly Detail'!$4:$4, '2025 Overview (Budget)'!E$19, 'Monthly Detail'!60:60) | F30: =SUMIF('Monthly Detail'!$4:$4, '2025 Overview (Budget)'!F$19, 'Monthly Detail'!60:60) | G30: =SUMIF('Monthly Detail'!$4:$4, '2025 Overview (Budget)'!G$19, 'Monthly Detail'!60:60) | H30: =SUMIF('Monthly Detail'!$4:$4, '2025 Overview (Budget)'!H$19, 'Monthly Detail'!60:60) | I30: =SUMIF('Monthly Detail'!$4:$4, '2025 Overview (Budget)'!I$19, 'Monthly Detail'!60:60) | J30: =SUMIF('Monthly Detail'!$4:$4, '2025 Overview (Budget)'!J$19, 'Monthly Detail'!60:60) | ... L30: =SUMIF('Monthly Detail'!$4:$4, '2025 Overview (Budget)'!L$19, 'Monthly Detail'!60:60) | M30: =+'2025 AOP'!M30 | N30: =+'2025 AOP'!N30 | P30: =+SUM(C30:N30)
B31: Total Cost of Goods Sold (COGS) | C31: =SUM(C28:C30) | D31: =SUM(D28:D30) | E31: =SUM(E28:E30) | F31: =SUM(F28:F30) | G31: =SUM(G28:G30) | H31: =SUM(H28:H30) | I31: =SUM(I28:I30) | J31: =SUM(J28:J30) | ... N31: =SUM(N28:N30) | P31: =SUM(P28:P30)
B33: Gross Margin | C33: =+C22-C31 | D33: =+D22-D31 | E33: =+E22-E31 | F33: =+F22-F31 | G33: =+G22-G31 | H33: =+H22-H31 | I33: =+I22-I31 | J33: =+J22-J31 | ... N33: =+N22-N31 | P33: =+SUM(C33:N33)
B34: GM % | C34: =IFERROR(C33/C22, 0) | D34: =IFERROR(D33/D22, 0) | E34: =IFERROR(E33/E22, 0) | F34: =IFERROR(F33/F22, 0) | G34: =IFERROR(G33/G22, 0) | H34: =IFERROR(H33/H22, 0) | I34: =IFERROR(I33/I22, 0) | J34: =IFERROR(J33/J22, 0) | ... N34: =IFERROR(N33/N22, 0) | P34: =P33/P22
B36: General & Admintrative Expenses | C36: =SUMIF('Monthly Detail'!$4:$4, '2025 Overview (Budget)'!C$19, 'Monthly Detail'!$89:$89) | D36: =SUMIF('Monthly Detail'!$4:$4, '2025 Overview (Budget)'!D$19, 'Monthly Detail'!$89:$89) | E36: =SUMIF('Monthly Detail'!$4:$4, '2025 Overview (Budget)'!E$19, 'Monthly Detail'!$89:$89) | F36: =SUMIF('Monthly Detail'!$4:$4, '2025 Overview (Budget)'!F$19, 'Monthly Detail'!$89:$89) | G36: =SUMIF('Monthly Detail'!$4:$4, '2025 Overview (Budget)'!G$19, 'Monthly Detail'!$89:$89) | H36: =SUMIF('Monthly Detail'!$4:$4, '2025 Overview (Budget)'!H$19, 'Monthly Detail'!$89:$89) | I36: =SUMIF('Monthly Detail'!$4:$4, '2025 Overview (Budget)'!I$19, 'Monthly Detail'!$89:$89) | J36: =SUMIF('Monthly Detail'!$4:$4, '2025 Overview (Budget)'!J$19, 'Monthly Detail'!$89:$89) | K36: =SUMIF('Monthly Detail'!$4:$4, '2025 Overview (Budget)'!K$19, 'Monthly Detail'!$89:$89) | L36: =SUMIF('Monthly Detail'!$4:$4, '2025 Overview'!L$19, 'Monthly Detail'!$89:$89)+SUMIF('Monthly Detail'!$4:$4, '2025 Overview'!L$19, 'Monthly Detail'!$90:$90) | M36: =+'2025 AOP'!M36 | N36: =+'2025 AOP'!N36 | P36: =SUM(C36:O36)
B37: Operating Expenses | C37: =SUM(C36:C36) | D37: =SUM(D36:D36) | E37: =SUM(E36:E36) | F37: =SUM(F36:F36) | G37: =SUM(G36:G36) | H37: =SUM(H36:H36) | I37: =SUM(I36:I36) | J37: =SUM(J36:J36) | ... N37: =SUM(N36:N36) | P37: =SUM(P36:P36)
B39: Net Operating Income (EBITDA) | C39: =C33-C37 | D39: =D33-D37 | E39: =E33-E37 | F39: =F33-F37 | G39: =G33-G37 | H39: =H33-H37 | I39: =I33-I37 | J39: =J33-J37 | ... N39: =N33-N37 | P39: =P33-P37
B40: EBITDA % | C40: =IFERROR(C39/C22, 0) | D40: =IFERROR(D39/D22, 0) | E40: =IFERROR(E39/E22, 0) | F40: =IFERROR(F39/F22, 0) | G40: =IFERROR(G39/G22, 0) | H40: =IFERROR(H39/H22, 0) | I40: =IFERROR(I39/I22, 0) | J40: =IFERROR(J39/J22, 0) | ... N40: =IFERROR(N39/N22, 0) | P40: =P39/P22
B42: Other Income / (Expense) | C42: =SUMIF('Monthly Detail'!$4:$4, '2025 Overview (Budget)'!C$19, 'Monthly Detail'!95:95) | D42: =SUMIF('Monthly Detail'!$4:$4, '2025 Overview (Budget)'!D$19, 'Monthly Detail'!95:95) | E42: =SUMIF('Monthly Detail'!$4:$4, '2025 Overview (Budget)'!E$19, 'Monthly Detail'!95:95) | F42: =SUMIF('Monthly Detail'!$4:$4, '2025 Overview (Budget)'!F$19, 'Monthly Detail'!95:95) | G42: =SUMIF('Monthly Detail'!$4:$4, '2025 Overview (Budget)'!G$19, 'Monthly Detail'!95:95) | H42: =SUMIF('Monthly Detail'!$4:$4, '2025 Overview (Budget)'!H$19, 'Monthly Detail'!95:95) | I42: =SUMIF('Monthly Detail'!$4:$4, '2025 Overview (Budget)'!I$19, 'Monthly Detail'!95:95) | J42: =SUMIF('Monthly Detail'!$4:$4, '2025 Overview (Budget)'!J$19, 'Monthly Detail'!95:95) | ... L42: =SUMIF('Monthly Detail'!$4:$4, '2025 Overview (Budget)'!L$19, 'Monthly Detail'!95:95) | M42: =SUMIF('Monthly Detail'!$4:$4, '2025 Overview (Budget)'!M$19, 'Monthly Detail'!130:130) | N42: =SUMIF('Monthly Detail'!$4:$4, '2025 Overview (Budget)'!N$19, 'Monthly Detail'!130:130) | P42: =SUM(C42:O42)
B43: Net Income | C43: =C39+SUM(C42:C42) | D43: =D39+SUM(D42:D42) | E43: =E39+SUM(E42:E42) | F43: =F39+SUM(F42:F42) | G43: =G39+SUM(G42:G42) | H43: =H39+SUM(H42:H42) | I43: =I39+SUM(I42:I42) | J43: =J39+SUM(J42:J42) | ... N43: =N39+SUM(N42:N42) | P43: =P39+SUM(P42:P42)
B44: NI % | C44: =IFERROR(C43/C22, 0) | D44: =IFERROR(D43/D22, 0) | E44: =IFERROR(E43/E22, 0) | F44: =IFERROR(F43/F22, 0) | G44: =IFERROR(G43/G22, 0) | H44: =IFERROR(H43/H22, 0) | I44: =IFERROR(I43/I22, 0) | J44: =IFERROR(J43/J22, 0) | ... N44: =IFERROR(N43/N22, 0) | P44: =P43/P22
B46: Operating (Business) Cash | C46: =SUMIF('Monthly Detail'!$4:$4, '2025 Overview (Budget)'!C$19, 'Monthly Detail'!112:112) | D46: =SUMIF('Monthly Detail'!$4:$4, '2025 Overview (Budget)'!D$19, 'Monthly Detail'!112:112) | E46: =SUMIF('Monthly Detail'!$4:$4, '2025 Overview (Budget)'!E$19, 'Monthly Detail'!112:112) | F46: =SUMIF('Monthly Detail'!$4:$4, '2025 Overview (Budget)'!F$19, 'Monthly Detail'!112:112) | G46: =SUMIF('Monthly Detail'!$4:$4, '2025 Overview (Budget)'!G$19, 'Monthly Detail'!112:112) | H46: =SUMIF('Monthly Detail'!$4:$4, '2025 Overview (Budget)'!H$19, 'Monthly Detail'!112:112) | I46: =SUMIF('Monthly Detail'!$4:$4, '2025 Overview (Budget)'!I$19, 'Monthly Detail'!112:112) | J46: =SUMIF('Monthly Detail'!$4:$4, '2025 Overview (Budget)'!J$19, 'Monthly Detail'!112:112) | ... L46: =SUMIF('Monthly Detail'!$4:$4, '2025 Overview (Budget)'!L$19, 'Monthly Detail'!112:112) | M46: =+'2025 AOP'!M46 | N46: =+'2025 AOP'!N46
B47: Savings Cash | C47: =SUMIF('Monthly Detail'!$4:$4, '2025 Overview (Budget)'!C$19, 'Monthly Detail'!106:106) | D47: =SUMIF('Monthly Detail'!$4:$4, '2025 Overview (Budget)'!D$19, 'Monthly Detail'!106:106) | E47: =SUMIF('Monthly Detail'!$4:$4, '2025 Overview (Budget)'!E$19, 'Monthly Detail'!106:106) | F47: =SUMIF('Monthly Detail'!$4:$4, '2025 Overview (Budget)'!F$19, 'Monthly Detail'!106:106) | G47: =SUMIF('Monthly Detail'!$4:$4, '2025 Overview (Budget)'!G$19, 'Monthly Detail'!106:106) | H47: =SUMIF('Monthly Detail'!$4:$4, '2025 Overview (Budget)'!H$19, 'Monthly Detail'!106:106) | I47: =SUMIF('Monthly Detail'!$4:$4, '2025 Overview (Budget)'!I$19, 'Monthly Detail'!106:106) | J47: =SUMIF('Monthly Detail'!$4:$4, '2025 Overview (Budget)'!J$19, 'Monthly Detail'!106:106) | ... L47: =SUMIF('Monthly Detail'!$4:$4, '2025 Overview (Budget)'!L$19, 'Monthly Detail'!106:106) | M47: =+'2025 AOP'!M47 | N47: =+'2025 AOP'!N47
B48: Total Cash Balance | C48: =SUMIF('Monthly Detail'!$4:$4, '2025 Overview (Budget)'!C$19, 'Monthly Detail'!173:173) | D48: =SUMIF('Monthly Detail'!$4:$4, '2025 Overview (Budget)'!D$19, 'Monthly Detail'!173:173) | E48: =SUMIF('Monthly Detail'!$4:$4, '2025 Overview (Budget)'!E$19, 'Monthly Detail'!173:173) | F48: =SUMIF('Monthly Detail'!$4:$4, '2025 Overview (Budget)'!F$19, 'Monthly Detail'!173:173) | G48: =SUMIF('Monthly Detail'!$4:$4, '2025 Overview (Budget)'!G$19, 'Monthly Detail'!173:173) | H48: =SUMIF('Monthly Detail'!$4:$4, '2025 Overview (Budget)'!H$19, 'Monthly Detail'!173:173) | I48: =SUMIF('Monthly Detail'!$4:$4, '2025 Overview (Budget)'!I$19, 'Monthly Detail'!173:173) | J48: =SUMIF('Monthly Detail'!$4:$4, '2025 Overview (Budget)'!J$19, 'Monthly Detail'!173:173) | ... L48: =SUMIF('Monthly Detail'!$4:$4, '2025 Overview (Budget)'!L$19, 'Monthly Detail'!173:173) | M48: =+'2025 AOP'!M48 | N48: =+'2025 AOP'!N48
B49: Total Cash Inflow (Outflow) | C49: =SUMIF('Monthly Detail'!$4:$4, '2025 Overview (Budget)'!C$19, 'Monthly Detail'!170:170) | D49: =SUMIF('Monthly Detail'!$4:$4, '2025 Overview (Budget)'!D$19, 'Monthly Detail'!170:170) | E49: =SUMIF('Monthly Detail'!$4:$4, '2025 Overview (Budget)'!E$19, 'Monthly Detail'!170:170) | F49: =SUMIF('Monthly Detail'!$4:$4, '2025 Overview (Budget)'!F$19, 'Monthly Detail'!170:170) | G49: =SUMIF('Monthly Detail'!$4:$4, '2025 Overview (Budget)'!G$19, 'Monthly Detail'!170:170) | H49: =SUMIF('Monthly Detail'!$4:$4, '2025 Overview (Budget)'!H$19, 'Monthly Detail'!170:170) | I49: =SUMIF('Monthly Detail'!$4:$4, '2025 Overview (Budget)'!I$19, 'Monthly Detail'!170:170) | J49: =SUMIF('Monthly Detail'!$4:$4, '2025 Overview (Budget)'!J$19, 'Monthly Detail'!170:170) | ... L49: =SUMIF('Monthly Detail'!$4:$4, '2025 Overview (Budget)'!L$19, 'Monthly Detail'!170:170) | M49: =+'2025 AOP'!M49 | N49: =+'2025 AOP'!N49
B50: Operating Cash Burn | C50: =-SUMIF('Monthly Detail'!$4:$4, '2025 Overview (Budget)'!C$19, 'Monthly Detail'!89:89) | D50: =-SUMIF('Monthly Detail'!$4:$4, '2025 Overview (Budget)'!D$19, 'Monthly Detail'!89:89) | E50: =-SUMIF('Monthly Detail'!$4:$4, '2025 Overview (Budget)'!E$19, 'Monthly Detail'!89:89) | F50: =-SUMIF('Monthly Detail'!$4:$4, '2025 Overview (Budget)'!F$19, 'Monthly Detail'!89:89) | G50: =-SUMIF('Monthly Detail'!$4:$4, '2025 Overview (Budget)'!G$19, 'Monthly Detail'!89:89) | H50: =-SUMIF('Monthly Detail'!$4:$4, '2025 Overview (Budget)'!H$19, 'Monthly Detail'!89:89) | I50: =-SUMIF('Monthly Detail'!$4:$4, '2025 Overview (Budget)'!I$19, 'Monthly Detail'!89:89) | J50: =-SUMIF('Monthly Detail'!$4:$4, '2025 Overview (Budget)'!J$19, 'Monthly Detail'!89:89) | ... L50: =-SUMIF('Monthly Detail'!$4:$4, '2025 Overview (Budget)'!L$19, 'Monthly Detail'!89:89) | M50: =+'2025 AOP'!M50 | N50: =+'2025 AOP'!N50
B51: Owner Cash Burn/Allowance | C51: =SUMIF('Monthly Detail'!$4:$4, '2025 Overview (Budget)'!C$19, 'Monthly Detail'!154:154) | D51: =SUMIF('Monthly Detail'!$4:$4, '2025 Overview (Budget)'!D$19, 'Monthly Detail'!154:154) | E51: =SUMIF('Monthly Detail'!$4:$4, '2025 Overview (Budget)'!E$19, 'Monthly Detail'!154:154) | F51: =SUMIF('Monthly Detail'!$4:$4, '2025 Overview (Budget)'!F$19, 'Monthly Detail'!154:154) | G51: =SUMIF('Monthly Detail'!$4:$4, '2025 Overview (Budget)'!G$19, 'Monthly Detail'!154:154) | H51: =SUMIF('Monthly Detail'!$4:$4, '2025 Overview (Budget)'!H$19, 'Monthly Detail'!154:154) | I51: =SUMIF('Monthly Detail'!$4:$4, '2025 Overview (Budget)'!I$19, 'Monthly Detail'!154:154) | J51: =SUMIF('Monthly Detail'!$4:$4, '2025 Overview (Budget)'!J$19, 'Monthly Detail'!154:154) | ... L51: =SUMIF('Monthly Detail'!$4:$4, '2025 Overview (Budget)'!L$19, 'Monthly Detail'!154:154) | M51: =+'2025 AOP'!M51 | N51: =+'2025 AOP'!N51
B52: Operating Cash Runway | C52: =+C46-SUM('Monthly Detail'!AC89:AN89)-SUM('Monthly Detail'!AC61:AN61) | D52: =+D46-SUM('Monthly Detail'!AD89:AO89)-SUM('Monthly Detail'!AD61:AO61) | E52: =+E46-SUM('Monthly Detail'!AE89:AP89)-SUM('Monthly Detail'!AE61:AP61) | F52: =+F46-SUM('Monthly Detail'!AF89:AQ89)-SUM('Monthly Detail'!AF61:AQ61) | G52: =+G46-SUM('Monthly Detail'!AG89:AR89)-SUM('Monthly Detail'!AG61:AR61) | H52: =+H46-SUM('Monthly Detail'!AH89:AS89)-SUM('Monthly Detail'!AH61:AS61) | I52: =+I46-SUM('Monthly Detail'!AI89:AT89)-SUM('Monthly Detail'!AI61:AT61) | J52: =+J46-SUM('Monthly Detail'!AJ89:AU89)-SUM('Monthly Detail'!AJ61:AU61) | ... L52: =+L46-SUM('Monthly Detail'!AL89:AW89)-SUM('Monthly Detail'!AL61:AW61) | M52: =+'2025 AOP'!M52 | N52: =+'2025 AOP'!N52
B53: Owner Cash Runway | C53: =+C48-SUM('Monthly Detail'!AC89:AN89)-SUM('Monthly Detail'!AC61:AN61) | D53: =+D48-SUM('Monthly Detail'!AD89:AO89)-SUM('Monthly Detail'!AD61:AO61) | E53: =+E48-SUM('Monthly Detail'!AE89:AP89)-SUM('Monthly Detail'!AE61:AP61) | F53: =+F48-SUM('Monthly Detail'!AF89:AQ89)-SUM('Monthly Detail'!AF61:AQ61) | G53: =+G48-SUM('Monthly Detail'!AG89:AR89)-SUM('Monthly Detail'!AG61:AR61) | H53: =+H48-SUM('Monthly Detail'!AH89:AS89)-SUM('Monthly Detail'!AH61:AS61) | I53: =+I48-SUM('Monthly Detail'!AI89:AT89)-SUM('Monthly Detail'!AI61:AT61) | J53: =+J48-SUM('Monthly Detail'!AJ89:AU89)-SUM('Monthly Detail'!AJ61:AU61) | ... L53: =+L48-SUM('Monthly Detail'!AL89:AW89)-SUM('Monthly Detail'!AL61:AW61) | M53: =+'2025 AOP'!M53 | N53: =+'2025 AOP'!N53
B54: Operating Cash Runway - Burn Rate | C54: =+C46/-C50 | D54: =+D46/-D50 | E54: =+E46/-E50 | F54: =+F46/-F50 | G54: =+G46/-G50 | H54: =+H46/-H50 | I54: =+I46/-I50 | J54: =+J46/-J50 | ... L54: =+L46/-L50 | M54: =-'2025 AOP'!M54 | N54: =-'2025 AOP'!N54
B55: Cash Runway - Owner Burn Rate | C55: =+IFERROR(C48/-C51, 0) | D55: =+IFERROR(D48/-D51, 0) | E55: =+IFERROR(E48/-E51, 0) | F55: =+IFERROR(F48/-F51, 0) | G55: =+IFERROR(G48/-G51, 0) | H55: =+IFERROR(H48/-H51, 0) | I55: =+IFERROR(I48/-I51, 0) | J55: =+IFERROR(J48/-J51, 0) | ... L55: =+IFERROR(L48/-L51, 0) | M55: =+'2025 AOP'!M55 | N55: =+'2025 AOP'!N55

Sheet 2025 Overview
B15: 2025 Overview
C18: January | D18: February | E18: March | F18: April | G18: May | H18: June | I18: July | J18: August | K18: September | L18: October | M18: November | N18: December | P18: Total
C19: 45688 | D19: 45716 | E19: 45747 | F19: 45777 | G19: 45808 | H19: 45838 | I19: 45869 | J19: 45900 | K19: 45930 | L19: 45961 | M19: 45991 | N19: 46022 | O19: 45322
B20: Service Income | C20: =SUMIF('Monthly Detail'!$4:$4, '2025 Overview'!C$19, 'Monthly Detail'!13:13) | D20: =SUMIF('Monthly Detail'!$4:$4, '2025 Overview'!D$19, 'Monthly Detail'!13:13) | E20: =SUMIF('Monthly Detail'!$4:$4, '2025 Overview'!E$19, 'Monthly Detail'!13:13) | F20: =SUMIF('Monthly Detail'!$4:$4, '2025 Overview'!F$19, 'Monthly Detail'!13:13) | G20: =SUMIF('Monthly Detail'!$4:$4, '2025 Overview'!G$19, 'Monthly Detail'!13:13) | H20: =SUMIF('Monthly Detail'!$4:$4, '2025 Overview'!H$19, 'Monthly Detail'!13:13) | I20: =SUMIF('Monthly Detail'!$4:$4, '2025 Overview'!I$19, 'Monthly Detail'!13:13) | J20: =SUMIF('Monthly Detail'!$4:$4, '2025 Overview'!J$19, 'Monthly Detail'!13:13) | ... N20: =SUMIF('Monthly Detail'!$4:$4, '2025 Overview'!N$19, 'Monthly Detail'!13:13) | P20: =SUM(C20:O20)
B21: Misc. | C21: =SUMIF('Monthly Detail'!$4:$4, '2025 Overview'!C$19, 'Monthly Detail'!12:12) | D21: =SUMIF('Monthly Detail'!$4:$4, '2025 Overview'!D$19, 'Monthly Detail'!12:12) | E21: =SUMIF('Monthly Detail'!$4:$4, '2025 Overview'!E$19, 'Monthly Detail'!12:12) | F21: =SUMIF('Monthly Detail'!$4:$4, '2025 Overview'!F$19, 'Monthly Detail'!12:12) | G21: =SUMIF('Monthly Detail'!$4:$4, '2025 Overview'!G$19, 'Monthly Detail'!12:12) | H21: =SUMIF('Monthly Detail'!$4:$4, '2025 Overview'!H$19, 'Monthly Detail'!12:12) | I21: =SUMIF('Monthly Detail'!$4:$4, '2025 Overview'!I$19, 'Monthly Detail'!12:12) | J21: =SUMIF('Monthly Detail'!$4:$4, '2025 Overview'!J$19, 'Monthly Detail'!12:12) | ... N21: =SUMIF('Monthly Detail'!$4:$4, '2025 Overview'!N$19, 'Monthly Detail'!12:12) | P21: =SUM(C21:O21)
B22: Total Income | C22: =SUM(C20:C21) | D22: =SUM(D20:D21) | E22: =SUM(E20:E21) | F22: =SUM(F20:F21) | G22: =SUM(G20:G21) | H22: =SUM(H20:H21) | I22: =SUM(I20:I21) | J22: =SUM(J20:J21) | ... N22: =SUM(N20:N21) | P22: =SUM(P20:P20)
B23: # of Appointments | C23: =SUMIF('Monthly Detail'!$4:$4, '2025 Overview'!C$19, 'Monthly Detail'!15:15) | D23: =SUMIF('Monthly Detail'!$4:$4, '2025 Overview'!D$19, 'Monthly Detail'!15:15) | E23: =SUMIF('Monthly Detail'!$4:$4, '2025 Overview'!E$19, 'Monthly Detail'!15:15) | F23: =SUMIF('Monthly Detail'!$4:$4, '2025 Overview'!F$19, 'Monthly Detail'!15:15) | G23: =SUMIF('Monthly Detail'!$4:$4, '2025 Overview'!G$19, 'Monthly Detail'!15:15) | H23: =SUMIF('Monthly Detail'!$4:$4, '2025 Overview'!H$19, 'Monthly Detail'!15:15) | I23: =SUMIF('Monthly Detail'!$4:$4, '2025 Overview'!I$19, 'Monthly Detail'!15:15) | J23: =SUMIF('Monthly Detail'!$4:$4, '2025 Overview'!J$19, 'Monthly Detail'!15:15) | ... N23: =SUMIF('Monthly Detail'!$4:$4, '2025 Overview'!N$19, 'Monthly Detail'!15:15) | P23: =+SUM(C23:N23)
B24: MRR | C24: =SUMIF('Monthly Detail'!$4:$4, '2025 Overview'!C$19, 'Monthly Detail'!41:41) | D24: =SUMIF('Monthly Detail'!$4:$4, '2025 Overview'!D$19, 'Monthly Detail'!41:41) | E24: =SUMIF('Monthly Detail'!$4:$4, '2025 Overview'!E$19, 'Monthly Detail'!41:41) | F24: =SUMIF('Monthly Detail'!$4:$4, '2025 Overview'!F$19, 'Monthly Detail'!41:41) | G24: =SUMIF('Monthly Detail'!$4:$4, '2025 Overview'!G$19, 'Monthly Detail'!41:41) | H24: =SUMIF('Monthly Detail'!$4:$4, '2025 Overview'!H$19, 'Monthly Detail'!41:41) | I24: =SUMIF('Monthly Detail'!$4:$4, '2025 Overview'!I$19, 'Monthly Detail'!41:41) | J24: =SUMIF('Monthly Detail'!$4:$4, '2025 Overview'!J$19, 'Monthly Detail'!41:41) | ... N24: =SUMIF('Monthly Detail'!$4:$4, '2025 Overview'!N$19, 'Monthly Detail'!41:41) | P24: =+AVERAGE(C24:N24)
B25: Recurring Client Base | C25: =SUMIF('Monthly Detail'!$4:$4, '2025 Overview'!C$19, 'Monthly Detail'!17:17) | D25: =SUMIF('Monthly Detail'!$4:$4, '2025 Overview'!D$19, 'Monthly Detail'!17:17) | E25: =SUMIF('Monthly Detail'!$4:$4, '2025 Overview'!E$19, 'Monthly Detail'!17:17) | F25: =SUMIF('Monthly Detail'!$4:$4, '2025 Overview'!F$19, 'Monthly Detail'!17:17) | G25: =SUMIF('Monthly Detail'!$4:$4, '2025 Overview'!G$19, 'Monthly Detail'!17:17) | H25: =SUMIF('Monthly Detail'!$4:$4, '2025 Overview'!H$19, 'Monthly Detail'!17:17) | I25: =SUMIF('Monthly Detail'!$4:$4, '2025 Overview'!I$19, 'Monthly Detail'!17:17) | J25: =SUMIF('Monthly Detail'!$4:$4, '2025 Overview'!J$19, 'Monthly Detail'!17:17) | ... N25: =SUMIF('Monthly Detail'!$4:$4, '2025 Overview'!N$19, 'Monthly Detail'!17:17)
B28: Software - COS | C28: =SUMIF('Monthly Detail'!$4:$4, '2025 Overview'!C$19, 'Monthly Detail'!58:58) | D28: =SUMIF('Monthly Detail'!$4:$4, '2025 Overview'!D$19, 'Monthly Detail'!58:58) | E28: =SUMIF('Monthly Detail'!$4:$4, '2025 Overview'!E$19, 'Monthly Detail'!58:58) | F28: =SUMIF('Monthly Detail'!$4:$4, '2025 Overview'!F$19, 'Monthly Detail'!58:58) | G28: =SUMIF('Monthly Detail'!$4:$4, '2025 Overview'!G$19, 'Monthly Detail'!58:58) | H28: =SUMIF('Monthly Detail'!$4:$4, '2025 Overview'!H$19, 'Monthly Detail'!58:58) | I28: =SUMIF('Monthly Detail'!$4:$4, '2025 Overview'!I$19, 'Monthly Detail'!58:58) | J28: =SUMIF('Monthly Detail'!$4:$4, '2025 Overview'!J$19, 'Monthly Detail'!58:58) | ... N28: =SUMIF('Monthly Detail'!$4:$4, '2025 Overview'!N$19, 'Monthly Detail'!58:58) | P28: =+SUM(C28:N28)
B29: Materials - COGS | C29: =SUMIF('Monthly Detail'!$4:$4, '2025 Overview'!C$19, 'Monthly Detail'!59:59) | D29: =SUMIF('Monthly Detail'!$4:$4, '2025 Overview'!D$19, 'Monthly Detail'!59:59) | E29: =SUMIF('Monthly Detail'!$4:$4, '2025 Overview'!E$19, 'Monthly Detail'!59:59) | F29: =SUMIF('Monthly Detail'!$4:$4, '2025 Overview'!F$19, 'Monthly Detail'!59:59) | G29: =SUMIF('Monthly Detail'!$4:$4, '2025 Overview'!G$19, 'Monthly Detail'!59:59) | H29: =SUMIF('Monthly Detail'!$4:$4, '2025 Overview'!H$19, 'Monthly Detail'!59:59) | I29: =SUMIF('Monthly Detail'!$4:$4, '2025 Overview'!I$19, 'Monthly Detail'!59:59) | J29: =SUMIF('Monthly Detail'!$4:$4, '2025 Overview'!J$19, 'Monthly Detail'!59:59) | ... N29: =SUMIF('Monthly Detail'!$4:$4, '2025 Overview'!N$19, 'Monthly Detail'!59:59) | P29: =+SUM(C29:N29)
B30: Contractors - COS | C30: =SUMIF('Monthly Detail'!$4:$4, '2025 Overview'!C$19, 'Monthly Detail'!60:60) | D30: =SUMIF('Monthly Detail'!$4:$4, '2025 Overview'!D$19, 'Monthly Detail'!60:60) | E30: =SUMIF('Monthly Detail'!$4:$4, '2025 Overview'!E$19, 'Monthly Detail'!60:60) | F30: =SUMIF('Monthly Detail'!$4:$4, '2025 Overview'!F$19, 'Monthly Detail'!60:60) | G30: =SUMIF('Monthly Detail'!$4:$4, '2025 Overview'!G$19, 'Monthly Detail'!60:60) | H30: =SUMIF('Monthly Detail'!$4:$4, '2025 Overview'!H$19, 'Monthly Detail'!60:60) | I30: =SUMIF('Monthly Detail'!$4:$4, '2025 Overview'!I$19, 'Monthly Detail'!60:60) | J30: =SUMIF('Monthly Detail'!$4:$4, '2025 Overview'!J$19, 'Monthly Detail'!60:60) | ... N30: =SUMIF('Monthly Detail'!$4:$4, '2025 Overview'!N$19, 'Monthly Detail'!60:60) | P30: =+SUM(C30:N30)
B31: Total Cost of Goods Sold (COGS) | C31: =SUM(C28:C30) | D31: =SUM(D28:D30) | E31: =SUM(E28:E30) | F31: =SUM(F28:F30) | G31: =SUM(G28:G30) | H31: =SUM(H28:H30) | I31: =SUM(I28:I30) | J31: =SUM(J28:J30) | ... N31: =SUM(N28:N30) | P31: =SUM(P28:P30)
B33: Gross Margin | C33: =+C22-C31 | D33: =+D22-D31 | E33: =+E22-E31 | F33: =+F22-F31 | G33: =+G22-G31 | H33: =+H22-H31 | I33: =+I22-I31 | J33: =+J22-J31 | ... N33: =+N22-N31 | P33: =+SUM(C33:N33)
B34: GM % | C34: =IFERROR(C33/C22, 0) | D34: =IFERROR(D33/D22, 0) | E34: =IFERROR(E33/E22, 0) | F34: =IFERROR(F33/F22, 0) | G34: =IFERROR(G33/G22, 0) | H34: =IFERROR(H33/H22, 0) | I34: =IFERROR(I33/I22, 0) | J34: =IFERROR(J33/J22, 0) | ... N34: =IFERROR(N33/N22, 0) | P34: =P33/P22
B36: General & Admintrative Expenses | C36: =SUMIF('Monthly Detail'!$4:$4, '2025 Overview'!C$19, 'Monthly Detail'!$89:$89)+SUMIF('Monthly Detail'!$4:$4, '2025 Overview'!C$19, 'Monthly Detail'!$90:$90) | D36: =SUMIF('Monthly Detail'!$4:$4, '2025 Overview'!D$19, 'Monthly Detail'!$89:$89)+SUMIF('Monthly Detail'!$4:$4, '2025 Overview'!D$19, 'Monthly Detail'!$90:$90) | E36: =SUMIF('Monthly Detail'!$4:$4, '2025 Overview'!E$19, 'Monthly Detail'!$89:$89)+SUMIF('Monthly Detail'!$4:$4, '2025 Overview'!E$19, 'Monthly Detail'!$90:$90) | F36: =SUMIF('Monthly Detail'!$4:$4, '2025 Overview'!F$19, 'Monthly Detail'!$89:$89)+SUMIF('Monthly Detail'!$4:$4, '2025 Overview'!F$19, 'Monthly Detail'!$90:$90) | G36: =SUMIF('Monthly Detail'!$4:$4, '2025 Overview'!G$19, 'Monthly Detail'!$89:$89)+SUMIF('Monthly Detail'!$4:$4, '2025 Overview'!G$19, 'Monthly Detail'!$90:$90) | H36: =SUMIF('Monthly Detail'!$4:$4, '2025 Overview'!H$19, 'Monthly Detail'!$89:$89)+SUMIF('Monthly Detail'!$4:$4, '2025 Overview'!H$19, 'Monthly Detail'!$90:$90) | I36: =SUMIF('Monthly Detail'!$4:$4, '2025 Overview'!I$19, 'Monthly Detail'!$89:$89)+SUMIF('Monthly Detail'!$4:$4, '2025 Overview'!I$19, 'Monthly Detail'!$90:$90) | J36: =SUMIF('Monthly Detail'!$4:$4, '2025 Overview'!J$19, 'Monthly Detail'!$89:$89)+SUMIF('Monthly Detail'!$4:$4, '2025 Overview'!J$19, 'Monthly Detail'!$90:$90) | ... N36: =SUMIF('Monthly Detail'!$4:$4, '2025 Overview'!N$19, 'Monthly Detail'!$89:$89)+SUMIF('Monthly Detail'!$4:$4, '2025 Overview'!N$19, 'Monthly Detail'!$90:$90) | P36: =SUM(C36:O36)
B37: Operating Expenses | C37: =SUM(C36:C36) | D37: =SUM(D36:D36) | E37: =SUM(E36:E36) | F37: =SUM(F36:F36) | G37: =SUM(G36:G36) | H37: =SUM(H36:H36) | I37: =SUM(I36:I36) | J37: =SUM(J36:J36) | ... N37: =SUM(N36:N36) | P37: =SUM(P36:P36)
B39: Net Operating Income (EBITDA) | C39: =C33-C37 | D39: =D33-D37 | E39: =E33-E37 | F39: =F33-F37 | G39: =G33-G37 | H39: =H33-H37 | I39: =I33-I37 | J39: =J33-J37 | ... N39: =N33-N37 | P39: =P33-P37
B40: EBITDA % | C40: =IFERROR(C39/C22, 0) | D40: =IFERROR(D39/D22, 0) | E40: =IFERROR(E39/E22, 0) | F40: =IFERROR(F39/F22, 0) | G40: =IFERROR(G39/G22, 0) | H40: =IFERROR(H39/H22, 0) | I40: =IFERROR(I39/I22, 0) | J40: =IFERROR(J39/J22, 0) | ... N40: =IFERROR(N39/N22, 0) | P40: =P39/P22
B42: Other Income / (Expense) | C42: =SUMIF('Monthly Detail'!$4:$4, '2025 Overview'!C$19, 'Monthly Detail'!95:95) | D42: =SUMIF('Monthly Detail'!$4:$4, '2025 Overview'!D$19, 'Monthly Detail'!95:95) | E42: =SUMIF('Monthly Detail'!$4:$4, '2025 Overview'!E$19, 'Monthly Detail'!95:95) | F42: =SUMIF('Monthly Detail'!$4:$4, '2025 Overview'!F$19, 'Monthly Detail'!95:95) | G42: =SUMIF('Monthly Detail'!$4:$4, '2025 Overview'!G$19, 'Monthly Detail'!95:95) | H42: =SUMIF('Monthly Detail'!$4:$4, '2025 Overview'!H$19, 'Monthly Detail'!95:95) | I42: =SUMIF('Monthly Detail'!$4:$4, '2025 Overview'!I$19, 'Monthly Detail'!95:95) | J42: =SUMIF('Monthly Detail'!$4:$4, '2025 Overview'!J$19, 'Monthly Detail'!95:95) | ... N42: =SUMIF('Monthly Detail'!$4:$4, '2025 Overview'!N$19, 'Monthly Detail'!95:95) | P42: =SUM(C42:O42)
B43: Net Income | C43: =C39+SUM(C42:C42) | D43: =D39+SUM(D42:D42) | E43: =E39+SUM(E42:E42) | F43: =F39+SUM(F42:F42) | G43: =G39+SUM(G42:G42) | H43: =H39+SUM(H42:H42) | I43: =I39+SUM(I42:I42) | J43: =J39+SUM(J42:J42) | ... N43: =N39+SUM(N42:N42) | P43: =P39+SUM(P42:P42)
B44: NI % | C44: =IFERROR(C43/C22, 0) | D44: =IFERROR(D43/D22, 0) | E44: =IFERROR(E43/E22, 0) | F44: =IFERROR(F43/F22, 0) | G44: =IFERROR(G43/G22, 0) | H44: =IFERROR(H43/H22, 0) | I44: =IFERROR(I43/I22, 0) | J44: =IFERROR(J43/J22, 0) | ... N44: =IFERROR(N43/N22, 0) | P44: =P43/P22
B46: Operating (Business) Cash | C46: =SUMIF('Monthly Detail'!$4:$4, '2025 Overview'!C$19, 'Monthly Detail'!112:112) | D46: =SUMIF('Monthly Detail'!$4:$4, '2025 Overview'!D$19, 'Monthly Detail'!112:112) | E46: =SUMIF('Monthly Detail'!$4:$4, '2025 Overview'!E$19, 'Monthly Detail'!112:112) | F46: =SUMIF('Monthly Detail'!$4:$4, '2025 Overview'!F$19, 'Monthly Detail'!112:112) | G46: =SUMIF('Monthly Detail'!$4:$4, '2025 Overview'!G$19, 'Monthly Detail'!112:112) | H46: =SUMIF('Monthly Detail'!$4:$4, '2025 Overview'!H$19, 'Monthly Detail'!112:112) | I46: =SUMIF('Monthly Detail'!$4:$4, '2025 Overview'!I$19, 'Monthly Detail'!112:112) | J46: =SUMIF('Monthly Detail'!$4:$4, '2025 Overview'!J$19, 'Monthly Detail'!112:112) | ... N46: =SUMIF('Monthly Detail'!$4:$4, '2025 Overview'!N$19, 'Monthly Detail'!112:112)
B47: Savings Cash | C47: =SUMIF('Monthly Detail'!$4:$4, '2025 Overview'!C$19, 'Monthly Detail'!106:106) | D47: =SUMIF('Monthly Detail'!$4:$4, '2025 Overview'!D$19, 'Monthly Detail'!106:106) | E47: =SUMIF('Monthly Detail'!$4:$4, '2025 Overview'!E$19, 'Monthly Detail'!106:106) | F47: =SUMIF('Monthly Detail'!$4:$4, '2025 Overview'!F$19, 'Monthly Detail'!106:106) | G47: =SUMIF('Monthly Detail'!$4:$4, '2025 Overview'!G$19, 'Monthly Detail'!106:106) | H47: =SUMIF('Monthly Detail'!$4:$4, '2025 Overview'!H$19, 'Monthly Detail'!106:106) | I47: =SUMIF('Monthly Detail'!$4:$4, '2025 Overview'!I$19, 'Monthly Detail'!106:106) | J47: =SUMIF('Monthly Detail'!$4:$4, '2025 Overview'!J$19, 'Monthly Detail'!106:106) | ... N47: =SUMIF('Monthly Detail'!$4:$4, '2025 Overview'!N$19, 'Monthly Detail'!106:106)
B48: Total Cash Balance | C48: =SUMIF('Monthly Detail'!$4:$4, '2025 Overview'!C$19, 'Monthly Detail'!173:173) | D48: =SUMIF('Monthly Detail'!$4:$4, '2025 Overview'!D$19, 'Monthly Detail'!173:173) | E48: =SUMIF('Monthly Detail'!$4:$4, '2025 Overview'!E$19, 'Monthly Detail'!173:173) | F48: =SUMIF('Monthly Detail'!$4:$4, '2025 Overview'!F$19, 'Monthly Detail'!173:173) | G48: =SUMIF('Monthly Detail'!$4:$4, '2025 Overview'!G$19, 'Monthly Detail'!173:173) | H48: =SUMIF('Monthly Detail'!$4:$4, '2025 Overview'!H$19, 'Monthly Detail'!173:173) | I48: =SUMIF('Monthly Detail'!$4:$4, '2025 Overview'!I$19, 'Monthly Detail'!173:173) | J48: =SUMIF('Monthly Detail'!$4:$4, '2025 Overview'!J$19, 'Monthly Detail'!173:173) | ... N48: =SUMIF('Monthly Detail'!$4:$4, '2025 Overview'!N$19, 'Monthly Detail'!173:173) | P48: =+(SUM(C43:E43)*0.153)-SUM('Monthly Detail'!AO69:AP69)
B49: Total Cash Inflow (Outflow) | C49: =SUMIF('Monthly Detail'!$4:$4, '2025 Overview'!C$19, 'Monthly Detail'!170:170) | D49: =SUMIF('Monthly Detail'!$4:$4, '2025 Overview'!D$19, 'Monthly Detail'!170:170) | E49: =SUMIF('Monthly Detail'!$4:$4, '2025 Overview'!E$19, 'Monthly Detail'!170:170) | F49: =SUMIF('Monthly Detail'!$4:$4, '2025 Overview'!F$19, 'Monthly Detail'!170:170) | G49: =SUMIF('Monthly Detail'!$4:$4, '2025 Overview'!G$19, 'Monthly Detail'!170:170) | H49: =SUMIF('Monthly Detail'!$4:$4, '2025 Overview'!H$19, 'Monthly Detail'!170:170) | I49: =SUMIF('Monthly Detail'!$4:$4, '2025 Overview'!I$19, 'Monthly Detail'!170:170) | J49: =SUMIF('Monthly Detail'!$4:$4, '2025 Overview'!J$19, 'Monthly Detail'!170:170) | ... N49: =SUMIF('Monthly Detail'!$4:$4, '2025 Overview'!N$19, 'Monthly Detail'!170:170) | P49: =+SUM(C43:H43)*0.15
B50: Operating Cash Burn | C50: =-SUMIF('Monthly Detail'!$4:$4, '2025 Overview'!C$19, 'Monthly Detail'!89:89) | D50: =-SUMIF('Monthly Detail'!$4:$4, '2025 Overview'!D$19, 'Monthly Detail'!89:89) | E50: =-SUMIF('Monthly Detail'!$4:$4, '2025 Overview'!E$19, 'Monthly Detail'!89:89) | F50: =-SUMIF('Monthly Detail'!$4:$4, '2025 Overview'!F$19, 'Monthly Detail'!89:89) | G50: =-SUMIF('Monthly Detail'!$4:$4, '2025 Overview'!G$19, 'Monthly Detail'!89:89) | H50: =-SUMIF('Monthly Detail'!$4:$4, '2025 Overview'!H$19, 'Monthly Detail'!89:89) | I50: =-SUMIF('Monthly Detail'!$4:$4, '2025 Overview'!I$19, 'Monthly Detail'!89:89) | J50: =-SUMIF('Monthly Detail'!$4:$4, '2025 Overview'!J$19, 'Monthly Detail'!89:89) | ... N50: =-SUMIF('Monthly Detail'!$4:$4, '2025 Overview'!N$19, 'Monthly Detail'!89:89) | P50: =+SUM('Monthly Detail'!AO69:AS69)
B51: Owner Cash Burn/Allowance | C51: =SUMIF('Monthly Detail'!$4:$4, '2025 Overview'!C$19, 'Monthly Detail'!154:154) | D51: =SUMIF('Monthly Detail'!$4:$4, '2025 Overview'!D$19, 'Monthly Detail'!154:154) | E51: =SUMIF('Monthly Detail'!$4:$4, '2025 Overview'!E$19, 'Monthly Detail'!154:154) | F51: =SUMIF('Monthly Detail'!$4:$4, '2025 Overview'!F$19, 'Monthly Detail'!154:154) | G51: =SUMIF('Monthly Detail'!$4:$4, '2025 Overview'!G$19, 'Monthly Detail'!154:154) | H51: =SUMIF('Monthly Detail'!$4:$4,'2025 Overview'!H$19,'Monthly Detail'!154:154)-SUMIF('Monthly Detail'!$4:$4,H19,'Monthly Detail'!68:68) | I51: =SUMIF('Monthly Detail'!$4:$4,'2025 Overview'!I$19,'Monthly Detail'!154:154)-SUMIF('Monthly Detail'!$4:$4,I19,'Monthly Detail'!68:68) | J51: =SUMIF('Monthly Detail'!$4:$4,'2025 Overview'!J$19,'Monthly Detail'!154:154)-SUMIF('Monthly Detail'!$4:$4,J19,'Monthly Detail'!68:68) | K51: =SUMIF('Monthly Detail'!$4:$4,'2025 Overview'!K$19,'Monthly Detail'!154:154)-SUMIF('Monthly Detail'!$4:$4,K19,'Monthly Detail'!68:68) | L51: =SUMIF('Monthly Detail'!$4:$4,'2025 Overview'!L$19,'Monthly Detail'!154:154)-SUMIF('Monthly Detail'!$4:$4,L19,'Monthly Detail'!68:68) | M51: =SUMIF('Monthly Detail'!$4:$4,'2025 Overview'!M$19,'Monthly Detail'!154:154)-SUMIF('Monthly Detail'!$4:$4,M19,'Monthly Detail'!68:68) | N51: =SUMIF('Monthly Detail'!$4:$4,'2025 Overview'!N$19,'Monthly Detail'!154:154)-SUMIF('Monthly Detail'!$4:$4,N19,'Monthly Detail'!68:68) | P51: =+P49-P50
B52: Operating Cash Runway | C52: =+C46-SUM('Monthly Detail'!AC89:AN89)-SUM('Monthly Detail'!AC61:AN61) | D52: =+D46-SUM('Monthly Detail'!AD89:AO89)-SUM('Monthly Detail'!AD61:AO61) | E52: =+E46-SUM('Monthly Detail'!AE89:AP89)-SUM('Monthly Detail'!AE61:AP61) | F52: =+F46-SUM('Monthly Detail'!AF89:AQ89)-SUM('Monthly Detail'!AF61:AQ61) | G52: =+G46-SUM('Monthly Detail'!AG89:AR89)-SUM('Monthly Detail'!AG61:AR61) | H52: =+H46-SUM('Monthly Detail'!AH89:AS89)-SUM('Monthly Detail'!AH61:AS61) | I52: =+I46-SUM('Monthly Detail'!AI89:AT89)-SUM('Monthly Detail'!AI61:AT61) | J52: =+J46-SUM('Monthly Detail'!AJ89:AU89)-SUM('Monthly Detail'!AJ61:AU61) | ... N52: =+N46-SUM('Monthly Detail'!AN89:AY89)-SUM('Monthly Detail'!AN61:AY61)
B53: Owner Cash Runway | C53: =+C48-SUM('Monthly Detail'!AC89:AN89)-SUM('Monthly Detail'!AC61:AN61) | D53: =+D48-SUM('Monthly Detail'!AD89:AO89)-SUM('Monthly Detail'!AD61:AO61) | E53: =+E48-SUM('Monthly Detail'!AE89:AP89)-SUM('Monthly Detail'!AE61:AP61) | F53: =+F48-SUM('Monthly Detail'!AF89:AQ89)-SUM('Monthly Detail'!AF61:AQ61) | G53: =+G48-SUM('Monthly Detail'!AG89:AR89)-SUM('Monthly Detail'!AG61:AR61) | H53: =+H48-SUM('Monthly Detail'!AH89:AS89)-SUM('Monthly Detail'!AH61:AS61) | I53: =+I48-SUM('Monthly Detail'!AI89:AT89)-SUM('Monthly Detail'!AI61:AT61) | J53: =+J48-SUM('Monthly Detail'!AJ89:AU89)-SUM('Monthly Detail'!AJ61:AU61) | ... N53: =+N48-SUM('Monthly Detail'!AN89:AY89)-SUM('Monthly Detail'!AN61:AY61)
B54: Operating Cash Runway - Burn Rate | C54: =+C46/-C50 | D54: =+D46/-D50 | E54: =+E46/-E50 | F54: =+F46/-F50 | G54: =+G46/-G50 | H54: =+H46/-H50 | I54: =+I46/-I50 | J54: =+J46/-J50 | ... N54: =+N46/-N50
B55: Cash Runway - Owner Burn Rate | C55: =+IFERROR(C48/-C51, 0) | D55: =+IFERROR(D48/-D51, 0) | E55: =+IFERROR(E48/-E51, 0) | F55: =+IFERROR(F48/-F51, 0) | G55: =+IFERROR(G48/-G51, 0) | H55: =+IFERROR(H48/-H51, 0) | I55: =+IFERROR(I48/-I51, 0) | J55: =+IFERROR(J48/-J51, 0) | ... N55: =+IFERROR(N48/-N51, 0)

Sheet 2025 AOP
B15: 2025 Overview
C18: January | D18: February | E18: March | F18: April | G18: May | H18: June | I18: July | J18: August | K18: September | L18: October | M18: November | N18: December | P18: Total
C19: 45688 | D19: 45716 | E19: 45747 | F19: 45777 | G19: 45808 | H19: 45838 | I19: 45869 | J19: 45900 | K19: 45930 | L19: 45961 | M19: 45991 | N19: 46022 | O19: 45322
B20: Service Income | C20: 7249.7138 | D20: 4913.4872 | E20: 6536.7151 | F20: 9380.6106 | G20: 10754.417 | H20: 10296.469 | I20: 8231.419 | J20: 7580.1793 | K20: 6911.5121 | L20: 7871.8411 | M20: 7017.7073 | N20: 8571.1673 | P20: 95315.238
B21: Misc. | C21: 0 | D21: 0 | E21: 0 | F21: 0 | G21: 0 | H21: 0 | I21: 0 | J21: 0 | K21: 0 | L21: 0 | M21: 0 | N21: 0 | P21: 0
B22: Total Income | C22: 7249.7138 | D22: 4913.4872 | E22: 6536.7151 | F22: 9380.6106 | G22: 10754.417 | H22: 10296.469 | I22: 8231.419 | J22: 7580.1793 | K22: 6911.5121 | L22: 7871.8411 | M22: 7017.7073 | N22: 8571.1673 | P22: 95315.238
B23: # of Appointments | C23: 80.370052 | D23: 59.794008 | E23: 75.759674 | F23: 108.72005 | G23: 130.30784 | H23: 113.65213 | I23: 95.401071 | J23: 92.036778 | K23: 76.462454 | L23: 91.23361 | M23: 85.852884 | N23: 94.608295 | P23: 1104.1988
B24: MRR | C24: 5375.6771 | D24: 3207.5442 | E24: 4505.4852 | F24: 6748.1072 | G24: 7779.5024 | H24: 7231.6338 | I24: 6123.8576 | J24: 5252.8868 | K24: 4808.0085 | L24: 5880.5453 | M24: 4643.0956 | N24: 6105.5718 | P24: 5638.493
B25: Recurring Client Base | C25: 40.158949 | D25: 33.93714 | E25: 40.724568 | F25: 55.996281 | G25: 66.743042 | H25: 59.955614 | I25: 47.511996 | J25: 49.208853 | K25: 40.724568 | L25: 45.24952 | M25: 48.077615 | N25: 49.208853
B28: Software - COS | C28: 214.68476 | D28: 145.50241 | E28: 193.57083 | F28: 277.78671 | G28: 318.46904 | H28: 304.9079 | I28: 243.75586 | J28: 224.47079 | K28: 204.66964 | L28: 233.10773 | M28: 207.81439 | N28: 253.81678 | P28: 2822.5568
B29: Materials - COGS | C29: 244.43671 | D29: 165.66677 | E29: 220.39672 | F29: 316.28361 | G29: 362.60387 | H29: 347.16337 | I29: 277.53661 | J29: 255.57893 | K29: 233.03366 | L29: 265.41282 | M29: 236.61421 | N29: 288.99182 | P29: 3213.7191
B30: Contractors - COS | C30: 0 | D30: 300 | E30: 540 | F30: 940.80078 | G30: 1179.6343 | H30: 980.02097 | I30: 381.01607 | J30: 540 | K30: 300 | L30: 558.50415 | M30: 540 | N30: 680.08064 | P30: 6940.0569
B31: Total Cost of Goods Sold (COGS) | C31: 459.12148 | D31: 611.16918 | E31: 953.96755 | F31: 1534.8711 | G31: 1860.7072 | H31: 1632.0922 | I31: 902.30854 | J31: 1020.0497 | K31: 737.7033 | L31: 1057.0247 | M31: 984.4286 | N31: 1222.8892 | P31: 12976.333
B33: Gross Margin | C33: 6790.5923 | D33: 4302.318 | E33: 5582.7475 | F33: 7845.7395 | G33: 8893.7095 | H33: 8664.3768 | I33: 7329.1104 | J33: 6560.1295 | K33: 6173.8088 | L33: 6814.8164 | M33: 6033.2787 | N33: 7348.278 | P33: 82338.906
B34: GM % | C34: 0.9366704 | D34: 0.87561397 | E34: 0.8540601 | F34: 0.83637834 | G34: 0.82698204 | H34: 0.8414901 | I34: 0.89038238 | J34: 0.86543198 | K34: 0.89326456 | L34: 0.86572078 | M34: 0.85972219 | N34: 0.85732524 | P34: 0.86385878
B36: General & Admintrative Expenses | C36: 2422.1893 | D36: 6297.7867 | E36: 6297.7867 | F36: 6297.7867 | G36: 6297.7867 | H36: 6347.7867 | I36: 6297.7867 | J36: 6297.7867 | K36: 6297.7867 | L36: 6402.7867 | M36: 6297.7867 | N36: 6297.7867 | P36: 71852.843
B37: Operating Expenses | C37: 2422.1893 | D37: 6297.7867 | E37: 6297.7867 | F37: 6297.7867 | G37: 6297.7867 | H37: 6347.7867 | I37: 6297.7867 | J37: 6297.7867 | K37: 6297.7867 | L37: 6402.7867 | M37: 6297.7867 | N37: 6297.7867 | P37: 71852.843
B39: Net Operating Income (EBITDA) | C39: 4368.403 | D39: -1995.4687 | E39: -715.03914 | F39: 1547.9528 | G39: 2595.9228 | H39: 2316.5901 | I39: 1031.3238 | J39: 262.34287 | K39: -123.97782 | L39: 412.0297 | M39: -264.50799 | N39: 1050.4914 | P39: 10486.063
B40: EBITDA % | C40: 0.60256213 | D40: -0.40612066 | E40: -0.10938815 | F40: 0.16501621 | G40: 0.24138202 | H40: 0.22498879 | I40: 0.12529113 | J40: 0.034609059 | K40: -0.017937872 | L40: 0.052342228 | M40: -0.037691511 | N40: 0.12256106 | P40: 0.11001455
B42: Other Income / (Expense) | C42: 0 | D42: 0 | E42: 0 | F42: 0 | G42: 0 | H42: 0 | I42: 0 | J42: 0 | K42: 0 | L42: 0 | M42: 0 | N42: 0 | P42: 0
B43: Net Income | C43: 4368.403 | D43: -1995.4687 | E43: -715.03914 | F43: 1547.9528 | G43: 2595.9228 | H43: 2316.5901 | I43: 1031.3238 | J43: 262.34287 | K43: -123.97782 | L43: 412.0297 | M43: -264.50799 | N43: 1050.4914 | P43: 10486.063
B44: NI % | C44: 0.60256213 | D44: -0.40612066 | E44: -0.10938815 | F44: 0.16501621 | G44: 0.24138202 | H44: 0.22498879 | I44: 0.12529113 | J44: 0.034609059 | K44: -0.017937872 | L44: 0.052342228 | M44: -0.037691511 | N44: 0.12256106 | P44: 0.11001455
B46: Operating (Business) Cash | C46: 1971.0959 | D46: 1048.9393 | E46: 874.49432 | F46: 2144.9226 | G46: 4127.9302 | H46: 5968.4948 | I46: 5707.9614 | J46: 4917.3937 | K46: 3876.0898 | L46: 3148.398 | M46: 2019.7107 | N46: 1694.3507
B47: Savings Cash | C47: 28.95 | D47: 28.95 | E47: 28.95 | F47: 28.95 | G47: 28.95 | H47: 28.95 | I47: 28.95 | J47: 28.95 | K47: 28.95 | L47: 28.95 | M47: 28.95 | N47: 28.95
B48: Total Cash Balance | C48: 3032.4552 | D48: 1613.7528 | E48: 1345.3759 | F48: 3299.881 | G48: 6350.6618 | H48: 9182.2997 | I48: 8781.4791 | J48: 7565.2211 | K48: 5963.215 | L48: 4843.6892 | M48: 3107.2473 | N48: 2606.6934
B49: Total Cash Inflow (Outflow) | C49: 2311.7784 | D49: -1418.7024 | E49: -268.3769 | F49: 1954.5051 | G49: 3050.7809 | H49: 2831.6379 | I49: -400.8206 | J49: -1216.258 | K49: -1602.006 | L49: -1119.5258 | M49: -1736.4419 | N49: -500.55389
B50: Operating Cash Burn | C50: 2422.1893 | D50: 6297.7867 | E50: 6297.7867 | F50: 6297.7867 | G50: 6297.7867 | H50: 6347.7867 | I50: 6297.7867 | J50: 6297.7867 | K50: 6297.7867 | L50: 6402.7867 | M50: 6297.7867 | N50: 6297.7867
B51: Owner Cash Burn/Allowance | C51: -2000 | D51: -1500 | E51: -1500 | F51: -1500 | G51: -1500 | H51: -1500 | I51: -1500 | J51: -1500 | K51: -1500 | L51: -1500 | M51: -1500 | N51: -1500
B52: Operating Cash Runway | C52: -32096.07 | D52: -38423.252 | E52: -44525.631 | F52: -49542.441 | G52: -51632.187 | H52: -54259.202 | I52: -59152.84 | J52: -63722.694 | K52: -69200.348 | L52: -73914.531 | M52: -78664.644 | N52: -83134.825
B53: Owner Cash Runway | C53: -31034.711 | D53: -37858.439 | E53: -44054.75 | F53: -48387.483 | G53: -49409.456 | H53: -51045.397 | I53: -56079.322 | J53: -61074.867 | K53: -67113.223 | L53: -72219.24 | M53: -77577.107 | N53: -82222.482
B54: Operating Cash Runway - Burn Rate | C54: -0.81376623 | D54: -0.16655682 | E54: -0.13885741 | F54: -0.34058356 | G54: -0.65545729 | H54: -0.94024817 | I54: -0.90634404 | J54: -0.780813 | K54: -0.61546857 | L54: -0.49172308 | M54: -0.32070167 | N54: -0.26903907
B55: Cash Runway - Owner Burn Rate | C55: 1.5162276 | D55: 1.0758352 | E55: 0.89691725 | F55: 2.1999206 | G55: 4.2337745 | H55: 6.1215331 | I55: 5.8543194 | J55: 5.0434807 | K55: 3.9754767 | L55: 3.2291261 | M55: 2.0714982 | N55: 1.7377956

Sheet 2024 Overview
B15: 2024 Overview
C18: January | D18: February | E18: March | F18: April | G18: May | H18: June | I18: July | J18: August | K18: September | L18: October | M18: November | N18: December | P18: Total
C19: 45322 | D19: 45351 | E19: 45382 | F19: 45412 | G19: 45443 | H19: 45473 | I19: 45504 | J19: 45535 | K19: 45565 | L19: 45596 | M19: 45626 | N19: 45657 | O19: 45322
B20: Service Income | C20: =SUMIF('Monthly Detail'!$4:$4, '2024 Overview'!C$19, 'Monthly Detail'!13:13) | D20: =SUMIF('Monthly Detail'!$4:$4, '2024 Overview'!D$19, 'Monthly Detail'!13:13) | E20: =SUMIF('Monthly Detail'!$4:$4, '2024 Overview'!E$19, 'Monthly Detail'!13:13) | F20: =SUMIF('Monthly Detail'!$4:$4, '2024 Overview'!F$19, 'Monthly Detail'!13:13) | G20: =SUMIF('Monthly Detail'!$4:$4, '2024 Overview'!G$19, 'Monthly Detail'!13:13) | H20: =SUMIF('Monthly Detail'!$4:$4, '2024 Overview'!H$19, 'Monthly Detail'!13:13) | I20: =SUMIF('Monthly Detail'!$4:$4, '2024 Overview'!I$19, 'Monthly Detail'!13:13) | J20: =SUMIF('Monthly Detail'!$4:$4, '2024 Overview'!J$19, 'Monthly Detail'!13:13) | ... N20: =SUMIF('Monthly Detail'!$4:$4, '2024 Overview'!N$19, 'Monthly Detail'!13:13) | P20: =SUM(C20:O20)
B21: Misc. | C21: =SUMIF('Monthly Detail'!$4:$4, '2024 Overview'!C$19, 'Monthly Detail'!12:12) | D21: =SUMIF('Monthly Detail'!$4:$4, '2024 Overview'!D$19, 'Monthly Detail'!12:12) | E21: =SUMIF('Monthly Detail'!$4:$4, '2024 Overview'!E$19, 'Monthly Detail'!12:12) | F21: =SUMIF('Monthly Detail'!$4:$4, '2024 Overview'!F$19, 'Monthly Detail'!12:12) | G21: =SUMIF('Monthly Detail'!$4:$4, '2024 Overview'!G$19, 'Monthly Detail'!12:12) | H21: =SUMIF('Monthly Detail'!$4:$4, '2024 Overview'!H$19, 'Monthly Detail'!12:12) | I21: =SUMIF('Monthly Detail'!$4:$4, '2024 Overview'!I$19, 'Monthly Detail'!12:12) | J21: =SUMIF('Monthly Detail'!$4:$4, '2024 Overview'!J$19, 'Monthly Detail'!12:12) | ... N21: =SUMIF('Monthly Detail'!$4:$4, '2024 Overview'!N$19, 'Monthly Detail'!12:12) | P21: =SUM(C21:O21)
B22: Total Income | C22: =SUM(C20:C21) | D22: =SUM(D20:D21) | E22: =SUM(E20:E21) | F22: =SUM(F20:F21) | G22: =SUM(G20:G21) | H22: =SUM(H20:H21) | I22: =SUM(I20:I21) | J22: =SUM(J20:J21) | ... N22: =SUM(N20:N21) | P22: =SUM(P20:P20)
B23: # of Appointments | C23: =+'Monthly Detail'!AB15 | D23: =+'Monthly Detail'!AC15 | E23: =+'Monthly Detail'!AD15 | F23: =+'Monthly Detail'!AE15 | G23: =+'Monthly Detail'!AF15 | H23: =+'Monthly Detail'!AG15 | I23: =+'Monthly Detail'!AH15 | J23: =+'Monthly Detail'!AI15 | ... N23: =+'Monthly Detail'!AM15 | P23: =+SUM(C23:N23)
B24: MRR | C24: =+'Monthly Detail'!AB41 | D24: =+'Monthly Detail'!AC41 | E24: =+'Monthly Detail'!AD41 | F24: =+'Monthly Detail'!AE41 | G24: =+'Monthly Detail'!AF41 | H24: =+'Monthly Detail'!AG41 | I24: =+'Monthly Detail'!AH41 | J24: =+'Monthly Detail'!AI41 | ... N24: =+'Monthly Detail'!AM41 | P24: =+AVERAGE(C24:N24)
B25: Recurring Client Base | C25: =+'Monthly Detail'!AB17 | D25: =+'Monthly Detail'!AC17 | E25: =+'Monthly Detail'!AD17 | F25: =+'Monthly Detail'!AE17 | G25: =+'Monthly Detail'!AF17 | H25: =+'Monthly Detail'!AG17 | I25: =+'Monthly Detail'!AH17 | J25: =+'Monthly Detail'!AI17 | ... N25: =+'Monthly Detail'!AM17
B28: Software - COS | C28: =SUMIF('Monthly Detail'!$4:$4, '2024 Overview'!C$19, 'Monthly Detail'!58:58) | D28: =SUMIF('Monthly Detail'!$4:$4, '2024 Overview'!D$19, 'Monthly Detail'!58:58) | E28: =SUMIF('Monthly Detail'!$4:$4, '2024 Overview'!E$19, 'Monthly Detail'!58:58) | F28: =SUMIF('Monthly Detail'!$4:$4, '2024 Overview'!F$19, 'Monthly Detail'!58:58) | G28: =SUMIF('Monthly Detail'!$4:$4, '2024 Overview'!G$19, 'Monthly Detail'!58:58) | H28: =SUMIF('Monthly Detail'!$4:$4, '2024 Overview'!H$19, 'Monthly Detail'!58:58) | I28: =SUMIF('Monthly Detail'!$4:$4, '2024 Overview'!I$19, 'Monthly Detail'!58:58) | J28: =SUMIF('Monthly Detail'!$4:$4, '2024 Overview'!J$19, 'Monthly Detail'!58:58) | ... N28: =SUMIF('Monthly Detail'!$4:$4, '2024 Overview'!N$19, 'Monthly Detail'!58:58) | P28: =+SUM(C28:N28)
B29: Materials - COGS | C29: =SUMIF('Monthly Detail'!$4:$4, '2024 Overview'!C$19, 'Monthly Detail'!59:59) | D29: =SUMIF('Monthly Detail'!$4:$4, '2024 Overview'!D$19, 'Monthly Detail'!59:59) | E29: =SUMIF('Monthly Detail'!$4:$4, '2024 Overview'!E$19, 'Monthly Detail'!59:59) | F29: =SUMIF('Monthly Detail'!$4:$4, '2024 Overview'!F$19, 'Monthly Detail'!59:59) | G29: =SUMIF('Monthly Detail'!$4:$4, '2024 Overview'!G$19, 'Monthly Detail'!59:59) | H29: =SUMIF('Monthly Detail'!$4:$4, '2024 Overview'!H$19, 'Monthly Detail'!59:59) | I29: =SUMIF('Monthly Detail'!$4:$4, '2024 Overview'!I$19, 'Monthly Detail'!59:59) | J29: =SUMIF('Monthly Detail'!$4:$4, '2024 Overview'!J$19, 'Monthly Detail'!59:59) | ... N29: =SUMIF('Monthly Detail'!$4:$4, '2024 Overview'!N$19, 'Monthly Detail'!59:59) | P29: =+SUM(C29:N29)
B30: Contractors - COS | C30: =SUMIF('Monthly Detail'!$4:$4, '2024 Overview'!C$19, 'Monthly Detail'!60:60) | D30: =SUMIF('Monthly Detail'!$4:$4, '2024 Overview'!D$19, 'Monthly Detail'!60:60) | E30: =SUMIF('Monthly Detail'!$4:$4, '2024 Overview'!E$19, 'Monthly Detail'!60:60) | F30: =SUMIF('Monthly Detail'!$4:$4, '2024 Overview'!F$19, 'Monthly Detail'!60:60) | G30: =SUMIF('Monthly Detail'!$4:$4, '2024 Overview'!G$19, 'Monthly Detail'!60:60) | H30: =SUMIF('Monthly Detail'!$4:$4, '2024 Overview'!H$19, 'Monthly Detail'!60:60) | I30: =SUMIF('Monthly Detail'!$4:$4, '2024 Overview'!I$19, 'Monthly Detail'!60:60) | J30: =SUMIF('Monthly Detail'!$4:$4, '2024 Overview'!J$19, 'Monthly Detail'!60:60) | ... N30: =SUMIF('Monthly Detail'!$4:$4, '2024 Overview'!N$19, 'Monthly Detail'!60:60) | P30: =+SUM(C30:N30)
B31: Total Cost of Goods Sold (COGS) | C31: =SUM(C28:C30) | D31: =SUM(D28:D30) | E31: =SUM(E28:E30) | F31: =SUM(F28:F30) | G31: =SUM(G28:G30) | H31: =SUM(H28:H30) | I31: =SUM(I28:I30) | J31: =SUM(J28:J30) | ... N31: =SUM(N28:N30) | P31: =SUM(P28:P30)
B33: Gross Margin | C33: =+C22-C31 | D33: =+D22-D31 | E33: =+E22-E31 | F33: =+F22-F31 | G33: =+G22-G31 | H33: =+H22-H31 | I33: =+I22-I31 | J33: =+J22-J31 | ... N33: =+N22-N31 | P33: =+SUM(C33:N33)
B34: GM % | C34: =IFERROR(C33/C22, 0) | D34: =IFERROR(D33/D22, 0) | E34: =IFERROR(E33/E22, 0) | F34: =IFERROR(F33/F22, 0) | G34: =IFERROR(G33/G22, 0) | H34: =IFERROR(H33/H22, 0) | I34: =IFERROR(I33/I22, 0) | J34: =IFERROR(J33/J22, 0) | ... N34: =IFERROR(N33/N22, 0) | P34: =P33/P22
B36: General & Admintrative Expenses | C36: =SUMIF('Monthly Detail'!$4:$4, '2024 Overview'!C$19, 'Monthly Detail'!$89:$89) | D36: =SUMIF('Monthly Detail'!$4:$4, '2024 Overview'!D$19, 'Monthly Detail'!$89:$89) | E36: =SUMIF('Monthly Detail'!$4:$4, '2024 Overview'!E$19, 'Monthly Detail'!$89:$89) | F36: =SUMIF('Monthly Detail'!$4:$4, '2024 Overview'!F$19, 'Monthly Detail'!$89:$89) | G36: =SUMIF('Monthly Detail'!$4:$4, '2024 Overview'!G$19, 'Monthly Detail'!$89:$89) | H36: =SUMIF('Monthly Detail'!$4:$4, '2024 Overview'!H$19, 'Monthly Detail'!$89:$89) | I36: =SUMIF('Monthly Detail'!$4:$4, '2024 Overview'!I$19, 'Monthly Detail'!$89:$89) | J36: =SUMIF('Monthly Detail'!$4:$4, '2024 Overview'!J$19, 'Monthly Detail'!$89:$89) | ... N36: =SUMIF('Monthly Detail'!$4:$4, '2024 Overview'!N$19, 'Monthly Detail'!$89:$89) | P36: =SUM(C36:O36)
B37: Operating Expenses | C37: =SUM(C36:C36) | D37: =SUM(D36:D36) | E37: =SUM(E36:E36) | F37: =SUM(F36:F36) | G37: =SUM(G36:G36) | H37: =SUM(H36:H36) | I37: =SUM(I36:I36) | J37: =SUM(J36:J36) | ... N37: =SUM(N36:N36) | P37: =SUM(P36:P36)
B39: Net Operating Income (EBITDA) | C39: =C33-C37 | D39: =D33-D37 | E39: =E33-E37 | F39: =F33-F37 | G39: =G33-G37 | H39: =H33-H37 | I39: =I33-I37 | J39: =J33-J37 | ... N39: =N33-N37 | P39: =P33-P37
B40: EBITDA % | C40: =IFERROR(C39/C22, 0) | D40: =IFERROR(D39/D22, 0) | E40: =IFERROR(E39/E22, 0) | F40: =IFERROR(F39/F22, 0) | G40: =IFERROR(G39/G22, 0) | H40: =IFERROR(H39/H22, 0) | I40: =IFERROR(I39/I22, 0) | J40: =IFERROR(J39/J22, 0) | ... N40: =IFERROR(N39/N22, 0) | P40: =P39/P22
B42: Other Income / (Expense) | C42: =SUMIF('Monthly Detail'!$4:$4, '2024 Overview'!C$19, 'Monthly Detail'!130:130) | D42: =SUMIF('Monthly Detail'!$4:$4, '2024 Overview'!D$19, 'Monthly Detail'!130:130) | E42: =SUMIF('Monthly Detail'!$4:$4, '2024 Overview'!E$19, 'Monthly Detail'!130:130) | F42: =SUMIF('Monthly Detail'!$4:$4, '2024 Overview'!F$19, 'Monthly Detail'!130:130) | G42: =SUMIF('Monthly Detail'!$4:$4, '2024 Overview'!G$19, 'Monthly Detail'!130:130) | H42: =SUMIF('Monthly Detail'!$4:$4, '2024 Overview'!H$19, 'Monthly Detail'!130:130) | I42: =SUMIF('Monthly Detail'!$4:$4, '2024 Overview'!I$19, 'Monthly Detail'!130:130) | J42: =SUMIF('Monthly Detail'!$4:$4, '2024 Overview'!J$19, 'Monthly Detail'!130:130) | ... N42: =SUMIF('Monthly Detail'!$4:$4, '2024 Overview'!N$19, 'Monthly Detail'!130:130) | P42: =SUM(C42:O42)
B43: Net Income | C43: =C39+SUM(C42:C42) | D43: =D39+SUM(D42:D42) | E43: =E39+SUM(E42:E42) | F43: =F39+SUM(F42:F42) | G43: =G39+SUM(G42:G42) | H43: =H39+SUM(H42:H42) | I43: =I39+SUM(I42:I42) | J43: =J39+SUM(J42:J42) | ... N43: =N39+SUM(N42:N42) | P43: =P39+SUM(P42:P42)
B44: NI % | C44: =IFERROR(C43/C22, 0) | D44: =IFERROR(D43/D22, 0) | E44: =IFERROR(E43/E22, 0) | F44: =IFERROR(F43/F22, 0) | G44: =IFERROR(G43/G22, 0) | H44: =IFERROR(H43/H22, 0) | I44: =IFERROR(I43/I22, 0) | J44: =IFERROR(J43/J22, 0) | ... N44: =IFERROR(N43/N22, 0) | P44: =P43/P22
B46: Operating (Business) Cash | C46: =+'Monthly Detail'!AB112 | D46: =+'Monthly Detail'!AC112 | E46: =+'Monthly Detail'!AD112 | F46: =+'Monthly Detail'!AE112 | G46: =+'Monthly Detail'!AF112 | H46: =+'Monthly Detail'!AG112 | I46: =+'Monthly Detail'!AH112 | J46: =+'Monthly Detail'!AI112 | ... N46: =+'Monthly Detail'!AM112
B47: Savings Cash | C47: =+'Monthly Detail'!AB106 | D47: =+'Monthly Detail'!AC106 | E47: =+'Monthly Detail'!AD106 | F47: =+'Monthly Detail'!AE106 | G47: =+'Monthly Detail'!AF106 | H47: =+'Monthly Detail'!AG106 | I47: =+'Monthly Detail'!AH106 | J47: =+'Monthly Detail'!AI106 | ... N47: =+'Monthly Detail'!AM106
B48: Total Cash Balance | C48: =+'Monthly Detail'!AB173 | D48: =+'Monthly Detail'!AC173 | E48: =+'Monthly Detail'!AD173 | F48: =+'Monthly Detail'!AE173 | G48: =+'Monthly Detail'!AF173 | H48: =+'Monthly Detail'!AG173 | I48: =+'Monthly Detail'!AH173 | J48: =+'Monthly Detail'!AI173 | ... N48: =+'Monthly Detail'!AM173
B49: Total Cash Inflow (Outflow) | C49: =SUMIF('Monthly Detail'!$4:$4, '2024 Overview'!C$19, 'Monthly Detail'!170:170) | D49: =SUMIF('Monthly Detail'!$4:$4, '2024 Overview'!D$19, 'Monthly Detail'!170:170) | E49: =SUMIF('Monthly Detail'!$4:$4, '2024 Overview'!E$19, 'Monthly Detail'!170:170) | F49: =SUMIF('Monthly Detail'!$4:$4, '2024 Overview'!F$19, 'Monthly Detail'!170:170) | G49: =SUMIF('Monthly Detail'!$4:$4, '2024 Overview'!G$19, 'Monthly Detail'!170:170) | H49: =SUMIF('Monthly Detail'!$4:$4, '2024 Overview'!H$19, 'Monthly Detail'!170:170) | I49: =SUMIF('Monthly Detail'!$4:$4, '2024 Overview'!I$19, 'Monthly Detail'!170:170) | J49: =SUMIF('Monthly Detail'!$4:$4, '2024 Overview'!J$19, 'Monthly Detail'!170:170) | ... N49: =SUMIF('Monthly Detail'!$4:$4, '2024 Overview'!N$19, 'Monthly Detail'!170:170)
B50: Operating Cash Burn | C50: =-'Monthly Detail'!AB89 | D50: =-'Monthly Detail'!AC89 | E50: =-'Monthly Detail'!AD89 | F50: =-'Monthly Detail'!AE89 | G50: =-'Monthly Detail'!AF89 | H50: =-'Monthly Detail'!AG89 | I50: =-'Monthly Detail'!AH89 | J50: =-'Monthly Detail'!AI89 | ... N50: =-'Monthly Detail'!AM89
B51: Owner Cash Burn | C51: =+'Monthly Detail'!AB154 | D51: =+'Monthly Detail'!AC154 | E51: =+'Monthly Detail'!AD154 | F51: =+'Monthly Detail'!AE154 | G51: =+'Monthly Detail'!AF154 | H51: =+'Monthly Detail'!AG154 | I51: =+'Monthly Detail'!AH154 | J51: =+'Monthly Detail'!AI154 | ... N51: =+'Monthly Detail'!AM154
B52: Operating Cash Runway | C52: =+C46-SUM('Monthly Detail'!AC89:AN89)-SUM('Monthly Detail'!AC61:AN61) | D52: =+D46-SUM('Monthly Detail'!AD89:AO89)-SUM('Monthly Detail'!AD61:AO61) | E52: =+E46-SUM('Monthly Detail'!AE89:AP89)-SUM('Monthly Detail'!AE61:AP61) | F52: =+F46-SUM('Monthly Detail'!AF89:AQ89)-SUM('Monthly Detail'!AF61:AQ61) | G52: =+G46-SUM('Monthly Detail'!AG89:AR89)-SUM('Monthly Detail'!AG61:AR61) | H52: =+H46-SUM('Monthly Detail'!AH89:AS89)-SUM('Monthly Detail'!AH61:AS61) | I52: =+I46-SUM('Monthly Detail'!AI89:AT89)-SUM('Monthly Detail'!AI61:AT61) | J52: =+J46-SUM('Monthly Detail'!AJ89:AU89)-SUM('Monthly Detail'!AJ61:AU61) | ... N52: =+N46-SUM('Monthly Detail'!AN89:AY89)-SUM('Monthly Detail'!AN61:AY61)
B53: Owner Cash Runway | C53: =+C48-SUM('Monthly Detail'!AC89:AN89)-SUM('Monthly Detail'!AC61:AN61) | D53: =+D48-SUM('Monthly Detail'!AD89:AO89)-SUM('Monthly Detail'!AD61:AO61) | E53: =+E48-SUM('Monthly Detail'!AE89:AP89)-SUM('Monthly Detail'!AE61:AP61) | F53: =+F48-SUM('Monthly Detail'!AF89:AQ89)-SUM('Monthly Detail'!AF61:AQ61) | G53: =+G48-SUM('Monthly Detail'!AG89:AR89)-SUM('Monthly Detail'!AG61:AR61) | H53: =+H48-SUM('Monthly Detail'!AH89:AS89)-SUM('Monthly Detail'!AH61:AS61) | I53: =+I48-SUM('Monthly Detail'!AI89:AT89)-SUM('Monthly Detail'!AI61:AT61) | J53: =+J48-SUM('Monthly Detail'!AJ89:AU89)-SUM('Monthly Detail'!AJ61:AU61) | ... N53: =+N48-SUM('Monthly Detail'!AN89:AY89)-SUM('Monthly Detail'!AN61:AY61)
B54: Operating Cash Runway - Burn Rate | C54: =+C46/-C50 | D54: =+D46/-D50 | E54: =+E46/-E50 | F54: =+F46/-F50 | G54: =+G46/-G50 | H54: =+H46/-H50 | I54: =+I46/-I50 | J54: =+J46/-J50 | ... N54: =+N46/-N50
B55: Cash Runway - Owner Burn Rate | C55: =+IFERROR(C48/-C51, 0) | D55: =+IFERROR(D48/-D51, 0) | E55: =+IFERROR(E48/-E51, 0) | F55: =+IFERROR(F48/-F51, 0) | G55: =+IFERROR(G48/-G51, 0) | H55: =+IFERROR(H48/-H51, 0) | I55: =+IFERROR(I48/-I51, 0) | J55: =+IFERROR(J48/-J51, 0) | ... N55: =+IFERROR(N48/-N51, 0)

Sheet 2022 Overview
C10: =TEXT('Monthly Detail'!D4,"mmmm") | D10: =TEXT('Monthly Detail'!E4,"mmmm") | E10: =TEXT('Monthly Detail'!F4,"mmmm") | F10: =TEXT('Monthly Detail'!G4,"mmmm") | G10: =TEXT('Monthly Detail'!H4,"mmmm") | H10: =TEXT('Monthly Detail'!I4,"mmmm") | I10: =TEXT('Monthly Detail'!J4,"mmmm") | J10: =TEXT('Monthly Detail'!K4,"mmmm") | ... N10: =TEXT('Monthly Detail'!O4,"mmmm") | P10: Total
C11: 44592 | D11: 44620 | E11: 44651 | F11: 44681 | G11: 44712 | H11: 44742 | I11: 44773 | J11: 44804 | K11: 44834 | L11: 44865 | M11: 44895 | N11: 44926
B12: Service Income | C12: =SUMIF('Monthly Detail'!$4:$4, '2022 Overview'!C$11, 'Monthly Detail'!9:9) | D12: =SUMIF('Monthly Detail'!$4:$4, '2022 Overview'!D$11, 'Monthly Detail'!9:9) | E12: =SUMIF('Monthly Detail'!$4:$4, '2022 Overview'!E$11, 'Monthly Detail'!9:9) | F12: =SUMIF('Monthly Detail'!$4:$4, '2022 Overview'!F$11, 'Monthly Detail'!9:9) | G12: =SUMIF('Monthly Detail'!$4:$4, '2022 Overview'!G$11, 'Monthly Detail'!9:9) | H12: =SUMIF('Monthly Detail'!$4:$4, '2022 Overview'!H$11, 'Monthly Detail'!9:9) | I12: =SUMIF('Monthly Detail'!$4:$4, '2022 Overview'!I$11, 'Monthly Detail'!9:9) | J12: =SUMIF('Monthly Detail'!$4:$4, '2022 Overview'!J$11, 'Monthly Detail'!9:9) | ... N12: =SUMIF('Monthly Detail'!$4:$4, '2022 Overview'!N$11, 'Monthly Detail'!9:9) | P12: =SUM(C12:O12)
B13: Misc. | C13: =SUMIF('Monthly Detail'!$4:$4, '2022 Overview'!C$11, 'Monthly Detail'!12:12) | D13: =SUMIF('Monthly Detail'!$4:$4, '2022 Overview'!D$11, 'Monthly Detail'!12:12) | E13: =SUMIF('Monthly Detail'!$4:$4, '2022 Overview'!E$11, 'Monthly Detail'!12:12) | F13: =SUMIF('Monthly Detail'!$4:$4, '2022 Overview'!F$11, 'Monthly Detail'!12:12) | G13: =SUMIF('Monthly Detail'!$4:$4, '2022 Overview'!G$11, 'Monthly Detail'!12:12) | H13: =SUMIF('Monthly Detail'!$4:$4, '2022 Overview'!H$11, 'Monthly Detail'!12:12) | I13: =SUMIF('Monthly Detail'!$4:$4, '2022 Overview'!I$11, 'Monthly Detail'!12:12) | J13: =SUMIF('Monthly Detail'!$4:$4, '2022 Overview'!J$11, 'Monthly Detail'!12:12) | ... N13: =SUMIF('Monthly Detail'!$4:$4, '2022 Overview'!N$11, 'Monthly Detail'!12:12)
B14: Total Income | C14: 0.1 | D14: 0.1 | E14: 0.1 | F14: 0.1 | G14: 0.1 | H14: 0.1 | I14: 0.1 | J14: =SUM(J12:J13) | K14: =SUM(K12:K13) | L14: =SUM(L12:L13) | M14: =SUM(M12:M13) | N14: =SUM(N12:N13) | P14: =SUM(P12:P12)
B16: Gross Margin | C16: =C14 | D16: =D14 | E16: =E14 | F16: =F14 | G16: =G14 | H16: =H14 | I16: =I14 | J16: =J14 | ... N16: =N14 | P16: =P14
B17: GM % | C17: =C16/C14 | D17: =D16/D14 | E17: =E16/E14 | F17: =F16/F14 | G17: =G16/G14 | H17: =H16/H14 | I17: =I16/I14 | J17: =J16/J14 | ... N17: =N16/N14 | P17: =P16/P14
B19: General & Admintrative Expenses | C19: =SUMIF('Monthly Detail'!$4:$4, '2023 Overview'!C$11, 'Monthly Detail'!$89:$89) | D19: =SUMIF('Monthly Detail'!$4:$4, '2023 Overview'!D$11, 'Monthly Detail'!$89:$89) | E19: =SUMIF('Monthly Detail'!$4:$4, '2023 Overview'!E$11, 'Monthly Detail'!$89:$89) | F19: =SUMIF('Monthly Detail'!$4:$4, '2023 Overview'!F$11, 'Monthly Detail'!$89:$89) | G19: =SUMIF('Monthly Detail'!$4:$4, '2023 Overview'!G$11, 'Monthly Detail'!$89:$89) | H19: =SUMIF('Monthly Detail'!$4:$4, '2023 Overview'!H$11, 'Monthly Detail'!$89:$89) | I19: =SUMIF('Monthly Detail'!$4:$4, '2023 Overview'!I$11, 'Monthly Detail'!$89:$89) | J19: =SUMIF('Monthly Detail'!$4:$4, '2023 Overview'!J$11, 'Monthly Detail'!$89:$89) | ... N19: =SUMIF('Monthly Detail'!$4:$4, '2023 Overview'!N$11, 'Monthly Detail'!$89:$89) | P19: =SUM(C19:O19)
B20: Owner Guarenteed Payments | C20: =SUMIF('Monthly Detail'!$4:$4, '2022 Overview'!C$11, 'Monthly Detail'!47:47) | D20: =SUMIF('Monthly Detail'!$4:$4, '2022 Overview'!D$11, 'Monthly Detail'!47:47) | E20: =SUMIF('Monthly Detail'!$4:$4, '2022 Overview'!E$11, 'Monthly Detail'!47:47) | F20: =SUMIF('Monthly Detail'!$4:$4, '2022 Overview'!F$11, 'Monthly Detail'!47:47) | G20: =SUMIF('Monthly Detail'!$4:$4, '2022 Overview'!G$11, 'Monthly Detail'!47:47) | H20: =SUMIF('Monthly Detail'!$4:$4, '2022 Overview'!H$11, 'Monthly Detail'!47:47) | I20: =SUMIF('Monthly Detail'!$4:$4, '2022 Overview'!I$11, 'Monthly Detail'!47:47) | J20: =SUMIF('Monthly Detail'!$4:$4, '2022 Overview'!J$11, 'Monthly Detail'!47:47) | ... N20: =SUMIF('Monthly Detail'!$4:$4, '2022 Overview'!N$11, 'Monthly Detail'!47:47) | P20: =SUM(C20:O20)
B21: Operating Expenses | C21: =SUM(C19:C20) | D21: =SUM(D19:D20) | E21: =SUM(E19:E20) | F21: =SUM(F19:F20) | G21: =SUM(G19:G20) | H21: =SUM(H19:H20) | I21: =SUM(I19:I20) | J21: =SUM(J19:J20) | ... N21: =SUM(N19:N20) | P21: =SUM(P19:P20)
B23: Net Operating Income (EBITDA) | C23: =C16-C21 | D23: =D16-D21 | E23: =E16-E21 | F23: =F16-F21 | G23: =G16-G21 | H23: =H16-H21 | I23: =I16-I21 | J23: =J16-J21 | ... N23: =N16-N21 | P23: =P16-P21
B24: EBITDA % | C24: =C23/C14 | D24: =D23/D14 | E24: =E23/E14 | F24: =F23/F14 | G24: =G23/G14 | H24: =H23/H14 | I24: =I23/I14 | J24: =J23/J14 | ... N24: =N23/N14 | P24: =P23/P14
B26: Other Income / (Expense) | C26: =SUMIF('Monthly Detail'!$4:$4, '2022 Overview'!C$11, 'Monthly Detail'!77:77) | D26: =SUMIF('Monthly Detail'!$4:$4, '2022 Overview'!D$11, 'Monthly Detail'!77:77) | E26: =SUMIF('Monthly Detail'!$4:$4, '2022 Overview'!E$11, 'Monthly Detail'!77:77) | F26: =SUMIF('Monthly Detail'!$4:$4, '2022 Overview'!F$11, 'Monthly Detail'!77:77) | G26: =SUMIF('Monthly Detail'!$4:$4, '2022 Overview'!G$11, 'Monthly Detail'!77:77) | H26: =SUMIF('Monthly Detail'!$4:$4, '2022 Overview'!H$11, 'Monthly Detail'!77:77) | I26: =SUMIF('Monthly Detail'!$4:$4, '2022 Overview'!I$11, 'Monthly Detail'!77:77) | J26: =SUMIF('Monthly Detail'!$4:$4, '2022 Overview'!J$11, 'Monthly Detail'!77:77) | ... N26: =SUMIF('Monthly Detail'!$4:$4, '2022 Overview'!N$11, 'Monthly Detail'!77:77) | P26: =SUM(C26:O26)
B27: Net Income | C27: =C23+SUM(C26:C26) | D27: =D23+SUM(D26:D26) | E27: =E23+SUM(E26:E26) | F27: =F23+SUM(F26:F26) | G27: =G23+SUM(G26:G26) | H27: =H23+SUM(H26:H26) | I27: =I23+SUM(I26:I26) | J27: =J23+SUM(J26:J26) | ... N27: =N23+SUM(N26:N26) | P27: =P23+SUM(P26:P26)
B28: NI % | C28: =C27/C14 | D28: =D27/D14 | E28: =E27/E14 | F28: =F27/F14 | G28: =G27/G14 | H28: =H27/H14 | I28: =I27/I14 | J28: =J27/J14 | ... N28: =N27/N14 | P28: =P27/P14
B30: Operating Cash | C30: =SUMIF('Monthly Detail'!$4:$4, '2022 Overview'!C$11, 'Monthly Detail'!173:173) | D30: =SUMIF('Monthly Detail'!$4:$4, '2022 Overview'!D$11, 'Monthly Detail'!173:173) | E30: =SUMIF('Monthly Detail'!$4:$4, '2022 Overview'!E$11, 'Monthly Detail'!173:173) | F30: =SUMIF('Monthly Detail'!$4:$4, '2022 Overview'!F$11, 'Monthly Detail'!173:173) | G30: =SUMIF('Monthly Detail'!$4:$4, '2022 Overview'!G$11, 'Monthly Detail'!173:173) | H30: =SUMIF('Monthly Detail'!$4:$4, '2022 Overview'!H$11, 'Monthly Detail'!173:173) | I30: =SUMIF('Monthly Detail'!$4:$4, '2022 Overview'!I$11, 'Monthly Detail'!173:173) | J30: =SUMIF('Monthly Detail'!$4:$4, '2022 Overview'!J$11, 'Monthly Detail'!173:173) | ... N30: =SUMIF('Monthly Detail'!$4:$4, '2022 Overview'!N$11, 'Monthly Detail'!173:173)
B31: Cash Inflow (Outflow) | C31: =SUMIF('Monthly Detail'!$4:$4, '2022 Overview'!C$11, 'Monthly Detail'!158:158) | D31: =D30-C30 | E31: =E30-D30 | F31: =F30-E30 | G31: =G30-F30 | H31: =H30-G30 | I31: =I30-H30 | J31: =J30-I30 | K31: =K30-J30 | ... N31: =N30-M30

Sheet Quarterly Overview
C9: 45382 | D9: 45473 | F9: 45565 | H9: 45657
C10: Q1 2025 | D10: Q2 2025 | E10: Variance | F10: Q3 2025 | G10: Variance | H10: Q4 2025 | I10: Variance | K10: Total
C11: =+C10 | D11: =+D10 | F11: =+F10 | H11: =+H10 | J11: 45322
B12: Nail Tech Services | C12: =SUMIF('Monthly Detail'!$3:$3, 'Quarterly Overview'!C$11, 'Monthly Detail'!13:13) | D12: =SUMIF('Monthly Detail'!$3:$3, 'Quarterly Overview'!D$11, 'Monthly Detail'!13:13) | E12: =+D12-C12 | F12: =SUMIF('Monthly Detail'!$3:$3, 'Quarterly Overview'!F$11, 'Monthly Detail'!13:13) | G12: =+F12-D12 | H12: =SUMIF('Monthly Detail'!$3:$3, 'Quarterly Overview'!H$11, 'Monthly Detail'!13:13) | I12: =+H12-F12 | K12: =SUM(C12,D12,F12,H12)
B13: Total Income | C13: =SUM(C12:C12) | D13: =SUM(D12:D12) | E13: =+D13-C13 | F13: =SUM(F12:F12) | G13: =+F13-D13 | H13: =SUM(H12:H12) | I13: =+H13-F13 | K13: =SUM(K12:K12)
B14: # of Appointments | C14: =+SUMIFS('Monthly Detail'!15:15,'Monthly Detail'!$3:$3,'Quarterly Overview'!C$10) | D14: =+SUMIFS('Monthly Detail'!15:15,'Monthly Detail'!$3:$3,'Quarterly Overview'!D$10) | E14: =+D14-C14 | F14: =+SUMIFS('Monthly Detail'!15:15,'Monthly Detail'!$3:$3,'Quarterly Overview'!F$10) | G14: =+F14-D14 | H14: =+SUMIFS('Monthly Detail'!15:15,'Monthly Detail'!$3:$3,'Quarterly Overview'!H$10) | I14: =+H14-F14 | K14: =+SUM(C14,D14,F14,H14)
B15: MRR | C15: =+AVERAGEIFS('Monthly Detail'!41:41,'Monthly Detail'!$3:$3,'Quarterly Overview'!C$10) | D15: =+AVERAGEIFS('Monthly Detail'!41:41,'Monthly Detail'!$3:$3,'Quarterly Overview'!D$10) | E15: =+D15-C15 | F15: =+AVERAGEIFS('Monthly Detail'!41:41,'Monthly Detail'!$3:$3,'Quarterly Overview'!F$10) | G15: =+F15-D15 | H15: =+AVERAGEIFS('Monthly Detail'!41:41,'Monthly Detail'!$3:$3,'Quarterly Overview'!H$10) | I15: =+H15-F15 | K15: =+AVERAGE(C15,D15,F15,H15)
B16: Recurring Client Base | C16: =+AVERAGEIFS('Monthly Detail'!17:17,'Monthly Detail'!$3:$3,'Quarterly Overview'!C$10) | D16: =+AVERAGEIFS('Monthly Detail'!17:17,'Monthly Detail'!$3:$3,'Quarterly Overview'!D$10) | E16: =+D16-C16 | F16: =+AVERAGEIFS('Monthly Detail'!17:17,'Monthly Detail'!$3:$3,'Quarterly Overview'!F$10) | G16: =+F16-D16 | H16: =+AVERAGEIFS('Monthly Detail'!17:17,'Monthly Detail'!$3:$3,'Quarterly Overview'!H$10) | I16: =+H16-F16 | K16: =+AVERAGE(C16,D16,F16,H16)
B18: Software - COS | C18: =SUMIF('Monthly Detail'!$3:$3, 'Quarterly Overview'!C$11, 'Monthly Detail'!58:58) | D18: =SUMIF('Monthly Detail'!$3:$3, 'Quarterly Overview'!D$11, 'Monthly Detail'!58:58) | E18: =+D18-C18 | F18: =SUMIF('Monthly Detail'!$3:$3, 'Quarterly Overview'!F$11, 'Monthly Detail'!58:58) | G18: =+F18-D18 | H18: =SUMIF('Monthly Detail'!$3:$3, 'Quarterly Overview'!H$11, 'Monthly Detail'!58:58) | I18: =+H18-F18 | K18: =SUM(C18,D18,F18,H18)
B19: Materials - COGS | C19: =SUMIF('Monthly Detail'!$3:$3, 'Quarterly Overview'!C$11, 'Monthly Detail'!59:59) | D19: =SUMIF('Monthly Detail'!$3:$3, 'Quarterly Overview'!D$11, 'Monthly Detail'!59:59) | E19: =+D19-C19 | F19: =SUMIF('Monthly Detail'!$3:$3, 'Quarterly Overview'!F$11, 'Monthly Detail'!59:59) | G19: =+F19-D19 | H19: =SUMIF('Monthly Detail'!$3:$3, 'Quarterly Overview'!H$11, 'Monthly Detail'!59:59) | I19: =+H19-F19 | K19: =SUM(C19,D19,F19,H19)
B20: Contractors - COGS | C20: =SUMIF('Monthly Detail'!$3:$3, 'Quarterly Overview'!C$11, 'Monthly Detail'!60:60) | D20: =SUMIF('Monthly Detail'!$3:$3, 'Quarterly Overview'!D$11, 'Monthly Detail'!60:60) | E20: =+D20-C20 | F20: =SUMIF('Monthly Detail'!$3:$3, 'Quarterly Overview'!F$11, 'Monthly Detail'!60:60) | G20: =+F20-D20 | H20: =SUMIF('Monthly Detail'!$3:$3, 'Quarterly Overview'!H$11, 'Monthly Detail'!60:60) | I20: =+H20-F20 | K20: =SUM(C20,D20,F20,H20)
B21: Total Cost of Goods Sold (COGS) | C21: =SUM(C18:C20) | D21: =SUM(D18:D20) | E21: =SUM(E18:E19) | F21: =SUM(F18:F20) | G21: =+F21-D21 | H21: =SUM(H18:H20) | I21: =+H21-F21 | K21: =SUM(K18:K20)
B23: Gross Margin | C23: =C13-C21 | D23: =D13-D21 | E23: =+D23-C23 | F23: =F13-F21 | G23: =+F23-D23 | H23: =H13-H21 | I23: =+H23-F23 | K23: =K13-K21
B24: GM % | C24: =C23/C13 | D24: =D23/D13 | E24: =+D24-C24 | F24: =F23/F13 | G24: =+F24-D24 | H24: =H23/H13 | I24: =+H24-F24 | K24: =K23/K13
B26: General & Admintrative Expenses | C26: =SUMIF('Monthly Detail'!$3:$3, 'Quarterly Overview'!C$11, 'Monthly Detail'!$89:$89) | D26: =SUMIF('Monthly Detail'!$3:$3, 'Quarterly Overview'!D$11, 'Monthly Detail'!$89:$89) | E26: =+D26-C26 | F26: =SUMIF('Monthly Detail'!$3:$3, 'Quarterly Overview'!F$11, 'Monthly Detail'!$89:$89) | G26: =+F26-D26 | H26: =SUMIF('Monthly Detail'!$3:$3, 'Quarterly Overview'!H$11, 'Monthly Detail'!$89:$89) | I26: =+H26-F26 | K26: =SUM(C26,D26,F26,H26)
B27: Operating Expenses | C27: =SUM(C26:C26) | D27: =SUM(D26:D26) | E27: =SUM(E26:E26) | F27: =SUM(F26:F26) | G27: =+F27-D27 | H27: =SUM(H26:H26) | I27: =+H27-F27 | K27: =SUM(K26:K26)
B29: Net Operating Income (EBITDA) | C29: =C23-C27 | D29: =D23-D27 | E29: =+D29-C29 | F29: =F23-F27 | G29: =+F29-D29 | H29: =H23-H27 | I29: =+H29-F29 | K29: =K23-K27
B30: EBITDA % | C30: =C29/C13 | D30: =D29/D13 | E30: =+D30-C30 | F30: =F29/F13 | G30: =+F30-D30 | H30: =H29/H13 | I30: =+H30-F30 | K30: =K29/K13
B32: Other Income / (Expense) | C32: =SUMIF('Monthly Detail'!$3:$3, 'Quarterly Overview'!C$11, 'Monthly Detail'!96:96) | D32: =SUMIF('Monthly Detail'!$3:$3, 'Quarterly Overview'!D$11, 'Monthly Detail'!96:96) | E32: =+D32-C32 | F32: =SUMIF('Monthly Detail'!$3:$3, 'Quarterly Overview'!F$11, 'Monthly Detail'!96:96) | G32: =+F32-D32 | H32: =SUMIF('Monthly Detail'!$3:$3, 'Quarterly Overview'!H$11, 'Monthly Detail'!96:96) | I32: =+H32-F32 | K32: =SUM(C32,D32,F32,H32)
B33: Net Income | C33: =C29+SUM(C32:C32) | D33: =D29+SUM(D32:D32) | E33: =+D33-C33 | F33: =F29+SUM(F32:F32) | G33: =+F33-D33 | H33: =H29+SUM(H32:H32) | I33: =+H33-F33 | K33: =K29+SUM(K32:K32)
B34: NI % | C34: =C33/C13 | D34: =D33/D13 | E34: =+D34-C34 | F34: =F33/F13 | G34: =+F34-D34 | H34: =H33/H13 | I34: =+H34-F34 | K34: =K33/K13
B36: Operating Cash | C36: =SUMIF('Monthly Detail'!$4:$4, 'Quarterly Overview'!C$9, 'Monthly Detail'!173:173) | D36: =SUMIF('Monthly Detail'!$4:$4, 'Quarterly Overview'!D$9, 'Monthly Detail'!173:173) | F36: =SUMIF('Monthly Detail'!$4:$4, 'Quarterly Overview'!F$9, 'Monthly Detail'!173:173) | H36: =SUMIF('Monthly Detail'!$4:$4, 'Quarterly Overview'!H$9, 'Monthly Detail'!173:173)
B37: Cash Inflow (Outflow) | C37: =SUMIF('Monthly Detail'!$3:$3, 'Quarterly Overview'!C$10, 'Monthly Detail'!170:170) | D37: =SUMIF('Monthly Detail'!$3:$3, 'Quarterly Overview'!D$10, 'Monthly Detail'!170:170) | E37: =+D37-C37 | F37: =SUMIF('Monthly Detail'!$3:$3, 'Quarterly Overview'!F$10, 'Monthly Detail'!170:170) | G37: =+F37-D37 | H37: =SUMIF('Monthly Detail'!$3:$3, 'Quarterly Overview'!H$10, 'Monthly Detail'!170:170) | I37: =+H37-F37
C41: Q1 | D41: Q2 | F41: Q3 | H41: Q4
B42: 2024 AOP Income | C42: =+SUM(#REF!) | D42: =+SUM(#REF!) | F42: =+SUM(#REF!) | H42: =+SUM(#REF!)
B43: 2024 AOP Net Income | C43: =+SUM(#REF!) | D43: =+SUM(#REF!) | F43: =+SUM(#REF!) | H43: =+SUM(#REF!)
B44: 2024 AOP Avg. Appointments | C44: =+AVERAGE(#REF!) | D44: =+AVERAGE(#REF!) | F44: =+AVERAGE(#REF!) | H44: =+AVERAGE(#REF!)
B45: 2024 AOP Avg. MRR | C45: =+AVERAGE(#REF!) | D45: =+AVERAGE(#REF!) | F45: =+AVERAGE(#REF!) | H45: =+AVERAGE(#REF!)
B46: 2024 AOP Avg. Client Base | C46: =+AVERAGE(#REF!) | D46: =+AVERAGE(#REF!) | F46: =+AVERAGE(#REF!) | H46: =+AVERAGE(#REF!)

Sheet 2

Sheet Monthly Detail
D1: =YEAR(D4) | E1: =YEAR(E4) | F1: =YEAR(F4) | G1: =YEAR(G4) | H1: =YEAR(H4) | I1: =YEAR(I4) | J1: =YEAR(J4) | K1: =YEAR(K4) | ... DG1: =YEAR(DG4)
G2: Peak | H2: Peak | I2: Shoulder | J2: Shoulder | K2: Trough | L2: Shoulder | M2: Shoulder | N2: Trough | O2: Shoulder | P2: Peak | Q2: Peak | R2: Shoulder | S2: Trough | T2: Trough | U2: Shoulder | V2: Peak | W2: Shoulder | X2: Peak | Y2: Peak | Z2: Peak | AA2: Shoulder | AB2: Shoulder | AC2: Shoulder | AD2: Shoulder | AE2: Peak | AF2: Peak | AG2: Peak | AH2: Shoulder | AI2: Shoulder | AJ2: Trough | AK2: Shoulder | AL2: Trough | AM2: =+AA2 | AN2: =+AB2 | AO2: =+AC2 | AP2: =+AD2 | AQ2: =+AE2 | AR2: =+AF2 | AS2: Shoulder | AT2: =+AH2 | AU2: =+AI2 | AV2: =+AJ2 | AW2: =+AK2 | AX2: =+AL2 | AY2: =+AM2 | AZ2: =+AN2 | BA2: =+AO2 | ... DG2: =+CU2
D3: =+"Q1 "&D1 | E3: =+"Q1 "&E1 | F3: =+"Q1 "&F1 | G3: =+"Q2 "&G1 | H3: =+"Q2 "&H1 | I3: =+"Q2 "&I1 | J3: =+"Q3 "&J1 | K3: =+"Q3 "&K1 | L3: =+"Q3 "&L1 | M3: =+"Q4 "&M1 | N3: =+"Q4 "&N1 | O3: =+"Q4 "&O1 | P3: =+"Q1 "&P1 | Q3: =+"Q1 "&Q1 | R3: =+"Q1 "&R1 | S3: =+"Q2 "&S1 | T3: =+"Q2 "&T1 | U3: =+"Q2 "&U1 | V3: =+"Q3 "&V1 | W3: =+"Q3 "&W1 | X3: =+"Q3 "&X1 | Y3: =+"Q4 "&Y1 | Z3: =+"Q4 "&Z1 | AA3: =+"Q4 "&AA1 | AB3: =+"Q1 "&AB1 | AC3: =+"Q1 "&AC1 | AD3: =+"Q1 "&AD1 | AE3: =+"Q2 "&AE1 | AF3: =+"Q2 "&AF1 | AG3: =+"Q2 "&AG1 | AH3: =+"Q3 "&AH1 | AI3: =+"Q3 "&AI1 | AJ3: =+"Q3 "&AJ1 | AK3: =+"Q4 "&AK1 | AL3: =+"Q4 "&AL1 | AM3: =+"Q4 "&AM1 | AN3: =+"Q1 "&AN1 | AO3: =+"Q1 "&AO1 | AP3: =+"Q1 "&AP1 | AQ3: =+"Q2 "&AQ1 | AR3: =+"Q2 "&AR1 | AS3: =+"Q2 "&AS1 | AT3: =+"Q3 "&AT1 | AU3: =+"Q3 "&AU1 | AV3: =+"Q3 "&AV1 | AW3: =+"Q4 "&AW1 | AX3: =+"Q4 "&AX1 | AY3: =+"Q4 "&AY1 | AZ3: =+"Q1 "&AZ1 | BA3: =+"Q1 "&BA1 | BB3: =+"Q1 "&BB1 | BC3: =+"Q2 "&BC1 | BD3: =+"Q2 "&BD1 | BE3: =+"Q2 "&BE1 | BF3: =+"Q3 "&BF1 | BG3: =+"Q3 "&BG1 | BH3: =+"Q3 "&BH1 | BI3: =+"Q4 "&BI1 | BJ3: =+"Q4 "&BJ1 | BK3: =+"Q4 "&BK1 | BL3: =+"Q1 "&BL1 | BM3: =+"Q1 "&BM1 | BN3: =+"Q1 "&BN1 | BO3: =+"Q2 "&BO1 | BP3: =+"Q2 "&BP1 | BQ3: =+"Q2 "&BQ1 | BR3: =+"Q3 "&BR1 | BS3: =+"Q3 "&BS1 | BT3: =+"Q3 "&BT1 | BU3: =+"Q4 "&BU1 | BV3: =+"Q4 "&BV1 | BW3: =+"Q4 "&BW1 | BX3: =+"Q1 "&BX1 | BY3: =+"Q1 "&BY1 | BZ3: =+"Q1 "&BZ1 | CA3: =+"Q2 "&CA1 | CB3: =+"Q2 "&CB1 | CC3: =+"Q2 "&CC1 | CD3: =+"Q3 "&CD1 | CE3: =+"Q3 "&CE1 | CF3: =+"Q3 "&CF1 | CG3: =+"Q4 "&CG1 | CH3: =+"Q4 "&CH1 | CI3: =+"Q4 "&CI1 | CJ3: =+"Q1 "&CJ1 | CK3: =+"Q1 "&CK1 | CL3: =+"Q1 "&CL1 | CM3: =+"Q2 "&CM1 | CN3: =+"Q2 "&CN1 | CO3: =+"Q2 "&CO1 | CP3: =+"Q3 "&CP1 | CQ3: =+"Q3 "&CQ1 | CR3: =+"Q3 "&CR1 | CS3: =+"Q4 "&CS1 | CT3: =+"Q4 "&CT1 | CU3: =+"Q4 "&CU1 | CV3: =+"Q1 "&CV1 | CW3: =+"Q1 "&CW1 | CX3: =+"Q1 "&CX1 | CY3: =+"Q2 "&CY1 | CZ3: =+"Q2 "&CZ1 | DA3: =+"Q2 "&DA1 | DB3: =+"Q3 "&DB1 | DC3: =+"Q3 "&DC1 | DD3: =+"Q3 "&DD1 | DE3: =+"Q4 "&DE1 | DF3: =+"Q4 "&DF1 | DG3: =+"Q4 "&DG1
D4: 44592 | E4: 44620 | F4: 44651 | G4: 44681 | H4: 44712 | I4: 44742 | J4: 44773 | K4: 44804 | L4: 44834 | M4: 44865 | N4: 44895 | O4: 44926 | P4: 44957 | Q4: 44985 | R4: 45016 | S4: 45046 | T4: 45077 | U4: 45107 | V4: 45138 | W4: 45169 | X4: 45199 | Y4: 45230 | Z4: 45260 | AA4: 45291 | AB4: 45322 | AC4: 45351 | AD4: 45382 | AE4: 45412 | AF4: 45443 | AG4: 45473 | AH4: 45504 | AI4: 45535 | AJ4: 45565 | AK4: 45596 | AL4: 45626 | AM4: 45657 | AN4: 45688 | AO4: 45716 | AP4: 45747 | AQ4: 45777 | AR4: 45808 | AS4: 45838 | AT4: 45869 | AU4: 45900 | AV4: 45930 | AW4: 45961 | AX4: 45991 | AY4: 46022 | AZ4: 46053 | BA4: 46081 | BB4: 46112 | BC4: 46142 | BD4: 46173 | BE4: 46203 | BF4: 46234 | BG4: 46265 | BH4: 46295 | BI4: 46326 | BJ4: 46356 | BK4: 46387 | BL4: 46418 | BM4: 46446 | BN4: 46477 | BO4: 46507 | BP4: 46538 | BQ4: 46568 | BR4: 46599 | BS4: 46630 | BT4: 46660 | BU4: 46691 | BV4: 46721 | BW4: 46752 | BX4: 46783 | BY4: 46812 | BZ4: 46843 | CA4: 46873 | CB4: 46904 | CC4: 46934 | CD4: 46965 | CE4: 46996 | CF4: 47026 | CG4: 47057 | CH4: 47087 | CI4: 47118 | CJ4: 47149 | CK4: 47177 | CL4: 47208 | CM4: 47238 | CN4: 47269 | CO4: 47299 | CP4: 47330 | CQ4: 47361 | CR4: 47391 | CS4: 47422 | CT4: 47452 | CU4: 47483 | CV4: 47514 | CW4: 47542 | CX4: 47573 | CY4: 47603 | CZ4: 47634 | DA4: 47664 | DB4: 47695 | DC4: 47726 | DD4: 47756 | DE4: 47787 | DF4: 47817 | DG4: 47848
B5: Income
B6: 40100 Nail Technician Services | V6: 0 | AB6: 5520 | AC6: 6528.4 | AD6: 7633.5 | AE6: 7610.5 | AF6: 7767.15 | AG6: 6976.15 | AH6: 5696 | AI6: 7172.75 | AJ6: 4463.25 | AK6: 7444.5 | AL6: 4717 | AM6: 6221.6 | AN6: 6476.75 | AO6: 6155.39 | AP6: 6650.25 | AQ6: 7459.5 | AR6: 7496.95 | AS6: 6520.45 | AT6: 7050.8 | AU6: 7217.85 | AV6: 5873.45 | AW6: =6611 | AX6: =AX32*AX30 | AY6: =AY32*AY30 | AZ6: =AZ32*AZ30 | BA6: =BA32*BA30 | BB6: =BB32*BB30 | BC6: =BC32*BC30 | BD6: =BD32*BD30 | BE6: =BE32*BE30 | ... DG6: =DG32*DG30
B7: 40800 Tips | AB7: 208.5 | AC7: 282.85 | AD7: 291.5 | AE7: 286.5 | AF7: 310.85 | AG7: 357.85 | AH7: 349.5 | AI7: 382.25 | AJ7: 357 | AK7: 387.5 | AL7: 221.75 | AM7: 260.4 | AN7: 274.3 | AO7: 345.75 | AP7: 458.25 | AQ7: 402.25 | AR7: 410.67 | AS7: 382 | AT7: 382.75 | AU7: 435.5 | AV7: 387 | AW7: =387.25 | AX7: =+AX6*AX10 | AY7: =+AY6*AY10 | AZ7: =+AZ6*AZ10 | BA7: =+BA6*BA10 | BB7: =+BB6*BB10 | BC7: =+BC6*BC10 | BD7: =+BD6*BD10 | BE7: =+BE6*BE10 | ... DG7: =+DG6*DG10
B8: 40900 Refunds/Discounts | AC8: -65 | AD8: -285.75 | AE8: -80 | AF8: -30 | AG8: -180 | AH8: -30 | AI8: -260 | AJ8: -282.25 | AK8: -135 | AL8: 0 | AM8: -330 | AN8: -30 | AO8: 0 | AP8: 0 | AQ8: 0 | AR8: -30 | AS8: -15 | AT8: -15 | AU8: 0 | AV8: -90 | AX8: =+AX6*AX11 | AY8: =+AY6*AY11 | AZ8: =+AZ6*AZ11 | BA8: =+BA6*BA11 | BB8: =+BB6*BB11 | BC8: =+BC6*BC11 | BD8: =+BD6*BD11 | BE8: =+BE6*BE11 | ... DG8: =+DG6*DG11
B9: Total 40000 Service Income | C9: Revenue | D9: =+(D6) | E9: =+(E6) | F9: 0 | G9: 0 | H9: 0 | I9: 0 | J9: 0 | K9: =SUM(K6:K6) | L9: =SUM(L6:L6) | M9: =SUM(M6:M6) | N9: =SUM(N6:N6) | O9: =SUM(O6:O6) | P9: =SUM(P6:P6) | Q9: =SUM(Q6:Q6) | R9: =SUM(R6:R6) | ... AA9: =SUM(AA6:AA6) | AB9: =SUM(AB6:AB8) | AC9: =SUM(AC6:AC8) | AD9: =SUM(AD6:AD8) | AE9: =SUM(AE6:AE8) | AF9: =SUM(AF6:AF8) | AG9: =SUM(AG6:AG8) | AH9: =SUM(AH6:AH8) | AI9: =SUM(AI6:AI8) | ... DG9: =SUM(DG6:DG8)
C10: Tips as a % of Revenue | AB10: =+AB7/AB9 | AC10: =+AC7/AC9 | AD10: =+AD7/AD9 | AE10: =+AE7/AE9 | AF10: =+AF7/AF9 | AG10: =+AG7/AG9 | AH10: =+AH7/AH9 | AI10: =+AI7/AI9 | ... AW10: =+AW7/AW9 | AX10: =+AVERAGE(AR10:AW10) | AY10: =+AX10 | AZ10: =+AY10 | BA10: =+AZ10 | BB10: =+BA10 | BC10: =+BB10 | BD10: =+BC10 | BE10: =+BD10 | BF10: =+BE10 | ... DG10: =+DF10
C11: Refunds as a % of Revenue | AB11: =+AB8/AB9 | AC11: =+AC8/AC9 | AD11: =+AD8/AD9 | AE11: =+AE8/AE9 | AF11: =+AF8/AF9 | AG11: =+AG8/AG9 | AH11: =+AH8/AH9 | AI11: =+AI8/AI9 | ... AW11: =+AW8/AW9 | AX11: =+AVERAGE(AR11:AW11) | AY11: =+AX11 | AZ11: =+AY11 | BA11: =+AZ11 | BB11: =+BA11 | BC11: =+BB11 | BD11: =+BC11 | BE11: =+BD11 | BF11: =+BE11 | ... DG11: =+DF11
B12: 70000 Miscellaneous | D12: =0 | E12: =0 | F12: =0 | G12: =0 | H12: =0 | I12: =0 | J12: =0 | K12: 0 | L12: 0 | N12: 0 | O12: 0 | AX12: =AW12 | AY12: =AX12 | AZ12: =AY12 | BA12: =AZ12 | BB12: =BA12 | BC12: =BB12 | BD12: =BC12 | BE12: =BD12 | ... DG12: =DF12
B13: Total Income | D13: =(D9)+(D12) | E13: =(E9)+(E12) | F13: =(F9)+(F12) | G13: =(G9)+(G12) | H13: =(H9)+(H12) | I13: =(I9)+(I12) | J13: =(J9)+(J12) | K13: =K12+K9 | L13: =L12+L9 | M13: =M12+M9 | N13: =N12+N9 | O13: =O12+O9 | P13: =P12+P9 | Q13: =Q12+Q9 | R13: =R12+R9 | ... DG13: =DG12+DG9
C15: # of Successful Appointments | E15: 12 | F15: 8 | G15: 7 | H15: 10 | I15: 13 | J15: 11 | K15: 5 | L15: 9 | M15: 17 | N15: 11 | O15: 7 | P15: 12 | Q15: 10 | R15: 10 | S15: 7 | T15: 9 | U15: 12 | V15: =99-24 | W15: 177 | X15: 191 | Y15: 190 | Z15: 188 | AA15: 207 | AB15: 67 | AC15: 74 | AD15: 77 | AE15: 78 | AF15: 82 | AG15: 75 | AH15: 66 | AI15: 74 | AJ15: 48 | AK15: 81 | AL15: 50 | AM15: 61 | AN15: 66 | AO15: 69 | AP15: 68 | AQ15: 82 | AR15: 83 | AS15: 72 | AT15: 76 | AU15: 73 | AV15: 62 | AW15: 72 | AX15: =+AX16*AX26 | AY15: =+AY16*AY26 | AZ15: =+AZ16*AZ26 | BA15: =+BA16*BA26 | BB15: =+BB16*BB26 | BC15: =+BC16*BC26 | BD15: =+BD16*BD26 | BE15: =+BE16*BE26 | ... DG15: =+DG16*DG26
C16: # of Active Clients | W16: 123 | X16: 123 | Y16: 129 | Z16: 127 | AA16: 126 | AB16: 55 | AC16: 69 | AD16: 68 | AE16: 66 | AF16: 69 | AG16: 65 | AH16: 54 | AI16: 65 | AJ16: 42 | AK16: 66 | AL16: 46 | AM16: 54 | AN16: 59 | AO16: 59 | AP16: 63 | AQ16: 69 | AR16: 78 | AS16: 62 | AT16: 67 | AU16: 60 | AV16: 54 | AW16: 58 | AX16: =+AX22*AX25 | AY16: =+AY22*AY25 | AZ16: =+AZ22*AZ25 | BA16: =+BA22*BA25 | BB16: =+BB22*BB25 | BC16: =+BC22*BC25 | BD16: =+BD22*BD25 | BE16: =+BE22*BE25 | ... DG16: =+DG22*DG25
C17: # of Recurring Client Base | X17: 73 | Y17: 71 | Z17: 72 | AA17: 75 | AB17: 30 | AC17: 34 | AD17: 27 | AE17: 19 | AF17: 30 | AG17: 30 | AH17: 29 | AI17: 34 | AJ17: 37 | AK17: 29 | AL17: 28 | AM17: 25 | AN17: 35 | AO17: 32 | AP17: 31 | AQ17: 30 | AR17: 38 | AS17: 37 | AT17: 34 | AU17: 32 | AV17: 36 | AW17: 33 | AX17: =+AW17*(1+AX24) | AY17: =+AX17*(1+AY24) | AZ17: =+AY17*(1+AZ24) | BA17: =+AZ17*(1+BA24) | BB17: =+BA17*(1+BB24) | BC17: =+BB17*(1+BC24) | BD17: =+BC17*(1+BD24) | BE17: =+BD17*(1+BE24) | ... DG17: =+DF17*(1+DG24)
C18: Net New Clients | E18: =SUM(E19:E20) | F18: =SUM(F19:F20) | G18: =SUM(G19:G20) | H18: =SUM(H19:H20) | I18: =SUM(I19:I20) | J18: =SUM(J19:J20) | K18: =SUM(K19:K20) | L18: =SUM(L19:L20) | ... DG18: =SUM(DG19:DG20)
C19: Additions | F19: =+IF(F15>E15,F15-E15, 0) | G19: =+IF(G15>F15,G15-F15, 0) | H19: =+IF(H15>G15,H15-G15, 0) | I19: =+IF(I15>H15,I15-H15, 0) | J19: =+IF(J15>I15,J15-I15, 0) | K19: =+IF(K15>J15,K15-J15, 0) | L19: =+IF(L15>K15,L15-K15, 0) | M19: =+IF(M15>L15,M15-L15, 0) | ... V19: =+IF(V15>U15,V15-U15, 0) | W19: 62 | X19: 62 | Y19: 56 | Z19: 29 | AA19: 19 | AB19: 0 | AC19: 37 | AD19: 42 | AE19: 50 | AF19: 40 | AG19: 35 | AH19: 25 | AI19: 31 | AJ19: 8 | AK19: 37 | AL19: 18 | AM19: 29 | AN19: 24 | AO19: 27 | AP19: 32 | AQ19: 39 | AR19: 40 | AS19: 25 | AT19: 33 | AU19: 28 | AV19: 18 | AW19: 24 | AX19: =IF(AX2="Trough",INDEX($I$50:$I$52,MATCH(AX2,$E$50:$E$52,0)),IF(AX2="Shoulder",INDEX($I$50:$I$52,MATCH(AX2,$E$50:$E$52,0)),INDEX($I$50:$I$52,MATCH(AX2,$E$50:$E$52,0)))) | AY19: =IF(AY2="Trough",INDEX($I$50:$I$52,MATCH(AY2,$E$50:$E$52,0)),IF(AY2="Shoulder",INDEX($I$50:$I$52,MATCH(AY2,$E$50:$E$52,0)),INDEX($I$50:$I$52,MATCH(AY2,$E$50:$E$52,0)))) | AZ19: =IF(AZ2="Trough",INDEX($J$50:$J$52,MATCH(AZ2,$E$50:$E$52,0)),IF(AZ2="Shoulder",INDEX($J$50:$J$52,MATCH(AZ2,$E$50:$E$52,0)),INDEX($J$50:$J$52,MATCH(AZ2,$E$50:$E$52,0)))) | BA19: =IF(BA2="Trough",INDEX($J$50:$J$52,MATCH(BA2,$E$50:$E$52,0)),IF(BA2="Shoulder",INDEX($J$50:$J$52,MATCH(BA2,$E$50:$E$52,0)),INDEX($J$50:$J$52,MATCH(BA2,$E$50:$E$52,0)))) | BB19: =IF(BB2="Trough",INDEX($J$50:$J$52,MATCH(BB2,$E$50:$E$52,0)),IF(BB2="Shoulder",INDEX($J$50:$J$52,MATCH(BB2,$E$50:$E$52,0)),INDEX($J$50:$J$52,MATCH(BB2,$E$50:$E$52,0)))) | BC19: =IF(BC2="Trough",INDEX($J$50:$J$52,MATCH(BC2,$E$50:$E$52,0)),IF(BC2="Shoulder",INDEX($J$50:$J$52,MATCH(BC2,$E$50:$E$52,0)),INDEX($J$50:$J$52,MATCH(BC2,$E$50:$E$52,0)))) | BD19: =IF(BD2="Trough",INDEX($J$50:$J$52,MATCH(BD2,$E$50:$E$52,0)),IF(BD2="Shoulder",INDEX($J$50:$J$52,MATCH(BD2,$E$50:$E$52,0)),INDEX($J$50:$J$52,MATCH(BD2,$E$50:$E$52,0)))) | BE19: =IF(BE2="Trough",INDEX($J$50:$J$52,MATCH(BE2,$E$50:$E$52,0)),IF(BE2="Shoulder",INDEX($J$50:$J$52,MATCH(BE2,$E$50:$E$52,0)),INDEX($J$50:$J$52,MATCH(BE2,$E$50:$E$52,0)))) | BF19: =IF(BF2="Trough",INDEX($J$50:$J$52,MATCH(BF2,$E$50:$E$52,0)),IF(BF2="Shoulder",INDEX($J$50:$J$52,MATCH(BF2,$E$50:$E$52,0)),INDEX($J$50:$J$52,MATCH(BF2,$E$50:$E$52,0)))) | BG19: =IF(BG2="Trough",INDEX($J$50:$J$52,MATCH(BG2,$E$50:$E$52,0)),IF(BG2="Shoulder",INDEX($J$50:$J$52,MATCH(BG2,$E$50:$E$52,0)),INDEX($J$50:$J$52,MATCH(BG2,$E$50:$E$52,0)))) | ... BK19: =IF(BK2="Trough",INDEX($J$50:$J$52,MATCH(BK2,$E$50:$E$52,0)),IF(BK2="Shoulder",INDEX($J$50:$J$52,MATCH(BK2,$E$50:$E$52,0)),INDEX($J$50:$J$52,MATCH(BK2,$E$50:$E$52,0)))) | BL19: =+IF(BL2="Trough",INDEX($K$50:$K$52,MATCH(BL2,$E$50:$E$52,0)),IF(BL2="Shoulder",INDEX($K$50:$K$52,MATCH(BL2,$E$50:$E$52,0)),INDEX($K$50:$K$52,MATCH(BL2,$E$50:$E$52,0)))) | BM19: =+IF(BM2="Trough",INDEX($K$50:$K$52,MATCH(BM2,$E$50:$E$52,0)),IF(BM2="Shoulder",INDEX($K$50:$K$52,MATCH(BM2,$E$50:$E$52,0)),INDEX($K$50:$K$52,MATCH(BM2,$E$50:$E$52,0)))) | BN19: =+IF(BN2="Trough",INDEX($K$50:$K$52,MATCH(BN2,$E$50:$E$52,0)),IF(BN2="Shoulder",INDEX($K$50:$K$52,MATCH(BN2,$E$50:$E$52,0)),INDEX($K$50:$K$52,MATCH(BN2,$E$50:$E$52,0)))) | BO19: =+IF(BO2="Trough",INDEX($K$50:$K$52,MATCH(BO2,$E$50:$E$52,0)),IF(BO2="Shoulder",INDEX($K$50:$K$52,MATCH(BO2,$E$50:$E$52,0)),INDEX($K$50:$K$52,MATCH(BO2,$E$50:$E$52,0)))) | BP19: =+IF(BP2="Trough",INDEX($K$50:$K$52,MATCH(BP2,$E$50:$E$52,0)),IF(BP2="Shoulder",INDEX($K$50:$K$52,MATCH(BP2,$E$50:$E$52,0)),INDEX($K$50:$K$52,MATCH(BP2,$E$50:$E$52,0)))) | BQ19: =+IF(BQ2="Trough",INDEX($K$50:$K$52,MATCH(BQ2,$E$50:$E$52,0)),IF(BQ2="Shoulder",INDEX($K$50:$K$52,MATCH(BQ2,$E$50:$E$52,0)),INDEX($K$50:$K$52,MATCH(BQ2,$E$50:$E$52,0)))) | BR19: =+IF(BR2="Trough",INDEX($K$50:$K$52,MATCH(BR2,$E$50:$E$52,0)),IF(BR2="Shoulder",INDEX($K$50:$K$52,MATCH(BR2,$E$50:$E$52,0)),INDEX($K$50:$K$52,MATCH(BR2,$E$50:$E$52,0)))) | BS19: =+IF(BS2="Trough",INDEX($K$50:$K$52,MATCH(BS2,$E$50:$E$52,0)),IF(BS2="Shoulder",INDEX($K$50:$K$52,MATCH(BS2,$E$50:$E$52,0)),INDEX($K$50:$K$52,MATCH(BS2,$E$50:$E$52,0)))) | ... BW19: =+IF(BW2="Trough",INDEX($K$50:$K$52,MATCH(BW2,$E$50:$E$52,0)),IF(BW2="Shoulder",INDEX($K$50:$K$52,MATCH(BW2,$E$50:$E$52,0)),INDEX($K$50:$K$52,MATCH(BW2,$E$50:$E$52,0)))) | BX19: =IF(BX2="Trough",INDEX($L$50:$L$52,MATCH(BX2,$E$50:$E$52,0)),IF(BX2="Shoulder",INDEX($L$50:$L$52,MATCH(BX2,$E$50:$E$52,0)),INDEX($L$50:$L$52,MATCH(BX2,$E$50:$E$52,0)))) | BY19: =IF(BY2="Trough",INDEX($L$50:$L$52,MATCH(BY2,$E$50:$E$52,0)),IF(BY2="Shoulder",INDEX($L$50:$L$52,MATCH(BY2,$E$50:$E$52,0)),INDEX($L$50:$L$52,MATCH(BY2,$E$50:$E$52,0)))) | BZ19: =IF(BZ2="Trough",INDEX($L$50:$L$52,MATCH(BZ2,$E$50:$E$52,0)),IF(BZ2="Shoulder",INDEX($L$50:$L$52,MATCH(BZ2,$E$50:$E$52,0)),INDEX($L$50:$L$52,MATCH(BZ2,$E$50:$E$52,0)))) | CA19: =IF(CA2="Trough",INDEX($L$50:$L$52,MATCH(CA2,$E$50:$E$52,0)),IF(CA2="Shoulder",INDEX($L$50:$L$52,MATCH(CA2,$E$50:$E$52,0)),INDEX($L$50:$L$52,MATCH(CA2,$E$50:$E$52,0)))) | CB19: =IF(CB2="Trough",INDEX($L$50:$L$52,MATCH(CB2,$E$50:$E$52,0)),IF(CB2="Shoulder",INDEX($L$50:$L$52,MATCH(CB2,$E$50:$E$52,0)),INDEX($L$50:$L$52,MATCH(CB2,$E$50:$E$52,0)))) | CC19: =IF(CC2="Trough",INDEX($L$50:$L$52,MATCH(CC2,$E$50:$E$52,0)),IF(CC2="Shoulder",INDEX($L$50:$L$52,MATCH(CC2,$E$50:$E$52,0)),INDEX($L$50:$L$52,MATCH(CC2,$E$50:$E$52,0)))) | CD19: =IF(CD2="Trough",INDEX($L$50:$L$52,MATCH(CD2,$E$50:$E$52,0)),IF(CD2="Shoulder",INDEX($L$50:$L$52,MATCH(CD2,$E$50:$E$52,0)),INDEX($L$50:$L$52,MATCH(CD2,$E$50:$E$52,0)))) | CE19: =IF(CE2="Trough",INDEX($L$50:$L$52,MATCH(CE2,$E$50:$E$52,0)),IF(CE2="Shoulder",INDEX($L$50:$L$52,MATCH(CE2,$E$50:$E$52,0)),INDEX($L$50:$L$52,MATCH(CE2,$E$50:$E$52,0)))) | ... CI19: =IF(CI2="Trough",INDEX($L$50:$L$52,MATCH(CI2,$E$50:$E$52,0)),IF(CI2="Shoulder",INDEX($L$50:$L$52,MATCH(CI2,$E$50:$E$52,0)),INDEX($L$50:$L$52,MATCH(CI2,$E$50:$E$52,0)))) | CJ19: =IF(CJ2="Trough",INDEX($M$50:$M$52,MATCH(CJ2,$E$50:$E$52,0)),IF(CJ2="Shoulder",INDEX($M$50:$M$52,MATCH(CJ2,$E$50:$E$52,0)),INDEX($M$50:$M$52,MATCH(CJ2,$E$50:$E$52,0)))) | CK19: =IF(CK2="Trough",INDEX($M$50:$M$52,MATCH(CK2,$E$50:$E$52,0)),IF(CK2="Shoulder",INDEX($M$50:$M$52,MATCH(CK2,$E$50:$E$52,0)),INDEX($M$50:$M$52,MATCH(CK2,$E$50:$E$52,0)))) | CL19: =IF(CL2="Trough",INDEX($M$50:$M$52,MATCH(CL2,$E$50:$E$52,0)),IF(CL2="Shoulder",INDEX($M$50:$M$52,MATCH(CL2,$E$50:$E$52,0)),INDEX($M$50:$M$52,MATCH(CL2,$E$50:$E$52,0)))) | CM19: =IF(CM2="Trough",INDEX($M$50:$M$52,MATCH(CM2,$E$50:$E$52,0)),IF(CM2="Shoulder",INDEX($M$50:$M$52,MATCH(CM2,$E$50:$E$52,0)),INDEX($M$50:$M$52,MATCH(CM2,$E$50:$E$52,0)))) | CN19: =IF(CN2="Trough",INDEX($M$50:$M$52,MATCH(CN2,$E$50:$E$52,0)),IF(CN2="Shoulder",INDEX($M$50:$M$52,MATCH(CN2,$E$50:$E$52,0)),INDEX($M$50:$M$52,MATCH(CN2,$E$50:$E$52,0)))) | CO19: =IF(CO2="Trough",INDEX($M$50:$M$52,MATCH(CO2,$E$50:$E$52,0)),IF(CO2="Shoulder",INDEX($M$50:$M$52,MATCH(CO2,$E$50:$E$52,0)),INDEX($M$50:$M$52,MATCH(CO2,$E$50:$E$52,0)))) | CP19: =IF(CP2="Trough",INDEX($M$50:$M$52,MATCH(CP2,$E$50:$E$52,0)),IF(CP2="Shoulder",INDEX($M$50:$M$52,MATCH(CP2,$E$50:$E$52,0)),INDEX($M$50:$M$52,MATCH(CP2,$E$50:$E$52,0)))) | CQ19: =IF(CQ2="Trough",INDEX($M$50:$M$52,MATCH(CQ2,$E$50:$E$52,0)),IF(CQ2="Shoulder",INDEX($M$50:$M$52,MATCH(CQ2,$E$50:$E$52,0)),INDEX($M$50:$M$52,MATCH(CQ2,$E$50:$E$52,0)))) | ... CU19: =IF(CU2="Trough",INDEX($M$50:$M$52,MATCH(CU2,$E$50:$E$52,0)),IF(CU2="Shoulder",INDEX($M$50:$M$52,MATCH(CU2,$E$50:$E$52,0)),INDEX($M$50:$M$52,MATCH(CU2,$E$50:$E$52,0)))) | CV19: =IF(CV2="Trough",INDEX($N$50:$N$52,MATCH(CV2,$E$50:$E$52,0)),IF(CV2="Shoulder",INDEX($N$50:$N$52,MATCH(CV2,$E$50:$E$52,0)),INDEX($N$50:$N$52,MATCH(CV2,$E$50:$E$52,0)))) | CW19: =IF(CW2="Trough",INDEX($N$50:$N$52,MATCH(CW2,$E$50:$E$52,0)),IF(CW2="Shoulder",INDEX($N$50:$N$52,MATCH(CW2,$E$50:$E$52,0)),INDEX($N$50:$N$52,MATCH(CW2,$E$50:$E$52,0)))) | CX19: =IF(CX2="Trough",INDEX($N$50:$N$52,MATCH(CX2,$E$50:$E$52,0)),IF(CX2="Shoulder",INDEX($N$50:$N$52,MATCH(CX2,$E$50:$E$52,0)),INDEX($N$50:$N$52,MATCH(CX2,$E$50:$E$52,0)))) | CY19: =IF(CY2="Trough",INDEX($N$50:$N$52,MATCH(CY2,$E$50:$E$52,0)),IF(CY2="Shoulder",INDEX($N$50:$N$52,MATCH(CY2,$E$50:$E$52,0)),INDEX($N$50:$N$52,MATCH(CY2,$E$50:$E$52,0)))) | CZ19: =IF(CZ2="Trough",INDEX($N$50:$N$52,MATCH(CZ2,$E$50:$E$52,0)),IF(CZ2="Shoulder",INDEX($N$50:$N$52,MATCH(CZ2,$E$50:$E$52,0)),INDEX($N$50:$N$52,MATCH(CZ2,$E$50:$E$52,0)))) | DA19: =IF(DA2="Trough",INDEX($N$50:$N$52,MATCH(DA2,$E$50:$E$52,0)),IF(DA2="Shoulder",INDEX($N$50:$N$52,MATCH(DA2,$E$50:$E$52,0)),INDEX($N$50:$N$52,MATCH(DA2,$E$50:$E$52,0)))) | DB19: =IF(DB2="Trough",INDEX($N$50:$N$52,MATCH(DB2,$E$50:$E$52,0)),IF(DB2="Shoulder",INDEX($N$50:$N$52,MATCH(DB2,$E$50:$E$52,0)),INDEX($N$50:$N$52,MATCH(DB2,$E$50:$E$52,0)))) | DC19: =IF(DC2="Trough",INDEX($N$50:$N$52,MATCH(DC2,$E$50:$E$52,0)),IF(DC2="Shoulder",INDEX($N$50:$N$52,MATCH(DC2,$E$50:$E$52,0)),INDEX($N$50:$N$52,MATCH(DC2,$E$50:$E$52,0)))) | ... DG19: =IF(DG2="Trough",INDEX($N$50:$N$52,MATCH(DG2,$E$50:$E$52,0)),IF(DG2="Shoulder",INDEX($N$50:$N$52,MATCH(DG2,$E$50:$E$52,0)),INDEX($N$50:$N$52,MATCH(DG2,$E$50:$E$52,0))))
C20: Subtrctions | F20: =+IF(F15<E15,F15-E15, 0) | G20: =+IF(G15<F15,G15-F15, 0) | H20: =+IF(H15<G15,H15-G15, 0) | I20: =+IF(I15<H15,I15-H15, 0) | J20: =+IF(J15<I15,J15-I15, 0) | K20: =+IF(K15<J15,K15-J15, 0) | L20: =+IF(L15<K15,L15-K15, 0) | M20: =+IF(M15<L15,M15-L15, 0) | ... V20: =+IF(V15<U15,V15-U15, 0) | W20: -38 | X20: -38 | Y20: -53 | Z20: -20 | AA20: -17 | AB20: 0 | AC20: -23 | AD20: -43 | AE20: -52 | AF20: -37 | AG20: -39 | AH20: -36 | AI20: -20 | AJ20: -31 | AK20: -13 | AL20: -38 | AM20: -21 | AN20: -19 | AO20: -27 | AP20: -28 | AQ20: -33 | AR20: -31 | AS20: -40 | AT20: -28 | AU20: -35 | AV20: -24 | AW20: -21 | AX20: =ROUNDUP(AW16*AX36, 0) | AY20: =ROUNDUP(AX16*AY36, 0) | AZ20: =ROUNDUP(AY16*AZ36, 0) | BA20: =ROUNDUP(AZ16*BA36, 0) | BB20: =ROUNDUP(BA16*BB36, 0) | BC20: =ROUNDUP(BB16*BC36, 0) | BD20: =ROUNDUP(BC16*BD36, 0) | BE20: =ROUNDUP(BD16*BE36, 0) | ... DG20: =ROUNDUP(DF16*DG36, 0)
C21: # of Anticipated Appointments | P21: 21 | Q21: 22 | R21: 20 | S21: 16 | T21: 25 | U21: 22 | V21: 100 | W21: 218 | X21: 243 | Y21: 240 | Z21: 237 | AA21: 224 | AB21: 71 | AC21: 82 | AD21: 85 | AE21: 87 | AF21: 89 | AG21: 80 | AH21: 79 | AI21: 88 | AJ21: 52 | AK21: 91 | AL21: 55 | AM21: 66 | AN21: 70 | AO21: 74 | AP21: 72 | AQ21: 90 | AR21: 90 | AS21: 77 | AT21: 88 | AU21: 84 | AV21: 68 | AW21: 76 | AX21: =+(AX23*AW15)+AX15 | AY21: =+(AY23*AX15)+AY15 | AZ21: =+(AZ23*AY15)+AZ15 | BA21: =+(BA23*AZ15)+BA15 | BB21: =+(BB23*BA15)+BB15 | BC21: =+(BC23*BB15)+BC15 | BD21: =+(BD23*BC15)+BD15 | BE21: =+(BE23*BD15)+BE15 | ... DG21: =+(DG23*DF15)+DG15
C22: # of Anticipated Clients | W22: 135 | X22: 139 | Y22: 144 | Z22: 143 | AA22: 135 | AB22: 59 | AC22: 74 | AD22: 74 | AE22: 73 | AF22: 72 | AG22: 68 | AH22: 65 | AI22: 73 | AJ22: 43 | AK22: 70 | AL22: 47 | AM22: 57 | AN22: 63 | AO22: 60 | AP22: 65 | AQ22: 70 | AR22: 80 | AS22: 64 | AT22: 74 | AU22: 66 | AV22: 56 | AW22: 61 | AX22: =+AW22+AX18 | AY22: =+AX22+AY18 | AZ22: =+AY22+AZ18 | BA22: =+AZ22+BA18 | BB22: =+BA22+BB18 | BC22: =+BB22+BC18 | BD22: =+BC22+BD18 | BE22: =+BD22+BE18 | ... DG22: =+DF22+DG18
C23: Reschedule/Cancellation Rate | V23: =+(V21-V15)/V21 | W23: =+(W21-W15)/W21 | X23: =+(X21-X15)/X21 | Y23: =+(Y21-Y15)/Y21 | Z23: =+(Z21-Z15)/Z21 | AA23: =+(AA21-AA15)/AA21 | AB23: =+(AB21-AB15)/AB21 | AC23: =+(AC21-AC15)/AC21 | ... AW23: =+(AW21-AW15)/AW21 | AX23: =+AVERAGE(AR23:AW23) | AY23: =+AX23 | AZ23: 0.08 | BA23: =+AZ23 | BB23: =+BA23 | BC23: =+BB23 | BD23: =+BC23 | BE23: =+BD23 | BF23: =+BE23 | BG23: =+BF23 | BH23: =+BG23 | ... BK23: =+BJ23 | BL23: 0.05 | BM23: =+BL23 | BN23: =+BM23 | BO23: =+BN23 | BP23: =+BO23 | BQ23: =+BP23 | BR23: =+BQ23 | BS23: =+BR23 | BT23: =+BS23 | ... BW23: =+BV23 | BX23: 0.03 | BY23: =+BX23 | BZ23: =+BY23 | CA23: =+BZ23 | CB23: =+CA23 | CC23: =+CB23 | CD23: =+CC23 | CE23: =+CD23 | CF23: =+CE23 | ... DG23: =+DF23
C24: Client Base Growth Rate | X24: =+(X16/W16)-1 | Y24: =+(Y16/X16)-1 | Z24: =+(Z16/Y16)-1 | AA24: =+(AA16/Z16)-1 | AB24: =+(AB16/AA16)-1 | AC24: =+(AC16/AB16)-1 | AD24: =+(AD16/AC16)-1 | AE24: =+(AE16/AD16)-1 | ... DG24: =+(DG16/DF16)-1
C25: Client Hit Rate | W25: =+(W16/W22) | X25: =+(X16/X22) | Y25: =+(Y16/Y22) | Z25: =+(Z16/Z22) | AA25: =+(AA16/AA22) | AB25: =+(AB16/AB22) | AC25: =+(AC16/AC22) | AD25: =+(AD16/AD22) | ... AW25: =+(AW16/AW22) | AX25: =+AVERAGE(AR25:AW25) | AY25: =+AX25 | AZ25: =+AY25 | BA25: =+AZ25 | BB25: =+BA25 | BC25: =+BB25 | BD25: =+BC25 | BE25: =+BD25 | BF25: =+BE25 | ... DG25: =+DF25
C26: Appt Multiplier | W26: =+W15/W16 | X26: =+X15/X16 | Y26: =+Y15/Y16 | Z26: =+Z15/Z16 | AA26: =+AA15/AA16 | AB26: =+AB15/AB16 | AC26: =+AC15/AC16 | AD26: =+AD15/AD16 | ... AW26: =+AW15/AW16 | AX26: =+AL26 | AY26: =+AM26 | AZ26: =+AN26 | BA26: =+AO26 | BB26: =+AP26 | BC26: =+AQ26 | BD26: =+AR26 | BE26: =+AS26 | ... DG26: =+CU26
B27: Coverage
B28: 90 | C28: Billing Days | E28: =NETWORKDAYS(D4+1,E4,Holidays!$B$3:$B$62) | F28: =NETWORKDAYS(E4+1,F4,Holidays!$B$3:$B$62) | G28: =NETWORKDAYS(F4+1,G4,Holidays!$B$3:$B$62) | H28: =NETWORKDAYS(G4+1,H4,Holidays!$B$3:$B$62) | I28: =NETWORKDAYS(H4+1,I4,Holidays!$B$3:$B$62) | J28: =NETWORKDAYS(I4+1,J4,Holidays!$B$3:$B$62) | K28: =NETWORKDAYS(J4+1,K4,Holidays!$B$3:$B$62) | L28: =NETWORKDAYS(K4+1,L4,Holidays!$B$3:$B$62) | ... DG28: =NETWORKDAYS(DF4+1,DG4,Holidays!$B$3:$B$62)
C29: Hours / Day / Client | E29: =+E30/E28/E15 | F29: =+F30/F28/F15 | G29: =+G30/G28/G15 | H29: =+H30/H28/H15 | I29: =+I30/I28/I15 | J29: =+J30/J28/J15 | K29: =+K30/K28/K15 | L29: =+L30/L28/L15 | ... AW29: =+AW30/AW28/AW15 | AX29: =+AL29 | AY29: =+AM29 | AZ29: =+AN29 | BA29: =+AO29 | BB29: =+AP29 | BC29: =+AQ29 | BD29: =+AR29 | BE29: =+AS29 | ... DG29: =+CU29
C30: Total Billable Hours | E30: 1 | F30: 1 | G30: 1 | H30: 1 | I30: 1 | J30: 1 | K30: 7.5 | L30: =20.5 | M30: 57.25 | N30: 31 | O30: 15 | P30: 26.33 | Q30: 21.25 | R30: 19.75 | S30: 18.25 | T30: 41.25 | U30: 41.5 | V30: 32.25 | W30: 115.25 | X30: 123.25 | Y30: 120.5 | Z30: 121.25 | AA30: 129.5 | AB30: 134.5 | AC30: 155 | AD30: 183.75 | AE30: 176.75 | AF30: 180 | AG30: 157.5 | AH30: 143 | AI30: 165.5 | AJ30: 92.75 | AK30: 177.5 | AL30: 113 | AM30: 135 | AN30: 138.5 | AO30: 143.75 | AP30: 155.5 | AQ30: 170.75 | AR30: 168.75 | AS30: 135 | AT30: 146 | AU30: 150.85 | AV30: 124 | AW30: 140 | AX30: =+AX15*AX28*AX29 | AY30: =+AY15*AY28*AY29 | AZ30: =+AZ15*AZ28*AZ29 | BA30: =+BA15*BA28*BA29 | BB30: =+BB15*BB28*BB29 | BC30: =+BC15*BC28*BC29 | BD30: =+BD15*BD28*BD29 | BE30: =+BE15*BE28*BE29 | ... DG30: =+DG15*DG28*DG29
C31: Nonbillable Hours | L31: 3.75 | M31: 14.75 | N31: 13.5 | O31: 14 | P31: 14 | Q31: 14 | R31: 5.5 | S31: 4.5 | T31: 5 | U31: 25.75 | V31: 11.75 | W31: 26.75 | X31: 33.75 | Y31: 32.5 | Z31: 31.5 | AA31: 10.75 | AB31: 7.75 | AC31: 16 | AD31: 19.75 | AE31: 23.75 | AF31: 21 | AG31: 14.5 | AH31: 31.75 | AI31: 33 | AJ31: 11.5 | AK31: 21.5 | AL31: 11.25 | AM31: 11.25 | AN31: 11 | AO31: 14.25 | AP31: 6.25 | AQ31: 15 | AR31: 12.5 | AS31: 8 | AT31: 26 | AU31: 20 | AV31: 11.25 | AW31: 6.25 | AX31: =+AX33*(AX21-AX15) | AY31: =+AY33*(AY21-AY15) | AZ31: =+AZ33*(AZ21-AZ15) | BA31: =+BA33*(BA21-BA15) | BB31: =+BB33*(BB21-BB15) | BC31: =+BC33*(BC21-BC15) | BD31: =+BD33*(BD21-BD15) | BE31: =+BE33*(BE21-BE15) | ... DG31: =+DG33*(DG21-DG15)
C32: Realized / Effective Bill Rate | E32: =+E13/(E30+E31) | F32: =+F13/(F30+F31) | G32: =+G13/(G30+G31) | H32: =+H13/(H30+H31) | I32: =+I13/(I30+I31) | J32: =+J13/(J30+J31) | K32: =+K13/(K30+K31) | L32: =+L13/(L30+L31) | ... AW32: =+AW13/(AW30+AW31) | AX32: =+AVERAGE(AR32:AW32)+3 | AY32: =+AX32 | AZ32: =+IF(AZ1<>AY1, AY32*1.05, AY32) | BA32: =+IF(BA1<>AZ1, AZ32*1.05, AZ32) | BB32: =+IF(BB1<>BA1, BA32*1.05, BA32) | BC32: =+IF(BC1<>BB1, BB32*1.05, BB32) | BD32: =+IF(BD1<>BC1, BC32*1.05, BC32) | BE32: =+IF(BE1<>BD1, BD32*1.05, BD32) | BF32: =+IF(BF1<>BE1, BE32*1.05, BE32) | BG32: =+IF(BG1<>BF1, BF32*1.05, BF32) | ... DG32: =+IF(DG1<>DF1, DF32*1.05, DF32)
C33: Nonbillable Hours/Lost Appt | W33: =+(W31/(W21-W15)) | X33: =+(X31/(X21-X15)) | Y33: =+(Y31/(Y21-Y15)) | Z33: =+(Z31/(Z21-Z15)) | AA33: =+(AA31/(AA21-AA15)) | AB33: =(AB31/(AB21-AB15)) | AC33: =(AC31/(AC21-AC15)) | AD33: =(AD31/(AD21-AD15)) | AE33: =(AE31/(AE21-AE15)) | AF33: =(AF31/(AF21-AF15)) | AG33: =(AG31/(AG21-AG15)) | AH33: =(AH31/(AH21-AH15)) | AI33: =(AI31/(AI21-AI15)) | ... AW33: =(AW31/(AW21-AW15)) | AX33: =+AVERAGE(AR33:AW33) | AY33: =+AX33 | AZ33: =+AY33 | BA33: =+AZ33 | BB33: =+BA33 | BC33: =+BB33 | BD33: =+BC33 | BE33: =+BD33 | BF33: =+BE33 | ... DG33: =+DF33
C34: Productivity Utilization | V34: =+V30/(V30+V31) | W34: =+W30/(W30+W31) | X34: =+X30/(X30+X31) | Y34: =+Y30/(Y30+Y31) | Z34: =+Z30/(Z30+Z31) | AA34: =+AA30/(AA30+AA31) | AB34: =+AB30/(AB30+AB31) | AC34: =+AC30/(AC30+AC31) | ... DG34: =+DG30/(DG30+DG31)
C36: T6M Avg Monthly Attrition | L36: =+AVERAGE(F20:L20)/L15 | M36: =+AVERAGE(G20:M20)/M15 | N36: =+AVERAGE(H20:N20)/N15 | O36: =+AVERAGE(I20:O20)/O15 | P36: =+AVERAGE(J20:P20)/P15 | Q36: =+AVERAGE(K20:Q20)/Q15 | R36: =+AVERAGE(L20:R20)/R15 | S36: =+AVERAGE(M20:S20)/S15 | ... V36: =+AVERAGE(P20:V20)/V15 | W36: =+AVERAGE(Q20:W20)/W16 | X36: =+AVERAGE(Q20:W20)/AVERAGE(Q16:W16) | Y36: =+AVERAGE(R20:X20)/AVERAGE(R16:X16) | Z36: =+AVERAGE(S20:Y20)/AVERAGE(S16:Y16) | AA36: =+AVERAGE(T20:Z20)/AVERAGE(T16:Z16) | AB36: =+AVERAGE(U20:AA20)/AVERAGE(U16:AA16) | AC36: =+AVERAGE(V20:AB20)/AVERAGE(V16:AB16) | AD36: =+AVERAGE(W20:AC20)/AVERAGE(W16:AC16) | AE36: =+AVERAGE(X20:AD20)/AVERAGE(X16:AD16) | ... DG36: =+AVERAGE(CZ20:DF20)/AVERAGE(CZ16:DF16)
C37: Implied Tenure | L37: =1/-L36 | M37: =1/-M36 | N37: =1/-N36 | O37: =1/-O36 | P37: =1/-P36 | Q37: =1/-Q36 | R37: =1/-R36 | S37: =1/-S36 | ... DG37: =1/-DG36
C38: Average Revenue | L38: =+L13/L15 | M38: =+M13/M15 | N38: =+N13/N15 | O38: =+O13/O15 | P38: =+P13/P15 | Q38: =+Q13/Q15 | R38: =+R13/R15 | S38: =+S13/S15 | ... V38: =+V13/V15 | W38: =+W13/W16 | X38: =+X13/X16 | Y38: =+Y13/Y16 | Z38: =+Z13/Z16 | AA38: =+AA13/AA16 | AB38: =+(AB13/AB16)*AB26 | AC38: =+(AC13/AC16)*AC26 | AD38: =+(AD13/AD16)*AD26 | AE38: =+(AE13/AE16)*AE26 | AF38: =+(AF13/AF16)*AF26 | AG38: =+(AG13/AG16)*AG26 | AH38: =+(AH13/AH16)*AH26 | AI38: =+(AI13/AI16)*AI26 | ... DG38: =+(DG13/DG16)*DG26
C39: Lifetime Revenue | L39: =+L38*L37 | M39: =+M38*M37 | N39: =+N38*N37 | O39: =+O38*O37 | P39: =+P38*P37 | Q39: =+Q38*Q37 | R39: =+R38*R37 | S39: =+S38*S37 | ... DG39: =+DG38*DG37
C40: GM% | L40: =+L92/L13 | M40: =+M92/M13 | N40: =+N92/N13 | O40: =+O92/O13 | P40: =+P92/P13 | Q40: 0 | R40: 0 | S40: 0 | T40: 0 | U40: 0 | V40: 0 | W40: =+W92/W13 | X40: =+X92/X13 | Y40: =+Y92/Y13 | Z40: =+Z92/Z13 | AA40: =+AA92/AA13 | AB40: =+AB65/AB13 | AC40: =+AC65/AC13 | AD40: =+AD65/AD13 | AE40: =+AE65/AE13 | AF40: =+AF65/AF13 | AG40: =+AG65/AG13 | AH40: =+AH65/AH13 | AI40: =+AI65/AI13 | ... DG40: =+DG65/DG13
C41: MRR | W41: =+(W38)*W17*W26 | X41: =+(X38)*X17*X26 | Y41: =+(Y38)*Y17*Y26 | Z41: =+(Z38)*Z17*Z26 | AA41: =+(AA38)*AA17*AA26 | AB41: =+(AB38)*AB17 | AC41: =+(AC38)*AC17 | AD41: =+(AD38)*AD17 | AE41: =+(AE38)*AE17 | AF41: =+(AF38)*AF17 | AG41: =+(AG38)*AG17 | AH41: =+(AH38)*AH17 | AI41: =+(AI38)*AI17 | ... DG41: =+(DG38)*DG17
C42: T6M LTV | L42: =+IFERROR(AVERAGE(L40*L39,K40*K39, J40*J39, I40*I39,H39*H40,G39*G40), 0) | M42: =+IFERROR(AVERAGE(M40*M39,L40*L39, K40*K39, J40*J39,I39*I40,H39*H40), 0) | N42: =+IFERROR(AVERAGE(N40*N39,M40*M39, L40*L39, K40*K39,J39*J40,I39*I40), 0) | O42: =+IFERROR(AVERAGE(O40*O39,N40*N39, M40*M39, L40*L39,K39*K40,J39*J40), 0) | P42: =+IFERROR(AVERAGE(P40*P39,O40*O39, N40*N39, M40*M39,L39*L40,K39*K40), 0) | Q42: =+IFERROR(AVERAGE(Q40*Q39,P40*P39, O40*O39, N40*N39,M39*M40,L39*L40), 0) | R42: =+IFERROR(AVERAGE(R40*R39,Q40*Q39, P40*P39, O40*O39,N39*N40,M39*M40), 0) | S42: =+IFERROR(AVERAGE(S40*S39,R40*R39, Q40*Q39, P40*P39,O39*O40,N39*N40), 0) | ... DG42: =+IFERROR(AVERAGE(DG40*DG39,DF40*DF39, DE40*DE39, DD40*DD39,DC39*DC40,DB39*DB40), 0)
C43: T6M CAC | L43: =+AVERAGE(J89:L89) | M43: =+AVERAGE(K89:M89) | N43: =+AVERAGE(L89:N89) | O43: =+AVERAGE(M89:O89) | P43: =+AVERAGE(N89:P89) | Q43: =+AVERAGE(O89:Q89) | R43: =+AVERAGE(P89:R89) | S43: =+AVERAGE(Q89:S89) | ... V43: =+AVERAGE(T89:V89) | X43: =+AVERAGE(V93:X93) | Y43: =+AVERAGE(W93:Y93) | Z43: =+AVERAGE(X93:Z93) | AA43: =+AVERAGE(Y93:AA93) | AB43: =+AVERAGE(W93:AB93)/AB17 | AC43: =+AVERAGE(X93:AC93)/AC17 | AD43: =+AVERAGE(Y93:AD93)/AD17 | AE43: =+AVERAGE(Z93:AE93)/AE17 | AF43: =+AVERAGE(AA93:AF93)/AF17 | AG43: =+AVERAGE(AB93:AG93)/AG17 | AH43: =+AVERAGE(AC93:AH93)/AH17 | AI43: =+AVERAGE(AD93:AI93)/AI17 | ... DG43: =+AVERAGE(DB93:DG93)/DG17
C44: LTV/CAC | L44: =+L42/L43 | M44: =+M42/M43 | N44: =+N42/N43 | O44: =+O42/O43 | P44: =+P42/P43 | Q44: =+Q42/Q43 | R44: =+R42/R43 | S44: =+S42/S43 | ... U44: =+U42/U43 | V44: 0 | W44: =+W42/W43 | X44: =+X42/X43 | Y44: =+Y42/Y43 | Z44: =+Z42/Z43 | AA44: =+AA42/AA43 | AB44: =+AB42/AB43 | AC44: =+AC42/AC43 | AD44: =+AD42/AD43 | ... DG44: =+DG42/DG43
C45: Payback | L45: =+L43/(L38*L40) | M45: =+M43/(M38*M40) | N45: =+N43/(N38*N40) | O45: =+O43/(O38*O40) | P45: =+P43/(P38*P40) | Q45: =+Q43/(Q38*Q40) | R45: =+R43/(R38*R40) | S45: =+S43/(S38*S40) | ... U45: =+U43/(U38*U40) | V45: 0 | W45: =+W43/(W38*W40) | X45: =+X43/(X38*X40) | Y45: =+Y43/(Y38*Y40) | Z45: =+Z43/(Z38*Z40) | AA45: =+AA43/(AA38*AA40) | AB45: =+AB43/(AB38*AB40) | AC45: =+AC43/(AC38*AC40) | AD45: =+AD43/(AD38*AD40) | ... DG45: =+DG43/(DG38*DG40)
C46: Utilization % | E46: =+E29/8 | F46: =+F29/8 | G46: =+G29/8 | H46: =+H29/8 | I46: =+I29/8 | J46: =+J29/8 | K46: =+K29/8 | L46: =+L29/8 | ... DG46: =+DG29/8
F48: 2022 | G48: 2023 | H48: 2024 | I48: 2025 | J48: 2026 | K48: 2027 | L48: 2028 | M48: 2029 | N48: 2030 | Q48: 2022 | R48: 2023 | S48: 2024 | T48: 2025 | U48: 2026 | V48: 2027 | W48: 2028 | X48: 2028 | Y48: 2028 | Z48: 2028 | AA48: 2028 | AB48: 2028 | AC48: 2028 | AD48: 2028 | AE48: 2028 | AF48: 2029 | AG48: 2029 | AH48: 2029 | AI48: 2029 | AJ48: 2029 | AK48: 2029 | AL48: 2029 | AM48: 2029 | AN48: 2029 | AO48: 2029 | AP48: 2029 | AQ48: 2029 | AR48: 2029 | AS48: 2029 | AT48: 2029 | AU48: 2029 | AV48: 2029 | AW48: 2029
E49: Average | F49: =ROUNDUP(AVERAGE(F50:F52), 0) | G49: =ROUNDUP(AVERAGE(G50:G52), 0) | H49: =ROUNDUP(AVERAGE(H50:H52), 0) | I49: =ROUNDUP(AVERAGE(I50:I52), 0) | J49: =ROUNDUP(AVERAGE(J50:J52), 0) | K49: =ROUNDUP(AVERAGE(K50:K52), 0) | L49: =ROUNDUP(AVERAGE(L50:L52), 0) | M49: =ROUNDUP(AVERAGE(M50:M52), 0) | N49: =ROUNDUP(AVERAGE(N50:N52), 0) | P49: Average | Q49: =ROUNDUP(AVERAGE(Q50:Q52), 0) | R49: =ROUNDUP(AVERAGE(R50:R52), 0) | S49: =ROUNDUP(AVERAGE(S50:S52), 0) | T49: =ROUNDUP(AVERAGE(T50:T52), 0) | U49: =ROUNDUP(AVERAGE(U50:U52), 0) | V49: =ROUNDUP(AVERAGE(V50:V52), 0) | W49: =ROUNDUP(AVERAGE(W50:W52), 0) | X49: =ROUNDUP(AVERAGE(X50:X52), 0) | ... AW49: =ROUNDUP(AVERAGE(AW50:AW52), 0)
E50: Peak | F50: =ROUNDUP(AVERAGEIFS($E$15:$DG$15, $H$2:$DJ$2,$E$50, $H$1:$DJ$1, F48), 0) | G50: =ROUNDUP(AVERAGEIFS($H$19:$DJ$19, $H$2:$DJ$2,$E50, $H$1:$DJ$1, G$48), 0) | H50: =ROUNDUP(AVERAGEIFS($H$19:$DJ$19, $H$2:$DJ$2,$E50, $H$1:$DJ$1, H$48), 0) | I50: =+H50+3 | J50: =+I50+3 | K50: =+J50+3 | L50: =+K50+3 | M50: =+L50+3 | N50: =+M50+3 | P50: Peak | Q50: =AVERAGEIFS($E$29:$DG$29, $H$2:$DJ$2,$E$50, $H$1:$DJ$1, Q48) | R50: =AVERAGEIFS($E$29:$DG$29, $H$2:$DJ$2,$E$50, $H$1:$DJ$1, R48) | S50: =AVERAGEIFS($E$29:$DG$29, $H$2:$DJ$2,$E$50, $H$1:$DJ$1, S48) | T50: =AVERAGEIFS($E$29:$DG$29, $H$2:$DJ$2,$E$50, $H$1:$DJ$1, T48) | U50: =AVERAGEIFS($E$29:$DG$29, $H$2:$DJ$2,$E$50, $H$1:$DJ$1, U48) | V50: =AVERAGEIFS($E$29:$DG$29, $H$2:$DJ$2,$E$50, $H$1:$DJ$1, V48) | W50: =AVERAGEIFS($E$29:$DG$29, $H$2:$DJ$2,$E$50, $H$1:$DJ$1, W48) | X50: =AVERAGEIFS($E$29:$DG$29, $H$2:$DJ$2,$E$50, $H$1:$DJ$1, X48) | ... AW50: =AVERAGEIFS($E$29:$DG$29, $H$2:$DJ$2,$E$50, $H$1:$DJ$1, AW48)
E51: Shoulder | F51: =ROUNDUP(AVERAGEIFS($E$15:$DG$15, $H$2:$DJ$2,$E$51, $H$1:$DJ$1, F48), 0) | G51: =ROUNDUP(AVERAGEIFS($H$19:$DJ$19, $H$2:$DJ$2,$E51, $H$1:$DJ$1, G$48), 0) | H51: =ROUNDUP(AVERAGEIFS($H$19:$DJ$19, $H$2:$DJ$2,$E51, $H$1:$DJ$1, H$48), 0) | I51: =+H51+2 | J51: =+I51+2 | K51: =+J51+2 | L51: =+K51+2 | M51: =+L51+2 | N51: =+M51+2 | P51: Shoulder | Q51: =+AVERAGEIFS($E$29:$DG$29, $H$2:$DJ$2,$E$51, $H$1:$DJ$1, Q48) | R51: =+AVERAGEIFS($E$29:$DG$29, $H$2:$DJ$2,$E$51, $H$1:$DJ$1, R48) | S51: =+AVERAGEIFS($E$29:$DG$29, $H$2:$DJ$2,$E$51, $H$1:$DJ$1, S48) | T51: =+AVERAGEIFS($E$29:$DG$29, $H$2:$DJ$2,$E$51, $H$1:$DJ$1, T48) | U51: =+AVERAGEIFS($E$29:$DG$29, $H$2:$DJ$2,$E$51, $H$1:$DJ$1, U48) | V51: =+AVERAGEIFS($E$29:$DG$29, $H$2:$DJ$2,$E$51, $H$1:$DJ$1, V48) | W51: =+AVERAGEIFS($E$29:$DG$29, $H$2:$DJ$2,$E$51, $H$1:$DJ$1, W48) | X51: =+AVERAGEIFS($E$29:$DG$29, $H$2:$DJ$2,$E$51, $H$1:$DJ$1, X48) | ... AW51: =+AVERAGEIFS($E$29:$DG$29, $H$2:$DJ$2,$E$51, $H$1:$DJ$1, AW48)
E52: Trough | F52: =ROUNDUP(AVERAGEIFS($E$15:$DG$15, $H$2:$DJ$2,$E$52, $H$1:$DJ$1, F48), 0) | G52: =ROUNDUP(AVERAGEIFS($H$19:$DJ$19, $H$2:$DJ$2,$E52, $H$1:$DJ$1, G$48), 0) | H52: =ROUNDUP(AVERAGEIFS($H$19:$DJ$19, $H$2:$DJ$2,$E52, $H$1:$DJ$1, H$48), 0) | I52: =+H52+1 | J52: =+I52+1 | K52: =+J52+1 | L52: =+K52+1 | M52: =+L52+1 | N52: =+M52+1 | P52: Trough | Q52: =AVERAGEIFS($E$29:$DG$29, $H$2:$DJ$2,$E$52, $H$1:$DJ$1, Q48) | R52: =AVERAGEIFS($E$29:$DG$29, $H$2:$DJ$2,$E$52, $H$1:$DJ$1, R48) | S52: =AVERAGEIFS($E$29:$DG$29, $H$2:$DJ$2,$E$52, $H$1:$DJ$1, S48) | T52: =AVERAGEIFS($E$29:$DG$29, $H$2:$DJ$2,$E$52, $H$1:$DJ$1, T48) | U52: =AVERAGEIFS($E$29:$DG$29, $H$2:$DJ$2,$E$52, $H$1:$DJ$1, U48) | V52: =AVERAGEIFS($E$29:$DG$29, $H$2:$DJ$2,$E$52, $H$1:$DJ$1, V48) | W52: =AVERAGEIFS($E$29:$DG$29, $H$2:$DJ$2,$E$52, $H$1:$DJ$1, W48) | X52: =AVERAGEIFS($E$29:$DG$29, $H$2:$DJ$2,$E$52, $H$1:$DJ$1, X48) | ... AW52: =AVERAGEIFS($E$29:$DG$29, $H$2:$DJ$2,$E$52, $H$1:$DJ$1, AW48)
E53: Trough | F53: =F52/F49-1 | G53: =G52/G49-1 | H53: =H52/H49-1 | I53: =I52/I49-1 | J53: =J52/J49-1 | K53: =K52/K49-1 | L53: =L52/L49-1 | M53: =M52/M49-1 | N53: =N52/N49-1 | P53: Trough | Q53: =Q52/Q49-1 | R53: =R52/R49-1 | S53: =S52/S49-1 | T53: =T52/T49-1 | U53: =U52/U49-1 | V53: =V52/V49-1 | W53: =W52/W49-1 | X53: =X52/X49-1 | ... AW53: =AW52/AW49-1
E54: Shoulder | F54: =F51/F49-1 | G54: =G51/G49-1 | H54: =H51/H49-1 | I54: =I51/I49-1 | J54: =J51/J49-1 | K54: =K51/K49-1 | L54: =L51/L49-1 | M54: =M51/M49-1 | N54: =N51/N49-1 | P54: Shoulder | Q54: =Q51/Q49-1 | R54: =R51/R49-1 | S54: =S51/S49-1 | T54: =T51/T49-1 | U54: =U51/U49-1 | V54: =V51/V49-1 | W54: =W51/W49-1 | X54: =X51/X49-1 | ... AW54: =AW51/AW49-1
B57: Cost of Goods Sold
B58: 50100 Software - COS | AB58: 144.34 | AC58: 195.79 | AD58: 210.1 | AE58: 193.92 | AF58: 192.8 | AG58: 204.71 | AH58: 174.91 | AI58: 191.38 | AJ58: 128.31 | AK58: 231.31 | AL58: 160.15 | AM58: 171.4 | AN58: 197.3 | AO58: 202.11 | AP58: 214.54 | AQ58: 247.79 | AR58: 240.23 | AS58: 182.1 | AT58: 216.6 | AU58: 205.55 | AV58: 222.12 | AW58: =282 | AX58: =+AX62*AX9 | AY58: =+AY62*AY9 | AZ58: =+AZ62*AZ9 | BA58: =+BA62*BA9 | BB58: =+BB62*BB9 | BC58: =+BC62*BC9 | BD58: =+BD62*BD9 | BE58: =+BE62*BE9 | ... DG58: =+DG62*DG9
B59: 50200 Materials - COGS | AB59: 359.46 | AC59: 458.1 | AD59: 321.74 | AE59: 142.87 | AF59: 753.32 | AG59: 314.9 | AH59: 165.74 | AI59: 38.46 | AJ59: 28.36 | AK59: 357.18 | AL59: 356.29 | AM59: 589.19 | AN59: 249.98 | AO59: 497.5 | AP59: 810.15 | AQ59: 352.78 | AR59: 754.25 | AS59: 503.73 | AT59: 588.11 | AU59: 768.16 | AV59: 893.43 | AW59: =578.51 | AX59: =+AX63*AX9 | AY59: =+AY63*AY9 | AZ59: =+AZ63*AZ9 | BA59: =+BA63*BA9 | BB59: =+BB63*BB9 | BC59: =+BC63*BC9 | BD59: =+BD63*BD9 | BE59: =+BE63*BE9 | ... DG59: =+DG63*DG9
B60: 50300 Sub-Contractors | AF60: 475 | AG60: 765 | AH60: 394 | AI60: 610 | AJ60: 210 | AK60: 770 | AL60: 432 | AM60: 470 | AN60: 50 | AO60: 45 | AR60: 629 | AV60: 30 | AX60: =+'People Plan'!Y13 | AY60: =+'People Plan'!Z13 | AZ60: =+'People Plan'!AA13 | BA60: =+'People Plan'!AB13 | BB60: =+'People Plan'!AC13 | BC60: =+'People Plan'!AD13 | BD60: =+'People Plan'!AE13 | BE60: =+'People Plan'!AF13 | ... DG60: =+'People Plan'!CH13
B61: Total Cost of Goods Sold | V61: =+SUM(V58:V59) | W61: =+SUM(W58:W59) | X61: =+SUM(X58:X59) | Y61: =+SUM(Y58:Y59) | Z61: =+SUM(Z58:Z59) | AA61: =+SUM(AA58:AA59) | AB61: =SUM(AB58:AB60) | AC61: =SUM(AC58:AC60) | AD61: =SUM(AD58:AD60) | AE61: =SUM(AE58:AE60) | AF61: =SUM(AF58:AF60) | AG61: =SUM(AG58:AG60) | AH61: =SUM(AH58:AH60) | AI61: =SUM(AI58:AI60) | ... DG61: =SUM(DG58:DG60)
C62: COS as a % of Revenue | W62: =+W58/W13 | X62: =+X58/X13 | Y62: =+Y58/Y13 | Z62: =+Z58/Z13 | AA62: =+AA58/AA13 | AB62: =+AB58/AB13 | AC62: =+AC58/AC13 | AD62: =+AD58/AD13 | ... AW62: =+AW58/AW13 | AX62: =+AVERAGE(AR62:AW62) | AY62: =+AX62 | AZ62: =+AY62 | BA62: =+AZ62 | BB62: =+BA62 | BC62: =+BB62 | BD62: =+BC62 | BE62: =+BD62 | BF62: =+BE62 | ... DG62: =+DF62
C63: COGS as a % of Revenue | W63: =+W59/W13 | X63: =+X59/X13 | Y63: =+Y59/Y13 | Z63: =+Z59/Z13 | AA63: =+AA59/AA13 | AB63: =+AB59/AB13 | AC63: =+AC59/AC13 | AD63: =+AD59/AD13 | ... AW63: =+AW59/AW13 | AX63: =+AVERAGE(AR63:AW63) | AY63: =+AX63 | AZ63: =+AY63 | BA63: =+AZ63 | BB63: =+BA63 | BC63: =+BB63 | BD63: =+BC63 | BE63: =+BD63 | BF63: =+BE63 | ... DG63: =+DF63
B65: Gross Profit | D65: =(D13)-(0) | E65: =(E13)-(0) | F65: =(F13)-(0) | G65: =(G13)-(0) | H65: =(H13)-(0) | I65: =(I13)-(0) | J65: =(J13)-(0) | K65: =K13 | L65: =L13 | M65: =M13 | N65: =N13 | O65: =O13 | P65: =P13 | Q65: =Q13 | R65: =R13 | ... U65: =U13 | V65: =V13-V61 | W65: =W13-W61 | X65: =X13-X61 | Y65: =Y13-Y61 | Z65: =Z13-Z61 | AA65: =AA13-AA61 | AB65: =AB13-AB61 | AC65: =AC13-AC61 | ... DG65: =DG13-DG61
C66: GP% | AB66: =+AB65/AB13 | AC66: =+AC65/AC13 | AD66: =+AD65/AD13 | AE66: =+AE65/AE13 | AF66: =+AF65/AF13 | AG66: =+AG65/AG13 | AH66: =+AH65/AH13 | AI66: =+AI65/AI13 | ... DG66: =+DG65/DG13
B67: Expenses
B68: Owner Salary | AO68: 1300 | AP68: 1430 | AQ68: 1950 | AR68: 1365 | AS68: 650 | AT68: 650 | AU68: 715 | AV68: 438.75 | AW68: 650 | AX68: =+'People Plan'!Y18 | AY68: =+'People Plan'!Z18 | AZ68: =+'People Plan'!AA18 | BA68: =+'People Plan'!AB18 | BB68: =+'People Plan'!AC18 | BC68: =+'People Plan'!AD18 | BD68: =+'People Plan'!AE18 | BE68: =+'People Plan'!AF18 | ... DG68: =+'People Plan'!CH18
B69: Owner Payroll Taxes | AO69: 117.31 | AP69: 90.58 | AQ69: 146.47 | AR69: 85.27 | AS69: 15.88 | AT69: 65.98 | AU69: 61.61 | AV69: 33.57 | AW69: 49.74 | AX69: =+AX68*AX72 | AY69: =+AY68*AY72 | AZ69: =+AZ68*AZ72 | BA69: =+BA68*BA72 | BB69: =+BB68*BB72 | BC69: =+BC68*BC72 | BD69: =+BD68*BD72 | BE69: =+BE68*BE72 | ... DG69: =+DG68*DG72
B70: Owner Benefits | AQ70: 500 | AR70: 500 | AS70: 500 | AT70: 500 | AU70: 500 | AV70: 500 | AW70: 500 | AX70: =+AW70 | AY70: =+AX70 | AZ70: =+AY70 | BA70: =+AZ70 | BB70: =+BA70 | BC70: =+BB70 | BD70: =+BC70 | BE70: =+BD70 | ... DG70: =+DF70
B71: Total Owner Payroll Burden | T71: =SUM(T68:T70) | U71: =SUM(U68:U70) | V71: =SUM(V68:V70) | W71: =SUM(W68:W70) | X71: =SUM(X68:X70) | Y71: =SUM(Y68:Y70) | Z71: =SUM(Z68:Z70) | AA71: =SUM(AA68:AA70) | ... DG71: =SUM(DG68:DG70)
C72: Payroll Tax as a % of Salary | AO72: =+AO69/AO68 | AP72: =+AP69/AP68 | AQ72: =+AQ69/AQ68 | AR72: =+AR69/AR68 | AS72: =+AS69/AS68 | AT72: =+AT69/AT68 | AU72: =+AU69/AU68 | AV72: =+AV69/AV68 | AW72: =+AW69/AW68 | AX72: =+AVERAGE(AU72:AW72) | AY72: =+AX72 | AZ72: =+AY72 | BA72: =+AZ72 | BB72: =+BA72 | BC72: =+BB72 | BD72: =+BC72 | BE72: =+BD72 | BF72: =+BE72 | ... DG72: =+DF72
C73: Benefits as a % of Salary | AX73: 0.045 | AY73: =+AX73 | AZ73: =+AY73 | BA73: =+AZ73 | BB73: =+BA73 | BC73: =+BB73 | BD73: =+BC73 | BE73: =+BD73 | BF73: =+BE73 | ... BV73: =+BU73 | BW73: 0.15 | BX73: =+BW73 | BY73: =+BX73 | BZ73: =+BY73 | CA73: =+BZ73 | CB73: =+CA73 | CC73: =+CB73 | CD73: =+CC73 | CE73: =+CD73 | ... CH73: =+CG73 | CI73: 0.2 | CJ73: =+CI73 | CK73: =+CJ73 | CL73: =+CK73 | CM73: =+CL73 | CN73: =+CM73 | CO73: =+CN73 | CP73: =+CO73 | CQ73: =+CP73 | ... DG73: =+DF73
B74: 60200 Travel | AN74: 0 | AO74: 0 | AP74: 0 | AQ74: 0 | AR74: 0 | AS74: 0 | AT74: 0 | AU74: 0 | AV74: 0 | AW74: 0 | AX74: =+AVERAGE(AU74:AW74) | AY74: =AX74 | AZ74: =AY74 | BA74: =AZ74 | BB74: =BA74 | BC74: =BB74 | BD74: =BC74 | BE74: =BD74 | BF74: =BE74 | ... DG74: =DF74
B75: 60210 Airfare & Hotels | AB75: 264.53 | AE75: 238.31 | AI75: 8 | AL75: 168.97 | AX75: 50 | AY75: =AX75 | AZ75: =AY75 | BA75: =AZ75 | BB75: =BA75 | BC75: =BB75 | BD75: =BC75 | BE75: =BD75 | BF75: =BE75 | ... DG75: =DF75
B76: 60230 Parking & Tolls | AE76: 23.82 | AP76: 26.9 | AQ76: 0 | AR76: 0 | AS76: 0 | AT76: 5 | AU76: 0 | AV76: 0 | AW76: 0 | AX76: =+IF(AX1<>AW1, AW76*1.1, AW76) | AY76: =+IF(AY1<>AX1, AX76*1.1, AX76) | AZ76: =+IF(AZ1<>AY1, AY76*1.1, AY76) | BA76: =+IF(BA1<>AZ1, AZ76*1.1, AZ76) | BB76: =+IF(BB1<>BA1, BA76*1.1, BA76) | BC76: =+IF(BC1<>BB1, BB76*1.1, BB76) | BD76: =+IF(BD1<>BC1, BC76*1.1, BC76) | BE76: =+IF(BE1<>BD1, BD76*1.1, BD76) | ... DG76: =+IF(DG1<>DF1, DF76*1.1, DF76)
B77: 60240 Personal Mileage Reimbursement | AD77: 90.45 | AE77: 25.46 | AF77: 25.46 | AG77: 25.46 | AH77: 42.22 | AI77: 29.48 | AJ77: 14.41 | AK77: 43.23 | AL77: 14.41 | AM77: 28.82 | AN77: 14.41 | AO77: 14.41 | AP77: 14.41 | AQ77: 14.41 | AR77: 28.82 | AS77: 14.41 | AT77: 28.82 | AU77: 28.82 | AV77: 14.41 | AW77: 28.82 | AX77: =+IF(AX1<>AW1, AW77*1.1, AW77) | AY77: =+IF(AY1<>AX1, AX77*1.1, AX77) | AZ77: =+IF(AZ1<>AY1, AY77*1.1, AY77) | BA77: =+IF(BA1<>AZ1, AZ77*1.1, AZ77) | BB77: =+IF(BB1<>BA1, BA77*1.1, BA77) | BC77: =+IF(BC1<>BB1, BB77*1.1, BB77) | BD77: =+IF(BD1<>BC1, BC77*1.1, BC77) | BE77: =+IF(BE1<>BD1, BD77*1.1, BD77) | ... DG77: =+IF(DG1<>DF1, DF77*1.1, DF77)
B78: Total 60200 Travel | AB78: =SUM(AB75:AB77) | AC78: =SUM(AC75:AC77) | AD78: =SUM(AD75:AD77) | AE78: =SUM(AE75:AE77) | AF78: =SUM(AF75:AF77) | AG78: =SUM(AG75:AG77) | AH78: =SUM(AH75:AH77) | AI78: =SUM(AI75:AI77) | ... DG78: =SUM(DG75:DG77)
B79: 60300 Legal & Accounting Services
B80: 60310 Finance & Accounting | AJ80: 400 | AK80: 284.47 | AL80: 330.08 | AM80: 280.5 | AN80: 211.67 | AO80: 368.33 | AP80: 353.33 | AQ80: 330 | AR80: 297.5 | AS80: 276.25 | AT80: 382.5 | AU80: 297.5 | AV80: 318.75 | AW80: 383.75 | AX80: 350 | AY80: =+IF(AX$1<>AY$1, AX80*1.1, AX80) | AZ80: =+IF(AY$1<>AZ$1, AY80*1.1, AY80) | BA80: =+IF(AZ$1<>BA$1, AZ80*1.1, AZ80) | BB80: =+IF(BA$1<>BB$1, BA80*1.1, BA80) | BC80: =+IF(BB$1<>BC$1, BB80*1.1, BB80) | BD80: =+IF(BC$1<>BD$1, BC80*1.1, BC80) | BE80: =+IF(BD$1<>BE$1, BD80*1.1, BD80) | BF80: =+IF(BE$1<>BF$1, BE80*1.1, BE80) | ... DG80: =+IF(DF$1<>DG$1, DF80*1.1, DF80)
B81: 60320 Legal Fees | AR81: 75.51 | AS81: 0 | AT81: 0 | AU81: 0 | AV81: 0 | AW81: 0 | AX81: =+AL81 | AY81: =+AM81 | AZ81: =+AN81 | BA81: =+AO81 | BB81: =+AP81 | BC81: =+AQ81 | BD81: =+AR81 | BE81: =+AS81 | ... DG81: =+CU81
B82: Total 60300 Legal & Accounting Services | AB82: =SUM(AB79:AB80) | AC82: =SUM(AC79:AC80) | AD82: =SUM(AD79:AD80) | AE82: =SUM(AE79:AE80) | AF82: =SUM(AF79:AF80) | AG82: =SUM(AG79:AG80) | AH82: =SUM(AH79:AH80) | AI82: =SUM(AI79:AI80) | ... AM82: =SUM(AM79:AM80) | AN82: =SUM(AN79:AN81) | AO82: =SUM(AO79:AO81) | AP82: =SUM(AP79:AP81) | AQ82: =SUM(AQ79:AQ81) | AR82: =SUM(AR79:AR81) | AS82: =SUM(AS79:AS81) | AT82: =SUM(AT79:AT81) | AU82: =SUM(AU79:AU81) | ... DG82: =SUM(DG79:DG81)
B83: 60400 Office Supplies & Software | AB83: 547.22 | AC83: 375.07 | AD83: 593.53 | AE83: 398.74 | AF83: 1137.21 | AG83: 529.98 | AH83: 364.08 | AI83: 622.52 | AJ83: 373.8 | AK83: 181.44 | AL83: 265.57 | AM83: 123 | AN83: 174.52 | AO83: 221.82 | AP83: 103.99 | AQ83: 171.41 | AR83: 149.99 | AS83: 149.99 | AT83: 165.59 | AU83: 277.13 | AV83: 159.99 | AW83: =205.51 | AX83: =+IF(AX1<>AW1, AW83*1.1, AW83) | AY83: =+IF(AY1<>AX1, AX83*1.1, AX83) | AZ83: =+IF(AZ1<>AY1, AY83*1.1, AY83) | BA83: =+IF(BA1<>AZ1, AZ83*1.1, AZ83) | BB83: =+IF(BB1<>BA1, BA83*1.1, BA83) | BC83: =+IF(BC1<>BB1, BB83*1.1, BB83) | BD83: =+IF(BD1<>BC1, BC83*1.1, BC83) | BE83: =+IF(BE1<>BD1, BD83*1.1, BD83) | ... DG83: =+IF(DG1<>DF1, DF83*1.1, DF83)
B84: 60600 Bank Fees & Service Charges | AE84: 5 | AF84: 10 | AG84: 10 | AH84: 10 | AI84: 70 | AJ84: 20 | AK84: 15.31 | AL84: 25.99 | AM84: 171 | AN84: 25 | AO84: 25 | AP84: 25 | AQ84: 25 | AR84: 25 | AS84: 25 | AT84: 25 | AU84: 25 | AV84: 15 | AW84: =30 | AX84: =+IF(AX1<>AW1, AW84*1.1, AW84) | AY84: =+IF(AY1<>AX1, AX84*1.1, AX84) | AZ84: =+IF(AZ1<>AY1, AY84*1.1, AY84) | BA84: =+IF(BA1<>AZ1, AZ84*1.1, AZ84) | BB84: =+IF(BB1<>BA1, BA84*1.1, BA84) | BC84: =+IF(BC1<>BB1, BB84*1.1, BB84) | BD84: =+IF(BD1<>BC1, BC84*1.1, BC84) | BE84: =+IF(BE1<>BD1, BD84*1.1, BD84) | ... DG84: =+IF(DG1<>DF1, DF84*1.1, DF84)
B85: 60700 Facility & Storage Rent | AB85: 108 | AC85: 108 | AD85: 108 | AE85: 108 | AF85: 1408.55 | AG85: 1372.64 | AH85: 1372.64 | AI85: 1682.55 | AJ85: 1372.64 | AK85: 1372.64 | AL85: 1711.17 | AM85: 1414.26 | AN85: 1684.72 | AO85: 1374.5 | AP85: 1373.88 | AQ85: 1635.01 | AR85: 1411.37 | AS85: 1507.24 | AT85: 1680.57 | AU85: 1424.48 | AV85: 1441.35 | AW85: =1761.79 | AX85: =+AVERAGE(AR85:AW85) | AY85: =IF(AY1<>AX1, AX85*1.1,AX85) | AZ85: =IF(AZ1<>AY1, AY85*1.1,AY85) | BA85: =IF(BA1<>AZ1, AZ85*1.1,AZ85) | BB85: =IF(BB1<>BA1, BA85*1.1,BA85) | BC85: =IF(BC1<>BB1, BB85*1.1,BB85) | BD85: =IF(BD1<>BC1, BC85*1.1,BC85) | BE85: =IF(BE1<>BD1, BD85*1.1,BD85) | BF85: =IF(BF1<>BE1, BE85*1.1,BE85) | ... DG85: =IF(DG1<>DF1, DF85*1.1,DF85)
B86: 60800 Business Insurance | AB86: 40.21 | AC86: 366.97 | AE86: 409.3 | AF86: 43.4 | AG86: 239.61 | AH86: 43.4 | AI86: 286.16 | AJ86: 51.62 | AK86: 112.74 | AL86: 196.16 | AM86: 275.89 | AN86: 51.58 | AO86: 196.74 | AP86: 226.74 | AQ86: 391.9 | AR86: 51.58 | AS86: 216.74 | AT86: 176.95 | AU86: 216.91 | AV86: 221.96 | AW86: =222 | AX86: =+AVERAGE(AU86:AW86) | AY86: =IF(AY1<>AX1, AX86*1.1,AX86) | AZ86: =IF(AZ1<>AY1, AY86*1.1,AY86) | BA86: =IF(BA1<>AZ1, AZ86*1.1,AZ86) | BB86: =IF(BB1<>BA1, BA86*1.1,BA86) | BC86: =IF(BC1<>BB1, BB86*1.1,BB86) | BD86: =IF(BD1<>BC1, BC86*1.1,BC86) | BE86: =IF(BE1<>BD1, BD86*1.1,BD86) | BF86: =IF(BF1<>BE1, BE86*1.1,BE86) | ... DG86: =IF(DG1<>DF1, DF86*1.1,DF86)
B87: 60900 Donations | AF87: 40 | AX87: 10 | AY87: =IF(AY1<>AX1, AX87*1.1,AX87) | AZ87: =IF(AZ1<>AY1, AY87*1.1,AY87) | BA87: =IF(BA1<>AZ1, AZ87*1.1,AZ87) | BB87: =IF(BB1<>BA1, BA87*1.1,BA87) | BC87: =IF(BC1<>BB1, BB87*1.1,BB87) | BD87: =IF(BD1<>BC1, BC87*1.1,BC87) | BE87: =IF(BE1<>BD1, BD87*1.1,BD87) | BF87: =IF(BF1<>BE1, BE87*1.1,BE87) | ... DG87: =IF(DG1<>DF1, DF87*1.1,DF87)
B88: 61000 Business Licences | AG88: 50 | AK88: 105 | AU88: 62.81 | AV88: 0 | AW88: 0 | AX88: =+AL88 | AY88: =+AM88 | AZ88: =+AN88 | BA88: =+AO88 | BB88: =+AP88 | BC88: =+AQ88 | BD88: =+AR88 | BE88: =+AS88 | ... DG88: =+CU88
B89: Total G&A Expenses | D89: =SUM(D74:D78) | E89: =SUM(E74:E78) | F89: =SUM(F74:F78) | G89: =SUM(G74:G78) | H89: =SUM(H74:H78) | I89: =SUM(I74:I78) | J89: =SUM(J74:J78) | K89: =SUM(K74:K78) | ... U89: =SUM(U74:U78) | V89: =SUM(V74:V86) | W89: =SUM(W74:W86) | X89: =SUM(X74:X86) | Y89: =SUM(Y74:Y86) | Z89: =SUM(Z74:Z86) | AA89: =SUM(AA74:AA86) | AB89: =+SUM(AB71, AB78, AB82:AB88) | AC89: =+SUM(AC71, AC78, AC82:AC88) | AD89: =+SUM(AD71, AD78, AD82:AD88) | AE89: =+SUM(AE71, AE78, AE82:AE88) | AF89: =+SUM(AF71, AF78, AF82:AF88) | AG89: =+SUM(AG71, AG78, AG82:AG88) | AH89: =+SUM(AH71, AH78, AH82:AH88) | AI89: =+SUM(AI71, AI78, AI82:AI88) | ... DG89: =+SUM(DG71, DG78, DG82:DG88)
B90: Interest Paid | AW90: 16.13
B91: Total Expenses | D91: =SUM(D89:D89) | E91: =SUM(E89:E89) | F91: =SUM(F89:F89) | G91: =SUM(G89:G89) | H91: =SUM(H89:H89) | I91: =SUM(I89:I89) | J91: =SUM(J89:J89) | K91: =SUM(K89:K89) | ... AV91: =SUM(AV89:AV89) | AW91: =SUM(AW89:AW89)+AW90 | AX91: =SUM(AX89:AX89)+AX90 | AY91: =SUM(AY89:AY89)+AY90 | AZ91: =SUM(AZ89:AZ89)+AZ90 | BA91: =SUM(BA89:BA89)+BA90 | BB91: =SUM(BB89:BB89)+BB90 | BC91: =SUM(BC89:BC89)+BC90 | BD91: =SUM(BD89:BD89)+BD90 | ... DG91: =SUM(DG89:DG89)+DG90
B92: Net Operating Income | D92: =D65-D91 | E92: =E65-E91 | F92: =F65-F91 | G92: =G65-G91 | H92: =H65-H91 | I92: =I65-I91 | J92: =J65-J91 | K92: =K65-K91 | ... DG92: =DG65-DG91
C93: CAC | W93: =+SUM(W75:W77,W61) | X93: =+SUM(X75:X77,X61) | Y93: =+SUM(Y75:Y77,Y61) | Z93: =+SUM(Z75:Z77,Z61) | AA93: =+SUM(AA75:AA77,AA61) | AB93: =+SUM(AB75:AB77,AB61, AB85:AB86) | AC93: =+SUM(AC75:AC77,AC61, AC85:AC86) | AD93: =+SUM(AD75:AD77,AD61, AD85:AD86) | AE93: =+SUM(AE75:AE77,AE61, AE85:AE86) | AF93: =+SUM(AF75:AF77,AF61, AF85:AF86) | AG93: =+SUM(AG75:AG77,AG61, AG85:AG86) | AH93: =+SUM(AH75:AH77,AH61, AH85:AH86) | AI93: =+SUM(AI75:AI77,AI61, AI85:AI86) | ... DG93: =+SUM(DG75:DG77,DG61, DG85:DG86)
B94: Other Income
B95: Interest Income | P95: 0 | Q95: 0 | R95: 0 | X95: 0 | Y95: 0 | Z95: 0 | AA95: 0 | AB95: 0 | AC95: 0 | AD95: 0 | AE95: 0 | AF95: 0 | AG95: 0 | AH95: 0 | AI95: 0 | AJ95: 0 | AK95: 0 | AL95: 0 | AM95: 0 | AN95: 0 | AO95: 0 | AP95: 2.35 | AQ95: 3.21 | AR95: 4.3 | AS95: 3.94 | AT95: 4.21 | AU95: 3.44 | AV95: 2.61 | AW95: 1.78 | AX95: =AW95 | AY95: =AX95 | AZ95: =AY95 | BA95: =AZ95 | BB95: =BA95 | BC95: =BB95 | BD95: =BC95 | BE95: =BD95 | ... DG95: =DF95
B96: Total Other Income | D96: =D95 | E96: =E95 | F96: =F95 | G96: =G95 | H96: =H95 | I96: =I95 | J96: =J95 | K96: 0 | L96: 0 | N96: =N95 | O96: =O95 | P96: =P95 | Q96: =Q95 | R96: =R95 | S96: =S95 | T96: =T95 | U96: =U95 | ... DG96: =DG95
B97: Net Other Income | D97: =D96 | E97: =E96 | F97: =F96 | G97: =G96 | H97: =H96 | I97: =I96 | J97: =J96 | K97: =K96 | ... DG97: =DG96
B98: Net Income | D98: =D92+D97 | E98: =E92+E97 | F98: =F92+F97 | G98: =G92+G97 | H98: =H92+H97 | I98: =I92+I97 | J98: =J92+J97 | K98: =K92+K97 | ... DG98: =DG92+DG97
B102: ASSETS
B103: Current Assets
B104: Bank Accounts
B105: 10100 Operating - 2528 | AB105: 260.54 | AC105: 592.16 | AD105: 287.01 | AE105: 310.12 | AF105: 382.24 | AG105: 223.41 | AH105: -42.23 | AI105: 419.06 | AJ105: -99.91 | AK105: 294.48 | AL105: 115.05 | AM105: 158.48 | AN105: 378.97 | AO105: 146.71 | AP105: 454.06 | AQ105: 209.74 | AR105: 785.34 | AS105: 815.92 | AT105: 277.28 | AU105: 542.45 | AV105: 526.25 | AW105: =599.48 | AX105: =+AW105+AX170 | AY105: =+AX105+AY170 | AZ105: =+AY105+AZ170 | BA105: =+AZ105+BA170 | BB105: =+BA105+BB170 | BC105: =+BB105+BC170 | BD105: =+BC105+BD170 | BE105: =+BD105+BE170 | ... DG105: =+DF105+DG170
B106: 10200 Savings - 7351 | AB106: 130.91 | AC106: 33.95 | AD106: 770.48 | AE106: 79.36 | AF106: 107.93 | AG106: 496.7 | AH106: 27.5 | AI106: 53.18 | AJ106: 110.31 | AK106: 540.47 | AL106: 28.95 | AM106: 92.91 | AN106: 45.02 | AO106: 68.56 | AP106: 0.03 | AQ106: 9.57 | AR106: 150.5 | AS106: 17.12 | AT106: 50.77 | AU106: 0.77 | AV106: 37.46 | AW106: =15.87 | AX106: =+AW106 | AY106: =+AX106 | AZ106: =+AY106 | BA106: =+AZ106 | BB106: =+BA106 | BC106: =+BB106 | BD106: =+BC106 | BE106: =+BD106 | ... DG106: =+DF106
B107: 10300 Tax - 9887 | AB107: 541.95 | AC107: 419.66 | AD107: 1750.64 | AE107: 495.44 | AF107: 755.47 | AG107: 797.2 | AH107: 1788.29 | AI107: 644.48 | AJ107: 112.76 | AK107: 831.56 | AL107: 1468.65 | AM107: 685.86 | AN107: 519.07 | AO107: 274.31 | AP107: 0.14 | AQ107: 38.29 | AR107: 276.86 | AS107: 158.34 | AT107: 133.11 | AU107: 3.07 | AV107: 241.74 | AW107: =63.45 | AX107: =+AW107 | AY107: =+AX107 | AZ107: =+AY107 | BA107: =+AZ107 | BB107: =+BA107 | BC107: =+BB107 | BD107: =+BC107 | BE107: =+BD107 | ... DG107: =+DF107
B108: 10400 VACU Checking - 2865 | AC108: 0 | AD108: 0 | AE108: 895 | AF108: 1364.89 | AG108: 1103.06 | AH108: 1139.18 | AI108: -55.2 | AJ108: 0.31 | AK108: 605.31 | AL108: 224.02 | AM108: 488.75 | AN108: 1097.26 | AO108: 401.39 | AP108: 82.66 | AQ108: 547.45 | AR108: 1327.16 | AS108: 1711.63 | AT108: 1168.87 | AU108: 1355.36 | AV108: 346.15 | AW108: =38.99 | AX108: =+AW108 | AY108: =+AX108 | AZ108: =+AY108 | BA108: =+AZ108 | BB108: =+BA108 | BC108: =+BB108 | BD108: =+BC108 | BE108: =+BD108 | ... DG108: =+DF108
B109: 10500 Cash | AB109: 0 | AC109: 0 | AD109: 0 | AE109: 0 | AF109: 0 | AG109: 0 | AH109: 0 | AI109: 0 | AJ109: 0 | AK109: 0 | AL109: 0 | AM109: 0 | AN109: 0 | AO109: 0 | AP109: 0 | AQ109: 0 | AR109: 0 | AS109: 0 | AT109: 0 | AU109: 0 | AV109: 0 | AW109: 0
...

Sheet 3

Sheet October
A1: Student | B1: Date | C1: Hours | D1: Rate ($/hr) | E1: Coin | F1: Billed? | G1: Received payment? | H1: Topic | I1: Tip? | J1: Paid via invoice? | K1: Totals
A2: Abby Owen | B2: 44836 | C2: 1 | D2: 50 | E2: 50 | F2: Yes | G2: Yes | H2: Math (general homework) | I2: No | J2: No | K2: 50 | N2: BALANCED
A3: Abby Owen | B3: 44846 | C3: 2 | D3: 50 | E3: 100 | F3: Yes | G3: Yes | H3: Algebra 2 | I3: No | J3: YES | K3: 100
A4: Abby Owen | B4: 44858 | C4: 1 | D4: 50 | E4: 50 | F4: Yes | G4: Yes | H4: Emergency Math Lab | I4: No | J4: YES | K4: 50
A5: Abby Owen | B5: 44859 | C5: 0.75 | D5: 50 | E5: 37.5 | F5: Yes | G5: Yes | H5: Logarithmic Functions Review | I5: No | J5: YES | K5: 37.5
A6: Abby Owen | B6: 44861 | C6: 1 | D6: 50 | E6: 50 | F6: Yes | G6: Yes | H6: Precalc - Exponentials and Logs | I6: No | J6: YES | K6: 50
A7: Addison O'Connor | B7: 44849 | C7: 1 | D7: 60 | E7: 60 | F7: Yes | G7: Yes | H7: Choreography Review | I7: No | J7: YES | K7: 60
A8: Caroline Frey | B8: 44852 | C8: 3.5 | D8: 50 | E8: 175 | F8: Yes | G8: Yes | H8: TN and CoC Essay Supplement Finalization | I8: Yes | J8: No - Venmo b/c tip; sent to personal account but transferred accordingly (sent to Eric and Eric venmo'd business acc) | K8: 200
A9: Caroline Frey | B9: 44857 | C9: 1 | D9: 50 | E9: 50 | F9: Yes | G9: Yes | H9: Bama Honors Appliation | I9: No | J9: No - venmo b/c tip | K9: 50
A10: Claire Cecotti | B10: 44837 | C10: 1 | D10: 50 | E10: 50 | F10: Yes | G10: Yes | H10: SAT Math, Piecewise Functions Test | I10: No | J10: YES | K10: 50
A11: Elle Mishler | B11: 44842 | C11: 1 | D11: 60 | E11: 60 | F11: Yes | G11: Yes | H11: Algebra 1 | I11: No | J11: YES | K11: 60
A12: Elle Mishler | B12: 44846 | C12: 1 | D12: 60 | E12: 60 | F12: Yes | G12: Yes | H12: Algebra 1 | I12: No | J12: YES | K12: 60
A13: Elle Mishler | B13: 44853 | C13: 1.25 | D13: 60 | E13: 75 | F13: Yes | G13: Yes | H13: Algebra 1 Review | I13: No | J13: YES | K13: 75
A14: Gabby Bagot | B14: 44856 | C14: 1 | D14: 60 | E14: 60 | F14: Yes | G14: Yes | H14: Algebra 1 | I14: No | J14: YES | K14: 60 | N14: *Sujay 21 Oct, 23 Oct, 29 Oct, and 30 Oct were all billed together.
A15: Julia Cecotti | B15: 44845 | C15: 1 | D15: 50 | E15: 50 | F15: Yes | G15: Yes | H15: Precalc - piecewise functions | I15: No | J15: YES | K15: 50
A16: Julia Cecotti | B16: 44851 | C16: 1.5 | D16: 50 | E16: 75 | F16: Yes | G16: Yes | H16: Limits and Discontinuity | I16: No | J16: YES | K16: 75
A17: Kathryn Oakford | B17: 44851 | C17: 1.5 | D17: 50 | E17: 75 | F17: Yes | G17: Yes | H17: Business Calculus | I17: No | J17: YES | K17: 75
A18: Kathryn Oakford | B18: 44857 | C18: 1.5 | D18: 50 | E18: 75 | F18: Yes | G18: Yes | H18: Business Calculus | I18: No | J18: YES | K18: 75 | O18: Row Labels | P18: Sum of Hours | Q18: Sum of Coin
A19: Kaylie Thompson | B19: 44836 | C19: 1.5 | D19: 50 | E19: 75 | F19: Yes | G19: Yes | H19: Common App Finalizaiton | I19: No | J19: No | K19: 75 | O19: Abby Owen | P19: 5.75 | Q19: 287.5
A20: Maddie Wilson | B20: 44836 | C20: 2 | D20: 50 | E20: 100 | F20: Yes | G20: Yes | H20: ACT Math | I20: No | J20: No | K20: 100 | O20: Addison O'Connor | P20: 1 | Q20: 60
A21: Maddie Wilson | B21: 44854 | C21: 1.5 | D21: 50 | E21: 75 | F21: Yes | G21: Yes | H21: ACT Math | I21: No | J21: No - received via PayPal and Transferred | K21: 75 | O21: Caroline Frey | P21: 4.5 | Q21: 225
A22: Maddox Rogers | B22: 44847 | C22: 2 | D22: 50 | E22: 100 | F22: Yes | G22: Yes | H22: College Essay | I22: No | J22: YES | K22: 100 | O22: Claire Cecotti | P22: 1 | Q22: 50
A23: Naura Peters | B23: 44856 | C23: 0.5 | D23: 60 | E23: 30 | F23: Yes | G23: Yes | H23: Private lesson | I23: No | J23: YES | K23: 30 | O23: Elle Mishler | P23: 3.25 | Q23: 195
A24: Nicolette Batori | B24: 44857 | C24: 2 | D24: 50 | E24: 100 | F24: Yes | G24: Yes | H24: AP Test Advice, Volunteering advice, SAT Math | I24: No | J24: YES | K24: 100 | O24: Gabby Bagot | P24: 1 | Q24: 60
A25: Nicolette Batori | B25: 44863 | C25: 1 | D25: 50 | E25: 50 | F25: Yes | G25: Yes | H25: SAT Math | I25: No | J25: YES | K25: 50 | O25: Julia Cecotti | P25: 2.5 | Q25: 125
A26: Nicolette Batori | B26: 44865 | C26: 1 | D26: 50 | E26: 50 | F26: Yes | G26: Yes | H26: SAT Math | I26: No | J26: YES | K26: 50 | O26: Kathryn Oakford | P26: 3 | Q26: 150
A27: Rohan Skanda | B27: 44838 | C27: 1 | D27: 50 | E27: 50 | F27: Yes | G27: Yes | H27: AOS Integrated Math + Science | I27: No | J27: YES | K27: 50 | O27: Kaylie Thompson | P27: 1.5 | Q27: 75
A28: Rohan Skanda | B28: 44840 | C28: 2 | D28: 50 | E28: 100 | F28: Yes | G28: Yes | H28: AOS Integrated Math + Science | I28: No | J28: YES | K28: 100 | O28: Maddie Wilson | P28: 3.5 | Q28: 175
A29: Rohan Skanda | B29: 44851 | C29: 1.5 | D29: 50 | E29: 75 | F29: Yes | G29: Yes | H29: Math and Physics Review | I29: No | J29: YES | K29: 75 | O29: Maddox Rogers | P29: 2 | Q29: 100
A30: Rohan Skanda | B30: 44857 | C30: 1 | D30: 50 | E30: 75 | F30: Yes | G30: Yes | H30: AOS Integrated Math + Science | I30: No | J30: YES | K30: 75 | O30: Naura Peters | P30: 0.5 | Q30: 30
... A36: Sophia Gonzales | B36: 44861 | C36: 1 | D36: 60 | E36: 60 | F36: Yes | G36: Yes | H36: Physics | I36: No | J36: YES | K36: 60 | O36: Grand Total | P36: 57.25 | Q36: 2840
A37: Sujay Penugonda | B37: 44840 | C37: 1.5 | D37: 50 | E37: 75 | F37: Yes | G37: Yes | H37: Supplemental Essays | I37: No | J37: YES | K37: 75
A38: Sujay Penugonda | B38: 44855 | C38: 2 | D38: 50 | E38: 100 | F38: Yes | G38: Yes | H38: College Essay | I38: No | J38: YES | K38: 100
A39: Sujay Penugonda | B39: 44857 | C39: 0.5 | D39: 50 | E39: 25 | F39: No | G39: Yes | H39: College Essay | I39: No | J39: YES | K39: 25
A40: Sujay Penugonda | B40: 44863 | C40: 5 | D40: 50 | E40: 125 | F40: Yes | G40: Yes | H40: College Essay | I40: No | J40: YES | K40: 250
A41: Sujay Penugonda | B41: 44864 | C41: 2.5 | D41: 50 | E41: 125 | F41: Yes | G41: Yes | H41: College Essay | I41: No | J41: No - asked to send via Zelle. Transferred from personal to biz immediately. | K41: 125
K43: =SUM(K2:K41)

Sheet September
A1: Student | B1: Date | C1: Hours | D1: Rate ($/hr) | E1: Coin | F1: Billed? | G1: Received payment? | H1: Topic | I1: Tip? | J1: Totals
A2: Rohan Skanda | B2: 44822 | C2: 1 | D2: 50 | E2: 50 | F2: Yes | G2: Yes | H2: AOS Math/Science | I2: No | J2: 50 | M2: BALANCED
A3: Maddie Wilson | B3: 44822 | C3: 2 | D3: 50 | E3: 100 | F3: Yes | G3: Yes | H3: College Essay | I3: No | J3: 100
A4: Caroline Frey | B4: 44822 | C4: 1.5 | D4: 50 | E4: 75 | F4: Yes | G4: Yes | H4: College Supplemental Essays | I4: 25 | J4: 100
A5: Kathryn Oakford | B5: 44822 | C5: 1.5 | D5: 50 | E5: 75 | F5: Yes | G5: Yes | H5: Business Calc | I5: No | J5: 75
A6: Kaylie Thompson | B6: 44822 | C6: 1.5 | D6: 50 | E6: 75 | F6: Yes | G6: Yes | H6: College Essay | I6: No | J6: 75
A7: Abby Owen | B7: 44823 | C7: 2 | D7: 50 | E7: 100 | F7: Yes | G7: Yes | H7: Math Practice for Quiz | I7: No | J7: 100
A8: Kathryn Oakford | B8: 44823 | C8: 1 | D8: 50 | E8: 50 | F8: Yes | G8: Yes | H8: Business Calc | I8: No | J8: 50
A9: Maddie Wilson | B9: 44826 | C9: 1 | D9: 50 | E9: 50 | F9: Yes | G9: Yes | H9: ACT Math, NHS Essay | I9: No | J9: 50
A10: Mckenzie Frey | B10: 44827 | C10: 0.5 | D10: 50 | E10: 25 | F10: No | G10: Yes (accounted for in October w Caroline) | H10: PR/Project Planning | O10: Row Labels | P10: Sum of Hours | Q10: Sum of Coin
A11: Maddie Wilson | B11: 44827 | C11: 1 | D11: 50 | E11: 50 | F11: Yes | G11: Yes | H11: NHS Essay | I11: No | J11: 50 | O11: Abby Owen | P11: 2 | Q11: 100
A12: Claire Cecotti | B12: 44829 | C12: 1 | D12: 50 | E12: 50 | F12: Yes | G12: Yes | H12: Algebra Review/SAT Math | I12: No | J12: 50 | O12: Caroline Frey | P12: 1.5 | Q12: 75
A13: Maddie Wilson | B13: 44829 | C13: 2 | D13: 100 | E13: 100 | F13: Yes | G13: Yes | H13: Supplemental Essays | I13: No | J13: 100 | O13: Claire Cecotti | P13: 2 | Q13: 100
A14: Sam Cormier | B14: 44829 | C14: 2 | D14: 100 | E14: 100 | F14: Yes | G14: Yes | H14: Supplemental Essays | I14: No | J14: 100 | O14: Kathryn Oakford | P14: 2.5 | Q14: 125
A15: Claire Cecotti | B15: 44830 | C15: 1 | D15: 50 | E15: 50 | F15: Yes | G15: Yes | H15: Algebra Review/SAT Math | I15: No | J15: 50 | O15: Kaylie Thompson | P15: 1.5 | Q15: 75
A16: Maddie Wilson | B16: 44832 | C16: 1.5 | D16: 50 | E16: 75 | F16: Yes | G16: Yes | H16: Supplemental Essays | I16: No | J16: 75 | O16: Maddie Wilson | P16: 7.5 | Q16: 375
O17: Mckenzie Frey | P17: 0.5 | Q17: 25
J18: =SUM(J2:J16) | O18: Rohan Skanda | P18: 1 | Q18: 50
O19: Sam Cormier | P19: 2 | Q19: 100
O20: Grand Total | P20: 20.5 | Q20: 1025

Sheet August
A1: Student | B1: Date | C1: Hours | D1: Rate ($/hr) | E1: Coin | F1: Billed? | G1: Received payment? | H1: Topic | I1: Tip? | J1: Totals
A2: Caroline Frey | B2: 44793 | C2: 0.5 | D2: 50 | E2: =C2*D2 | F2: Yes | G2: Yes | H2: Adderal form | I2: 10 | J2: =E2+I2
A3: Nicolette Batori | B3: 44794 | C3: 1.5 | D3: 50 | E3: =C3*D3 | F3: No | G3: Yes | H3: SAT/ACT overview, college talk/prep | I3: 0 | J3: =E3+I3
A4: Maddie Wilson | B4: 44794 | C4: 1 | D4: 50 | E4: =C4*D4 | F4: No | G4: No | H4: ACT Science | J4: =E4+I4
A5: Sujay Penugonda | B5: 44796 | C5: 2 | D5: 50 | E5: =C5*D5 | F5: Yes | G5: Yes | H5: Essay | J5: =E5+I5 | O5: Row Labels | P5: Sum of Hours | Q5: Sum of Coin
A6: Maddie Wilson | B6: 44796 | C6: 2 | D6: 50 | E6: =C6*D6 | F6: No | G6: No | H6: ACT Math, college essay | J6: =E6+I6 | O6: Caroline Frey | P6: 0.5 | Q6: 25
A7: Matthew Aasen | B7: 44796 | C7: 0.5 | D7: 50 | E7: =C7*D7 | F7: Yes | G7: Yes | H7: 2nd read common app | J7: =E7+I7 | O7: Maddie Wilson | P7: 3 | Q7: 150
O8: Matthew Aasen | P8: 0.5 | Q8: 25
O9: Nicolette Batori | P9: 1.5 | Q9: 75
J10: =SUM(J2:J7) | O10: Sujay Penugonda | P10: 2 | Q10: 100
O11: Grand Total | P11: 7.5 | Q11: 375
J12: BALANCED

Sheet Actual vs. Forecast
B14: 45991
D15: 45535 | E15: 45565 | F15: 45596 | G15: 45626 | H15: 45657 | I15: 45688 | J15: 45716 | K15: 45747 | L15: 45777 | M15: 45808 | N15: 45838 | O15: 45869 | P15: 45900 | Q15: 45930 | R15: 45961 | S15: Forecast | T15: 45565 | U15: 45596 | V15: 45626 | W15: 45657 | X15: 45688 | Y15: 45716 | Z15: 45747 | AA15: 45777 | AB15: 45808 | AC15: 45838 | AD15: 45869 | AE15: 45900 | AF15: 45930 | AG15: 45961 | AH15: Actual | AI15: 45688 | AJ15: 45716 | AK15: 45747 | AL15: 45777 | AM15: 45808 | AN15: 45838 | AO15: 45869 | AP15: 45900 | AQ15: 45930 | AR15: 45961 | AS15: Budget | AT15: 46022 | AU15: Variance (Forecast) | AV15: Variance (Budget)
B16: Total Income | D16: 12767.593 | E16: 6113.1712 | F16: 6127.5858 | G16: 6569.6086 | H16: 5526.456 | I16: 7567.2767 | J16: 7549.4577 | K16: 6427.3261 | L16: 5052.1016 | M16: 5184.0236 | N16: 5656.028 | O16: 7290.1838 | P16: 6944.7903 | Q16: 7864.4087 | R16: 8702.984 | S16: =+SUMIF('Monthly Detail'!$4:$4, $B$14,'Monthly Detail'!$13:$13) | T16: 4188 | U16: 4938.75 | V16: 4938.75 | W16: 6152 | X16: 6721.05 | Y16: 6501.14 | Z16: 7108.5 | AA16: 7861.75 | AB16: 7877.62 | AC16: 6887.45 | AD16: 7418.55 | AE16: 7653.35 | AF16: 6170.45 | AG16: 6998.25 | AH16: =+SUMIF('Monthly Detail'!$4:$4, $B$14,'Monthly Detail'!$13:$13) | AI16: 7249.7138 | AJ16: 4913.4872 | AK16: 6536.7151 | AL16: 9380.6106 | AM16: 10754.417 | AN16: 10296.469 | AO16: 8231.419 | AP16: 7580.1793 | AQ16: 6911.5121 | AR16: 7871.8411 | AS16: 7017.7073 | AT16: 8571.1673 | AU16: =+AH16-S16 | AV16: =+AH16-AS16
B17: KPIs | C17: # of Successful Appointments | D17: 256.51065 | E17: 54.700956 | F17: 60.509581 | G17: 80.177126 | H17: 67.422003 | I17: 74.919583 | J17: 82.981115 | K17: 86.779039 | L17: 108.87894 | M17: 114.89662 | N17: 112.59858 | O17: 88.894305 | P17: 90.046534 | Q17: 58.764254 | R17: 79.396517 | S17: =+SUMIF('Monthly Detail'!$4:$4, $B$14,'Monthly Detail'!15:15) | T17: 48 | U17: 50 | V17: 50 | W17: 61 | X17: 66 | Y17: 69 | Z17: 68 | AA17: 82 | AB17: 83 | AC17: 72 | AD17: 76 | AE17: 73 | AF17: 62 | AG17: 72 | AH17: =+SUMIF('Monthly Detail'!$4:$4, $B$14,'Monthly Detail'!15:15) | AI17: 80.370052 | AJ17: 59.794008 | AK17: 75.759674 | AL17: 108.72005 | AM17: 130.30784 | AN17: 113.65213 | AO17: 95.401071 | AP17: 92.036778 | AQ17: 76.462454 | AR17: 91.23361 | AS17: 85.852884 | AT17: 94.608295 | AU17: =+AH17-S17 | AV17: =+AH17-AS17
C18: # of Active Clients | D18: 165.87294 | E18: 50.532061 | F18: 52.404372 | G18: 68.511632 | H18: 57.612335 | I18: 64.019043 | J18: 70.907651 | K18: 74.152989 | L18: 92.128336 | M18: 96.681303 | N18: 97.585438 | O18: 72.731704 | P18: 79.094929 | Q18: 51.418722 | R18: 64.693458 | S18: =+SUMIF('Monthly Detail'!$4:$4, $B$14,'Monthly Detail'!16:16) | T18: 42 | U18: 46 | V18: 46 | W18: 54 | X18: 59 | Y18: 59 | Z18: 63 | AA18: 69 | AB18: 78 | AC18: 62 | AD18: 67 | AE18: 60 | AF18: 54 | AG18: 58 | AH18: =+SUMIF('Monthly Detail'!$4:$4, $B$14,'Monthly Detail'!16:16) | AI18: 65.975416 | AJ18: 55.753873 | AK18: 66.904647 | AL18: 91.99389 | AM18: 109.64928 | AN18: 98.498509 | AO18: 78.055422 | AP18: 80.843115 | AQ18: 66.904647 | AR18: 74.338497 | AS18: 78.984653 | AT18: 80.843115 | AU18: =+AH18-S18 | AV18: =+AH18-AS18
C19: # of Recurring Client Base | D19: 100.62958 | E19: 26.845158 | F19: 46.165756 | G19: 30.103596 | H19: 35.068378 | I19: 29.638446 | J19: 42.063861 | K19: 40.21857 | L19: 45.332991 | M19: 42.035349 | N19: 47.541624 | O19: 43.404404 | P19: 40.137725 | Q19: 27.423319 | R19: 43.128972 | S19: =+SUMIF('Monthly Detail'!$4:$4, $B$14,'Monthly Detail'!17:17) | T19: 37 | U19: 28 | V19: 28 | W19: 25 | X19: 35 | Y19: 32 | Z19: 31 | AA19: 30 | AB19: 38 | AC19: 37 | AD19: 34 | AE19: 32 | AF19: 36 | AG19: 33 | AH19: =+SUMIF('Monthly Detail'!$4:$4, $B$14,'Monthly Detail'!17:17) | AI19: 40.158949 | AJ19: 33.93714 | AK19: 40.724568 | AL19: 55.996281 | AM19: 66.743042 | AN19: 59.955614 | AO19: 47.511996 | AP19: 49.208853 | AQ19: 40.724568 | AR19: 45.24952 | AS19: 48.077615 | AT19: 49.208853 | AU19: =+AH19-S19 | AV19: =+AH19-AS19
C20: Net New Prospective Clients | D20: 19 | E20: -19 | F20: 14 | G20: 4 | H20: 15 | I20: 12 | J20: 12 | K20: 14 | L20: 31 | M20: 30 | N20: 21 | O20: 11 | P20: 8 | Q20: -12 | R20: 12 | S20: =+SUMIF('Monthly Detail'!$4:$4, $B$14,'Monthly Detail'!18:18) | T20: -23 | U20: -20 | V20: -20 | W20: 8 | X20: 5 | Y20: 0 | Z20: 4 | AA20: 6 | AB20: 9 | AC20: -15 | AD20: 5 | AE20: -7 | AF20: -6 | AG20: 3 | AH20: =+SUMIF('Monthly Detail'!$4:$4, $B$14,'Monthly Detail'!18:18) | AI20: 9 | AJ20: -11 | AK20: 12 | AL20: 27 | AM20: 19 | AN20: -12 | AO20: -22 | AP20: 3 | AQ20: -15 | AR20: 8 | AS20: 5 | AT20: 2 | AU20: =+AH20-S20 | AV20: =+AH20-AS20
C21: # of Anticipated Appointments | D21: 283.23352 | E21: 61.120073 | F21: 65.670948 | G21: 88.973898 | H21: 72.954254 | I21: 81.803715 | J21: 89.247965 | K21: 92.278227 | L21: 114.05627 | M21: 120.85285 | N21: 118.4458 | O21: 93.836718 | P21: 96.266988 | Q21: 65.510346 | R21: 85.463765 | S21: =+SUMIF('Monthly Detail'!$4:$4, $B$14,'Monthly Detail'!21:21) | T21: 52 | U21: 55 | V21: 55 | W21: 66 | X21: 70 | Y21: 74 | Z21: 72 | AA21: 90 | AB21: 90 | AC21: 77 | AD21: 88 | AE21: 84 | AF21: 68 | AG21: 76 | AH21: =+SUMIF('Monthly Detail'!$4:$4, $B$14,'Monthly Detail'!21:21) | AI21: 87.112253 | AJ21: 67.831014 | AK21: 81.739075 | AL21: 116.29602 | AM21: 141.17985 | AN21: 126.68291 | AO21: 106.76628 | AP21: 101.57688 | AQ21: 85.666132 | AR21: 98.879855 | AS21: 94.976245 | AT21: 103.19358 | AU21: =+AH21-S21 | AV21: =+AH21-AS21
C22: # of Anticipated Clients | D22: 175 | E22: 57 | F22: 57 | G22: 74 | H22: 62 | I22: 69 | J22: 75 | K22: 78 | L22: 96 | M22: 100 | N22: 101 | O22: 75 | P22: 82 | Q22: 54 | R22: 68 | S22: =+SUMIF('Monthly Detail'!$4:$4, $B$14,'Monthly Detail'!22:22) | T22: 43 | U22: 47 | V22: 47 | W22: 57 | X22: 63 | Y22: 64 | Z22: 65 | AA22: 70 | AB22: 80 | AC22: 64 | AD22: 74 | AE22: 66 | AF22: 56 | AG22: 61 | AH22: =+SUMIF('Monthly Detail'!$4:$4, $B$14,'Monthly Detail'!22:22) | AI22: 71 | AJ22: 60 | AK22: 72 | AL22: 99 | AM22: 118 | AN22: 106 | AO22: 84 | AP22: 87 | AQ22: 72 | AR22: 80 | AS22: 85 | AT22: 87 | AU22: =+AH22-S22 | AV22: =+AH22-AS22
C23: Reschedule/Cancellation Rate | D23: 0.11568339 | E23: 0.11462709 | F23: 0.10752848 | G23: 0.10860212 | H23: 0.11064502 | I23: 0.11285462 | J23: 0.09495227 | K23: 0.07969838 | L23: 0.076137126 | M23: 0.072636923 | N23: 0.07044837 | O23: 0.068644619 | P23: 0.081848082 | Q23: 0.092412217 | R23: 0.097858841 | S23: =+SUMIF('Monthly Detail'!$4:$4, $B$14,'Monthly Detail'!23:23) | T23: 0.076923077 | U23: 0.090909091 | V23: 0.090909091 | W23: 0.075757576 | X23: 0.057142857 | Y23: 0.067567568 | Z23: 0.055555556 | AA23: 0.088888889 | AB23: 0.077777778 | AC23: 0.064935065 | AD23: 0.13636364 | AE23: 0.13095238 | AF23: 0.088235294 | AG23: 0.052631579 | AH23: =+SUMIF('Monthly Detail'!$4:$4, $B$14,'Monthly Detail'!23:23) | AI23: 0.1 | AJ23: 0.1 | AK23: 0.1 | AL23: 0.1 | AM23: 0.1 | AN23: 0.1 | AO23: 0.1 | AP23: 0.1 | AQ23: 0.1 | AR23: 0.1 | AS23: 0.1 | AT23: 0.1 | AU23: =+AH23-S23 | AV23: =+AH23-AS23
C24: Client Base Growth Rate | D24: 0.1058196 | E24: -0.21043654 | F24: 0.24772314 | G24: 0.038055033 | H24: 0.25244207 | I24: 0.18553784 | J24: 0.20182459 | K24: 0.25683033 | L24: 0.46235454 | M24: 0.4011783 | N24: 0.25109536 | O24: 0.173092 | P24: 0.18052132 | Q24: -0.14302129 | R24: 0.198027 | S24: =+SUMIF('Monthly Detail'!$4:$4, $B$14,'Monthly Detail'!24:24) | T24: -0.35384615 | U24: -0.3030303 | V24: -0.3030303 | W24: 0.17391304 | X24: 0.092592593 | Y24: 0 | Z24: 0.06779661 | AA24: 0.095238095 | AB24: 0.13043478 | AC24: -0.20512821 | AD24: 0.080645161 | AE24: -0.10447761 | AF24: -0.1 | AG24: 0.074074074 | AH24: =+SUMIF('Monthly Detail'!$4:$4, $B$14,'Monthly Detail'!24:24) | AI24: 0.14516129 | AJ24: -0.15492958 | AK24: 0.2 | AL24: 0.375 | AM24: 0.19191919 | AN24: -0.10169492 | AO24: -0.20754717 | AP24: 0.035714286 | AQ24: -0.17241379 | AR24: 0.11111111 | AS24: 0.0625 | AT24: 0.023529412 | AU24: =+AH24-S24 | AV24: =+AH24-AS24
C25: Client Hit Rate | D25: 0.94784537 | E25: 0.88652739 | F25: 0.91937494 | G25: 0.92583287 | H25: 0.92923121 | I25: 0.92781222 | J25: 0.94543534 | K25: 0.95067935 | L25: 0.95967017 | M25: 0.96681303 | N25: 0.96619246 | O25: 0.96975605 | P25: 0.9645723 | Q25: 0.95219856 | R25: 0.95137439 | S25: =+SUMIF('Monthly Detail'!$4:$4, $B$14,'Monthly Detail'!25:25) | T25: 0.97674419 | U25: 0.9787234 | V25: 0.9787234 | W25: 0.94736842 | X25: 0.93650794 | Y25: 0.921875 | Z25: 0.96923077 | AA25: 0.98571429 | AB25: 0.975 | AC25: 0.96875 | AD25: 0.90540541 | AE25: 0.90909091 | AF25: 0.96428571 | AG25: 0.95081967 | AH25: =+SUMIF('Monthly Detail'!$4:$4, $B$14,'Monthly Detail'!25:25) | AI25: 0.92923121 | AJ25: 0.92923121 | AK25: 0.92923121 | AL25: 0.92923121 | AM25: 0.92923121 | AN25: 0.92923121 | AO25: 0.92923121 | AP25: 0.92923121 | AQ25: 0.92923121 | AR25: 0.92923121 | AS25: 0.92923121 | AT25: 0.92923121 | AU25: =+AH25-S25 | AV25: =+AH25-AS25
C26: Appt Multiplier | D26: 1.5464286 | E26: 1.15 | F26: 1.1546667 | G26: 1.1702703 | H26: 1.1702703 | I26: 1.1702703 | J26: 1.1702703 | K26: 1.1702703 | L26: 1.1818182 | M26: 1.1884058 | N26: 1.1538462 | O26: 1.2222222 | P26: 1.1384615 | Q26: 1.1428571 | R26: 1.2272727 | S26: =+SUMIF('Monthly Detail'!$4:$4, $B$14,'Monthly Detail'!26:26) | T26: 1.1428571 | U26: 1.0869565 | V26: 1.0869565 | W26: 1.1296296 | X26: 1.1186441 | Y26: 1.1694915 | Z26: 1.0793651 | AA26: 1.1884058 | AB26: 1.0641026 | AC26: 1.1612903 | AD26: 1.1343284 | AE26: 1.2166667 | AF26: 1.1481481 | AG26: 1.2413793 | AH26: =+SUMIF('Monthly Detail'!$4:$4, $B$14,'Monthly Detail'!26:26) | AI26: 1.2181818 | AJ26: 1.0724638 | AK26: 1.1323529 | AL26: 1.1818182 | AM26: 1.1884058 | AN26: 1.1538462 | AO26: 1.2222222 | AP26: 1.1384615 | AQ26: 1.1428571 | AR26: 1.2272727 | AS26: 1.0869565 | AT26: 1.1702703 | AU26: =+AH26-S26 | AV26: =+AH26-AS26
C27: Total Billable Hours | D27: 169.29703 | E27: 68.923205 | F27: 69.586018 | G27: 76.16827 | H27: 64.050903 | I27: 86.157521 | J27: 82.981115 | K27: 127.56519 | L27: 108.87894 | M27: 109.90112 | N27: 118.22851 | O27: 147.56455 | P27: 142.68283 | Q27: 157.74121 | R27: 173.98619 | S27: =+SUMIF('Monthly Detail'!$4:$4, $B$14,'Monthly Detail'!30:30) | T27: 48 | U27: 50 | V27: 50 | W27: 61 | X27: 66 | Y27: 143.75 | Z27: 155.5 | AA27: 170.75 | AB27: 168.75 | AC27: 135 | AD27: 146 | AE27: 150.85 | AF27: 124 | AG27: 140 | AH27: =+SUMIF('Monthly Detail'!$4:$4, $B$14,'Monthly Detail'!30:30) | AI27: 84.023237 | AJ27: 56.946675 | AK27: 75.759674 | AL27: 108.72005 | AM27: 124.64229 | AN27: 119.33473 | AO27: 95.401071 | AP27: 87.853288 | AQ27: 80.103523 | AR27: 91.23361 | AS27: 81.334311 | AT27: 99.338709 | AU27: =+AH27-S27 | AV27: =+AH27-AS27
C28: Realized / Effective Bill Rate | D28: 75.41534 | E28: 86.436561 | F28: 84.880717 | G28: 83.730254 | H28: 83.625003 | I28: 85.65042 | J28: 88.961992 | K28: 48.977397 | L28: 44.7571 | M28: 45.364762 | N28: 45.983802 | O28: 47.000307 | P28: 46.181383 | Q28: 47.304227 | R28: 47.58341 | S28: =+SUMIF('Monthly Detail'!$4:$4, $B$14,'Monthly Detail'!32:32) | T28: 80.538462 | U28: 89.795455 | V28: 89.795455 | W28: 93.212121 | X28: 96.015 | Y28: 41.146456 | Z28: 43.94745 | AA28: 42.324361 | AB28: 43.462731 | AC28: 48.163986 | AD28: 43.131105 | AE28: 44.795727 | AF28: 45.622551 | AG28: 47.851282 | AH28: =+SUMIF('Monthly Detail'!$4:$4, $B$14,'Monthly Detail'!32:32) | AI28: 83.625003 | AJ28: 83.625003 | AK28: 83.625003 | AL28: 83.625003 | AM28: 83.625003 | AN28: 83.625003 | AO28: 83.625003 | AP28: 83.625003 | AQ28: 83.625003 | AR28: 83.625003 | AS28: 83.625003 | AT28: 83.625003 | AU28: =+AH28-S28 | AV28: =+AH28-AS28
C29: Productivity Utilization | D29: 0 | E29: 0 | F29: 0 | G29: 0 | H29: 0 | I29: 0 | J29: 0 | K29: 0 | L29: 0 | M29: 0 | N29: 0 | O29: 0 | P29: 0 | Q29: 0 | R29: 0 | S29: =+SUMIF('Monthly Detail'!$4:$4, A14,'Monthly Detail'!30:30) | T29: 0 | U29: 0 | V29: 0 | W29: 0 | X29: 0 | Y29: 0 | Z29: 0 | AA29: 0 | AB29: 0 | AC29: 0 | AD29: 0 | AE29: 0 | AF29: 0 | AG29: 0 | AH29: =+SUMIF('Monthly Detail'!$4:$4, P14,'Monthly Detail'!30:30) | AI29: 0 | AJ29: 0 | AK29: 0 | AL29: 0 | AM29: 0 | AN29: 0 | AO29: 0 | AP29: 0 | AQ29: 0 | AR29: 0 | AS29: 0 | AT29: 0 | AU29: =+AH29-S29 | AV29: =+AH29-AS29
AU30: =+AH30-S30 | AV30: =+AH30-AS30
C31: Utilization % | D31: 0.00375 | E31: 0.0075 | F31: 0.00625 | G31: 0.00625 | H31: 0.00625 | I31: 0.00625 | J31: 0.00625 | K31: 0.00875 | L31: 0.0056818182 | M31: 0.0054347826 | N31: 0.00625 | O31: 0.0094318182 | P31: 0.0094318182 | Q31: 0.015251736 | R31: 0.011909554 | S31: =+SUMIF('Monthly Detail'!$4:$4, $B$14,'Monthly Detail'!46:46) | T31: 0.005952381 | U31: 0.0065789474 | V31: 0.0065789474 | W31: 0.0065789474 | X31: 0.0054347826 | Y31: 0.013020833 | Z31: 0.013611695 | AA31: 0.011831347 | AB31: 0.011551889 | AC31: 0.011160714 | AD31: 0.010915072 | AE31: 0.012300228 | AF31: 0.011363636 | AG31: 0.010567633 | AH31: =+SUMIF('Monthly Detail'!$4:$4, $B$14,'Monthly Detail'!46:46) | AI31: 0.0056818182 | AJ31: 0.005952381 | AK31: 0.005952381 | AL31: 0.0056818182 | AM31: 0.0054347826 | AN31: 0.00625 | AO31: 0.0056818182 | AP31: 0.0056818182 | AQ31: 0.005952381 | AR31: 0.0054347826 | AS31: 0.0065789474 | AT31: 0.00625 | AU31: =+AH31-S31 | AV31: =+AH31-AS31
AU32: =+AH32-S32 | AV32: =+AH32-AS32
B33: Cost of Goods Sold | AU33: =+AH33-S33 | AV33: =+AH33-AS33
B34: Software - COS | D34: 447.17994 | E34: 163.21368 | F34: 166.80002 | G34: 185.26974 | H34: 163.65417 | I34: 219.35718 | J34: 219.19167 | K34: 191.81129 | L34: 152.37539 | M34: 157.62129 | N34: 170.15145 | O34: 217.58497 | P34: 203.90093 | Q34: 228.97022 | R34: 261.82209 | S34: =+SUMIF('Monthly Detail'!$4:$4, $B$14,'Monthly Detail'!58:58) | T34: 128.31 | U34: 160.15 | V34: 160.15 | W34: 171.4 | X34: 197.3 | Y34: 202.11 | Z34: 214.54 | AA34: 247.79 | AB34: 240.23 | AC34: 182.1 | AD34: 216.6 | AE34: 205.55 | AF34: 222.12 | AG34: 282 | AH34: =+SUMIF('Monthly Detail'!$4:$4, $B$14,'Monthly Detail'!58:58) | AI34: 214.68476 | AJ34: 145.50241 | AK34: 193.57083 | AL34: 277.78671 | AM34: 318.46904 | AN34: 304.9079 | AO34: 243.75586 | AP34: 224.47079 | AQ34: 204.66964 | AR34: 233.10773 | AS34: 207.81439 | AT34: 253.81678 | AU34: =+AH34-S34 | AV34: =+AH34-AS34
B35: Materials - COGS | D35: 93.188842 | E35: 209.70961 | F35: 174.10754 | G35: 245.00488 | H35: 186.33408 | I35: 319.58204 | J35: 330.96078 | K35: 365.80507 | L35: 372.17717 | M35: 416.83871 | N35: 477.04279 | O35: 587.36947 | P35: 601.14481 | Q35: 720.04632 | R35: 780.64705 | S35: =+SUMIF('Monthly Detail'!$4:$4, $B$14,'Monthly Detail'!59:59) | T35: 28.36 | U35: 356.29 | V35: 356.29 | W35: 589.19 | X35: 249.98 | Y35: 544.29 | Z35: 810.15 | AA35: 682.78 | AB35: 754.25 | AC35: 503.73 | AD35: 588.11 | AE35: 768.16 | AF35: 893.43 | AG35: 578.51 | AH35: =+SUMIF('Monthly Detail'!$4:$4, $B$14,'Monthly Detail'!59:59) | AI35: 244.43671 | AJ35: 165.66677 | AK35: 220.39672 | AL35: 316.28361 | AM35: 362.60387 | AN35: 347.16337 | AO35: 277.53661 | AP35: 255.57893 | AQ35: 233.03366 | AR35: 265.41282 | AS35: 236.61421 | AT35: 288.99182 | AU35: =+AH35-S35 | AV35: =+AH35-AS35
B36: Contractors - COS | E36: 450 | F36: 540 | G36: 540 | H36: 600 | I36: 0 | J36: 300 | K36: 1103.4778 | L36: 448.18414 | M36: 0 | N36: 0 | O36: 998.46819 | P36: 925.24239 | Q36: 1091.1182 | R36: 1394.7929 | S36: =+SUMIF('Monthly Detail'!$4:$4, $B$14,'Monthly Detail'!60:60) | T36: 210 | U36: 432 | V36: 432 | W36: 470 | X36: 50 | Y36: 45 | Z36: 0 | AA36: 0 | AB36: 629 | AC36: 0 | AD36: 0 | AE36: 0 | AF36: 30 | AG36: 0 | AH36: =+SUMIF('Monthly Detail'!$4:$4, $B$14,'Monthly Detail'!60:60) | AI36: 0 | AJ36: 300 | AK36: 540 | AL36: 940.80078 | AM36: 1179.6343 | AN36: 980.02097 | AO36: 381.01607 | AP36: 540 | AQ36: 300 | AR36: 558.50415 | AS36: 540 | AT36: 680.08064 | AU36: =+AH36-S36 | AV36: =+AH36-AS36
B37: Total Expenses | D37: 540.36878 | E37: 822.92329 | F37: 880.90756 | G37: 970.27462 | H37: 949.98825 | I37: 538.93922 | J37: 850.15245 | K37: 1661.0942 | L37: 972.7367 | M37: 574.46 | N37: 647.19424 | O37: 1803.4226 | P37: 1730.2881 | Q37: 2040.1347 | R37: 2437.2621 | S37: =+SUM(S34:S36) | T37: 366.67 | U37: 948.44 | V37: 948.44 | W37: 1230.59 | X37: 497.28 | Y37: 791.4 | Z37: 1024.69 | AA37: 930.57 | AB37: 1623.48 | AC37: 685.83 | AD37: 804.71 | AE37: 973.71 | AF37: 1145.55 | AG37: 860.51 | AH37: =+SUM(AH34:AH36) | AI37: 459.12148 | AJ37: 611.16918 | AK37: 953.96755 | AL37: 1534.8711 | AM37: 1860.7072 | AN37: 1632.0922 | AO37: 902.30854 | AP37: 1020.0497 | AQ37: 737.7033 | AR37: 1057.0247 | AS37: 984.4286 | AT37: 1222.8892 | AU37: =+AH37-S37 | AV37: =+AH37-AS37
B38: Gross Profit | D38: 12227.224 | E38: 5290.2479 | F38: 5246.6782 | G38: 5599.334 | H38: 4576.4677 | I38: 7028.3375 | J38: 6699.3053 | K38: 4766.232 | L38: 4079.3649 | M38: 4609.5636 | N38: 5008.8337 | O38: 5486.7612 | P38: 5214.5021 | Q38: 5824.2739 | R38: 6265.7219 | S38: =+S16-S37 | T38: 3821.33 | U38: 3990.31 | V38: 3990.31 | W38: 4921.41 | X38: 6223.77 | Y38: 5709.74 | Z38: 6083.81 | AA38: 6931.18 | AB38: 6254.14 | AC38: 6201.62 | AD38: 6613.84 | AE38: 6679.64 | AF38: 5024.9 | AG38: 6137.74 | AH38: =+AH16-AH37 | AI38: 6790.5923 | AJ38: 4302.318 | AK38: 5582.7475 | AL38: 7845.7395 | AM38: 8893.7095 | AN38: 8664.3768 | AO38: 7329.1104 | AP38: 6560.1295 | AQ38: 6173.8088 | AR38: 6814.8164 | AS38: 6033.2787 | AT38: 7348.278 | AU38: =+AH38-S38 | AV38: =+AH38-AS38
B39: GP% | D39: 0.95767654 | E39: 0.8653852 | F39: 0.85623905 | G39: 0.85230861 | H39: 0.82810172 | I39: 0.92878029 | J39: 0.88738894 | K39: 0.74155751 | L39: 0.807459 | M39: 0.88918646 | N39: 0.88557443 | O39: 0.75262316 | P39: 0.75085092 | Q39: 0.74058638 | R39: 0.71995099 | S39: =+S38/S16 | T39: 0.91244747 | U39: 0.8079595 | V39: 0.8079595 | W39: 0.79996912 | X39: 0.92601156 | Y39: 0.8782675 | Z39: 0.85585004 | AA39: 0.88163322 | AB39: 0.79391237 | AC39: 0.90042323 | AD39: 0.89152732 | AE39: 0.87277336 | AF39: 0.81434903 | AG39: 0.87703926 | AH39: =+AH38/AH16 | AI39: 0.9366704 | AJ39: 0.87561397 | AK39: 0.8540601 | AL39: 0.83637834 | AM39: 0.82698204 | AN39: 0.8414901 | AO39: 0.89038238 | AP39: 0.86543198 | AQ39: 0.89326456 | AR39: 0.86572078 | AS39: 0.85972219 | AT39: 0.85732524 | AU39: =+AH39-S39 | AV39: =+AH39-AS39
AU40: =+AH40-S40 | AV40: =+AH40-AS40
B41: Expenses | AU41: =+AH41-S41 | AV41: =+AH41-AS41
B42: Owner Payroll Burden | J42: 3813.1 | K42: 1906.55 | L42: 1906.55 | M42: 2599.175 | N42: 2659.6256 | O42: 2659.6495 | P42: 2659.6762 | Q42: 2655.33 | R42: 2636.6706 | S42: =+SUMIF('Monthly Detail'!$4:$4, $B$14,'Monthly Detail'!71:71) | Y42: 739.41 | Z42: 1583.73 | AA42: 2659.62 | AB42: 2803.6 | AC42: 1219.9 | AD42: 1215.98 | AE42: 1219.9 | AF42: 982.41 | AG42: 1199.74 | AH42: =+SUMIF('Monthly Detail'!$4:$4, $B$14,'Monthly Detail'!71:71) | AJ42: 0 | AK42: 0 | AR42: 0 | AU42: =+AH42-S42 | AV42: =+AH42-AS42
B43: Travel | D43: 55 | E43: 39.48 | F43: 38.703333 | G43: 294.04 | H43: 289.01667 | I43: 293.82 | J43: 214.41 | K43: 214.41 | L43: 141.31 | M43: 114.41 | N43: 78.82 | O43: 78.82 | P43: 78.82 | Q43: 78.82 | R43: 64.41 | S43: =+SUMIF('Monthly Detail'!$4:$4, $B$14,'Monthly Detail'!78:78) | T43: 14.41 | U43: 183.38 | V43: 183.38 | W43: 28.82 | X43: 14.41 | Y43: 14.41 | Z43: 41.31 | AA43: 14.41 | AB43: 28.82 | AC43: 28.82 | AD43: 33.82 | AE43: 28.82 | AF43: 14.41 | AG43: 28.82 | AH43: =+SUMIF('Monthly Detail'!$4:$4, $B$14,'Monthly Detail'!78:78) | AI43: 242.91833 | AJ43: 242.91833 | AK43: 242.91833 | AL43: 242.91833 | AM43: 242.91833 | AN43: 242.91833 | AO43: 242.91833 | AP43: 242.91833 | AQ43: 242.91833 | AR43: 242.91833 | AS43: 242.91833 | AT43: 242.91833 | AU43: =+AH43-S43 | AV43: =+AH43-AS43
B44: Legal & Accounting Services | D44: 300 | E44: 400 | F44: 340 | G44: 340 | H44: 340 | I44: 340 | J44: 211.67 | K44: 368.33 | L44: 353.33 | M44: 330 | N44: 350 | O44: 350 | P44: 350 | Q44: 350 | R44: 350 | S44: =+SUMIF('Monthly Detail'!$4:$4, $B$14,'Monthly Detail'!82:82) | T44: 400 | U44: 330.08 | V44: 330.08 | W44: 280.5 | X44: 211.67 | Y44: 368.33 | Z44: 353.33 | AA44: 330 | AB44: 373.01 | AC44: 276.25 | AD44: 382.5 | AE44: 297.5 | AF44: 318.75 | AG44: 383.75 | AH44: =+SUMIF('Monthly Detail'!$4:$4, $B$14,'Monthly Detail'!82:82) | AI44: 340 | AJ44: 340 | AK44: 340 | AL44: 340 | AM44: 340 | AN44: 340 | AO44: 340 | AP44: 340 | AQ44: 340 | AR44: 340 | AS44: 340 | AT44: 340 | AU44: =+AH44-S44 | AV44: =+AH44-AS44
B45: Office Supplies & Software | D45: 405.49667 | E45: 505.52667 | F45: 453.46667 | G45: 392.58667 | H45: 273.60333 | I45: 190.00333 | J45: 174.52 | K45: 221.82 | L45: 103.99 | M45: 171.41 | N45: 149.99 | O45: 149.99 | P45: 149.99 | Q45: 277.13 | R45: 159.99 | S45: =+SUMIF('Monthly Detail'!$4:$4, $B$14,'Monthly Detail'!83:83) | T45: 373.8 | U45: 265.57 | V45: 265.57 | W45: 123 | X45: 174.52 | Y45: 221.82 | Z45: 103.99 | AA45: 171.41 | AB45: 149.99 | AC45: 149.99 | AD45: 165.59 | AE45: 277.13 | AF45: 159.99 | AG45: 205.51 | AH45: =+SUMIF('Monthly Detail'!$4:$4, $B$14,'Monthly Detail'!83:83) | AI45: 300.96367 | AJ45: 300.96367 | AK45: 300.96367 | AL45: 300.96367 | AM45: 300.96367 | AN45: 300.96367 | AO45: 300.96367 | AP45: 300.96367 | AQ45: 300.96367 | AR45: 300.96367 | AS45: 300.96367 | AT45: 300.96367 | AU45: =+AH45-S45 | AV45: =+AH45-AS45
B46: Bank Fees | D46: 0 | E46: 30 | F46: 33.333333 | G46: 35.103333 | H46: 20.433333 | I46: 22.1 | J46: 25 | K46: 25 | L46: 25 | M46: 25 | N46: 25 | O46: 25 | P46: 25 | Q46: 25 | R46: 15 | S46: =+SUMIF('Monthly Detail'!$4:$4, $B$14,'Monthly Detail'!84:84) | T46: 20 | U46: 25.99 | V46: 25.99 | W46: 25 | X46: 25 | Y46: 25 | Z46: 25 | AA46: 25 | AB46: 25 | AC46: 25 | AD46: 25 | AE46: 25 | AF46: 15 | AG46: 30 | AH46: =+SUMIF('Monthly Detail'!$4:$4, $B$14,'Monthly Detail'!84:84) | AI46: 22.476667 | AJ46: 22.476667 | AK46: 22.476667 | AL46: 22.476667 | AM46: 22.476667 | AN46: 22.476667 | AO46: 22.476667 | AP46: 22.476667 | AQ46: 22.476667 | AR46: 22.476667 | AS46: 22.476667 | AT46: 22.476667 | AU46: =+AH46-S46 | AV46: =+AH46-AS46
B47: Facility & Storage Rent | D47: 308.83 | E47: 1475.9433 | F47: 1372.64 | G47: 1372.64 | H47: 1372.64 | I47: 1414.26 | J47: 1853.192 | K47: 1511.95 | L47: 1536.0283 | M47: 1646.4233 | N47: 1579.79 | O47: 1497.7867 | P47: 1468.2067 | Q47: 1555.425 | R47: 1516.67 | S47: =+SUMIF('Monthly Detail'!$4:$4, $B$14,'Monthly Detail'!85:85) | T47: 1372.64 | U47: 1711.17 | V47: 1711.17 | W47: 1414.26 | X47: 1684.72 | Y47: 1374.5 | Z47: 1658.88 | AA47: 2035.01 | AB47: 1711.37 | AC47: 1507.24 | AD47: 1680.57 | AE47: 1724.48 | AF47: 1441.35 | AG47: 1761.79 | AH47: =+SUMIF('Monthly Detail'!$4:$4, $B$14,'Monthly Detail'!85:85) | AI47: 1372.64 | AJ47: 1509.904 | AK47: 1509.904 | AL47: 1509.904 | AM47: 1509.904 | AN47: 1509.904 | AO47: 1509.904 | AP47: 1509.904 | AQ47: 1509.904 | AR47: 1509.904 | AS47: 1509.904 | AT47: 1509.904 | AU47: =+AH47-S47 | AV47: =+AH47-AS47
B48: Business Insurance | D48: 0.25 | E48: 10 | F48: 127.06 | G48: 150.17333 | H48: 120.17333 | I48: 194.93 | J48: 174.54333 | K48: 174.73667 | L48: 158.35333 | M48: 271.79333 | N48: 223.40667 | O48: 220.07333 | P48: 161.68667 | Q48: 203.53333 | R48: 205.27333 | S48: =+SUMIF('Monthly Detail'!$4:$4, $B$14,'Monthly Detail'!86:86) | T48: 51.62 | U48: 196.16 | V48: 196.16 | W48: 275.89 | X48: 51.58 | Y48: 196.74 | Z48: 226.74 | AA48: 391.9 | AB48: 51.58 | AC48: 216.74 | AD48: 176.95 | AE48: 216.91 | AF48: 221.96 | AG48: 222 | AH48: =+SUMIF('Monthly Detail'!$4:$4, $B$14,'Monthly Detail'!86:86) | AI48: 132.19067 | AJ48: 132.19067 | AK48: 132.19067 | AL48: 132.19067 | AM48: 132.19067 | AN48: 132.19067 | AO48: 132.19067 | AP48: 132.19067 | AQ48: 132.19067 | AR48: 132.19067 | AS48: 132.19067 | AT48: 132.19067 | AU48: =+AH48-S48 | AV48: =+AH48-AS48
B49: Donations | D49: 399.80333 | E49: 10 | F49: 10 | G49: 10 | H49: 10 | I49: 10 | J49: 10 | K49: 10 | L49: 10 | M49: 10 | N49: 10 | O49: 10 | P49: 10 | Q49: 10 | R49: 10 | S49: =+SUMIF('Monthly Detail'!$4:$4, $B$14,'Monthly Detail'!87:87) | T49: 0 | U49: 0 | V49: 0 | W49: 0 | X49: 0 | Y49: 0 | Z49: 0 | AA49: 0 | AB49: 0 | AC49: 0 | AD49: 0 | AE49: 0 | AF49: 0 | AG49: 0 | AH49: =+SUMIF('Monthly Detail'!$4:$4, $B$14,'Monthly Detail'!87:87) | AI49: 11 | AJ49: 11 | AK49: 11 | AL49: 11 | AM49: 11 | AN49: 11 | AO49: 11 | AP49: 11 | AQ49: 11 | AR49: 11 | AS49: 11 | AT49: 11 | AU49: =+AH49-S49 | AV49: =+AH49-AS49
B50: Licenses | D50: 0 | E50: 0 | F50: 0 | G50: 0 | H50: 0 | I50: 0 | J50: 0 | K50: 0 | L50: 0 | M50: 0 | N50: 50 | O50: 0 | P50: 0 | Q50: 0 | R50: 105 | S50: =+SUMIF('Monthly Detail'!$4:$4, $B$14,'Monthly Detail'!88:88) | T50: 0 | U50: 0 | V50: 0 | W50: 0 | X50: 0 | Y50: 0 | Z50: 0 | AA50: 0 | AB50: 0 | AC50: 0 | AD50: 0 | AE50: 62.81 | AF50: 0 | AG50: 0 | AH50: =+SUMIF('Monthly Detail'!$4:$4, $B$14,'Monthly Detail'!88:88) | AI50: 0 | AJ50: 0 | AK50: 0 | AL50: 0 | AM50: 0 | AN50: 50 | AO50: 0 | AP50: 0 | AQ50: 0 | AR50: 105 | AS50: 0 | AT50: 0 | AU50: =+AH50-S50 | AV50: =+AH50-AS50
B51: Interest Paid | R51: 0 | S51: =+SUMIF('Monthly Detail'!$4:$4, $B$14,'Monthly Detail'!90:90) | AG51: 16.13 | AH51: =+SUMIF('Monthly Detail'!$4:$4, $B$14,'Monthly Detail'!90:90) | AR51: 0 | AU51: =+AH51-S51 | AV51: =+AH51-AS51
B52: Total Expenses | D52: 1469.38 | E52: =+SUM(E43:E50) | F52: 2375.2033 | G52: 2594.5433 | H52: 2425.8667 | I52: 2465.1133 | J52: =+SUM(J42:J50) | K52: 4432.7967 | L52: 4234.5617 | M52: 5168.2117 | N52: 5126.6323 | O52: 4991.3195 | P52: 4903.3795 | Q52: 5155.2383 | R52: 5063.0139 | S52: =+SUM(S42:S51) | T52: 2232.47 | U52: 2712.35 | V52: 2712.35 | W52: 2147.47 | X52: 2161.9 | Y52: 2940.21 | Z52: 3992.98 | AA52: 5627.35 | AB52: 5143.37 | AC52: 3423.94 | AD52: 3680.41 | AE52: 3852.55 | AF52: 3153.87 | AG52: 3847.74 | AH52: =+SUM(AH42:AH51) | AI52: 2422.1893 | AJ52: 2559.4533 | AK52: 2559.4533 | AL52: 2559.4533 | AM52: 2559.4533 | AN52: 2609.4533 | AO52: 2559.4533 | AP52: 2559.4533 | AQ52: 2559.4533 | AR52: 2664.4533 | AS52: 2559.4533 | AT52: 2559.4533 | AU52: =+AH52-S52 | AV52: =+AH52-AS52
B53: Net Operating Income | D53: 10757.844 | E53: =+E38-E52 | F53: 2871.4749 | G53: 3004.7906 | H53: 2150.601 | I53: 4563.2241 | J53: =+J38-J52 | K53: 333.43531 | L53: -155.1968 | M53: -558.64806 | N53: -117.79855 | O53: 495.44168 | P53: 311.12261 | Q53: 669.03558 | R53: 1202.708 | S53: =+S38-S52 | T53: 1588.86 | U53: 1277.96 | V53: 1277.96 | W53: 2773.94 | X53: 4061.87 | Y53: 2769.53 | Z53: 2090.83 | AA53: 1303.83 | AB53: 1110.77 | AC53: 2777.68 | AD53: 2933.43 | AE53: 2827.09 | AF53: 1871.03 | AG53: 2290 | AH53: =+AH38-AH52 | AI53: 4368.403 | AJ53: 1742.8647 | AK53: 3023.2942 | AL53: 5286.2862 | AM53: 6334.2562 | AN53: 6054.9235 | AO53: 4769.6571 | AP53: 4000.6762 | AQ53: 3614.3555 | AR53: 4150.363 | AS53: 3473.8253 | AT53: 4788.8247 | AU53: =+AH53-S53 | AV53: =+AH53-AS53
B54: NOI% | D54: 0.84258985 | E54: =+E53/E16 | F54: 0.46861439 | G54: 0.45737742 | H54: 0.38914651 | I54: 0.60302065 | J54: =+J53/J16 | K54: 0.051877765 | L54: -0.030719257 | M54: -0.10776341 | N54: -0.02082708 | O54: 0.067960108 | P54: 0.044799425 | Q54: 0.085071314 | R54: 0.1381949 | S54: =+S53/S16 | T54: 0.37938395 | U54: 0.25876183 | V54: 0.25876183 | W54: 0.45090052 | X54: 0.60435051 | Y54: 0.42600682 | Z54: 0.29413097 | AA54: 0.16584475 | AB54: 0.14100325 | AC54: 0.40329585 | AD54: 0.39541824 | AE54: 0.36939249 | AF54: 0.30322424 | AG54: 0.32722466 | AH54: =+AH53/AH16 | AI54: 0.60256213 | AJ54: 0.35471033 | AK54: 0.46250971 | AL54: 0.56353327 | AM54: 0.58899114 | AN54: 0.58805824 | AO54: 0.57944531 | AP54: 0.52778121 | AQ54: 0.52294714 | AR54: 0.52724172 | AS54: 0.49500858 | AT54: 0.55871325 | AU54: =+AH54-S54 | AV54: =+AH54-AS54
B55: Interest Income | D55: 0 | E55: 0 | F55: 0 | G55: 0 | H55: 0 | I55: 0 | J55: 0 | K55: 0 | L55: 0 | M55: 0 | N55: 0 | O55: 0 | P55: 0 | Q55: 0 | R55: 0 | S55: =+SUMIF('Monthly Detail'!$4:$4,#REF!, 'Monthly Detail'!105:105) | T55: 0 | U55: 0 | V55: 0 | W55: 0 | X55: 0 | Y55: 0 | Z55: 0 | AA55: 0 | AB55: 0 | AC55: 0 | AD55: 0 | AE55: 0 | AF55: 0 | AG55: 0 | AH55: =+SUMIF('Monthly Detail'!$4:$4,#REF!, 'Monthly Detail'!105:105) | AI55: 0 | AJ55: 0 | AK55: 0 | AL55: 0 | AM55: 0 | AN55: 0 | AO55: 0 | AP55: 0 | AQ55: 0 | AR55: 0 | AS55: 0 | AT55: 0 | AU55: =+AH55-S55 | AV55: =+AH55-AS55
B56: Total Other Income | D56: 0 | E56: 0 | F56: 0 | G56: 0 | H56: 0 | I56: 0 | J56: 0 | K56: 0 | L56: 0 | M56: 0 | N56: 0 | O56: 0 | P56: 0 | Q56: 3.44 | R56: 2.61 | S56: =+SUMIF('Monthly Detail'!$4:$4, $B$14,'Monthly Detail'!95:95) | T56: 0 | U56: 0 | V56: 0 | W56: 0 | X56: 0 | Y56: 0 | Z56: 0 | AA56: 0 | AB56: 0 | AC56: 0 | AD56: 0 | AE56: 3.44 | AF56: 2.61 | AG56: 1.78 | AH56: =+SUMIF('Monthly Detail'!$4:$4, $B$14,'Monthly Detail'!95:95) | AI56: 0 | AJ56: 0 | AK56: 0 | AL56: 0 | AM56: 0 | AN56: 0 | AO56: 0 | AP56: 0 | AQ56: 0 | AR56: 0 | AS56: 0 | AT56: 0 | AU56: =+AH56-S56 | AV56: =+AH56-AS56
B57: Net Other Income | D57: 0 | E57: 0 | F57: 0 | G57: 0 | H57: 0 | I57: 0 | J57: 0 | K57: 0 | L57: 0 | M57: 0 | N57: 0 | O57: 0 | P57: 0 | Q57: 3.44 | R57: 2.61 | S57: =+S56 | T57: 0 | U57: 0 | V57: 0 | W57: 0 | X57: 0 | Y57: 0 | Z57: 0 | AA57: 0 | AB57: 0 | AC57: 0 | AD57: 0 | AE57: 3.44 | AF57: 2.61 | AG57: 1.78 | AH57: =+AH56 | AI57: 0 | AJ57: 0 | AK57: 0 | AL57: 0 | AM57: 0 | AN57: 0 | AO57: 0 | AP57: 0 | AQ57: 0 | AR57: 0 | AS57: 0 | AT57: 0 | AU57: =+AH57-S57 | AV57: =+AH57-AS57
B58: Owner Personal Burden | D58: -3048.16 | E58: -3126.69 | F58: -2700 | G58: -3130 | H58: -3130 | I58: -2000 | J58: -2000 | K58: -150 | L58: -150 | M58: -150 | N58: -150 | O58: -150 | P58: -150 | Q58: -150 | R58: -4027.91 | S58: ='Monthly Detail'!AH154 | T58: -2737.77 | U58: -2394.39 | V58: -2307.56 | W58: -4112.45 | X58: -3431.58 | Y58: -1624.48 | Z58: -1148.72 | AA58: -150 | AB58: -150 | AC58: -150 | AD58: -2635.22 | AE58: -2635.22 | AF58: -4027.91 | AG58: -4027.91 | AH58: ='Monthly Detail'!AW154 | AI58: -2307.56 | AJ58: -2307.56 | AK58: -2307.56 | AL58: -2307.56 | AM58: -2307.56 | AN58: -2307.56 | AO58: -2307.56 | AP58: -2307.56 | AQ58: -2307.56 | AR58: -2307.56 | AS58: -2307.56 | AT58: -2307.56 | AU58: =+AH58-S58 | AV58: =+AH58-AS58
B59: Net Income | D59: 10757.844 | E59: 3219.2979 | F59: 2871.4749 | G59: 3004.7906 | H59: 2150.601 | I59: 4563.2241 | J59: =+J57+J53 | K59: 333.43531 | L59: -155.1968 | M59: -558.64806 | N59: -117.79855 | O59: 495.44168 | P59: 311.12261 | Q59: 672.47558 | R59: 1205.318 | S59: =+S57+S53 | T59: 1588.86 | U59: 1277.96 | V59: 1277.96 | W59: 2773.94 | X59: 4061.87 | Y59: 2769.53 | Z59: 2090.83 | AA59: 1303.83 | AB59: 1110.77 | AC59: 2777.68 | AD59: 2933.43 | AE59: 2830.53 | AF59: 1873.64 | AG59: 2291.78 | AH59: =+AH57+AH53 | AI59: 4368.403 | AJ59: 1742.8647 | AK59: 3023.2942 | AL59: 5286.2862 | AM59: 6334.2562 | AN59: 6054.9235 | AO59: 4769.6571 | AP59: 4000.6762 | AQ59: 3614.3555 | AR59: 4150.363 | AS59: 3473.8253 | AT59: 4788.8247 | AU59: =+AH59-S59 | AV59: =+AH59-AS59

Sheet People Plan
H1: =YEAR(H4) | I1: =YEAR(I4) | J1: =YEAR(J4) | K1: =YEAR(K4) | L1: =YEAR(L4) | M1: =YEAR(M4) | N1: =YEAR(N4) | O1: =YEAR(O4) | ... DK1: =YEAR(DK4)
H2: =+'Monthly Detail'!AG2 | I2: =+'Monthly Detail'!AH2 | J2: =+'Monthly Detail'!AI2 | K2: =+'Monthly Detail'!AJ2 | L2: =+'Monthly Detail'!AK2 | M2: =+'Monthly Detail'!AL2 | N2: =+'Monthly Detail'!AM2 | O2: =+'Monthly Detail'!AN2 | ... DK2: =+'Monthly Detail'!EJ2
H3: =+"Q1 "&H1 | I3: =+"Q1 "&I1 | J3: =+"Q1 "&J1 | K3: =+"Q2 "&K1 | L3: =+"Q2 "&L1 | M3: =+"Q2 "&M1 | N3: =+"Q3 "&N1 | O3: =+"Q3 "&O1 | P3: =+"Q3 "&P1 | Q3: =+"Q4 "&Q1 | R3: =+"Q4 "&R1 | S3: =+"Q4 "&S1 | T3: =+"Q1 "&T1 | U3: =+"Q1 "&U1 | V3: =+"Q1 "&V1 | W3: =+"Q2 "&W1 | X3: =+"Q2 "&X1 | Y3: =+"Q2 "&Y1 | Z3: =+"Q3 "&Z1 | AA3: =+"Q3 "&AA1 | AB3: =+"Q3 "&AB1 | AC3: =+"Q4 "&AC1 | AD3: =+"Q4 "&AD1 | AE3: =+"Q4 "&AE1 | AF3: =+"Q1 "&AF1 | AG3: =+"Q1 "&AG1 | AH3: =+"Q1 "&AH1 | AI3: =+"Q2 "&AI1 | AJ3: =+"Q2 "&AJ1 | AK3: =+"Q2 "&AK1 | AL3: =+"Q3 "&AL1 | AM3: =+"Q3 "&AM1 | AN3: =+"Q3 "&AN1 | AO3: =+"Q4 "&AO1 | AP3: =+"Q4 "&AP1 | AQ3: =+"Q4 "&AQ1 | AR3: =+"Q1 "&AR1 | AS3: =+"Q1 "&AS1 | AT3: =+"Q1 "&AT1 | AU3: =+"Q2 "&AU1 | AV3: =+"Q2 "&AV1 | AW3: =+"Q2 "&AW1 | AX3: =+"Q3 "&AX1 | AY3: =+"Q3 "&AY1 | AZ3: =+"Q3 "&AZ1 | BA3: =+"Q4 "&BA1 | BB3: =+"Q4 "&BB1 | BC3: =+"Q4 "&BC1 | BD3: =+"Q1 "&BD1 | BE3: =+"Q1 "&BE1 | BF3: =+"Q1 "&BF1 | BG3: =+"Q2 "&BG1 | BH3: =+"Q2 "&BH1 | BI3: =+"Q2 "&BI1 | BJ3: =+"Q3 "&BJ1 | BK3: =+"Q3 "&BK1 | BL3: =+"Q3 "&BL1 | BM3: =+"Q4 "&BM1 | BN3: =+"Q4 "&BN1 | BO3: =+"Q4 "&BO1 | BP3: =+"Q1 "&BP1 | BQ3: =+"Q1 "&BQ1 | BR3: =+"Q1 "&BR1 | BS3: =+"Q2 "&BS1 | BT3: =+"Q2 "&BT1 | BU3: =+"Q2 "&BU1 | BV3: =+"Q3 "&BV1 | BW3: =+"Q3 "&BW1 | BX3: =+"Q3 "&BX1 | BY3: =+"Q4 "&BY1 | BZ3: =+"Q4 "&BZ1 | CA3: =+"Q4 "&CA1 | CB3: =+"Q1 "&CB1 | CC3: =+"Q1 "&CC1 | CD3: =+"Q1 "&CD1 | CE3: =+"Q2 "&CE1 | CF3: =+"Q2 "&CF1 | CG3: =+"Q2 "&CG1 | CH3: =+"Q3 "&CH1 | CI3: =+"Q3 "&CI1 | CJ3: =+"Q3 "&CJ1 | CK3: =+"Q4 "&CK1 | CL3: =+"Q4 "&CL1 | CM3: =+"Q4 "&CM1 | CN3: =+"Q1 "&CN1 | CO3: =+"Q1 "&CO1 | CP3: =+"Q1 "&CP1 | CQ3: =+"Q2 "&CQ1 | CR3: =+"Q2 "&CR1 | CS3: =+"Q2 "&CS1 | CT3: =+"Q3 "&CT1 | CU3: =+"Q3 "&CU1 | CV3: =+"Q3 "&CV1 | CW3: =+"Q4 "&CW1 | CX3: =+"Q4 "&CX1 | CY3: =+"Q4 "&CY1 | CZ3: =+"Q1 "&CZ1 | DA3: =+"Q1 "&DA1 | DB3: =+"Q1 "&DB1 | DC3: =+"Q2 "&DC1 | DD3: =+"Q2 "&DD1 | DE3: =+"Q2 "&DE1 | DF3: =+"Q3 "&DF1 | DG3: =+"Q3 "&DG1 | DH3: =+"Q3 "&DH1 | DI3: =+"Q4 "&DI1 | DJ3: =+"Q4 "&DJ1 | DK3: =+"Q4 "&DK1
H4: 45473 | I4: =+EOMONTH(H4,1) | J4: =+EOMONTH(I4,1) | K4: =+EOMONTH(J4,1) | L4: =+EOMONTH(K4,1) | M4: =+EOMONTH(L4,1) | N4: =+EOMONTH(M4,1) | O4: =+EOMONTH(N4,1) | P4: =+EOMONTH(O4,1) | ... DK4: =+EOMONTH(DJ4,1)
G6: 45443 | H6: 45473 | I6: =+EOMONTH(H6,1) | J6: =+EOMONTH(I6,1) | K6: =+EOMONTH(J6,1) | L6: =+EOMONTH(K6,1) | M6: =+EOMONTH(L6,1) | N6: =+EOMONTH(M6,1) | O6: =+EOMONTH(N6,1) | P6: =+EOMONTH(O6,1) | ... FB6: =+EOMONTH(FA6,1)
B7: Name | C7: Position | D7: Hourly Rate | E7: Avg. Hours/Month
B8: Diamond Hurt | C8: Assistant | D8: 10 | E8: 15 | G8: 0 | H8: 765 | I8: 394 | J8: 630 | K8: 210 | L8: 475 | M8: 432 | N8: =8*75 | O8: 50 | P8: 45 | Q8: 0 | R8: 0 | S8: 0 | T8: 0 | U8: 0 | V8: 0 | W8: 30 | X8: 0 | Y8: =+$D$8*((IF(Y2="Trough",0.5*$E$8,IF(Y2="Shoulder",0.9*$E$8,1.1*$E$8)))) | Z8: =+$D$8*((IF(Z2="Trough",0.5*$E$8,IF(Z2="Shoulder",0.9*$E$8,1.1*$E$8)))) | AA8: =+$D$8*((IF(AA2="Trough",0.5*$E$8,IF(AA2="Shoulder",0.9*$E$8,1.1*$E$8)))) | AB8: =+$D$8*((IF(AB2="Trough",0.5*$E$8,IF(AB2="Shoulder",0.9*$E$8,1.1*$E$8)))) | AC8: =+$D$8*((IF(AC2="Trough",0.5*$E$8,IF(AC2="Shoulder",0.9*$E$8,1.1*$E$8)))) | AD8: =+$D$8*((IF(AD2="Trough",0.5*$E$8,IF(AD2="Shoulder",0.9*$E$8,1.1*$E$8)))) | AE8: =+$D$8*((IF(AE2="Trough",0.5*$E$8,IF(AE2="Shoulder",0.9*$E$8,1.1*$E$8)))) | AF8: =+$D$8*((IF(AF2="Trough",0.5*$E$8,IF(AF2="Shoulder",0.9*$E$8,1.1*$E$8)))) | ... FB8: =+$D$8*((IF(FB2="Trough",0.5*$E$8,IF(FB2="Shoulder",0.9*$E$8,1.1*$E$8))))
B9: New | C9: Nail Tech Sub | D9: 15 | Y9: =+IF(('Monthly Detail'!AX30-'Monthly Detail'!$B$28)>0,('Monthly Detail'!AX30-'Monthly Detail'!$B$28)*'People Plan'!$D$9, 0) | Z9: =+IF(('Monthly Detail'!AY30-'Monthly Detail'!$B$28)>0,('Monthly Detail'!AY30-'Monthly Detail'!$B$28)*'People Plan'!$D$9, 0) | AA9: =+IF(('Monthly Detail'!AZ30-'Monthly Detail'!$B$28)>0,('Monthly Detail'!AZ30-'Monthly Detail'!$B$28)*'People Plan'!$D$9, 0) | AB9: =+IF(('Monthly Detail'!BA30-'Monthly Detail'!$B$28)>0,('Monthly Detail'!BA30-'Monthly Detail'!$B$28)*'People Plan'!$D$9, 0) | AC9: =+IF(('Monthly Detail'!BB30-'Monthly Detail'!$B$28)>0,('Monthly Detail'!BB30-'Monthly Detail'!$B$28)*'People Plan'!$D$9, 0) | AD9: =+IF(('Monthly Detail'!BC30-'Monthly Detail'!$B$28)>0,('Monthly Detail'!BC30-'Monthly Detail'!$B$28)*'People Plan'!$D$9, 0) | AE9: =+IF(('Monthly Detail'!BD30-'Monthly Detail'!$B$28)>0,('Monthly Detail'!BD30-'Monthly Detail'!$B$28)*'People Plan'!$D$9, 0) | AF9: =+IF(('Monthly Detail'!BE30-'Monthly Detail'!$B$28)>0,('Monthly Detail'!BE30-'Monthly Detail'!$B$28)*'People Plan'!$D$9, 0) | ... FB9: =+IF(('Monthly Detail'!GA30-'Monthly Detail'!$B$28)>0,('Monthly Detail'!GA30-'Monthly Detail'!$B$28)*'People Plan'!$D$9, 0)
E13: Total Sub Contractors | G13: =SUM(G8:G12) | H13: =SUM(H8:H12) | I13: =SUM(I8:I12) | J13: =SUM(J8:J12) | K13: =SUM(K8:K12) | L13: =SUM(L8:L12) | M13: =SUM(M8:M12) | N13: =SUM(N8:N12) | ... FB13: =SUM(FB8:FB12)
E14: Salary
B15: Iyalonna West | C15: Owner | D15: 85 | E15: 20 | P15: 1300 | Q15: 1430 | R15: 1950 | S15: 1365 | T15: 650 | U15: 650 | V15: 715 | W15: 438.75 | X15: 650 | Y15: =+IF(Y$1<>X$1,R15*1.05, R15) | Z15: =+IF(Z$1<>Y$1,Y15*1.05, Y15) | AA15: =+IF(AA$1<>Z$1,Z15*1.05, Z15) | AB15: =+IF(AB$1<>AA$1,AA15*1.05, AA15) | AC15: =+IF(AC$1<>AB$1,AB15*1.05, AB15) | AD15: =+IF(AD$1<>AC$1,AC15*1.05, AC15) | AE15: =+IF(AE$1<>AD$1,AD15*1.05, AD15) | AF15: =+IF(AF$1<>AE$1,AE15*1.05, AE15) | AG15: =+IF(AG$1<>AF$1,AF15*1.05, AF15) | ... FB15: =+IF(FB$1<>FA$1,FA15*1.05, FA15)
E18: Total G&A Wages | G18: =SUM(G13:G17) | H18: =SUM(H14:H17) | I18: =SUM(I14:I17) | J18: =SUM(J14:J17) | K18: =SUM(K14:K17) | L18: =SUM(L14:L17) | M18: =SUM(M14:M17) | N18: =SUM(N14:N17) | O18: =SUM(O14:O17) | ... FB18: =SUM(FB14:FB17)

Sheet Holidays
B2: Holidays
B3: 43831 | C3: New Years
B4: 43850 | C4: MLK
B5: 43878 | C5: Presidents Day
B6: 43976 | C6: Memorial Day
B7: 44081 | C7: Labor Day
B8: 44016 | C8: 4th of July
B9: 44161 | C9: Thanksgiving
B10: =+B9+1 | C10: Black Friday
B11: 44189 | C11: Christmas Eve
B12: =+B11+1 | C12: Christmas
B13: =+B3+366 | C13: New Years
B14: =+B4+366 | C14: MLK
B15: =+B5+366 | C15: Presidents Day
B16: =+B6+366 | C16: Memorial Day
B17: =+B7+366 | C17: Labor Day
B18: =+B8+366 | C18: 4th of July
B19: =+B9+366 | C19: Thanksgiving
B20: =+B10+366 | C20: Black Friday
B21: =+B11+366 | C21: Christmas Eve
B22: =+B12+366 | C22: Christmas
B23: =+B13+365 | C23: New Years
B24: =+B14+365 | C24: MLK
B25: =+B15+365 | C25: Presidents Day
B26: =+B16+365 | C26: Memorial Day
B27: =+B17+365 | C27: Labor Day
B28: =+B18+365 | C28: 4th of July
B29: =+B19+365 | C29: Thanksgiving
B30: =+B20+365 | C30: Black Friday
B31: =+B21+365 | C31: Christmas Eve
B32: =+B22+365 | C32: Christmas
B33: =+B23+365 | C33: New Years
B34: =+B24+365 | C34: MLK
... B93: =+B83+365 | C93: New Years

Sheet December
A1: Student | B1: Date | C1: Hours | D1: Rate ($/hr) | E1: Coin | F1: Billed? | G1: Received payment? | H1: Topic | I1: Tip? | J1: Paid via invoice? | K1: Totals
A2: Caroline Frey | B2: Asynchronous | C2: 2 | D2: 50 | E2: 100 | F2: Yes | G2: Yes | H2: Honors College Essays | J2: Venmo for Tip | K2: 100
A3: Elle Mishler | B3: 44906 | C3: 1.25 | D3: 60 | E3: 75 | F3: Yes | G3: Yes | H3: Algebra 1 | I3: No | J3: QBA | K3: 75
A4: John Surles | B4: 44907 | C4: 1 | D4: 60 | E4: 60 | F4: Yes | G4: Yes | H4: Advanced Functions - Fundamental Therem of Algebra, Conjugate Theorem | I4: No | J4: QBA | K4: 60
A5: John Surles | B5: 44908 | C5: 1.5 | D5: 60 | E5: 90 | F5: Yes | G5: Yes | H5: Advanced Functions - Fundamental Therem of Algebra, Conjugate Theorem | I5: No | J5: QBA | K5: 90
A6: John Surles | B6: 44910 | C6: 1.5 | D6: 60 | E6: 90 | F6: Yes | G6: Yes | H6: Advanced Functions - Fundamental Therem of Algebra, Conjugate Theorem | I6: No | J6: QBA | K6: 90
A7: Leyla Aggarwal | B7: 44905 | C7: 1 | D7: 60 | E7: 60 | F7: Yes | G7: Yes | H7: Dance Private | I7: No | J7: QBA | K7: 60
A8: Rohan Skanda | B8: 44898 | C8: 1.5 | D8: 50 | E8: 75 | F8: Yes | G8: Yes | H8: AOS Integrated Math + Science | I8: No | J8: QBA | K8: 75
A9: Rohan Skanda | B9: 44900 | C9: 1.5 | D9: 50 | E9: 75 | F9: Yes | G9: Yes | H9: AOS Integrated Math + Science | I9: No | J9: QBA | K9: 75
A10: Rohan Skanda | B10: 44903 | C10: 1 | D10: 50 | E10: 50 | F10: Yes | G10: Yes | H10: AOS Integrated Math + Science | I10: No | J10: QBA | K10: 50
A11: Rohan Skanda | B11: 44906 | C11: 2 | D11: 50 | E11: 100 | F11: Yes | G11: Yes | H11: AOS Integrated Math + Science | I11: No | J11: QBA | K11: 100
A12: Rohan Skanda | B12: 44907 | C12: 1.25 | D12: 50 | E12: 62.5 | F12: Yes | G12: Yes | H12: AOS Integrated Math + Science | I12: No | J12: QBA | K12: 62.5 | XFD12: Yes
A13: Rohan Skanda | B13: 44908 | C13: 1.5 | D13: 50 | E13: 75 | F13: Yes | G13: Yes | H13: AOS Integrated Math + Science | I13: No | J13: QBA | K13: 75
A14: Rohan Skanda | B14: 44909 | C14: 0.5 | D14: 50 | E14: 25 | F14: Yes | G14: Yes | H14: AOS Integrated Math + Science | I14: No | J14: QBA | K14: 25
A15: Sophia Gonzales | B15: 44904 | C15: 2 | D15: 60 | E15: 120 | F15: Yes (billed with 11-Dec invoice) | G15: Yes | H15: Physics - Centripetal force and circular motion | I15: No | J15: QBA | K15: 0
A16: Sophia Gonzales | B16: 44906 | C16: 1.25 | D16: 60 | E16: 75 | F16: Yes | G16: Yes | H16: Physics - Energy | I16: No | J16: QBA | K16: 195
K18: =SUM(K2:K16)

Sheet November
A1: Student | B1: Date | C1: Hours | D1: Rate ($/hr) | E1: Coin | F1: Billed? | G1: Received payment? | H1: Topic | I1: Tip? | J1: Paid via invoice? | K1: Totals
A2: Abby Owen | B2: 44868 | C2: 1 | D2: 50 | E2: 50 | F2: Yes | G2: Yes | H2: Properties of logs and exponents; APERT | I2: No | J2: Yes | K2: 50 | R2: Row Labels | S2: Sum of Hours | T2: Sum of Coin
A3: Brayden Wulff | B3: 44878 | C3: 1 | D3: 60 | E3: 60 | F3: Yes | G3: Yes | H3: Math Analysis | I3: No | J3: QBA | K3: 60 | R3: Abby Owen | S3: 1 | T3: 50
A4: Brayden Wulff | B4: 44880 | C4: 1.5 | D4: 60 | E4: 90 | F4: Yes | G4: Yes | H4: Math Analysis | I4: No | J4: QBA | K4: 90 | R4: Brayden Wulff | S4: 2.5 | T4: 150
A5: Elle Mishler | B5: 44872 | C5: 1 | D5: 60 | E5: 60 | F5: Yes | G5: Yes | H5: Algebra 1 - Absolute Value Functions | I5: No | J5: QBA | K5: 60 | R5: Elle Mishler | S5: 2.5 | T5: 150
A6: Elle Mishler | B6: 44892 | C6: 1.5 | D6: 60 | E6: 90 | F6: Yes | G6: Yes | H6: Algebra 1 - Graphing, Domain, and Range | I6: No | J6: QBA | K6: 90 | R6: Emma Thacker | S6: 2.5 | T6: 150
A7: Emma Thacker | B7: 44878 | C7: 1 | D7: 60 | E7: 60 | F7: Yes | G7: Yes | H7: Algebra 2 Trig | I7: No | J7: QBA | K7: 60 | R7: Julia Cecotti | S7: 1.5 | T7: 75
A8: Emma Thacker | B8: 44884 | C8: 1.5 | D8: 60 | E8: 90 | F8: Yes | G8: Yes | H8: Algebra 2 Trig | I8: No | J8: QBA | K8: 90 | R8: Kathryn Oakford | S8: 1 | T8: 50
A9: Julia Cecotti | B9: 44875 | C9: 1.5 | D9: 50 | E9: 75 | F9: Yes | G9: Yes | H9: Precalc - rational functions, domain/range, holes, asymptotes, graphing, factoring | I9: No | J9: QBA | K9: 75 | R9: Naura Peters | S9: 0.5 | T9: 30
A10: Kathryn Oakford | B10: 44886 | C10: 1 | D10: 50 | E10: 50 | F10: Yes | G10: Yes | H10: Business Calc (College) | I10: No | J10: QBA | K10: 50 | R10: Nicolette Batori | S10: 7.5 | T10: 375
A11: Naura Peters | B11: 44877 | C11: 0.5 | D11: 60 | E11: 30 | F11: Yes | G11: Yes | H11: Dance | I11: No | J11: QBA | K11: 30 | R11: Rohan Skanda | S11: 9 | T11: 450
A12: Nicolette Batori | B12: 44871 | C12: 2 | D12: 50 | E12: 100 | F12: Yes | G12: Yes | H12: SAT Math (Calculator Section) | I12: No | J12: QBA | K12: 100 | R12: Sienna Cormier | S12: 2 | T12: 100
A13: Nicolette Batori | B13: 44873 | C13: 1 | D13: 50 | E13: 50 | F13: Yes | G13: Yes | H13: Trig Proofs | I13: No | J13: QBA | K13: 50 | R13: Sophia Gonzales | S13: 1 | T13: 60
A14: Nicolette Batori | B14: 44884 | C14: 1.5 | D14: 50 | E14: 75 | F14: Yes | G14: Yes | H14: SAT English | I14: No | J14: QBA | K14: 75 | R14: Grand Total | S14: 31 | T14: 1640
A15: Nicolette Batori | B15: 44891 | C15: 1.5 | D15: 50 | E15: 75 | F15: Yes | G15: Yes | H15: SAT Grammar | I15: No | J15: QBA | K15: 75 | L15: * Billed with 27 Nov invoice
A16: Nicolette Batori | B16: 44892 | C16: 1.5 | D16: 50 | E16: 75 | F16: Yes | G16: Yes | H16: SAT Reading Comprehension | I16: No | J16: QBA | K16: 75
A17: Rohan Skanda | B17: 44868 | C17: 1.25 | D17: 50 | E17: 62.5 | F17: Yes | G17: Yes | H17: Difference Quotient, pre-calc | I17: No | J17: Yes | K17: 62.5
A18: Rohan Skanda | B18: 44873 | C18: 1 | D18: 50 | E18: 50 | F18: Yes | G18: Yes | H18: AOS Integrated Math and Science | I18: No | J18: QBA | K18: 50
A19: Rohan Skanda | B19: 44875 | C19: 1.25 | D19: 50 | E19: 62.5 | F19: Yes | G19: Yes | H19: Physics - Position and Veloicty | I19: No | J19: QBA | K19: 62.5
A20: Rohan Skanda | B20: 44886 | C20: 1.5 | D20: 50 | E20: 75 | F20: Yes | G20: Yes | H20: AOS Integrated Math and Science | I20: No | J20: QBA | K20: 75
A21: Rohan Skanda | B21: 44891 | C21: 1 | D21: 50 | E21: 50 | F21: Yes | G21: Yes | H21: AOS Integrated Math and Science | I21: No | J21: QBA | K21: 50 | L21: * Billed with 27 Nov invoice
A22: Rohan Skanda | B22: 44892 | C22: 2 | D22: 50 | E22: 100 | F22: Yes | G22: Yes | H22: AOS Integrated Math and Science | I22: No | J22: QBA | K22: 100
A23: Rohan Skanda | B23: 44893 | C23: 1 | D23: 50 | E23: 50 | F23: Yes | G23: Yes | H23: AOS Integrated Math and Science | I23: No | J23: QBA | K23: 50
A24: Sienna Cormier | B24: 44895 | C24: 2 | D24: 50 | E24: 100 | F24: Yes | G24: Yes | H24: Chemistry | I24: No | J24: QBA | K24: 100
A25: Sophia Gonzales | B25: 44886 | C25: 1 | D25: 60 | E25: 60 | F25: Yes | G25: Yes | H25: Physics - Angles, Motion | J25: QBA | K25: 60
A27: MONTH GROSS | K27: =SUM(K2:K25)

Sheet River
A1: DATE | B1: TIME | C1: MONEY
A2: 44825 | B2: 0.75 | C2: =B2*50 | E2: TOTAL EARNINGS FOR THIS PD: | I2: Paying through ESTINSTITUTE venmo. Should get tax forms from them.
A3: 44826 | B3: 1 | C3: 50 | E3: =C14+C15 | I3: Made xfer of total - venmo tax removal to ensure everything would be viewable on NFCU
A4: 44833 | B4: 2 | C4: 100
A5: 44836 | B5: 1.75 | C5: 87.5
A6: 44837 | B6: 0.75 | C6: 37.5
A7: 44838 | B7: 1.25 | C7: 62.5
A8: 44839 | B8: 1.5 | C8: 75
A9: 44846 | B9: 1.5 | C9: 75
A10: 44850 | B10: 1.5 | C10: 75
A12: Total | B12: =SUM(B2:B10) | C12: =B12*50
A14: BILLED | B14: 12 | C14: 600
A15: TIP | C15: 100
A16: BALANCE | B16: 0 | C16: 0
A18: DATE | B18: TIME | C18: MONEY
A19: 44852 | B19: 1 | C19: 50
A20: 44858 | B20: 1 | C20: 50
A21: 44859 | B21: 1 | C21: 50
A22: 44861 | B22: 2.5 | C22: 125
A23: 44862 | B23: 1 | C23: 50
A24: 44871 | B24: 1.5 | C24: 75
A25: 44872 | B25: 2 | C25: 100
A26: 44872 | B26: 1 | C26: 50
A27: 44872 | B27: 2 | C27: 100
A28: 44872 | B28: 1 | C28: 50
A29: 44873 | B29: 1.5 | C29: 75
A30: 44886 | B30: 1.5 | C30: 75
... A33: 44893 | B33: 1 | C33: 50
A34: Total | B34: =SUM(B19:B33) | C34: =B34*50
A36: BILLED | B36: 14 | C36: 700
A37: TIP | C37: 100
A38: BALANCE | C38: 300
A40: DATE | B40: TIME | C40: MONEY
