Workbook

Sheet 1

Sheet Annual Summary
D17: 2023 | E17: =+D17+1 -> 2024 | F17: =+E17+1 -> 2025 | G17: =+F17+1 -> 2026 | H17: =+G17+1 -> 2027 | I17: =+H17+1 -> 2028 | J17: =+I17+1 -> 2029 | K17: =+J17+1 -> 2030
C19: Service Income | D19: =SUMIF('Monthly Detail'!$1:$1,'Annual Summary'!D$17, 'Monthly Detail'!9:9) -> 0 | E19: =SUMIF('Monthly Detail'!$1:$1,'Annual Summary'!E$17, 'Monthly Detail'!9:9) -> 79769.25 | F19: =SUMIF('Monthly Detail'!$1:$1,'Annual Summary'!F$17, 'Monthly Detail'!9:9) -> 83940.526 | G19: =SUMIF('Monthly Detail'!$1:$1,'Annual Summary'!G$17, 'Monthly Detail'!9:9) -> 109871.85 | H19: =SUMIF('Monthly Detail'!$1:$1,'Annual Summary'!H$17, 'Monthly Detail'!9:9) -> 121228.95 | I19: =SUMIF('Monthly Detail'!$1:$1,'Annual Summary'!I$17, 'Monthly Detail'!9:9) -> 130035.95 | J19: =SUMIF('Monthly Detail'!$1:$1,'Annual Summary'!J$17, 'Monthly Detail'!9:9) -> 141575.52 | K19: =SUMIF('Monthly Detail'!$1:$1,'Annual Summary'!K$17, 'Monthly Detail'!9:9) -> 153006.67
C20: Misc | D20: =SUMIF('Monthly Detail'!$1:$1,'Annual Summary'!D$17, 'Monthly Detail'!12:12) -> 0 | E20: =SUMIF('Monthly Detail'!$1:$1,'Annual Summary'!E$17, 'Monthly Detail'!12:12) -> 0 | F20: =SUMIF('Monthly Detail'!$1:$1,'Annual Summary'!F$17, 'Monthly Detail'!12:12) -> 0 | G20: =SUMIF('Monthly Detail'!$1:$1,'Annual Summary'!G$17, 'Monthly Detail'!12:12) -> 0 | H20: =SUMIF('Monthly Detail'!$1:$1,'Annual Summary'!H$17, 'Monthly Detail'!12:12) -> 0 | I20: =SUMIF('Monthly Detail'!$1:$1,'Annual Summary'!I$17, 'Monthly Detail'!12:12) -> 0 | J20: =SUMIF('Monthly Detail'!$1:$1,'Annual Summary'!J$17, 'Monthly Detail'!12:12) -> 0 | K20: =SUMIF('Monthly Detail'!$1:$1,'Annual Summary'!K$17, 'Monthly Detail'!12:12) -> 0
C21: Total Income | D21: =SUM(D19:D20) -> 0 | E21: =SUM(E19:E20) -> 79769.25 | F21: =SUM(F19:F20) -> 83940.526 | G21: =SUM(G19:G20) -> 109871.85 | H21: =SUM(H19:H20) -> 121228.95 | I21: =SUM(I19:I20) -> 130035.95 | J21: =SUM(J19:J20) -> 141575.52 | K21: =SUM(K19:K20) -> 153006.67
C22: # of Appointments | D22: =SUMIF('Monthly Detail'!$1:$1,'Annual Summary'!D$17, 'Monthly Detail'!15:15) -> 1088 | E22: =SUMIF('Monthly Detail'!$1:$1,'Annual Summary'!E$17, 'Monthly Detail'!15:15) -> 833 | F22: =SUMIF('Monthly Detail'!$1:$1,'Annual Summary'!F$17, 'Monthly Detail'!15:15) -> 831.12105 | G22: =SUMIF('Monthly Detail'!$1:$1,'Annual Summary'!G$17, 'Monthly Detail'!15:15) -> 973.77711 | H22: =SUMIF('Monthly Detail'!$1:$1,'Annual Summary'!H$17, 'Monthly Detail'!15:15) -> 1022.363 | I22: =SUMIF('Monthly Detail'!$1:$1,'Annual Summary'!I$17, 'Monthly Detail'!15:15) -> 1047.1866 | J22: =SUMIF('Monthly Detail'!$1:$1,'Annual Summary'!J$17, 'Monthly Detail'!15:15) -> 1082.9691 | K22: =SUMIF('Monthly Detail'!$1:$1,'Annual Summary'!K$17, 'Monthly Detail'!15:15) -> 1115.3786
C23: MRR | D23: =AVERAGEIF('Monthly Detail'!$1:$1,'Annual Summary'!D$17, 'Monthly Detail'!41:41) -> 0 | E23: =AVERAGEIF('Monthly Detail'!$1:$1,'Annual Summary'!E$17, 'Monthly Detail'!41:41) -> 3744.252 | F23: =AVERAGEIF('Monthly Detail'!$1:$1,'Annual Summary'!F$17, 'Monthly Detail'!41:41) -> 4353.5441 | G23: =AVERAGEIF('Monthly Detail'!$1:$1,'Annual Summary'!G$17, 'Monthly Detail'!41:41) -> 5969.5711 | H23: =AVERAGEIF('Monthly Detail'!$1:$1,'Annual Summary'!H$17, 'Monthly Detail'!41:41) -> 6583.9447 | I23: =AVERAGEIF('Monthly Detail'!$1:$1,'Annual Summary'!I$17, 'Monthly Detail'!41:41) -> 7060.2912 | J23: =AVERAGEIF('Monthly Detail'!$1:$1,'Annual Summary'!J$17, 'Monthly Detail'!41:41) -> 7689.7926 | K23: =AVERAGEIF('Monthly Detail'!$1:$1,'Annual Summary'!K$17, 'Monthly Detail'!41:41) -> 8311.1904
C24: Recurring Client Base | D24: =AVERAGEIF('Monthly Detail'!$1:$1,'Annual Summary'!D$17, 'Monthly Detail'!17:17) -> 72.75 | E24: =AVERAGEIF('Monthly Detail'!$1:$1,'Annual Summary'!E$17, 'Monthly Detail'!17:17) -> 29.333333 | F24: =AVERAGEIF('Monthly Detail'!$1:$1,'Annual Summary'!F$17, 'Monthly Detail'!17:17) -> 32.784416 | G24: =AVERAGEIF('Monthly Detail'!$1:$1,'Annual Summary'!G$17, 'Monthly Detail'!17:17) -> 40.304436 | H24: =AVERAGEIF('Monthly Detail'!$1:$1,'Annual Summary'!H$17, 'Monthly Detail'!17:17) -> 42.321899 | I24: =AVERAGEIF('Monthly Detail'!$1:$1,'Annual Summary'!I$17, 'Monthly Detail'!17:17) -> 43.353047 | J24: =AVERAGEIF('Monthly Detail'!$1:$1,'Annual Summary'!J$17, 'Monthly Detail'!17:17) -> 44.832521 | K24: =AVERAGEIF('Monthly Detail'!$1:$1,'Annual Summary'!K$17, 'Monthly Detail'!17:17) -> 46.177496
C25: YOY Compounded Growth % | E25: - | F25: =(F21/E21)-1 -> 0.052291779 | G25: =(G21/F21)-1 -> 0.30892494 | H25: =(H21/G21)-1 -> 0.10336682 | I25: =(I21/H21)-1 -> 0.072647622 | J25: =(J21/I21)-1 -> 0.088741423 | K25: =(K21/J21)-1 -> 0.080742435
C27: Materials - COGS | D27: =SUMIF('Monthly Detail'!$1:$1,'Annual Summary'!D$17, 'Monthly Detail'!58:58) -> 0 | E27: =SUMIF('Monthly Detail'!$1:$1,'Annual Summary'!E$17, 'Monthly Detail'!58:58) -> 2199.12 | F27: =SUMIF('Monthly Detail'!$1:$1,'Annual Summary'!F$17, 'Monthly Detail'!58:58) -> 2612.3259 | G27: =SUMIF('Monthly Detail'!$1:$1,'Annual Summary'!G$17, 'Monthly Detail'!58:58) -> 3466.1347 | H27: =SUMIF('Monthly Detail'!$1:$1,'Annual Summary'!H$17, 'Monthly Detail'!58:58) -> 3824.418 | I27: =SUMIF('Monthly Detail'!$1:$1,'Annual Summary'!I$17, 'Monthly Detail'!58:58) -> 4102.2529 | J27: =SUMIF('Monthly Detail'!$1:$1,'Annual Summary'!J$17, 'Monthly Detail'!58:58) -> 4466.2926 | K27: =SUMIF('Monthly Detail'!$1:$1,'Annual Summary'!K$17, 'Monthly Detail'!58:58) -> 4826.9119
C28: Software - COS | D28: =SUMIF('Monthly Detail'!$1:$1,'Annual Summary'!D$17, 'Monthly Detail'!59:59) -> 0 | E28: =SUMIF('Monthly Detail'!$1:$1,'Annual Summary'!E$17, 'Monthly Detail'!59:59) -> 3885.61 | F28: =SUMIF('Monthly Detail'!$1:$1,'Annual Summary'!F$17, 'Monthly Detail'!59:59) -> 7219.8394 | G28: =SUMIF('Monthly Detail'!$1:$1,'Annual Summary'!G$17, 'Monthly Detail'!59:59) -> 10547.417 | H28: =SUMIF('Monthly Detail'!$1:$1,'Annual Summary'!H$17, 'Monthly Detail'!59:59) -> 11637.67 | I28: =SUMIF('Monthly Detail'!$1:$1,'Annual Summary'!I$17, 'Monthly Detail'!59:59) -> 12483.119 | J28: =SUMIF('Monthly Detail'!$1:$1,'Annual Summary'!J$17, 'Monthly Detail'!59:59) -> 13590.889 | K28: =SUMIF('Monthly Detail'!$1:$1,'Annual Summary'!K$17, 'Monthly Detail'!59:59) -> 14688.25
C29: Contractors - COS | D29: =SUMIF('Monthly Detail'!$1:$1,'Annual Summary'!D$17, 'Monthly Detail'!60:60) -> 0 | E29: =SUMIF('Monthly Detail'!$1:$1,'Annual Summary'!E$17, 'Monthly Detail'!60:60) -> 4126 | F29: =SUMIF('Monthly Detail'!$1:$1,'Annual Summary'!F$17, 'Monthly Detail'!60:60) -> 2010.0674 | G29: =SUMIF('Monthly Detail'!$1:$1,'Annual Summary'!G$17, 'Monthly Detail'!60:60) -> 16122.451 | H29: =SUMIF('Monthly Detail'!$1:$1,'Annual Summary'!H$17, 'Monthly Detail'!60:60) -> 17685.97 | I29: =SUMIF('Monthly Detail'!$1:$1,'Annual Summary'!I$17, 'Monthly Detail'!60:60) -> 18383.214 | J29: =SUMIF('Monthly Detail'!$1:$1,'Annual Summary'!J$17, 'Monthly Detail'!60:60) -> 19601.658 | K29: =SUMIF('Monthly Detail'!$1:$1,'Annual Summary'!K$17, 'Monthly Detail'!60:60) -> 20604.203
C30: Total Cost of Goods Sold (COGS) | D30: =SUM(D27:D29) -> 0 | E30: =SUM(E27:E29) -> 10210.73 | F30: =SUM(F27:F29) -> 11842.233 | G30: =SUM(G27:G29) -> 30136.003 | H30: =SUM(H27:H29) -> 33148.057 | I30: =SUM(I27:I29) -> 34968.585 | J30: =SUM(J27:J29) -> 37658.839 | K30: =SUM(K27:K29) -> 40119.364
C32: Gross Margin | D32: =D21-D30 -> 0 | E32: =E21-E30 -> 69558.52 | F32: =F21-F30 -> 72098.293 | G32: =G21-G30 -> 79735.845 | H32: =H21-H30 -> 88080.895 | I32: =I21-I30 -> 95067.362 | J32: =J21-J30 -> 103916.68 | K32: =K21-K30 -> 112887.31
C33: GM % | D33: =+D32/D21 -> #DIV/0! | E33: =+E32/E21 -> 0.87199667 | F33: =+F32/F21 -> 0.85892115 | G33: =+G32/G21 -> 0.72571679 | H33: =+H32/H21 -> 0.72656649 | I33: =+I32/I21 -> 0.73108524 | J33: =+J32/J21 -> 0.73400177 | K33: =+K32/K21 -> 0.73779337
C35: General & Admintrative Expenses | D35: =SUMIF('Monthly Detail'!$1:$1,'Annual Summary'!D$17, 'Monthly Detail'!$89:$89) -> 0 | E35: =SUMIF('Monthly Detail'!$1:$1,'Annual Summary'!E$17, 'Monthly Detail'!$89:$89)+SUMIF('Monthly Detail'!$1:$1,'Annual Summary'!E$17, 'Monthly Detail'!$90:$90) -> 22587.09 | F35: =SUMIF('Monthly Detail'!$1:$1,'Annual Summary'!F$17, 'Monthly Detail'!$89:$89)+SUMIF('Monthly Detail'!$1:$1,'Annual Summary'!F$17, 'Monthly Detail'!$90:$90) -> 46291.585 | G35: =SUMIF('Monthly Detail'!$1:$1,'Annual Summary'!G$17, 'Monthly Detail'!$89:$89)+SUMIF('Monthly Detail'!$1:$1,'Annual Summary'!G$17, 'Monthly Detail'!$90:$90) -> 64715.343 | H35: =SUMIF('Monthly Detail'!$1:$1,'Annual Summary'!H$17, 'Monthly Detail'!$89:$89)+SUMIF('Monthly Detail'!$1:$1,'Annual Summary'!H$17, 'Monthly Detail'!$90:$90) -> 69186.591 | I35: =SUMIF('Monthly Detail'!$1:$1,'Annual Summary'!I$17, 'Monthly Detail'!$89:$89)+SUMIF('Monthly Detail'!$1:$1,'Annual Summary'!I$17, 'Monthly Detail'!$90:$90) -> 74038.641 | J35: =SUMIF('Monthly Detail'!$1:$1,'Annual Summary'!J$17, 'Monthly Detail'!$89:$89) -> 79306.258 | K35: =SUMIF('Monthly Detail'!$1:$1,'Annual Summary'!K$17, 'Monthly Detail'!$89:$89) -> 85027.516
C36: Operating Expense | D36: =SUM(D35:D35) -> 0 | E36: =SUM(E35:E35) -> 22587.09 | F36: =SUM(F35:F35) -> 46291.585 | G36: =SUM(G35:G35) -> 64715.343 | H36: =SUM(H35:H35) -> 69186.591 | I36: =SUM(I35:I35) -> 74038.641 | J36: =SUM(J35:J35) -> 79306.258 | K36: =SUM(K35:K35) -> 85027.516
C38: Net Operating Income (EBITDA) | D38: =D32-D36 -> 0 | E38: =E32-E36 -> 46971.43 | F38: =F32-F36 -> 25806.708 | G38: =G32-G36 -> 15020.503 | H38: =H32-H36 -> 18894.304 | I38: =I32-I36 -> 21028.72 | J38: =J32-J36 -> 24610.425 | K38: =K32-K36 -> 27859.794
C39: EBITDA % | D39: =D38/D21 -> #DIV/0! | E39: =E38/E21 -> 0.58884131 | F39: =F38/F21 -> 0.3074404 | G39: =G38/G21 -> 0.13670929 | H39: =H38/H21 -> 0.15585636 | I39: =I38/I21 -> 0.16171467 | J39: =J38/J21 -> 0.17383249 | K39: =K38/K21 -> 0.18208222
C41: Other Income / (Expense) | D41: =SUMIF('Monthly Detail'!$1:$1,'Annual Summary'!D$17, 'Monthly Detail'!95:95) -> 0 | E41: =SUMIF('Monthly Detail'!$1:$1,'Annual Summary'!E$17, 'Monthly Detail'!95:95) -> 0 | F41: =SUMIF('Monthly Detail'!$1:$1,'Annual Summary'!F$17, 'Monthly Detail'!95:95) -> 29.4 | G41: =SUMIF('Monthly Detail'!$1:$1,'Annual Summary'!G$17, 'Monthly Detail'!95:95) -> 21.36 | H41: =SUMIF('Monthly Detail'!$1:$1,'Annual Summary'!H$17, 'Monthly Detail'!95:95) -> 21.36 | I41: =SUMIF('Monthly Detail'!$1:$1,'Annual Summary'!I$17, 'Monthly Detail'!95:95) -> 21.36 | J41: =SUMIF('Monthly Detail'!$1:$1,'Annual Summary'!J$17, 'Monthly Detail'!95:95) -> 21.36 | K41: =SUMIF('Monthly Detail'!$1:$1,'Annual Summary'!K$17, 'Monthly Detail'!95:95) -> 21.36
C42: Net Income | D42: =D38+D41 -> 0 | E42: =E38+E41 -> 46971.43 | F42: =F38+F41 -> 25836.108 | G42: =G38+G41 -> 15041.863 | H42: =H38+H41 -> 18915.664 | I42: =I38+I41 -> 21050.08 | J42: =J38+J41 -> 24631.785 | K42: =K38+K41 -> 27881.154
C43: NI % | D43: =D42/D21 -> #DIV/0! | E43: =E42/E21 -> 0.58884131 | F43: =F42/F21 -> 0.30779064 | G43: =G42/G21 -> 0.1369037 | H43: =H42/H21 -> 0.15603256 | I43: =I42/I21 -> 0.16187893 | J43: =J42/J21 -> 0.17398336 | K43: =K42/K21 -> 0.18222182
C44: Estimated Tax Burden | D44: =+IF(D42>0, D42*0.25, 0) -> 0 | E44: =+IF(E42>0, E42*0.25, 0) -> 11742.858 | F44: =+IF(F42>0, F42*0.25, 0) -> 6459.0271 | G44: =+IF(G42>0, G42*0.25, 0) -> 3760.4657 | H44: =+IF(H42>0, H42*0.25, 0) -> 4728.9159 | I44: =+IF(I42>0, I42*0.25, 0) -> 5262.5201 | J44: =+IF(J42>0, J42*0.25, 0) -> 6157.9462 | K44: =+IF(K42>0, K42*0.25, 0) -> 6970.2886
C45: Cash Balance | D45: #VALUE! | E45: =+SUMIF('Monthly Detail'!$4:$4, DATE(E17, 12, 31),'Monthly Detail'!$173:$173) -> 1426 | F45: =+SUMIF('Monthly Detail'!$4:$4, DATE(F17, 12, 31),'Monthly Detail'!$173:$173) -> 6984.8443 | G45: =+SUMIF('Monthly Detail'!$4:$4, DATE(G17, 12, 31),'Monthly Detail'!$173:$173) -> 20154.649 | H45: =+SUMIF('Monthly Detail'!$4:$4, DATE(H17, 12, 31),'Monthly Detail'!$173:$173) -> 37243.866 | I45: =+SUMIF('Monthly Detail'!$4:$4, DATE(I17, 12, 31),'Monthly Detail'!$173:$173) -> 56498.005 | J45: =+SUMIF('Monthly Detail'!$4:$4, DATE(J17, 12, 31),'Monthly Detail'!$173:$173) -> 79302.154 | K45: =+SUMIF('Monthly Detail'!$4:$4, DATE(K17, 12, 31),'Monthly Detail'!$173:$173) -> 105334.86

Sheet 2023 Overview
C10: =TEXT('Monthly Detail'!D4,"mmmm") -> January | D10: =TEXT('Monthly Detail'!E4,"mmmm") -> February | E10: =TEXT('Monthly Detail'!F4,"mmmm") -> March | F10: =TEXT('Monthly Detail'!G4,"mmmm") -> April | G10: =TEXT('Monthly Detail'!H4,"mmmm") -> May | H10: =TEXT('Monthly Detail'!I4,"mmmm") -> June | I10: =TEXT('Monthly Detail'!J4,"mmmm") -> July | J10: =TEXT('Monthly Detail'!K4,"mmmm") -> August | ... N10: =TEXT('Monthly Detail'!O4,"mmmm") -> December | P10: Total
C11: 44957 | D11: 44985 | E11: 45016 | F11: 45046 | G11: 45077 | H11: 45107 | I11: 45138 | J11: 45169 | K11: 45199 | L11: 45230 | M11: 45260 | N11: 45291 | O11: 45322
B12: Service Income | C12: =SUMIF('Monthly Detail'!$4:$4, '2023 Overview'!C$11, 'Monthly Detail'!9:9) -> 0 | D12: =SUMIF('Monthly Detail'!$4:$4, '2023 Overview'!D$11, 'Monthly Detail'!9:9) -> 0 | E12: =SUMIF('Monthly Detail'!$4:$4, '2023 Overview'!E$11, 'Monthly Detail'!9:9) -> 0 | F12: =SUMIF('Monthly Detail'!$4:$4, '2023 Overview'!F$11, 'Monthly Detail'!9:9) -> 0 | G12: =SUMIF('Monthly Detail'!$4:$4, '2023 Overview'!G$11, 'Monthly Detail'!9:9) -> 0 | H12: =SUMIF('Monthly Detail'!$4:$4, '2023 Overview'!H$11, 'Monthly Detail'!9:9) -> 0 | I12: =SUMIF('Monthly Detail'!$4:$4, '2023 Overview'!I$11, 'Monthly Detail'!9:9) -> 0 | J12: =SUMIF('Monthly Detail'!$4:$4, '2023 Overview'!J$11, 'Monthly Detail'!9:9) -> 0 | ... N12: =SUMIF('Monthly Detail'!$4:$4, '2023 Overview'!N$11, 'Monthly Detail'!9:9) -> 0 | P12: =SUM(C12:O12) -> 0
B13: Misc. | C13: =SUMIF('Monthly Detail'!$4:$4, '2023 Overview'!C$11, 'Monthly Detail'!12:12) -> 0 | D13: =SUMIF('Monthly Detail'!$4:$4, '2023 Overview'!D$11, 'Monthly Detail'!12:12) -> 0 | E13: =SUMIF('Monthly Detail'!$4:$4, '2023 Overview'!E$11, 'Monthly Detail'!12:12) -> 0 | F13: =SUMIF('Monthly Detail'!$4:$4, '2023 Overview'!F$11, 'Monthly Detail'!12:12) -> 0 | G13: =SUMIF('Monthly Detail'!$4:$4, '2023 Overview'!G$11, 'Monthly Detail'!12:12) -> 0 | H13: =SUMIF('Monthly Detail'!$4:$4, '2023 Overview'!H$11, 'Monthly Detail'!12:12) -> 0 | I13: =SUMIF('Monthly Detail'!$4:$4, '2023 Overview'!I$11, 'Monthly Detail'!12:12) -> 0 | J13: =SUMIF('Monthly Detail'!$4:$4, '2023 Overview'!J$11, 'Monthly Detail'!12:12) -> 0 | ... N13: =SUMIF('Monthly Detail'!$4:$4, '2023 Overview'!N$11, 'Monthly Detail'!12:12) -> 0
B14: Total Income | C14: =SUM(C12:C13) -> 0 | D14: =SUM(D12:D13) -> 0 | E14: =SUM(E12:E13) -> 0 | F14: =SUM(F12:F13) -> 0 | G14: =SUM(G12:G13) -> 0 | H14: =SUM(H12:H13) -> 0 | I14: =SUM(I12:I13) -> 0 | J14: =SUM(J12:J13) -> 0 | ... N14: =SUM(N12:N13) -> 0 | P14: =SUM(P12:P12) -> 0
B16: Gross Margin | C16: =C14 -> 0 | D16: =D14 -> 0 | E16: =E14 -> 0 | F16: =F14 -> 0 | G16: =G14 -> 0 | H16: =H14 -> 0 | I16: =I14 -> 0 | J16: =J14 -> 0 | ... N16: =N14 -> 0 | P16: =P14 -> 0
B17: GM % | C17: =C16/C14 -> #DIV/0! | D17: =D16/D14 -> #DIV/0! | E17: =E16/E14 -> #DIV/0! | F17: =F16/F14 -> #DIV/0! | G17: =G16/G14 -> #DIV/0! | H17: =H16/H14 -> #DIV/0! | I17: =I16/I14 -> #DIV/0! | J17: =J16/J14 -> #DIV/0! | ... N17: =N16/N14 -> #DIV/0! | P17: =P16/P14 -> #DIV/0!
B19: General & Admintrative Expenses | C19: =SUMIF('Monthly Detail'!$4:$4, '2023 Overview'!C$11, 'Monthly Detail'!$89:$89) -> 0 | D19: =SUMIF('Monthly Detail'!$4:$4, '2023 Overview'!D$11, 'Monthly Detail'!$89:$89) -> 0 | E19: =SUMIF('Monthly Detail'!$4:$4, '2023 Overview'!E$11, 'Monthly Detail'!$89:$89) -> 0 | F19: =SUMIF('Monthly Detail'!$4:$4, '2023 Overview'!F$11, 'Monthly Detail'!$89:$89) -> 0 | G19: =SUMIF('Monthly Detail'!$4:$4, '2023 Overview'!G$11, 'Monthly Detail'!$89:$89) -> 0 | H19: =SUMIF('Monthly Detail'!$4:$4, '2023 Overview'!H$11, 'Monthly Detail'!$89:$89) -> 0 | I19: =SUMIF('Monthly Detail'!$4:$4, '2023 Overview'!I$11, 'Monthly Detail'!$89:$89) -> 0 | J19: =SUMIF('Monthly Detail'!$4:$4, '2023 Overview'!J$11, 'Monthly Detail'!$89:$89) -> 0 | ... N19: =SUMIF('Monthly Detail'!$4:$4, '2023 Overview'!N$11, 'Monthly Detail'!$89:$89) -> 0 | P19: =SUM(C19:O19) -> 0
B20: Operating Expenses | C20: =SUM(C19:C19) -> 0 | D20: =SUM(D19:D19) -> 0 | E20: =SUM(E19:E19) -> 0 | F20: =SUM(F19:F19) -> 0 | G20: =SUM(G19:G19) -> 0 | H20: =SUM(H19:H19) -> 0 | I20: =SUM(I19:I19) -> 0 | J20: =SUM(J19:J19) -> 0 | ... N20: =SUM(N19:N19) -> 0 | P20: =SUM(P19:P19) -> 0
B22: Net Operating Income (EBITDA) | C22: =C16-C20 -> 0 | D22: =D16-D20 -> 0 | E22: =E16-E20 -> 0 | F22: =F16-F20 -> 0 | G22: =G16-G20 -> 0 | H22: =H16-H20 -> 0 | I22: =I16-I20 -> 0 | J22: =J16-J20 -> 0 | ... N22: =N16-N20 -> 0 | P22: =P16-P20 -> 0
B23: EBITDA % | C23: =C22/C14 -> #DIV/0! | D23: =D22/D14 -> #DIV/0! | E23: =E22/E14 -> #DIV/0! | F23: =F22/F14 -> #DIV/0! | G23: =G22/G14 -> #DIV/0! | H23: =H22/H14 -> #DIV/0! | I23: =I22/I14 -> #DIV/0! | J23: =J22/J14 -> #DIV/0! | ... N23: =N22/N14 -> #DIV/0! | P23: =P22/P14 -> #DIV/0!
B25: Other Income / (Expense) | C25: =SUMIF('Monthly Detail'!$4:$4, '2023 Overview'!C$11, 'Monthly Detail'!95:95) -> 0 | D25: =SUMIF('Monthly Detail'!$4:$4, '2023 Overview'!D$11, 'Monthly Detail'!95:95) -> 0 | E25: =SUMIF('Monthly Detail'!$4:$4, '2023 Overview'!E$11, 'Monthly Detail'!95:95) -> 0 | F25: =SUMIF('Monthly Detail'!$4:$4, '2023 Overview'!F$11, 'Monthly Detail'!95:95) -> 0 | G25: =SUMIF('Monthly Detail'!$4:$4, '2023 Overview'!G$11, 'Monthly Detail'!95:95) -> 0 | H25: =SUMIF('Monthly Detail'!$4:$4, '2023 Overview'!H$11, 'Monthly Detail'!95:95) -> 0 | I25: =SUMIF('Monthly Detail'!$4:$4, '2023 Overview'!I$11, 'Monthly Detail'!95:95) -> 0 | J25: =SUMIF('Monthly Detail'!$4:$4, '2023 Overview'!J$11, 'Monthly Detail'!95:95) -> 0 | ... N25: =SUMIF('Monthly Detail'!$4:$4, '2023 Overview'!N$11, 'Monthly Detail'!95:95) -> 0 | P25: =SUM(C25:O25) -> 0
B26: Net Income | C26: =C22+SUM(C25:C25) -> 0 | D26: =D22+SUM(D25:D25) -> 0 | E26: =E22+SUM(E25:E25) -> 0 | F26: =F22+SUM(F25:F25) -> 0 | G26: =G22+SUM(G25:G25) -> 0 | H26: =H22+SUM(H25:H25) -> 0 | I26: =I22+SUM(I25:I25) -> 0 | J26: =J22+SUM(J25:J25) -> 0 | ... N26: =N22+SUM(N25:N25) -> 0 | P26: =P22+SUM(P25:P25) -> 0
B27: NI % | C27: =C26/C14 -> #DIV/0! | D27: =D26/D14 -> #DIV/0! | E27: =E26/E14 -> #DIV/0! | F27: =F26/F14 -> #DIV/0! | G27: =G26/G14 -> #DIV/0! | H27: =H26/H14 -> #DIV/0! | I27: =I26/I14 -> #DIV/0! | J27: =J26/J14 -> #DIV/0! | ... N27: =N26/N14 -> #DIV/0! | P27: =P26/P14 -> #DIV/0!
B29: Operating Cash | C29: =SUMIF('Monthly Detail'!$4:$4, '2023 Overview'!C$11, 'Monthly Detail'!173:173) -> 0 | D29: =SUMIF('Monthly Detail'!$4:$4, '2023 Overview'!D$11, 'Monthly Detail'!173:173) -> 0 | E29: =SUMIF('Monthly Detail'!$4:$4, '2023 Overview'!E$11, 'Monthly Detail'!173:173) -> 0 | F29: =SUMIF('Monthly Detail'!$4:$4, '2023 Overview'!F$11, 'Monthly Detail'!173:173) -> 0 | G29: =SUMIF('Monthly Detail'!$4:$4, '2023 Overview'!G$11, 'Monthly Detail'!173:173) -> 0 | H29: =SUMIF('Monthly Detail'!$4:$4, '2023 Overview'!H$11, 'Monthly Detail'!173:173) -> 0 | I29: =SUMIF('Monthly Detail'!$4:$4, '2023 Overview'!I$11, 'Monthly Detail'!173:173) -> 0 | J29: =SUMIF('Monthly Detail'!$4:$4, '2023 Overview'!J$11, 'Monthly Detail'!173:173) -> 0 | ... N29: =SUMIF('Monthly Detail'!$4:$4, '2023 Overview'!N$11, 'Monthly Detail'!173:173) -> 0
B30: Cash Inflow (Outflow) | C30: =SUMIF('Monthly Detail'!$4:$4, '2023 Overview'!C$11, 'Monthly Detail'!170:170) -> 0 | D30: =SUMIF('Monthly Detail'!$4:$4, '2023 Overview'!D$11, 'Monthly Detail'!170:170) -> 0 | E30: =SUMIF('Monthly Detail'!$4:$4, '2023 Overview'!E$11, 'Monthly Detail'!170:170) -> 0 | F30: =SUMIF('Monthly Detail'!$4:$4, '2023 Overview'!F$11, 'Monthly Detail'!170:170) -> 0 | G30: =SUMIF('Monthly Detail'!$4:$4, '2023 Overview'!G$11, 'Monthly Detail'!170:170) -> 0 | H30: =SUMIF('Monthly Detail'!$4:$4, '2023 Overview'!H$11, 'Monthly Detail'!170:170) -> 0 | I30: =SUMIF('Monthly Detail'!$4:$4, '2023 Overview'!I$11, 'Monthly Detail'!170:170) -> 0 | J30: =SUMIF('Monthly Detail'!$4:$4, '2023 Overview'!J$11, 'Monthly Detail'!170:170) -> 0 | ... N30: =SUMIF('Monthly Detail'!$4:$4, '2023 Overview'!N$11, 'Monthly Detail'!170:170) -> 0

Sheet 2025 Overview (Budget)
B15: 2025 Overview (Annual Operating Plan)
C18: January | D18: February | E18: March | F18: April | G18: May | H18: June | I18: July | J18: August | K18: September | L18: October | M18: November | N18: December | P18: Total
C19: 45688 | D19: 45716 | E19: 45747 | F19: 45777 | G19: 45808 | H19: 45838 | I19: 45869 | J19: 45900 | K19: 45930 | L19: 45961 | M19: 45991 | N19: 46022 | O19: 45322
B20: Service Income | C20: =SUMIF('Monthly Detail'!$4:$4, '2025 Overview (Budget)'!C$19, 'Monthly Detail'!13:13) -> 6721.05 | D20: =SUMIF('Monthly Detail'!$4:$4, '2025 Overview (Budget)'!D$19, 'Monthly Detail'!13:13) -> 6501.14 | E20: =SUMIF('Monthly Detail'!$4:$4, '2025 Overview (Budget)'!E$19, 'Monthly Detail'!13:13) -> 7108.5 | F20: =SUMIF('Monthly Detail'!$4:$4, '2025 Overview (Budget)'!F$19, 'Monthly Detail'!13:13) -> 7861.75 | G20: =SUMIF('Monthly Detail'!$4:$4, '2025 Overview (Budget)'!G$19, 'Monthly Detail'!13:13) -> 7877.62 | H20: =SUMIF('Monthly Detail'!$4:$4, '2025 Overview (Budget)'!H$19, 'Monthly Detail'!13:13) -> 6887.45 | I20: =SUMIF('Monthly Detail'!$4:$4, '2025 Overview (Budget)'!I$19, 'Monthly Detail'!13:13) -> 7418.55 | J20: =SUMIF('Monthly Detail'!$4:$4, '2025 Overview (Budget)'!J$19, 'Monthly Detail'!13:13) -> 7653.35 | ... L20: =SUMIF('Monthly Detail'!$4:$4, '2025 Overview (Budget)'!L$19, 'Monthly Detail'!13:13) -> 6998.25 | M20: =+'2025 AOP'!M20 -> 7017.7073 | N20: =+'2025 AOP'!N20 -> 8571.1673 | P20: =SUM(C20:O20) -> 86786.985
B21: Misc. | C21: =SUMIF('Monthly Detail'!$4:$4, '2025 Overview (Budget)'!C$19, 'Monthly Detail'!12:12) -> 0 | D21: =SUMIF('Monthly Detail'!$4:$4, '2025 Overview (Budget)'!D$19, 'Monthly Detail'!12:12) -> 0 | E21: =SUMIF('Monthly Detail'!$4:$4, '2025 Overview (Budget)'!E$19, 'Monthly Detail'!12:12) -> 0 | F21: =SUMIF('Monthly Detail'!$4:$4, '2025 Overview (Budget)'!F$19, 'Monthly Detail'!12:12) -> 0 | G21: =SUMIF('Monthly Detail'!$4:$4, '2025 Overview (Budget)'!G$19, 'Monthly Detail'!12:12) -> 0 | H21: =SUMIF('Monthly Detail'!$4:$4, '2025 Overview (Budget)'!H$19, 'Monthly Detail'!12:12) -> 0 | I21: =SUMIF('Monthly Detail'!$4:$4, '2025 Overview (Budget)'!I$19, 'Monthly Detail'!12:12) -> 0 | J21: =SUMIF('Monthly Detail'!$4:$4, '2025 Overview (Budget)'!J$19, 'Monthly Detail'!12:12) -> 0 | ... L21: =SUMIF('Monthly Detail'!$4:$4, '2025 Overview (Budget)'!L$19, 'Monthly Detail'!12:12) -> 0 | M21: =+'2025 AOP'!M21 -> 0 | N21: =+'2025 AOP'!N21 -> 0 | P21: =SUM(C21:O21) -> 0
B22: Total Income | C22: =SUM(C20:C21) -> 6721.05 | D22: =SUM(D20:D21) -> 6501.14 | E22: =SUM(E20:E21) -> 7108.5 | F22: =SUM(F20:F21) -> 7861.75 | G22: =SUM(G20:G21) -> 7877.62 | H22: =SUM(H20:H21) -> 6887.45 | I22: =SUM(I20:I21) -> 7418.55 | J22: =SUM(J20:J21) -> 7653.35 | ... L22: =SUM(L20:L21) -> 6998.25 | M22: =+'2025 AOP'!M22 -> 7017.7073 | N22: =+'2025 AOP'!N22 -> 8571.1673 | P22: =SUM(P20:P20) -> 86786.985
B23: # of Appointments | C23: =SUMIF('Monthly Detail'!$4:$4, '2025 Overview (Budget)'!C$19, 'Monthly Detail'!15:15) -> 66 | D23: =SUMIF('Monthly Detail'!$4:$4, '2025 Overview (Budget)'!D$19, 'Monthly Detail'!15:15) -> 69 | E23: =SUMIF('Monthly Detail'!$4:$4, '2025 Overview (Budget)'!E$19, 'Monthly Detail'!15:15) -> 68 | F23: =SUMIF('Monthly Detail'!$4:$4, '2025 Overview (Budget)'!F$19, 'Monthly Detail'!15:15) -> 82 | G23: =SUMIF('Monthly Detail'!$4:$4, '2025 Overview (Budget)'!G$19, 'Monthly Detail'!15:15) -> 83 | H23: =SUMIF('Monthly Detail'!$4:$4, '2025 Overview (Budget)'!H$19, 'Monthly Detail'!15:15) -> 72 | I23: =SUMIF('Monthly Detail'!$4:$4, '2025 Overview (Budget)'!I$19, 'Monthly Detail'!15:15) -> 76 | J23: =SUMIF('Monthly Detail'!$4:$4, '2025 Overview (Budget)'!J$19, 'Monthly Detail'!15:15) -> 73 | ... L23: =SUMIF('Monthly Detail'!$4:$4, '2025 Overview (Budget)'!L$19, 'Monthly Detail'!15:15) -> 72 | M23: =+'2025 AOP'!M23 -> 85.852884 | N23: =+'2025 AOP'!N23 -> 94.608295 | P23: =+SUM(C23:N23) -> 903.46118
B24: MRR | C24: =SUMIF('Monthly Detail'!$4:$4, '2025 Overview (Budget)'!C$19, 'Monthly Detail'!41:41) -> 4460.105 | D24: =SUMIF('Monthly Detail'!$4:$4, '2025 Overview (Budget)'!D$19, 'Monthly Detail'!41:41) -> 4123.6763 | E24: =SUMIF('Monthly Detail'!$4:$4, '2025 Overview (Budget)'!E$19, 'Monthly Detail'!41:41) -> 3775.4392 | F24: =SUMIF('Monthly Detail'!$4:$4, '2025 Overview (Budget)'!F$19, 'Monthly Detail'!41:41) -> 4062.1519 | G24: =SUMIF('Monthly Detail'!$4:$4, '2025 Overview (Budget)'!G$19, 'Monthly Detail'!41:41) -> 4083.8286 | H24: =SUMIF('Monthly Detail'!$4:$4, '2025 Overview (Budget)'!H$19, 'Monthly Detail'!41:41) -> 4773.1964 | I24: =SUMIF('Monthly Detail'!$4:$4, '2025 Overview (Budget)'!I$19, 'Monthly Detail'!41:41) -> 4270.3349 | J24: =SUMIF('Monthly Detail'!$4:$4, '2025 Overview (Budget)'!J$19, 'Monthly Detail'!41:41) -> 4966.1738 | ... L24: =SUMIF('Monthly Detail'!$4:$4, '2025 Overview (Budget)'!L$19, 'Monthly Detail'!41:41) -> 4942.8781 | M24: =+'2025 AOP'!M24 -> 4643.0956 | N24: =+'2025 AOP'!N24 -> 6105.5718 | P24: =+AVERAGE(C24:N24) -> 4577.4593
B25: Recurring Client Base | C25: =SUMIF('Monthly Detail'!$4:$4, '2025 Overview (Budget)'!C$19, 'Monthly Detail'!17:17) -> 35 | D25: =SUMIF('Monthly Detail'!$4:$4, '2025 Overview (Budget)'!D$19, 'Monthly Detail'!17:17) -> 32 | E25: =SUMIF('Monthly Detail'!$4:$4, '2025 Overview (Budget)'!E$19, 'Monthly Detail'!17:17) -> 31 | F25: =SUMIF('Monthly Detail'!$4:$4, '2025 Overview (Budget)'!F$19, 'Monthly Detail'!17:17) -> 30 | G25: =SUMIF('Monthly Detail'!$4:$4, '2025 Overview (Budget)'!G$19, 'Monthly Detail'!17:17) -> 38 | H25: =SUMIF('Monthly Detail'!$4:$4, '2025 Overview (Budget)'!H$19, 'Monthly Detail'!17:17) -> 37 | I25: =SUMIF('Monthly Detail'!$4:$4, '2025 Overview (Budget)'!I$19, 'Monthly Detail'!17:17) -> 34 | J25: =SUMIF('Monthly Detail'!$4:$4, '2025 Overview (Budget)'!J$19, 'Monthly Detail'!17:17) -> 32 | ... L25: =SUMIF('Monthly Detail'!$4:$4, '2025 Overview (Budget)'!L$19, 'Monthly Detail'!17:17) -> 33 | M25: =+'2025 AOP'!M25 -> 48.077615 | N25: =+'2025 AOP'!N25 -> 49.208853
B28: Software - COS | C28: =SUMIF('Monthly Detail'!$4:$4, '2025 Overview (Budget)'!C$19, 'Monthly Detail'!58:58) -> 197.3 | D28: =SUMIF('Monthly Detail'!$4:$4, '2025 Overview (Budget)'!D$19, 'Monthly Detail'!58:58) -> 202.11 | E28: =SUMIF('Monthly Detail'!$4:$4, '2025 Overview (Budget)'!E$19, 'Monthly Detail'!58:58) -> 214.54 | F28: =SUMIF('Monthly Detail'!$4:$4, '2025 Overview (Budget)'!F$19, 'Monthly Detail'!58:58) -> 247.79 | G28: =SUMIF('Monthly Detail'!$4:$4, '2025 Overview (Budget)'!G$19, 'Monthly Detail'!58:58) -> 240.23 | H28: =SUMIF('Monthly Detail'!$4:$4, '2025 Overview (Budget)'!H$19, 'Monthly Detail'!58:58) -> 182.1 | I28: =SUMIF('Monthly Detail'!$4:$4, '2025 Overview (Budget)'!I$19, 'Monthly Detail'!58:58) -> 216.6 | J28: =SUMIF('Monthly Detail'!$4:$4, '2025 Overview (Budget)'!J$19, 'Monthly Detail'!58:58) -> 205.55 | ... L28: =SUMIF('Monthly Detail'!$4:$4, '2025 Overview (Budget)'!L$19, 'Monthly Detail'!58:58) -> 282 | M28: =+'2025 AOP'!M28 -> 207.81439 | N28: =+'2025 AOP'!N28 -> 253.81678 | P28: =+SUM(C28:N28) -> 2671.9712
B29: Materials - COGS | C29: =SUMIF('Monthly Detail'!$4:$4, '2025 Overview (Budget)'!C$19, 'Monthly Detail'!59:59) -> 249.98 | D29: =SUMIF('Monthly Detail'!$4:$4, '2025 Overview (Budget)'!D$19, 'Monthly Detail'!59:59) -> 497.5 | E29: =SUMIF('Monthly Detail'!$4:$4, '2025 Overview (Budget)'!E$19, 'Monthly Detail'!59:59) -> 810.15 | F29: =SUMIF('Monthly Detail'!$4:$4, '2025 Overview (Budget)'!F$19, 'Monthly Detail'!59:59) -> 352.78 | G29: =SUMIF('Monthly Detail'!$4:$4, '2025 Overview (Budget)'!G$19, 'Monthly Detail'!59:59) -> 754.25 | H29: =SUMIF('Monthly Detail'!$4:$4, '2025 Overview (Budget)'!H$19, 'Monthly Detail'!59:59) -> 503.73 | I29: =SUMIF('Monthly Detail'!$4:$4, '2025 Overview (Budget)'!I$19, 'Monthly Detail'!59:59) -> 588.11 | J29: =SUMIF('Monthly Detail'!$4:$4, '2025 Overview (Budget)'!J$19, 'Monthly Detail'!59:59) -> 768.16 | ... L29: =SUMIF('Monthly Detail'!$4:$4, '2025 Overview (Budget)'!L$19, 'Monthly Detail'!59:59) -> 578.51 | M29: =+'2025 AOP'!M29 -> 236.61421 | N29: =+'2025 AOP'!N29 -> 288.99182 | P29: =+SUM(C29:N29) -> 6522.206
B30: Contractors - COS | C30: =SUMIF('Monthly Detail'!$4:$4, '2025 Overview (Budget)'!C$19, 'Monthly Detail'!60:60) -> 50 | D30: =SUMIF('Monthly Detail'!$4:$4, '2025 Overview (Budget)'!D$19, 'Monthly Detail'!60:60) -> 45 | E30: =SUMIF('Monthly Detail'!$4:$4, '2025 Overview (Budget)'!E$19, 'Monthly Detail'!60:60) -> 0 | F30: =SUMIF('Monthly Detail'!$4:$4, '2025 Overview (Budget)'!F$19, 'Monthly Detail'!60:60) -> 0 | G30: =SUMIF('Monthly Detail'!$4:$4, '2025 Overview (Budget)'!G$19, 'Monthly Detail'!60:60) -> 629 | H30: =SUMIF('Monthly Detail'!$4:$4, '2025 Overview (Budget)'!H$19, 'Monthly Detail'!60:60) -> 0 | I30: =SUMIF('Monthly Detail'!$4:$4, '2025 Overview (Budget)'!I$19, 'Monthly Detail'!60:60) -> 0 | J30: =SUMIF('Monthly Detail'!$4:$4, '2025 Overview (Budget)'!J$19, 'Monthly Detail'!60:60) -> 0 | ... L30: =SUMIF('Monthly Detail'!$4:$4, '2025 Overview (Budget)'!L$19, 'Monthly Detail'!60:60) -> 0 | M30: =+'2025 AOP'!M30 -> 540 | N30: =+'2025 AOP'!N30 -> 680.08064 | P30: =+SUM(C30:N30) -> 1974.0806
B31: Total Cost of Goods Sold (COGS) | C31: =SUM(C28:C30) -> 497.28 | D31: =SUM(D28:D30) -> 744.61 | E31: =SUM(E28:E30) -> 1024.69 | F31: =SUM(F28:F30) -> 600.57 | G31: =SUM(G28:G30) -> 1623.48 | H31: =SUM(H28:H30) -> 685.83 | I31: =SUM(I28:I30) -> 804.71 | J31: =SUM(J28:J30) -> 973.71 | ... N31: =SUM(N28:N30) -> 1222.8892 | P31: =SUM(P28:P30) -> 11168.258
B33: Gross Margin | C33: =+C22-C31 -> 6223.77 | D33: =+D22-D31 -> 5756.53 | E33: =+E22-E31 -> 6083.81 | F33: =+F22-F31 -> 7261.18 | G33: =+G22-G31 -> 6254.14 | H33: =+H22-H31 -> 6201.62 | I33: =+I22-I31 -> 6613.84 | J33: =+J22-J31 -> 6679.64 | ... N33: =+N22-N31 -> 7348.278 | P33: =+SUM(C33:N33) -> 75618.727
B34: GM % | C34: =IFERROR(C33/C22, 0) -> 0.92601156 | D34: =IFERROR(D33/D22, 0) -> 0.8854647 | E34: =IFERROR(E33/E22, 0) -> 0.85585004 | F34: =IFERROR(F33/F22, 0) -> 0.92360861 | G34: =IFERROR(G33/G22, 0) -> 0.79391237 | H34: =IFERROR(H33/H22, 0) -> 0.90042323 | I34: =IFERROR(I33/I22, 0) -> 0.89152732 | J34: =IFERROR(J33/J22, 0) -> 0.87277336 | ... N34: =IFERROR(N33/N22, 0) -> 0.85732524 | P34: =P33/P22 -> 0.87131414
B36: General & Admintrative Expenses | C36: =SUMIF('Monthly Detail'!$4:$4, '2025 Overview (Budget)'!C$19, 'Monthly Detail'!$89:$89) -> 2161.9 | D36: =SUMIF('Monthly Detail'!$4:$4, '2025 Overview (Budget)'!D$19, 'Monthly Detail'!$89:$89) -> 3618.11 | E36: =SUMIF('Monthly Detail'!$4:$4, '2025 Overview (Budget)'!E$19, 'Monthly Detail'!$89:$89) -> 3644.83 | F36: =SUMIF('Monthly Detail'!$4:$4, '2025 Overview (Budget)'!F$19, 'Monthly Detail'!$89:$89) -> 5164.2 | G36: =SUMIF('Monthly Detail'!$4:$4, '2025 Overview (Budget)'!G$19, 'Monthly Detail'!$89:$89) -> 3990.04 | H36: =SUMIF('Monthly Detail'!$4:$4, '2025 Overview (Budget)'!H$19, 'Monthly Detail'!$89:$89) -> 3355.51 | I36: =SUMIF('Monthly Detail'!$4:$4, '2025 Overview (Budget)'!I$19, 'Monthly Detail'!$89:$89) -> 3680.41 | J36: =SUMIF('Monthly Detail'!$4:$4, '2025 Overview (Budget)'!J$19, 'Monthly Detail'!$89:$89) -> 3609.26 | K36: =SUMIF('Monthly Detail'!$4:$4, '2025 Overview (Budget)'!K$19, 'Monthly Detail'!$89:$89) -> 3143.78 | L36: =SUMIF('Monthly Detail'!$4:$4, '2025 Overview'!L$19, 'Monthly Detail'!$89:$89)+SUMIF('Monthly Detail'!$4:$4, '2025 Overview'!L$19, 'Monthly Detail'!$90:$90) -> 3847.74 | M36: =+'2025 AOP'!M36 -> 6297.7867 | N36: =+'2025 AOP'!N36 -> 6297.7867 | P36: =SUM(C36:O36) -> 48811.353
B37: Operating Expenses | C37: =SUM(C36:C36) -> 2161.9 | D37: =SUM(D36:D36) -> 3618.11 | E37: =SUM(E36:E36) -> 3644.83 | F37: =SUM(F36:F36) -> 5164.2 | G37: =SUM(G36:G36) -> 3990.04 | H37: =SUM(H36:H36) -> 3355.51 | I37: =SUM(I36:I36) -> 3680.41 | J37: =SUM(J36:J36) -> 3609.26 | ... N37: =SUM(N36:N36) -> 6297.7867 | P37: =SUM(P36:P36) -> 48811.353
B39: Net Operating Income (EBITDA) | C39: =C33-C37 -> 4061.87 | D39: =D33-D37 -> 2138.42 | E39: =E33-E37 -> 2438.98 | F39: =F33-F37 -> 2096.98 | G39: =G33-G37 -> 2264.1 | H39: =H33-H37 -> 2846.11 | I39: =I33-I37 -> 2933.43 | J39: =J33-J37 -> 3070.38 | ... N39: =N33-N37 -> 1050.4914 | P39: =P33-P37 -> 26807.373
B40: EBITDA % | C40: =IFERROR(C39/C22, 0) -> 0.60435051 | D40: =IFERROR(D39/D22, 0) -> 0.32893 | E40: =IFERROR(E39/E22, 0) -> 0.34310755 | F40: =IFERROR(F39/F22, 0) -> 0.26673196 | G40: =IFERROR(G39/G22, 0) -> 0.28740914 | H40: =IFERROR(H39/H22, 0) -> 0.41323131 | I40: =IFERROR(I39/I22, 0) -> 0.39541824 | J40: =IFERROR(J39/J22, 0) -> 0.40118118 | ... N40: =IFERROR(N39/N22, 0) -> 0.12256106 | P40: =P39/P22 -> 0.30888702
B42: Other Income / (Expense) | C42: =SUMIF('Monthly Detail'!$4:$4, '2025 Overview (Budget)'!C$19, 'Monthly Detail'!95:95) -> 0 | D42: =SUMIF('Monthly Detail'!$4:$4, '2025 Overview (Budget)'!D$19, 'Monthly Detail'!95:95) -> 0 | E42: =SUMIF('Monthly Detail'!$4:$4, '2025 Overview (Budget)'!E$19, 'Monthly Detail'!95:95) -> 2.35 | F42: =SUMIF('Monthly Detail'!$4:$4, '2025 Overview (Budget)'!F$19, 'Monthly Detail'!95:95) -> 3.21 | G42: =SUMIF('Monthly Detail'!$4:$4, '2025 Overview (Budget)'!G$19, 'Monthly Detail'!95:95) -> 4.3 | H42: =SUMIF('Monthly Detail'!$4:$4, '2025 Overview (Budget)'!H$19, 'Monthly Detail'!95:95) -> 3.94 | I42: =SUMIF('Monthly Detail'!$4:$4, '2025 Overview (Budget)'!I$19, 'Monthly Detail'!95:95) -> 4.21 | J42: =SUMIF('Monthly Detail'!$4:$4, '2025 Overview (Budget)'!J$19, 'Monthly Detail'!95:95) -> 3.44 | ... L42: =SUMIF('Monthly Detail'!$4:$4, '2025 Overview (Budget)'!L$19, 'Monthly Detail'!95:95) -> 1.78 | M42: =SUMIF('Monthly Detail'!$4:$4, '2025 Overview (Budget)'!M$19, 'Monthly Detail'!130:130) -> 0 | N42: =SUMIF('Monthly Detail'!$4:$4, '2025 Overview (Budget)'!N$19, 'Monthly Detail'!130:130) -> 0 | P42: =SUM(C42:O42) -> 25.84
B43: Net Income | C43: =C39+SUM(C42:C42) -> 4061.87 | D43: =D39+SUM(D42:D42) -> 2138.42 | E43: =E39+SUM(E42:E42) -> 2441.33 | F43: =F39+SUM(F42:F42) -> 2100.19 | G43: =G39+SUM(G42:G42) -> 2268.4 | H43: =H39+SUM(H42:H42) -> 2850.05 | I43: =I39+SUM(I42:I42) -> 2937.64 | J43: =J39+SUM(J42:J42) -> 3073.82 | ... N43: =N39+SUM(N42:N42) -> 1050.4914 | P43: =P39+SUM(P42:P42) -> 26833.213
B44: NI % | C44: =IFERROR(C43/C22, 0) -> 0.60435051 | D44: =IFERROR(D43/D22, 0) -> 0.32893 | E44: =IFERROR(E43/E22, 0) -> 0.34343814 | F44: =IFERROR(F43/F22, 0) -> 0.26714027 | G44: =IFERROR(G43/G22, 0) -> 0.28795499 | H44: =IFERROR(H43/H22, 0) -> 0.41380337 | I44: =IFERROR(I43/I22, 0) -> 0.39598574 | J44: =IFERROR(J43/J22, 0) -> 0.40163066 | ... N44: =IFERROR(N43/N22, 0) -> 0.12256106 | P44: =P43/P22 -> 0.30918476
B46: Operating (Business) Cash | C46: =SUMIF('Monthly Detail'!$4:$4, '2025 Overview (Budget)'!C$19, 'Monthly Detail'!112:112) -> 1326.208 | D46: =SUMIF('Monthly Detail'!$4:$4, '2025 Overview (Budget)'!D$19, 'Monthly Detail'!112:112) -> 1606.7285 | E46: =SUMIF('Monthly Detail'!$4:$4, '2025 Overview (Budget)'!E$19, 'Monthly Detail'!112:112) -> 2203.006 | F46: =SUMIF('Monthly Detail'!$4:$4, '2025 Overview (Budget)'!F$19, 'Monthly Detail'!112:112) -> 2800.369 | G46: =SUMIF('Monthly Detail'!$4:$4, '2025 Overview (Budget)'!G$19, 'Monthly Detail'!112:112) -> 4253.561 | H46: =SUMIF('Monthly Detail'!$4:$4, '2025 Overview (Budget)'!H$19, 'Monthly Detail'!112:112) -> 4362.1695 | I46: =SUMIF('Monthly Detail'!$4:$4, '2025 Overview (Budget)'!I$19, 'Monthly Detail'!112:112) -> 4312.256 | J46: =SUMIF('Monthly Detail'!$4:$4, '2025 Overview (Budget)'!J$19, 'Monthly Detail'!112:112) -> 4650.8085 | ... L46: =SUMIF('Monthly Detail'!$4:$4, '2025 Overview (Budget)'!L$19, 'Monthly Detail'!112:112) -> 3819.153 | M46: =+'2025 AOP'!M46 -> 2019.7107 | N46: =+'2025 AOP'!N46 -> 1694.3507
B47: Savings Cash | C47: =SUMIF('Monthly Detail'!$4:$4, '2025 Overview (Budget)'!C$19, 'Monthly Detail'!106:106) -> 45.02 | D47: =SUMIF('Monthly Detail'!$4:$4, '2025 Overview (Budget)'!D$19, 'Monthly Detail'!106:106) -> 68.56 | E47: =SUMIF('Monthly Detail'!$4:$4, '2025 Overview (Budget)'!E$19, 'Monthly Detail'!106:106) -> 0.03 | F47: =SUMIF('Monthly Detail'!$4:$4, '2025 Overview (Budget)'!F$19, 'Monthly Detail'!106:106) -> 9.57 | G47: =SUMIF('Monthly Detail'!$4:$4, '2025 Overview (Budget)'!G$19, 'Monthly Detail'!106:106) -> 150.5 | H47: =SUMIF('Monthly Detail'!$4:$4, '2025 Overview (Budget)'!H$19, 'Monthly Detail'!106:106) -> 17.12 | I47: =SUMIF('Monthly Detail'!$4:$4, '2025 Overview (Budget)'!I$19, 'Monthly Detail'!106:106) -> 50.77 | J47: =SUMIF('Monthly Detail'!$4:$4, '2025 Overview (Budget)'!J$19, 'Monthly Detail'!106:106) -> 0.77 | ... L47: =SUMIF('Monthly Detail'!$4:$4, '2025 Overview (Budget)'!L$19, 'Monthly Detail'!106:106) -> 15.87 | M47: =+'2025 AOP'!M47 -> 28.95 | N47: =+'2025 AOP'!N47 -> 28.95
B48: Total Cash Balance | C48: =SUMIF('Monthly Detail'!$4:$4, '2025 Overview (Budget)'!C$19, 'Monthly Detail'!173:173) -> 2040.32 | D48: =SUMIF('Monthly Detail'!$4:$4, '2025 Overview (Budget)'!D$19, 'Monthly Detail'!173:173) -> 2471.89 | E48: =SUMIF('Monthly Detail'!$4:$4, '2025 Overview (Budget)'!E$19, 'Monthly Detail'!173:173) -> 3389.24 | F48: =SUMIF('Monthly Detail'!$4:$4, '2025 Overview (Budget)'!F$19, 'Monthly Detail'!173:173) -> 4308.26 | G48: =SUMIF('Monthly Detail'!$4:$4, '2025 Overview (Budget)'!G$19, 'Monthly Detail'!173:173) -> 6543.94 | H48: =SUMIF('Monthly Detail'!$4:$4, '2025 Overview (Budget)'!H$19, 'Monthly Detail'!173:173) -> 6711.03 | I48: =SUMIF('Monthly Detail'!$4:$4, '2025 Overview (Budget)'!I$19, 'Monthly Detail'!173:173) -> 6634.24 | J48: =SUMIF('Monthly Detail'!$4:$4, '2025 Overview (Budget)'!J$19, 'Monthly Detail'!173:173) -> 7155.09 | ... L48: =SUMIF('Monthly Detail'!$4:$4, '2025 Overview (Budget)'!L$19, 'Monthly Detail'!173:173) -> 5875.62 | M48: =+'2025 AOP'!M48 -> 3107.2473 | N48: =+'2025 AOP'!N48 -> 2606.6934
B49: Total Cash Inflow (Outflow) | C49: =SUMIF('Monthly Detail'!$4:$4, '2025 Overview (Budget)'!C$19, 'Monthly Detail'!170:170) -> 614.32 | D49: =SUMIF('Monthly Detail'!$4:$4, '2025 Overview (Budget)'!D$19, 'Monthly Detail'!170:170) -> 431.57 | E49: =SUMIF('Monthly Detail'!$4:$4, '2025 Overview (Budget)'!E$19, 'Monthly Detail'!170:170) -> 917.35 | F49: =SUMIF('Monthly Detail'!$4:$4, '2025 Overview (Budget)'!F$19, 'Monthly Detail'!170:170) -> 919.02 | G49: =SUMIF('Monthly Detail'!$4:$4, '2025 Overview (Budget)'!G$19, 'Monthly Detail'!170:170) -> 2235.68 | H49: =SUMIF('Monthly Detail'!$4:$4, '2025 Overview (Budget)'!H$19, 'Monthly Detail'!170:170) -> 167.09 | I49: =SUMIF('Monthly Detail'!$4:$4, '2025 Overview (Budget)'!I$19, 'Monthly Detail'!170:170) -> -76.79 | J49: =SUMIF('Monthly Detail'!$4:$4, '2025 Overview (Budget)'!J$19, 'Monthly Detail'!170:170) -> 520.85 | ... L49: =SUMIF('Monthly Detail'!$4:$4, '2025 Overview (Budget)'!L$19, 'Monthly Detail'!170:170) -> -532.03 | M49: =+'2025 AOP'!M49 -> -1736.4419 | N49: =+'2025 AOP'!N49 -> -500.55389
B50: Operating Cash Burn | C50: =-SUMIF('Monthly Detail'!$4:$4, '2025 Overview (Budget)'!C$19, 'Monthly Detail'!89:89) -> -2161.9 | D50: =-SUMIF('Monthly Detail'!$4:$4, '2025 Overview (Budget)'!D$19, 'Monthly Detail'!89:89) -> -3618.11 | E50: =-SUMIF('Monthly Detail'!$4:$4, '2025 Overview (Budget)'!E$19, 'Monthly Detail'!89:89) -> -3644.83 | F50: =-SUMIF('Monthly Detail'!$4:$4, '2025 Overview (Budget)'!F$19, 'Monthly Detail'!89:89) -> -5164.2 | G50: =-SUMIF('Monthly Detail'!$4:$4, '2025 Overview (Budget)'!G$19, 'Monthly Detail'!89:89) -> -3990.04 | H50: =-SUMIF('Monthly Detail'!$4:$4, '2025 Overview (Budget)'!H$19, 'Monthly Detail'!89:89) -> -3355.51 | I50: =-SUMIF('Monthly Detail'!$4:$4, '2025 Overview (Budget)'!I$19, 'Monthly Detail'!89:89) -> -3680.41 | J50: =-SUMIF('Monthly Detail'!$4:$4, '2025 Overview (Budget)'!J$19, 'Monthly Detail'!89:89) -> -3609.26 | ... L50: =-SUMIF('Monthly Detail'!$4:$4, '2025 Overview (Budget)'!L$19, 'Monthly Detail'!89:89) -> -3831.61 | M50: =+'2025 AOP'!M50 -> 6297.7867 | N50: =+'2025 AOP'!N50 -> 6297.7867
B51: Owner Cash Burn/Allowance | C51: =SUMIF('Monthly Detail'!$4:$4, '2025 Overview (Budget)'!C$19, 'Monthly Detail'!154:154) -> -3116.58 | D51: =SUMIF('Monthly Detail'!$4:$4, '2025 Overview (Budget)'!D$19, 'Monthly Detail'!154:154) -> -1624.48 | E51: =SUMIF('Monthly Detail'!$4:$4, '2025 Overview (Budget)'!E$19, 'Monthly Detail'!154:154) -> -1433.72 | F51: =SUMIF('Monthly Detail'!$4:$4, '2025 Overview (Budget)'!F$19, 'Monthly Detail'!154:154) -> -1790.11 | G51: =SUMIF('Monthly Detail'!$4:$4, '2025 Overview (Budget)'!G$19, 'Monthly Detail'!154:154) -> -774.65 | H51: =SUMIF('Monthly Detail'!$4:$4, '2025 Overview (Budget)'!H$19, 'Monthly Detail'!154:154) -> -2413.31 | I51: =SUMIF('Monthly Detail'!$4:$4, '2025 Overview (Budget)'!I$19, 'Monthly Detail'!154:154) -> -3588.01 | J51: =SUMIF('Monthly Detail'!$4:$4, '2025 Overview (Budget)'!J$19, 'Monthly Detail'!154:154) -> -2335.22 | ... L51: =SUMIF('Monthly Detail'!$4:$4, '2025 Overview (Budget)'!L$19, 'Monthly Detail'!154:154) -> -2593.56 | M51: =+'2025 AOP'!M51 -> -1500 | N51: =+'2025 AOP'!N51 -> -1500
B52: Operating Cash Runway | C52: =+C46-SUM('Monthly Detail'!AC89:AN89)-SUM('Monthly Detail'!AC61:AN61) -> -32667.032 | D52: =+D46-SUM('Monthly Detail'!AD89:AO89)-SUM('Monthly Detail'!AD61:AO61) -> -35245.302 | E52: =+E46-SUM('Monthly Detail'!AE89:AP89)-SUM('Monthly Detail'!AE61:AP61) -> -37994.724 | F52: =+F46-SUM('Monthly Detail'!AF89:AQ89)-SUM('Monthly Detail'!AF61:AQ61) -> -41616.711 | G52: =+G46-SUM('Monthly Detail'!AG89:AR89)-SUM('Monthly Detail'!AG61:AR61) -> -41691.299 | H52: =+H46-SUM('Monthly Detail'!AH89:AS89)-SUM('Monthly Detail'!AH61:AS61) -> -42111.731 | I52: =+I46-SUM('Monthly Detail'!AI89:AT89)-SUM('Monthly Detail'!AI61:AT61) -> -44079.774 | J52: =+J46-SUM('Monthly Detail'!AJ89:AU89)-SUM('Monthly Detail'!AJ61:AU61) -> -44785.641 | ... L52: =+L46-SUM('Monthly Detail'!AL89:AW89)-SUM('Monthly Detail'!AL61:AW61) -> -48526.287 | M52: =+'2025 AOP'!M52 -> -78664.644 | N52: =+'2025 AOP'!N52 -> -83134.825
B53: Owner Cash Runway | C53: =+C48-SUM('Monthly Detail'!AC89:AN89)-SUM('Monthly Detail'!AC61:AN61) -> -31952.92 | D53: =+D48-SUM('Monthly Detail'!AD89:AO89)-SUM('Monthly Detail'!AD61:AO61) -> -34380.14 | E53: =+E48-SUM('Monthly Detail'!AE89:AP89)-SUM('Monthly Detail'!AE61:AP61) -> -36808.49 | F53: =+F48-SUM('Monthly Detail'!AF89:AQ89)-SUM('Monthly Detail'!AF61:AQ61) -> -40108.82 | G53: =+G48-SUM('Monthly Detail'!AG89:AR89)-SUM('Monthly Detail'!AG61:AR61) -> -39400.92 | H53: =+H48-SUM('Monthly Detail'!AH89:AS89)-SUM('Monthly Detail'!AH61:AS61) -> -39762.87 | I53: =+I48-SUM('Monthly Detail'!AI89:AT89)-SUM('Monthly Detail'!AI61:AT61) -> -41757.79 | J53: =+J48-SUM('Monthly Detail'!AJ89:AU89)-SUM('Monthly Detail'!AJ61:AU61) -> -42281.36 | ... L53: =+L48-SUM('Monthly Detail'!AL89:AW89)-SUM('Monthly Detail'!AL61:AW61) -> -46469.82 | M53: =+'2025 AOP'!M53 -> -77577.107 | N53: =+'2025 AOP'!N53 -> -82222.482
B54: Operating Cash Runway - Burn Rate | C54: =+C46/-C50 -> 0.61344558 | D54: =+D46/-D50 -> 0.44407951 | E54: =+E46/-E50 -> 0.60441941 | F54: =+F46/-F50 -> 0.54226579 | G54: =+G46/-G50 -> 1.0660447 | H54: =+H46/-H50 -> 1.3000019 | I54: =+I46/-I50 -> 1.1716782 | J54: =+J46/-J50 -> 1.2885767 | ... L54: =+L46/-L50 -> 0.99674889 | M54: =-'2025 AOP'!M54 -> 0.32070167 | N54: =-'2025 AOP'!N54 -> 0.26903907
B55: Cash Runway - Owner Burn Rate | C55: =+IFERROR(C48/-C51, 0) -> 0.65466633 | D55: =+IFERROR(D48/-D51, 0) -> 1.52165 | E55: =+IFERROR(E48/-E51, 0) -> 2.3639483 | F55: =+IFERROR(F48/-F51, 0) -> 2.4067013 | G55: =+IFERROR(G48/-G51, 0) -> 8.4476086 | H55: =+IFERROR(H48/-H51, 0) -> 2.7808404 | I55: =+IFERROR(I48/-I51, 0) -> 1.8490027 | J55: =+IFERROR(J48/-J51, 0) -> 3.0639897 | ... L55: =+IFERROR(L48/-L51, 0) -> 2.2654652 | M55: =+'2025 AOP'!M55 -> 2.0714982 | N55: =+'2025 AOP'!N55 -> 1.7377956

Sheet 2025 Overview
B15: 2025 Overview
C18: January | D18: February | E18: March | F18: April | G18: May | H18: June | I18: July | J18: August | K18: September | L18: October | M18: November | N18: December | P18: Total
C19: 45688 | D19: 45716 | E19: 45747 | F19: 45777 | G19: 45808 | H19: 45838 | I19: 45869 | J19: 45900 | K19: 45930 | L19: 45961 | M19: 45991 | N19: 46022 | O19: 45322
B20: Service Income | C20: =SUMIF('Monthly Detail'!$4:$4, '2025 Overview'!C$19, 'Monthly Detail'!13:13) -> 6721.05 | D20: =SUMIF('Monthly Detail'!$4:$4, '2025 Overview'!D$19, 'Monthly Detail'!13:13) -> 6501.14 | E20: =SUMIF('Monthly Detail'!$4:$4, '2025 Overview'!E$19, 'Monthly Detail'!13:13) -> 7108.5 | F20: =SUMIF('Monthly Detail'!$4:$4, '2025 Overview'!F$19, 'Monthly Detail'!13:13) -> 7861.75 | G20: =SUMIF('Monthly Detail'!$4:$4, '2025 Overview'!G$19, 'Monthly Detail'!13:13) -> 7877.62 | H20: =SUMIF('Monthly Detail'!$4:$4, '2025 Overview'!H$19, 'Monthly Detail'!13:13) -> 6887.45 | I20: =SUMIF('Monthly Detail'!$4:$4, '2025 Overview'!I$19, 'Monthly Detail'!13:13) -> 7418.55 | J20: =SUMIF('Monthly Detail'!$4:$4, '2025 Overview'!J$19, 'Monthly Detail'!13:13) -> 7653.35 | ... N20: =SUMIF('Monthly Detail'!$4:$4, '2025 Overview'!N$19, 'Monthly Detail'!13:13) -> 7465.3408 | P20: =SUM(C20:O20) -> 83940.526
B21: Misc. | C21: =SUMIF('Monthly Detail'!$4:$4, '2025 Overview'!C$19, 'Monthly Detail'!12:12) -> 0 | D21: =SUMIF('Monthly Detail'!$4:$4, '2025 Overview'!D$19, 'Monthly Detail'!12:12) -> 0 | E21: =SUMIF('Monthly Detail'!$4:$4, '2025 Overview'!E$19, 'Monthly Detail'!12:12) -> 0 | F21: =SUMIF('Monthly Detail'!$4:$4, '2025 Overview'!F$19, 'Monthly Detail'!12:12) -> 0 | G21: =SUMIF('Monthly Detail'!$4:$4, '2025 Overview'!G$19, 'Monthly Detail'!12:12) -> 0 | H21: =SUMIF('Monthly Detail'!$4:$4, '2025 Overview'!H$19, 'Monthly Detail'!12:12) -> 0 | I21: =SUMIF('Monthly Detail'!$4:$4, '2025 Overview'!I$19, 'Monthly Detail'!12:12) -> 0 | J21: =SUMIF('Monthly Detail'!$4:$4, '2025 Overview'!J$19, 'Monthly Detail'!12:12) -> 0 | ... N21: =SUMIF('Monthly Detail'!$4:$4, '2025 Overview'!N$19, 'Monthly Detail'!12:12) -> 0 | P21: =SUM(C21:O21) -> 0
B22: Total Income | C22: =SUM(C20:C21) -> 6721.05 | D22: =SUM(D20:D21) -> 6501.14 | E22: =SUM(E20:E21) -> 7108.5 | F22: =SUM(F20:F21) -> 7861.75 | G22: =SUM(G20:G21) -> 7877.62 | H22: =SUM(H20:H21) -> 6887.45 | I22: =SUM(I20:I21) -> 7418.55 | J22: =SUM(J20:J21) -> 7653.35 | ... N22: =SUM(N20:N21) -> 7465.3408 | P22: =SUM(P20:P20) -> 83940.526
B23: # of Appointments | C23: =SUMIF('Monthly Detail'!$4:$4, '2025 Overview'!C$19, 'Monthly Detail'!15:15) -> 66 | D23: =SUMIF('Monthly Detail'!$4:$4, '2025 Overview'!D$19, 'Monthly Detail'!15:15) -> 69 | E23: =SUMIF('Monthly Detail'!$4:$4, '2025 Overview'!E$19, 'Monthly Detail'!15:15) -> 68 | F23: =SUMIF('Monthly Detail'!$4:$4, '2025 Overview'!F$19, 'Monthly Detail'!15:15) -> 82 | G23: =SUMIF('Monthly Detail'!$4:$4, '2025 Overview'!G$19, 'Monthly Detail'!15:15) -> 83 | H23: =SUMIF('Monthly Detail'!$4:$4, '2025 Overview'!H$19, 'Monthly Detail'!15:15) -> 72 | I23: =SUMIF('Monthly Detail'!$4:$4, '2025 Overview'!I$19, 'Monthly Detail'!15:15) -> 76 | J23: =SUMIF('Monthly Detail'!$4:$4, '2025 Overview'!J$19, 'Monthly Detail'!15:15) -> 73 | ... N23: =SUMIF('Monthly Detail'!$4:$4, '2025 Overview'!N$19, 'Monthly Detail'!15:15) -> 59.815338 | P23: =+SUM(C23:N23) -> 831.12105
B24: MRR | C24: =SUMIF('Monthly Detail'!$4:$4, '2025 Overview'!C$19, 'Monthly Detail'!41:41) -> 4460.105 | D24: =SUMIF('Monthly Detail'!$4:$4, '2025 Overview'!D$19, 'Monthly Detail'!41:41) -> 4123.6763 | E24: =SUMIF('Monthly Detail'!$4:$4, '2025 Overview'!E$19, 'Monthly Detail'!41:41) -> 3775.4392 | F24: =SUMIF('Monthly Detail'!$4:$4, '2025 Overview'!F$19, 'Monthly Detail'!41:41) -> 4062.1519 | G24: =SUMIF('Monthly Detail'!$4:$4, '2025 Overview'!G$19, 'Monthly Detail'!41:41) -> 4083.8286 | H24: =SUMIF('Monthly Detail'!$4:$4, '2025 Overview'!H$19, 'Monthly Detail'!41:41) -> 4773.1964 | I24: =SUMIF('Monthly Detail'!$4:$4, '2025 Overview'!I$19, 'Monthly Detail'!41:41) -> 4270.3349 | J24: =SUMIF('Monthly Detail'!$4:$4, '2025 Overview'!J$19, 'Monthly Detail'!41:41) -> 4966.1738 | ... N24: =SUMIF('Monthly Detail'!$4:$4, '2025 Overview'!N$19, 'Monthly Detail'!41:41) -> 4798.1261 | P24: =+AVERAGE(C24:N24) -> 4353.5441
B25: Recurring Client Base | C25: =SUMIF('Monthly Detail'!$4:$4, '2025 Overview'!C$19, 'Monthly Detail'!17:17) -> 35 | D25: =SUMIF('Monthly Detail'!$4:$4, '2025 Overview'!D$19, 'Monthly Detail'!17:17) -> 32 | E25: =SUMIF('Monthly Detail'!$4:$4, '2025 Overview'!E$19, 'Monthly Detail'!17:17) -> 31 | F25: =SUMIF('Monthly Detail'!$4:$4, '2025 Overview'!F$19, 'Monthly Detail'!17:17) -> 30 | G25: =SUMIF('Monthly Detail'!$4:$4, '2025 Overview'!G$19, 'Monthly Detail'!17:17) -> 38 | H25: =SUMIF('Monthly Detail'!$4:$4, '2025 Overview'!H$19, 'Monthly Detail'!17:17) -> 37 | I25: =SUMIF('Monthly Detail'!$4:$4, '2025 Overview'!I$19, 'Monthly Detail'!17:17) -> 34 | J25: =SUMIF('Monthly Detail'!$4:$4, '2025 Overview'!J$19, 'Monthly Detail'!17:17) -> 32 | ... N25: =SUMIF('Monthly Detail'!$4:$4, '2025 Overview'!N$19, 'Monthly Detail'!17:17) -> 30.127454
B28: Software - COS | C28: =SUMIF('Monthly Detail'!$4:$4, '2025 Overview'!C$19, 'Monthly Detail'!58:58) -> 197.3 | D28: =SUMIF('Monthly Detail'!$4:$4, '2025 Overview'!D$19, 'Monthly Detail'!58:58) -> 202.11 | E28: =SUMIF('Monthly Detail'!$4:$4, '2025 Overview'!E$19, 'Monthly Detail'!58:58) -> 214.54 | F28: =SUMIF('Monthly Detail'!$4:$4, '2025 Overview'!F$19, 'Monthly Detail'!58:58) -> 247.79 | G28: =SUMIF('Monthly Detail'!$4:$4, '2025 Overview'!G$19, 'Monthly Detail'!58:58) -> 240.23 | H28: =SUMIF('Monthly Detail'!$4:$4, '2025 Overview'!H$19, 'Monthly Detail'!58:58) -> 182.1 | I28: =SUMIF('Monthly Detail'!$4:$4, '2025 Overview'!I$19, 'Monthly Detail'!58:58) -> 216.6 | J28: =SUMIF('Monthly Detail'!$4:$4, '2025 Overview'!J$19, 'Monthly Detail'!58:58) -> 205.55 | ... N28: =SUMIF('Monthly Detail'!$4:$4, '2025 Overview'!N$19, 'Monthly Detail'!58:58) -> 235.50961 | P28: =+SUM(C28:N28) -> 2612.3259
B29: Materials - COGS | C29: =SUMIF('Monthly Detail'!$4:$4, '2025 Overview'!C$19, 'Monthly Detail'!59:59) -> 249.98 | D29: =SUMIF('Monthly Detail'!$4:$4, '2025 Overview'!D$19, 'Monthly Detail'!59:59) -> 497.5 | E29: =SUMIF('Monthly Detail'!$4:$4, '2025 Overview'!E$19, 'Monthly Detail'!59:59) -> 810.15 | F29: =SUMIF('Monthly Detail'!$4:$4, '2025 Overview'!F$19, 'Monthly Detail'!59:59) -> 352.78 | G29: =SUMIF('Monthly Detail'!$4:$4, '2025 Overview'!G$19, 'Monthly Detail'!59:59) -> 754.25 | H29: =SUMIF('Monthly Detail'!$4:$4, '2025 Overview'!H$19, 'Monthly Detail'!59:59) -> 503.73 | I29: =SUMIF('Monthly Detail'!$4:$4, '2025 Overview'!I$19, 'Monthly Detail'!59:59) -> 588.11 | J29: =SUMIF('Monthly Detail'!$4:$4, '2025 Overview'!J$19, 'Monthly Detail'!59:59) -> 768.16 | ... N29: =SUMIF('Monthly Detail'!$4:$4, '2025 Overview'!N$19, 'Monthly Detail'!59:59) -> 716.65365 | P29: =+SUM(C29:N29) -> 7219.8394
B30: Contractors - COS | C30: =SUMIF('Monthly Detail'!$4:$4, '2025 Overview'!C$19, 'Monthly Detail'!60:60) -> 50 | D30: =SUMIF('Monthly Detail'!$4:$4, '2025 Overview'!D$19, 'Monthly Detail'!60:60) -> 45 | E30: =SUMIF('Monthly Detail'!$4:$4, '2025 Overview'!E$19, 'Monthly Detail'!60:60) -> 0 | F30: =SUMIF('Monthly Detail'!$4:$4, '2025 Overview'!F$19, 'Monthly Detail'!60:60) -> 0 | G30: =SUMIF('Monthly Detail'!$4:$4, '2025 Overview'!G$19, 'Monthly Detail'!60:60) -> 629 | H30: =SUMIF('Monthly Detail'!$4:$4, '2025 Overview'!H$19, 'Monthly Detail'!60:60) -> 0 | I30: =SUMIF('Monthly Detail'!$4:$4, '2025 Overview'!I$19, 'Monthly Detail'!60:60) -> 0 | J30: =SUMIF('Monthly Detail'!$4:$4, '2025 Overview'!J$19, 'Monthly Detail'!60:60) -> 0 | ... N30: =SUMIF('Monthly Detail'!$4:$4, '2025 Overview'!N$19, 'Monthly Detail'!60:60) -> 979.69132 | P30: =+SUM(C30:N30) -> 2010.0674
B31: Total Cost of Goods Sold (COGS) | C31: =SUM(C28:C30) -> 497.28 | D31: =SUM(D28:D30) -> 744.61 | E31: =SUM(E28:E30) -> 1024.69 | F31: =SUM(F28:F30) -> 600.57 | G31: =SUM(G28:G30) -> 1623.48 | H31: =SUM(H28:H30) -> 685.83 | I31: =SUM(I28:I30) -> 804.71 | J31: =SUM(J28:J30) -> 973.71 | ... N31: =SUM(N28:N30) -> 1931.8546 | P31: =SUM(P28:P30) -> 11842.233
B33: Gross Margin | C33: =+C22-C31 -> 6223.77 | D33: =+D22-D31 -> 5756.53 | E33: =+E22-E31 -> 6083.81 | F33: =+F22-F31 -> 7261.18 | G33: =+G22-G31 -> 6254.14 | H33: =+H22-H31 -> 6201.62 | I33: =+I22-I31 -> 6613.84 | J33: =+J22-J31 -> 6679.64 | ... N33: =+N22-N31 -> 5533.4862 | P33: =+SUM(C33:N33) -> 72098.293
B34: GM % | C34: =IFERROR(C33/C22, 0) -> 0.92601156 | D34: =IFERROR(D33/D22, 0) -> 0.8854647 | E34: =IFERROR(E33/E22, 0) -> 0.85585004 | F34: =IFERROR(F33/F22, 0) -> 0.92360861 | G34: =IFERROR(G33/G22, 0) -> 0.79391237 | H34: =IFERROR(H33/H22, 0) -> 0.90042323 | I34: =IFERROR(I33/I22, 0) -> 0.89152732 | J34: =IFERROR(J33/J22, 0) -> 0.87277336 | ... N34: =IFERROR(N33/N22, 0) -> 0.74122352 | P34: =P33/P22 -> 0.85892115
B36: General & Admintrative Expenses | C36: =SUMIF('Monthly Detail'!$4:$4, '2025 Overview'!C$19, 'Monthly Detail'!$89:$89)+SUMIF('Monthly Detail'!$4:$4, '2025 Overview'!C$19, 'Monthly Detail'!$90:$90) -> 2161.9 | D36: =SUMIF('Monthly Detail'!$4:$4, '2025 Overview'!D$19, 'Monthly Detail'!$89:$89)+SUMIF('Monthly Detail'!$4:$4, '2025 Overview'!D$19, 'Monthly Detail'!$90:$90) -> 3618.11 | E36: =SUMIF('Monthly Detail'!$4:$4, '2025 Overview'!E$19, 'Monthly Detail'!$89:$89)+SUMIF('Monthly Detail'!$4:$4, '2025 Overview'!E$19, 'Monthly Detail'!$90:$90) -> 3644.83 | F36: =SUMIF('Monthly Detail'!$4:$4, '2025 Overview'!F$19, 'Monthly Detail'!$89:$89)+SUMIF('Monthly Detail'!$4:$4, '2025 Overview'!F$19, 'Monthly Detail'!$90:$90) -> 5164.2 | G36: =SUMIF('Monthly Detail'!$4:$4, '2025 Overview'!G$19, 'Monthly Detail'!$89:$89)+SUMIF('Monthly Detail'!$4:$4, '2025 Overview'!G$19, 'Monthly Detail'!$90:$90) -> 3990.04 | H36: =SUMIF('Monthly Detail'!$4:$4, '2025 Overview'!H$19, 'Monthly Detail'!$89:$89)+SUMIF('Monthly Detail'!$4:$4, '2025 Overview'!H$19, 'Monthly Detail'!$90:$90) -> 3355.51 | I36: =SUMIF('Monthly Detail'!$4:$4, '2025 Overview'!I$19, 'Monthly Detail'!$89:$89)+SUMIF('Monthly Detail'!$4:$4, '2025 Overview'!I$19, 'Monthly Detail'!$90:$90) -> 3680.41 | J36: =SUMIF('Monthly Detail'!$4:$4, '2025 Overview'!J$19, 'Monthly Detail'!$89:$89)+SUMIF('Monthly Detail'!$4:$4, '2025 Overview'!J$19, 'Monthly Detail'!$90:$90) -> 3609.26 | ... N36: =SUMIF('Monthly Detail'!$4:$4, '2025 Overview'!N$19, 'Monthly Detail'!$89:$89)+SUMIF('Monthly Detail'!$4:$4, '2025 Overview'!N$19, 'Monthly Detail'!$90:$90) -> 5037.9024 | P36: =SUM(C36:O36) -> 46291.585
B37: Operating Expenses | C37: =SUM(C36:C36) -> 2161.9 | D37: =SUM(D36:D36) -> 3618.11 | E37: =SUM(E36:E36) -> 3644.83 | F37: =SUM(F36:F36) -> 5164.2 | G37: =SUM(G36:G36) -> 3990.04 | H37: =SUM(H36:H36) -> 3355.51 | I37: =SUM(I36:I36) -> 3680.41 | J37: =SUM(J36:J36) -> 3609.26 | ... N37: =SUM(N36:N36) -> 5037.9024 | P37: =SUM(P36:P36) -> 46291.585
B39: Net Operating Income (EBITDA) | C39: =C33-C37 -> 4061.87 | D39: =D33-D37 -> 2138.42 | E39: =E33-E37 -> 2438.98 | F39: =F33-F37 -> 2096.98 | G39: =G33-G37 -> 2264.1 | H39: =H33-H37 -> 2846.11 | I39: =I33-I37 -> 2933.43 | J39: =J33-J37 -> 3070.38 | ... N39: =N33-N37 -> 495.58378 | P39: =P33-P37 -> 25806.708
B40: EBITDA % | C40: =IFERROR(C39/C22, 0) -> 0.60435051 | D40: =IFERROR(D39/D22, 0) -> 0.32893 | E40: =IFERROR(E39/E22, 0) -> 0.34310755 | F40: =IFERROR(F39/F22, 0) -> 0.26673196 | G40: =IFERROR(G39/G22, 0) -> 0.28740914 | H40: =IFERROR(H39/H22, 0) -> 0.41323131 | I40: =IFERROR(I39/I22, 0) -> 0.39541824 | J40: =IFERROR(J39/J22, 0) -> 0.40118118 | ... N40: =IFERROR(N39/N22, 0) -> 0.066384616 | P40: =P39/P22 -> 0.3074404
B42: Other Income / (Expense) | C42: =SUMIF('Monthly Detail'!$4:$4, '2025 Overview'!C$19, 'Monthly Detail'!95:95) -> 0 | D42: =SUMIF('Monthly Detail'!$4:$4, '2025 Overview'!D$19, 'Monthly Detail'!95:95) -> 0 | E42: =SUMIF('Monthly Detail'!$4:$4, '2025 Overview'!E$19, 'Monthly Detail'!95:95) -> 2.35 | F42: =SUMIF('Monthly Detail'!$4:$4, '2025 Overview'!F$19, 'Monthly Detail'!95:95) -> 3.21 | G42: =SUMIF('Monthly Detail'!$4:$4, '2025 Overview'!G$19, 'Monthly Detail'!95:95) -> 4.3 | H42: =SUMIF('Monthly Detail'!$4:$4, '2025 Overview'!H$19, 'Monthly Detail'!95:95) -> 3.94 | I42: =SUMIF('Monthly Detail'!$4:$4, '2025 Overview'!I$19, 'Monthly Detail'!95:95) -> 4.21 | J42: =SUMIF('Monthly Detail'!$4:$4, '2025 Overview'!J$19, 'Monthly Detail'!95:95) -> 3.44 | ... N42: =SUMIF('Monthly Detail'!$4:$4, '2025 Overview'!N$19, 'Monthly Detail'!95:95) -> 1.78 | P42: =SUM(C42:O42) -> 29.4
B43: Net Income | C43: =C39+SUM(C42:C42) -> 4061.87 | D43: =D39+SUM(D42:D42) -> 2138.42 | E43: =E39+SUM(E42:E42) -> 2441.33 | F43: =F39+SUM(F42:F42) -> 2100.19 | G43: =G39+SUM(G42:G42) -> 2268.4 | H43: =H39+SUM(H42:H42) -> 2850.05 | I43: =I39+SUM(I42:I42) -> 2937.64 | J43: =J39+SUM(J42:J42) -> 3073.82 | ... N43: =N39+SUM(N42:N42) -> 497.36378 | P43: =P39+SUM(P42:P42) -> 25836.108
B44: NI % | C44: =IFERROR(C43/C22, 0) -> 0.60435051 | D44: =IFERROR(D43/D22, 0) -> 0.32893 | E44: =IFERROR(E43/E22, 0) -> 0.34343814 | F44: =IFERROR(F43/F22, 0) -> 0.26714027 | G44: =IFERROR(G43/G22, 0) -> 0.28795499 | H44: =IFERROR(H43/H22, 0) -> 0.41380337 | I44: =IFERROR(I43/I22, 0) -> 0.39598574 | J44: =IFERROR(J43/J22, 0) -> 0.40163066 | ... N44: =IFERROR(N43/N22, 0) -> 0.066623051 | P44: =P43/P22 -> 0.30779064
B46: Operating (Business) Cash | C46: =SUMIF('Monthly Detail'!$4:$4, '2025 Overview'!C$19, 'Monthly Detail'!112:112) -> 1326.208 | D46: =SUMIF('Monthly Detail'!$4:$4, '2025 Overview'!D$19, 'Monthly Detail'!112:112) -> 1606.7285 | E46: =SUMIF('Monthly Detail'!$4:$4, '2025 Overview'!E$19, 'Monthly Detail'!112:112) -> 2203.006 | F46: =SUMIF('Monthly Detail'!$4:$4, '2025 Overview'!F$19, 'Monthly Detail'!112:112) -> 2800.369 | G46: =SUMIF('Monthly Detail'!$4:$4, '2025 Overview'!G$19, 'Monthly Detail'!112:112) -> 4253.561 | H46: =SUMIF('Monthly Detail'!$4:$4, '2025 Overview'!H$19, 'Monthly Detail'!112:112) -> 4362.1695 | I46: =SUMIF('Monthly Detail'!$4:$4, '2025 Overview'!I$19, 'Monthly Detail'!112:112) -> 4312.256 | J46: =SUMIF('Monthly Detail'!$4:$4, '2025 Overview'!J$19, 'Monthly Detail'!112:112) -> 4650.8085 | ... N46: =SUMIF('Monthly Detail'!$4:$4, '2025 Overview'!N$19, 'Monthly Detail'!112:112) -> 4540.1488
B47: Savings Cash | C47: =SUMIF('Monthly Detail'!$4:$4, '2025 Overview'!C$19, 'Monthly Detail'!106:106) -> 45.02 | D47: =SUMIF('Monthly Detail'!$4:$4, '2025 Overview'!D$19, 'Monthly Detail'!106:106) -> 68.56 | E47: =SUMIF('Monthly Detail'!$4:$4, '2025 Overview'!E$19, 'Monthly Detail'!106:106) -> 0.03 | F47: =SUMIF('Monthly Detail'!$4:$4, '2025 Overview'!F$19, 'Monthly Detail'!106:106) -> 9.57 | G47: =SUMIF('Monthly Detail'!$4:$4, '2025 Overview'!G$19, 'Monthly Detail'!106:106) -> 150.5 | H47: =SUMIF('Monthly Detail'!$4:$4, '2025 Overview'!H$19, 'Monthly Detail'!106:106) -> 17.12 | I47: =SUMIF('Monthly Detail'!$4:$4, '2025 Overview'!I$19, 'Monthly Detail'!106:106) -> 50.77 | J47: =SUMIF('Monthly Detail'!$4:$4, '2025 Overview'!J$19, 'Monthly Detail'!106:106) -> 0.77 | ... N47: =SUMIF('Monthly Detail'!$4:$4, '2025 Overview'!N$19, 'Monthly Detail'!106:106) -> 15.87
B48: Total Cash Balance | C48: =SUMIF('Monthly Detail'!$4:$4, '2025 Overview'!C$19, 'Monthly Detail'!173:173) -> 2040.32 | D48: =SUMIF('Monthly Detail'!$4:$4, '2025 Overview'!D$19, 'Monthly Detail'!173:173) -> 2471.89 | E48: =SUMIF('Monthly Detail'!$4:$4, '2025 Overview'!E$19, 'Monthly Detail'!173:173) -> 3389.24 | F48: =SUMIF('Monthly Detail'!$4:$4, '2025 Overview'!F$19, 'Monthly Detail'!173:173) -> 4308.26 | G48: =SUMIF('Monthly Detail'!$4:$4, '2025 Overview'!G$19, 'Monthly Detail'!173:173) -> 6543.94 | H48: =SUMIF('Monthly Detail'!$4:$4, '2025 Overview'!H$19, 'Monthly Detail'!173:173) -> 6711.03 | I48: =SUMIF('Monthly Detail'!$4:$4, '2025 Overview'!I$19, 'Monthly Detail'!173:173) -> 6634.24 | J48: =SUMIF('Monthly Detail'!$4:$4, '2025 Overview'!J$19, 'Monthly Detail'!173:173) -> 7155.09 | ... N48: =SUMIF('Monthly Detail'!$4:$4, '2025 Overview'!N$19, 'Monthly Detail'!173:173) -> 6984.8443 | P48: =+(SUM(C43:E43)*0.153)-SUM('Monthly Detail'!AO69:AP69) -> 1114.2779
B49: Total Cash Inflow (Outflow) | C49: =SUMIF('Monthly Detail'!$4:$4, '2025 Overview'!C$19, 'Monthly Detail'!170:170) -> 614.32 | D49: =SUMIF('Monthly Detail'!$4:$4, '2025 Overview'!D$19, 'Monthly Detail'!170:170) -> 431.57 | E49: =SUMIF('Monthly Detail'!$4:$4, '2025 Overview'!E$19, 'Monthly Detail'!170:170) -> 917.35 | F49: =SUMIF('Monthly Detail'!$4:$4, '2025 Overview'!F$19, 'Monthly Detail'!170:170) -> 919.02 | G49: =SUMIF('Monthly Detail'!$4:$4, '2025 Overview'!G$19, 'Monthly Detail'!170:170) -> 2235.68 | H49: =SUMIF('Monthly Detail'!$4:$4, '2025 Overview'!H$19, 'Monthly Detail'!170:170) -> 167.09 | I49: =SUMIF('Monthly Detail'!$4:$4, '2025 Overview'!I$19, 'Monthly Detail'!170:170) -> -76.79 | J49: =SUMIF('Monthly Detail'!$4:$4, '2025 Overview'!J$19, 'Monthly Detail'!170:170) -> 520.85 | ... N49: =SUMIF('Monthly Detail'!$4:$4, '2025 Overview'!N$19, 'Monthly Detail'!170:170) -> 275.45941 | P49: =+SUM(C43:H43)*0.15 -> 2379.039
B50: Operating Cash Burn | C50: =-SUMIF('Monthly Detail'!$4:$4, '2025 Overview'!C$19, 'Monthly Detail'!89:89) -> -2161.9 | D50: =-SUMIF('Monthly Detail'!$4:$4, '2025 Overview'!D$19, 'Monthly Detail'!89:89) -> -3618.11 | E50: =-SUMIF('Monthly Detail'!$4:$4, '2025 Overview'!E$19, 'Monthly Detail'!89:89) -> -3644.83 | F50: =-SUMIF('Monthly Detail'!$4:$4, '2025 Overview'!F$19, 'Monthly Detail'!89:89) -> -5164.2 | G50: =-SUMIF('Monthly Detail'!$4:$4, '2025 Overview'!G$19, 'Monthly Detail'!89:89) -> -3990.04 | H50: =-SUMIF('Monthly Detail'!$4:$4, '2025 Overview'!H$19, 'Monthly Detail'!89:89) -> -3355.51 | I50: =-SUMIF('Monthly Detail'!$4:$4, '2025 Overview'!I$19, 'Monthly Detail'!89:89) -> -3680.41 | J50: =-SUMIF('Monthly Detail'!$4:$4, '2025 Overview'!J$19, 'Monthly Detail'!89:89) -> -3609.26 | ... N50: =-SUMIF('Monthly Detail'!$4:$4, '2025 Overview'!N$19, 'Monthly Detail'!89:89) -> -5037.9024 | P50: =+SUM('Monthly Detail'!AO69:AS69) -> 455.51
B51: Owner Cash Burn/Allowance | C51: =SUMIF('Monthly Detail'!$4:$4, '2025 Overview'!C$19, 'Monthly Detail'!154:154) -> -3116.58 | D51: =SUMIF('Monthly Detail'!$4:$4, '2025 Overview'!D$19, 'Monthly Detail'!154:154) -> -1624.48 | E51: =SUMIF('Monthly Detail'!$4:$4, '2025 Overview'!E$19, 'Monthly Detail'!154:154) -> -1433.72 | F51: =SUMIF('Monthly Detail'!$4:$4, '2025 Overview'!F$19, 'Monthly Detail'!154:154) -> -1790.11 | G51: =SUMIF('Monthly Detail'!$4:$4, '2025 Overview'!G$19, 'Monthly Detail'!154:154) -> -774.65 | H51: =SUMIF('Monthly Detail'!$4:$4,'2025 Overview'!H$19,'Monthly Detail'!154:154)-SUMIF('Monthly Detail'!$4:$4,H19,'Monthly Detail'!68:68) -> -3063.31 | I51: =SUMIF('Monthly Detail'!$4:$4,'2025 Overview'!I$19,'Monthly Detail'!154:154)-SUMIF('Monthly Detail'!$4:$4,I19,'Monthly Detail'!68:68) -> -4238.01 | J51: =SUMIF('Monthly Detail'!$4:$4,'2025 Overview'!J$19,'Monthly Detail'!154:154)-SUMIF('Monthly Detail'!$4:$4,J19,'Monthly Detail'!68:68) -> -3050.22 | K51: =SUMIF('Monthly Detail'!$4:$4,'2025 Overview'!K$19,'Monthly Detail'!154:154)-SUMIF('Monthly Detail'!$4:$4,K19,'Monthly Detail'!68:68) -> -4466.66 | L51: =SUMIF('Monthly Detail'!$4:$4,'2025 Overview'!L$19,'Monthly Detail'!154:154)-SUMIF('Monthly Detail'!$4:$4,L19,'Monthly Detail'!68:68) -> -3243.56 | M51: =SUMIF('Monthly Detail'!$4:$4,'2025 Overview'!M$19,'Monthly Detail'!154:154)-SUMIF('Monthly Detail'!$4:$4,M19,'Monthly Detail'!68:68) -> -2100 | N51: =SUMIF('Monthly Detail'!$4:$4,'2025 Overview'!N$19,'Monthly Detail'!154:154)-SUMIF('Monthly Detail'!$4:$4,N19,'Monthly Detail'!68:68) -> -2100 | P51: =+P49-P50 -> 1923.529
B52: Operating Cash Runway | C52: =+C46-SUM('Monthly Detail'!AC89:AN89)-SUM('Monthly Detail'!AC61:AN61) -> -32667.032 | D52: =+D46-SUM('Monthly Detail'!AD89:AO89)-SUM('Monthly Detail'!AD61:AO61) -> -35245.302 | E52: =+E46-SUM('Monthly Detail'!AE89:AP89)-SUM('Monthly Detail'!AE61:AP61) -> -37994.724 | F52: =+F46-SUM('Monthly Detail'!AF89:AQ89)-SUM('Monthly Detail'!AF61:AQ61) -> -41616.711 | G52: =+G46-SUM('Monthly Detail'!AG89:AR89)-SUM('Monthly Detail'!AG61:AR61) -> -41691.299 | H52: =+H46-SUM('Monthly Detail'!AH89:AS89)-SUM('Monthly Detail'!AH61:AS61) -> -42111.731 | I52: =+I46-SUM('Monthly Detail'!AI89:AT89)-SUM('Monthly Detail'!AI61:AT61) -> -44079.774 | J52: =+J46-SUM('Monthly Detail'!AJ89:AU89)-SUM('Monthly Detail'!AJ61:AU61) -> -44785.641 | ... N52: =+N46-SUM('Monthly Detail'!AN89:AY89)-SUM('Monthly Detail'!AN61:AY61) -> -53577.539
B53: Owner Cash Runway | C53: =+C48-SUM('Monthly Detail'!AC89:AN89)-SUM('Monthly Detail'!AC61:AN61) -> -31952.92 | D53: =+D48-SUM('Monthly Detail'!AD89:AO89)-SUM('Monthly Detail'!AD61:AO61) -> -34380.14 | E53: =+E48-SUM('Monthly Detail'!AE89:AP89)-SUM('Monthly Detail'!AE61:AP61) -> -36808.49 | F53: =+F48-SUM('Monthly Detail'!AF89:AQ89)-SUM('Monthly Detail'!AF61:AQ61) -> -40108.82 | G53: =+G48-SUM('Monthly Detail'!AG89:AR89)-SUM('Monthly Detail'!AG61:AR61) -> -39400.92 | H53: =+H48-SUM('Monthly Detail'!AH89:AS89)-SUM('Monthly Detail'!AH61:AS61) -> -39762.87 | I53: =+I48-SUM('Monthly Detail'!AI89:AT89)-SUM('Monthly Detail'!AI61:AT61) -> -41757.79 | J53: =+J48-SUM('Monthly Detail'!AJ89:AU89)-SUM('Monthly Detail'!AJ61:AU61) -> -42281.36 | ... N53: =+N48-SUM('Monthly Detail'!AN89:AY89)-SUM('Monthly Detail'!AN61:AY61) -> -51132.843
B54: Operating Cash Runway - Burn Rate | C54: =+C46/-C50 -> 0.61344558 | D54: =+D46/-D50 -> 0.44407951 | E54: =+E46/-E50 -> 0.60441941 | F54: =+F46/-F50 -> 0.54226579 | G54: =+G46/-G50 -> 1.0660447 | H54: =+H46/-H50 -> 1.3000019 | I54: =+I46/-I50 -> 1.1716782 | J54: =+J46/-J50 -> 1.2885767 | ... N54: =+N46/-N50 -> 0.90119824
B55: Cash Runway - Owner Burn Rate | C55: =+IFERROR(C48/-C51, 0) -> 0.65466633 | D55: =+IFERROR(D48/-D51, 0) -> 1.52165 | E55: =+IFERROR(E48/-E51, 0) -> 2.3639483 | F55: =+IFERROR(F48/-F51, 0) -> 2.4067013 | G55: =+IFERROR(G48/-G51, 0) -> 8.4476086 | H55: =+IFERROR(H48/-H51, 0) -> 2.1907773 | I55: =+IFERROR(I48/-I51, 0) -> 1.565414 | J55: =+IFERROR(J48/-J51, 0) -> 2.3457619 | ... N55: =+IFERROR(N48/-N51, 0) -> 3.3261164

Sheet 2025 AOP
B15: 2025 Overview
C18: January | D18: February | E18: March | F18: April | G18: May | H18: June | I18: July | J18: August | K18: September | L18: October | M18: November | N18: December | P18: Total
C19: 45688 | D19: 45716 | E19: 45747 | F19: 45777 | G19: 45808 | H19: 45838 | I19: 45869 | J19: 45900 | K19: 45930 | L19: 45961 | M19: 45991 | N19: 46022 | O19: 45322
B20: Service Income | C20: 7249.7138 | D20: 4913.4872 | E20: 6536.7151 | F20: 9380.6106 | G20: 10754.417 | H20: 10296.469 | I20: 8231.419 | J20: 7580.1793 | K20: 6911.5121 | L20: 7871.8411 | M20: 7017.7073 | N20: 8571.1673 | P20: 95315.238
B21: Misc. | C21: 0 | D21: 0 | E21: 0 | F21: 0 | G21: 0 | H21: 0 | I21: 0 | J21: 0 | K21: 0 | L21: 0 | M21: 0 | N21: 0 | P21: 0
B22: Total Income | C22: 7249.7138 | D22: 4913.4872 | E22: 6536.7151 | F22: 9380.6106 | G22: 10754.417 | H22: 10296.469 | I22: 8231.419 | J22: 7580.1793 | K22: 6911.5121 | L22: 7871.8411 | M22: 7017.7073 | N22: 8571.1673 | P22: 95315.238
B23: # of Appointments | C23: 80.370052 | D23: 59.794008 | E23: 75.759674 | F23: 108.72005 | G23: 130.30784 | H23: 113.65213 | I23: 95.401071 | J23: 92.036778 | K23: 76.462454 | L23: 91.23361 | M23: 85.852884 | N23: 94.608295 | P23: 1104.1988
B24: MRR | C24: 5375.6771 | D24: 3207.5442 | E24: 4505.4852 | F24: 6748.1072 | G24: 7779.5024 | H24: 7231.6338 | I24: 6123.8576 | J24: 5252.8868 | K24: 4808.0085 | L24: 5880.5453 | M24: 4643.0956 | N24: 6105.5718 | P24: 5638.493
B25: Recurring Client Base | C25: 40.158949 | D25: 33.93714 | E25: 40.724568 | F25: 55.996281 | G25: 66.743042 | H25: 59.955614 | I25: 47.511996 | J25: 49.208853 | K25: 40.724568 | L25: 45.24952 | M25: 48.077615 | N25: 49.208853
B28: Software - COS | C28: 214.68476 | D28: 145.50241 | E28: 193.57083 | F28: 277.78671 | G28: 318.46904 | H28: 304.9079 | I28: 243.75586 | J28: 224.47079 | K28: 204.66964 | L28: 233.10773 | M28: 207.81439 | N28: 253.81678 | P28: 2822.5568
B29: Materials - COGS | C29: 244.43671 | D29: 165.66677 | E29: 220.39672 | F29: 316.28361 | G29: 362.60387 | H29: 347.16337 | I29: 277.53661 | J29: 255.57893 | K29: 233.03366 | L29: 265.41282 | M29: 236.61421 | N29: 288.99182 | P29: 3213.7191
B30: Contractors - COS | C30: 0 | D30: 300 | E30: 540 | F30: 940.80078 | G30: 1179.6343 | H30: 980.02097 | I30: 381.01607 | J30: 540 | K30: 300 | L30: 558.50415 | M30: 540 | N30: 680.08064 | P30: 6940.0569
B31: Total Cost of Goods Sold (COGS) | C31: 459.12148 | D31: 611.16918 | E31: 953.96755 | F31: 1534.8711 | G31: 1860.7072 | H31: 1632.0922 | I31: 902.30854 | J31: 1020.0497 | K31: 737.7033 | L31: 1057.0247 | M31: 984.4286 | N31: 1222.8892 | P31: 12976.333
B33: Gross Margin | C33: 6790.5923 | D33: 4302.318 | E33: 5582.7475 | F33: 7845.7395 | G33: 8893.7095 | H33: 8664.3768 | I33: 7329.1104 | J33: 6560.1295 | K33: 6173.8088 | L33: 6814.8164 | M33: 6033.2787 | N33: 7348.278 | P33: 82338.906
B34: GM % | C34: 0.9366704 | D34: 0.87561397 | E34: 0.8540601 | F34: 0.83637834 | G34: 0.82698204 | H34: 0.8414901 | I34: 0.89038238 | J34: 0.86543198 | K34: 0.89326456 | L34: 0.86572078 | M34: 0.85972219 | N34: 0.85732524 | P34: 0.86385878
B36: General & Admintrative Expenses | C36: 2422.1893 | D36: 6297.7867 | E36: 6297.7867 | F36: 6297.7867 | G36: 6297.7867 | H36: 6347.7867 | I36: 6297.7867 | J36: 6297.7867 | K36: 6297.7867 | L36: 6402.7867 | M36: 6297.7867 | N36: 6297.7867 | P36: 71852.843
B37: Operating Expenses | C37: 2422.1893 | D37: 6297.7867 | E37: 6297.7867 | F37: 6297.7867 | G37: 6297.7867 | H37: 6347.7867 | I37: 6297.7867 | J37: 6297.7867 | K37: 6297.7867 | L37: 6402.7867 | M37: 6297.7867 | N37: 6297.7867 | P37: 71852.843
B39: Net Operating Income (EBITDA) | C39: 4368.403 | D39: -1995.4687 | E39: -715.03914 | F39: 1547.9528 | G39: 2595.9228 | H39: 2316.5901 | I39: 1031.3238 | J39: 262.34287 | K39: -123.97782 | L39: 412.0297 | M39: -264.50799 | N39: 1050.4914 | P39: 10486.063
B40: EBITDA % | C40: 0.60256213 | D40: -0.40612066 | E40: -0.10938815 | F40: 0.16501621 | G40: 0.24138202 | H40: 0.22498879 | I40: 0.12529113 | J40: 0.034609059 | K40: -0.017937872 | L40: 0.052342228 | M40: -0.037691511 | N40: 0.12256106 | P40: 0.11001455
B42: Other Income / (Expense) | C42: 0 | D42: 0 | E42: 0 | F42: 0 | G42: 0 | H42: 0 | I42: 0 | J42: 0 | K42: 0 | L42: 0 | M42: 0 | N42: 0 | P42: 0
B43: Net Income | C43: 4368.403 | D43: -1995.4687 | E43: -715.03914 | F43: 1547.9528 | G43: 2595.9228 | H43: 2316.5901 | I43: 1031.3238 | J43: 262.34287 | K43: -123.97782 | L43: 412.0297 | M43: -264.50799 | N43: 1050.4914 | P43: 10486.063
B44: NI % | C44: 0.60256213 | D44: -0.40612066 | E44: -0.10938815 | F44: 0.16501621 | G44: 0.24138202 | H44: 0.22498879 | I44: 0.12529113 | J44: 0.034609059 | K44: -0.017937872 | L44: 0.052342228 | M44: -0.037691511 | N44: 0.12256106 | P44: 0.11001455
B46: Operating (Business) Cash | C46: 1971.0959 | D46: 1048.9393 | E46: 874.49432 | F46: 2144.9226 | G46: 4127.9302 | H46: 5968.4948 | I46: 5707.9614 | J46: 4917.3937 | K46: 3876.0898 | L46: 3148.398 | M46: 2019.7107 | N46: 1694.3507
B47: Savings Cash | C47: 28.95 | D47: 28.95 | E47: 28.95 | F47: 28.95 | G47: 28.95 | H47: 28.95 | I47: 28.95 | J47: 28.95 | K47: 28.95 | L47: 28.95 | M47: 28.95 | N47: 28.95
B48: Total Cash Balance | C48: 3032.4552 | D48: 1613.7528 | E48: 1345.3759 | F48: 3299.881 | G48: 6350.6618 | H48: 9182.2997 | I48: 8781.4791 | J48: 7565.2211 | K48: 5963.215 | L48: 4843.6892 | M48: 3107.2473 | N48: 2606.6934
B49: Total Cash Inflow (Outflow) | C49: 2311.7784 | D49: -1418.7024 | E49: -268.3769 | F49: 1954.5051 | G49: 3050.7809 | H49: 2831.6379 | I49: -400.8206 | J49: -1216.258 | K49: -1602.006 | L49: -1119.5258 | M49: -1736.4419 | N49: -500.55389
B50: Operating Cash Burn | C50: 2422.1893 | D50: 6297.7867 | E50: 6297.7867 | F50: 6297.7867 | G50: 6297.7867 | H50: 6347.7867 | I50: 6297.7867 | J50: 6297.7867 | K50: 6297.7867 | L50: 6402.7867 | M50: 6297.7867 | N50: 6297.7867
B51: Owner Cash Burn/Allowance | C51: -2000 | D51: -1500 | E51: -1500 | F51: -1500 | G51: -1500 | H51: -1500 | I51: -1500 | J51: -1500 | K51: -1500 | L51: -1500 | M51: -1500 | N51: -1500
B52: Operating Cash Runway | C52: -32096.07 | D52: -38423.252 | E52: -44525.631 | F52: -49542.441 | G52: -51632.187 | H52: -54259.202 | I52: -59152.84 | J52: -63722.694 | K52: -69200.348 | L52: -73914.531 | M52: -78664.644 | N52: -83134.825
B53: Owner Cash Runway | C53: -31034.711 | D53: -37858.439 | E53: -44054.75 | F53: -48387.483 | G53: -49409.456 | H53: -51045.397 | I53: -56079.322 | J53: -61074.867 | K53: -67113.223 | L53: -72219.24 | M53: -77577.107 | N53: -82222.482
B54: Operating Cash Runway - Burn Rate | C54: -0.81376623 | D54: -0.16655682 | E54: -0.13885741 | F54: -0.34058356 | G54: -0.65545729 | H54: -0.94024817 | I54: -0.90634404 | J54: -0.780813 | K54: -0.61546857 | L54: -0.49172308 | M54: -0.32070167 | N54: -0.26903907
B55: Cash Runway - Owner Burn Rate | C55: 1.5162276 | D55: 1.0758352 | E55: 0.89691725 | F55: 2.1999206 | G55: 4.2337745 | H55: 6.1215331 | I55: 5.8543194 | J55: 5.0434807 | K55: 3.9754767 | L55: 3.2291261 | M55: 2.0714982 | N55: 1.7377956

Sheet 2024 Overview
B15: 2024 Overview
C18: January | D18: February | E18: March | F18: April | G18: May | H18: June | I18: July | J18: August | K18: September | L18: October | M18: November | N18: December | P18: Total
C19: 45322 | D19: 45351 | E19: 45382 | F19: 45412 | G19: 45443 | H19: 45473 | I19: 45504 | J19: 45535 | K19: 45565 | L19: 45596 | M19: 45626 | N19: 45657 | O19: 45322
B20: Service Income | C20: =SUMIF('Monthly Detail'!$4:$4, '2024 Overview'!C$19, 'Monthly Detail'!13:13) -> 5728.5 | D20: =SUMIF('Monthly Detail'!$4:$4, '2024 Overview'!D$19, 'Monthly Detail'!13:13) -> 6746.25 | E20: =SUMIF('Monthly Detail'!$4:$4, '2024 Overview'!E$19, 'Monthly Detail'!13:13) -> 7639.25 | F20: =SUMIF('Monthly Detail'!$4:$4, '2024 Overview'!F$19, 'Monthly Detail'!13:13) -> 7817 | G20: =SUMIF('Monthly Detail'!$4:$4, '2024 Overview'!G$19, 'Monthly Detail'!13:13) -> 8048 | H20: =SUMIF('Monthly Detail'!$4:$4, '2024 Overview'!H$19, 'Monthly Detail'!13:13) -> 7154 | I20: =SUMIF('Monthly Detail'!$4:$4, '2024 Overview'!I$19, 'Monthly Detail'!13:13) -> 6015.5 | J20: =SUMIF('Monthly Detail'!$4:$4, '2024 Overview'!J$19, 'Monthly Detail'!13:13) -> 7295 | ... N20: =SUMIF('Monthly Detail'!$4:$4, '2024 Overview'!N$19, 'Monthly Detail'!13:13) -> 6152 | P20: =SUM(C20:O20) -> 79769.25
B21: Misc. | C21: =SUMIF('Monthly Detail'!$4:$4, '2024 Overview'!C$19, 'Monthly Detail'!12:12) -> 0 | D21: =SUMIF('Monthly Detail'!$4:$4, '2024 Overview'!D$19, 'Monthly Detail'!12:12) -> 0 | E21: =SUMIF('Monthly Detail'!$4:$4, '2024 Overview'!E$19, 'Monthly Detail'!12:12) -> 0 | F21: =SUMIF('Monthly Detail'!$4:$4, '2024 Overview'!F$19, 'Monthly Detail'!12:12) -> 0 | G21: =SUMIF('Monthly Detail'!$4:$4, '2024 Overview'!G$19, 'Monthly Detail'!12:12) -> 0 | H21: =SUMIF('Monthly Detail'!$4:$4, '2024 Overview'!H$19, 'Monthly Detail'!12:12) -> 0 | I21: =SUMIF('Monthly Detail'!$4:$4, '2024 Overview'!I$19, 'Monthly Detail'!12:12) -> 0 | J21: =SUMIF('Monthly Detail'!$4:$4, '2024 Overview'!J$19, 'Monthly Detail'!12:12) -> 0 | ... N21: =SUMIF('Monthly Detail'!$4:$4, '2024 Overview'!N$19, 'Monthly Detail'!12:12) -> 0 | P21: =SUM(C21:O21) -> 0
B22: Total Income | C22: =SUM(C20:C21) -> 5728.5 | D22: =SUM(D20:D21) -> 6746.25 | E22: =SUM(E20:E21) -> 7639.25 | F22: =SUM(F20:F21) -> 7817 | G22: =SUM(G20:G21) -> 8048 | H22: =SUM(H20:H21) -> 7154 | I22: =SUM(I20:I21) -> 6015.5 | J22: =SUM(J20:J21) -> 7295 | ... N22: =SUM(N20:N21) -> 6152 | P22: =SUM(P20:P20) -> 79769.25
B23: # of Appointments | C23: =+'Monthly Detail'!AB15 -> 67 | D23: =+'Monthly Detail'!AC15 -> 74 | E23: =+'Monthly Detail'!AD15 -> 77 | F23: =+'Monthly Detail'!AE15 -> 78 | G23: =+'Monthly Detail'!AF15 -> 82 | H23: =+'Monthly Detail'!AG15 -> 75 | I23: =+'Monthly Detail'!AH15 -> 66 | J23: =+'Monthly Detail'!AI15 -> 74 | ... N23: =+'Monthly Detail'!AM15 -> 61 | P23: =+SUM(C23:N23) -> 833
B24: MRR | C24: =+'Monthly Detail'!AB41 -> 3806.3752 | D24: =+'Monthly Detail'!AC41 -> 3565.126 | E24: =+'Monthly Detail'!AD41 -> 3434.6887 | F24: =+'Monthly Detail'!AE41 -> 2659.5028 | G24: =+'Monthly Detail'!AF41 -> 4158.3869 | H24: =+'Monthly Detail'!AG41 -> 3809.8225 | I24: =+'Monthly Detail'!AH41 -> 3948.4455 | J24: =+'Monthly Detail'!AI41 -> 4344.1941 | ... N24: =+'Monthly Detail'!AM41 -> 3217.3525 | P24: =+AVERAGE(C24:N24) -> 3744.252
B25: Recurring Client Base | C25: =+'Monthly Detail'!AB17 -> 30 | D25: =+'Monthly Detail'!AC17 -> 34 | E25: =+'Monthly Detail'!AD17 -> 27 | F25: =+'Monthly Detail'!AE17 -> 19 | G25: =+'Monthly Detail'!AF17 -> 30 | H25: =+'Monthly Detail'!AG17 -> 30 | I25: =+'Monthly Detail'!AH17 -> 29 | J25: =+'Monthly Detail'!AI17 -> 34 | ... N25: =+'Monthly Detail'!AM17 -> 25
B28: Software - COS | C28: =SUMIF('Monthly Detail'!$4:$4, '2024 Overview'!C$19, 'Monthly Detail'!58:58) -> 144.34 | D28: =SUMIF('Monthly Detail'!$4:$4, '2024 Overview'!D$19, 'Monthly Detail'!58:58) -> 195.79 | E28: =SUMIF('Monthly Detail'!$4:$4, '2024 Overview'!E$19, 'Monthly Detail'!58:58) -> 210.1 | F28: =SUMIF('Monthly Detail'!$4:$4, '2024 Overview'!F$19, 'Monthly Detail'!58:58) -> 193.92 | G28: =SUMIF('Monthly Detail'!$4:$4, '2024 Overview'!G$19, 'Monthly Detail'!58:58) -> 192.8 | H28: =SUMIF('Monthly Detail'!$4:$4, '2024 Overview'!H$19, 'Monthly Detail'!58:58) -> 204.71 | I28: =SUMIF('Monthly Detail'!$4:$4, '2024 Overview'!I$19, 'Monthly Detail'!58:58) -> 174.91 | J28: =SUMIF('Monthly Detail'!$4:$4, '2024 Overview'!J$19, 'Monthly Detail'!58:58) -> 191.38 | ... N28: =SUMIF('Monthly Detail'!$4:$4, '2024 Overview'!N$19, 'Monthly Detail'!58:58) -> 171.4 | P28: =+SUM(C28:N28) -> 2199.12
B29: Materials - COGS | C29: =SUMIF('Monthly Detail'!$4:$4, '2024 Overview'!C$19, 'Monthly Detail'!59:59) -> 359.46 | D29: =SUMIF('Monthly Detail'!$4:$4, '2024 Overview'!D$19, 'Monthly Detail'!59:59) -> 458.1 | E29: =SUMIF('Monthly Detail'!$4:$4, '2024 Overview'!E$19, 'Monthly Detail'!59:59) -> 321.74 | F29: =SUMIF('Monthly Detail'!$4:$4, '2024 Overview'!F$19, 'Monthly Detail'!59:59) -> 142.87 | G29: =SUMIF('Monthly Detail'!$4:$4, '2024 Overview'!G$19, 'Monthly Detail'!59:59) -> 753.32 | H29: =SUMIF('Monthly Detail'!$4:$4, '2024 Overview'!H$19, 'Monthly Detail'!59:59) -> 314.9 | I29: =SUMIF('Monthly Detail'!$4:$4, '2024 Overview'!I$19, 'Monthly Detail'!59:59) -> 165.74 | J29: =SUMIF('Monthly Detail'!$4:$4, '2024 Overview'!J$19, 'Monthly Detail'!59:59) -> 38.46 | ... N29: =SUMIF('Monthly Detail'!$4:$4, '2024 Overview'!N$19, 'Monthly Detail'!59:59) -> 589.19 | P29: =+SUM(C29:N29) -> 3885.61
B30: Contractors - COS | C30: =SUMIF('Monthly Detail'!$4:$4, '2024 Overview'!C$19, 'Monthly Detail'!60:60) -> 0 | D30: =SUMIF('Monthly Detail'!$4:$4, '2024 Overview'!D$19, 'Monthly Detail'!60:60) -> 0 | E30: =SUMIF('Monthly Detail'!$4:$4, '2024 Overview'!E$19, 'Monthly Detail'!60:60) -> 0 | F30: =SUMIF('Monthly Detail'!$4:$4, '2024 Overview'!F$19, 'Monthly Detail'!60:60) -> 0 | G30: =SUMIF('Monthly Detail'!$4:$4, '2024 Overview'!G$19, 'Monthly Detail'!60:60) -> 475 | H30: =SUMIF('Monthly Detail'!$4:$4, '2024 Overview'!H$19, 'Monthly Detail'!60:60) -> 765 | I30: =SUMIF('Monthly Detail'!$4:$4, '2024 Overview'!I$19, 'Monthly Detail'!60:60) -> 394 | J30: =SUMIF('Monthly Detail'!$4:$4, '2024 Overview'!J$19, 'Monthly Detail'!60:60) -> 610 | ... N30: =SUMIF('Monthly Detail'!$4:$4, '2024 Overview'!N$19, 'Monthly Detail'!60:60) -> 470 | P30: =+SUM(C30:N30) -> 4126
B31: Total Cost of Goods Sold (COGS) | C31: =SUM(C28:C30) -> 503.8 | D31: =SUM(D28:D30) -> 653.89 | E31: =SUM(E28:E30) -> 531.84 | F31: =SUM(F28:F30) -> 336.79 | G31: =SUM(G28:G30) -> 1421.12 | H31: =SUM(H28:H30) -> 1284.61 | I31: =SUM(I28:I30) -> 734.65 | J31: =SUM(J28:J30) -> 839.84 | ... N31: =SUM(N28:N30) -> 1230.59 | P31: =SUM(P28:P30) -> 10210.73
B33: Gross Margin | C33: =+C22-C31 -> 5224.7 | D33: =+D22-D31 -> 6092.36 | E33: =+E22-E31 -> 7107.41 | F33: =+F22-F31 -> 7480.21 | G33: =+G22-G31 -> 6626.88 | H33: =+H22-H31 -> 5869.39 | I33: =+I22-I31 -> 5280.85 | J33: =+J22-J31 -> 6455.16 | ... N33: =+N22-N31 -> 4921.41 | P33: =+SUM(C33:N33) -> 69558.52
B34: GM % | C34: =IFERROR(C33/C22, 0) -> 0.91205377 | D34: =IFERROR(D33/D22, 0) -> 0.90307356 | E34: =IFERROR(E33/E22, 0) -> 0.9303806 | F34: =IFERROR(F33/F22, 0) -> 0.9569157 | G34: =IFERROR(G33/G22, 0) -> 0.82341948 | H34: =IFERROR(H33/H22, 0) -> 0.82043472 | I34: =IFERROR(I33/I22, 0) -> 0.87787383 | J34: =IFERROR(J33/J22, 0) -> 0.88487457 | ... N34: =IFERROR(N33/N22, 0) -> 0.79996912 | P34: =P33/P22 -> 0.87199667
B36: General & Admintrative Expenses | C36: =SUMIF('Monthly Detail'!$4:$4, '2024 Overview'!C$19, 'Monthly Detail'!$89:$89) -> 959.96 | D36: =SUMIF('Monthly Detail'!$4:$4, '2024 Overview'!D$19, 'Monthly Detail'!$89:$89) -> 850.04 | E36: =SUMIF('Monthly Detail'!$4:$4, '2024 Overview'!E$19, 'Monthly Detail'!$89:$89) -> 791.98 | F36: =SUMIF('Monthly Detail'!$4:$4, '2024 Overview'!F$19, 'Monthly Detail'!$89:$89) -> 1208.63 | G36: =SUMIF('Monthly Detail'!$4:$4, '2024 Overview'!G$19, 'Monthly Detail'!$89:$89) -> 2664.62 | H36: =SUMIF('Monthly Detail'!$4:$4, '2024 Overview'!H$19, 'Monthly Detail'!$89:$89) -> 2227.69 | I36: =SUMIF('Monthly Detail'!$4:$4, '2024 Overview'!I$19, 'Monthly Detail'!$89:$89) -> 1832.34 | J36: =SUMIF('Monthly Detail'!$4:$4, '2024 Overview'!J$19, 'Monthly Detail'!$89:$89) -> 2698.71 | ... N36: =SUMIF('Monthly Detail'!$4:$4, '2024 Overview'!N$19, 'Monthly Detail'!$89:$89) -> 2293.47 | P36: =SUM(C36:O36) -> 22587.09
B37: Operating Expenses | C37: =SUM(C36:C36) -> 959.96 | D37: =SUM(D36:D36) -> 850.04 | E37: =SUM(E36:E36) -> 791.98 | F37: =SUM(F36:F36) -> 1208.63 | G37: =SUM(G36:G36) -> 2664.62 | H37: =SUM(H36:H36) -> 2227.69 | I37: =SUM(I36:I36) -> 1832.34 | J37: =SUM(J36:J36) -> 2698.71 | ... N37: =SUM(N36:N36) -> 2293.47 | P37: =SUM(P36:P36) -> 22587.09
B39: Net Operating Income (EBITDA) | C39: =C33-C37 -> 4264.74 | D39: =D33-D37 -> 5242.32 | E39: =E33-E37 -> 6315.43 | F39: =F33-F37 -> 6271.58 | G39: =G33-G37 -> 3962.26 | H39: =H33-H37 -> 3641.7 | I39: =I33-I37 -> 3448.51 | J39: =J33-J37 -> 3756.45 | ... N39: =N33-N37 -> 2627.94 | P39: =P33-P37 -> 46971.43
B40: EBITDA % | C40: =IFERROR(C39/C22, 0) -> 0.74447761 | D40: =IFERROR(D39/D22, 0) -> 0.77707171 | E40: =IFERROR(E39/E22, 0) -> 0.82670812 | F40: =IFERROR(F39/F22, 0) -> 0.80230012 | G40: =IFERROR(G39/G22, 0) -> 0.49232853 | H40: =IFERROR(H39/H22, 0) -> 0.50904389 | I40: =IFERROR(I39/I22, 0) -> 0.57327072 | J40: =IFERROR(J39/J22, 0) -> 0.51493489 | ... N40: =IFERROR(N39/N22, 0) -> 0.4271684 | P40: =P39/P22 -> 0.58884131
B42: Other Income / (Expense) | C42: =SUMIF('Monthly Detail'!$4:$4, '2024 Overview'!C$19, 'Monthly Detail'!130:130) -> 0 | D42: =SUMIF('Monthly Detail'!$4:$4, '2024 Overview'!D$19, 'Monthly Detail'!130:130) -> 0 | E42: =SUMIF('Monthly Detail'!$4:$4, '2024 Overview'!E$19, 'Monthly Detail'!130:130) -> 0 | F42: =SUMIF('Monthly Detail'!$4:$4, '2024 Overview'!F$19, 'Monthly Detail'!130:130) -> 0 | G42: =SUMIF('Monthly Detail'!$4:$4, '2024 Overview'!G$19, 'Monthly Detail'!130:130) -> 0 | H42: =SUMIF('Monthly Detail'!$4:$4, '2024 Overview'!H$19, 'Monthly Detail'!130:130) -> 0 | I42: =SUMIF('Monthly Detail'!$4:$4, '2024 Overview'!I$19, 'Monthly Detail'!130:130) -> 0 | J42: =SUMIF('Monthly Detail'!$4:$4, '2024 Overview'!J$19, 'Monthly Detail'!130:130) -> 0 | ... N42: =SUMIF('Monthly Detail'!$4:$4, '2024 Overview'!N$19, 'Monthly Detail'!130:130) -> 0 | P42: =SUM(C42:O42) -> 0
B43: Net Income | C43: =C39+SUM(C42:C42) -> 4264.74 | D43: =D39+SUM(D42:D42) -> 5242.32 | E43: =E39+SUM(E42:E42) -> 6315.43 | F43: =F39+SUM(F42:F42) -> 6271.58 | G43: =G39+SUM(G42:G42) -> 3962.26 | H43: =H39+SUM(H42:H42) -> 3641.7 | I43: =I39+SUM(I42:I42) -> 3448.51 | J43: =J39+SUM(J42:J42) -> 3756.45 | ... N43: =N39+SUM(N42:N42) -> 2627.94 | P43: =P39+SUM(P42:P42) -> 46971.43
B44: NI % | C44: =IFERROR(C43/C22, 0) -> 0.74447761 | D44: =IFERROR(D43/D22, 0) -> 0.77707171 | E44: =IFERROR(E43/E22, 0) -> 0.82670812 | F44: =IFERROR(F43/F22, 0) -> 0.80230012 | G44: =IFERROR(G43/G22, 0) -> 0.49232853 | H44: =IFERROR(H43/H22, 0) -> 0.50904389 | I44: =IFERROR(I43/I22, 0) -> 0.57327072 | J44: =IFERROR(J43/J22, 0) -> 0.51493489 | ... N44: =IFERROR(N43/N22, 0) -> 0.4271684 | P44: =P43/P22 -> 0.58884131
B46: Operating (Business) Cash | C46: =+'Monthly Detail'!AB112 -> 606.71 | D46: =+'Monthly Detail'!AC112 -> 679.7505 | E46: =+'Monthly Detail'!AD112 -> 1825.2845 | F46: =+'Monthly Detail'!AE112 -> 1156.948 | G46: =+'Monthly Detail'!AF112 -> 1696.8445 | H46: =+'Monthly Detail'!AG112 -> 1703.2405 | I46: =+'Monthly Detail'!AH112 -> 1893.281 | J46: =+'Monthly Detail'!AI112 -> 689.988 | ... N46: =+'Monthly Detail'!AM112 -> 926.9
B47: Savings Cash | C47: =+'Monthly Detail'!AB106 -> 130.91 | D47: =+'Monthly Detail'!AC106 -> 33.95 | E47: =+'Monthly Detail'!AD106 -> 770.48 | F47: =+'Monthly Detail'!AE106 -> 79.36 | G47: =+'Monthly Detail'!AF106 -> 107.93 | H47: =+'Monthly Detail'!AG106 -> 496.7 | I47: =+'Monthly Detail'!AH106 -> 27.5 | J47: =+'Monthly Detail'!AI106 -> 53.18 | ... N47: =+'Monthly Detail'!AM106 -> 92.91
B48: Total Cash Balance | C48: =+'Monthly Detail'!AB173 -> 933.4 | D48: =+'Monthly Detail'!AC173 -> 1045.77 | E48: =+'Monthly Detail'!AD173 -> 2808.13 | F48: =+'Monthly Detail'!AE173 -> 1779.92 | G48: =+'Monthly Detail'!AF173 -> 2610.53 | H48: =+'Monthly Detail'!AG173 -> 2620.37 | I48: =+'Monthly Detail'!AH173 -> 2912.74 | J48: =+'Monthly Detail'!AI173 -> 1061.52 | ... N48: =+'Monthly Detail'!AM173 -> 1426
B49: Total Cash Inflow (Outflow) | C49: =SUMIF('Monthly Detail'!$4:$4, '2024 Overview'!C$19, 'Monthly Detail'!170:170) -> 933.4 | D49: =SUMIF('Monthly Detail'!$4:$4, '2024 Overview'!D$19, 'Monthly Detail'!170:170) -> 112.37 | E49: =SUMIF('Monthly Detail'!$4:$4, '2024 Overview'!E$19, 'Monthly Detail'!170:170) -> 1762.36 | F49: =SUMIF('Monthly Detail'!$4:$4, '2024 Overview'!F$19, 'Monthly Detail'!170:170) -> -1028.21 | G49: =SUMIF('Monthly Detail'!$4:$4, '2024 Overview'!G$19, 'Monthly Detail'!170:170) -> 830.61 | H49: =SUMIF('Monthly Detail'!$4:$4, '2024 Overview'!H$19, 'Monthly Detail'!170:170) -> 9.84 | I49: =SUMIF('Monthly Detail'!$4:$4, '2024 Overview'!I$19, 'Monthly Detail'!170:170) -> 292.37 | J49: =SUMIF('Monthly Detail'!$4:$4, '2024 Overview'!J$19, 'Monthly Detail'!170:170) -> -1851.22 | ... N49: =SUMIF('Monthly Detail'!$4:$4, '2024 Overview'!N$19, 'Monthly Detail'!170:170) -> -410.67
B50: Operating Cash Burn | C50: =-'Monthly Detail'!AB89 -> -959.96 | D50: =-'Monthly Detail'!AC89 -> -850.04 | E50: =-'Monthly Detail'!AD89 -> -791.98 | F50: =-'Monthly Detail'!AE89 -> -1208.63 | G50: =-'Monthly Detail'!AF89 -> -2664.62 | H50: =-'Monthly Detail'!AG89 -> -2227.69 | I50: =-'Monthly Detail'!AH89 -> -1832.34 | J50: =-'Monthly Detail'!AI89 -> -2698.71 | ... N50: =-'Monthly Detail'!AM89 -> -2293.47
B51: Owner Cash Burn | C51: =+'Monthly Detail'!AB154 -> -4414.2 | D51: =+'Monthly Detail'!AC154 -> -5131.49 | E51: =+'Monthly Detail'!AD154 -> -4430.43 | F51: =+'Monthly Detail'!AE154 -> -7086.41 | G51: =+'Monthly Detail'!AF154 -> -3432.23 | H51: =+'Monthly Detail'!AG154 -> -3463.07 | I51: =+'Monthly Detail'!AH154 -> -2858.95 | J51: =+'Monthly Detail'!AI154 -> -5679.53 | ... N51: =+'Monthly Detail'!AM154 -> -3648.26
B52: Operating Cash Runway | C52: =+C46-SUM('Monthly Detail'!AC89:AN89)-SUM('Monthly Detail'!AC61:AN61) -> -33386.53 | D52: =+D46-SUM('Monthly Detail'!AD89:AO89)-SUM('Monthly Detail'!AD61:AO61) -> -36172.28 | E52: =+E46-SUM('Monthly Detail'!AE89:AP89)-SUM('Monthly Detail'!AE61:AP61) -> -38372.446 | F52: =+F46-SUM('Monthly Detail'!AF89:AQ89)-SUM('Monthly Detail'!AF61:AQ61) -> -43260.132 | G52: =+G46-SUM('Monthly Detail'!AG89:AR89)-SUM('Monthly Detail'!AG61:AR61) -> -44248.015 | H52: =+H46-SUM('Monthly Detail'!AH89:AS89)-SUM('Monthly Detail'!AH61:AS61) -> -44770.66 | I52: =+I46-SUM('Monthly Detail'!AI89:AT89)-SUM('Monthly Detail'!AI61:AT61) -> -46498.749 | J52: =+J46-SUM('Monthly Detail'!AJ89:AU89)-SUM('Monthly Detail'!AJ61:AU61) -> -48746.462 | ... N52: =+N46-SUM('Monthly Detail'!AN89:AY89)-SUM('Monthly Detail'!AN61:AY61) -> -57190.787
B53: Owner Cash Runway | C53: =+C48-SUM('Monthly Detail'!AC89:AN89)-SUM('Monthly Detail'!AC61:AN61) -> -33059.84 | D53: =+D48-SUM('Monthly Detail'!AD89:AO89)-SUM('Monthly Detail'!AD61:AO61) -> -35806.26 | E53: =+E48-SUM('Monthly Detail'!AE89:AP89)-SUM('Monthly Detail'!AE61:AP61) -> -37389.6 | F53: =+F48-SUM('Monthly Detail'!AF89:AQ89)-SUM('Monthly Detail'!AF61:AQ61) -> -42637.16 | G53: =+G48-SUM('Monthly Detail'!AG89:AR89)-SUM('Monthly Detail'!AG61:AR61) -> -43334.33 | H53: =+H48-SUM('Monthly Detail'!AH89:AS89)-SUM('Monthly Detail'!AH61:AS61) -> -43853.53 | I53: =+I48-SUM('Monthly Detail'!AI89:AT89)-SUM('Monthly Detail'!AI61:AT61) -> -45479.29 | J53: =+J48-SUM('Monthly Detail'!AJ89:AU89)-SUM('Monthly Detail'!AJ61:AU61) -> -48374.93 | ... N53: =+N48-SUM('Monthly Detail'!AN89:AY89)-SUM('Monthly Detail'!AN61:AY61) -> -56691.687
B54: Operating Cash Runway - Burn Rate | C54: =+C46/-C50 -> 0.63201592 | D54: =+D46/-D50 -> 0.79966884 | E54: =+E46/-E50 -> 2.3047103 | F54: =+F46/-F50 -> 0.95723919 | G54: =+G46/-G50 -> 0.63680544 | H54: =+H46/-H50 -> 0.76457698 | I54: =+I46/-I50 -> 1.0332586 | J54: =+J46/-J50 -> 0.25567327 | ... N54: =+N46/-N50 -> 0.40414743
B55: Cash Runway - Owner Burn Rate | C55: =+IFERROR(C48/-C51, 0) -> 0.21145394 | D55: =+IFERROR(D48/-D51, 0) -> 0.20379461 | E55: =+IFERROR(E48/-E51, 0) -> 0.63382787 | F55: =+IFERROR(F48/-F51, 0) -> 0.25117373 | G55: =+IFERROR(G48/-G51, 0) -> 0.76059297 | H55: =+IFERROR(H48/-H51, 0) -> 0.756661 | I55: =+IFERROR(I48/-I51, 0) -> 1.0188146 | J55: =+IFERROR(J48/-J51, 0) -> 0.18690279 | ... N55: =+IFERROR(N48/-N51, 0) -> 0.39087126

Sheet 2022 Overview
C10: =TEXT('Monthly Detail'!D4,"mmmm") -> January | D10: =TEXT('Monthly Detail'!E4,"mmmm") -> February | E10: =TEXT('Monthly Detail'!F4,"mmmm") -> March | F10: =TEXT('Monthly Detail'!G4,"mmmm") -> April | G10: =TEXT('Monthly Detail'!H4,"mmmm") -> May | H10: =TEXT('Monthly Detail'!I4,"mmmm") -> June | I10: =TEXT('Monthly Detail'!J4,"mmmm") -> July | J10: =TEXT('Monthly Detail'!K4,"mmmm") -> August | ... N10: =TEXT('Monthly Detail'!O4,"mmmm") -> December | P10: Total
C11: 44592 | D11: 44620 | E11: 44651 | F11: 44681 | G11: 44712 | H11: 44742 | I11: 44773 | J11: 44804 | K11: 44834 | L11: 44865 | M11: 44895 | N11: 44926
B12: Service Income | C12: =SUMIF('Monthly Detail'!$4:$4, '2022 Overview'!C$11, 'Monthly Detail'!9:9) -> 0 | D12: =SUMIF('Monthly Detail'!$4:$4, '2022 Overview'!D$11, 'Monthly Detail'!9:9) -> 0 | E12: =SUMIF('Monthly Detail'!$4:$4, '2022 Overview'!E$11, 'Monthly Detail'!9:9) -> 0 | F12: =SUMIF('Monthly Detail'!$4:$4, '2022 Overview'!F$11, 'Monthly Detail'!9:9) -> 0 | G12: =SUMIF('Monthly Detail'!$4:$4, '2022 Overview'!G$11, 'Monthly Detail'!9:9) -> 0 | H12: =SUMIF('Monthly Detail'!$4:$4, '2022 Overview'!H$11, 'Monthly Detail'!9:9) -> 0 | I12: =SUMIF('Monthly Detail'!$4:$4, '2022 Overview'!I$11, 'Monthly Detail'!9:9) -> 0 | J12: =SUMIF('Monthly Detail'!$4:$4, '2022 Overview'!J$11, 'Monthly Detail'!9:9) -> 0 | ... N12: =SUMIF('Monthly Detail'!$4:$4, '2022 Overview'!N$11, 'Monthly Detail'!9:9) -> 0 | P12: =SUM(C12:O12) -> 0
B13: Misc. | C13: =SUMIF('Monthly Detail'!$4:$4, '2022 Overview'!C$11, 'Monthly Detail'!12:12) -> 0 | D13: =SUMIF('Monthly Detail'!$4:$4, '2022 Overview'!D$11, 'Monthly Detail'!12:12) -> 0 | E13: =SUMIF('Monthly Detail'!$4:$4, '2022 Overview'!E$11, 'Monthly Detail'!12:12) -> 0 | F13: =SUMIF('Monthly Detail'!$4:$4, '2022 Overview'!F$11, 'Monthly Detail'!12:12) -> 0 | G13: =SUMIF('Monthly Detail'!$4:$4, '2022 Overview'!G$11, 'Monthly Detail'!12:12) -> 0 | H13: =SUMIF('Monthly Detail'!$4:$4, '2022 Overview'!H$11, 'Monthly Detail'!12:12) -> 0 | I13: =SUMIF('Monthly Detail'!$4:$4, '2022 Overview'!I$11, 'Monthly Detail'!12:12) -> 0 | J13: =SUMIF('Monthly Detail'!$4:$4, '2022 Overview'!J$11, 'Monthly Detail'!12:12) -> 0 | ... N13: =SUMIF('Monthly Detail'!$4:$4, '2022 Overview'!N$11, 'Monthly Detail'!12:12) -> 0
B14: Total Income | C14: 0.1 | D14: 0.1 | E14: 0.1 | F14: 0.1 | G14: 0.1 | H14: 0.1 | I14: 0.1 | J14: =SUM(J12:J13) -> 0 | K14: =SUM(K12:K13) -> 0 | L14: =SUM(L12:L13) -> 0 | M14: =SUM(M12:M13) -> 0 | N14: =SUM(N12:N13) -> 0 | P14: =SUM(P12:P12) -> 0
B16: Gross Margin | C16: =C14 -> 0.1 | D16: =D14 -> 0.1 | E16: =E14 -> 0.1 | F16: =F14 -> 0.1 | G16: =G14 -> 0.1 | H16: =H14 -> 0.1 | I16: =I14 -> 0.1 | J16: =J14 -> 0 | ... N16: =N14 -> 0 | P16: =P14 -> 0
B17: GM % | C17: =C16/C14 -> 1 | D17: =D16/D14 -> 1 | E17: =E16/E14 -> 1 | F17: =F16/F14 -> 1 | G17: =G16/G14 -> 1 | H17: =H16/H14 -> 1 | I17: =I16/I14 -> 1 | J17: =J16/J14 -> #DIV/0! | ... N17: =N16/N14 -> #DIV/0! | P17: =P16/P14 -> #DIV/0!
B19: General & Admintrative Expenses | C19: =SUMIF('Monthly Detail'!$4:$4, '2023 Overview'!C$11, 'Monthly Detail'!$89:$89) -> 0 | D19: =SUMIF('Monthly Detail'!$4:$4, '2023 Overview'!D$11, 'Monthly Detail'!$89:$89) -> 0 | E19: =SUMIF('Monthly Detail'!$4:$4, '2023 Overview'!E$11, 'Monthly Detail'!$89:$89) -> 0 | F19: =SUMIF('Monthly Detail'!$4:$4, '2023 Overview'!F$11, 'Monthly Detail'!$89:$89) -> 0 | G19: =SUMIF('Monthly Detail'!$4:$4, '2023 Overview'!G$11, 'Monthly Detail'!$89:$89) -> 0 | H19: =SUMIF('Monthly Detail'!$4:$4, '2023 Overview'!H$11, 'Monthly Detail'!$89:$89) -> 0 | I19: =SUMIF('Monthly Detail'!$4:$4, '2023 Overview'!I$11, 'Monthly Detail'!$89:$89) -> 0 | J19: =SUMIF('Monthly Detail'!$4:$4, '2023 Overview'!J$11, 'Monthly Detail'!$89:$89) -> 0 | ... N19: =SUMIF('Monthly Detail'!$4:$4, '2023 Overview'!N$11, 'Monthly Detail'!$89:$89) -> 0 | P19: =SUM(C19:O19) -> 0
B20: Owner Guarenteed Payments | C20: =SUMIF('Monthly Detail'!$4:$4, '2022 Overview'!C$11, 'Monthly Detail'!47:47) -> 0 | D20: =SUMIF('Monthly Detail'!$4:$4, '2022 Overview'!D$11, 'Monthly Detail'!47:47) -> 0 | E20: =SUMIF('Monthly Detail'!$4:$4, '2022 Overview'!E$11, 'Monthly Detail'!47:47) -> 0 | F20: =SUMIF('Monthly Detail'!$4:$4, '2022 Overview'!F$11, 'Monthly Detail'!47:47) -> 0 | G20: =SUMIF('Monthly Detail'!$4:$4, '2022 Overview'!G$11, 'Monthly Detail'!47:47) -> 0 | H20: =SUMIF('Monthly Detail'!$4:$4, '2022 Overview'!H$11, 'Monthly Detail'!47:47) -> 0 | I20: =SUMIF('Monthly Detail'!$4:$4, '2022 Overview'!I$11, 'Monthly Detail'!47:47) -> 0 | J20: =SUMIF('Monthly Detail'!$4:$4, '2022 Overview'!J$11, 'Monthly Detail'!47:47) -> 0 | ... N20: =SUMIF('Monthly Detail'!$4:$4, '2022 Overview'!N$11, 'Monthly Detail'!47:47) -> 0 | P20: =SUM(C20:O20) -> 0
B21: Operating Expenses | C21: =SUM(C19:C20) -> 0 | D21: =SUM(D19:D20) -> 0 | E21: =SUM(E19:E20) -> 0 | F21: =SUM(F19:F20) -> 0 | G21: =SUM(G19:G20) -> 0 | H21: =SUM(H19:H20) -> 0 | I21: =SUM(I19:I20) -> 0 | J21: =SUM(J19:J20) -> 0 | ... N21: =SUM(N19:N20) -> 0 | P21: =SUM(P19:P20) -> 0
B23: Net Operating Income (EBITDA) | C23: =C16-C21 -> 0.1 | D23: =D16-D21 -> 0.1 | E23: =E16-E21 -> 0.1 | F23: =F16-F21 -> 0.1 | G23: =G16-G21 -> 0.1 | H23: =H16-H21 -> 0.1 | I23: =I16-I21 -> 0.1 | J23: =J16-J21 -> 0 | ... N23: =N16-N21 -> 0 | P23: =P16-P21 -> 0
B24: EBITDA % | C24: =C23/C14 -> 1 | D24: =D23/D14 -> 1 | E24: =E23/E14 -> 1 | F24: =F23/F14 -> 1 | G24: =G23/G14 -> 1 | H24: =H23/H14 -> 1 | I24: =I23/I14 -> 1 | J24: =J23/J14 -> #DIV/0! | ... N24: =N23/N14 -> #DIV/0! | P24: =P23/P14 -> #DIV/0!
B26: Other Income / (Expense) | C26: =SUMIF('Monthly Detail'!$4:$4, '2022 Overview'!C$11, 'Monthly Detail'!77:77) -> 0 | D26: =SUMIF('Monthly Detail'!$4:$4, '2022 Overview'!D$11, 'Monthly Detail'!77:77) -> 0 | E26: =SUMIF('Monthly Detail'!$4:$4, '2022 Overview'!E$11, 'Monthly Detail'!77:77) -> 0 | F26: =SUMIF('Monthly Detail'!$4:$4, '2022 Overview'!F$11, 'Monthly Detail'!77:77) -> 0 | G26: =SUMIF('Monthly Detail'!$4:$4, '2022 Overview'!G$11, 'Monthly Detail'!77:77) -> 0 | H26: =SUMIF('Monthly Detail'!$4:$4, '2022 Overview'!H$11, 'Monthly Detail'!77:77) -> 0 | I26: =SUMIF('Monthly Detail'!$4:$4, '2022 Overview'!I$11, 'Monthly Detail'!77:77) -> 0 | J26: =SUMIF('Monthly Detail'!$4:$4, '2022 Overview'!J$11, 'Monthly Detail'!77:77) -> 0 | ... N26: =SUMIF('Monthly Detail'!$4:$4, '2022 Overview'!N$11, 'Monthly Detail'!77:77) -> 0 | P26: =SUM(C26:O26) -> 0
B27: Net Income | C27: =C23+SUM(C26:C26) -> 0.1 | D27: =D23+SUM(D26:D26) -> 0.1 | E27: =E23+SUM(E26:E26) -> 0.1 | F27: =F23+SUM(F26:F26) -> 0.1 | G27: =G23+SUM(G26:G26) -> 0.1 | H27: =H23+SUM(H26:H26) -> 0.1 | I27: =I23+SUM(I26:I26) -> 0.1 | J27: =J23+SUM(J26:J26) -> 0 | ... N27: =N23+SUM(N26:N26) -> 0 | P27: =P23+SUM(P26:P26) -> 0
B28: NI % | C28: =C27/C14 -> 1 | D28: =D27/D14 -> 1 | E28: =E27/E14 -> 1 | F28: =F27/F14 -> 1 | G28: =G27/G14 -> 1 | H28: =H27/H14 -> 1 | I28: =I27/I14 -> 1 | J28: =J27/J14 -> #DIV/0! | ... N28: =N27/N14 -> #DIV/0! | P28: =P27/P14 -> #DIV/0!
B30: Operating Cash | C30: =SUMIF('Monthly Detail'!$4:$4, '2022 Overview'!C$11, 'Monthly Detail'!173:173) -> 0 | D30: =SUMIF('Monthly Detail'!$4:$4, '2022 Overview'!D$11, 'Monthly Detail'!173:173) -> 0 | E30: =SUMIF('Monthly Detail'!$4:$4, '2022 Overview'!E$11, 'Monthly Detail'!173:173) -> 0 | F30: =SUMIF('Monthly Detail'!$4:$4, '2022 Overview'!F$11, 'Monthly Detail'!173:173) -> 0 | G30: =SUMIF('Monthly Detail'!$4:$4, '2022 Overview'!G$11, 'Monthly Detail'!173:173) -> 0 | H30: =SUMIF('Monthly Detail'!$4:$4, '2022 Overview'!H$11, 'Monthly Detail'!173:173) -> 0 | I30: =SUMIF('Monthly Detail'!$4:$4, '2022 Overview'!I$11, 'Monthly Detail'!173:173) -> 0 | J30: =SUMIF('Monthly Detail'!$4:$4, '2022 Overview'!J$11, 'Monthly Detail'!173:173) -> 0 | ... N30: =SUMIF('Monthly Detail'!$4:$4, '2022 Overview'!N$11, 'Monthly Detail'!173:173) -> 0
B31: Cash Inflow (Outflow) | C31: =SUMIF('Monthly Detail'!$4:$4, '2022 Overview'!C$11, 'Monthly Detail'!158:158) -> 0 | D31: =D30-C30 -> 0 | E31: =E30-D30 -> 0 | F31: =F30-E30 -> 0 | G31: =G30-F30 -> 0 | H31: =H30-G30 -> 0 | I31: =I30-H30 -> 0 | J31: =J30-I30 -> 0 | K31: =K30-J30 -> 0 | ... N31: =N30-M30 -> 0

Sheet Quarterly Overview
C9: 45382 | D9: 45473 | F9: 45565 | H9: 45657
C10: Q1 2025 | D10: Q2 2025 | E10: Variance | F10: Q3 2025 | G10: Variance | H10: Q4 2025 | I10: Variance | K10: Total
C11: =+C10 -> Q1 2025 | D11: =+D10 -> Q2 2025 | F11: =+F10 -> Q3 2025 | H11: =+H10 -> Q4 2025 | J11: 45322
B12: Nail Tech Services | C12: =SUMIF('Monthly Detail'!$3:$3, 'Quarterly Overview'!C$11, 'Monthly Detail'!13:13) -> 20330.69 | D12: =SUMIF('Monthly Detail'!$3:$3, 'Quarterly Overview'!D$11, 'Monthly Detail'!13:13) -> 22626.82 | E12: =+D12-C12 -> 2296.13 | F12: =SUMIF('Monthly Detail'!$3:$3, 'Quarterly Overview'!F$11, 'Monthly Detail'!13:13) -> 21242.35 | G12: =+F12-D12 -> -1384.47 | H12: =SUMIF('Monthly Detail'!$3:$3, 'Quarterly Overview'!H$11, 'Monthly Detail'!13:13) -> 19740.666 | I12: =+H12-F12 -> -1501.684 | K12: =SUM(C12,D12,F12,H12) -> 83940.526
B13: Total Income | C13: =SUM(C12:C12) -> 20330.69 | D13: =SUM(D12:D12) -> 22626.82 | E13: =+D13-C13 -> 2296.13 | F13: =SUM(F12:F12) -> 21242.35 | G13: =+F13-D13 -> -1384.47 | H13: =SUM(H12:H12) -> 19740.666 | I13: =+H13-F13 -> -1501.684 | K13: =SUM(K12:K12) -> 83940.526
B14: # of Appointments | C14: =+SUMIFS('Monthly Detail'!15:15,'Monthly Detail'!$3:$3,'Quarterly Overview'!C$10) -> 203 | D14: =+SUMIFS('Monthly Detail'!15:15,'Monthly Detail'!$3:$3,'Quarterly Overview'!D$10) -> 237 | E14: =+D14-C14 -> 34 | F14: =+SUMIFS('Monthly Detail'!15:15,'Monthly Detail'!$3:$3,'Quarterly Overview'!F$10) -> 211 | G14: =+F14-D14 -> -26 | H14: =+SUMIFS('Monthly Detail'!15:15,'Monthly Detail'!$3:$3,'Quarterly Overview'!H$10) -> 180.12105 | I14: =+H14-F14 -> -30.87895 | K14: =+SUM(C14,D14,F14,H14) -> 831.12105
B15: MRR | C15: =+AVERAGEIFS('Monthly Detail'!41:41,'Monthly Detail'!$3:$3,'Quarterly Overview'!C$10) -> 4119.7401 | D15: =+AVERAGEIFS('Monthly Detail'!41:41,'Monthly Detail'!$3:$3,'Quarterly Overview'!D$10) -> 4306.3923 | E15: =+D15-C15 -> 186.65214 | F15: =+AVERAGEIFS('Monthly Detail'!41:41,'Monthly Detail'!$3:$3,'Quarterly Overview'!F$10) -> 4653.1897 | G15: =+F15-D15 -> 346.79742 | H15: =+AVERAGEIFS('Monthly Detail'!41:41,'Monthly Detail'!$3:$3,'Quarterly Overview'!H$10) -> 4334.8542 | I15: =+H15-F15 -> -318.33547 | K15: =+AVERAGE(C15,D15,F15,H15) -> 4353.5441
B16: Recurring Client Base | C16: =+AVERAGEIFS('Monthly Detail'!17:17,'Monthly Detail'!$3:$3,'Quarterly Overview'!C$10) -> 32.666667 | D16: =+AVERAGEIFS('Monthly Detail'!17:17,'Monthly Detail'!$3:$3,'Quarterly Overview'!D$10) -> 35 | E16: =+D16-C16 -> 2.3333333 | F16: =+AVERAGEIFS('Monthly Detail'!17:17,'Monthly Detail'!$3:$3,'Quarterly Overview'!F$10) -> 34 | G16: =+F16-D16 -> -1 | H16: =+AVERAGEIFS('Monthly Detail'!17:17,'Monthly Detail'!$3:$3,'Quarterly Overview'!H$10) -> 29.470998 | I16: =+H16-F16 -> -4.5290015 | K16: =+AVERAGE(C16,D16,F16,H16) -> 32.784416
B18: Software - COS | C18: =SUMIF('Monthly Detail'!$3:$3, 'Quarterly Overview'!C$11, 'Monthly Detail'!58:58) -> 613.95 | D18: =SUMIF('Monthly Detail'!$3:$3, 'Quarterly Overview'!D$11, 'Monthly Detail'!58:58) -> 670.12 | E18: =+D18-C18 -> 56.17 | F18: =SUMIF('Monthly Detail'!$3:$3, 'Quarterly Overview'!F$11, 'Monthly Detail'!58:58) -> 644.27 | G18: =+F18-D18 -> -25.85 | H18: =SUMIF('Monthly Detail'!$3:$3, 'Quarterly Overview'!H$11, 'Monthly Detail'!58:58) -> 683.98586 | I18: =+H18-F18 -> 39.715862 | K18: =SUM(C18,D18,F18,H18) -> 2612.3259
B19: Materials - COGS | C19: =SUMIF('Monthly Detail'!$3:$3, 'Quarterly Overview'!C$11, 'Monthly Detail'!59:59) -> 1557.63 | D19: =SUMIF('Monthly Detail'!$3:$3, 'Quarterly Overview'!D$11, 'Monthly Detail'!59:59) -> 1610.76 | E19: =+D19-C19 -> 53.13 | F19: =SUMIF('Monthly Detail'!$3:$3, 'Quarterly Overview'!F$11, 'Monthly Detail'!59:59) -> 2249.7 | G19: =+F19-D19 -> 638.94 | H19: =SUMIF('Monthly Detail'!$3:$3, 'Quarterly Overview'!H$11, 'Monthly Detail'!59:59) -> 1801.7494 | I19: =+H19-F19 -> -447.95061 | K19: =SUM(C19,D19,F19,H19) -> 7219.8394
B20: Contractors - COGS | C20: =SUMIF('Monthly Detail'!$3:$3, 'Quarterly Overview'!C$11, 'Monthly Detail'!60:60) -> 95 | D20: =SUMIF('Monthly Detail'!$3:$3, 'Quarterly Overview'!D$11, 'Monthly Detail'!60:60) -> 629 | E20: =+D20-C20 -> 534 | F20: =SUMIF('Monthly Detail'!$3:$3, 'Quarterly Overview'!F$11, 'Monthly Detail'!60:60) -> 30 | G20: =+F20-D20 -> -599 | H20: =SUMIF('Monthly Detail'!$3:$3, 'Quarterly Overview'!H$11, 'Monthly Detail'!60:60) -> 1256.0674 | I20: =+H20-F20 -> 1226.0674 | K20: =SUM(C20,D20,F20,H20) -> 2010.0674
B21: Total Cost of Goods Sold (COGS) | C21: =SUM(C18:C20) -> 2266.58 | D21: =SUM(D18:D20) -> 2909.88 | E21: =SUM(E18:E19) -> 109.3 | F21: =SUM(F18:F20) -> 2923.97 | G21: =+F21-D21 -> 14.09 | H21: =SUM(H18:H20) -> 3741.8026 | I21: =+H21-F21 -> 817.83264 | K21: =SUM(K18:K20) -> 11842.233
B23: Gross Margin | C23: =C13-C21 -> 18064.11 | D23: =D13-D21 -> 19716.94 | E23: =+D23-C23 -> 1652.83 | F23: =F13-F21 -> 18318.38 | G23: =+F23-D23 -> -1398.56 | H23: =H13-H21 -> 15998.863 | I23: =+H23-F23 -> -2319.5167 | K23: =K13-K21 -> 72098.293
B24: GM % | C24: =C23/C13 -> 0.88851436 | D24: =D23/D13 -> 0.87139686 | E24: =+D24-C24 -> -0.017117495 | F24: =F23/F13 -> 0.86235186 | G24: =+F24-D24 -> -0.009045006 | H24: =H23/H13 -> 0.81045206 | I24: =+H24-F24 -> -0.051899802 | K24: =K23/K13 -> 0.85892115
B26: General & Admintrative Expenses | C26: =SUMIF('Monthly Detail'!$3:$3, 'Quarterly Overview'!C$11, 'Monthly Detail'!$89:$89) -> 9424.84 | D26: =SUMIF('Monthly Detail'!$3:$3, 'Quarterly Overview'!D$11, 'Monthly Detail'!$89:$89) -> 12509.75 | E26: =+D26-C26 -> 3084.91 | F26: =SUMIF('Monthly Detail'!$3:$3, 'Quarterly Overview'!F$11, 'Monthly Detail'!$89:$89) -> 10433.45 | G26: =+F26-D26 -> -2076.3 | H26: =SUMIF('Monthly Detail'!$3:$3, 'Quarterly Overview'!H$11, 'Monthly Detail'!$89:$89) -> 13907.415 | I26: =+H26-F26 -> 3473.9648 | K26: =SUM(C26,D26,F26,H26) -> 46275.455
B27: Operating Expenses | C27: =SUM(C26:C26) -> 9424.84 | D27: =SUM(D26:D26) -> 12509.75 | E27: =SUM(E26:E26) -> 3084.91 | F27: =SUM(F26:F26) -> 10433.45 | G27: =+F27-D27 -> -2076.3 | H27: =SUM(H26:H26) -> 13907.415 | I27: =+H27-F27 -> 3473.9648 | K27: =SUM(K26:K26) -> 46275.455
B29: Net Operating Income (EBITDA) | C29: =C23-C27 -> 8639.27 | D29: =D23-D27 -> 7207.19 | E29: =+D29-C29 -> -1432.08 | F29: =F23-F27 -> 7884.93 | G29: =+F29-D29 -> 677.74 | H29: =H23-H27 -> 2091.4485 | I29: =+H29-F29 -> -5793.4815 | K29: =K23-K27 -> 25822.838
B30: EBITDA % | C30: =C29/C13 -> 0.42493737 | D30: =D29/D13 -> 0.31852421 | E30: =+D30-C30 -> -0.10641316 | F30: =F29/F13 -> 0.37118916 | G30: =+F30-D30 -> 0.052664946 | H30: =H29/H13 -> 0.1059462 | I30: =+H30-F30 -> -0.26524296 | K30: =K29/K13 -> 0.30763256
B32: Other Income / (Expense) | C32: =SUMIF('Monthly Detail'!$3:$3, 'Quarterly Overview'!C$11, 'Monthly Detail'!96:96) -> 2.35 | D32: =SUMIF('Monthly Detail'!$3:$3, 'Quarterly Overview'!D$11, 'Monthly Detail'!96:96) -> 11.45 | E32: =+D32-C32 -> 9.1 | F32: =SUMIF('Monthly Detail'!$3:$3, 'Quarterly Overview'!F$11, 'Monthly Detail'!96:96) -> 10.26 | G32: =+F32-D32 -> -1.19 | H32: =SUMIF('Monthly Detail'!$3:$3, 'Quarterly Overview'!H$11, 'Monthly Detail'!96:96) -> 5.34 | I32: =+H32-F32 -> -4.92 | K32: =SUM(C32,D32,F32,H32) -> 29.4
B33: Net Income | C33: =C29+SUM(C32:C32) -> 8641.62 | D33: =D29+SUM(D32:D32) -> 7218.64 | E33: =+D33-C33 -> -1422.98 | F33: =F29+SUM(F32:F32) -> 7895.19 | G33: =+F33-D33 -> 676.55 | H33: =H29+SUM(H32:H32) -> 2096.7885 | I33: =+H33-F33 -> -5798.4015 | K33: =K29+SUM(K32:K32) -> 25852.238
B34: NI % | C34: =C33/C13 -> 0.42505296 | D34: =D33/D13 -> 0.31903025 | E34: =+D34-C34 -> -0.10602271 | F34: =F33/F13 -> 0.37167215 | G34: =+F34-D34 -> 0.052641907 | H34: =H33/H13 -> 0.1062167 | I34: =+H34-F34 -> -0.26545545 | K34: =K33/K13 -> 0.3079828
B36: Operating Cash | C36: =SUMIF('Monthly Detail'!$4:$4, 'Quarterly Overview'!C$9, 'Monthly Detail'!173:173) -> 2808.13 | D36: =SUMIF('Monthly Detail'!$4:$4, 'Quarterly Overview'!D$9, 'Monthly Detail'!173:173) -> 2620.37 | F36: =SUMIF('Monthly Detail'!$4:$4, 'Quarterly Overview'!F$9, 'Monthly Detail'!173:173) -> 123.47 | H36: =SUMIF('Monthly Detail'!$4:$4, 'Quarterly Overview'!H$9, 'Monthly Detail'!173:173) -> 1426
B37: Cash Inflow (Outflow) | C37: =SUMIF('Monthly Detail'!$3:$3, 'Quarterly Overview'!C$10, 'Monthly Detail'!170:170) -> 1963.24 | D37: =SUMIF('Monthly Detail'!$3:$3, 'Quarterly Overview'!D$10, 'Monthly Detail'!170:170) -> 3321.79 | E37: =+D37-C37 -> 1358.55 | F37: =SUMIF('Monthly Detail'!$3:$3, 'Quarterly Overview'!F$10, 'Monthly Detail'!170:170) -> -303.38 | G37: =+F37-D37 -> -3625.17 | H37: =SUMIF('Monthly Detail'!$3:$3, 'Quarterly Overview'!H$10, 'Monthly Detail'!170:170) -> 577.19434 | I37: =+H37-F37 -> 880.57434
C41: Q1 | D41: Q2 | F41: Q3 | H41: Q4
B42: 2024 AOP Income | C42: =+SUM(#REF!) -> #REF! | D42: =+SUM(#REF!) -> #REF! | F42: =+SUM(#REF!) -> #REF! | H42: =+SUM(#REF!) -> #REF!
B43: 2024 AOP Net Income | C43: =+SUM(#REF!) -> #REF! | D43: =+SUM(#REF!) -> #REF! | F43: =+SUM(#REF!) -> #REF! | H43: =+SUM(#REF!) -> #REF!
B44: 2024 AOP Avg. Appointments | C44: =+AVERAGE(#REF!) -> #REF! | D44: =+AVERAGE(#REF!) -> #REF! | F44: =+AVERAGE(#REF!) -> #REF! | H44: =+AVERAGE(#REF!) -> #REF!
B45: 2024 AOP Avg. MRR | C45: =+AVERAGE(#REF!) -> #REF! | D45: =+AVERAGE(#REF!) -> #REF! | F45: =+AVERAGE(#REF!) -> #REF! | H45: =+AVERAGE(#REF!) -> #REF!
B46: 2024 AOP Avg. Client Base | C46: =+AVERAGE(#REF!) -> #REF! | D46: =+AVERAGE(#REF!) -> #REF! | F46: =+AVERAGE(#REF!) -> #REF! | H46: =+AVERAGE(#REF!) -> #REF!

Sheet 2

Sheet Monthly Detail
D1: =YEAR(D4) -> 2022 | E1: =YEAR(E4) -> 2022 | F1: =YEAR(F4) -> 2022 | G1: =YEAR(G4) -> 2022 | H1: =YEAR(H4) -> 2022 | I1: =YEAR(I4) -> 2022 | J1: =YEAR(J4) -> 2022 | K1: =YEAR(K4) -> 2022 | ... DG1: =YEAR(DG4) -> 2030
G2: Peak | H2: Peak | I2: Shoulder | J2: Shoulder | K2: Trough | L2: Shoulder | M2: Shoulder | N2: Trough | O2: Shoulder | P2: Peak | Q2: Peak | R2: Shoulder | S2: Trough | T2: Trough | U2: Shoulder | V2: Peak | W2: Shoulder | X2: Peak | Y2: Peak | Z2: Peak | AA2: Shoulder | AB2: Shoulder | AC2: Shoulder | AD2: Shoulder | AE2: Peak | AF2: Peak | AG2: Peak | AH2: Shoulder | AI2: Shoulder | AJ2: Trough | AK2: Shoulder | AL2: Trough | AM2: =+AA2 -> Shoulder | AN2: =+AB2 -> Shoulder | AO2: =+AC2 -> Shoulder | AP2: =+AD2 -> Shoulder | AQ2: =+AE2 -> Peak | AR2: =+AF2 -> Peak | AS2: Shoulder | AT2: =+AH2 -> Shoulder | AU2: =+AI2 -> Shoulder | AV2: =+AJ2 -> Trough | AW2: =+AK2 -> Shoulder | AX2: =+AL2 -> Trough | AY2: =+AM2 -> Shoulder | AZ2: =+AN2 -> Shoulder | BA2: =+AO2 -> Shoulder | ... DG2: =+CU2 -> Shoulder
D3: =+"Q1 "&D1 -> Q1 2022 | E3: =+"Q1 "&E1 -> Q1 2022 | F3: =+"Q1 "&F1 -> Q1 2022 | G3: =+"Q2 "&G1 -> Q2 2022 | H3: =+"Q2 "&H1 -> Q2 2022 | I3: =+"Q2 "&I1 -> Q2 2022 | J3: =+"Q3 "&J1 -> Q3 2022 | K3: =+"Q3 "&K1 -> Q3 2022 | L3: =+"Q3 "&L1 -> Q3 2022 | M3: =+"Q4 "&M1 -> Q4 2022 | N3: =+"Q4 "&N1 -> Q4 2022 | O3: =+"Q4 "&O1 -> Q4 2022 | P3: =+"Q1 "&P1 -> Q1 2023 | Q3: =+"Q1 "&Q1 -> Q1 2023 | R3: =+"Q1 "&R1 -> Q1 2023 | S3: =+"Q2 "&S1 -> Q2 2023 | T3: =+"Q2 "&T1 -> Q2 2023 | U3: =+"Q2 "&U1 -> Q2 2023 | V3: =+"Q3 "&V1 -> Q3 2023 | W3: =+"Q3 "&W1 -> Q3 2023 | X3: =+"Q3 "&X1 -> Q3 2023 | Y3: =+"Q4 "&Y1 -> Q4 2023 | Z3: =+"Q4 "&Z1 -> Q4 2023 | AA3: =+"Q4 "&AA1 -> Q4 2023 | AB3: =+"Q1 "&AB1 -> Q1 2024 | AC3: =+"Q1 "&AC1 -> Q1 2024 | AD3: =+"Q1 "&AD1 -> Q1 2024 | AE3: =+"Q2 "&AE1 -> Q2 2024 | AF3: =+"Q2 "&AF1 -> Q2 2024 | AG3: =+"Q2 "&AG1 -> Q2 2024 | AH3: =+"Q3 "&AH1 -> Q3 2024 | AI3: =+"Q3 "&AI1 -> Q3 2024 | AJ3: =+"Q3 "&AJ1 -> Q3 2024 | AK3: =+"Q4 "&AK1 -> Q4 2024 | AL3: =+"Q4 "&AL1 -> Q4 2024 | AM3: =+"Q4 "&AM1 -> Q4 2024 | AN3: =+"Q1 "&AN1 -> Q1 2025 | AO3: =+"Q1 "&AO1 -> Q1 2025 | AP3: =+"Q1 "&AP1 -> Q1 2025 | AQ3: =+"Q2 "&AQ1 -> Q2 2025 | AR3: =+"Q2 "&AR1 -> Q2 2025 | AS3: =+"Q2 "&AS1 -> Q2 2025 | AT3: =+"Q3 "&AT1 -> Q3 2025 | AU3: =+"Q3 "&AU1 -> Q3 2025 | AV3: =+"Q3 "&AV1 -> Q3 2025 | AW3: =+"Q4 "&AW1 -> Q4 2025 | AX3: =+"Q4 "&AX1 -> Q4 2025 | AY3: =+"Q4 "&AY1 -> Q4 2025 | AZ3: =+"Q1 "&AZ1 -> Q1 2026 | BA3: =+"Q1 "&BA1 -> Q1 2026 | BB3: =+"Q1 "&BB1 -> Q1 2026 | BC3: =+"Q2 "&BC1 -> Q2 2026 | BD3: =+"Q2 "&BD1 -> Q2 2026 | BE3: =+"Q2 "&BE1 -> Q2 2026 | BF3: =+"Q3 "&BF1 -> Q3 2026 | BG3: =+"Q3 "&BG1 -> Q3 2026 | BH3: =+"Q3 "&BH1 -> Q3 2026 | BI3: =+"Q4 "&BI1 -> Q4 2026 | BJ3: =+"Q4 "&BJ1 -> Q4 2026 | BK3: =+"Q4 "&BK1 -> Q4 2026 | BL3: =+"Q1 "&BL1 -> Q1 2027 | BM3: =+"Q1 "&BM1 -> Q1 2027 | BN3: =+"Q1 "&BN1 -> Q1 2027 | BO3: =+"Q2 "&BO1 -> Q2 2027 | BP3: =+"Q2 "&BP1 -> Q2 2027 | BQ3: =+"Q2 "&BQ1 -> Q2 2027 | BR3: =+"Q3 "&BR1 -> Q3 2027 | BS3: =+"Q3 "&BS1 -> Q3 2027 | BT3: =+"Q3 "&BT1 -> Q3 2027 | BU3: =+"Q4 "&BU1 -> Q4 2027 | BV3: =+"Q4 "&BV1 -> Q4 2027 | BW3: =+"Q4 "&BW1 -> Q4 2027 | BX3: =+"Q1 "&BX1 -> Q1 2028 | BY3: =+"Q1 "&BY1 -> Q1 2028 | BZ3: =+"Q1 "&BZ1 -> Q1 2028 | CA3: =+"Q2 "&CA1 -> Q2 2028 | CB3: =+"Q2 "&CB1 -> Q2 2028 | CC3: =+"Q2 "&CC1 -> Q2 2028 | CD3: =+"Q3 "&CD1 -> Q3 2028 | CE3: =+"Q3 "&CE1 -> Q3 2028 | CF3: =+"Q3 "&CF1 -> Q3 2028 | CG3: =+"Q4 "&CG1 -> Q4 2028 | CH3: =+"Q4 "&CH1 -> Q4 2028 | CI3: =+"Q4 "&CI1 -> Q4 2028 | CJ3: =+"Q1 "&CJ1 -> Q1 2029 | CK3: =+"Q1 "&CK1 -> Q1 2029 | CL3: =+"Q1 "&CL1 -> Q1 2029 | CM3: =+"Q2 "&CM1 -> Q2 2029 | CN3: =+"Q2 "&CN1 -> Q2 2029 | CO3: =+"Q2 "&CO1 -> Q2 2029 | CP3: =+"Q3 "&CP1 -> Q3 2029 | CQ3: =+"Q3 "&CQ1 -> Q3 2029 | CR3: =+"Q3 "&CR1 -> Q3 2029 | CS3: =+"Q4 "&CS1 -> Q4 2029 | CT3: =+"Q4 "&CT1 -> Q4 2029 | CU3: =+"Q4 "&CU1 -> Q4 2029 | CV3: =+"Q1 "&CV1 -> Q1 2030 | CW3: =+"Q1 "&CW1 -> Q1 2030 | CX3: =+"Q1 "&CX1 -> Q1 2030 | CY3: =+"Q2 "&CY1 -> Q2 2030 | CZ3: =+"Q2 "&CZ1 -> Q2 2030 | DA3: =+"Q2 "&DA1 -> Q2 2030 | DB3: =+"Q3 "&DB1 -> Q3 2030 | DC3: =+"Q3 "&DC1 -> Q3 2030 | DD3: =+"Q3 "&DD1 -> Q3 2030 | DE3: =+"Q4 "&DE1 -> Q4 2030 | DF3: =+"Q4 "&DF1 -> Q4 2030 | DG3: =+"Q4 "&DG1 -> Q4 2030
D4: 44592 | E4: 44620 | F4: 44651 | G4: 44681 | H4: 44712 | I4: 44742 | J4: 44773 | K4: 44804 | L4: 44834 | M4: 44865 | N4: 44895 | O4: 44926 | P4: 44957 | Q4: 44985 | R4: 45016 | S4: 45046 | T4: 45077 | U4: 45107 | V4: 45138 | W4: 45169 | X4: 45199 | Y4: 45230 | Z4: 45260 | AA4: 45291 | AB4: 45322 | AC4: 45351 | AD4: 45382 | AE4: 45412 | AF4: 45443 | AG4: 45473 | AH4: 45504 | AI4: 45535 | AJ4: 45565 | AK4: 45596 | AL4: 45626 | AM4: 45657 | AN4: 45688 | AO4: 45716 | AP4: 45747 | AQ4: 45777 | AR4: 45808 | AS4: 45838 | AT4: 45869 | AU4: 45900 | AV4: 45930 | AW4: 45961 | AX4: 45991 | AY4: 46022 | AZ4: 46053 | BA4: 46081 | BB4: 46112 | BC4: 46142 | BD4: 46173 | BE4: 46203 | BF4: 46234 | BG4: 46265 | BH4: 46295 | BI4: 46326 | BJ4: 46356 | BK4: 46387 | BL4: 46418 | BM4: 46446 | BN4: 46477 | BO4: 46507 | BP4: 46538 | BQ4: 46568 | BR4: 46599 | BS4: 46630 | BT4: 46660 | BU4: 46691 | BV4: 46721 | BW4: 46752 | BX4: 46783 | BY4: 46812 | BZ4: 46843 | CA4: 46873 | CB4: 46904 | CC4: 46934 | CD4: 46965 | CE4: 46996 | CF4: 47026 | CG4: 47057 | CH4: 47087 | CI4: 47118 | CJ4: 47149 | CK4: 47177 | CL4: 47208 | CM4: 47238 | CN4: 47269 | CO4: 47299 | CP4: 47330 | CQ4: 47361 | CR4: 47391 | CS4: 47422 | CT4: 47452 | CU4: 47483 | CV4: 47514 | CW4: 47542 | CX4: 47573 | CY4: 47603 | CZ4: 47634 | DA4: 47664 | DB4: 47695 | DC4: 47726 | DD4: 47756 | DE4: 47787 | DF4: 47817 | DG4: 47848
B5: Income
B6: 40100 Nail Technician Services | V6: 0 | AB6: 5520 | AC6: 6528.4 | AD6: 7633.5 | AE6: 7610.5 | AF6: 7767.15 | AG6: 6976.15 | AH6: 5696 | AI6: 7172.75 | AJ6: 4463.25 | AK6: 7444.5 | AL6: 4717 | AM6: 6221.6 | AN6: 6476.75 | AO6: 6155.39 | AP6: 6650.25 | AQ6: 7459.5 | AR6: 7496.95 | AS6: 6520.45 | AT6: 7050.8 | AU6: 7217.85 | AV6: 5873.45 | AW6: =6611 -> 6611 | AX6: =AX32*AX30 -> 5016.588 | AY6: =AY32*AY30 -> 7096.8363 | AZ6: =AZ32*AZ30 -> 6704.1644 | BA6: =BA32*BA30 -> 7861.239 | BB6: =BB32*BB30 -> 8716.6905 | BC6: =BC32*BC30 -> 10487.082 | BD6: =BD32*BD30 -> 9845.5809 | BE6: =BE32*BE30 -> 9996.4826 | ... DG6: =DG32*DG30 -> 12030.536
B7: 40800 Tips | AB7: 208.5 | AC7: 282.85 | AD7: 291.5 | AE7: 286.5 | AF7: 310.85 | AG7: 357.85 | AH7: 349.5 | AI7: 382.25 | AJ7: 357 | AK7: 387.5 | AL7: 221.75 | AM7: 260.4 | AN7: 274.3 | AO7: 345.75 | AP7: 458.25 | AQ7: 402.25 | AR7: 410.67 | AS7: 382 | AT7: 382.75 | AU7: 435.5 | AV7: 387 | AW7: =387.25 -> 387.25 | AX7: =+AX6*AX10 -> 279.37779 | AY7: =+AY6*AY10 -> 395.22848 | AZ7: =+AZ6*AZ10 -> 373.36027 | BA7: =+BA6*BA10 -> 437.79868 | BB7: =+BB6*BB10 -> 485.43946 | BC7: =+BC6*BC10 -> 584.03396 | BD7: =+BD6*BD10 -> 548.30826 | BE7: =+BE6*BE10 -> 556.7121 | ... DG7: =+DG6*DG10 -> 669.99018
B8: 40900 Refunds/Discounts | AC8: -65 | AD8: -285.75 | AE8: -80 | AF8: -30 | AG8: -180 | AH8: -30 | AI8: -260 | AJ8: -282.25 | AK8: -135 | AL8: 0 | AM8: -330 | AN8: -30 | AO8: 0 | AP8: 0 | AQ8: 0 | AR8: -30 | AS8: -15 | AT8: -15 | AU8: 0 | AV8: -90 | AX8: =+AX6*AX11 -> -18.890577 | AY8: =+AY6*AY11 -> -26.724007 | AZ8: =+AZ6*AZ11 -> -25.245353 | BA8: =+BA6*BA11 -> -29.602459 | BB8: =+BB6*BB11 -> -32.823767 | BC8: =+BC6*BC11 -> -39.490392 | BD8: =+BD6*BD11 -> -37.074742 | BE8: =+BE6*BE11 -> -37.642981 | ... DG8: =+DG6*DG11 -> -45.30246
B9: Total 40000 Service Income | C9: Revenue | D9: =+(D6) -> 0 | E9: =+(E6) -> 0 | F9: 0 | G9: 0 | H9: 0 | I9: 0 | J9: 0 | K9: =SUM(K6:K6) -> 0 | L9: =SUM(L6:L6) -> 0 | M9: =SUM(M6:M6) -> 0 | N9: =SUM(N6:N6) -> 0 | O9: =SUM(O6:O6) -> 0 | P9: =SUM(P6:P6) -> 0 | Q9: =SUM(Q6:Q6) -> 0 | R9: =SUM(R6:R6) -> 0 | ... AA9: =SUM(AA6:AA6) -> 0 | AB9: =SUM(AB6:AB8) -> 5728.5 | AC9: =SUM(AC6:AC8) -> 6746.25 | AD9: =SUM(AD6:AD8) -> 7639.25 | AE9: =SUM(AE6:AE8) -> 7817 | AF9: =SUM(AF6:AF8) -> 8048 | AG9: =SUM(AG6:AG8) -> 7154 | AH9: =SUM(AH6:AH8) -> 6015.5 | AI9: =SUM(AI6:AI8) -> 7295 | ... DG9: =SUM(DG6:DG8) -> 12655.224
C10: Tips as a % of Revenue | AB10: =+AB7/AB9 -> 0.036396963 | AC10: =+AC7/AC9 -> 0.041926996 | AD10: =+AD7/AD9 -> 0.038158196 | AE10: =+AE7/AE9 -> 0.036650889 | AF10: =+AF7/AF9 -> 0.038624503 | AG10: =+AG7/AG9 -> 0.050020967 | AH10: =+AH7/AH9 -> 0.058099909 | AI10: =+AI7/AI9 -> 0.052398903 | ... AW10: =+AW7/AW9 -> 0.055335262 | AX10: =+AVERAGE(AR10:AW10) -> 0.055690799 | AY10: =+AX10 -> 0.055690799 | AZ10: =+AY10 -> 0.055690799 | BA10: =+AZ10 -> 0.055690799 | BB10: =+BA10 -> 0.055690799 | BC10: =+BB10 -> 0.055690799 | BD10: =+BC10 -> 0.055690799 | BE10: =+BD10 -> 0.055690799 | BF10: =+BE10 -> 0.055690799 | ... DG10: =+DF10 -> 0.055690799
C11: Refunds as a % of Revenue | AB11: =+AB8/AB9 -> 0 | AC11: =+AC8/AC9 -> -0.0096349824 | AD11: =+AD8/AD9 -> -0.037405504 | AE11: =+AE8/AE9 -> -0.010234105 | AF11: =+AF8/AF9 -> -0.0037276342 | AG11: =+AG8/AG9 -> -0.025160749 | AH11: =+AH8/AH9 -> -0.0049871166 | AI11: =+AI8/AI9 -> -0.03564085 | ... AW11: =+AW8/AW9 -> 0 | AX11: =+AVERAGE(AR11:AW11) -> -0.0037656226 | AY11: =+AX11 -> -0.0037656226 | AZ11: =+AY11 -> -0.0037656226 | BA11: =+AZ11 -> -0.0037656226 | BB11: =+BA11 -> -0.0037656226 | BC11: =+BB11 -> -0.0037656226 | BD11: =+BC11 -> -0.0037656226 | BE11: =+BD11 -> -0.0037656226 | BF11: =+BE11 -> -0.0037656226 | ... DG11: =+DF11 -> -0.0037656226
B12: 70000 Miscellaneous | D12: =0 -> 0 | E12: =0 -> 0 | F12: =0 -> 0 | G12: =0 -> 0 | H12: =0 -> 0 | I12: =0 -> 0 | J12: =0 -> 0 | K12: 0 | L12: 0 | N12: 0 | O12: 0 | AX12: =AW12 -> 0 | AY12: =AX12 -> 0 | AZ12: =AY12 -> 0 | BA12: =AZ12 -> 0 | BB12: =BA12 -> 0 | BC12: =BB12 -> 0 | BD12: =BC12 -> 0 | BE12: =BD12 -> 0 | ... DG12: =DF12 -> 0
B13: Total Income | D13: =(D9)+(D12) -> 0 | E13: =(E9)+(E12) -> 0 | F13: =(F9)+(F12) -> 0 | G13: =(G9)+(G12) -> 0 | H13: =(H9)+(H12) -> 0 | I13: =(I9)+(I12) -> 0 | J13: =(J9)+(J12) -> 0 | K13: =K12+K9 -> 0 | L13: =L12+L9 -> 0 | M13: =M12+M9 -> 0 | N13: =N12+N9 -> 0 | O13: =O12+O9 -> 0 | P13: =P12+P9 -> 0 | Q13: =Q12+Q9 -> 0 | R13: =R12+R9 -> 0 | ... DG13: =DG12+DG9 -> 12655.224
C15: # of Successful Appointments | E15: 12 | F15: 8 | G15: 7 | H15: 10 | I15: 13 | J15: 11 | K15: 5 | L15: 9 | M15: 17 | N15: 11 | O15: 7 | P15: 12 | Q15: 10 | R15: 10 | S15: 7 | T15: 9 | U15: 12 | V15: =99-24 -> 75 | W15: 177 | X15: 191 | Y15: 190 | Z15: 188 | AA15: 207 | AB15: 67 | AC15: 74 | AD15: 77 | AE15: 78 | AF15: 82 | AG15: 75 | AH15: 66 | AI15: 74 | AJ15: 48 | AK15: 81 | AL15: 50 | AM15: 61 | AN15: 66 | AO15: 69 | AP15: 68 | AQ15: 82 | AR15: 83 | AS15: 72 | AT15: 76 | AU15: 73 | AV15: 62 | AW15: 72 | AX15: =+AX16*AX26 -> 48.305712 | AY15: =+AY16*AY26 -> 59.815338 | AZ15: =+AZ16*AZ26 -> 65.580099 | BA15: =+BA16*BA26 -> 74.090127 | BB15: =+BB16*BB26 -> 71.442207 | BC15: =+BC16*BC26 -> 98.886246 | BD15: =+BD16*BD26 -> 99.610964 | BE15: =+BE16*BE26 -> 99.924194 | ... DG15: =+DG16*DG26 -> 75.837303
C16: # of Active Clients | W16: 123 | X16: 123 | Y16: 129 | Z16: 127 | AA16: 126 | AB16: 55 | AC16: 69 | AD16: 68 | AE16: 66 | AF16: 69 | AG16: 65 | AH16: 54 | AI16: 65 | AJ16: 42 | AK16: 66 | AL16: 46 | AM16: 54 | AN16: 59 | AO16: 59 | AP16: 63 | AQ16: 69 | AR16: 78 | AS16: 62 | AT16: 67 | AU16: 60 | AV16: 54 | AW16: 58 | AX16: =+AX22*AX25 -> 44.441255 | AY16: =+AY22*AY25 -> 52.951283 | AZ16: =+AZ22*AZ25 -> 58.624634 | BA16: =+BA22*BA25 -> 63.352427 | BB16: =+BB22*BB25 -> 66.189103 | BC16: =+BC22*BC25 -> 83.209158 | BD16: =+BD22*BD25 -> 93.610303 | BE16: =+BE22*BE25 -> 86.045834 | ... DG16: =+DG22*DG25 -> 67.134662
C17: # of Recurring Client Base | X17: 73 | Y17: 71 | Z17: 72 | AA17: 75 | AB17: 30 | AC17: 34 | AD17: 27 | AE17: 19 | AF17: 30 | AG17: 30 | AH17: 29 | AI17: 34 | AJ17: 37 | AK17: 29 | AL17: 28 | AM17: 25 | AN17: 35 | AO17: 32 | AP17: 31 | AQ17: 30 | AR17: 38 | AS17: 37 | AT17: 34 | AU17: 32 | AV17: 36 | AW17: 33 | AX17: =+AW17*(1+AX24) -> 25.285542 | AY17: =+AX17*(1+AY24) -> 30.127454 | AZ17: =+AY17*(1+AZ24) -> 33.355395 | BA17: =+AZ17*(1+BA24) -> 36.045347 | BB17: =+BA17*(1+BB24) -> 37.659317 | BC17: =+BB17*(1+BC24) -> 47.343142 | BD17: =+BC17*(1+BD24) -> 53.261035 | BE17: =+BD17*(1+BE24) -> 48.957113 | ... DG17: =+DF17*(1+DG24) -> 38.197308
C18: Net New Clients | E18: =SUM(E19:E20) -> 0 | F18: =SUM(F19:F20) -> -4 | G18: =SUM(G19:G20) -> -1 | H18: =SUM(H19:H20) -> 3 | I18: =SUM(I19:I20) -> 3 | J18: =SUM(J19:J20) -> -2 | K18: =SUM(K19:K20) -> -6 | L18: =SUM(L19:L20) -> 4 | ... DG18: =SUM(DG19:DG20) -> 11
C19: Additions | F19: =+IF(F15>E15,F15-E15, 0) -> 0 | G19: =+IF(G15>F15,G15-F15, 0) -> 0 | H19: =+IF(H15>G15,H15-G15, 0) -> 3 | I19: =+IF(I15>H15,I15-H15, 0) -> 3 | J19: =+IF(J15>I15,J15-I15, 0) -> 0 | K19: =+IF(K15>J15,K15-J15, 0) -> 0 | L19: =+IF(L15>K15,L15-K15, 0) -> 4 | M19: =+IF(M15>L15,M15-L15, 0) -> 8 | ... V19: =+IF(V15>U15,V15-U15, 0) -> 63 | W19: 62 | X19: 62 | Y19: 56 | Z19: 29 | AA19: 19 | AB19: 0 | AC19: 37 | AD19: 42 | AE19: 50 | AF19: 40 | AG19: 35 | AH19: 25 | AI19: 31 | AJ19: 8 | AK19: 37 | AL19: 18 | AM19: 29 | AN19: 24 | AO19: 27 | AP19: 32 | AQ19: 39 | AR19: 40 | AS19: 25 | AT19: 33 | AU19: 28 | AV19: 18 | AW19: 24 | AX19: =IF(AX2="Trough",INDEX($I$50:$I$52,MATCH(AX2,$E$50:$E$52,0)),IF(AX2="Shoulder",INDEX($I$50:$I$52,MATCH(AX2,$E$50:$E$52,0)),INDEX($I$50:$I$52,MATCH(AX2,$E$50:$E$52,0)))) -> 14 | AY19: =IF(AY2="Trough",INDEX($I$50:$I$52,MATCH(AY2,$E$50:$E$52,0)),IF(AY2="Shoulder",INDEX($I$50:$I$52,MATCH(AY2,$E$50:$E$52,0)),INDEX($I$50:$I$52,MATCH(AY2,$E$50:$E$52,0)))) -> 31 | AZ19: =IF(AZ2="Trough",INDEX($J$50:$J$52,MATCH(AZ2,$E$50:$E$52,0)),IF(AZ2="Shoulder",INDEX($J$50:$J$52,MATCH(AZ2,$E$50:$E$52,0)),INDEX($J$50:$J$52,MATCH(AZ2,$E$50:$E$52,0)))) -> 33 | BA19: =IF(BA2="Trough",INDEX($J$50:$J$52,MATCH(BA2,$E$50:$E$52,0)),IF(BA2="Shoulder",INDEX($J$50:$J$52,MATCH(BA2,$E$50:$E$52,0)),INDEX($J$50:$J$52,MATCH(BA2,$E$50:$E$52,0)))) -> 33 | BB19: =IF(BB2="Trough",INDEX($J$50:$J$52,MATCH(BB2,$E$50:$E$52,0)),IF(BB2="Shoulder",INDEX($J$50:$J$52,MATCH(BB2,$E$50:$E$52,0)),INDEX($J$50:$J$52,MATCH(BB2,$E$50:$E$52,0)))) -> 33 | BC19: =IF(BC2="Trough",INDEX($J$50:$J$52,MATCH(BC2,$E$50:$E$52,0)),IF(BC2="Shoulder",INDEX($J$50:$J$52,MATCH(BC2,$E$50:$E$52,0)),INDEX($J$50:$J$52,MATCH(BC2,$E$50:$E$52,0)))) -> 48 | BD19: =IF(BD2="Trough",INDEX($J$50:$J$52,MATCH(BD2,$E$50:$E$52,0)),IF(BD2="Shoulder",INDEX($J$50:$J$52,MATCH(BD2,$E$50:$E$52,0)),INDEX($J$50:$J$52,MATCH(BD2,$E$50:$E$52,0)))) -> 48 | BE19: =IF(BE2="Trough",INDEX($J$50:$J$52,MATCH(BE2,$E$50:$E$52,0)),IF(BE2="Shoulder",INDEX($J$50:$J$52,MATCH(BE2,$E$50:$E$52,0)),INDEX($J$50:$J$52,MATCH(BE2,$E$50:$E$52,0)))) -> 33 | BF19: =IF(BF2="Trough",INDEX($J$50:$J$52,MATCH(BF2,$E$50:$E$52,0)),IF(BF2="Shoulder",INDEX($J$50:$J$52,MATCH(BF2,$E$50:$E$52,0)),INDEX($J$50:$J$52,MATCH(BF2,$E$50:$E$52,0)))) -> 33 | BG19: =IF(BG2="Trough",INDEX($J$50:$J$52,MATCH(BG2,$E$50:$E$52,0)),IF(BG2="Shoulder",INDEX($J$50:$J$52,MATCH(BG2,$E$50:$E$52,0)),INDEX($J$50:$J$52,MATCH(BG2,$E$50:$E$52,0)))) -> 33 | ... BK19: =IF(BK2="Trough",INDEX($J$50:$J$52,MATCH(BK2,$E$50:$E$52,0)),IF(BK2="Shoulder",INDEX($J$50:$J$52,MATCH(BK2,$E$50:$E$52,0)),INDEX($J$50:$J$52,MATCH(BK2,$E$50:$E$52,0)))) -> 33 | BL19: =+IF(BL2="Trough",INDEX($K$50:$K$52,MATCH(BL2,$E$50:$E$52,0)),IF(BL2="Shoulder",INDEX($K$50:$K$52,MATCH(BL2,$E$50:$E$52,0)),INDEX($K$50:$K$52,MATCH(BL2,$E$50:$E$52,0)))) -> 35 | BM19: =+IF(BM2="Trough",INDEX($K$50:$K$52,MATCH(BM2,$E$50:$E$52,0)),IF(BM2="Shoulder",INDEX($K$50:$K$52,MATCH(BM2,$E$50:$E$52,0)),INDEX($K$50:$K$52,MATCH(BM2,$E$50:$E$52,0)))) -> 35 | BN19: =+IF(BN2="Trough",INDEX($K$50:$K$52,MATCH(BN2,$E$50:$E$52,0)),IF(BN2="Shoulder",INDEX($K$50:$K$52,MATCH(BN2,$E$50:$E$52,0)),INDEX($K$50:$K$52,MATCH(BN2,$E$50:$E$52,0)))) -> 35 | BO19: =+IF(BO2="Trough",INDEX($K$50:$K$52,MATCH(BO2,$E$50:$E$52,0)),IF(BO2="Shoulder",INDEX($K$50:$K$52,MATCH(BO2,$E$50:$E$52,0)),INDEX($K$50:$K$52,MATCH(BO2,$E$50:$E$52,0)))) -> 51 | BP19: =+IF(BP2="Trough",INDEX($K$50:$K$52,MATCH(BP2,$E$50:$E$52,0)),IF(BP2="Shoulder",INDEX($K$50:$K$52,MATCH(BP2,$E$50:$E$52,0)),INDEX($K$50:$K$52,MATCH(BP2,$E$50:$E$52,0)))) -> 51 | BQ19: =+IF(BQ2="Trough",INDEX($K$50:$K$52,MATCH(BQ2,$E$50:$E$52,0)),IF(BQ2="Shoulder",INDEX($K$50:$K$52,MATCH(BQ2,$E$50:$E$52,0)),INDEX($K$50:$K$52,MATCH(BQ2,$E$50:$E$52,0)))) -> 35 | BR19: =+IF(BR2="Trough",INDEX($K$50:$K$52,MATCH(BR2,$E$50:$E$52,0)),IF(BR2="Shoulder",INDEX($K$50:$K$52,MATCH(BR2,$E$50:$E$52,0)),INDEX($K$50:$K$52,MATCH(BR2,$E$50:$E$52,0)))) -> 35 | BS19: =+IF(BS2="Trough",INDEX($K$50:$K$52,MATCH(BS2,$E$50:$E$52,0)),IF(BS2="Shoulder",INDEX($K$50:$K$52,MATCH(BS2,$E$50:$E$52,0)),INDEX($K$50:$K$52,MATCH(BS2,$E$50:$E$52,0)))) -> 35 | ... BW19: =+IF(BW2="Trough",INDEX($K$50:$K$52,MATCH(BW2,$E$50:$E$52,0)),IF(BW2="Shoulder",INDEX($K$50:$K$52,MATCH(BW2,$E$50:$E$52,0)),INDEX($K$50:$K$52,MATCH(BW2,$E$50:$E$52,0)))) -> 35 | BX19: =IF(BX2="Trough",INDEX($L$50:$L$52,MATCH(BX2,$E$50:$E$52,0)),IF(BX2="Shoulder",INDEX($L$50:$L$52,MATCH(BX2,$E$50:$E$52,0)),INDEX($L$50:$L$52,MATCH(BX2,$E$50:$E$52,0)))) -> 37 | BY19: =IF(BY2="Trough",INDEX($L$50:$L$52,MATCH(BY2,$E$50:$E$52,0)),IF(BY2="Shoulder",INDEX($L$50:$L$52,MATCH(BY2,$E$50:$E$52,0)),INDEX($L$50:$L$52,MATCH(BY2,$E$50:$E$52,0)))) -> 37 | BZ19: =IF(BZ2="Trough",INDEX($L$50:$L$52,MATCH(BZ2,$E$50:$E$52,0)),IF(BZ2="Shoulder",INDEX($L$50:$L$52,MATCH(BZ2,$E$50:$E$52,0)),INDEX($L$50:$L$52,MATCH(BZ2,$E$50:$E$52,0)))) -> 37 | CA19: =IF(CA2="Trough",INDEX($L$50:$L$52,MATCH(CA2,$E$50:$E$52,0)),IF(CA2="Shoulder",INDEX($L$50:$L$52,MATCH(CA2,$E$50:$E$52,0)),INDEX($L$50:$L$52,MATCH(CA2,$E$50:$E$52,0)))) -> 54 | CB19: =IF(CB2="Trough",INDEX($L$50:$L$52,MATCH(CB2,$E$50:$E$52,0)),IF(CB2="Shoulder",INDEX($L$50:$L$52,MATCH(CB2,$E$50:$E$52,0)),INDEX($L$50:$L$52,MATCH(CB2,$E$50:$E$52,0)))) -> 54 | CC19: =IF(CC2="Trough",INDEX($L$50:$L$52,MATCH(CC2,$E$50:$E$52,0)),IF(CC2="Shoulder",INDEX($L$50:$L$52,MATCH(CC2,$E$50:$E$52,0)),INDEX($L$50:$L$52,MATCH(CC2,$E$50:$E$52,0)))) -> 37 | CD19: =IF(CD2="Trough",INDEX($L$50:$L$52,MATCH(CD2,$E$50:$E$52,0)),IF(CD2="Shoulder",INDEX($L$50:$L$52,MATCH(CD2,$E$50:$E$52,0)),INDEX($L$50:$L$52,MATCH(CD2,$E$50:$E$52,0)))) -> 37 | CE19: =IF(CE2="Trough",INDEX($L$50:$L$52,MATCH(CE2,$E$50:$E$52,0)),IF(CE2="Shoulder",INDEX($L$50:$L$52,MATCH(CE2,$E$50:$E$52,0)),INDEX($L$50:$L$52,MATCH(CE2,$E$50:$E$52,0)))) -> 37 | ... CI19: =IF(CI2="Trough",INDEX($L$50:$L$52,MATCH(CI2,$E$50:$E$52,0)),IF(CI2="Shoulder",INDEX($L$50:$L$52,MATCH(CI2,$E$50:$E$52,0)),INDEX($L$50:$L$52,MATCH(CI2,$E$50:$E$52,0)))) -> 37 | CJ19: =IF(CJ2="Trough",INDEX($M$50:$M$52,MATCH(CJ2,$E$50:$E$52,0)),IF(CJ2="Shoulder",INDEX($M$50:$M$52,MATCH(CJ2,$E$50:$E$52,0)),INDEX($M$50:$M$52,MATCH(CJ2,$E$50:$E$52,0)))) -> 39 | CK19: =IF(CK2="Trough",INDEX($M$50:$M$52,MATCH(CK2,$E$50:$E$52,0)),IF(CK2="Shoulder",INDEX($M$50:$M$52,MATCH(CK2,$E$50:$E$52,0)),INDEX($M$50:$M$52,MATCH(CK2,$E$50:$E$52,0)))) -> 39 | CL19: =IF(CL2="Trough",INDEX($M$50:$M$52,MATCH(CL2,$E$50:$E$52,0)),IF(CL2="Shoulder",INDEX($M$50:$M$52,MATCH(CL2,$E$50:$E$52,0)),INDEX($M$50:$M$52,MATCH(CL2,$E$50:$E$52,0)))) -> 39 | CM19: =IF(CM2="Trough",INDEX($M$50:$M$52,MATCH(CM2,$E$50:$E$52,0)),IF(CM2="Shoulder",INDEX($M$50:$M$52,MATCH(CM2,$E$50:$E$52,0)),INDEX($M$50:$M$52,MATCH(CM2,$E$50:$E$52,0)))) -> 57 | CN19: =IF(CN2="Trough",INDEX($M$50:$M$52,MATCH(CN2,$E$50:$E$52,0)),IF(CN2="Shoulder",INDEX($M$50:$M$52,MATCH(CN2,$E$50:$E$52,0)),INDEX($M$50:$M$52,MATCH(CN2,$E$50:$E$52,0)))) -> 57 | CO19: =IF(CO2="Trough",INDEX($M$50:$M$52,MATCH(CO2,$E$50:$E$52,0)),IF(CO2="Shoulder",INDEX($M$50:$M$52,MATCH(CO2,$E$50:$E$52,0)),INDEX($M$50:$M$52,MATCH(CO2,$E$50:$E$52,0)))) -> 39 | CP19: =IF(CP2="Trough",INDEX($M$50:$M$52,MATCH(CP2,$E$50:$E$52,0)),IF(CP2="Shoulder",INDEX($M$50:$M$52,MATCH(CP2,$E$50:$E$52,0)),INDEX($M$50:$M$52,MATCH(CP2,$E$50:$E$52,0)))) -> 39 | CQ19: =IF(CQ2="Trough",INDEX($M$50:$M$52,MATCH(CQ2,$E$50:$E$52,0)),IF(CQ2="Shoulder",INDEX($M$50:$M$52,MATCH(CQ2,$E$50:$E$52,0)),INDEX($M$50:$M$52,MATCH(CQ2,$E$50:$E$52,0)))) -> 39 | ... CU19: =IF(CU2="Trough",INDEX($M$50:$M$52,MATCH(CU2,$E$50:$E$52,0)),IF(CU2="Shoulder",INDEX($M$50:$M$52,MATCH(CU2,$E$50:$E$52,0)),INDEX($M$50:$M$52,MATCH(CU2,$E$50:$E$52,0)))) -> 39 | CV19: =IF(CV2="Trough",INDEX($N$50:$N$52,MATCH(CV2,$E$50:$E$52,0)),IF(CV2="Shoulder",INDEX($N$50:$N$52,MATCH(CV2,$E$50:$E$52,0)),INDEX($N$50:$N$52,MATCH(CV2,$E$50:$E$52,0)))) -> 41 | CW19: =IF(CW2="Trough",INDEX($N$50:$N$52,MATCH(CW2,$E$50:$E$52,0)),IF(CW2="Shoulder",INDEX($N$50:$N$52,MATCH(CW2,$E$50:$E$52,0)),INDEX($N$50:$N$52,MATCH(CW2,$E$50:$E$52,0)))) -> 41 | CX19: =IF(CX2="Trough",INDEX($N$50:$N$52,MATCH(CX2,$E$50:$E$52,0)),IF(CX2="Shoulder",INDEX($N$50:$N$52,MATCH(CX2,$E$50:$E$52,0)),INDEX($N$50:$N$52,MATCH(CX2,$E$50:$E$52,0)))) -> 41 | CY19: =IF(CY2="Trough",INDEX($N$50:$N$52,MATCH(CY2,$E$50:$E$52,0)),IF(CY2="Shoulder",INDEX($N$50:$N$52,MATCH(CY2,$E$50:$E$52,0)),INDEX($N$50:$N$52,MATCH(CY2,$E$50:$E$52,0)))) -> 60 | CZ19: =IF(CZ2="Trough",INDEX($N$50:$N$52,MATCH(CZ2,$E$50:$E$52,0)),IF(CZ2="Shoulder",INDEX($N$50:$N$52,MATCH(CZ2,$E$50:$E$52,0)),INDEX($N$50:$N$52,MATCH(CZ2,$E$50:$E$52,0)))) -> 60 | DA19: =IF(DA2="Trough",INDEX($N$50:$N$52,MATCH(DA2,$E$50:$E$52,0)),IF(DA2="Shoulder",INDEX($N$50:$N$52,MATCH(DA2,$E$50:$E$52,0)),INDEX($N$50:$N$52,MATCH(DA2,$E$50:$E$52,0)))) -> 41 | DB19: =IF(DB2="Trough",INDEX($N$50:$N$52,MATCH(DB2,$E$50:$E$52,0)),IF(DB2="Shoulder",INDEX($N$50:$N$52,MATCH(DB2,$E$50:$E$52,0)),INDEX($N$50:$N$52,MATCH(DB2,$E$50:$E$52,0)))) -> 41 | DC19: =IF(DC2="Trough",INDEX($N$50:$N$52,MATCH(DC2,$E$50:$E$52,0)),IF(DC2="Shoulder",INDEX($N$50:$N$52,MATCH(DC2,$E$50:$E$52,0)),INDEX($N$50:$N$52,MATCH(DC2,$E$50:$E$52,0)))) -> 41 | ... DG19: =IF(DG2="Trough",INDEX($N$50:$N$52,MATCH(DG2,$E$50:$E$52,0)),IF(DG2="Shoulder",INDEX($N$50:$N$52,MATCH(DG2,$E$50:$E$52,0)),INDEX($N$50:$N$52,MATCH(DG2,$E$50:$E$52,0)))) -> 41
C20: Subtrctions | F20: =+IF(F15<E15,F15-E15, 0) -> -4 | G20: =+IF(G15<F15,G15-F15, 0) -> -1 | H20: =+IF(H15<G15,H15-G15, 0) -> 0 | I20: =+IF(I15<H15,I15-H15, 0) -> 0 | J20: =+IF(J15<I15,J15-I15, 0) -> -2 | K20: =+IF(K15<J15,K15-J15, 0) -> -6 | L20: =+IF(L15<K15,L15-K15, 0) -> 0 | M20: =+IF(M15<L15,M15-L15, 0) -> 0 | ... V20: =+IF(V15<U15,V15-U15, 0) -> 0 | W20: -38 | X20: -38 | Y20: -53 | Z20: -20 | AA20: -17 | AB20: 0 | AC20: -23 | AD20: -43 | AE20: -52 | AF20: -37 | AG20: -39 | AH20: -36 | AI20: -20 | AJ20: -31 | AK20: -13 | AL20: -38 | AM20: -21 | AN20: -19 | AO20: -27 | AP20: -28 | AQ20: -33 | AR20: -31 | AS20: -40 | AT20: -28 | AU20: -35 | AV20: -24 | AW20: -21 | AX20: =ROUNDUP(AW16*AX36, 0) -> -28 | AY20: =ROUNDUP(AX16*AY36, 0) -> -22 | AZ20: =ROUNDUP(AY16*AZ36, 0) -> -27 | BA20: =ROUNDUP(AZ16*BA36, 0) -> -28 | BB20: =ROUNDUP(BA16*BB36, 0) -> -30 | BC20: =ROUNDUP(BB16*BC36, 0) -> -30 | BD20: =ROUNDUP(BC16*BD36, 0) -> -37 | BE20: =ROUNDUP(BD16*BE36, 0) -> -41 | ... DG20: =ROUNDUP(DF16*DG36, 0) -> -30
C21: # of Anticipated Appointments | P21: 21 | Q21: 22 | R21: 20 | S21: 16 | T21: 25 | U21: 22 | V21: 100 | W21: 218 | X21: 243 | Y21: 240 | Z21: 237 | AA21: 224 | AB21: 71 | AC21: 82 | AD21: 85 | AE21: 87 | AF21: 89 | AG21: 80 | AH21: 79 | AI21: 88 | AJ21: 52 | AK21: 91 | AL21: 55 | AM21: 66 | AN21: 70 | AO21: 74 | AP21: 72 | AQ21: 90 | AR21: 90 | AS21: 77 | AT21: 88 | AU21: 84 | AV21: 68 | AW21: 76 | AX21: =+(AX23*AW15)+AX15 -> 54.916461 | AY21: =+(AY23*AX15)+AY15 -> 64.250573 | AZ21: =+(AZ23*AY15)+AZ15 -> 70.365326 | BA21: =+(BA23*AZ15)+BA15 -> 79.336535 | BB21: =+(BB23*BA15)+BB15 -> 77.369417 | BC21: =+(BC23*BB15)+BC15 -> 104.60162 | BD21: =+(BD23*BC15)+BD15 -> 107.52186 | BE21: =+(BE23*BD15)+BE15 -> 107.89307 | ... DG21: =+(DG23*DF15)+DG15 -> 77.687309
C22: # of Anticipated Clients | W22: 135 | X22: 139 | Y22: 144 | Z22: 143 | AA22: 135 | AB22: 59 | AC22: 74 | AD22: 74 | AE22: 73 | AF22: 72 | AG22: 68 | AH22: 65 | AI22: 73 | AJ22: 43 | AK22: 70 | AL22: 47 | AM22: 57 | AN22: 63 | AO22: 60 | AP22: 65 | AQ22: 70 | AR22: 80 | AS22: 64 | AT22: 74 | AU22: 66 | AV22: 56 | AW22: 61 | AX22: =+AW22+AX18 -> 47 | AY22: =+AX22+AY18 -> 56 | AZ22: =+AY22+AZ18 -> 62 | BA22: =+AZ22+BA18 -> 67 | BB22: =+BA22+BB18 -> 70 | BC22: =+BB22+BC18 -> 88 | BD22: =+BC22+BD18 -> 99 | BE22: =+BD22+BE18 -> 91 | ... DG22: =+DF22+DG18 -> 71
C23: Reschedule/Cancellation Rate | V23: =+(V21-V15)/V21 -> 0.25 | W23: =+(W21-W15)/W21 -> 0.18807339 | X23: =+(X21-X15)/X21 -> 0.21399177 | Y23: =+(Y21-Y15)/Y21 -> 0.20833333 | Z23: =+(Z21-Z15)/Z21 -> 0.20675105 | AA23: =+(AA21-AA15)/AA21 -> 0.075892857 | AB23: =+(AB21-AB15)/AB21 -> 0.056338028 | AC23: =+(AC21-AC15)/AC21 -> 0.097560976 | ... AW23: =+(AW21-AW15)/AW21 -> 0.052631579 | AX23: =+AVERAGE(AR23:AW23) -> 0.091815956 | AY23: =+AX23 -> 0.091815956 | AZ23: 0.08 | BA23: =+AZ23 -> 0.08 | BB23: =+BA23 -> 0.08 | BC23: =+BB23 -> 0.08 | BD23: =+BC23 -> 0.08 | BE23: =+BD23 -> 0.08 | BF23: =+BE23 -> 0.08 | BG23: =+BF23 -> 0.08 | BH23: =+BG23 -> 0.08 | ... BK23: =+BJ23 -> 0.08 | BL23: 0.05 | BM23: =+BL23 -> 0.05 | BN23: =+BM23 -> 0.05 | BO23: =+BN23 -> 0.05 | BP23: =+BO23 -> 0.05 | BQ23: =+BP23 -> 0.05 | BR23: =+BQ23 -> 0.05 | BS23: =+BR23 -> 0.05 | BT23: =+BS23 -> 0.05 | ... BW23: =+BV23 -> 0.05 | BX23: 0.03 | BY23: =+BX23 -> 0.03 | BZ23: =+BY23 -> 0.03 | CA23: =+BZ23 -> 0.03 | CB23: =+CA23 -> 0.03 | CC23: =+CB23 -> 0.03 | CD23: =+CC23 -> 0.03 | CE23: =+CD23 -> 0.03 | CF23: =+CE23 -> 0.03 | ... DG23: =+DF23 -> 0.03
C24: Client Base Growth Rate | X24: =+(X16/W16)-1 -> 0 | Y24: =+(Y16/X16)-1 -> 0.048780488 | Z24: =+(Z16/Y16)-1 -> -0.015503876 | AA24: =+(AA16/Z16)-1 -> -0.0078740157 | AB24: =+(AB16/AA16)-1 -> -0.56349206 | AC24: =+(AC16/AB16)-1 -> 0.25454545 | AD24: =+(AD16/AC16)-1 -> -0.014492754 | AE24: =+(AE16/AD16)-1 -> -0.029411765 | ... DG24: =+(DG16/DF16)-1 -> 0.18333333
C25: Client Hit Rate | W25: =+(W16/W22) -> 0.91111111 | X25: =+(X16/X22) -> 0.88489209 | Y25: =+(Y16/Y22) -> 0.89583333 | Z25: =+(Z16/Z22) -> 0.88811189 | AA25: =+(AA16/AA22) -> 0.93333333 | AB25: =+(AB16/AB22) -> 0.93220339 | AC25: =+(AC16/AC22) -> 0.93243243 | AD25: =+(AD16/AD22) -> 0.91891892 | ... AW25: =+(AW16/AW22) -> 0.95081967 | AX25: =+AVERAGE(AR25:AW25) -> 0.94555862 | AY25: =+AX25 -> 0.94555862 | AZ25: =+AY25 -> 0.94555862 | BA25: =+AZ25 -> 0.94555862 | BB25: =+BA25 -> 0.94555862 | BC25: =+BB25 -> 0.94555862 | BD25: =+BC25 -> 0.94555862 | BE25: =+BD25 -> 0.94555862 | BF25: =+BE25 -> 0.94555862 | ... DG25: =+DF25 -> 0.94555862
C26: Appt Multiplier | W26: =+W15/W16 -> 1.4390244 | X26: =+X15/X16 -> 1.5528455 | Y26: =+Y15/Y16 -> 1.4728682 | Z26: =+Z15/Z16 -> 1.480315 | AA26: =+AA15/AA16 -> 1.6428571 | AB26: =+AB15/AB16 -> 1.2181818 | AC26: =+AC15/AC16 -> 1.0724638 | AD26: =+AD15/AD16 -> 1.1323529 | ... AW26: =+AW15/AW16 -> 1.2413793 | AX26: =+AL26 -> 1.0869565 | AY26: =+AM26 -> 1.1296296 | AZ26: =+AN26 -> 1.1186441 | BA26: =+AO26 -> 1.1694915 | BB26: =+AP26 -> 1.0793651 | BC26: =+AQ26 -> 1.1884058 | BD26: =+AR26 -> 1.0641026 | BE26: =+AS26 -> 1.1612903 | ... DG26: =+CU26 -> 1.1296296
B27: Coverage
B28: 90 | C28: Billing Days | E28: =NETWORKDAYS(D4+1,E4,Holidays!$B$3:$B$62) -> 19 | F28: =NETWORKDAYS(E4+1,F4,Holidays!$B$3:$B$62) -> 23 | G28: =NETWORKDAYS(F4+1,G4,Holidays!$B$3:$B$62) -> 21 | H28: =NETWORKDAYS(G4+1,H4,Holidays!$B$3:$B$62) -> 21 | I28: =NETWORKDAYS(H4+1,I4,Holidays!$B$3:$B$62) -> 22 | J28: =NETWORKDAYS(I4+1,J4,Holidays!$B$3:$B$62) -> 20 | K28: =NETWORKDAYS(J4+1,K4,Holidays!$B$3:$B$62) -> 23 | L28: =NETWORKDAYS(K4+1,L4,Holidays!$B$3:$B$62) -> 21 | ... DG28: =NETWORKDAYS(DF4+1,DG4,Holidays!$B$3:$B$62) -> 22
C29: Hours / Day / Client | E29: =+E30/E28/E15 -> 0.0043859649 | F29: =+F30/F28/F15 -> 0.0054347826 | G29: =+G30/G28/G15 -> 0.0068027211 | H29: =+H30/H28/H15 -> 0.0047619048 | I29: =+I30/I28/I15 -> 0.0034965035 | J29: =+J30/J28/J15 -> 0.0045454545 | K29: =+K30/K28/K15 -> 0.065217391 | L29: =+L30/L28/L15 -> 0.10846561 | ... AW29: =+AW30/AW28/AW15 -> 0.084541063 | AX29: =+AL29 -> 0.11894737 | AY29: =+AM29 -> 0.11647972 | AZ29: =+AN29 -> 0.091238472 | BA29: =+AO29 -> 0.10416667 | BB29: =+AP29 -> 0.10889356 | BC29: =+AQ29 -> 0.094650776 | BD29: =+AR29 -> 0.092415115 | BE29: =+AS29 -> 0.089285714 | ... DG29: =+CU29 -> 0.11647972
C30: Total Billable Hours | E30: 1 | F30: 1 | G30: 1 | H30: 1 | I30: 1 | J30: 1 | K30: 7.5 | L30: =20.5 -> 20.5 | M30: 57.25 | N30: 31 | O30: 15 | P30: 26.33 | Q30: 21.25 | R30: 19.75 | S30: 18.25 | T30: 41.25 | U30: 41.5 | V30: 32.25 | W30: 115.25 | X30: 123.25 | Y30: 120.5 | Z30: 121.25 | AA30: 129.5 | AB30: 134.5 | AC30: 155 | AD30: 183.75 | AE30: 176.75 | AF30: 180 | AG30: 157.5 | AH30: 143 | AI30: 165.5 | AJ30: 92.75 | AK30: 177.5 | AL30: 113 | AM30: 135 | AN30: 138.5 | AO30: 143.75 | AP30: 155.5 | AQ30: 170.75 | AR30: 168.75 | AS30: 135 | AT30: 146 | AU30: 150.85 | AV30: 124 | AW30: 140 | AX30: =+AX15*AX28*AX29 -> 103.42507 | AY30: =+AY15*AY28*AY29 -> 146.31275 | AZ30: =+AZ15*AZ28*AZ29 -> 131.63542 | BA30: =+BA15*BA28*BA29 -> 154.35443 | BB30: =+BB15*BB28*BB29 -> 171.15111 | BC30: =+BC15*BC28*BC29 -> 205.91252 | BD30: =+BD15*BD28*BD29 -> 193.31673 | BE30: =+BE15*BE28*BE29 -> 196.27967 | ... DG30: =+DG15*DG28*DG29 -> 194.33718
C31: Nonbillable Hours | L31: 3.75 | M31: 14.75 | N31: 13.5 | O31: 14 | P31: 14 | Q31: 14 | R31: 5.5 | S31: 4.5 | T31: 5 | U31: 25.75 | V31: 11.75 | W31: 26.75 | X31: 33.75 | Y31: 32.5 | Z31: 31.5 | AA31: 10.75 | AB31: 7.75 | AC31: 16 | AD31: 19.75 | AE31: 23.75 | AF31: 21 | AG31: 14.5 | AH31: 31.75 | AI31: 33 | AJ31: 11.5 | AK31: 21.5 | AL31: 11.25 | AM31: 11.25 | AN31: 11 | AO31: 14.25 | AP31: 6.25 | AQ31: 15 | AR31: 12.5 | AS31: 8 | AT31: 26 | AU31: 20 | AV31: 11.25 | AW31: 6.25 | AX31: =+AX33*(AX21-AX15) -> 11.908231 | AY31: =+AY33*(AY21-AY15) -> 7.9893832 | AZ31: =+AZ33*(AZ21-AZ15) -> 8.619839 | BA31: =+BA33*(BA21-BA15) -> 9.4505844 | BB31: =+BB33*(BB21-BB15) -> 10.676943 | BC31: =+BC33*(BC21-BC15) -> 10.295358 | BD31: =+BD33*(BD21-BD15) -> 14.25025 | BE31: =+BE33*(BE21-BE15) -> 14.354687 | ... DG31: =+DG33*(DG21-DG15) -> 3.3324968
C32: Realized / Effective Bill Rate | E32: =+E13/(E30+E31) -> 0 | F32: =+F13/(F30+F31) -> 0 | G32: =+G13/(G30+G31) -> 0 | H32: =+H13/(H30+H31) -> 0 | I32: =+I13/(I30+I31) -> 0 | J32: =+J13/(J30+J31) -> 0 | K32: =+K13/(K30+K31) -> 0 | L32: =+L13/(L30+L31) -> 0 | ... AW32: =+AW13/(AW30+AW31) -> 47.851282 | AX32: =+AVERAGE(AR32:AW32)+3 -> 48.504564 | AY32: =+AX32 -> 48.504564 | AZ32: =+IF(AZ1<>AY1, AY32*1.05, AY32) -> 50.929792 | BA32: =+IF(BA1<>AZ1, AZ32*1.05, AZ32) -> 50.929792 | BB32: =+IF(BB1<>BA1, BA32*1.05, BA32) -> 50.929792 | BC32: =+IF(BC1<>BB1, BB32*1.05, BB32) -> 50.929792 | BD32: =+IF(BD1<>BC1, BC32*1.05, BC32) -> 50.929792 | BE32: =+IF(BE1<>BD1, BD32*1.05, BD32) -> 50.929792 | BF32: =+IF(BF1<>BE1, BE32*1.05, BE32) -> 50.929792 | BG32: =+IF(BG1<>BF1, BF32*1.05, BF32) -> 50.929792 | ... DG32: =+IF(DG1<>DF1, DF32*1.05, DF32) -> 61.90548
C33: Nonbillable Hours/Lost Appt | W33: =+(W31/(W21-W15)) -> 0.65243902 | X33: =+(X31/(X21-X15)) -> 0.64903846 | Y33: =+(Y31/(Y21-Y15)) -> 0.65 | Z33: =+(Z31/(Z21-Z15)) -> 0.64285714 | AA33: =+(AA31/(AA21-AA15)) -> 0.63235294 | AB33: =(AB31/(AB21-AB15)) -> 1.9375 | AC33: =(AC31/(AC21-AC15)) -> 2 | AD33: =(AD31/(AD21-AD15)) -> 2.46875 | AE33: =(AE31/(AE21-AE15)) -> 2.6388889 | AF33: =(AF31/(AF21-AF15)) -> 3 | AG33: =(AG31/(AG21-AG15)) -> 2.9 | AH33: =(AH31/(AH21-AH15)) -> 2.4423077 | AI33: =(AI31/(AI21-AI15)) -> 2.3571429 | ... AW33: =(AW31/(AW21-AW15)) -> 1.5625 | AX33: =+AVERAGE(AR33:AW33) -> 1.8013438 | AY33: =+AX33 -> 1.8013438 | AZ33: =+AY33 -> 1.8013438 | BA33: =+AZ33 -> 1.8013438 | BB33: =+BA33 -> 1.8013438 | BC33: =+BB33 -> 1.8013438 | BD33: =+BC33 -> 1.8013438 | BE33: =+BD33 -> 1.8013438 | BF33: =+BE33 -> 1.8013438 | ... DG33: =+DF33 -> 1.8013438
C34: Productivity Utilization | V34: =+V30/(V30+V31) -> 0.73295455 | W34: =+W30/(W30+W31) -> 0.81161972 | X34: =+X30/(X30+X31) -> 0.78503185 | Y34: =+Y30/(Y30+Y31) -> 0.7875817 | Z34: =+Z30/(Z30+Z31) -> 0.79378069 | AA34: =+AA30/(AA30+AA31) -> 0.92335116 | AB34: =+AB30/(AB30+AB31) -> 0.94551845 | AC34: =+AC30/(AC30+AC31) -> 0.90643275 | ... DG34: =+DG30/(DG30+DG31) -> 0.98314108
C36: T6M Avg Monthly Attrition | L36: =+AVERAGE(F20:L20)/L15 -> -0.20634921 | M36: =+AVERAGE(G20:M20)/M15 -> -0.075630252 | N36: =+AVERAGE(H20:N20)/N15 -> -0.18181818 | O36: =+AVERAGE(I20:O20)/O15 -> -0.36734694 | P36: =+AVERAGE(J20:P20)/P15 -> -0.21428571 | Q36: =+AVERAGE(K20:Q20)/Q15 -> -0.25714286 | R36: =+AVERAGE(L20:R20)/R15 -> -0.17142857 | S36: =+AVERAGE(M20:S20)/S15 -> -0.30612245 | ... V36: =+AVERAGE(P20:V20)/V15 -> -0.0095238095 | W36: =+AVERAGE(Q20:W20)/W16 -> -0.049941928 | X36: =+AVERAGE(Q20:W20)/AVERAGE(Q16:W16) -> -0.049941928 | Y36: =+AVERAGE(R20:X20)/AVERAGE(R16:X16) -> -0.091753775 | Z36: =+AVERAGE(S20:Y20)/AVERAGE(S16:Y16) -> -0.15085714 | AA36: =+AVERAGE(T20:Z20)/AVERAGE(T16:Z16) -> -0.16960729 | AB36: =+AVERAGE(U20:AA20)/AVERAGE(U16:AA16) -> -0.18880801 | AC36: =+AVERAGE(V20:AB20)/AVERAGE(V16:AB16) -> -0.20832462 | AD36: =+AVERAGE(W20:AC20)/AVERAGE(W16:AC16) -> -0.25132979 | AE36: =+AVERAGE(X20:AD20)/AVERAGE(X16:AD16) -> -0.27833572 | ... DG36: =+AVERAGE(CZ20:DF20)/AVERAGE(CZ16:DF16) -> -0.51939107
C37: Implied Tenure | L37: =1/-L36 -> 4.8461538 | M37: =1/-M36 -> 13.222222 | N37: =1/-N36 -> 5.5 | O37: =1/-O36 -> 2.7222222 | P37: =1/-P36 -> 4.6666667 | Q37: =1/-Q36 -> 3.8888889 | R37: =1/-R36 -> 5.8333333 | S37: =1/-S36 -> 3.2666667 | ... DG37: =1/-DG36 -> 1.9253315
C38: Average Revenue | L38: =+L13/L15 -> 0 | M38: =+M13/M15 -> 0 | N38: =+N13/N15 -> 0 | O38: =+O13/O15 -> 0 | P38: =+P13/P15 -> 0 | Q38: =+Q13/Q15 -> 0 | R38: =+R13/R15 -> 0 | S38: =+S13/S15 -> 0 | ... V38: =+V13/V15 -> 0 | W38: =+W13/W16 -> 0 | X38: =+X13/X16 -> 0 | Y38: =+Y13/Y16 -> 0 | Z38: =+Z13/Z16 -> 0 | AA38: =+AA13/AA16 -> 0 | AB38: =+(AB13/AB16)*AB26 -> 126.87917 | AC38: =+(AC13/AC16)*AC26 -> 104.85665 | AD38: =+(AD13/AD16)*AD26 -> 127.21069 | AE38: =+(AE13/AE16)*AE26 -> 139.97383 | AF38: =+(AF13/AF16)*AF26 -> 138.6129 | AG38: =+(AG13/AG16)*AG26 -> 126.99408 | AH38: =+(AH13/AH16)*AH26 -> 136.15329 | AI38: =+(AI13/AI16)*AI26 -> 127.77041 | ... DG38: =+(DG13/DG16)*DG26 -> 212.94091
C39: Lifetime Revenue | L39: =+L38*L37 -> 0 | M39: =+M38*M37 -> 0 | N39: =+N38*N37 -> 0 | O39: =+O38*O37 -> 0 | P39: =+P38*P37 -> 0 | Q39: =+Q38*Q37 -> 0 | R39: =+R38*R37 -> 0 | S39: =+S38*S37 -> 0 | ... DG39: =+DG38*DG37 -> 409.98185
C40: GM% | L40: =+L92/L13 -> #DIV/0! | M40: =+M92/M13 -> #DIV/0! | N40: =+N92/N13 -> #DIV/0! | O40: =+O92/O13 -> #DIV/0! | P40: =+P92/P13 -> #DIV/0! | Q40: 0 | R40: 0 | S40: 0 | T40: 0 | U40: 0 | V40: 0 | W40: =+W92/W13 -> #DIV/0! | X40: =+X92/X13 -> #DIV/0! | Y40: =+Y92/Y13 -> #DIV/0! | Z40: =+Z92/Z13 -> #DIV/0! | AA40: =+AA92/AA13 -> #DIV/0! | AB40: =+AB65/AB13 -> 0.91205377 | AC40: =+AC65/AC13 -> 0.90307356 | AD40: =+AD65/AD13 -> 0.9303806 | AE40: =+AE65/AE13 -> 0.9569157 | AF40: =+AF65/AF13 -> 0.82341948 | AG40: =+AG65/AG13 -> 0.82043472 | AH40: =+AH65/AH13 -> 0.87787383 | AI40: =+AI65/AI13 -> 0.88487457 | ... DG40: =+DG65/DG13 -> 0.73811905
C41: MRR | W41: =+(W38)*W17*W26 -> 0 | X41: =+(X38)*X17*X26 -> 0 | Y41: =+(Y38)*Y17*Y26 -> 0 | Z41: =+(Z38)*Z17*Z26 -> 0 | AA41: =+(AA38)*AA17*AA26 -> 0 | AB41: =+(AB38)*AB17 -> 3806.3752 | AC41: =+(AC38)*AC17 -> 3565.126 | AD41: =+(AD38)*AD17 -> 3434.6887 | AE41: =+(AE38)*AE17 -> 2659.5028 | AF41: =+(AF38)*AF17 -> 4158.3869 | AG41: =+(AG38)*AG17 -> 3809.8225 | AH41: =+(AH38)*AH17 -> 3948.4455 | AI41: =+(AI38)*AI17 -> 4344.1941 | ... DG41: =+(DG38)*DG17 -> 8133.7695
C42: T6M LTV | L42: =+IFERROR(AVERAGE(L40*L39,K40*K39, J40*J39, I40*I39,H39*H40,G39*G40), 0) -> 0 | M42: =+IFERROR(AVERAGE(M40*M39,L40*L39, K40*K39, J40*J39,I39*I40,H39*H40), 0) -> 0 | N42: =+IFERROR(AVERAGE(N40*N39,M40*M39, L40*L39, K40*K39,J39*J40,I39*I40), 0) -> 0 | O42: =+IFERROR(AVERAGE(O40*O39,N40*N39, M40*M39, L40*L39,K39*K40,J39*J40), 0) -> 0 | P42: =+IFERROR(AVERAGE(P40*P39,O40*O39, N40*N39, M40*M39,L39*L40,K39*K40), 0) -> 0 | Q42: =+IFERROR(AVERAGE(Q40*Q39,P40*P39, O40*O39, N40*N39,M39*M40,L39*L40), 0) -> 0 | R42: =+IFERROR(AVERAGE(R40*R39,Q40*Q39, P40*P39, O40*O39,N39*N40,M39*M40), 0) -> 0 | S42: =+IFERROR(AVERAGE(S40*S39,R40*R39, Q40*Q39, P40*P39,O39*O40,N39*N40), 0) -> 0 | ... DG42: =+IFERROR(AVERAGE(DG40*DG39,DF40*DF39, DE40*DE39, DD40*DD39,DC39*DC40,DB39*DB40), 0) -> 289.97224
C43: T6M CAC | L43: =+AVERAGE(J89:L89) -> 0 | M43: =+AVERAGE(K89:M89) -> 0 | N43: =+AVERAGE(L89:N89) -> 0 | O43: =+AVERAGE(M89:O89) -> 0 | P43: =+AVERAGE(N89:P89) -> 0 | Q43: =+AVERAGE(O89:Q89) -> 0 | R43: =+AVERAGE(P89:R89) -> 0 | S43: =+AVERAGE(Q89:S89) -> 0 | ... V43: =+AVERAGE(T89:V89) -> 0 | X43: =+AVERAGE(V93:X93) -> 0 | Y43: =+AVERAGE(W93:Y93) -> 0 | Z43: =+AVERAGE(X93:Z93) -> 0 | AA43: =+AVERAGE(Y93:AA93) -> 0 | AB43: =+AVERAGE(W93:AB93)/AB17 -> 5.0918889 | AC43: =+AVERAGE(X93:AC93)/AC17 -> 10.026471 | AD43: =+AVERAGE(Y93:AD93)/AD17 -> 17.133889 | AE43: =+AVERAGE(Z93:AE93)/AE17 -> 34.362895 | AF43: =+AVERAGE(AA93:AF93)/AF17 -> 37.866111 | AG43: =+AVERAGE(AB93:AG93)/AG17 -> 54.101222 | AH43: =+AVERAGE(AC93:AH93)/AH17 -> 63.302241 | AI43: =+AVERAGE(AD93:AI93)/AI17 -> 62.410588 | ... DG43: =+AVERAGE(DB93:DG93)/DG17 -> 157.87463
C44: LTV/CAC | L44: =+L42/L43 -> #DIV/0! | M44: =+M42/M43 -> #DIV/0! | N44: =+N42/N43 -> #DIV/0! | O44: =+O42/O43 -> #DIV/0! | P44: =+P42/P43 -> #DIV/0! | Q44: =+Q42/Q43 -> #DIV/0! | R44: =+R42/R43 -> #DIV/0! | S44: =+S42/S43 -> #DIV/0! | ... U44: =+U42/U43 -> #DIV/0! | V44: 0 | W44: =+W42/W43 -> #DIV/0! | X44: =+X42/X43 -> #DIV/0! | Y44: =+Y42/Y43 -> #DIV/0! | Z44: =+Z42/Z43 -> #DIV/0! | AA44: =+AA42/AA43 -> #DIV/0! | AB44: =+AB42/AB43 -> 0 | AC44: =+AC42/AC43 -> 0 | AD44: =+AD42/AD43 -> 0 | ... DG44: =+DG42/DG43 -> 1.8367247
C45: Payback | L45: =+L43/(L38*L40) -> #DIV/0! | M45: =+M43/(M38*M40) -> #DIV/0! | N45: =+N43/(N38*N40) -> #DIV/0! | O45: =+O43/(O38*O40) -> #DIV/0! | P45: =+P43/(P38*P40) -> #DIV/0! | Q45: =+Q43/(Q38*Q40) -> #DIV/0! | R45: =+R43/(R38*R40) -> #DIV/0! | S45: =+S43/(S38*S40) -> #DIV/0! | ... U45: =+U43/(U38*U40) -> #DIV/0! | V45: 0 | W45: =+W43/(W38*W40) -> #DIV/0! | X45: =+X43/(X38*X40) -> #DIV/0! | Y45: =+Y43/(Y38*Y40) -> #DIV/0! | Z45: =+Z43/(Z38*Z40) -> #DIV/0! | AA45: =+AA43/(AA38*AA40) -> #DIV/0! | AB45: =+AB43/(AB38*AB40) -> 0.044001566 | AC45: =+AC43/(AC38*AC40) -> 0.10588367 | AD45: =+AD43/(AD38*AD40) -> 0.1447677 | ... DG45: =+DG43/(DG38*DG40) -> 1.0044465
C46: Utilization % | E46: =+E29/8 -> 0.00054824561 | F46: =+F29/8 -> 0.00067934783 | G46: =+G29/8 -> 0.00085034014 | H46: =+H29/8 -> 0.0005952381 | I46: =+I29/8 -> 0.00043706294 | J46: =+J29/8 -> 0.00056818182 | K46: =+K29/8 -> 0.0081521739 | L46: =+L29/8 -> 0.013558201 | ... DG46: =+DG29/8 -> 0.014559965
F48: 2022 | G48: 2023 | H48: 2024 | I48: 2025 | J48: 2026 | K48: 2027 | L48: 2028 | M48: 2029 | N48: 2030 | Q48: 2022 | R48: 2023 | S48: 2024 | T48: 2025 | U48: 2026 | V48: 2027 | W48: 2028 | X48: 2028 | Y48: 2028 | Z48: 2028 | AA48: 2028 | AB48: 2028 | AC48: 2028 | AD48: 2028 | AE48: 2028 | AF48: 2029 | AG48: 2029 | AH48: 2029 | AI48: 2029 | AJ48: 2029 | AK48: 2029 | AL48: 2029 | AM48: 2029 | AN48: 2029 | AO48: 2029 | AP48: 2029 | AQ48: 2029 | AR48: 2029 | AS48: 2029 | AT48: 2029 | AU48: 2029 | AV48: 2029 | AW48: 2029
E49: Average | F49: =ROUNDUP(AVERAGE(F50:F52), 0) -> 10 | G49: =ROUNDUP(AVERAGE(G50:G52), 0) -> 20 | H49: =ROUNDUP(AVERAGE(H50:H52), 0) -> 28 | I49: =ROUNDUP(AVERAGE(I50:I52), 0) -> 30 | J49: =ROUNDUP(AVERAGE(J50:J52), 0) -> 32 | K49: =ROUNDUP(AVERAGE(K50:K52), 0) -> 34 | L49: =ROUNDUP(AVERAGE(L50:L52), 0) -> 36 | M49: =ROUNDUP(AVERAGE(M50:M52), 0) -> 38 | N49: =ROUNDUP(AVERAGE(N50:N52), 0) -> 40 | P49: Average | Q49: =ROUNDUP(AVERAGE(Q50:Q52), 0) -> 1 | R49: =ROUNDUP(AVERAGE(R50:R52), 0) -> 1 | S49: =ROUNDUP(AVERAGE(S50:S52), 0) -> 1 | T49: =ROUNDUP(AVERAGE(T50:T52), 0) -> 1 | U49: =ROUNDUP(AVERAGE(U50:U52), 0) -> 1 | V49: =ROUNDUP(AVERAGE(V50:V52), 0) -> 1 | W49: =ROUNDUP(AVERAGE(W50:W52), 0) -> 1 | X49: =ROUNDUP(AVERAGE(X50:X52), 0) -> 1 | ... AW49: =ROUNDUP(AVERAGE(AW50:AW52), 0) -> 1
E50: Peak | F50: =ROUNDUP(AVERAGEIFS($E$15:$DG$15, $H$2:$DJ$2,$E$50, $H$1:$DJ$1, F48), 0) -> 12 | G50: =ROUNDUP(AVERAGEIFS($H$19:$DJ$19, $H$2:$DJ$2,$E50, $H$1:$DJ$1, G$48), 0) -> 36 | H50: =ROUNDUP(AVERAGEIFS($H$19:$DJ$19, $H$2:$DJ$2,$E50, $H$1:$DJ$1, H$48), 0) -> 42 | I50: =+H50+3 -> 45 | J50: =+I50+3 -> 48 | K50: =+J50+3 -> 51 | L50: =+K50+3 -> 54 | M50: =+L50+3 -> 57 | N50: =+M50+3 -> 60 | P50: Peak | Q50: =AVERAGEIFS($E$29:$DG$29, $H$2:$DJ$2,$E$50, $H$1:$DJ$1, Q48) -> 0.0043859649 | R50: =AVERAGEIFS($E$29:$DG$29, $H$2:$DJ$2,$E$50, $H$1:$DJ$1, R48) -> 0.10532123 | S50: =AVERAGEIFS($E$29:$DG$29, $H$2:$DJ$2,$E$50, $H$1:$DJ$1, S48) -> 0.10154242 | T50: =AVERAGEIFS($E$29:$DG$29, $H$2:$DJ$2,$E$50, $H$1:$DJ$1, T48) -> 0.097702569 | U50: =AVERAGEIFS($E$29:$DG$29, $H$2:$DJ$2,$E$50, $H$1:$DJ$1, U48) -> 0.097702569 | V50: =AVERAGEIFS($E$29:$DG$29, $H$2:$DJ$2,$E$50, $H$1:$DJ$1, V48) -> 0.097702569 | W50: =AVERAGEIFS($E$29:$DG$29, $H$2:$DJ$2,$E$50, $H$1:$DJ$1, W48) -> 0.097702569 | X50: =AVERAGEIFS($E$29:$DG$29, $H$2:$DJ$2,$E$50, $H$1:$DJ$1, X48) -> 0.097702569 | ... AW50: =AVERAGEIFS($E$29:$DG$29, $H$2:$DJ$2,$E$50, $H$1:$DJ$1, AW48) -> 0.097702569
E51: Shoulder | F51: =ROUNDUP(AVERAGEIFS($E$15:$DG$15, $H$2:$DJ$2,$E$51, $H$1:$DJ$1, F48), 0) -> 10 | G51: =ROUNDUP(AVERAGEIFS($H$19:$DJ$19, $H$2:$DJ$2,$E51, $H$1:$DJ$1, G$48), 0) -> 21 | H51: =ROUNDUP(AVERAGEIFS($H$19:$DJ$19, $H$2:$DJ$2,$E51, $H$1:$DJ$1, H$48), 0) -> 29 | I51: =+H51+2 -> 31 | J51: =+I51+2 -> 33 | K51: =+J51+2 -> 35 | L51: =+K51+2 -> 37 | M51: =+L51+2 -> 39 | N51: =+M51+2 -> 41 | P51: Shoulder | Q51: =+AVERAGEIFS($E$29:$DG$29, $H$2:$DJ$2,$E$51, $H$1:$DJ$1, Q48) -> 0.025749014 | R51: =+AVERAGEIFS($E$29:$DG$29, $H$2:$DJ$2,$E$51, $H$1:$DJ$1, R48) -> 0.10712703 | S51: =+AVERAGEIFS($E$29:$DG$29, $H$2:$DJ$2,$E$51, $H$1:$DJ$1, S48) -> 0.068991657 | T51: =+AVERAGEIFS($E$29:$DG$29, $H$2:$DJ$2,$E$51, $H$1:$DJ$1, T48) -> 0.10061158 | U51: =+AVERAGEIFS($E$29:$DG$29, $H$2:$DJ$2,$E$51, $H$1:$DJ$1, U48) -> 0.099269659 | V51: =+AVERAGEIFS($E$29:$DG$29, $H$2:$DJ$2,$E$51, $H$1:$DJ$1, V48) -> 0.099269659 | W51: =+AVERAGEIFS($E$29:$DG$29, $H$2:$DJ$2,$E$51, $H$1:$DJ$1, W48) -> 0.099269659 | X51: =+AVERAGEIFS($E$29:$DG$29, $H$2:$DJ$2,$E$51, $H$1:$DJ$1, X48) -> 0.099269659 | ... AW51: =+AVERAGEIFS($E$29:$DG$29, $H$2:$DJ$2,$E$51, $H$1:$DJ$1, AW48) -> 0.099269659
E52: Trough | F52: =ROUNDUP(AVERAGEIFS($E$15:$DG$15, $H$2:$DJ$2,$E$52, $H$1:$DJ$1, F48), 0) -> 8 | G52: =ROUNDUP(AVERAGEIFS($H$19:$DJ$19, $H$2:$DJ$2,$E52, $H$1:$DJ$1, G$48), 0) -> 1 | H52: =ROUNDUP(AVERAGEIFS($H$19:$DJ$19, $H$2:$DJ$2,$E52, $H$1:$DJ$1, H$48), 0) -> 13 | I52: =+H52+1 -> 14 | J52: =+I52+1 -> 15 | K52: =+J52+1 -> 16 | L52: =+K52+1 -> 17 | M52: =+L52+1 -> 18 | N52: =+M52+1 -> 19 | P52: Trough | Q52: =AVERAGEIFS($E$29:$DG$29, $H$2:$DJ$2,$E$52, $H$1:$DJ$1, Q48) -> 0.034989648 | R52: =AVERAGEIFS($E$29:$DG$29, $H$2:$DJ$2,$E$52, $H$1:$DJ$1, R48) -> 0.10816312 | S52: =AVERAGEIFS($E$29:$DG$29, $H$2:$DJ$2,$E$52, $H$1:$DJ$1, S48) -> 0.10332924 | T52: =AVERAGEIFS($E$29:$DG$29, $H$2:$DJ$2,$E$52, $H$1:$DJ$1, T48) -> 0.09384377 | U52: =AVERAGEIFS($E$29:$DG$29, $H$2:$DJ$2,$E$52, $H$1:$DJ$1, U48) -> 0.09384377 | V52: =AVERAGEIFS($E$29:$DG$29, $H$2:$DJ$2,$E$52, $H$1:$DJ$1, V48) -> 0.09384377 | W52: =AVERAGEIFS($E$29:$DG$29, $H$2:$DJ$2,$E$52, $H$1:$DJ$1, W48) -> 0.09384377 | X52: =AVERAGEIFS($E$29:$DG$29, $H$2:$DJ$2,$E$52, $H$1:$DJ$1, X48) -> 0.09384377 | ... AW52: =AVERAGEIFS($E$29:$DG$29, $H$2:$DJ$2,$E$52, $H$1:$DJ$1, AW48) -> 0.09384377
E53: Trough | F53: =F52/F49-1 -> -0.2 | G53: =G52/G49-1 -> -0.95 | H53: =H52/H49-1 -> -0.53571429 | I53: =I52/I49-1 -> -0.53333333 | J53: =J52/J49-1 -> -0.53125 | K53: =K52/K49-1 -> -0.52941176 | L53: =L52/L49-1 -> -0.52777778 | M53: =M52/M49-1 -> -0.52631579 | N53: =N52/N49-1 -> -0.525 | P53: Trough | Q53: =Q52/Q49-1 -> -0.96501035 | R53: =R52/R49-1 -> -0.89183688 | S53: =S52/S49-1 -> -0.89667076 | T53: =T52/T49-1 -> -0.90615623 | U53: =U52/U49-1 -> -0.90615623 | V53: =V52/V49-1 -> -0.90615623 | W53: =W52/W49-1 -> -0.90615623 | X53: =X52/X49-1 -> -0.90615623 | ... AW53: =AW52/AW49-1 -> -0.90615623
E54: Shoulder | F54: =F51/F49-1 -> 0 | G54: =G51/G49-1 -> 0.05 | H54: =H51/H49-1 -> 0.035714286 | I54: =I51/I49-1 -> 0.033333333 | J54: =J51/J49-1 -> 0.03125 | K54: =K51/K49-1 -> 0.029411765 | L54: =L51/L49-1 -> 0.027777778 | M54: =M51/M49-1 -> 0.026315789 | N54: =N51/N49-1 -> 0.025 | P54: Shoulder | Q54: =Q51/Q49-1 -> -0.97425099 | R54: =R51/R49-1 -> -0.89287297 | S54: =S51/S49-1 -> -0.93100834 | T54: =T51/T49-1 -> -0.89938842 | U54: =U51/U49-1 -> -0.90073034 | V54: =V51/V49-1 -> -0.90073034 | W54: =W51/W49-1 -> -0.90073034 | X54: =X51/X49-1 -> -0.90073034 | ... AW54: =AW51/AW49-1 -> -0.90073034
B57: Cost of Goods Sold
B58: 50100 Software - COS | AB58: 144.34 | AC58: 195.79 | AD58: 210.1 | AE58: 193.92 | AF58: 192.8 | AG58: 204.71 | AH58: 174.91 | AI58: 191.38 | AJ58: 128.31 | AK58: 231.31 | AL58: 160.15 | AM58: 171.4 | AN58: 197.3 | AO58: 202.11 | AP58: 214.54 | AQ58: 247.79 | AR58: 240.23 | AS58: 182.1 | AT58: 216.6 | AU58: 205.55 | AV58: 222.12 | AW58: =282 -> 282 | AX58: =+AX62*AX9 -> 166.47625 | AY58: =+AY62*AY9 -> 235.50961 | AZ58: =+AZ62*AZ9 -> 222.47873 | BA58: =+BA62*BA9 -> 260.87644 | BB58: =+BB62*BB9 -> 289.26473 | BC58: =+BC62*BC9 -> 348.01543 | BD58: =+BD62*BD9 -> 326.72713 | BE58: =+BE62*BE9 -> 331.73482 | ... DG58: =+DG62*DG9 -> 399.23521
B59: 50200 Materials - COGS | AB59: 359.46 | AC59: 458.1 | AD59: 321.74 | AE59: 142.87 | AF59: 753.32 | AG59: 314.9 | AH59: 165.74 | AI59: 38.46 | AJ59: 28.36 | AK59: 357.18 | AL59: 356.29 | AM59: 589.19 | AN59: 249.98 | AO59: 497.5 | AP59: 810.15 | AQ59: 352.78 | AR59: 754.25 | AS59: 503.73 | AT59: 588.11 | AU59: 768.16 | AV59: 893.43 | AW59: =578.51 -> 578.51 | AX59: =+AX63*AX9 -> 506.58574 | AY59: =+AY63*AY9 -> 716.65365 | AZ59: =+AZ63*AZ9 -> 677.0008 | BA59: =+BA63*BA9 -> 793.84466 | BB59: =+BB63*BB9 -> 880.22998 | BC59: =+BC63*BC9 -> 1059.0079 | BD59: =+BD63*BD9 -> 994.22773 | BE59: =+BE63*BE9 -> 1009.4661 | ... DG59: =+DG63*DG9 -> 1214.8692
B60: 50300 Sub-Contractors | AF60: 475 | AG60: 765 | AH60: 394 | AI60: 610 | AJ60: 210 | AK60: 770 | AL60: 432 | AM60: 470 | AN60: 50 | AO60: 45 | AR60: 629 | AV60: 30 | AX60: =+'People Plan'!Y13 -> 276.37608 | AY60: =+'People Plan'!Z13 -> 979.69132 | AZ60: =+'People Plan'!AA13 -> 759.53125 | BA60: =+'People Plan'!AB13 -> 1100.3165 | BB60: =+'People Plan'!AC13 -> 1352.2667 | BC60: =+'People Plan'!AD13 -> 1903.6878 | BD60: =+'People Plan'!AE13 -> 1714.751 | BE60: =+'People Plan'!AF13 -> 1729.195 | ... DG60: =+'People Plan'!CH13 -> 1700.0577
B61: Total Cost of Goods Sold | V61: =+SUM(V58:V59) -> 0 | W61: =+SUM(W58:W59) -> 0 | X61: =+SUM(X58:X59) -> 0 | Y61: =+SUM(Y58:Y59) -> 0 | Z61: =+SUM(Z58:Z59) -> 0 | AA61: =+SUM(AA58:AA59) -> 0 | AB61: =SUM(AB58:AB60) -> 503.8 | AC61: =SUM(AC58:AC60) -> 653.89 | AD61: =SUM(AD58:AD60) -> 531.84 | AE61: =SUM(AE58:AE60) -> 336.79 | AF61: =SUM(AF58:AF60) -> 1421.12 | AG61: =SUM(AG58:AG60) -> 1284.61 | AH61: =SUM(AH58:AH60) -> 734.65 | AI61: =SUM(AI58:AI60) -> 839.84 | ... DG61: =SUM(DG58:DG60) -> 3314.1621
C62: COS as a % of Revenue | W62: =+W58/W13 -> #DIV/0! | X62: =+X58/X13 -> #DIV/0! | Y62: =+Y58/Y13 -> #DIV/0! | Z62: =+Z58/Z13 -> #DIV/0! | AA62: =+AA58/AA13 -> #DIV/0! | AB62: =+AB58/AB13 -> 0.025196823 | AC62: =+AC58/AC13 -> 0.029022049 | AD62: =+AD58/AD13 -> 0.0275027 | ... AW62: =+AW58/AW13 -> 0.040295788 | AX62: =+AVERAGE(AR62:AW62) -> 0.031547068 | AY62: =+AX62 -> 0.031547068 | AZ62: =+AY62 -> 0.031547068 | BA62: =+AZ62 -> 0.031547068 | BB62: =+BA62 -> 0.031547068 | BC62: =+BB62 -> 0.031547068 | BD62: =+BC62 -> 0.031547068 | BE62: =+BD62 -> 0.031547068 | BF62: =+BE62 -> 0.031547068 | ... DG62: =+DF62 -> 0.031547068
C63: COGS as a % of Revenue | W63: =+W59/W13 -> #DIV/0! | X63: =+X59/X13 -> #DIV/0! | Y63: =+Y59/Y13 -> #DIV/0! | Z63: =+Z59/Z13 -> #DIV/0! | AA63: =+AA59/AA13 -> #DIV/0! | AB63: =+AB59/AB13 -> 0.062749411 | AC63: =+AC59/AC13 -> 0.067904391 | AD63: =+AD59/AD13 -> 0.0421167 | ... AW63: =+AW59/AW13 -> 0.082664952 | AX63: =+AVERAGE(AR63:AW63) -> 0.095997446 | AY63: =+AX63 -> 0.095997446 | AZ63: =+AY63 -> 0.095997446 | BA63: =+AZ63 -> 0.095997446 | BB63: =+BA63 -> 0.095997446 | BC63: =+BB63 -> 0.095997446 | BD63: =+BC63 -> 0.095997446 | BE63: =+BD63 -> 0.095997446 | BF63: =+BE63 -> 0.095997446 | ... DG63: =+DF63 -> 0.095997446
B65: Gross Profit | D65: =(D13)-(0) -> 0 | E65: =(E13)-(0) -> 0 | F65: =(F13)-(0) -> 0 | G65: =(G13)-(0) -> 0 | H65: =(H13)-(0) -> 0 | I65: =(I13)-(0) -> 0 | J65: =(J13)-(0) -> 0 | K65: =K13 -> 0 | L65: =L13 -> 0 | M65: =M13 -> 0 | N65: =N13 -> 0 | O65: =O13 -> 0 | P65: =P13 -> 0 | Q65: =Q13 -> 0 | R65: =R13 -> 0 | ... U65: =U13 -> 0 | V65: =V13-V61 -> 0 | W65: =W13-W61 -> 0 | X65: =X13-X61 -> 0 | Y65: =Y13-Y61 -> 0 | Z65: =Z13-Z61 -> 0 | AA65: =AA13-AA61 -> 0 | AB65: =AB13-AB61 -> 5224.7 | AC65: =AC13-AC61 -> 6092.36 | ... DG65: =DG13-DG61 -> 9341.062
C66: GP% | AB66: =+AB65/AB13 -> 0.91205377 | AC66: =+AC65/AC13 -> 0.90307356 | AD66: =+AD65/AD13 -> 0.9303806 | AE66: =+AE65/AE13 -> 0.9569157 | AF66: =+AF65/AF13 -> 0.82341948 | AG66: =+AG65/AG13 -> 0.82043472 | AH66: =+AH65/AH13 -> 0.87787383 | AI66: =+AI65/AI13 -> 0.88487457 | ... DG66: =+DG65/DG13 -> 0.73811905
B67: Expenses
B68: Owner Salary | AO68: 1300 | AP68: 1430 | AQ68: 1950 | AR68: 1365 | AS68: 650 | AT68: 650 | AU68: 715 | AV68: 438.75 | AW68: 650 | AX68: =+'People Plan'!Y18 -> 1950 | AY68: =+'People Plan'!Z18 -> 1950 | AZ68: =+'People Plan'!AA18 -> 2047.5 | BA68: =+'People Plan'!AB18 -> 2047.5 | BB68: =+'People Plan'!AC18 -> 2047.5 | BC68: =+'People Plan'!AD18 -> 2047.5 | BD68: =+'People Plan'!AE18 -> 2047.5 | BE68: =+'People Plan'!AF18 -> 2047.5 | ... DG68: =+'People Plan'!CH18 -> 2488.749
B69: Owner Payroll Taxes | AO69: 117.31 | AP69: 90.58 | AQ69: 146.47 | AR69: 85.27 | AS69: 15.88 | AT69: 65.98 | AU69: 61.61 | AV69: 33.57 | AW69: 49.74 | AX69: =+AX68*AX72 -> 155.48242 | AY69: =+AY68*AY72 -> 155.48242 | AZ69: =+AZ68*AZ72 -> 163.25655 | BA69: =+BA68*BA72 -> 163.25655 | BB69: =+BB68*BB72 -> 163.25655 | BC69: =+BC68*BC72 -> 163.25655 | BD69: =+BD68*BD72 -> 163.25655 | BE69: =+BE68*BE72 -> 163.25655 | ... DG69: =+DG68*DG72 -> 198.43935
B70: Owner Benefits | AQ70: 500 | AR70: 500 | AS70: 500 | AT70: 500 | AU70: 500 | AV70: 500 | AW70: 500 | AX70: =+AW70 -> 500 | AY70: =+AX70 -> 500 | AZ70: =+AY70 -> 500 | BA70: =+AZ70 -> 500 | BB70: =+BA70 -> 500 | BC70: =+BB70 -> 500 | BD70: =+BC70 -> 500 | BE70: =+BD70 -> 500 | ... DG70: =+DF70 -> 500
B71: Total Owner Payroll Burden | T71: =SUM(T68:T70) -> 0 | U71: =SUM(U68:U70) -> 0 | V71: =SUM(V68:V70) -> 0 | W71: =SUM(W68:W70) -> 0 | X71: =SUM(X68:X70) -> 0 | Y71: =SUM(Y68:Y70) -> 0 | Z71: =SUM(Z68:Z70) -> 0 | AA71: =SUM(AA68:AA70) -> 0 | ... DG71: =SUM(DG68:DG70) -> 3187.1884
C72: Payroll Tax as a % of Salary | AO72: =+AO69/AO68 -> 0.090238462 | AP72: =+AP69/AP68 -> 0.063342657 | AQ72: =+AQ69/AQ68 -> 0.075112821 | AR72: =+AR69/AR68 -> 0.062468864 | AS72: =+AS69/AS68 -> 0.024430769 | AT72: =+AT69/AT68 -> 0.10150769 | AU72: =+AU69/AU68 -> 0.086167832 | AV72: =+AV69/AV68 -> 0.076512821 | AW72: =+AW69/AW68 -> 0.076523077 | AX72: =+AVERAGE(AU72:AW72) -> 0.079734577 | AY72: =+AX72 -> 0.079734577 | AZ72: =+AY72 -> 0.079734577 | BA72: =+AZ72 -> 0.079734577 | BB72: =+BA72 -> 0.079734577 | BC72: =+BB72 -> 0.079734577 | BD72: =+BC72 -> 0.079734577 | BE72: =+BD72 -> 0.079734577 | BF72: =+BE72 -> 0.079734577 | ... DG72: =+DF72 -> 0.079734577
C73: Benefits as a % of Salary | AX73: 0.045 | AY73: =+AX73 -> 0.045 | AZ73: =+AY73 -> 0.045 | BA73: =+AZ73 -> 0.045 | BB73: =+BA73 -> 0.045 | BC73: =+BB73 -> 0.045 | BD73: =+BC73 -> 0.045 | BE73: =+BD73 -> 0.045 | BF73: =+BE73 -> 0.045 | ... BV73: =+BU73 -> 0.045 | BW73: 0.15 | BX73: =+BW73 -> 0.15 | BY73: =+BX73 -> 0.15 | BZ73: =+BY73 -> 0.15 | CA73: =+BZ73 -> 0.15 | CB73: =+CA73 -> 0.15 | CC73: =+CB73 -> 0.15 | CD73: =+CC73 -> 0.15 | CE73: =+CD73 -> 0.15 | ... CH73: =+CG73 -> 0.15 | CI73: 0.2 | CJ73: =+CI73 -> 0.2 | CK73: =+CJ73 -> 0.2 | CL73: =+CK73 -> 0.2 | CM73: =+CL73 -> 0.2 | CN73: =+CM73 -> 0.2 | CO73: =+CN73 -> 0.2 | CP73: =+CO73 -> 0.2 | CQ73: =+CP73 -> 0.2 | ... DG73: =+DF73 -> 0.2
B74: 60200 Travel | AN74: 0 | AO74: 0 | AP74: 0 | AQ74: 0 | AR74: 0 | AS74: 0 | AT74: 0 | AU74: 0 | AV74: 0 | AW74: 0 | AX74: =+AVERAGE(AU74:AW74) -> 0 | AY74: =AX74 -> 0 | AZ74: =AY74 -> 0 | BA74: =AZ74 -> 0 | BB74: =BA74 -> 0 | BC74: =BB74 -> 0 | BD74: =BC74 -> 0 | BE74: =BD74 -> 0 | BF74: =BE74 -> 0 | ... DG74: =DF74 -> 0
B75: 60210 Airfare & Hotels | AB75: 264.53 | AE75: 238.31 | AI75: 8 | AL75: 168.97 | AX75: 50 | AY75: =AX75 -> 50 | AZ75: =AY75 -> 50 | BA75: =AZ75 -> 50 | BB75: =BA75 -> 50 | BC75: =BB75 -> 50 | BD75: =BC75 -> 50 | BE75: =BD75 -> 50 | BF75: =BE75 -> 50 | ... DG75: =DF75 -> 50
B76: 60230 Parking & Tolls | AE76: 23.82 | AP76: 26.9 | AQ76: 0 | AR76: 0 | AS76: 0 | AT76: 5 | AU76: 0 | AV76: 0 | AW76: 0 | AX76: =+IF(AX1<>AW1, AW76*1.1, AW76) -> 0 | AY76: =+IF(AY1<>AX1, AX76*1.1, AX76) -> 0 | AZ76: =+IF(AZ1<>AY1, AY76*1.1, AY76) -> 0 | BA76: =+IF(BA1<>AZ1, AZ76*1.1, AZ76) -> 0 | BB76: =+IF(BB1<>BA1, BA76*1.1, BA76) -> 0 | BC76: =+IF(BC1<>BB1, BB76*1.1, BB76) -> 0 | BD76: =+IF(BD1<>BC1, BC76*1.1, BC76) -> 0 | BE76: =+IF(BE1<>BD1, BD76*1.1, BD76) -> 0 | ... DG76: =+IF(DG1<>DF1, DF76*1.1, DF76) -> 0
B77: 60240 Personal Mileage Reimbursement | AD77: 90.45 | AE77: 25.46 | AF77: 25.46 | AG77: 25.46 | AH77: 42.22 | AI77: 29.48 | AJ77: 14.41 | AK77: 43.23 | AL77: 14.41 | AM77: 28.82 | AN77: 14.41 | AO77: 14.41 | AP77: 14.41 | AQ77: 14.41 | AR77: 28.82 | AS77: 14.41 | AT77: 28.82 | AU77: 28.82 | AV77: 14.41 | AW77: 28.82 | AX77: =+IF(AX1<>AW1, AW77*1.1, AW77) -> 28.82 | AY77: =+IF(AY1<>AX1, AX77*1.1, AX77) -> 28.82 | AZ77: =+IF(AZ1<>AY1, AY77*1.1, AY77) -> 31.702 | BA77: =+IF(BA1<>AZ1, AZ77*1.1, AZ77) -> 31.702 | BB77: =+IF(BB1<>BA1, BA77*1.1, BA77) -> 31.702 | BC77: =+IF(BC1<>BB1, BB77*1.1, BB77) -> 31.702 | BD77: =+IF(BD1<>BC1, BC77*1.1, BC77) -> 31.702 | BE77: =+IF(BE1<>BD1, BD77*1.1, BD77) -> 31.702 | ... DG77: =+IF(DG1<>DF1, DF77*1.1, DF77) -> 46.414898
B78: Total 60200 Travel | AB78: =SUM(AB75:AB77) -> 264.53 | AC78: =SUM(AC75:AC77) -> 0 | AD78: =SUM(AD75:AD77) -> 90.45 | AE78: =SUM(AE75:AE77) -> 287.59 | AF78: =SUM(AF75:AF77) -> 25.46 | AG78: =SUM(AG75:AG77) -> 25.46 | AH78: =SUM(AH75:AH77) -> 42.22 | AI78: =SUM(AI75:AI77) -> 37.48 | ... DG78: =SUM(DG75:DG77) -> 96.414898
B79: 60300 Legal & Accounting Services
B80: 60310 Finance & Accounting | AJ80: 400 | AK80: 284.47 | AL80: 330.08 | AM80: 280.5 | AN80: 211.67 | AO80: 368.33 | AP80: 353.33 | AQ80: 330 | AR80: 297.5 | AS80: 276.25 | AT80: 382.5 | AU80: 297.5 | AV80: 318.75 | AW80: 383.75 | AX80: 350 | AY80: =+IF(AX$1<>AY$1, AX80*1.1, AX80) -> 350 | AZ80: =+IF(AY$1<>AZ$1, AY80*1.1, AY80) -> 385 | BA80: =+IF(AZ$1<>BA$1, AZ80*1.1, AZ80) -> 385 | BB80: =+IF(BA$1<>BB$1, BA80*1.1, BA80) -> 385 | BC80: =+IF(BB$1<>BC$1, BB80*1.1, BB80) -> 385 | BD80: =+IF(BC$1<>BD$1, BC80*1.1, BC80) -> 385 | BE80: =+IF(BD$1<>BE$1, BD80*1.1, BD80) -> 385 | BF80: =+IF(BE$1<>BF$1, BE80*1.1, BE80) -> 385 | ... DG80: =+IF(DF$1<>DG$1, DF80*1.1, DF80) -> 563.6785
B81: 60320 Legal Fees | AR81: 75.51 | AS81: 0 | AT81: 0 | AU81: 0 | AV81: 0 | AW81: 0 | AX81: =+AL81 -> 0 | AY81: =+AM81 -> 0 | AZ81: =+AN81 -> 0 | BA81: =+AO81 -> 0 | BB81: =+AP81 -> 0 | BC81: =+AQ81 -> 0 | BD81: =+AR81 -> 75.51 | BE81: =+AS81 -> 0 | ... DG81: =+CU81 -> 0
B82: Total 60300 Legal & Accounting Services | AB82: =SUM(AB79:AB80) -> 0 | AC82: =SUM(AC79:AC80) -> 0 | AD82: =SUM(AD79:AD80) -> 0 | AE82: =SUM(AE79:AE80) -> 0 | AF82: =SUM(AF79:AF80) -> 0 | AG82: =SUM(AG79:AG80) -> 0 | AH82: =SUM(AH79:AH80) -> 0 | AI82: =SUM(AI79:AI80) -> 0 | ... AM82: =SUM(AM79:AM80) -> 280.5 | AN82: =SUM(AN79:AN81) -> 211.67 | AO82: =SUM(AO79:AO81) -> 368.33 | AP82: =SUM(AP79:AP81) -> 353.33 | AQ82: =SUM(AQ79:AQ81) -> 330 | AR82: =SUM(AR79:AR81) -> 373.01 | AS82: =SUM(AS79:AS81) -> 276.25 | AT82: =SUM(AT79:AT81) -> 382.5 | AU82: =SUM(AU79:AU81) -> 297.5 | ... DG82: =SUM(DG79:DG81) -> 563.6785
B83: 60400 Office Supplies & Software | AB83: 547.22 | AC83: 375.07 | AD83: 593.53 | AE83: 398.74 | AF83: 1137.21 | AG83: 529.98 | AH83: 364.08 | AI83: 622.52 | AJ83: 373.8 | AK83: 181.44 | AL83: 265.57 | AM83: 123 | AN83: 174.52 | AO83: 221.82 | AP83: 103.99 | AQ83: 171.41 | AR83: 149.99 | AS83: 149.99 | AT83: 165.59 | AU83: 277.13 | AV83: 159.99 | AW83: =205.51 -> 205.51 | AX83: =+IF(AX1<>AW1, AW83*1.1, AW83) -> 205.51 | AY83: =+IF(AY1<>AX1, AX83*1.1, AX83) -> 205.51 | AZ83: =+IF(AZ1<>AY1, AY83*1.1, AY83) -> 226.061 | BA83: =+IF(BA1<>AZ1, AZ83*1.1, AZ83) -> 226.061 | BB83: =+IF(BB1<>BA1, BA83*1.1, BA83) -> 226.061 | BC83: =+IF(BC1<>BB1, BB83*1.1, BB83) -> 226.061 | BD83: =+IF(BD1<>BC1, BC83*1.1, BC83) -> 226.061 | BE83: =+IF(BE1<>BD1, BD83*1.1, BD83) -> 226.061 | ... DG83: =+IF(DG1<>DF1, DF83*1.1, DF83) -> 330.97591
B84: 60600 Bank Fees & Service Charges | AE84: 5 | AF84: 10 | AG84: 10 | AH84: 10 | AI84: 70 | AJ84: 20 | AK84: 15.31 | AL84: 25.99 | AM84: 171 | AN84: 25 | AO84: 25 | AP84: 25 | AQ84: 25 | AR84: 25 | AS84: 25 | AT84: 25 | AU84: 25 | AV84: 15 | AW84: =30 -> 30 | AX84: =+IF(AX1<>AW1, AW84*1.1, AW84) -> 30 | AY84: =+IF(AY1<>AX1, AX84*1.1, AX84) -> 30 | AZ84: =+IF(AZ1<>AY1, AY84*1.1, AY84) -> 33 | BA84: =+IF(BA1<>AZ1, AZ84*1.1, AZ84) -> 33 | BB84: =+IF(BB1<>BA1, BA84*1.1, BA84) -> 33 | BC84: =+IF(BC1<>BB1, BB84*1.1, BB84) -> 33 | BD84: =+IF(BD1<>BC1, BC84*1.1, BC84) -> 33 | BE84: =+IF(BE1<>BD1, BD84*1.1, BD84) -> 33 | ... DG84: =+IF(DG1<>DF1, DF84*1.1, DF84) -> 48.3153
B85: 60700 Facility & Storage Rent | AB85: 108 | AC85: 108 | AD85: 108 | AE85: 108 | AF85: 1408.55 | AG85: 1372.64 | AH85: 1372.64 | AI85: 1682.55 | AJ85: 1372.64 | AK85: 1372.64 | AL85: 1711.17 | AM85: 1414.26 | AN85: 1684.72 | AO85: 1374.5 | AP85: 1373.88 | AQ85: 1635.01 | AR85: 1411.37 | AS85: 1507.24 | AT85: 1680.57 | AU85: 1424.48 | AV85: 1441.35 | AW85: =1761.79 -> 1761.79 | AX85: =+AVERAGE(AR85:AW85) -> 1537.8 | AY85: =IF(AY1<>AX1, AX85*1.1,AX85) -> 1537.8 | AZ85: =IF(AZ1<>AY1, AY85*1.1,AY85) -> 1691.58 | BA85: =IF(BA1<>AZ1, AZ85*1.1,AZ85) -> 1691.58 | BB85: =IF(BB1<>BA1, BA85*1.1,BA85) -> 1691.58 | BC85: =IF(BC1<>BB1, BB85*1.1,BB85) -> 1691.58 | BD85: =IF(BD1<>BC1, BC85*1.1,BC85) -> 1691.58 | BE85: =IF(BE1<>BD1, BD85*1.1,BD85) -> 1691.58 | BF85: =IF(BF1<>BE1, BE85*1.1,BE85) -> 1691.58 | ... DG85: =IF(DG1<>DF1, DF85*1.1,DF85) -> 2476.6423
B86: 60800 Business Insurance | AB86: 40.21 | AC86: 366.97 | AE86: 409.3 | AF86: 43.4 | AG86: 239.61 | AH86: 43.4 | AI86: 286.16 | AJ86: 51.62 | AK86: 112.74 | AL86: 196.16 | AM86: 275.89 | AN86: 51.58 | AO86: 196.74 | AP86: 226.74 | AQ86: 391.9 | AR86: 51.58 | AS86: 216.74 | AT86: 176.95 | AU86: 216.91 | AV86: 221.96 | AW86: =222 -> 222 | AX86: =+AVERAGE(AU86:AW86) -> 220.29 | AY86: =IF(AY1<>AX1, AX86*1.1,AX86) -> 220.29 | AZ86: =IF(AZ1<>AY1, AY86*1.1,AY86) -> 242.319 | BA86: =IF(BA1<>AZ1, AZ86*1.1,AZ86) -> 242.319 | BB86: =IF(BB1<>BA1, BA86*1.1,BA86) -> 242.319 | BC86: =IF(BC1<>BB1, BB86*1.1,BB86) -> 242.319 | BD86: =IF(BD1<>BC1, BC86*1.1,BC86) -> 242.319 | BE86: =IF(BE1<>BD1, BD86*1.1,BD86) -> 242.319 | BF86: =IF(BF1<>BE1, BE86*1.1,BE86) -> 242.319 | ... DG86: =IF(DG1<>DF1, DF86*1.1,DF86) -> 354.77925
B87: 60900 Donations | AF87: 40 | AX87: 10 | AY87: =IF(AY1<>AX1, AX87*1.1,AX87) -> 10 | AZ87: =IF(AZ1<>AY1, AY87*1.1,AY87) -> 11 | BA87: =IF(BA1<>AZ1, AZ87*1.1,AZ87) -> 11 | BB87: =IF(BB1<>BA1, BA87*1.1,BA87) -> 11 | BC87: =IF(BC1<>BB1, BB87*1.1,BB87) -> 11 | BD87: =IF(BD1<>BC1, BC87*1.1,BC87) -> 11 | BE87: =IF(BE1<>BD1, BD87*1.1,BD87) -> 11 | BF87: =IF(BF1<>BE1, BE87*1.1,BE87) -> 11 | ... DG87: =IF(DG1<>DF1, DF87*1.1,DF87) -> 16.1051
B88: 61000 Business Licences | AG88: 50 | AK88: 105 | AU88: 62.81 | AV88: 0 | AW88: 0 | AX88: =+AL88 -> 0 | AY88: =+AM88 -> 0 | AZ88: =+AN88 -> 0 | BA88: =+AO88 -> 0 | BB88: =+AP88 -> 0 | BC88: =+AQ88 -> 0 | BD88: =+AR88 -> 0 | BE88: =+AS88 -> 0 | ... DG88: =+CU88 -> 0
B89: Total G&A Expenses | D89: =SUM(D74:D78) -> 0 | E89: =SUM(E74:E78) -> 0 | F89: =SUM(F74:F78) -> 0 | G89: =SUM(G74:G78) -> 0 | H89: =SUM(H74:H78) -> 0 | I89: =SUM(I74:I78) -> 0 | J89: =SUM(J74:J78) -> 0 | K89: =SUM(K74:K78) -> 0 | ... U89: =SUM(U74:U78) -> 0 | V89: =SUM(V74:V86) -> 0 | W89: =SUM(W74:W86) -> 0 | X89: =SUM(X74:X86) -> 0 | Y89: =SUM(Y74:Y86) -> 0 | Z89: =SUM(Z74:Z86) -> 0 | AA89: =SUM(AA74:AA86) -> 0 | AB89: =+SUM(AB71, AB78, AB82:AB88) -> 959.96 | AC89: =+SUM(AC71, AC78, AC82:AC88) -> 850.04 | AD89: =+SUM(AD71, AD78, AD82:AD88) -> 791.98 | AE89: =+SUM(AE71, AE78, AE82:AE88) -> 1208.63 | AF89: =+SUM(AF71, AF78, AF82:AF88) -> 2664.62 | AG89: =+SUM(AG71, AG78, AG82:AG88) -> 2227.69 | AH89: =+SUM(AH71, AH78, AH82:AH88) -> 1832.34 | AI89: =+SUM(AI71, AI78, AI82:AI88) -> 2698.71 | ... DG89: =+SUM(DG71, DG78, DG82:DG88) -> 7074.0996
B90: Interest Paid | AW90: 16.13
B91: Total Expenses | D91: =SUM(D89:D89) -> 0 | E91: =SUM(E89:E89) -> 0 | F91: =SUM(F89:F89) -> 0 | G91: =SUM(G89:G89) -> 0 | H91: =SUM(H89:H89) -> 0 | I91: =SUM(I89:I89) -> 0 | J91: =SUM(J89:J89) -> 0 | K91: =SUM(K89:K89) -> 0 | ... AV91: =SUM(AV89:AV89) -> 3143.78 | AW91: =SUM(AW89:AW89)+AW90 -> 3847.74 | AX91: =SUM(AX89:AX89)+AX90 -> 5037.9024 | AY91: =SUM(AY89:AY89)+AY90 -> 5037.9024 | AZ91: =SUM(AZ89:AZ89)+AZ90 -> 5381.4185 | BA91: =SUM(BA89:BA89)+BA90 -> 5381.4185 | BB91: =SUM(BB89:BB89)+BB90 -> 5381.4185 | BC91: =SUM(BC89:BC89)+BC90 -> 5381.4185 | BD91: =SUM(BD89:BD89)+BD90 -> 5456.9285 | ... DG91: =SUM(DG89:DG89)+DG90 -> 7074.0996
B92: Net Operating Income | D92: =D65-D91 -> 0 | E92: =E65-E91 -> 0 | F92: =F65-F91 -> 0 | G92: =G65-G91 -> 0 | H92: =H65-H91 -> 0 | I92: =I65-I91 -> 0 | J92: =J65-J91 -> 0 | K92: =K65-K91 -> 0 | ... DG92: =DG65-DG91 -> 2266.9624
C93: CAC | W93: =+SUM(W75:W77,W61) -> 0 | X93: =+SUM(X75:X77,X61) -> 0 | Y93: =+SUM(Y75:Y77,Y61) -> 0 | Z93: =+SUM(Z75:Z77,Z61) -> 0 | AA93: =+SUM(AA75:AA77,AA61) -> 0 | AB93: =+SUM(AB75:AB77,AB61, AB85:AB86) -> 916.54 | AC93: =+SUM(AC75:AC77,AC61, AC85:AC86) -> 1128.86 | AD93: =+SUM(AD75:AD77,AD61, AD85:AD86) -> 730.29 | AE93: =+SUM(AE75:AE77,AE61, AE85:AE86) -> 1141.68 | AF93: =+SUM(AF75:AF77,AF61, AF85:AF86) -> 2898.53 | AG93: =+SUM(AG75:AG77,AG61, AG85:AG86) -> 2922.32 | AH93: =+SUM(AH75:AH77,AH61, AH85:AH86) -> 2192.91 | AI93: =+SUM(AI75:AI77,AI61, AI85:AI86) -> 2846.03 | ... DG93: =+SUM(DG75:DG77,DG61, DG85:DG86) -> 6241.9985
B94: Other Income
B95: Interest Income | P95: 0 | Q95: 0 | R95: 0 | X95: 0 | Y95: 0 | Z95: 0 | AA95: 0 | AB95: 0 | AC95: 0 | AD95: 0 | AE95: 0 | AF95: 0 | AG95: 0 | AH95: 0 | AI95: 0 | AJ95: 0 | AK95: 0 | AL95: 0 | AM95: 0 | AN95: 0 | AO95: 0 | AP95: 2.35 | AQ95: 3.21 | AR95: 4.3 | AS95: 3.94 | AT95: 4.21 | AU95: 3.44 | AV95: 2.61 | AW95: 1.78 | AX95: =AW95 -> 1.78 | AY95: =AX95 -> 1.78 | AZ95: =AY95 -> 1.78 | BA95: =AZ95 -> 1.78 | BB95: =BA95 -> 1.78 | BC95: =BB95 -> 1.78 | BD95: =BC95 -> 1.78 | BE95: =BD95 -> 1.78 | ... DG95: =DF95 -> 1.78
B96: Total Other Income | D96: =D95 -> 0 | E96: =E95 -> 0 | F96: =F95 -> 0 | G96: =G95 -> 0 | H96: =H95 -> 0 | I96: =I95 -> 0 | J96: =J95 -> 0 | K96: 0 | L96: 0 | N96: =N95 -> 0 | O96: =O95 -> 0 | P96: =P95 -> 0 | Q96: =Q95 -> 0 | R96: =R95 -> 0 | S96: =S95 -> 0 | T96: =T95 -> 0 | U96: =U95 -> 0 | ... DG96: =DG95 -> 1.78
B97: Net Other Income | D97: =D96 -> 0 | E97: =E96 -> 0 | F97: =F96 -> 0 | G97: =G96 -> 0 | H97: =H96 -> 0 | I97: =I96 -> 0 | J97: =J96 -> 0 | K97: =K96 -> 0 | ... DG97: =DG96 -> 1.78
B98: Net Income | D98: =D92+D97 -> 0 | E98: =E92+E97 -> 0 | F98: =F92+F97 -> 0 | G98: =G92+G97 -> 0 | H98: =H92+H97 -> 0 | I98: =I92+I97 -> 0 | J98: =J92+J97 -> 0 | K98: =K92+K97 -> 0 | ... DG98: =DG92+DG97 -> 2268.7424
B102: ASSETS
B103: Current Assets
B104: Bank Accounts
B105: 10100 Operating - 2528 | AB105: 260.54 | AC105: 592.16 | AD105: 287.01 | AE105: 310.12 | AF105: 382.24 | AG105: 223.41 | AH105: -42.23 | AI105: 419.06 | AJ105: -99.91 | AK105: 294.48 | AL105: 115.05 | AM105: 158.48 | AN105: 378.97 | AO105: 146.71 | AP105: 454.06 | AQ105: 209.74 | AR105: 785.34 | AS105: 815.92 | AT105: 277.28 | AU105: 542.45 | AV105: 526.25 | AW105: =599.48 -> 599.48 | AX105: =+AW105+AX170 -> 1433.2449 | AY105: =+AX105+AY170 -> 1708.7043 | AZ105: =+AY105+AZ170 -> 1585.9071 | BA105: =+AZ105+BA170 -> 2130.6716 | BB105: =+BA105+BB170 -> 3219.009 | BC105: =+BB105+BC170 -> 5349.0906 | BD105: =+BC105+BD170 -> 7087.2243 | BE105: =+BD105+BE170 -> 8997.5256 | ... DG105: =+DF105+DG170 -> 100058.72
B106: 10200 Savings - 7351 | AB106: 130.91 | AC106: 33.95 | AD106: 770.48 | AE106: 79.36 | AF106: 107.93 | AG106: 496.7 | AH106: 27.5 | AI106: 53.18 | AJ106: 110.31 | AK106: 540.47 | AL106: 28.95 | AM106: 92.91 | AN106: 45.02 | AO106: 68.56 | AP106: 0.03 | AQ106: 9.57 | AR106: 150.5 | AS106: 17.12 | AT106: 50.77 | AU106: 0.77 | AV106: 37.46 | AW106: =15.87 -> 15.87 | AX106: =+AW106 -> 15.87 | AY106: =+AX106 -> 15.87 | AZ106: =+AY106 -> 15.87 | BA106: =+AZ106 -> 15.87 | BB106: =+BA106 -> 15.87 | BC106: =+BB106 -> 15.87 | BD106: =+BC106 -> 15.87 | BE106: =+BD106 -> 15.87 | ... DG106: =+DF106 -> 15.87
B107: 10300 Tax - 9887 | AB107: 541.95 | AC107: 419.66 | AD107: 1750.64 | AE107: 495.44 | AF107: 755.47 | AG107: 797.2 | AH107: 1788.29 | AI107: 644.48 | AJ107: 112.76 | AK107: 831.56 | AL107: 1468.65 | AM107: 685.86 | AN107: 519.07 | AO107: 274.31 | AP107: 0.14 | AQ107: 38.29 | AR107: 276.86 | AS107: 158.34 | AT107: 133.11 | AU107: 3.07 | AV107: 241.74 | AW107: =63.45 -> 63.45 | AX107: =+AW107 -> 63.45 | AY107: =+AX107 -> 63.45 | AZ107: =+AY107 -> 63.45 | BA107: =+AZ107 -> 63.45 | BB107: =+BA107 -> 63.45 | BC107: =+BB107 -> 63.45 | BD107: =+BC107 -> 63.45 | BE107: =+BD107 -> 63.45 | ... DG107: =+DF107 -> 63.45
B108: 10400 VACU Checking - 2865 | AC108: 0 | AD108: 0 | AE108: 895 | AF108: 1364.89 | AG108: 1103.06 | AH108: 1139.18 | AI108: -55.2 | AJ108: 0.31 | AK108: 605.31 | AL108: 224.02 | AM108: 488.75 | AN108: 1097.26 | AO108: 401.39 | AP108: 82.66 | AQ108: 547.45 | AR108: 1327.16 | AS108: 1711.63 | AT108: 1168.87 | AU108: 1355.36 | AV108: 346.15 | AW108: =38.99 -> 38.99 | AX108: =+AW108 -> 38.99 | AY108: =+AX108 -> 38.99 | AZ108: =+AY108 -> 38.99 | BA108: =+AZ108 -> 38.99 | BB108: =+BA108 -> 38.99 | BC108: =+BB108 -> 38.99 | BD108: =+BC108 -> 38.99 | BE108: =+BD108 -> 38.99 | ... DG108: =+DF108 -> 38.99
B109: 10500 Cash | AB109: 0 | AC109: 0 | AD109: 0 | AE109: 0 | AF109: 0 | AG109: 0 | AH109: 0 | AI109: 0 | AJ109: 0 | AK109: 0 | AL109: 0 | AM109: 0 | AN109: 0 | AO109: 0 | AP109: 0 | AQ109: 0 | AR109: 0 | AS109: 0 | AT109: 0 | AU109: 0 | AV109: 0 | AW109: 0
...

Sheet 3

Sheet October
A1: Student | B1: Date | C1: Hours | D1: Rate ($/hr) | E1: Coin | F1: Billed? | G1: Received payment? | H1: Topic | I1: Tip? | J1: Paid via invoice? | K1: Totals
A2: Abby Owen | B2: 44836 | C2: 1 | D2: 50 | E2: 50 | F2: Yes | G2: Yes | H2: Math (general homework) | I2: No | J2: No | K2: 50 | N2: BALANCED
A3: Abby Owen | B3: 44846 | C3: 2 | D3: 50 | E3: 100 | F3: Yes | G3: Yes | H3: Algebra 2 | I3: No | J3: YES | K3: 100
A4: Abby Owen | B4: 44858 | C4: 1 | D4: 50 | E4: 50 | F4: Yes | G4: Yes | H4: Emergency Math Lab | I4: No | J4: YES | K4: 50
A5: Abby Owen | B5: 44859 | C5: 0.75 | D5: 50 | E5: 37.5 | F5: Yes | G5: Yes | H5: Logarithmic Functions Review | I5: No | J5: YES | K5: 37.5
A6: Abby Owen | B6: 44861 | C6: 1 | D6: 50 | E6: 50 | F6: Yes | G6: Yes | H6: Precalc - Exponentials and Logs | I6: No | J6: YES | K6: 50
A7: Addison O'Connor | B7: 44849 | C7: 1 | D7: 60 | E7: 60 | F7: Yes | G7: Yes | H7: Choreography Review | I7: No | J7: YES | K7: 60
A8: Caroline Frey | B8: 44852 | C8: 3.5 | D8: 50 | E8: 175 | F8: Yes | G8: Yes | H8: TN and CoC Essay Supplement Finalization | I8: Yes | J8: No - Venmo b/c tip; sent to personal account but transferred accordingly (sent to Eric and Eric venmo'd business acc) | K8: 200
A9: Caroline Frey | B9: 44857 | C9: 1 | D9: 50 | E9: 50 | F9: Yes | G9: Yes | H9: Bama Honors Appliation | I9: No | J9: No - venmo b/c tip | K9: 50
A10: Claire Cecotti | B10: 44837 | C10: 1 | D10: 50 | E10: 50 | F10: Yes | G10: Yes | H10: SAT Math, Piecewise Functions Test | I10: No | J10: YES | K10: 50
A11: Elle Mishler | B11: 44842 | C11: 1 | D11: 60 | E11: 60 | F11: Yes | G11: Yes | H11: Algebra 1 | I11: No | J11: YES | K11: 60
A12: Elle Mishler | B12: 44846 | C12: 1 | D12: 60 | E12: 60 | F12: Yes | G12: Yes | H12: Algebra 1 | I12: No | J12: YES | K12: 60
A13: Elle Mishler | B13: 44853 | C13: 1.25 | D13: 60 | E13: 75 | F13: Yes | G13: Yes | H13: Algebra 1 Review | I13: No | J13: YES | K13: 75
A14: Gabby Bagot | B14: 44856 | C14: 1 | D14: 60 | E14: 60 | F14: Yes | G14: Yes | H14: Algebra 1 | I14: No | J14: YES | K14: 60 | N14: *Sujay 21 Oct, 23 Oct, 29 Oct, and 30 Oct were all billed together.
A15: Julia Cecotti | B15: 44845 | C15: 1 | D15: 50 | E15: 50 | F15: Yes | G15: Yes | H15: Precalc - piecewise functions | I15: No | J15: YES | K15: 50
A16: Julia Cecotti | B16: 44851 | C16: 1.5 | D16: 50 | E16: 75 | F16: Yes | G16: Yes | H16: Limits and Discontinuity | I16: No | J16: YES | K16: 75
A17: Kathryn Oakford | B17: 44851 | C17: 1.5 | D17: 50 | E17: 75 | F17: Yes | G17: Yes | H17: Business Calculus | I17: No | J17: YES | K17: 75
A18: Kathryn Oakford | B18: 44857 | C18: 1.5 | D18: 50 | E18: 75 | F18: Yes | G18: Yes | H18: Business Calculus | I18: No | J18: YES | K18: 75 | O18: Row Labels | P18: Sum of Hours | Q18: Sum of Coin
A19: Kaylie Thompson | B19: 44836 | C19: 1.5 | D19: 50 | E19: 75 | F19: Yes | G19: Yes | H19: Common App Finalizaiton | I19: No | J19: No | K19: 75 | O19: Abby Owen | P19: 5.75 | Q19: 287.5
A20: Maddie Wilson | B20: 44836 | C20: 2 | D20: 50 | E20: 100 | F20: Yes | G20: Yes | H20: ACT Math | I20: No | J20: No | K20: 100 | O20: Addison O'Connor | P20: 1 | Q20: 60
A21: Maddie Wilson | B21: 44854 | C21: 1.5 | D21: 50 | E21: 75 | F21: Yes | G21: Yes | H21: ACT Math | I21: No | J21: No - received via PayPal and Transferred | K21: 75 | O21: Caroline Frey | P21: 4.5 | Q21: 225
A22: Maddox Rogers | B22: 44847 | C22: 2 | D22: 50 | E22: 100 | F22: Yes | G22: Yes | H22: College Essay | I22: No | J22: YES | K22: 100 | O22: Claire Cecotti | P22: 1 | Q22: 50
A23: Naura Peters | B23: 44856 | C23: 0.5 | D23: 60 | E23: 30 | F23: Yes | G23: Yes | H23: Private lesson | I23: No | J23: YES | K23: 30 | O23: Elle Mishler | P23: 3.25 | Q23: 195
A24: Nicolette Batori | B24: 44857 | C24: 2 | D24: 50 | E24: 100 | F24: Yes | G24: Yes | H24: AP Test Advice, Volunteering advice, SAT Math | I24: No | J24: YES | K24: 100 | O24: Gabby Bagot | P24: 1 | Q24: 60
A25: Nicolette Batori | B25: 44863 | C25: 1 | D25: 50 | E25: 50 | F25: Yes | G25: Yes | H25: SAT Math | I25: No | J25: YES | K25: 50 | O25: Julia Cecotti | P25: 2.5 | Q25: 125
A26: Nicolette Batori | B26: 44865 | C26: 1 | D26: 50 | E26: 50 | F26: Yes | G26: Yes | H26: SAT Math | I26: No | J26: YES | K26: 50 | O26: Kathryn Oakford | P26: 3 | Q26: 150
A27: Rohan Skanda | B27: 44838 | C27: 1 | D27: 50 | E27: 50 | F27: Yes | G27: Yes | H27: AOS Integrated Math + Science | I27: No | J27: YES | K27: 50 | O27: Kaylie Thompson | P27: 1.5 | Q27: 75
A28: Rohan Skanda | B28: 44840 | C28: 2 | D28: 50 | E28: 100 | F28: Yes | G28: Yes | H28: AOS Integrated Math + Science | I28: No | J28: YES | K28: 100 | O28: Maddie Wilson | P28: 3.5 | Q28: 175
A29: Rohan Skanda | B29: 44851 | C29: 1.5 | D29: 50 | E29: 75 | F29: Yes | G29: Yes | H29: Math and Physics Review | I29: No | J29: YES | K29: 75 | O29: Maddox Rogers | P29: 2 | Q29: 100
A30: Rohan Skanda | B30: 44857 | C30: 1 | D30: 50 | E30: 75 | F30: Yes | G30: Yes | H30: AOS Integrated Math + Science | I30: No | J30: YES | K30: 75 | O30: Naura Peters | P30: 0.5 | Q30: 30
... A36: Sophia Gonzales | B36: 44861 | C36: 1 | D36: 60 | E36: 60 | F36: Yes | G36: Yes | H36: Physics | I36: No | J36: YES | K36: 60 | O36: Grand Total | P36: 57.25 | Q36: 2840
A37: Sujay Penugonda | B37: 44840 | C37: 1.5 | D37: 50 | E37: 75 | F37: Yes | G37: Yes | H37: Supplemental Essays | I37: No | J37: YES | K37: 75
A38: Sujay Penugonda | B38: 44855 | C38: 2 | D38: 50 | E38: 100 | F38: Yes | G38: Yes | H38: College Essay | I38: No | J38: YES | K38: 100
A39: Sujay Penugonda | B39: 44857 | C39: 0.5 | D39: 50 | E39: 25 | F39: No | G39: Yes | H39: College Essay | I39: No | J39: YES | K39: 25
A40: Sujay Penugonda | B40: 44863 | C40: 5 | D40: 50 | E40: 125 | F40: Yes | G40: Yes | H40: College Essay | I40: No | J40: YES | K40: 250
A41: Sujay Penugonda | B41: 44864 | C41: 2.5 | D41: 50 | E41: 125 | F41: Yes | G41: Yes | H41: College Essay | I41: No | J41: No - asked to send via Zelle. Transferred from personal to biz immediately. | K41: 125
K43: =SUM(K2:K41) -> 2990

Sheet September
A1: Student | B1: Date | C1: Hours | D1: Rate ($/hr) | E1: Coin | F1: Billed? | G1: Received payment? | H1: Topic | I1: Tip? | J1: Totals
A2: Rohan Skanda | B2: 44822 | C2: 1 | D2: 50 | E2: 50 | F2: Yes | G2: Yes | H2: AOS Math/Science | I2: No | J2: 50 | M2: BALANCED
A3: Maddie Wilson | B3: 44822 | C3: 2 | D3: 50 | E3: 100 | F3: Yes | G3: Yes | H3: College Essay | I3: No | J3: 100
A4: Caroline Frey | B4: 44822 | C4: 1.5 | D4: 50 | E4: 75 | F4: Yes | G4: Yes | H4: College Supplemental Essays | I4: 25 | J4: 100
A5: Kathryn Oakford | B5: 44822 | C5: 1.5 | D5: 50 | E5: 75 | F5: Yes | G5: Yes | H5: Business Calc | I5: No | J5: 75
A6: Kaylie Thompson | B6: 44822 | C6: 1.5 | D6: 50 | E6: 75 | F6: Yes | G6: Yes | H6: College Essay | I6: No | J6: 75
A7: Abby Owen | B7: 44823 | C7: 2 | D7: 50 | E7: 100 | F7: Yes | G7: Yes | H7: Math Practice for Quiz | I7: No | J7: 100
A8: Kathryn Oakford | B8: 44823 | C8: 1 | D8: 50 | E8: 50 | F8: Yes | G8: Yes | H8: Business Calc | I8: No | J8: 50
A9: Maddie Wilson | B9: 44826 | C9: 1 | D9: 50 | E9: 50 | F9: Yes | G9: Yes | H9: ACT Math, NHS Essay | I9: No | J9: 50
A10: Mckenzie Frey | B10: 44827 | C10: 0.5 | D10: 50 | E10: 25 | F10: No | G10: Yes (accounted for in October w Caroline) | H10: PR/Project Planning | O10: Row Labels | P10: Sum of Hours | Q10: Sum of Coin
A11: Maddie Wilson | B11: 44827 | C11: 1 | D11: 50 | E11: 50 | F11: Yes | G11: Yes | H11: NHS Essay | I11: No | J11: 50 | O11: Abby Owen | P11: 2 | Q11: 100
A12: Claire Cecotti | B12: 44829 | C12: 1 | D12: 50 | E12: 50 | F12: Yes | G12: Yes | H12: Algebra Review/SAT Math | I12: No | J12: 50 | O12: Caroline Frey | P12: 1.5 | Q12: 75
A13: Maddie Wilson | B13: 44829 | C13: 2 | D13: 100 | E13: 100 | F13: Yes | G13: Yes | H13: Supplemental Essays | I13: No | J13: 100 | O13: Claire Cecotti | P13: 2 | Q13: 100
A14: Sam Cormier | B14: 44829 | C14: 2 | D14: 100 | E14: 100 | F14: Yes | G14: Yes | H14: Supplemental Essays | I14: No | J14: 100 | O14: Kathryn Oakford | P14: 2.5 | Q14: 125
A15: Claire Cecotti | B15: 44830 | C15: 1 | D15: 50 | E15: 50 | F15: Yes | G15: Yes | H15: Algebra Review/SAT Math | I15: No | J15: 50 | O15: Kaylie Thompson | P15: 1.5 | Q15: 75
A16: Maddie Wilson | B16: 44832 | C16: 1.5 | D16: 50 | E16: 75 | F16: Yes | G16: Yes | H16: Supplemental Essays | I16: No | J16: 75 | O16: Maddie Wilson | P16: 7.5 | Q16: 375
O17: Mckenzie Frey | P17: 0.5 | Q17: 25
J18: =SUM(J2:J16) -> 1025 | O18: Rohan Skanda | P18: 1 | Q18: 50
O19: Sam Cormier | P19: 2 | Q19: 100
O20: Grand Total | P20: 20.5 | Q20: 1025

Sheet August
A1: Student | B1: Date | C1: Hours | D1: Rate ($/hr) | E1: Coin | F1: Billed? | G1: Received payment? | H1: Topic | I1: Tip? | J1: Totals
A2: Caroline Frey | B2: 44793 | C2: 0.5 | D2: 50 | E2: =C2*D2 -> 25 | F2: Yes | G2: Yes | H2: Adderal form | I2: 10 | J2: =E2+I2 -> 35
A3: Nicolette Batori | B3: 44794 | C3: 1.5 | D3: 50 | E3: =C3*D3 -> 75 | F3: No | G3: Yes | H3: SAT/ACT overview, college talk/prep | I3: 0 | J3: =E3+I3 -> 75
A4: Maddie Wilson | B4: 44794 | C4: 1 | D4: 50 | E4: =C4*D4 -> 50 | F4: No | G4: No | H4: ACT Science | J4: =E4+I4 -> 50
A5: Sujay Penugonda | B5: 44796 | C5: 2 | D5: 50 | E5: =C5*D5 -> 100 | F5: Yes | G5: Yes | H5: Essay | J5: =E5+I5 -> 100 | O5: Row Labels | P5: Sum of Hours | Q5: Sum of Coin
A6: Maddie Wilson | B6: 44796 | C6: 2 | D6: 50 | E6: =C6*D6 -> 100 | F6: No | G6: No | H6: ACT Math, college essay | J6: =E6+I6 -> 100 | O6: Caroline Frey | P6: 0.5 | Q6: 25
A7: Matthew Aasen | B7: 44796 | C7: 0.5 | D7: 50 | E7: =C7*D7 -> 25 | F7: Yes | G7: Yes | H7: 2nd read common app | J7: =E7+I7 -> 25 | O7: Maddie Wilson | P7: 3 | Q7: 150
O8: Matthew Aasen | P8: 0.5 | Q8: 25
O9: Nicolette Batori | P9: 1.5 | Q9: 75
J10: =SUM(J2:J7) -> 385 | O10: Sujay Penugonda | P10: 2 | Q10: 100
O11: Grand Total | P11: 7.5 | Q11: 375
J12: BALANCED

Sheet Actual vs. Forecast
B14: 45961
D15: 45535 | E15: 45565 | F15: 45596 | G15: 45626 | H15: 45657 | I15: 45688 | J15: 45716 | K15: 45747 | L15: 45777 | M15: 45808 | N15: 45838 | O15: 45869 | P15: 45900 | Q15: 45930 | R15: Forecast | S15: 45565 | T15: 45596 | U15: 45626 | V15: 45657 | W15: 45688 | X15: 45716 | Y15: 45747 | Z15: 45777 | AA15: 45808 | AB15: 45838 | AC15: 45869 | AD15: 45900 | AE15: 45930 | AF15: Actual | AG15: 45688 | AH15: 45716 | AI15: 45747 | AJ15: 45777 | AK15: 45808 | AL15: 45838 | AM15: 45869 | AN15: 45900 | AO15: 45930 | AP15: Budget | AQ15: 45991 | AR15: 46022 | AS15: Variance (Forecast) | AT15: Variance (Budget)
B16: Total Income | D16: 12767.593 | E16: 6113.1712 | F16: 6127.5858 | G16: 6569.6086 | H16: 5526.456 | I16: 7567.2767 | J16: 7549.4577 | K16: 6427.3261 | L16: 5052.1016 | M16: 5184.0236 | N16: 5656.028 | O16: 7290.1838 | P16: 6944.7903 | Q16: 7864.4087 | R16: 8702.984 | S16: 4188 | T16: 4938.75 | U16: 4938.75 | V16: 6152 | W16: 6721.05 | X16: 6501.14 | Y16: 7108.5 | Z16: 7861.75 | AA16: 7877.62 | AB16: 6887.45 | AC16: 7418.55 | AD16: 7653.35 | AE16: 6170.45 | AF16: =+SUMIF('Monthly Detail'!$4:$4, $B$14,'Monthly Detail'!$13:$13) -> 6998.25 | AG16: 7249.7138 | AH16: 4913.4872 | AI16: 6536.7151 | AJ16: 9380.6106 | AK16: 10754.417 | AL16: 10296.469 | AM16: 8231.419 | AN16: 7580.1793 | AO16: 6911.5121 | AP16: 7871.8411 | AQ16: 7017.7073 | AR16: 8571.1673 | AS16: =+AF16-R16 -> -1704.734 | AT16: =+AF16-AP16 -> -873.59106
B17: KPIs | C17: # of Successful Appointments | D17: 256.51065 | E17: 54.700956 | F17: 60.509581 | G17: 80.177126 | H17: 67.422003 | I17: 74.919583 | J17: 82.981115 | K17: 86.779039 | L17: 108.87894 | M17: 114.89662 | N17: 112.59858 | O17: 88.894305 | P17: 90.046534 | Q17: 58.764254 | R17: 79.396517 | S17: 48 | T17: 50 | U17: 50 | V17: 61 | W17: 66 | X17: 69 | Y17: 68 | Z17: 82 | AA17: 83 | AB17: 72 | AC17: 76 | AD17: 73 | AE17: 62 | AF17: =+SUMIF('Monthly Detail'!$4:$4, $B$14,'Monthly Detail'!15:15) -> 72 | AG17: 80.370052 | AH17: 59.794008 | AI17: 75.759674 | AJ17: 108.72005 | AK17: 130.30784 | AL17: 113.65213 | AM17: 95.401071 | AN17: 92.036778 | AO17: 76.462454 | AP17: 91.23361 | AQ17: 85.852884 | AR17: 94.608295 | AS17: =+AF17-R17 -> -7.3965169 | AT17: =+AF17-AP17 -> -19.23361
C18: # of Active Clients | D18: 165.87294 | E18: 50.532061 | F18: 52.404372 | G18: 68.511632 | H18: 57.612335 | I18: 64.019043 | J18: 70.907651 | K18: 74.152989 | L18: 92.128336 | M18: 96.681303 | N18: 97.585438 | O18: 72.731704 | P18: 79.094929 | Q18: 51.418722 | R18: 64.693458 | S18: 42 | T18: 46 | U18: 46 | V18: 54 | W18: 59 | X18: 59 | Y18: 63 | Z18: 69 | AA18: 78 | AB18: 62 | AC18: 67 | AD18: 60 | AE18: 54 | AF18: =+SUMIF('Monthly Detail'!$4:$4, $B$14,'Monthly Detail'!16:16) -> 58 | AG18: 65.975416 | AH18: 55.753873 | AI18: 66.904647 | AJ18: 91.99389 | AK18: 109.64928 | AL18: 98.498509 | AM18: 78.055422 | AN18: 80.843115 | AO18: 66.904647 | AP18: 74.338497 | AQ18: 78.984653 | AR18: 80.843115 | AS18: =+AF18-R18 -> -6.6934582 | AT18: =+AF18-AP18 -> -16.338497
C19: # of Recurring Client Base | D19: 100.62958 | E19: 26.845158 | F19: 46.165756 | G19: 30.103596 | H19: 35.068378 | I19: 29.638446 | J19: 42.063861 | K19: 40.21857 | L19: 45.332991 | M19: 42.035349 | N19: 47.541624 | O19: 43.404404 | P19: 40.137725 | Q19: 27.423319 | R19: 43.128972 | S19: 37 | T19: 28 | U19: 28 | V19: 25 | W19: 35 | X19: 32 | Y19: 31 | Z19: 30 | AA19: 38 | AB19: 37 | AC19: 34 | AD19: 32 | AE19: 36 | AF19: =+SUMIF('Monthly Detail'!$4:$4, $B$14,'Monthly Detail'!17:17) -> 33 | AG19: 40.158949 | AH19: 33.93714 | AI19: 40.724568 | AJ19: 55.996281 | AK19: 66.743042 | AL19: 59.955614 | AM19: 47.511996 | AN19: 49.208853 | AO19: 40.724568 | AP19: 45.24952 | AQ19: 48.077615 | AR19: 49.208853 | AS19: =+AF19-R19 -> -10.128972 | AT19: =+AF19-AP19 -> -12.24952
C20: Net New Prospective Clients | D20: 19 | E20: -19 | F20: 14 | G20: 4 | H20: 15 | I20: 12 | J20: 12 | K20: 14 | L20: 31 | M20: 30 | N20: 21 | O20: 11 | P20: 8 | Q20: -12 | R20: 12 | S20: -23 | T20: -20 | U20: -20 | V20: 8 | W20: 5 | X20: 0 | Y20: 4 | Z20: 6 | AA20: 9 | AB20: -15 | AC20: 5 | AD20: -7 | AE20: -6 | AF20: =+SUMIF('Monthly Detail'!$4:$4, $B$14,'Monthly Detail'!18:18) -> 3 | AG20: 9 | AH20: -11 | AI20: 12 | AJ20: 27 | AK20: 19 | AL20: -12 | AM20: -22 | AN20: 3 | AO20: -15 | AP20: 8 | AQ20: 5 | AR20: 2 | AS20: =+AF20-R20 -> -9 | AT20: =+AF20-AP20 -> -5
C21: # of Anticipated Appointments | D21: 283.23352 | E21: 61.120073 | F21: 65.670948 | G21: 88.973898 | H21: 72.954254 | I21: 81.803715 | J21: 89.247965 | K21: 92.278227 | L21: 114.05627 | M21: 120.85285 | N21: 118.4458 | O21: 93.836718 | P21: 96.266988 | Q21: 65.510346 | R21: 85.463765 | S21: 52 | T21: 55 | U21: 55 | V21: 66 | W21: 70 | X21: 74 | Y21: 72 | Z21: 90 | AA21: 90 | AB21: 77 | AC21: 88 | AD21: 84 | AE21: 68 | AF21: =+SUMIF('Monthly Detail'!$4:$4, $B$14,'Monthly Detail'!21:21) -> 76 | AG21: 87.112253 | AH21: 67.831014 | AI21: 81.739075 | AJ21: 116.29602 | AK21: 141.17985 | AL21: 126.68291 | AM21: 106.76628 | AN21: 101.57688 | AO21: 85.666132 | AP21: 98.879855 | AQ21: 94.976245 | AR21: 103.19358 | AS21: =+AF21-R21 -> -9.463765 | AT21: =+AF21-AP21 -> -22.879855
C22: # of Anticipated Clients | D22: 175 | E22: 57 | F22: 57 | G22: 74 | H22: 62 | I22: 69 | J22: 75 | K22: 78 | L22: 96 | M22: 100 | N22: 101 | O22: 75 | P22: 82 | Q22: 54 | R22: 68 | S22: 43 | T22: 47 | U22: 47 | V22: 57 | W22: 63 | X22: 64 | Y22: 65 | Z22: 70 | AA22: 80 | AB22: 64 | AC22: 74 | AD22: 66 | AE22: 56 | AF22: =+SUMIF('Monthly Detail'!$4:$4, $B$14,'Monthly Detail'!22:22) -> 61 | AG22: 71 | AH22: 60 | AI22: 72 | AJ22: 99 | AK22: 118 | AL22: 106 | AM22: 84 | AN22: 87 | AO22: 72 | AP22: 80 | AQ22: 85 | AR22: 87 | AS22: =+AF22-R22 -> -7 | AT22: =+AF22-AP22 -> -19
C23: Reschedule/Cancellation Rate | D23: 0.11568339 | E23: 0.11462709 | F23: 0.10752848 | G23: 0.10860212 | H23: 0.11064502 | I23: 0.11285462 | J23: 0.09495227 | K23: 0.07969838 | L23: 0.076137126 | M23: 0.072636923 | N23: 0.07044837 | O23: 0.068644619 | P23: 0.081848082 | Q23: 0.092412217 | R23: 0.097858841 | S23: 0.076923077 | T23: 0.090909091 | U23: 0.090909091 | V23: 0.075757576 | W23: 0.057142857 | X23: 0.067567568 | Y23: 0.055555556 | Z23: 0.088888889 | AA23: 0.077777778 | AB23: 0.064935065 | AC23: 0.13636364 | AD23: 0.13095238 | AE23: 0.088235294 | AF23: =+SUMIF('Monthly Detail'!$4:$4, $B$14,'Monthly Detail'!23:23) -> 0.052631579 | AG23: 0.1 | AH23: 0.1 | AI23: 0.1 | AJ23: 0.1 | AK23: 0.1 | AL23: 0.1 | AM23: 0.1 | AN23: 0.1 | AO23: 0.1 | AP23: 0.1 | AQ23: 0.1 | AR23: 0.1 | AS23: =+AF23-R23 -> -0.045227262 | AT23: =+AF23-AP23 -> -0.047368421
C24: Client Base Growth Rate | D24: 0.1058196 | E24: -0.21043654 | F24: 0.24772314 | G24: 0.038055033 | H24: 0.25244207 | I24: 0.18553784 | J24: 0.20182459 | K24: 0.25683033 | L24: 0.46235454 | M24: 0.4011783 | N24: 0.25109536 | O24: 0.173092 | P24: 0.18052132 | Q24: -0.14302129 | R24: 0.198027 | S24: -0.35384615 | T24: -0.3030303 | U24: -0.3030303 | V24: 0.17391304 | W24: 0.092592593 | X24: 0 | Y24: 0.06779661 | Z24: 0.095238095 | AA24: 0.13043478 | AB24: -0.20512821 | AC24: 0.080645161 | AD24: -0.10447761 | AE24: -0.1 | AF24: =+SUMIF('Monthly Detail'!$4:$4, $B$14,'Monthly Detail'!24:24) -> 0.074074074 | AG24: 0.14516129 | AH24: -0.15492958 | AI24: 0.2 | AJ24: 0.375 | AK24: 0.19191919 | AL24: -0.10169492 | AM24: -0.20754717 | AN24: 0.035714286 | AO24: -0.17241379 | AP24: 0.11111111 | AQ24: 0.0625 | AR24: 0.023529412 | AS24: =+AF24-R24 -> -0.12395293 | AT24: =+AF24-AP24 -> -0.037037037
C25: Client Hit Rate | D25: 0.94784537 | E25: 0.88652739 | F25: 0.91937494 | G25: 0.92583287 | H25: 0.92923121 | I25: 0.92781222 | J25: 0.94543534 | K25: 0.95067935 | L25: 0.95967017 | M25: 0.96681303 | N25: 0.96619246 | O25: 0.96975605 | P25: 0.9645723 | Q25: 0.95219856 | R25: 0.95137439 | S25: 0.97674419 | T25: 0.9787234 | U25: 0.9787234 | V25: 0.94736842 | W25: 0.93650794 | X25: 0.921875 | Y25: 0.96923077 | Z25: 0.98571429 | AA25: 0.975 | AB25: 0.96875 | AC25: 0.90540541 | AD25: 0.90909091 | AE25: 0.96428571 | AF25: =+SUMIF('Monthly Detail'!$4:$4, $B$14,'Monthly Detail'!25:25) -> 0.95081967 | AG25: 0.92923121 | AH25: 0.92923121 | AI25: 0.92923121 | AJ25: 0.92923121 | AK25: 0.92923121 | AL25: 0.92923121 | AM25: 0.92923121 | AN25: 0.92923121 | AO25: 0.92923121 | AP25: 0.92923121 | AQ25: 0.92923121 | AR25: 0.92923121 | AS25: =+AF25-R25 -> -0.00055471362 | AT25: =+AF25-AP25 -> 0.02158846
C26: Appt Multiplier | D26: 1.5464286 | E26: 1.15 | F26: 1.1546667 | G26: 1.1702703 | H26: 1.1702703 | I26: 1.1702703 | J26: 1.1702703 | K26: 1.1702703 | L26: 1.1818182 | M26: 1.1884058 | N26: 1.1538462 | O26: 1.2222222 | P26: 1.1384615 | Q26: 1.1428571 | R26: 1.2272727 | S26: 1.1428571 | T26: 1.0869565 | U26: 1.0869565 | V26: 1.1296296 | W26: 1.1186441 | X26: 1.1694915 | Y26: 1.0793651 | Z26: 1.1884058 | AA26: 1.0641026 | AB26: 1.1612903 | AC26: 1.1343284 | AD26: 1.2166667 | AE26: 1.1481481 | AF26: =+SUMIF('Monthly Detail'!$4:$4, $B$14,'Monthly Detail'!26:26) -> 1.2413793 | AG26: 1.2181818 | AH26: 1.0724638 | AI26: 1.1323529 | AJ26: 1.1818182 | AK26: 1.1884058 | AL26: 1.1538462 | AM26: 1.2222222 | AN26: 1.1384615 | AO26: 1.1428571 | AP26: 1.2272727 | AQ26: 1.0869565 | AR26: 1.1702703 | AS26: =+AF26-R26 -> 0.014106583 | AT26: =+AF26-AP26 -> 0.014106583
C27: Total Billable Hours | D27: 169.29703 | E27: 68.923205 | F27: 69.586018 | G27: 76.16827 | H27: 64.050903 | I27: 86.157521 | J27: 82.981115 | K27: 127.56519 | L27: 108.87894 | M27: 109.90112 | N27: 118.22851 | O27: 147.56455 | P27: 142.68283 | Q27: 157.74121 | R27: 173.98619 | S27: 48 | T27: 50 | U27: 50 | V27: 61 | W27: 66 | X27: 143.75 | Y27: 155.5 | Z27: 170.75 | AA27: 168.75 | AB27: 135 | AC27: 146 | AD27: 150.85 | AE27: 124 | AF27: =+SUMIF('Monthly Detail'!$4:$4, $B$14,'Monthly Detail'!30:30) -> 140 | AG27: 84.023237 | AH27: 56.946675 | AI27: 75.759674 | AJ27: 108.72005 | AK27: 124.64229 | AL27: 119.33473 | AM27: 95.401071 | AN27: 87.853288 | AO27: 80.103523 | AP27: 91.23361 | AQ27: 81.334311 | AR27: 99.338709 | AS27: =+AF27-R27 -> -33.986194 | AT27: =+AF27-AP27 -> 48.76639
C28: Realized / Effective Bill Rate | D28: 75.41534 | E28: 86.436561 | F28: 84.880717 | G28: 83.730254 | H28: 83.625003 | I28: 85.65042 | J28: 88.961992 | K28: 48.977397 | L28: 44.7571 | M28: 45.364762 | N28: 45.983802 | O28: 47.000307 | P28: 46.181383 | Q28: 47.304227 | R28: 47.58341 | S28: 80.538462 | T28: 89.795455 | U28: 89.795455 | V28: 93.212121 | W28: 96.015 | X28: 41.146456 | Y28: 43.94745 | Z28: 42.324361 | AA28: 43.462731 | AB28: 48.163986 | AC28: 43.131105 | AD28: 44.795727 | AE28: 45.622551 | AF28: =+SUMIF('Monthly Detail'!$4:$4, $B$14,'Monthly Detail'!32:32) -> 47.851282 | AG28: 83.625003 | AH28: 83.625003 | AI28: 83.625003 | AJ28: 83.625003 | AK28: 83.625003 | AL28: 83.625003 | AM28: 83.625003 | AN28: 83.625003 | AO28: 83.625003 | AP28: 83.625003 | AQ28: 83.625003 | AR28: 83.625003 | AS28: =+AF28-R28 -> 0.26787197 | AT28: =+AF28-AP28 -> -35.77372
C29: Productivity Utilization | D29: 0 | E29: 0 | F29: 0 | G29: 0 | H29: 0 | I29: 0 | J29: 0 | K29: 0 | L29: 0 | M29: 0 | N29: 0 | O29: 0 | P29: 0 | Q29: 0 | R29: 0 | S29: 0 | T29: 0 | U29: 0 | V29: 0 | W29: 0 | X29: 0 | Y29: 0 | Z29: 0 | AA29: 0 | AB29: 0 | AC29: 0 | AD29: 0 | AE29: 0 | AF29: =+SUMIF('Monthly Detail'!$4:$4, O14,'Monthly Detail'!30:30) -> 0 | AG29: 0 | AH29: 0 | AI29: 0 | AJ29: 0 | AK29: 0 | AL29: 0 | AM29: 0 | AN29: 0 | AO29: 0 | AP29: 0 | AQ29: 0 | AR29: 0 | AS29: =+AF29-R29 -> 0 | AT29: =+AF29-AP29 -> 0
AS30: =+AF30-R30 -> 0 | AT30: =+AF30-AP30 -> 0
C31: Utilization % | D31: 0.00375 | E31: 0.0075 | F31: 0.00625 | G31: 0.00625 | H31: 0.00625 | I31: 0.00625 | J31: 0.00625 | K31: 0.00875 | L31: 0.0056818182 | M31: 0.0054347826 | N31: 0.00625 | O31: 0.0094318182 | P31: 0.0094318182 | Q31: 0.015251736 | R31: 0.011909554 | S31: 0.005952381 | T31: 0.0065789474 | U31: 0.0065789474 | V31: 0.0065789474 | W31: 0.0054347826 | X31: 0.013020833 | Y31: 0.013611695 | Z31: 0.011831347 | AA31: 0.011551889 | AB31: 0.011160714 | AC31: 0.010915072 | AD31: 0.012300228 | AE31: 0.011363636 | AF31: =+SUMIF('Monthly Detail'!$4:$4, $B$14,'Monthly Detail'!46:46) -> 0.010567633 | AG31: 0.0056818182 | AH31: 0.005952381 | AI31: 0.005952381 | AJ31: 0.0056818182 | AK31: 0.0054347826 | AL31: 0.00625 | AM31: 0.0056818182 | AN31: 0.0056818182 | AO31: 0.005952381 | AP31: 0.0054347826 | AQ31: 0.0065789474 | AR31: 0.00625 | AS31: =+AF31-R31 -> -0.0013419216 | AT31: =+AF31-AP31 -> 0.0051328502
AS32: =+AF32-R32 -> 0 | AT32: =+AF32-AP32 -> 0
B33: Cost of Goods Sold | AS33: =+AF33-R33 -> 0 | AT33: =+AF33-AP33 -> 0
B34: Software - COS | D34: 447.17994 | E34: 163.21368 | F34: 166.80002 | G34: 185.26974 | H34: 163.65417 | I34: 219.35718 | J34: 219.19167 | K34: 191.81129 | L34: 152.37539 | M34: 157.62129 | N34: 170.15145 | O34: 217.58497 | P34: 203.90093 | Q34: 228.97022 | R34: 261.82209 | S34: 128.31 | T34: 160.15 | U34: 160.15 | V34: 171.4 | W34: 197.3 | X34: 202.11 | Y34: 214.54 | Z34: 247.79 | AA34: 240.23 | AB34: 182.1 | AC34: 216.6 | AD34: 205.55 | AE34: 222.12 | AF34: =+SUMIF('Monthly Detail'!$4:$4, $B$14,'Monthly Detail'!58:58) -> 282 | AG34: 214.68476 | AH34: 145.50241 | AI34: 193.57083 | AJ34: 277.78671 | AK34: 318.46904 | AL34: 304.9079 | AM34: 243.75586 | AN34: 224.47079 | AO34: 204.66964 | AP34: 233.10773 | AQ34: 207.81439 | AR34: 253.81678 | AS34: =+AF34-R34 -> 20.177911 | AT34: =+AF34-AP34 -> 48.89227
B35: Materials - COGS | D35: 93.188842 | E35: 209.70961 | F35: 174.10754 | G35: 245.00488 | H35: 186.33408 | I35: 319.58204 | J35: 330.96078 | K35: 365.80507 | L35: 372.17717 | M35: 416.83871 | N35: 477.04279 | O35: 587.36947 | P35: 601.14481 | Q35: 720.04632 | R35: 780.64705 | S35: 28.36 | T35: 356.29 | U35: 356.29 | V35: 589.19 | W35: 249.98 | X35: 544.29 | Y35: 810.15 | Z35: 682.78 | AA35: 754.25 | AB35: 503.73 | AC35: 588.11 | AD35: 768.16 | AE35: 893.43 | AF35: =+SUMIF('Monthly Detail'!$4:$4, $B$14,'Monthly Detail'!59:59) -> 578.51 | AG35: 244.43671 | AH35: 165.66677 | AI35: 220.39672 | AJ35: 316.28361 | AK35: 362.60387 | AL35: 347.16337 | AM35: 277.53661 | AN35: 255.57893 | AO35: 233.03366 | AP35: 265.41282 | AQ35: 236.61421 | AR35: 288.99182 | AS35: =+AF35-R35 -> -202.13705 | AT35: =+AF35-AP35 -> 313.09718
B36: Contractors - COS | E36: 450 | F36: 540 | G36: 540 | H36: 600 | I36: 0 | J36: 300 | K36: 1103.4778 | L36: 448.18414 | M36: 0 | N36: 0 | O36: 998.46819 | P36: 925.24239 | Q36: 1091.1182 | R36: 1394.7929 | S36: 210 | T36: 432 | U36: 432 | V36: 470 | W36: 50 | X36: 45 | Y36: 0 | Z36: 0 | AA36: 629 | AB36: 0 | AC36: 0 | AD36: 0 | AE36: 30 | AF36: =+SUMIF('Monthly Detail'!$4:$4, $B$14,'Monthly Detail'!60:60) -> 0 | AG36: 0 | AH36: 300 | AI36: 540 | AJ36: 940.80078 | AK36: 1179.6343 | AL36: 980.02097 | AM36: 381.01607 | AN36: 540 | AO36: 300 | AP36: 558.50415 | AQ36: 540 | AR36: 680.08064 | AS36: =+AF36-R36 -> -1394.7929 | AT36: =+AF36-AP36 -> -558.50415
B37: Total Expenses | D37: 540.36878 | E37: 822.92329 | F37: 880.90756 | G37: 970.27462 | H37: 949.98825 | I37: 538.93922 | J37: 850.15245 | K37: 1661.0942 | L37: 972.7367 | M37: 574.46 | N37: 647.19424 | O37: 1803.4226 | P37: 1730.2881 | Q37: 2040.1347 | R37: 2437.2621 | S37: 366.67 | T37: 948.44 | U37: 948.44 | V37: 1230.59 | W37: 497.28 | X37: 791.4 | Y37: 1024.69 | Z37: 930.57 | AA37: 1623.48 | AB37: 685.83 | AC37: 804.71 | AD37: 973.71 | AE37: 1145.55 | AF37: =+SUM(AF34:AF36) -> 860.51 | AG37: 459.12148 | AH37: 611.16918 | AI37: 953.96755 | AJ37: 1534.8711 | AK37: 1860.7072 | AL37: 1632.0922 | AM37: 902.30854 | AN37: 1020.0497 | AO37: 737.7033 | AP37: 1057.0247 | AQ37: 984.4286 | AR37: 1222.8892 | AS37: =+AF37-R37 -> -1576.7521 | AT37: =+AF37-AP37 -> -196.5147
B38: Gross Profit | D38: 12227.224 | E38: 5290.2479 | F38: 5246.6782 | G38: 5599.334 | H38: 4576.4677 | I38: 7028.3375 | J38: 6699.3053 | K38: 4766.232 | L38: 4079.3649 | M38: 4609.5636 | N38: 5008.8337 | O38: 5486.7612 | P38: 5214.5021 | Q38: 5824.2739 | R38: 6265.7219 | S38: 3821.33 | T38: 3990.31 | U38: 3990.31 | V38: 4921.41 | W38: 6223.77 | X38: 5709.74 | Y38: 6083.81 | Z38: 6931.18 | AA38: 6254.14 | AB38: 6201.62 | AC38: 6613.84 | AD38: 6679.64 | AE38: 5024.9 | AF38: =+AF16-AF37 -> 6137.74 | AG38: 6790.5923 | AH38: 4302.318 | AI38: 5582.7475 | AJ38: 7845.7395 | AK38: 8893.7095 | AL38: 8664.3768 | AM38: 7329.1104 | AN38: 6560.1295 | AO38: 6173.8088 | AP38: 6814.8164 | AQ38: 6033.2787 | AR38: 7348.278 | AS38: =+AF38-R38 -> -127.98192 | AT38: =+AF38-AP38 -> -677.07636
